Workbook

Sheet 角色战力
A1: lv | B1: might | E1: 建筑战力 | F1: 基础值 | G1: 系数 | H1: 等级 | I1: 战力 | J1: 数量 | K1: 建筑总战力 | O1: city | P1: resouce | Q1: waterdragon
A2: 1 | B2: 0 | E2: Home | F2: 10 | G2: 2 | H2: 20 | I2: =F2*(2^(H2/G2-1)) -> 5120 | J2: 6 | K2: =I2*J2 -> 30720 | N2: 地块数量 | O2: 30 | P2: 38 | Q2: 13
A3: 2 | B3: 76 | C3: =B4/B3 -> 1.5263158 | E3: Garrison | F3: 10 | G3: 2 | H3: 20 | I3: =F3*(2^(H3/G3-1)) -> 5120 | J3: 12 | K3: =I3*J3 -> 61440
A4: 3 | B4: 116 | C4: =B5/B4 -> 1.6896552 | E4: Metalsmith | F4: 20 | G4: 2 | H4: 20 | I4: =F4*(2^(H4/G4-1)) -> 10240 | J4: 1 | K4: =I4*J4 -> 10240
A5: 4 | B5: 196 | C5: =B6/B5 -> 1.8163265 | E5: Rookery | F5: 20 | G5: 2 | H5: 20 | I5: =F5*(2^(H5/G5-1)) -> 10240 | J5: 1 | K5: =I5*J5 -> 10240
A6: 5 | B6: 356 | C6: =B7/B6 -> 1.8988764 | E6: Theater | F6: 30 | G6: 2 | H6: 20 | I6: =F6*(2^(H6/G6-1)) -> 15360 | J6: 1 | K6: =I6*J6 -> 15360
A7: 6 | B7: 676 | C7: =B8/B7 -> 1.9467456 | E7: Sentinel | F7: 20 | G7: 2 | H7: 20 | I7: =F7*(2^(H7/G7-1)) -> 10240 | J7: 1 | K7: =I7*J7 -> 10240
A8: 7 | B8: 1316 | C8: =B9/B8 -> 1.9726444 | E8: Factory | F8: 20 | G8: 2 | H8: 20 | I8: =F8*(2^(H8/G8-1)) -> 10240 | J8: 1 | K8: =I8*J8 -> 10240
A9: 8 | B9: 2596 | C9: =B10/B9 -> 1.9861325 | E9: DragonKeep | F9: 50 | G9: 2 | H9: 20 | I9: =F9*(2^(H9/G9-1)) -> 25600 | J9: 1 | K9: =I9*J9 -> 25600
A10: 9 | B10: 5156 | C10: =B11/B10 -> 1.9930178 | E10: Fortress | F10: 50 | G10: 2 | H10: 20 | I10: =F10*(2^(H10/G10-1)) -> 25600 | J10: 1 | K10: =I10*J10 -> 25600
A11: 10 | B11: 10276 | C11: =B12/B11 -> 1.6228104 | E11: OfficerQuarter | F11: 30 | G11: 2 | H11: 20 | I11: =F11*(2^(H11/G11-1)) -> 15360 | J11: 1 | K11: =I11*J11 -> 15360
A12: 11 | B12: 16676 | C12: =B13/B12 -> 1.4797314 | E12: MusterPoint | F12: 30 | G12: 2 | H12: 20 | I12: =F12*(2^(H12/G12-1)) -> 15360 | J12: 1 | K12: =I12*J12 -> 15360
A13: 12 | B13: 24676 | C13: =B14/B13 -> 1.4052521 | E13: ScienceCenter | F13: 30 | G13: 2 | H13: 20 | I13: =F13*(2^(H13/G13-1)) -> 15360 | J13: 1 | K13: =I13*J13 -> 15360
A14: 13 | B14: 34676 | C14: =B15/B14 -> 1.3604799 | E14: StorageVault | F14: 20 | G14: 2 | H14: 20 | I14: =F14*(2^(H14/G14-1)) -> 10240 | J14: 1 | K14: =I14*J14 -> 10240
... A20: 19 | B20: 175355 | C20: =B21/B20 -> 1.2719284 | E20: newbuilding | F20: 10 | G20: 1 | H20: 10 | I20: =F20*(2^(H20/G20-1)) -> 5120 | J20: 4 | K20: =I20*J20 -> 20480
A21: 20 | B21: 223039 | C21: =B22/B21 -> 1.2672358 | E21: waterdragonkeep | F21: 50 | G21: 2 | H21: 20 | I21: =F21*(2^(H21/G21-1)) -> 25600 | J21: total | K21: =SUM(K2:K20) -> 399360
A22: 21 | B22: 282643 | C22: =B23/B22 -> 1.2636046
A23: 22 | B23: 357149 | C23: =B24/B23 -> 1.2607651
A24: 23 | B24: 450281 | C24: =B25/B24 -> 1.2585408 | E24: TrainingCamp | F24: 15 | G24: 2 | H24: 20 | I24: =F24*(2^(H24/G24-1)) -> 7680
A25: 24 | B25: 566697 | C25: =B26/B25 -> 1.2567845 | E25: Silo | F25: 20 | G25: 2 | H25: 20 | I25: =F25*(2^(H25/G25-1)) -> 10240
A26: 25 | B26: 712216 | C26: =B27/B26 -> 1.2553986
A27: 26 | B27: 894115 | C27: =B28/B27 -> 1.2542995
A28: 27 | B28: 1121488 | C28: =B29/B28 -> 1.2534285
A29: 28 | B29: 1405705 | C29: =B30/B29 -> 1.2527358
A30: 29 | B30: 1760977 | C30: =B31/B30 -> 1.2521833
A31: 30 | B31: 2205066 | C31: =B32/B31 -> 1.2517439
A32: 31 | B32: 2760178 | C32: =B33/B32 -> 1.2513928
A33: 32 | B33: 3454067 | C33: =B34/B33 -> 1.2511133
A34: 33 | B34: 4321429 | C34: =B35/B34 -> 1.2508897
A35: 34 | B35: 5405631 | C35: =B36/B35 -> 1.2507113
A36: 35 | B36: 6760884 | C36: =B37/B36 -> 1.2505686
A37: 36 | B37: 8454949 | C37: =B38/B37 -> 1.2504549
... A51: 50 | B51: 192577614 | C51: =B52/B51 -> 0

Sheet 道具列表
A1: item Name | B1: Item Title | C1: Item Icon | D1: Item Type | E1: Category | F1: Rubies | G1: Enabled | H1: Buyable | I1: Usable | J1: Visible
A2: AtlagenHarvestNanosDay | B2: 1 Day Food Nanos | D2: Items::Types::ResourceBoost | E2: production | F2: 7 | G2: Yes | H2: Yes | I2: Yes | J2: Yes
A3: AtlagenHarvestNanosWeek | B3: 1 Week Food Nanos | D3: Items::Types::ResourceBoost | E3: production | F3: 40 | G3: Yes | H3: Yes | I3: Yes | J3: Yes
A4: BeginnerChestOne | B4: Beginner's Chest | D4: Items::Types::Chest | F4: 20 | G4: Yes | H4: No | I4: Yes | J4: No
A5: BeginnerOfferChest | B5: translation missing: en.items.beginnerofferchest.name | D5: Items::Types::Chest | F5: 1000 | G5: Yes | H5: No | I5: No | J5: No
A6: Blast | B6: 2.5 Day Speedup | D6: Items::Types::SpeedUp | E6: speedup | F6: 210 | G6: Yes | H6: Yes | I6: No | J6: Yes
A7: Blink | B7: 1 Minute Speedup | D7: Items::Types::SpeedUp | E7: speedup | F7: 1 | G7: Yes | H7: Yes | I7: No | J7: Yes
A8: Blitz | B8: 4 Day Speedup | D8: Items::Types::SpeedUp | E8: speedup | F8: 275 | G8: Yes | H8: Yes | I8: No | J8: Yes
A9: Bolt | B9: 24-Hour Speedup | D9: Items::Types::SpeedUp | E9: speedup | F9: 95 | G9: Yes | H9: Yes | I9: No | J9: Yes
A10: Bore | B10: 15-Hour Speedup | D10: Items::Types::SpeedUp | E10: speedup | F10: 65 | G10: Yes | H10: Yes | I10: No | J10: Yes
A11: Bounce | B11: 8-Hour Speedup | D11: Items::Types::SpeedUp | E11: speedup | F11: 40 | G11: Yes | H11: Yes | I11: No | J11: Yes
A12: BreatheFire | B12: Fire | D12: Items::Types::DoNothing | E12: dragon_actions | F12: 10 | G12: Yes | H12: Yes | I12: No | J12: Yes
A13: CeaseFireTreaty | B13: Ceasefire Treaty | D13: Items::Types::SafetyBoost | E13: general | F13: 25 | G13: Yes | H13: Yes | I13: Yes | J13: Yes
A14: ChartedWarpDevice | B14: Charted Warp Device | D14: Items::Types::WarpDevice | E14: general | F14: 75 | G14: Yes | H14: Yes | I14: No | J14: Yes
A15: CompletionGrant | B15: Completion Grant | D15: Items::Types::DoNothing | E15: general | F15: 40 | G15: Yes | H15: Yes | I15: No | J15: Yes
A16: CompletionGrantPortfolio | B16: Completion Portfolio | D16: Items::Types::Chest | E16: chest | F16: 155 | G16: Yes | H16: Yes | I16: Yes | J16: Yes
A17: CrimsonBull | B17: Crimson Bull | D17: Items::Types::ResourceBoost | F17: 10 | G17: Yes | H17: No | I17: No | J17: Yes
A18: DarkWarpDevice | B18: Dark Warp Device | D18: Items::Types::WarpDevice | E18: general | F18: 30 | G18: Yes | H18: Yes | I18: Yes | J18: Yes
A19: DoubleTaxDayDeclaration | B19: Double Tax Day Writ | D19: Items::Types::ResourceBoost | E19: production | F19: 10 | G19: Yes | H19: Yes | I19: Yes | J19: Yes
A20: DoubleTaxWeekDeclaration | B20: Double Tax Week Writ | D20: Items::Types::ResourceBoost | E20: production | F20: 40 | G20: Yes | H20: Yes | I20: Yes | J20: Yes
A21: DragonHearts | B21: Dragon Hearts | D21: Items::Types::ResourceBoost | E21: general | F21: 10 | G21: Yes | H21: Yes | I21: Yes | J21: Yes
A22: DragonRoar | B22: Roar | D22: Items::Types::DoNothing | E22: dragon_actions | F22: 10 | G22: Yes | H22: Yes | I22: No | J22: Yes
A23: DragonTransform | B23: Transform | D23: Items::Types::DragonTransform | F23: 10 | G23: Yes | H23: No | I23: No | J23: Yes
A24: DryadForestNanosDay | B24: 1 Day Wood Nanos | D24: Items::Types::ResourceBoost | E24: production | F24: 7 | G24: Yes | H24: Yes | I24: Yes | J24: Yes
A25: DryadForestNanosWeek | B25: 1 Week Wood Nanos | D25: Items::Types::ResourceBoost | E25: production | F25: 40 | G25: Yes | H25: Yes | I25: Yes | J25: Yes
A26: EpeoradMetalsNanosDay | B26: 1 Day Metals Nanos | D26: Items::Types::ResourceBoost | E26: production | F26: 7 | G26: Yes | H26: Yes | I26: Yes | J26: Yes
A27: EpeoradMetalsNanosWeek | B27: 1 Week Metals Nanos | D27: Items::Types::ResourceBoost | E27: production | F27: 40 | G27: Yes | H27: Yes | I27: Yes | J27: Yes
A28: Food250K | B28: 250,000 Food | D28: Items::Types::ResourceBundle | E28: resource | F28: 55 | G28: Yes | H28: Yes | I28: Yes | J28: Yes
A29: Food80K | B29: 80,000 Food | D29: Items::Types::ResourceBundle | E29: resource | F29: 20 | G29: Yes | H29: Yes | I29: Yes | J29: Yes
A30: ForcedMarchDrops | B30: Forced March Drops | D30: Items::Types::SpeedUp | E30: speedup | F30: 7 | G30: Yes | H30: Yes | I30: No | J30: Yes
A31: GeneralRename | B31: Identity Alternator | D31: Items::Types::IdentityAlternator | E31: general | F31: 10 | G31: Yes | H31: Yes | I31: No | J31: Yes
A32: GlowingShields | B32: Glowing Shields | D32: Items::Types::ResourceBoost | E32: general | F32: 10 | G32: Yes | H32: Yes | I32: Yes | J32: Yes
A33: Gold250K | B33: 250,000 Gold | D33: Items::Types::ResourceBundle | E33: resource | F33: 55 | G33: Yes | H33: Yes | I33: Yes | J33: Yes
A34: Gold80K | B34: 80,000 Gold | D34: Items::Types::ResourceBundle | E34: resource | F34: 20 | G34: Yes | H34: Yes | I34: Yes | J34: Yes
A35: GreatDragonArmorChest | B35: Great Dragon Armor Chest | D35: Items::Types::Chest | E35: chest | F35: 219 | G35: Yes | H35: No | I35: Yes | J35: Yes
... A43: NanoCrates | B43: Nano Crates | D43: Items::Types::Chest | E43: chest | F43: 145 | G43: Yes | H43: Yes | I43: Yes | J43: Yes
A44: NewPlayerProtection | B44: translation missing: en.items.newplayerprotection.name | D44: Items::Types::SafetyBoost | F44: 0 | G44: Yes | H44: No | I44: No | J44: No
A45: NomadicRecruitsDay | B45: Dragon's Call | D45: Items::Types::ResourceBoost | F45: 50 | G45: Yes | H45: No | I45: No | J45: Yes
A46: NpcInstanceGreatDragonChest | D46: Items::Types::Chest | F46: 1000 | G46: Yes | H46: No | I46: No | J46: No
A47: Ore250K | B47: 250,000 Metals | D47: Items::Types::ResourceBundle | E47: resource | F47: 55 | G47: Yes | H47: Yes | I47: Yes | J47: Yes
A48: Ore80K | B48: 80,000 Metals | D48: Items::Types::ResourceBundle | E48: resource | F48: 20 | G48: Yes | H48: Yes | I48: Yes | J48: Yes
A49: OreadStoneNanosDay | B49: 1 Day Stone Nanos | D49: Items::Types::ResourceBoost | E49: production | F49: 7 | G49: Yes | H49: Yes | I49: Yes | J49: Yes
A50: OreadStoneNanosWeek | B50: 1 Week Stone Nanos | D50: Items::Types::ResourceBoost | E50: production | F50: 40 | G50: Yes | H50: Yes | I50: Yes | J50: Yes
A51: PurpleBones | B51: Purple Bones | D51: Items::Types::ResourceBoost | F51: 10 | G51: Yes | H51: No | I51: No | J51: Yes
A52: RefreshProGeneral | B52: General Refresh | D52: Items::Types::GeneralRefresh | E52: general | F52: 10 | G52: Yes | H52: Yes | I52: No | J52: Yes
A53: ResourceChest | B53: Resource Chest | D53: Items::Types::Chest | E53: chest | F53: 250 | G53: Yes | H53: Yes | I53: Yes | J53: Yes
A54: Skip | B54: 15-Minute Speedup | D54: Items::Types::SpeedUp | E54: speedup | F54: 5 | G54: Yes | H54: Yes | I54: No | J54: Yes
A55: Stone250K | B55: 250,000 Stone | D55: Items::Types::ResourceBundle | E55: resource | F55: 55 | G55: Yes | H55: Yes | I55: Yes | J55: Yes
A56: Stone80K | B56: 80,000 Stone | D56: Items::Types::ResourceBundle | E56: resource | F56: 20 | G56: Yes | H56: Yes | I56: Yes | J56: Yes
A57: TestroniusPowder | B57: Testronius Powder | D57: Items::Types::SpeedUp | E57: speedup | F57: 25 | G57: Yes | H57: Yes | I57: No | J57: Yes
A58: TimeTrickstersBag | B58: Chronos Bag | D58: Items::Types::Chest | E58: chest | F58: 345 | G58: Yes | H58: Yes | I58: Yes | J58: Yes
A59: TranceMarchDrops | B59: Trance March Drops | D59: Items::Types::SpeedUp | E59: speedup | F59: 20 | G59: Yes | H59: Yes | I59: No | J59: Yes
A60: Wood250K | B60: 250,000 Wood | D60: Items::Types::ResourceBundle | E60: resource | F60: 55 | G60: Yes | H60: Yes | I60: Yes | J60: Yes
A61: Wood80K | B61: 80,000 Wood | D61: Items::Types::ResourceBundle | E61: resource | F61: 20 | G61: Yes | H61: Yes | I61: Yes | J61: Yes

Sheet 任务及升级奖励
B1: position | C1: food | D1: wood | E1: stone | F1: ore | G1: gold | I1: level | J1: ore | K1: wood | L1: stone | M1: food | N1: gold
A2: adjust_taxes | B2: 18 | C2: 0 | D2: 0 | E2: 0 | F2: 0 | G2: 1000 | I2: 1 | J2: 0 | K2: 0 | L2: 0 | M2: 0 | N2: 0
A3: aerial_combat_1 | B3: 119 | C3: 0 | D3: 0 | E3: 0 | F3: 0 | G3: 15000 | I3: 2 | J3: 310 | K3: 680 | L3: 320 | M3: 500 | N3: 600
A4: agriculture_research_1 | B4: 7 | C4: 0 | D4: 0 | E4: 0 | F4: 0 | G4: 2000 | I4: 3 | J4: 420 | K4: 1040 | L4: 680 | M4: 700 | N4: 1000
A5: anthropus_conquer | B5: 73 | C5: 5000 | D5: 0 | E5: 0 | F5: 0 | G5: 0 | I5: 4 | J5: 550 | K5: 1580 | L5: 1220 | M5: 1100 | N5: 1600
A6: ballistics_1 | B6: 65 | C6: 0 | D6: 0 | E6: 0 | F6: 0 | G6: 6000 | I6: 5 | J6: 870 | K6: 2300 | L6: 1940 | M6: 1700 | N6: 2400
A7: clairvoyance_1 | B7: 51 | C7: 0 | D7: 0 | E7: 0 | F7: 0 | G7: 7000 | I7: 6 | J7: 1270 | K7: 3200 | L7: 2840 | M7: 2450 | N7: 3400
A8: conquer_forest_1 | B8: 151 | C8: 1000 | D8: 4000 | E8: 1000 | F8: 1000 | G8: 1000 | I8: 7 | J8: 1750 | K8: 4280 | L8: 3920 | M8: 3350 | N8: 4600
A9: conquer_grassland_1 | B9: 152 | C9: 1000 | D9: 4000 | E9: 1000 | F9: 1000 | G9: 1000 | I9: 8 | J9: 2310 | K9: 5540 | L9: 5180 | M9: 4400 | N9: 6000
A10: conquer_high_level_forest_1 | B10: 156 | C10: 3000 | D10: 7000 | E10: 3000 | F10: 3000 | G10: 2500 | I10: 9 | J10: 2950 | K10: 6980 | L10: 6620 | M10: 5600 | N10: 7600
A11: conquer_high_level_forest_2 | B11: 176 | C11: 5000 | D11: 8500 | E11: 5000 | F11: 5000 | G11: 5000 | I11: 10 | J11: 3670 | K11: 8600 | L11: 8240 | M11: 6950 | N11: 9400
A12: conquer_high_level_forest_3 | B12: 188 | C12: 8000 | D12: 15000 | E12: 8000 | F12: 8000 | G12: 8000 | I12: 11 | J12: 4470 | K12: 10400 | L12: 10040 | M12: 8450 | N12: 11400
A13: conquer_high_level_grassland_1 | B13: 157 | C13: 3000 | D13: 7000 | E13: 3000 | F13: 3000 | G13: 2500 | I13: 12 | J13: 5350 | K13: 12380 | L13: 12020 | M13: 10100 | N13: 13600
... A51: garrison_build_5 | B51: 120 | C51: 8000 | D51: 8500 | E51: 8000 | F51: 8000 | G51: 0 | I51: 50 | J51: 0 | K51: 0 | L51: 0 | M51: 0 | N51: 0
A52: garrison_upgrade_1 | B52: 24 | C52: 2000 | D52: 2400 | E52: 3000 | F52: 2000 | G52: 0
A53: garrison_upgrade_1a | B53: 24 | C53: 2000 | D53: 2400 | E53: 3000 | F53: 2000 | G53: 0
A54: garrison_upgrade_2 | B54: 41 | C54: 4000 | D54: 4800 | E54: 6000 | F54: 4000 | G54: 0
A55: garrison_upgrade_3 | B55: 44 | C55: 6000 | D55: 8500 | E55: 8000 | F55: 6000 | G55: 0
A56: garrison_upgrade_4 | B56: 57 | C56: 8000 | D56: 8500 | E56: 10000 | F56: 8000 | G56: 0
A57: garrison_upgrade_5 | B57: 60 | C57: 8000 | D57: 8500 | E57: 10000 | F57: 8000 | G57: 0
A58: garrison_upgrade_6 | B58: 71 | C58: 8000 | D58: 8500 | E58: 10000 | F58: 8000 | G58: 0
A59: garrison_upgrade_7 | B59: 78 | C59: 8000 | D59: 8500 | E59: 10000 | F59: 8000 | G59: 0
A60: garrison_upgrade_8 | B60: 92 | C60: 8000 | D60: 8500 | E60: 10000 | F60: 8000 | G60: 0
A61: garrison_upgrade_9 | B61: 220 | C61: 8000 | D61: 8500 | E61: 10000 | F61: 8000 | G61: 0
A62: gold_production_1 | B62: 140 | C62: 0 | D62: 0 | E62: 0 | F62: 0 | G62: 1000
A63: gold_production_2 | B63: 107 | C63: 0 | D63: 0 | E63: 0 | F63: 0 | G63: 5000
... A234: woodcraft_research_1 | B234: 34 | C234: 0 | D234: 0 | E234: 0 | F234: 0 | G234: 2000

Sheet 金币产出
A1: 初始人口 | B1: 剧场等级 | C1: 幸福感系数 | D1: 对应的最优税率 | E1: home | F1: 增加人口上限 | G1: 数量 | H1: 总上限
A2: 50 | B2: 1 | C2: 1 | D2: =(C2/100+1)/2 -> 0.505 | E2: 1 | F2: 37 | H2: =F2*G2 -> 0 | J2: 税率 | K2: 0.6 | N2: [0, [100 - tax_rate + happiness_per_level[level.to_s] , 100].min].max
B3: 2 | C3: 3 | D3: =(C3/100+1)/2 -> 0.515 | E3: 2 | F3: 100 | H3: =F3*G3 -> 0 | N3: "happiness_per_level" : {"0":0,"1":1,"2":3,"3":4,"4":5,"5":6,"6":7,"7":8,"8":9,"9":10,"10":11,"11":12,"12":14,"13":15,"14":16,"15":18,"16":19,"17":20,"18":22,"19":23,"20":25},
A4: 龙之召唤 | B4: 3 | C4: 4 | D4: =(C4/100+1)/2 -> 0.52 | E4: 3 | F4: 187 | H4: =F4*G4 -> 0 | J4: 剧场等级 | K4: 16
A5: 1 | B5: 4 | C5: 5 | D5: =(C5/100+1)/2 -> 0.525 | E5: 4 | F5: 300 | H5: =F5*G5 -> 0
B6: 5 | C6: 6 | D6: =(C6/100+1)/2 -> 0.53 | E6: 5 | F6: 437 | H6: =F6*G6 -> 0 | J6: 幸福感 | K6: =MAX(0,MIN(1,1+LOOKUP(K4,B:B,C:C)/100-K2)) -> 0.59
B7: 6 | C7: 7 | D7: =(C7/100+1)/2 -> 0.535 | E7: 6 | F7: 600 | H7: =F7*G7 -> 0
B8: 7 | C8: 8 | D8: =(C8/100+1)/2 -> 0.54 | E8: 7 | F8: 787 | H8: =F8*G8 -> 0 | J8: 纳税人口 | K8: =H22*K6 -> 44279.5
B9: 8 | C9: 9 | D9: =(C9/100+1)/2 -> 0.545 | E9: 8 | F9: 1000 | H9: =F9*G9 -> 0
B10: 9 | C10: 10 | D10: =(C10/100+1)/2 -> 0.55 | E10: 9 | F10: 1237 | H10: =F10*G10 -> 0 | J10: 加倍税收道具 | K10: 0
B11: 10 | C11: 11 | D11: =(C11/100+1)/2 -> 0.555 | E11: 10 | F11: 1500 | H11: =F11*G11 -> 0
B12: 11 | C12: 12 | D12: =(C12/100+1)/2 -> 0.56 | E12: 11 | F12: 1787 | H12: =F12*G12 -> 0
B13: 12 | C13: 14 | D13: =(C13/100+1)/2 -> 0.57 | E13: 12 | F13: 2100 | H13: =F13*G13 -> 0 | J13: 金币产量/小时 | K13: =K8*K2*(1+K10) -> 26567.7
B14: 13 | C14: 15 | D14: =(C14/100+1)/2 -> 0.575 | E14: 13 | F14: 2437 | H14: =F14*G14 -> 0
B15: 14 | C15: 16 | D15: =(C15/100+1)/2 -> 0.58 | E15: 14 | F15: 2800 | H15: =F15*G15 -> 0
B16: 15 | C16: 18 | D16: =(C16/100+1)/2 -> 0.59 | E16: 15 | F16: 3187 | H16: =F16*G16 -> 0 | M16: 最优税率: | N16: （幸福感系数+1）/2
B17: 16 | C17: 19 | D17: =(C17/100+1)/2 -> 0.595 | E17: 16 | F17: 3600 | H17: =F17*G17 -> 0
B18: 17 | C18: 20 | D18: =(C18/100+1)/2 -> 0.6 | E18: 17 | F18: 4037 | H18: =F18*G18 -> 0
B19: 18 | C19: 22 | D19: =(C19/100+1)/2 -> 0.61 | E19: 18 | F19: 4500 | H19: =F19*G19 -> 0
B20: 19 | C20: 23 | D20: =(C20/100+1)/2 -> 0.615 | E20: 19 | F20: 4987 | H20: =F20*G20 -> 0
B21: 20 | C21: 25 | D21: =(C21/100+1)/2 -> 0.625 | E21: 20 | F21: 5500 | G21: 10 | H21: =F21*G21 -> 55000
G22: total | H22: =H21+A2+A5*20000 -> 75050

Sheet 资源产出
A1: 资源建筑等级 | B1: 雇佣人口 | C1: 产量每小时 | D1: 上限 | F1: 初始速度/小时 | G1: 100
A2: 1 | B2: 10 | C2: =B2*10 -> 100 | D2: =C2*100 -> 10000
A3: 2 | B3: 30 | C3: =B3*10 -> 300 | D3: =C3*100 -> 30000 | F3: （初始速度+建筑产出速度）*（1+科技加成+野外资源点加成+道具加成）
A4: 3 | B4: 60 | C4: =B4*10 -> 600 | D4: =C4*100 -> 60000
A5: 4 | B5: 100 | C5: =B5*10 -> 1000 | D5: =C5*100 -> 100000 | G5: 建筑数量 | H5: 12
A6: 5 | B6: 150 | C6: =B6*10 -> 1500 | D6: =C6*100 -> 150000 | G6: 建筑等级 | H6: 10
A7: 6 | B7: 210 | C7: =B7*10 -> 2100 | D7: =C7*100 -> 210000 | G7: 科技等级 | H7: 10 | I7: 科技加成 | J7: =0.1*H7 -> 1
A8: 7 | B8: 280 | C8: =B8*10 -> 2800 | D8: =C8*100 -> 280000 | G8: 野外点等级 | H8: 8
A9: 8 | B9: 360 | C9: =B9*10 -> 3600 | D9: =C9*100 -> 360000 | G9: 野外点数量 | H9: 5 | I9: 野外点加成 | J9: =H8*H9*0.05 -> 2
A10: 9 | B10: 450 | C10: =B10*10 -> 4500 | D10: =C10*100 -> 450000 | G10: 道具 | H10: 1 | I10: 道具加成 | J10: =H10*0.25 -> 0.25
A11: 10 | B11: 550 | C11: =B11*10 -> 5500 | D11: =C11*100 -> 550000
G12: 资源产出速度 | H12: =(G1+H5*LOOKUP(H6,A:A,C:C))*(1+J7+J9+J10) -> 11645
E14: 资源达到上限后资源点不再产出
E15: 野外共38个资源点
M16: level | N16: recover | O16: might
A17: water | B17: 雇佣人口 | C17: 产量每小时 | D17: 上限 | F17: 雇佣人口 | G17: laborers_per_level*(level*level+level) | J17: laborers_per_level | K17: 10 | M17: 1 | N17: =P17*12 -> 24 | O17: =INT(10*(2^(M17/2-1))) -> 7 | P17: =M17*M17+M17 -> 2
A18: 1 | B18: =B2*2 -> 20 | C18: =E18*2 -> 4 | D18: =C18*48 -> 192 | E18: =A2^2+A2 -> 2 | F18: 产量每小时 | G18: rate_increase_per_level*(level*level+level) | J18: rate_increase_per_level | K18: 2 | M18: 2 | N18: =P18*12 -> 72 | O18: =INT(10*(2^(M18/2-1))) -> 10 | P18: =M18*M18+M18 -> 6
A19: 2 | B19: =B3*2 -> 60 | C19: =E19*2 -> 12 | D19: =C19*48 -> 576 | E19: =A3^2+A3 -> 6 | F19: 产量上限 | G19: capacity_increase_per_level*(level*level+level) | J19: capacity_increase_per_level | K19: 96 | M19: 3 | N19: =P19*12 -> 144 | O19: =INT(10*(2^(M19/2-1))) -> 14 | P19: =M19*M19+M19 -> 12
A20: 3 | B20: =B4*2 -> 120 | C20: =E20*2 -> 24 | D20: =C20*48 -> 1152 | E20: =A4^2+A4 -> 12 | M20: 4 | N20: =P20*12 -> 240 | O20: =INT(10*(2^(M20/2-1))) -> 20 | P20: =M20*M20+M20 -> 20
A21: 4 | B21: =B5*2 -> 200 | C21: =E21*2 -> 40 | D21: =C21*48 -> 1920 | E21: =A5^2+A5 -> 20 | M21: 5 | N21: =P21*12 -> 360 | O21: =INT(10*(2^(M21/2-1))) -> 28 | P21: =M21*M21+M21 -> 30
A22: 5 | B22: =B6*2 -> 300 | C22: =E22*2 -> 60 | D22: =C22*48 -> 2880 | E22: =A6^2+A6 -> 30 | M22: 6 | N22: =P22*12 -> 504 | O22: =INT(10*(2^(M22/2-1))) -> 40 | P22: =M22*M22+M22 -> 42
A23: 6 | B23: =B7*2 -> 420 | C23: =E23*2 -> 84 | D23: =C23*48 -> 4032 | E23: =A7^2+A7 -> 42 | M23: 7 | N23: =P23*12 -> 672 | O23: =INT(10*(2^(M23/2-1))) -> 56 | P23: =M23*M23+M23 -> 56
A24: 7 | B24: =B8*2 -> 560 | C24: =E24*2 -> 112 | D24: =C24*48 -> 5376 | E24: =A8^2+A8 -> 56 | M24: 8 | N24: =P24*12 -> 864 | O24: =INT(10*(2^(M24/2-1))) -> 80 | P24: =M24*M24+M24 -> 72
A25: 8 | B25: =B9*2 -> 720 | C25: =E25*2 -> 144 | D25: =C25*48 -> 6912 | E25: =A9^2+A9 -> 72 | M25: 9 | N25: =P25*12 -> 1080 | O25: =INT(10*(2^(M25/2-1))) -> 113 | P25: =M25*M25+M25 -> 90
A26: 9 | B26: =B10*2 -> 900 | C26: =E26*2 -> 180 | D26: =C26*48 -> 8640 | E26: =A10^2+A10 -> 90 | M26: 10 | N26: =P26*12 -> 1320 | O26: =INT(10*(2^(M26/2-1))) -> 160 | P26: =M26*M26+M26 -> 110
A27: 10 | B27: =B11*2 -> 1100 | C27: =E27*2 -> 220 | D27: =C27*48 -> 10560 | E27: =A11^2+A11 -> 110 | M27: 11 | N27: =P27*12 -> 1584 | O27: =INT(10*(2^(M27/2-1))) -> 226 | P27: =M27*M27+M27 -> 132
B28: =B18/$E$18 -> 10 | C28: =C18/$E$18 -> 2 | D28: =D18/$E$18 -> 96 | M28: 12 | N28: =P28*12 -> 1872 | O28: =INT(10*(2^(M28/2-1))) -> 320 | P28: =M28*M28+M28 -> 156
M29: 13 | N29: =P29*12 -> 2184 | O29: =INT(10*(2^(M29/2-1))) -> 452 | P29: =M29*M29+M29 -> 182
M30: 14 | N30: =P30*12 -> 2520 | O30: =INT(10*(2^(M30/2-1))) -> 640 | P30: =M30*M30+M30 -> 210
M31: 15 | N31: =P31*12 -> 2880 | O31: =INT(10*(2^(M31/2-1))) -> 905 | P31: =M31*M31+M31 -> 240
M32: 16 | N32: =P32*12 -> 3264 | O32: =INT(10*(2^(M32/2-1))) -> 1280 | P32: =M32*M32+M32 -> 272
M33: 17 | N33: =P33*12 -> 3672 | O33: =INT(10*(2^(M33/2-1))) -> 1810 | P33: =M33*M33+M33 -> 306
M34: 18 | N34: =P34*12 -> 4104 | O34: =INT(10*(2^(M34/2-1))) -> 2560 | P34: =M34*M34+M34 -> 342
M35: 19 | N35: =P35*12 -> 4560 | O35: =INT(10*(2^(M35/2-1))) -> 3620 | P35: =M35*M35+M35 -> 380
M36: 20 | N36: =P36*12 -> 5040 | O36: =INT(10*(2^(M36/2-1))) -> 5120 | P36: =M36*M36+M36 -> 420

Sheet 野蛮营地怪及资源及掉落
A1: Anthropus Troops and Resources by Level | M1: 兵量及资源每5分钟恢复10%
A2: Level | B2: 1 | C2: 2 | D2: 3 | E2: 4 | F2: 5 | G2: 6 | H2: 7 | I2: 8 | J2: 9 | K2: 10 | L2: Equiv
A3: Brats | B3: 500 | C3: 1000 | D3: 2000 | E3: 5000 | F3: 10000 | G3: 15000 | H3: 30000 | I3: 60000 | J3: 120000 | K3: 250000 | L3: porter | M3: =VLOOKUP(L3,兵种!$A$2:$J$13,10,FALSE) -> 1 | N3: =K3*M3 -> 250000
A4: Cannibal | B4: 500 | C4: 1000 | D4: 2000 | E4: 5000 | F4: 10000 | G4: 15000 | H4: 30000 | I4: 60000 | J4: 120000 | K4: 250000 | L4: Conscript | M4: =VLOOKUP(L4,兵种!$A$2:$J$13,10,FALSE) -> 1 | N4: =K4*M4 -> 250000
A5: Stench | C5: 500 | D5: 1000 | E5: 600 | F5: 5000 | G5: 10000 | H5: 15000 | I5: 30000 | J5: 60000 | K5: 120000 | L5: Spy | M5: =VLOOKUP(L5,兵种!$A$2:$J$13,10,FALSE) -> 2 | N5: =K5*M5 -> 240000
A6: She-Devil | C6: 500 | D6: 1000 | E6: 2000 | F6: 5000 | G6: 10000 | H6: 15000 | I6: 30000 | J6: 60000 | K6: 120000 | L6: Halberdsman | M6: =VLOOKUP(L6,兵种!$A$2:$J$13,10,FALSE) -> 2 | N6: =K6*M6 -> 240000
A7: Clubber | D7: 500 | E7: 1000 | F7: 2000 | G7: 5000 | H7: 10000 | I7: 15000 | J7: 30000 | K7: 60000 | L7: Minotaur | M7: =VLOOKUP(L7,兵种!$A$2:$J$13,10,FALSE) -> 3 | N7: =K7*M7 -> 180000
A8: Hurler | E8: 500 | F8: 1000 | G8: 2000 | H8: 5000 | I8: 10000 | J8: 15000 | K8: 30000 | L8: Longbowman | M8: =VLOOKUP(L8,兵种!$A$2:$J$13,10,FALSE) -> 4 | N8: =K8*M8 -> 120000
A9: Shredder | F9: 500 | G9: 1000 | H9: 2000 | I9: 5000 | J9: 10000 | K9: 15000 | L9: SwiftStrikeDragon | M9: =VLOOKUP(L9,兵种!$A$2:$J$13,10,FALSE) -> 5 | N9: =K9*M9 -> 75000
A10: Chieftain | H10: 500 | I10: 1000 | J10: 2000 | K10: 4000 | L10: BattleDragon | M10: =VLOOKUP(L10,兵种!$A$2:$J$13,10,FALSE) -> 7 | N10: =K10*M10 -> 28000
A11: Bloods | J11: 1000 | K11: 2000 | L11: Giant | M11: =VLOOKUP(L11,兵种!$A$2:$J$13,10,FALSE) -> 9 | N11: =K11*M11 -> 18000
A12: Rager | K12: 1000 | L12: FireMirror | M12: =VLOOKUP(L12,兵种!$A$2:$J$13,10,FALSE) -> 10 | N12: =K12*M12 -> 10000
A13: Launchers
A14: Smash
A15: Gnashers
A16: Divers
B17: =SUM(B3:B16) -> 1000 | C17: =SUM(C3:C16) -> 3000 | D17: =SUM(D3:D16) -> 6500 | E17: =SUM(E3:E16) -> 14100 | F17: =SUM(F3:F16) -> 33500 | G17: =SUM(G3:G16) -> 58000 | H17: =SUM(H3:H16) -> 107500 | I17: =SUM(I3:I16) -> 211000 | ... K17: =SUM(K3:K16) -> 852000
B18: 1 | C18: 2 | D18: 3 | E18: 4 | F18: 5 | G18: 6 | H18: 7 | I18: 8 | J18: 9 | K18: 10
A19: Food | B19: 112500 | C19: 225000 | D19: 337500 | E19: 450000 | F19: 562500 | G19: 675000 | H19: 787500 | I19: 900000 | J19: 1012500 | K19: 1125000
A20: 30000 | B20: 30000 | C20: 30000 | D20: 30000 | E20: 30000 | F20: 30000 | G20: 30000 | H20: 35000 | I20: 40000 | J20: 45000 | K20: 50000
A21: Stone | B21: 500 | C21: 1000 | D21: 1500 | E21: 2000 | F21: 2500 | G21: 3000 | H21: 3500 | I21: 4000 | J21: 4500 | K21: 5000
A22: metal | B22: 500 | C22: 1000 | D22: 1500 | E22: 2000 | F22: 2500 | G22: 3000 | H22: 3500 | I22: 4000 | J22: 4500 | K22: 5000
A23: Gold | B23: 2500 | C23: 5000 | D23: 7500 | E23: 10000 | F23: 12500 | G23: 15000 | H23: 17500 | I23: 20000 | J23: 22500 | K23: 25000
A25: 道具产出 | C25: 权重
B26: 几率 | C26: 1 | D26: 2 | E26: 3 | F26: 4
A27: Blink | B27: 0.05 | C27: 4 | D27: 4 | E27: 4 | F27: 4
A28: Hop | B28: 0.05 | C28: 3 | D28: 3 | E28: 3 | F28: 3
A29: Skip | B29: 0.1 | C29: 2 | D29: 2 | E29: 2 | F29: 2
A30: Jump | B30: 0.1 | C30: 1 | D30: 1 | E30: 1 | F30: 1

Sheet 资源点怪及奖励
A1: Level | B1: 1 | C1: 2 | D1: 3 | E1: 4 | F1: 5 | G1: 6 | H1: 7 | I1: 8 | J1: 9 | K1: 10 | L1: Equiv
A2: Cannibals | B2: 50 | C2: 100 | D2: 200 | E2: 500 | F2: 1000 | G2: 2000 | H2: 2000 | I2: 5000 | J2: 10000 | K2: 20000 | L2: Con
A3: Stench | C3: 50 | D3: 100 | E3: 200 | F3: 500 | G3: =G2/2 -> 1000 | H3: =H2/2 -> 1000 | I3: 2000 | J3: 5000 | K3: 10000 | L3: Spy
A4: She-Devil | D4: 50 | E4: 100 | F4: 200 | G4: 500 | H4: 500 | I4: =I3/2 -> 1000 | J4: 2000 | K4: 5000 | L4: Hal
A5: Clubbers | E5: 50 | F5: 100 | G5: 200 | H5: 200 | I5: 500 | J5: =J4/2 -> 1000 | K5: 2000 | L5: Mino | M5: 可占领资源点等级取决于城堡等级
A6: Hurlers | F6: 50 | G6: 100 | H6: 100 | I6: 200 | J6: 500 | K6: =K5/2 -> 1000 | L6: LBM | M6: 每级野外资源点对应资源产出加速5%
A7: Shredders | G7: 50 | H7: 50 | I7: 100 | J7: 200 | K7: 500 | L7: SSD
A8: Chieftains | I8: 50 | J8: 100 | K8: 200 | L8: BD
A9: Bloods | J9: 50 | K9: 100 | L9: Giant
A10: Ragers | K10: 50 | L10: FM
B11: =SUM(B2:B10) -> 50 | C11: =SUM(C2:C10) -> 150 | D11: =SUM(D2:D10) -> 350 | E11: =SUM(E2:E10) -> 850 | F11: =SUM(F2:F10) -> 1850 | G11: =SUM(G2:G10) -> 3850 | H11: =SUM(H2:H10) -> 3850 | I11: =SUM(I2:I10) -> 8850 | ... K11: =SUM(K2:K10) -> 38850
A12: 1 | B12: 2 | C12: 3 | D12: 4 | E12: 5 | F12: 6 | G12: 7 | H12: 8 | I12: 9 | J12: 10
A13: Lake | B13: 1000 | C13: 2000 | D13: 3000 | E13: 4000 | F13: 5000 | G13: 6000 | H13: 7000 | I13: 8000 | J13: 9000 | K13: 10000 | L13: Food
A14: Hill | B14: 1000 | C14: 2000 | D14: 3000 | E14: 4000 | F14: 5000 | G14: 6000 | H14: 7000 | I14: 8000 | J14: 9000 | K14: 10000 | L14: Stone
A15: Mountain | B15: 1000 | C15: 2000 | D15: 3000 | E15: 4000 | F15: 5000 | G15: 6000 | H15: 7000 | I15: 8000 | J15: 9000 | K15: 10000 | L15: metal
A16: Forest | B16: 1000 | C16: 2000 | D16: 3000 | E16: 4000 | F16: 5000 | G16: 6000 | H16: 7000 | I16: 8000 | J16: 9000 | K16: 10000 | L16: Wood
A17: Savanna | B17: 1000 | C17: 2000 | D17: 3000 | E17: 4000 | F17: 5000 | G17: 6000 | H17: 7000 | I17: 8000 | J17: 9000 | K17: 10000 | L17: Food

Sheet 战役兵种及资源
B1: 1 | C1: 2 | D1: 3 | E1: 4 | F1: 5 | G1: 6 | H1: 7 | I1: 8 | J1: 9 | K1: 10
A2: Porter | B2: 5 | D2: 1000
A3: Conscript | C3: 25 | D3: 400
A4: Halberdsman | E4: 500 | H4: 1000
A5: Minotaur | E5: 500
A6: Longbowman | F6: 600 | H6: 1500
A7: SwiftStrikeDragon | G7: 1000
A8: BattleDragon | I8: 500 | J8: 600
A9: Giant | J9: 260
A10: BlackholeOne | K10: 10000000
A14: gold | B14: 1000 | C14: 2000 | D14: 3000 | E14: 4000 | F14: 5000 | G14: 6000 | H14: 7000 | I14: 8000 | J14: 9000 | K14: 20000
A15: food | B15: 1000 | C15: 2000 | D15: 3000 | E15: 4000 | F15: 5000 | G15: 6000 | H15: 7000 | I15: 8000 | J15: 9000 | K15: 20000
A16: wood | B16: 1000 | C16: 2000 | D16: 3000 | E16: 4000 | F16: 5000 | G16: 6000 | H16: 7000 | I16: 8000 | J16: 9000 | K16: 20000
A17: stone | B17: 1000 | C17: 2000 | D17: 3000 | E17: 4000 | F17: 5000 | G17: 6000 | H17: 7000 | I17: 8000 | J17: 9000 | K17: 20000
A18: ore | B18: 1000 | C18: 2000 | D18: 3000 | E18: 4000 | F18: 5000 | G18: 6000 | H18: 7000 | I18: 8000 | J18: 9000 | K18: 20000
A20: 掉落：
B21: replace
B22: PurpleBones | C22: 0.65
B23: DarkWarpDevice | C23: 0.2
B24: Bounce | C24: 0.1
B25: Bore | C25: 0.05
B26: once
B27: Helmet | C27: 0.65
B28: Tail | C28: 0.2
B29: Body | C29: 0.1
B30: Claw | C30: 0.05

Sheet 建筑消耗
A1: building_type | B1: level | C1: time | E1: ore | F1: wood | G1: stone | H1: food | I1: gold | J1: items | K1: time value | L1: total resource | M1: resource value | N1: DI value | O1: total instant upgrade price | P1: modified price
A2: Buildings::DragonKeep | B2: 0 | C2: 0 | D2: =IF(INT(C2/3600/24)=0,"",INT(C2/3600/24)&"D")&IF(INT(MOD(C2,3600*24)/3600)=0,"",INT(MOD(C2,3600*24)/3600)&"H")&IF(INT(MOD(C2,3600)/60)=0,"",INT(MOD(C2,3600)/60)&"M")&INT(MOD(C2,60))&"S" -> 0S | K2: 0 | L2: 0 | M2: 0 | O2: 0
A3: Buildings::DragonKeep | B3: 1 | C3: 5 | D3: =IF(INT(C3/3600/24)=0,"",INT(C3/3600/24)&"D")&IF(INT(MOD(C3,3600*24)/3600)=0,"",INT(MOD(C3,3600*24)/3600)&"H")&IF(INT(MOD(C3,3600)/60)=0,"",INT(MOD(C3,3600)/60)&"M")&INT(MOD(C3,60))&"S" -> 5S | E3: 700 | F3: 2500 | G3: 1200 | H3: 400 | I3: 1500 | K3: 0.083333333 | L3: 6300 | M3: 1.575 | O3: 1.6583333 | P3: 3
A4: Buildings::DragonKeep | B4: 2 | C4: 5 | D4: =IF(INT(C4/3600/24)=0,"",INT(C4/3600/24)&"D")&IF(INT(MOD(C4,3600*24)/3600)=0,"",INT(MOD(C4,3600*24)/3600)&"H")&IF(INT(MOD(C4,3600)/60)=0,"",INT(MOD(C4,3600)/60)&"M")&INT(MOD(C4,60))&"S" -> 5S | E4: 100 | F4: 100 | G4: 100 | H4: 100 | I4: 100 | K4: 0.083333333 | L4: 500 | M4: 0.125 | O4: 0.20833333 | P4: 1
A5: Buildings::DragonKeep | B5: 3 | C5: 190 | D5: =IF(INT(C5/3600/24)=0,"",INT(C5/3600/24)&"D")&IF(INT(MOD(C5,3600*24)/3600)=0,"",INT(MOD(C5,3600*24)/3600)&"H")&IF(INT(MOD(C5,3600)/60)=0,"",INT(MOD(C5,3600)/60)&"M")&INT(MOD(C5,60))&"S" -> 3M10S | E5: 738 | F5: 2638 | G5: 1266 | H5: 422 | I5: 1583 | K5: 3.1666667 | L5: 6647 | M5: 1.66175 | O5: 4.8284167 | P5: 7
A6: Buildings::DragonKeep | B6: 4 | C6: 277 | D6: =IF(INT(C6/3600/24)=0,"",INT(C6/3600/24)&"D")&IF(INT(MOD(C6,3600*24)/3600)=0,"",INT(MOD(C6,3600*24)/3600)&"H")&IF(INT(MOD(C6,3600)/60)=0,"",INT(MOD(C6,3600)/60)&"M")&INT(MOD(C6,60))&"S" -> 4M37S | E6: 1077 | F6: 3847 | G6: 1846 | H6: 615 | I6: 2308 | K6: 4.6166667 | L6: 9693 | M6: 2.42325 | O6: 7.0399167 | P6: 10
A7: Buildings::DragonKeep | B7: 5 | C7: 404 | D7: =IF(INT(C7/3600/24)=0,"",INT(C7/3600/24)&"D")&IF(INT(MOD(C7,3600*24)/3600)=0,"",INT(MOD(C7,3600*24)/3600)&"H")&IF(INT(MOD(C7,3600)/60)=0,"",INT(MOD(C7,3600)/60)&"M")&INT(MOD(C7,60))&"S" -> 6M44S | E7: 1571 | F7: 5611 | G7: 2693 | H7: 897 | I7: 3366 | K7: 4.04 | L7: 14138 | M7: 3.5345 | O7: 7.5745 | P7: 11
A8: Buildings::DragonKeep | B8: 6 | C8: 590 | D8: =IF(INT(C8/3600/24)=0,"",INT(C8/3600/24)&"D")&IF(INT(MOD(C8,3600*24)/3600)=0,"",INT(MOD(C8,3600*24)/3600)&"H")&IF(INT(MOD(C8,3600)/60)=0,"",INT(MOD(C8,3600)/60)&"M")&INT(MOD(C8,60))&"S" -> 9M50S | E8: 1529 | F8: 5462 | G8: 2622 | H8: 874 | I8: 3277 | K8: 5.9 | L8: 13764 | M8: 3.441 | O8: 9.341 | P8: 13
A9: Buildings::DragonKeep | B9: 7 | C9: 860 | D9: =IF(INT(C9/3600/24)=0,"",INT(C9/3600/24)&"D")&IF(INT(MOD(C9,3600*24)/3600)=0,"",INT(MOD(C9,3600*24)/3600)&"H")&IF(INT(MOD(C9,3600)/60)=0,"",INT(MOD(C9,3600)/60)&"M")&INT(MOD(C9,60))&"S" -> 14M20S | E9: 1672 | F9: 5972 | G9: 2866 | H9: 955 | I9: 3583 | K9: 8.6 | L9: 15048 | M9: 3.762 | O9: 12.362 | P9: 17
A10: Buildings::DragonKeep | B10: 8 | C10: 1254 | D10: =IF(INT(C10/3600/24)=0,"",INT(C10/3600/24)&"D")&IF(INT(MOD(C10,3600*24)/3600)=0,"",INT(MOD(C10,3600*24)/3600)&"H")&IF(INT(MOD(C10,3600)/60)=0,"",INT(MOD(C10,3600)/60)&"M")&INT(MOD(C10,60))&"S" -> 20M54S | E10: 2438 | F10: 8708 | G10: 4180 | H10: 1393 | I10: 5225 | J10: =48*60 -> 2880 | K10: 6.9666667 | L10: 21944 | M10: 5.486 | O10: 12.452667 | P10: 18
A11: Buildings::DragonKeep | B11: 9 | C11: 1828 | D11: =IF(INT(C11/3600/24)=0,"",INT(C11/3600/24)&"D")&IF(INT(MOD(C11,3600*24)/3600)=0,"",INT(MOD(C11,3600*24)/3600)&"H")&IF(INT(MOD(C11,3600)/60)=0,"",INT(MOD(C11,3600)/60)&"M")&INT(MOD(C11,60))&"S" -> 30M28S | E11: 3554 | F11: 12694 | G11: 6093 | H11: 2031 | I11: 7616 | K11: 10.155556 | L11: 31988 | M11: 7.997 | O11: 18.152556 | P11: 24
A12: Buildings::DragonKeep | B12: 10 | C12: 2665 | D12: =IF(INT(C12/3600/24)=0,"",INT(C12/3600/24)&"D")&IF(INT(MOD(C12,3600*24)/3600)=0,"",INT(MOD(C12,3600*24)/3600)&"H")&IF(INT(MOD(C12,3600)/60)=0,"",INT(MOD(C12,3600)/60)&"M")&INT(MOD(C12,60))&"S" -> 44M25S | E12: 5181 | F12: 18506 | G12: 8883 | H12: 2961 | I12: 11104 | K12: 14.805556 | L12: 46635 | M12: 11.65875 | O12: 26.464306 | P12: 35
A13: Buildings::DragonKeep | B13: 11 | C13: 3884 | D13: =IF(INT(C13/3600/24)=0,"",INT(C13/3600/24)&"D")&IF(INT(MOD(C13,3600*24)/3600)=0,"",INT(MOD(C13,3600*24)/3600)&"H")&IF(INT(MOD(C13,3600)/60)=0,"",INT(MOD(C13,3600)/60)&"M")&INT(MOD(C13,60))&"S" -> 1H4M44S | E13: 7552 | F13: 26972 | G13: 12946 | H13: 4315 | I13: 16183 | K13: 10.788889 | L13: 67968 | M13: 16.992 | O13: 27.780889 | P13: 37
A14: Buildings::DragonKeep | B14: 12 | C14: 5663 | D14: =IF(INT(C14/3600/24)=0,"",INT(C14/3600/24)&"D")&IF(INT(MOD(C14,3600*24)/3600)=0,"",INT(MOD(C14,3600*24)/3600)&"H")&IF(INT(MOD(C14,3600)/60)=0,"",INT(MOD(C14,3600)/60)&"M")&INT(MOD(C14,60))&"S" -> 1H34M23S | E14: 11011 | F14: 39326 | G14: 18876 | H14: 6292 | I14: 23595 | K14: 15.730556 | L14: 99100 | M14: 24.775 | O14: 40.505556 | P14: 53
A15: Buildings::DragonKeep | B15: 13 | C15: 8255 | D15: =IF(INT(C15/3600/24)=0,"",INT(C15/3600/24)&"D")&IF(INT(MOD(C15,3600*24)/3600)=0,"",INT(MOD(C15,3600*24)/3600)&"H")&IF(INT(MOD(C15,3600)/60)=0,"",INT(MOD(C15,3600)/60)&"M")&INT(MOD(C15,60))&"S" -> 2H17M35S | E15: 16051 | F15: 57326 | G15: 27516 | H15: 9172 | I15: 34395 | K15: 22.930556 | L15: 144460 | M15: 36.115 | O15: 59.045556 | P15: 77
A16: Buildings::DragonKeep | B16: 14 | C16: 12033 | D16: =IF(INT(C16/3600/24)=0,"",INT(C16/3600/24)&"D")&IF(INT(MOD(C16,3600*24)/3600)=0,"",INT(MOD(C16,3600*24)/3600)&"H")&IF(INT(MOD(C16,3600)/60)=0,"",INT(MOD(C16,3600)/60)&"M")&INT(MOD(C16,60))&"S" -> 3H20M33S | E16: 23397 | F16: 83562 | G16: 40110 | H16: 13370 | I16: 50137 | K16: 20.055 | L16: 210576 | M16: 52.644 | O16: 72.699 | P16: 95
A17: Buildings::DragonKeep | B17: 15 | C17: 17540 | D17: =IF(INT(C17/3600/24)=0,"",INT(C17/3600/24)&"D")&IF(INT(MOD(C17,3600*24)/3600)=0,"",INT(MOD(C17,3600*24)/3600)&"H")&IF(INT(MOD(C17,3600)/60)=0,"",INT(MOD(C17,3600)/60)&"M")&INT(MOD(C17,60))&"S" -> 4H52M20S | E17: 34105 | F17: 121805 | G17: 58466 | H17: 19488 | I17: 73083 | K17: 29.233333 | L17: 306947 | M17: 67.52834 | O17: 96.761673 | P17: 126
A18: Buildings::DragonKeep | B18: 16 | C18: 25568 | D18: =IF(INT(C18/3600/24)=0,"",INT(C18/3600/24)&"D")&IF(INT(MOD(C18,3600*24)/3600)=0,"",INT(MOD(C18,3600*24)/3600)&"H")&IF(INT(MOD(C18,3600)/60)=0,"",INT(MOD(C18,3600)/60)&"M")&INT(MOD(C18,60))&"S" -> 7H6M8S | E18: 49715 | F18: 177555 | G18: 85226 | H18: 28408 | I18: 106533 | K18: 42.613333 | L18: 447437 | M18: 98.43614 | O18: 141.04947 | P18: 184
A19: Buildings::DragonKeep | B19: 17 | C19: 37271 | D19: =IF(INT(C19/3600/24)=0,"",INT(C19/3600/24)&"D")&IF(INT(MOD(C19,3600*24)/3600)=0,"",INT(MOD(C19,3600*24)/3600)&"H")&IF(INT(MOD(C19,3600)/60)=0,"",INT(MOD(C19,3600)/60)&"M")&INT(MOD(C19,60))&"S" -> 10H21M11S | E19: 72471 | F19: 258826 | G19: 124236 | H19: 41412 | I19: 155295 | K19: 51.765278 | L19: 652240 | M19: 123.9256 | O19: 175.69088 | P19: 229
A20: Buildings::DragonKeep | B20: 18 | C20: 54329 | D20: =IF(INT(C20/3600/24)=0,"",INT(C20/3600/24)&"D")&IF(INT(MOD(C20,3600*24)/3600)=0,"",INT(MOD(C20,3600*24)/3600)&"H")&IF(INT(MOD(C20,3600)/60)=0,"",INT(MOD(C20,3600)/60)&"M")&INT(MOD(C20,60))&"S" -> 15H5M29S | E20: 105639 | F20: 377284 | G20: 181096 | H20: 60365 | I20: 226370 | K20: 65.396019 | L20: 950754 | M20: 180.64326 | O20: 246.03928 | P20: 320
A21: Buildings::DragonKeep | B21: 19 | C21: 79195 | D21: =IF(INT(C21/3600/24)=0,"",INT(C21/3600/24)&"D")&IF(INT(MOD(C21,3600*24)/3600)=0,"",INT(MOD(C21,3600*24)/3600)&"H")&IF(INT(MOD(C21,3600)/60)=0,"",INT(MOD(C21,3600)/60)&"M")&INT(MOD(C21,60))&"S" -> 21H59M55S | E21: 153990 | F21: 549965 | G21: 263983 | H21: 87994 | I21: 329979 | K21: 95.327315 | L21: 1385911 | M21: 263.32309 | O21: 358.6504 | P21: 467
A22: Buildings::DragonKeep | B22: 20 | C22: 115442 | D22: =IF(INT(C22/3600/24)=0,"",INT(C22/3600/24)&"D")&IF(INT(MOD(C22,3600*24)/3600)=0,"",INT(MOD(C22,3600*24)/3600)&"H")&IF(INT(MOD(C22,3600)/60)=0,"",INT(MOD(C22,3600)/60)&"M")&INT(MOD(C22,60))&"S" -> 1D8H4M2S | E22: 224470 | F22: 801680 | G22: 384806 | H22: 128268 | I22: 481008 | J22: CompletionGrant | K22: 126.93275 | L22: 2020232 | M22: 383.84408 | N22: 40 | O22: 550.77683 | P22: 717
A23: Buildings::Wall | B23: 0 | C23: 0 | D23: =IF(INT(C23/3600/24)=0,"",INT(C23/3600/24)&"D")&IF(INT(MOD(C23,3600*24)/3600)=0,"",INT(MOD(C23,3600*24)/3600)&"H")&IF(INT(MOD(C23,3600)/60)=0,"",INT(MOD(C23,3600)/60)&"M")&INT(MOD(C23,60))&"S" -> 0S | K23: 0 | L23: 0 | M23: 0 | O23: 0 | P23: 0
A24: Buildings::Wall | B24: 1 | C24: 0 | D24: =IF(INT(C24/3600/24)=0,"",INT(C24/3600/24)&"D")&IF(INT(MOD(C24,3600*24)/3600)=0,"",INT(MOD(C24,3600*24)/3600)&"H")&IF(INT(MOD(C24,3600)/60)=0,"",INT(MOD(C24,3600)/60)&"M")&INT(MOD(C24,60))&"S" -> 0S | E24: 0 | F24: 0 | G24: 0 | H24: 0 | I24: 0 | K24: 0 | L24: 0 | M24: 0 | O24: 0 | P24: 0
A25: Buildings::Wall | B25: 2 | C25: 1059 | D25: =IF(INT(C25/3600/24)=0,"",INT(C25/3600/24)&"D")&IF(INT(MOD(C25,3600*24)/3600)=0,"",INT(MOD(C25,3600*24)/3600)&"H")&IF(INT(MOD(C25,3600)/60)=0,"",INT(MOD(C25,3600)/60)&"M")&INT(MOD(C25,60))&"S" -> 17M39S | E25: 266 | F25: 798 | G25: 5324 | H25: 1597 | K25: 5.8833333 | L25: 7985 | M25: 1.99625 | O25: 7.8795833 | P25: 11
A26: Buildings::Wall | B26: 3 | C26: 1507 | D26: =IF(INT(C26/3600/24)=0,"",INT(C26/3600/24)&"D")&IF(INT(MOD(C26,3600*24)/3600)=0,"",INT(MOD(C26,3600*24)/3600)&"H")&IF(INT(MOD(C26,3600)/60)=0,"",INT(MOD(C26,3600)/60)&"M")&INT(MOD(C26,60))&"S" -> 25M7S | E26: 378 | F26: 1136 | G26: 7577 | H26: 2273 | K26: 8.3722222 | L26: 11364 | M26: 2.841 | O26: 11.213222 | P26: 15
A27: Buildings::Wall | B27: 4 | C27: 2144 | D27: =IF(INT(C27/3600/24)=0,"",INT(C27/3600/24)&"D")&IF(INT(MOD(C27,3600*24)/3600)=0,"",INT(MOD(C27,3600*24)/3600)&"H")&IF(INT(MOD(C27,3600)/60)=0,"",INT(MOD(C27,3600)/60)&"M")&INT(MOD(C27,60))&"S" -> 35M44S | E27: 539 | F27: 1617 | G27: 10780 | H27: 3234 | K27: 11.911111 | L27: 16170 | M27: 4.0425 | O27: 15.953611 | P27: 21
A28: Buildings::Wall | B28: 5 | C28: 3052 | D28: =IF(INT(C28/3600/24)=0,"",INT(C28/3600/24)&"D")&IF(INT(MOD(C28,3600*24)/3600)=0,"",INT(MOD(C28,3600*24)/3600)&"H")&IF(INT(MOD(C28,3600)/60)=0,"",INT(MOD(C28,3600)/60)&"M")&INT(MOD(C28,60))&"S" -> 50M52S | E28: 767 | F28: 2301 | G28: 15346 | H28: 4603 | K28: 16.955556 | L28: 23017 | M28: 5.75425 | O28: 22.709806 | P28: 26
A29: Buildings::Wall | B29: 6 | C29: 4343 | D29: =IF(INT(C29/3600/24)=0,"",INT(C29/3600/24)&"D")&IF(INT(MOD(C29,3600*24)/3600)=0,"",INT(MOD(C29,3600*24)/3600)&"H")&IF(INT(MOD(C29,3600)/60)=0,"",INT(MOD(C29,3600)/60)&"M")&INT(MOD(C29,60))&"S" -> 1H12M23S | E29: 1091 | F29: 3275 | G29: 21837 | H29: 6551 | K29: 12.063889 | L29: 32754 | M29: 8.1885 | O29: 20.252389 | P29: 30
A30: Buildings::Wall | B30: 7 | C30: 6181 | D30: =IF(INT(C30/3600/24)=0,"",INT(C30/3600/24)&"D")&IF(INT(MOD(C30,3600*24)/3600)=0,"",INT(MOD(C30,3600*24)/3600)&"H")&IF(INT(MOD(C30,3600)/60)=0,"",INT(MOD(C30,3600)/60)&"M")&INT(MOD(C30,60))&"S" -> 1H43M1S | E30: 1553 | F30: 4661 | G30: 31079 | H30: 9323 | K30: 17.169444 | L30: 46616 | M30: 11.654 | O30: 28.823444 | P30: 38
A31: Buildings::Wall | B31: 8 | C31: 8796 | D31: =IF(INT(C31/3600/24)=0,"",INT(C31/3600/24)&"D")&IF(INT(MOD(C31,3600*24)/3600)=0,"",INT(MOD(C31,3600*24)/3600)&"H")&IF(INT(MOD(C31,3600)/60)=0,"",INT(MOD(C31,3600)/60)&"M")&INT(MOD(C31,60))&"S" -> 2H26M36S | E31: 2211 | F31: 6634 | G31: 44227 | H31: 13268 | K31: 24.433333 | L31: 66340 | M31: 16.585 | O31: 41.018333 | P31: 54
A32: Buildings::Wall | B32: 9 | C32: 12517 | D32: =IF(INT(C32/3600/24)=0,"",INT(C32/3600/24)&"D")&IF(INT(MOD(C32,3600*24)/3600)=0,"",INT(MOD(C32,3600*24)/3600)&"H")&IF(INT(MOD(C32,3600)/60)=0,"",INT(MOD(C32,3600)/60)&"M")&INT(MOD(C32,60))&"S" -> 3H28M37S | E32: 3146 | F32: 9440 | G32: 62937 | H32: 18881 | K32: 20.861667 | L32: 94404 | M32: 23.601 | O32: 44.462667 | P32: 65
A33: Buildings::Wall | B33: 10 | C33: 17812 | D33: =IF(INT(C33/3600/24)=0,"",INT(C33/3600/24)&"D")&IF(INT(MOD(C33,3600*24)/3600)=0,"",INT(MOD(C33,3600*24)/3600)&"H")&IF(INT(MOD(C33,3600)/60)=0,"",INT(MOD(C33,3600)/60)&"M")&INT(MOD(C33,60))&"S" -> 4H56M52S | E33: 4478 | F33: 13434 | G33: 89562 | H33: 26868 | K33: 29.686667 | L33: 134342 | M33: 33.5855 | O33: 63.272167 | P33: 83
A34: Buildings::Wall | B34: 11 | C34: 25348 | D34: =IF(INT(C34/3600/24)=0,"",INT(C34/3600/24)&"D")&IF(INT(MOD(C34,3600*24)/3600)=0,"",INT(MOD(C34,3600*24)/3600)&"H")&IF(INT(MOD(C34,3600)/60)=0,"",INT(MOD(C34,3600)/60)&"M")&INT(MOD(C34,60))&"S" -> 7H2M28S | E34: 6372 | F34: 19118 | G34: 127454 | H34: 38236 | K34: 42.246667 | L34: 191180 | M34: 47.795 | O34: 90.041667 | P34: 118
A35: Buildings::Wall | B35: 12 | C35: 36071 | D35: =IF(INT(C35/3600/24)=0,"",INT(C35/3600/24)&"D")&IF(INT(MOD(C35,3600*24)/3600)=0,"",INT(MOD(C35,3600*24)/3600)&"H")&IF(INT(MOD(C35,3600)/60)=0,"",INT(MOD(C35,3600)/60)&"M")&INT(MOD(C35,60))&"S" -> 10H1M11S | E35: 9068 | F35: 27205 | G35: 181371 | H35: 54411 | K35: 50.098611 | L35: 272055 | M35: 59.8521 | O35: 109.95071 | P35: 143
A36: Buildings::Wall | B36: 13 | C36: 51331 | D36: =IF(INT(C36/3600/24)=0,"",INT(C36/3600/24)&"D")&IF(INT(MOD(C36,3600*24)/3600)=0,"",INT(MOD(C36,3600*24)/3600)&"H")&IF(INT(MOD(C36,3600)/60)=0,"",INT(MOD(C36,3600)/60)&"M")&INT(MOD(C36,60))&"S" -> 14H15M31S | E36: 12905 | F36: 38715 | G36: 258102 | H36: 77430 | K36: 71.293056 | L36: 387152 | M36: 85.17344 | O36: 156.4665 | P36: 204
... A42: Buildings::Wall | B42: 19 | C42: 426282 | D42: =IF(INT(C42/3600/24)=0,"",INT(C42/3600/24)&"D")&IF(INT(MOD(C42,3600*24)/3600)=0,"",INT(MOD(C42,3600*24)/3600)&"H")&IF(INT(MOD(C42,3600)/60)=0,"",INT(MOD(C42,3600)/60)&"M")&INT(MOD(C42,60))&"S" -> 4D22H24M42S | E42: 107171 | F42: 321514 | G42: 2143427 | H42: 643028 | K42: 339.20009 | L42: 3215140 | M42: 610.8766 | O42: 950.07669 | P42: 1236
A43: Buildings::Wall | B43: 20 | C43: 606620 | D43: =IF(INT(C43/3600/24)=0,"",INT(C43/3600/24)&"D")&IF(INT(MOD(C43,3600*24)/3600)=0,"",INT(MOD(C43,3600*24)/3600)&"H")&IF(INT(MOD(C43,3600)/60)=0,"",INT(MOD(C43,3600)/60)&"M")&INT(MOD(C43,60))&"S" -> 7D30M20S | E43: 152510 | F43: 457530 | G43: 3050201 | H43: 915060 | J43: CompletionGrant | K43: 482.69821 | L43: 4575301 | M43: 869.30719 | N43: 40 | O43: 1392.0054 | P43: 1810
A44: Buildings::OfficerQuarter | B44: 0 | C44: 0 | D44: =IF(INT(C44/3600/24)=0,"",INT(C44/3600/24)&"D")&IF(INT(MOD(C44,3600*24)/3600)=0,"",INT(MOD(C44,3600*24)/3600)&"H")&IF(INT(MOD(C44,3600)/60)=0,"",INT(MOD(C44,3600)/60)&"M")&INT(MOD(C44,60))&"S" -> 0S | K44: 0 | L44: 0 | M44: 0 | O44: 0 | P44: 0
A45: Buildings::OfficerQuarter | B45: 1 | C45: 148 | D45: =IF(INT(C45/3600/24)=0,"",INT(C45/3600/24)&"D")&IF(INT(MOD(C45,3600*24)/3600)=0,"",INT(MOD(C45,3600*24)/3600)&"H")&IF(INT(MOD(C45,3600)/60)=0,"",INT(MOD(C45,3600)/60)&"M")&INT(MOD(C45,60))&"S" -> 2M28S | E45: 260 | F45: 930 | G45: 446 | H45: 148 | K45: 2.4666667 | L45: 1784 | M45: 0.446 | O45: 2.9126667 | P45: 4
A46: Buildings::OfficerQuarter | B46: 2 | C46: 211 | D46: =IF(INT(C46/3600/24)=0,"",INT(C46/3600/24)&"D")&IF(INT(MOD(C46,3600*24)/3600)=0,"",INT(MOD(C46,3600*24)/3600)&"H")&IF(INT(MOD(C46,3600)/60)=0,"",INT(MOD(C46,3600)/60)&"M")&INT(MOD(C46,60))&"S" -> 3M31S | E46: 371 | F46: 1326 | G46: 636 | H46: 212 | K46: 3.5166667 | L46: 2545 | M46: 0.63625 | O46: 4.1529167 | P46: 6
A47: Buildings::OfficerQuarter | B47: 3 | C47: 301 | D47: =IF(INT(C47/3600/24)=0,"",INT(C47/3600/24)&"D")&IF(INT(MOD(C47,3600*24)/3600)=0,"",INT(MOD(C47,3600*24)/3600)&"H")&IF(INT(MOD(C47,3600)/60)=0,"",INT(MOD(C47,3600)/60)&"M")&INT(MOD(C47,60))&"S" -> 5M1S | E47: 529 | F47: 1892 | G47: 908 | H47: 302 | K47: 3.01 | L47: 3631 | M47: 0.90775 | O47: 3.91775 | P47: 7
A48: Buildings::OfficerQuarter | B48: 4 | C48: 428 | D48: =IF(INT(C48/3600/24)=0,"",INT(C48/3600/24)&"D")&IF(INT(MOD(C48,3600*24)/3600)=0,"",INT(MOD(C48,3600*24)/3600)&"H")&IF(INT(MOD(C48,3600)/60)=0,"",INT(MOD(C48,3600)/60)&"M")&INT(MOD(C48,60))&"S" -> 7M8S | E48: 753 | F48: 2690 | G48: 1291 | H48: 430 | K48: 4.28 | L48: 5164 | M48: 1.291 | O48: 5.571 | P48: 8
A49: Buildings::OfficerQuarter | B49: 5 | C49: 610 | D49: =IF(INT(C49/3600/24)=0,"",INT(C49/3600/24)&"D")&IF(INT(MOD(C49,3600*24)/3600)=0,"",INT(MOD(C49,3600*24)/3600)&"H")&IF(INT(MOD(C49,3600)/60)=0,"",INT(MOD(C49,3600)/60)&"M")&INT(MOD(C49,60))&"S" -> 10M10S | E49: 1073 | F49: 3834 | G49: 1840 | H49: 613 | K49: 6.1 | L49: 7360 | M49: 1.84 | O49: 7.94 | P49: 11
A50: Buildings::OfficerQuarter | B50: 6 | C50: 868 | D50: =IF(INT(C50/3600/24)=0,"",INT(C50/3600/24)&"D")&IF(INT(MOD(C50,3600*24)/3600)=0,"",INT(MOD(C50,3600*24)/3600)&"H")&IF(INT(MOD(C50,3600)/60)=0,"",INT(MOD(C50,3600)/60)&"M")&INT(MOD(C50,60))&"S" -> 14M28S | E50: 1527 | F50: 5456 | G50: 2618 | H50: 872 | K50: 8.68 | L50: 10473 | M50: 2.61825 | O50: 11.29825 | P50: 13
A51: Buildings::OfficerQuarter | B51: 7 | C51: 1235 | D51: =IF(INT(C51/3600/24)=0,"",INT(C51/3600/24)&"D")&IF(INT(MOD(C51,3600*24)/3600)=0,"",INT(MOD(C51,3600*24)/3600)&"H")&IF(INT(MOD(C51,3600)/60)=0,"",INT(MOD(C51,3600)/60)&"M")&INT(MOD(C51,60))&"S" -> 20M35S | E51: 2173 | F51: 7763 | G51: 3726 | H51: 1242 | K51: 6.8611111 | L51: 14904 | M51: 3.726 | O51: 10.587111 | P51: 15
A52: Buildings::OfficerQuarter | B52: 8 | C52: 1758 | D52: =IF(INT(C52/3600/24)=0,"",INT(C52/3600/24)&"D")&IF(INT(MOD(C52,3600*24)/3600)=0,"",INT(MOD(C52,3600*24)/3600)&"H")&IF(INT(MOD(C52,3600)/60)=0,"",INT(MOD(C52,3600)/60)&"M")&INT(MOD(C52,60))&"S" -> 29M18S | E52: 3094 | F52: 11050 | G52: 5304 | H52: 1768 | K52: 9.7666667 | L52: 21216 | M52: 5.304 | O52: 15.070667 | P52: 20
A53: Buildings::OfficerQuarter | B53: 9 | C53: 2502 | D53: =IF(INT(C53/3600/24)=0,"",INT(C53/3600/24)&"D")&IF(INT(MOD(C53,3600*24)/3600)=0,"",INT(MOD(C53,3600*24)/3600)&"H")&IF(INT(MOD(C53,3600)/60)=0,"",INT(MOD(C53,3600)/60)&"M")&INT(MOD(C53,60))&"S" -> 41M42S | E53: 4403 | F53: 15727 | G53: 7549 | H53: 2516 | K53: 13.9 | L53: 30195 | M53: 7.54875 | O53: 21.44875 | P53: 28
A54: Buildings::OfficerQuarter | B54: 10 | C54: 3561 | D54: =IF(INT(C54/3600/24)=0,"",INT(C54/3600/24)&"D")&IF(INT(MOD(C54,3600*24)/3600)=0,"",INT(MOD(C54,3600*24)/3600)&"H")&IF(INT(MOD(C54,3600)/60)=0,"",INT(MOD(C54,3600)/60)&"M")&INT(MOD(C54,60))&"S" -> 59M21S | E54: 6267 | F54: 22383 | G54: 10744 | H54: 3581 | K54: 19.783333 | L54: 42975 | M54: 10.74375 | O54: 30.527083 | P54: 35
A55: Buildings::OfficerQuarter | B55: 11 | C55: 5068 | D55: =IF(INT(C55/3600/24)=0,"",INT(C55/3600/24)&"D")&IF(INT(MOD(C55,3600*24)/3600)=0,"",INT(MOD(C55,3600*24)/3600)&"H")&IF(INT(MOD(C55,3600)/60)=0,"",INT(MOD(C55,3600)/60)&"M")&INT(MOD(C55,60))&"S" -> 1H24M28S | E55: 8919 | F55: 31856 | G55: 15291 | H55: 5097 | K55: 14.077778 | L55: 61163 | M55: 15.29075 | O55: 29.368528 | P55: 40
A56: Buildings::OfficerQuarter | B56: 12 | C56: 7212 | D56: =IF(INT(C56/3600/24)=0,"",INT(C56/3600/24)&"D")&IF(INT(MOD(C56,3600*24)/3600)=0,"",INT(MOD(C56,3600*24)/3600)&"H")&IF(INT(MOD(C56,3600)/60)=0,"",INT(MOD(C56,3600)/60)&"M")&INT(MOD(C56,60))&"S" -> 2H12S | E56: 12693 | F56: 45333 | G56: 21760 | H56: 7253 | K56: 20.033333 | L56: 87039 | M56: 21.75975 | O56: 41.793083 | P56: 55
... A63: Buildings::OfficerQuarter | B63: 19 | C63: 85233 | D63: =IF(INT(C63/3600/24)=0,"",INT(C63/3600/24)&"D")&IF(INT(MOD(C63,3600*24)/3600)=0,"",INT(MOD(C63,3600*24)/3600)&"H")&IF(INT(MOD(C63,3600)/60)=0,"",INT(MOD(C63,3600)/60)&"M")&INT(MOD(C63,60))&"S" -> 23H40M33S | E63: 150013 | F63: 535763 | G63: 257166 | H63: 85722 | K63: 102.59528 | L63: 1028664 | M63: 195.44616 | O63: 298.04144 | P63: 388
A64: Buildings::OfficerQuarter | B64: 20 | C64: 121291 | D64: =IF(INT(C64/3600/24)=0,"",INT(C64/3600/24)&"D")&IF(INT(MOD(C64,3600*24)/3600)=0,"",INT(MOD(C64,3600*24)/3600)&"H")&IF(INT(MOD(C64,3600)/60)=0,"",INT(MOD(C64,3600)/60)&"M")&INT(MOD(C64,60))&"S" -> 1D9H41M31S | E64: 213477 | F64: 762419 | G64: 365961 | H64: 121987 | J64: CompletionGrant | K64: 133.36395 | L64: 1463844 | M64: 278.13036 | N64: 40 | O64: 451.49431 | P64: 587
A65: Buildings::ScienceCenter | B65: 0 | D65: =IF(INT(C65/3600/24)=0,"",INT(C65/3600/24)&"D")&IF(INT(MOD(C65,3600*24)/3600)=0,"",INT(MOD(C65,3600*24)/3600)&"H")&IF(INT(MOD(C65,3600)/60)=0,"",INT(MOD(C65,3600)/60)&"M")&INT(MOD(C65,60))&"S" -> 0S | K65: 0 | L65: 0 | M65: 0 | O65: 0 | P65: 0
A66: Buildings::ScienceCenter | B66: 1 | C66: 0 | D66: =IF(INT(C66/3600/24)=0,"",INT(C66/3600/24)&"D")&IF(INT(MOD(C66,3600*24)/3600)=0,"",INT(MOD(C66,3600*24)/3600)&"H")&IF(INT(MOD(C66,3600)/60)=0,"",INT(MOD(C66,3600)/60)&"M")&INT(MOD(C66,60))&"S" -> 0S | K66: 0 | L66: 0 | M66: 0 | O66: 0 | P66: 0
A67: Buildings::ScienceCenter | B67: 2 | C67: 282 | D67: =IF(INT(C67/3600/24)=0,"",INT(C67/3600/24)&"D")&IF(INT(MOD(C67,3600*24)/3600)=0,"",INT(MOD(C67,3600*24)/3600)&"H")&IF(INT(MOD(C67,3600)/60)=0,"",INT(MOD(C67,3600)/60)&"M")&INT(MOD(C67,60))&"S" -> 4M42S | E67: 106 | F67: 1329 | G67: 797 | H67: 63 | K67: 4.7 | L67: 2295 | M67: 0.57375 | O67: 5.27375 | P67: 7
A68: Buildings::ScienceCenter | B68: 3 | C68: 402 | D68: =IF(INT(C68/3600/24)=0,"",INT(C68/3600/24)&"D")&IF(INT(MOD(C68,3600*24)/3600)=0,"",INT(MOD(C68,3600*24)/3600)&"H")&IF(INT(MOD(C68,3600)/60)=0,"",INT(MOD(C68,3600)/60)&"M")&INT(MOD(C68,60))&"S" -> 6M42S | E68: 151 | F68: 1895 | G68: 1137 | H68: 90 | K68: 4.02 | L68: 3273 | M68: 0.81825 | O68: 4.83825 | P68: 8
A69: Buildings::ScienceCenter | B69: 4 | C69: 572 | D69: =IF(INT(C69/3600/24)=0,"",INT(C69/3600/24)&"D")&IF(INT(MOD(C69,3600*24)/3600)=0,"",INT(MOD(C69,3600*24)/3600)&"H")&IF(INT(MOD(C69,3600)/60)=0,"",INT(MOD(C69,3600)/60)&"M")&INT(MOD(C69,60))&"S" -> 9M32S | E69: 215 | F69: 2696 | G69: 1617 | H69: 129 | K69: 5.72 | L69: 4657 | M69: 1.16425 | O69: 6.88425 | P69: 9
A70: Buildings::ScienceCenter | B70: 5 | C70: 814 | D70: =IF(INT(C70/3600/24)=0,"",INT(C70/3600/24)&"D")&IF(INT(MOD(C70,3600*24)/3600)=0,"",INT(MOD(C70,3600*24)/3600)&"H")&IF(INT(MOD(C70,3600)/60)=0,"",INT(MOD(C70,3600)/60)&"M")&INT(MOD(C70,60))&"S" -> 13M34S | E70: 307 | F70: 3837 | G70: 2302 | H70: 184 | K70: 8.14 | L70: 6630 | M70: 1.6575 | O70: 9.7975 | P70: 11
A71: Buildings::ScienceCenter | B71: 6 | C71: 1158 | D71: =IF(INT(C71/3600/24)=0,"",INT(C71/3600/24)&"D")&IF(INT(MOD(C71,3600*24)/3600)=0,"",INT(MOD(C71,3600*24)/3600)&"H")&IF(INT(MOD(C71,3600)/60)=0,"",INT(MOD(C71,3600)/60)&"M")&INT(MOD(C71,60))&"S" -> 19M18S | E71: 436 | F71: 5459 | G71: 3275 | H71: 262 | K71: 6.4333333 | L71: 9432 | M71: 2.358 | O71: 8.7913333 | P71: 13
A72: Buildings::ScienceCenter | B72: 7 | C72: 1649 | D72: =IF(INT(C72/3600/24)=0,"",INT(C72/3600/24)&"D")&IF(INT(MOD(C72,3600*24)/3600)=0,"",INT(MOD(C72,3600*24)/3600)&"H")&IF(INT(MOD(C72,3600)/60)=0,"",INT(MOD(C72,3600)/60)&"M")&INT(MOD(C72,60))&"S" -> 27M29S | E72: 621 | F72: 7774 | G72: 4664 | H72: 373 | K72: 9.1611111 | L72: 13432 | M72: 3.358 | O72: 12.519111 | P72: 17
A73: Buildings::ScienceCenter | B73: 8 | C73: 2347 | D73: =IF(INT(C73/3600/24)=0,"",INT(C73/3600/24)&"D")&IF(INT(MOD(C73,3600*24)/3600)=0,"",INT(MOD(C73,3600*24)/3600)&"H")&IF(INT(MOD(C73,3600)/60)=0,"",INT(MOD(C73,3600)/60)&"M")&INT(MOD(C73,60))&"S" -> 39M7S | E73: 885 | F73: 11064 | G73: 6638 | H73: 531 | K73: 13.038889 | L73: 19118 | M73: 4.7795 | O73: 17.818389 | P73: 24
A74: Buildings::ScienceCenter | B74: 9 | C74: 3339 | D74: =IF(INT(C74/3600/24)=0,"",INT(C74/3600/24)&"D")&IF(INT(MOD(C74,3600*24)/3600)=0,"",INT(MOD(C74,3600*24)/3600)&"H")&IF(INT(MOD(C74,3600)/60)=0,"",INT(MOD(C74,3600)/60)&"M")&INT(MOD(C74,60))&"S" -> 55M39S | E74: 1259 | F74: 15741 | G74: 9444 | H74: 755 | K74: 18.55 | L74: 27199 | M74: 6.79975 | O74: 25.34975 | P74: 30
A75: Buildings::ScienceCenter | B75: 10 | C75: 4752 | D75: =IF(INT(C75/3600/24)=0,"",INT(C75/3600/24)&"D")&IF(INT(MOD(C75,3600*24)/3600)=0,"",INT(MOD(C75,3600*24)/3600)&"H")&IF(INT(MOD(C75,3600)/60)=0,"",INT(MOD(C75,3600)/60)&"M")&INT(MOD(C75,60))&"S" -> 1H19M12S | E75: 1792 | F75: 22402 | G75: 13441 | H75: 1075 | K75: 13.2 | L75: 38710 | M75: 9.6775 | O75: 22.8775 | P75: 35
A76: Buildings::ScienceCenter | B76: 11 | C76: 6763 | D76: =IF(INT(C76/3600/24)=0,"",INT(C76/3600/24)&"D")&IF(INT(MOD(C76,3600*24)/3600)=0,"",INT(MOD(C76,3600*24)/3600)&"H")&IF(INT(MOD(C76,3600)/60)=0,"",INT(MOD(C76,3600)/60)&"M")&INT(MOD(C76,60))&"S" -> 1H52M43S | E76: 2550 | F76: 31883 | G76: 19130 | H76: 1530 | K76: 18.786111 | L76: 55093 | M76: 13.77325 | O76: 32.559361 | P76: 43
A77: Buildings::ScienceCenter | B77: 12 | C77: 9624 | D77: =IF(INT(C77/3600/24)=0,"",INT(C77/3600/24)&"D")&IF(INT(MOD(C77,3600*24)/3600)=0,"",INT(MOD(C77,3600*24)/3600)&"H")&IF(INT(MOD(C77,3600)/60)=0,"",INT(MOD(C77,3600)/60)&"M")&INT(MOD(C77,60))&"S" -> 2H40M24S | E77: 3629 | F77: 45371 | G77: 27222 | H77: 2177 | K77: 16.04 | L77: 78399 | M77: 19.59975 | O77: 35.63975 | P77: 47
A78: Buildings::ScienceCenter | B78: 13 | C78: 13696 | D78: =IF(INT(C78/3600/24)=0,"",INT(C78/3600/24)&"D")&IF(INT(MOD(C78,3600*24)/3600)=0,"",INT(MOD(C78,3600*24)/3600)&"H")&IF(INT(MOD(C78,3600)/60)=0,"",INT(MOD(C78,3600)/60)&"M")&INT(MOD(C78,60))&"S" -> 3H48M16S | E78: 5165 | F78: 64568 | G78: 38740 | H78: 3099 | K78: 22.826667 | L78: 111572 | M78: 27.893 | O78: 50.719667 | P78: 66
... A84: Buildings::ScienceCenter | B84: 19 | C84: 113742 | D84: =IF(INT(C84/3600/24)=0,"",INT(C84/3600/24)&"D")&IF(INT(MOD(C84,3600*24)/3600)=0,"",INT(MOD(C84,3600*24)/3600)&"H")&IF(INT(MOD(C84,3600)/60)=0,"",INT(MOD(C84,3600)/60)&"M")&INT(MOD(C84,60))&"S" -> 1D7H35M42S | E84: 42897 | F84: 536224 | G84: 321734 | H84: 25738 | K84: 125.06354 | L84: 926593 | M84: 176.05267 | O84: 301.11621 | P84: 392
A85: Buildings::ScienceCenter | B85: 20 | C85: 161861 | D85: =IF(INT(C85/3600/24)=0,"",INT(C85/3600/24)&"D")&IF(INT(MOD(C85,3600*24)/3600)=0,"",INT(MOD(C85,3600*24)/3600)&"H")&IF(INT(MOD(C85,3600)/60)=0,"",INT(MOD(C85,3600)/60)&"M")&INT(MOD(C85,60))&"S" -> 1D20H57M41S | E85: 61046 | F85: 763075 | G85: 457845 | H85: 36627 | J85: CompletionGrant | K85: 177.97216 | L85: 1318593 | M85: 250.53267 | N85: 40 | O85: 468.50483 | P85: 610
A86: Buildings::Factory | B86: 0 | D86: =IF(INT(C86/3600/24)=0,"",INT(C86/3600/24)&"D")&IF(INT(MOD(C86,3600*24)/3600)=0,"",INT(MOD(C86,3600*24)/3600)&"H")&IF(INT(MOD(C86,3600)/60)=0,"",INT(MOD(C86,3600)/60)&"M")&INT(MOD(C86,60))&"S" -> 0S | K86: 0 | L86: 0 | M86: 0 | O86: 0 | P86: 0
A87: Buildings::Factory | B87: 1 | C87: 223 | D87: =IF(INT(C87/3600/24)=0,"",INT(C87/3600/24)&"D")&IF(INT(MOD(C87,3600*24)/3600)=0,"",INT(MOD(C87,3600*24)/3600)&"H")&IF(INT(MOD(C87,3600)/60)=0,"",INT(MOD(C87,3600)/60)&"M")&INT(MOD(C87,60))&"S" -> 3M43S | E87: 560 | F87: 1408 | G87: 1180 | H87: 296 | K87: 3.7166667 | L87: 3444 | M87: 0.861 | O87: 4.5776667 | P87: 5
A88: Buildings::Factory | B88: 2 | C88: 317 | D88: =IF(INT(C88/3600/24)=0,"",INT(C88/3600/24)&"D")&IF(INT(MOD(C88,3600*24)/3600)=0,"",INT(MOD(C88,3600*24)/3600)&"H")&IF(INT(MOD(C88,3600)/60)=0,"",INT(MOD(C88,3600)/60)&"M")&INT(MOD(C88,60))&"S" -> 5M17S | E88: 797 | F88: 2003 | G88: 1678 | H88: 421 | K88: 3.17 | L88: 4899 | M88: 1.22475 | O88: 4.39475 | P88: 7
A89: Buildings::Factory | B89: 3 | C89: 452 | D89: =IF(INT(C89/3600/24)=0,"",INT(C89/3600/24)&"D")&IF(INT(MOD(C89,3600*24)/3600)=0,"",INT(MOD(C89,3600*24)/3600)&"H")&IF(INT(MOD(C89,3600)/60)=0,"",INT(MOD(C89,3600)/60)&"M")&INT(MOD(C89,60))&"S" -> 7M32S | E89: 1136 | F89: 2856 | G89: 2393 | H89: 601 | K89: 4.52 | L89: 6986 | M89: 1.7465 | O89: 6.2665 | P89: 9
A90: Buildings::Factory | B90: 4 | C90: 643 | D90: =IF(INT(C90/3600/24)=0,"",INT(C90/3600/24)&"D")&IF(INT(MOD(C90,3600*24)/3600)=0,"",INT(MOD(C90,3600*24)/3600)&"H")&IF(INT(MOD(C90,3600)/60)=0,"",INT(MOD(C90,3600)/60)&"M")&INT(MOD(C90,60))&"S" -> 10M43S | E90: 1616 | F90: 4063 | G90: 3405 | H90: 856 | K90: 6.43 | L90: 9940 | M90: 2.485 | O90: 8.915 | P90: 11
A91: Buildings::Factory | B91: 5 | C91: 916 | D91: =IF(INT(C91/3600/24)=0,"",INT(C91/3600/24)&"D")&IF(INT(MOD(C91,3600*24)/3600)=0,"",INT(MOD(C91,3600*24)/3600)&"H")&IF(INT(MOD(C91,3600)/60)=0,"",INT(MOD(C91,3600)/60)&"M")&INT(MOD(C91,60))&"S" -> 15M16S | E91: 2303 | F91: 5790 | G91: 4852 | H91: 1219 | K91: 5.0888889 | L91: 14164 | M91: 3.541 | O91: 8.6298889 | P91: 12
A92: Buildings::Factory | B92: 6 | C92: 1303 | D92: =IF(INT(C92/3600/24)=0,"",INT(C92/3600/24)&"D")&IF(INT(MOD(C92,3600*24)/3600)=0,"",INT(MOD(C92,3600*24)/3600)&"H")&IF(INT(MOD(C92,3600)/60)=0,"",INT(MOD(C92,3600)/60)&"M")&INT(MOD(C92,60))&"S" -> 21M43S | E92: 3276 | F92: 8236 | G92: 6902 | H92: 1735 | K92: 7.2388889 | L92: 20149 | M92: 5.03725 | O92: 12.276139 | P92: 16
A93: Buildings::Factory | B93: 7 | C93: 1855 | D93: =IF(INT(C93/3600/24)=0,"",INT(C93/3600/24)&"D")&IF(INT(MOD(C93,3600*24)/3600)=0,"",INT(MOD(C93,3600*24)/3600)&"H")&IF(INT(MOD(C93,3600)/60)=0,"",INT(MOD(C93,3600)/60)&"M")&INT(MOD(C93,60))&"S" -> 30M55S | E93: 4664 | F93: 11726 | G93: 9827 | H93: 2470 | K93: 10.305556 | L93: 28687 | M93: 7.17175 | O93: 17.477306 | P93: 23
A94: Buildings::Factory | B94: 8 | C94: 2640 | D94: =IF(INT(C94/3600/24)=0,"",INT(C94/3600/24)&"D")&IF(INT(MOD(C94,3600*24)/3600)=0,"",INT(MOD(C94,3600*24)/3600)&"H")&IF(INT(MOD(C94,3600)/60)=0,"",INT(MOD(C94,3600)/60)&"M")&INT(MOD(C94,60))&"S" -> 44M0S | E94: 6637 | F94: 16687 | G94: 13985 | H94: 3516 | K94: 14.666667 | L94: 40825 | M94: 10.20625 | O94: 24.872917 | P94: 32
A95: Buildings::Factory | B95: 9 | C95: 3757 | D95: =IF(INT(C95/3600/24)=0,"",INT(C95/3600/24)&"D")&IF(INT(MOD(C95,3600*24)/3600)=0,"",INT(MOD(C95,3600*24)/3600)&"H")&IF(INT(MOD(C95,3600)/60)=0,"",INT(MOD(C95,3600)/60)&"M")&INT(MOD(C95,60))&"S" -> 1H2M37S | E95: 9446 | F95: 23750 | G95: 19905 | H95: 5004 | K95: 10.436111 | L95: 58105 | M95: 14.52625 | O95: 24.962361 | P95: 34
A96: Buildings::Factory | B96: 10 | C96: 5347 | D96: =IF(INT(C96/3600/24)=0,"",INT(C96/3600/24)&"D")&IF(INT(MOD(C96,3600*24)/3600)=0,"",INT(MOD(C96,3600*24)/3600)&"H")&IF(INT(MOD(C96,3600)/60)=0,"",INT(MOD(C96,3600)/60)&"M")&INT(MOD(C96,60))&"S" -> 1H29M7S | E96: 13444 | F96: 33802 | G96: 28329 | H96: 7122 | K96: 14.852778 | L96: 82697 | M96: 20.67425 | O96: 35.527028 | P96: 47
A97: Buildings::Factory | B97: 11 | C97: 7609 | D97: =IF(INT(C97/3600/24)=0,"",INT(C97/3600/24)&"D")&IF(INT(MOD(C97,3600*24)/3600)=0,"",INT(MOD(C97,3600*24)/3600)&"H")&IF(INT(MOD(C97,3600)/60)=0,"",INT(MOD(C97,3600)/60)&"M")&INT(MOD(C97,60))&"S" -> 2H6M49S | E97: 19131 | F97: 48101 | G97: 40314 | H97: 10136 | K97: 21.136111 | L97: 117682 | M97: 29.4205 | O97: 50.556611 | P97: 66
A98: Buildings::Factory | B98: 12 | C98: 10828 | D98: =IF(INT(C98/3600/24)=0,"",INT(C98/3600/24)&"D")&IF(INT(MOD(C98,3600*24)/3600)=0,"",INT(MOD(C98,3600*24)/3600)&"H")&IF(INT(MOD(C98,3600)/60)=0,"",INT(MOD(C98,3600)/60)&"M")&INT(MOD(C98,60))&"S" -> 3H28S | E98: 27225 | F98: 68452 | G98: 57370 | H98: 14424 | K98: 18.046667 | L98: 167471 | M98: 41.86775 | O98: 59.914417 | P98: 78
... A105: Buildings::Factory | B105: 19 | C105: 127964 | D105: =IF(INT(C105/3600/24)=0,"",INT(C105/3600/24)&"D")&IF(INT(MOD(C105,3600*24)/3600)=0,"",INT(MOD(C105,3600*24)/3600)&"H")&IF(INT(MOD(C105,3600)/60)=0,"",INT(MOD(C105,3600)/60)&"M")&INT(MOD(C105,60))&"S" -> 1D11H32M44S | E105: 321744 | F105: 808972 | G105: 678009 | H105: 170474 | K105: 140.70116 | L105: 1979199 | M105: 376.04781 | O105: 516.74897 | P105: 672
A106: Buildings::Factory | B106: 20 | C106: 182099 | D106: =IF(INT(C106/3600/24)=0,"",INT(C106/3600/24)&"D")&IF(INT(MOD(C106,3600*24)/3600)=0,"",INT(MOD(C106,3600*24)/3600)&"H")&IF(INT(MOD(C106,3600)/60)=0,"",INT(MOD(C106,3600)/60)&"M")&INT(MOD(C106,60))&"S" -> 2D2H34M59S | E106: 457858 | F106: 1151209 | G106: 964842 | H106: 242593 | J106: CompletionGrant | K106: 200.22459 | L106: 2816502 | M106: 535.13538 | N106: 40 | O106: 775.35997 | P106: 1008
A107: Buildings::StorageVault | B107: 0 | D107: =IF(INT(C107/3600/24)=0,"",INT(C107/3600/24)&"D")&IF(INT(MOD(C107,3600*24)/3600)=0,"",INT(MOD(C107,3600*24)/3600)&"H")&IF(INT(MOD(C107,3600)/60)=0,"",INT(MOD(C107,3600)/60)&"M")&INT(MOD(C107,60))&"S" -> 0S | K107: 0 | L107: 0 | M107: 0 | O107: 0 | P107: 0
A108: Buildings::StorageVault | B108: 1 | C108: 248 | D108: =IF(INT(C108/3600/24)=0,"",INT(C108/3600/24)&"D")&IF(INT(MOD(C108,3600*24)/3600)=0,"",INT(MOD(C108,3600*24)/3600)&"H")&IF(INT(MOD(C108,3600)/60)=0,"",INT(MOD(C108,3600)/60)&"M")&INT(MOD(C108,60))&"S" -> 4M8S | E108: 112 | F108: 561 | G108: 374 | H108: 37 | K108: 4.1333333 | L108: 1084 | M108: 0.271 | O108: 4.4043333 | P108: 6
A109: Buildings::StorageVault | B109: 2 | C109: 353 | D109: =IF(INT(C109/3600/24)=0,"",INT(C109/3600/24)&"D")&IF(INT(MOD(C109,3600*24)/3600)=0,"",INT(MOD(C109,3600*24)/3600)&"H")&IF(INT(MOD(C109,3600)/60)=0,"",INT(MOD(C109,3600)/60)&"M")&INT(MOD(C109,60))&"S" -> 5M53S | E109: 159 | F109: 798 | G109: 532 | H109: 53 | K109: 3.53 | L109: 1542 | M109: 0.3855 | O109: 3.9155 | P109: 7
A110: Buildings::StorageVault | B110: 3 | C110: 502 | D110: =IF(INT(C110/3600/24)=0,"",INT(C110/3600/24)&"D")&IF(INT(MOD(C110,3600*24)/3600)=0,"",INT(MOD(C110,3600*24)/3600)&"H")&IF(INT(MOD(C110,3600)/60)=0,"",INT(MOD(C110,3600)/60)&"M")&INT(MOD(C110,60))&"S" -> 8M22S | E110: 227 | F110: 1135 | G110: 757 | H110: 75 | K110: 5.02 | L110: 2194 | M110: 0.5485 | O110: 5.5685 | P110: 8
A111: Buildings::StorageVault | B111: 4 | C111: 715 | D111: =IF(INT(C111/3600/24)=0,"",INT(C111/3600/24)&"D")&IF(INT(MOD(C111,3600*24)/3600)=0,"",INT(MOD(C111,3600*24)/3600)&"H")&IF(INT(MOD(C111,3600)/60)=0,"",INT(MOD(C111,3600)/60)&"M")&INT(MOD(C111,60))&"S" -> 11M55S | E111: 323 | F111: 1617 | G111: 1078 | H111: 107 | K111: 7.15 | L111: 3125 | M111: 0.78125 | O111: 7.93125 | P111: 9
A112: Buildings::StorageVault | B112: 5 | C112: 1018 | D112: =IF(INT(C112/3600/24)=0,"",INT(C112/3600/24)&"D")&IF(INT(MOD(C112,3600*24)/3600)=0,"",INT(MOD(C112,3600*24)/3600)&"H")&IF(INT(MOD(C112,3600)/60)=0,"",INT(MOD(C112,3600)/60)&"M")&INT(MOD(C112,60))&"S" -> 16M58S | E112: 460 | F112: 2303 | G112: 1535 | H112: 153 | K112: 5.6555556 | L112: 4451 | M112: 1.11275 | O112: 6.7683056 | P112: 10
A113: Buildings::StorageVault | B113: 6 | C113: 1448 | D113: =IF(INT(C113/3600/24)=0,"",INT(C113/3600/24)&"D")&IF(INT(MOD(C113,3600*24)/3600)=0,"",INT(MOD(C113,3600*24)/3600)&"H")&IF(INT(MOD(C113,3600)/60)=0,"",INT(MOD(C113,3600)/60)&"M")&INT(MOD(C113,60))&"S" -> 24M8S | E113: 655 | F113: 3276 | G113: 2184 | H113: 218 | K113: 8.0444444 | L113: 6333 | M113: 1.58325 | O113: 9.6276944 | P113: 13
A114: Buildings::StorageVault | B114: 7 | C114: 2061 | D114: =IF(INT(C114/3600/24)=0,"",INT(C114/3600/24)&"D")&IF(INT(MOD(C114,3600*24)/3600)=0,"",INT(MOD(C114,3600*24)/3600)&"H")&IF(INT(MOD(C114,3600)/60)=0,"",INT(MOD(C114,3600)/60)&"M")&INT(MOD(C114,60))&"S" -> 34M21S | E114: 932 | F114: 4663 | G114: 3109 | H114: 310 | K114: 11.45 | L114: 9014 | M114: 2.2535 | O114: 13.7035 | P114: 18
A115: Buildings::StorageVault | B115: 8 | C115: 2933 | D115: =IF(INT(C115/3600/24)=0,"",INT(C115/3600/24)&"D")&IF(INT(MOD(C115,3600*24)/3600)=0,"",INT(MOD(C115,3600*24)/3600)&"H")&IF(INT(MOD(C115,3600)/60)=0,"",INT(MOD(C115,3600)/60)&"M")&INT(MOD(C115,60))&"S" -> 48M53S | E115: 1327 | F115: 6637 | G115: 4424 | H115: 442 | K115: 16.294444 | L115: 12830 | M115: 3.2075 | O115: 19.501944 | P115: 22
A116: Buildings::StorageVault | B116: 9 | C116: 4175 | D116: =IF(INT(C116/3600/24)=0,"",INT(C116/3600/24)&"D")&IF(INT(MOD(C116,3600*24)/3600)=0,"",INT(MOD(C116,3600*24)/3600)&"H")&IF(INT(MOD(C116,3600)/60)=0,"",INT(MOD(C116,3600)/60)&"M")&INT(MOD(C116,60))&"S" -> 1H9M35S | E116: 1889 | F116: 9447 | G116: 6298 | H116: 629 | K116: 11.597222 | L116: 18263 | M116: 4.56575 | O116: 16.162972 | P116: 26
A117: Buildings::StorageVault | B117: 10 | C117: 5941 | D117: =IF(INT(C117/3600/24)=0,"",INT(C117/3600/24)&"D")&IF(INT(MOD(C117,3600*24)/3600)=0,"",INT(MOD(C117,3600*24)/3600)&"H")&IF(INT(MOD(C117,3600)/60)=0,"",INT(MOD(C117,3600)/60)&"M")&INT(MOD(C117,60))&"S" -> 1H39M1S | E117: 2688 | F117: 13443 | G117: 8962 | H117: 896 | K117: 16.502778 | L117: 25989 | M117: 6.49725 | O117: 23.000028 | P117: 30
A118: Buildings::StorageVault | B118: 11 | C118: 8454 | D118: =IF(INT(C118/3600/24)=0,"",INT(C118/3600/24)&"D")&IF(INT(MOD(C118,3600*24)/3600)=0,"",INT(MOD(C118,3600*24)/3600)&"H")&IF(INT(MOD(C118,3600)/60)=0,"",INT(MOD(C118,3600)/60)&"M")&INT(MOD(C118,60))&"S" -> 2H20M54S | E118: 3826 | F118: 19130 | G118: 12753 | H118: 1275 | K118: 23.483333 | L118: 36984 | M118: 9.246 | O118: 32.729333 | P118: 43
A119: Buildings::StorageVault | B119: 12 | C119: 12031 | D119: =IF(INT(C119/3600/24)=0,"",INT(C119/3600/24)&"D")&IF(INT(MOD(C119,3600*24)/3600)=0,"",INT(MOD(C119,3600*24)/3600)&"H")&IF(INT(MOD(C119,3600)/60)=0,"",INT(MOD(C119,3600)/60)&"M")&INT(MOD(C119,60))&"S" -> 3H20M31S | E119: 5444 | F119: 27224 | G119: 18149 | H119: 1814 | K119: 20.051667 | L119: 52631 | M119: 13.15775 | O119: 33.209417 | P119: 44
... A126: Buildings::StorageVault | B126: 19 | C126: 142186 | D126: =IF(INT(C126/3600/24)=0,"",INT(C126/3600/24)&"D")&IF(INT(MOD(C126,3600*24)/3600)=0,"",INT(MOD(C126,3600*24)/3600)&"H")&IF(INT(MOD(C126,3600)/60)=0,"",INT(MOD(C126,3600)/60)&"M")&INT(MOD(C126,60))&"S" -> 1D15H29M46S | E126: 64350 | F126: 321752 | G126: 214501 | H126: 21450 | K126: 156.33877 | L126: 622053 | M126: 118.19007 | O126: 274.52884 | P126: 357
A127: Buildings::StorageVault | B127: 20 | C127: 202338 | D127: =IF(INT(C127/3600/24)=0,"",INT(C127/3600/24)&"D")&IF(INT(MOD(C127,3600*24)/3600)=0,"",INT(MOD(C127,3600*24)/3600)&"H")&IF(INT(MOD(C127,3600)/60)=0,"",INT(MOD(C127,3600)/60)&"M")&INT(MOD(C127,60))&"S" -> 2D8H12M18S | E127: 91574 | F127: 457870 | G127: 305247 | H127: 30524 | J127: CompletionGrant | K127: 222.47813 | L127: 885215 | M127: 168.19085 | N127: 40 | O127: 430.66898 | P127: 560
A128: Buildings::Fortress | B128: 0 | D128: =IF(INT(C128/3600/24)=0,"",INT(C128/3600/24)&"D")&IF(INT(MOD(C128,3600*24)/3600)=0,"",INT(MOD(C128,3600*24)/3600)&"H")&IF(INT(MOD(C128,3600)/60)=0,"",INT(MOD(C128,3600)/60)&"M")&INT(MOD(C128,60))&"S" -> 0S | K128: 0 | L128: 0 | M128: 0 | O128: 0 | P128: 0
...

Sheet 科技消耗
A1: research type | B1: lv | C1: instance | D1: time | E1: ore | F1: wood | G1: food | H1: stone | I1: gold | J1: total | O1: item | P1: quantity | Q1: price | R1: 单价 | T1: ScienceCenter | U1: home | V1: wall | W1: Farm | X1: Lumbermill | Y1: Quarry | Z1: mine | AA1: Garrison | AB1: Metalsmith | AC1: Mining | AD1: Woodcraft | AE1: Rookery | AF1: Factory | AG1: Sentinel | AH1: Levitation | AI1: DragonKeep | AJ1: Dragonry
A2: Agriculture | B2: 1 | C2: 5 | D2: 30 | E2: 100 | G2: 500 | I2: 1000 | J2: =SUM(I2:I2) -> 1000 | K2: =IF(J2>$P$14,$R$15,IF(J2>$P$13,$R$14,$R$13))*J2 -> 0.25 | L2: =IF(D2>$P$10,$R$11,IF(D2>$P$9,$R$10,IF(D2>$P$8,$R$9,IF(D2>$P$7,$R$8,IF(D2>$P$6,$R$7,IF(D2>$P$5,$R$6,IF(D2>$P$4,$R$5,IF(D2>$P$3,$R$4,IF(D2>$P$2,$R$3,$R$2))))))))) -> 0.016666667 | M2: =D2*L2 -> 0.5 | N2: =K2+M2 -> 0.75 | O2: 1m | P2: 60 | Q2: 1 | R2: =Q2/P2 -> 0.016666667 | T2: 1 | W2: 1
B3: 2 | C3: 8 | D3: 876 | E3: 200 | G3: 1000 | I3: 2000 | J3: =SUM(I3:I3) -> 2000 | K3: =IF(J3>$P$14,$R$15,IF(J3>$P$13,$R$14,$R$13))*J3 -> 0.5 | L3: =IF(D3>$P$10,$R$11,IF(D3>$P$9,$R$10,IF(D3>$P$8,$R$9,IF(D3>$P$7,$R$8,IF(D3>$P$6,$R$7,IF(D3>$P$5,$R$6,IF(D3>$P$4,$R$5,IF(D3>$P$3,$R$4,IF(D3>$P$2,$R$3,$R$2))))))))) -> 0.0055555556 | M3: =D3*L3 -> 4.8666667 | N3: =K3+M3 -> 5.3666667 | O3: 5m | P3: 300 | Q3: 3 | R3: =Q3/P3 -> 0.01 | T3: 4 | W3: 2
B4: 3 | C4: 14 | D4: 1775 | E4: 400 | G4: 2000 | I4: 4000 | J4: =SUM(I4:I4) -> 4000 | K4: =IF(J4>$P$14,$R$15,IF(J4>$P$13,$R$14,$R$13))*J4 -> 1 | L4: =IF(D4>$P$10,$R$11,IF(D4>$P$9,$R$10,IF(D4>$P$8,$R$9,IF(D4>$P$7,$R$8,IF(D4>$P$6,$R$7,IF(D4>$P$5,$R$6,IF(D4>$P$4,$R$5,IF(D4>$P$3,$R$4,IF(D4>$P$2,$R$3,$R$2))))))))) -> 0.0027777778 | M4: =D4*L4 -> 4.9305556 | N4: =K4+M4 -> 5.9305556 | O4: 15m | P4: =15*60 -> 900 | Q4: 5 | R4: =Q4/P4 -> 0.0055555556 | T4: 6 | W4: 3
B5: 4 | C5: 22 | D5: 3595 | E5: 800 | G5: 4000 | I5: 8000 | J5: =SUM(I5:I5) -> 8000 | K5: =IF(J5>$P$14,$R$15,IF(J5>$P$13,$R$14,$R$13))*J5 -> 2 | L5: =IF(D5>$P$10,$R$11,IF(D5>$P$9,$R$10,IF(D5>$P$8,$R$9,IF(D5>$P$7,$R$8,IF(D5>$P$6,$R$7,IF(D5>$P$5,$R$6,IF(D5>$P$4,$R$5,IF(D5>$P$3,$R$4,IF(D5>$P$2,$R$3,$R$2))))))))) -> 0.0027777778 | M5: =D5*L5 -> 9.9861111 | N5: =K5+M5 -> 11.986111 | O5: 1h | P5: =3600 -> 3600 | Q5: 10 | R5: =Q5/P5 -> 0.0027777778 | T5: 8 | W5: 4
B6: 5 | C6: 34 | D6: 7280 | E6: 1600 | G6: 8000 | I6: 16000 | J6: =SUM(I6:I6) -> 16000 | K6: =IF(J6>$P$14,$R$15,IF(J6>$P$13,$R$14,$R$13))*J6 -> 4 | L6: =IF(D6>$P$10,$R$11,IF(D6>$P$9,$R$10,IF(D6>$P$8,$R$9,IF(D6>$P$7,$R$8,IF(D6>$P$6,$R$7,IF(D6>$P$5,$R$6,IF(D6>$P$4,$R$5,IF(D6>$P$3,$R$4,IF(D6>$P$2,$R$3,$R$2))))))))) -> 0.0016666667 | M6: =D6*L6 -> 12.133333 | N6: =K6+M6 -> 16.133333 | O6: 2.5h | P6: =2.5*3600 -> 9000 | Q6: 15 | R6: =Q6/P6 -> 0.0016666667 | T6: 10 | W6: 5
B7: 6 | C7: 51 | D7: 14743 | E7: 3200 | G7: 16000 | I7: 32000 | J7: =SUM(I7:I7) -> 32000 | K7: =IF(J7>$P$14,$R$15,IF(J7>$P$13,$R$14,$R$13))*J7 -> 8 | L7: =IF(D7>$P$10,$R$11,IF(D7>$P$9,$R$10,IF(D7>$P$8,$R$9,IF(D7>$P$7,$R$8,IF(D7>$P$6,$R$7,IF(D7>$P$5,$R$6,IF(D7>$P$4,$R$5,IF(D7>$P$3,$R$4,IF(D7>$P$2,$R$3,$R$2))))))))) -> 0.0013888889 | M7: =D7*L7 -> 20.476389 | N7: =K7+M7 -> 28.476389 | O7: 8h | P7: =8*3600 -> 28800 | Q7: 40 | R7: =Q7/P7 -> 0.0013888889 | T7: 12 | W7: 6
B8: 7 | C8: 79 | D8: 29856 | E8: 6400 | G8: 32000 | I8: 64000 | J8: =SUM(I8:I8) -> 64000 | K8: =IF(J8>$P$14,$R$15,IF(J8>$P$13,$R$14,$R$13))*J8 -> 16 | L8: =IF(D8>$P$10,$R$11,IF(D8>$P$9,$R$10,IF(D8>$P$8,$R$9,IF(D8>$P$7,$R$8,IF(D8>$P$6,$R$7,IF(D8>$P$5,$R$6,IF(D8>$P$4,$R$5,IF(D8>$P$3,$R$4,IF(D8>$P$2,$R$3,$R$2))))))))) -> 0.0012037037 | M8: =D8*L8 -> 35.937778 | N8: =K8+M8 -> 51.937778 | O8: 15hr | P8: =15*3600 -> 54000 | Q8: 65 | R8: =Q8/P8 -> 0.0012037037 | T8: 14 | W8: 7
B9: 8 | C9: 143 | D9: 60459 | E9: 12800 | G9: 64000 | I9: 128000 | J9: =SUM(I9:I9) -> 128000 | K9: =IF(J9>$P$14,$R$15,IF(J9>$P$13,$R$14,$R$13))*J9 -> 28.16 | L9: =IF(D9>$P$10,$R$11,IF(D9>$P$9,$R$10,IF(D9>$P$8,$R$9,IF(D9>$P$7,$R$8,IF(D9>$P$6,$R$7,IF(D9>$P$5,$R$6,IF(D9>$P$4,$R$5,IF(D9>$P$3,$R$4,IF(D9>$P$2,$R$3,$R$2))))))))) -> 0.001099537 | M9: =D9*L9 -> 66.47691 | N9: =K9+M9 -> 94.63691 | O9: 24h | P9: =24*3600 -> 86400 | Q9: 95 | R9: =Q9/P9 -> 0.001099537 | T9: 16 | W9: 8
B10: 9 | C10: 286 | D10: 122430 | E10: 25600 | G10: 128000 | I10: 256000 | J10: =SUM(I10:I10) -> 256000 | K10: =IF(J10>$P$14,$R$15,IF(J10>$P$13,$R$14,$R$13))*J10 -> 48.64 | L10: =IF(D10>$P$10,$R$11,IF(D10>$P$9,$R$10,IF(D10>$P$8,$R$9,IF(D10>$P$7,$R$8,IF(D10>$P$6,$R$7,IF(D10>$P$5,$R$6,IF(D10>$P$4,$R$5,IF(D10>$P$3,$R$4,IF(D10>$P$2,$R$3,$R$2))))))))) -> 0.00097222222 | M10: =D10*L10 -> 119.02917 | N10: =K10+M10 -> 167.66917 | O10: 2.5d | P10: =2.5*24*3600 -> 216000 | Q10: 210 | R10: =Q10/P10 -> 0.00097222222 | T10: 18 | W10: 9
B11: 10 | C11: 497 | D11: 247920 | E11: 51200 | G11: 256000 | I11: 512000 | J11: =SUM(I11:I11) -> 512000 | K11: =IF(J11>$P$14,$R$15,IF(J11>$P$13,$R$14,$R$13))*J11 -> 97.28 | L11: =IF(D11>$P$10,$R$11,IF(D11>$P$9,$R$10,IF(D11>$P$8,$R$9,IF(D11>$P$7,$R$8,IF(D11>$P$6,$R$7,IF(D11>$P$5,$R$6,IF(D11>$P$4,$R$5,IF(D11>$P$3,$R$4,IF(D11>$P$2,$R$3,$R$2))))))))) -> 0.00079571759 | M11: =D11*L11 -> 197.27431 | N11: =K11+M11 -> 294.55431 | O11: 4d | P11: =4*24*3600 -> 345600 | Q11: 275 | R11: =Q11/P11 -> 0.00079571759 | T11: 20 | W11: 10
B12: total | C12: =SUM(C2:C11) -> 1139 | D12: =SUM(D2:D11) -> 488964 | E12: =SUM(E2:E11) -> 102300 | F12: =SUM(F2:F11) -> 0 | G12: =SUM(G2:G11) -> 511500 | H12: =SUM(H2:H11) -> 0 | I12: =SUM(I2:I11) -> 1023000 | J12: =SUM(I12:I12) -> 1023000 | K12: =IF(J12>$P$14,$R$15,IF(J12>$P$13,$R$14,$R$13))*J12 -> 194.37 | L12: =IF(D12>$P$10,$R$11,IF(D12>$P$9,$R$10,IF(D12>$P$8,$R$9,IF(D12>$P$7,$R$8,IF(D12>$P$6,$R$7,IF(D12>$P$5,$R$6,IF(D12>$P$4,$R$5,IF(D12>$P$3,$R$4,IF(D12>$P$2,$R$3,$R$2))))))))) -> 0.00079571759 | M12: =D12*L12 -> 389.07726 | N12: =K12+M12 -> 583.44726
A13: Woodcraft | B13: 1 | C13: 6 | D13: 491 | E13: 100 | G13: 500 | I13: 1200 | J13: =SUM(I13:I13) -> 1200 | K13: =IF(J13>$P$14,$R$15,IF(J13>$P$13,$R$14,$R$13))*J13 -> 0.3 | L13: =IF(D13>$P$10,$R$11,IF(D13>$P$9,$R$10,IF(D13>$P$8,$R$9,IF(D13>$P$7,$R$8,IF(D13>$P$6,$R$7,IF(D13>$P$5,$R$6,IF(D13>$P$4,$R$5,IF(D13>$P$3,$R$4,IF(D13>$P$2,$R$3,$R$2))))))))) -> 0.0055555556 | M13: =D13*L13 -> 2.7277778 | N13: =K13+M13 -> 3.0277778 | O13: resource | P13: 80000 | Q13: 20 | R13: =Q13/P13 -> 0.00025 | T13: 2 | X13: 1
B14: 2 | C14: 9 | D14: 994 | E14: 200 | G14: 1000 | I14: 2400 | J14: =SUM(I14:I14) -> 2400 | K14: =IF(J14>$P$14,$R$15,IF(J14>$P$13,$R$14,$R$13))*J14 -> 0.6 | L14: =IF(D14>$P$10,$R$11,IF(D14>$P$9,$R$10,IF(D14>$P$8,$R$9,IF(D14>$P$7,$R$8,IF(D14>$P$6,$R$7,IF(D14>$P$5,$R$6,IF(D14>$P$4,$R$5,IF(D14>$P$3,$R$4,IF(D14>$P$2,$R$3,$R$2))))))))) -> 0.0027777778 | M14: =D14*L14 -> 2.7611111 | N14: =K14+M14 -> 3.3611111 | P14: 250000 | Q14: 55 | R14: =Q14/P14 -> 0.00022 | T14: 4 | X14: 2
B15: 3 | C15: 14 | D15: 2013 | E15: 400 | G15: 2000 | I15: 4800 | J15: =SUM(I15:I15) -> 4800 | K15: =IF(J15>$P$14,$R$15,IF(J15>$P$13,$R$14,$R$13))*J15 -> 1.2 | L15: =IF(D15>$P$10,$R$11,IF(D15>$P$9,$R$10,IF(D15>$P$8,$R$9,IF(D15>$P$7,$R$8,IF(D15>$P$6,$R$7,IF(D15>$P$5,$R$6,IF(D15>$P$4,$R$5,IF(D15>$P$3,$R$4,IF(D15>$P$2,$R$3,$R$2))))))))) -> 0.0027777778 | M15: =D15*L15 -> 5.5916667 | N15: =K15+M15 -> 6.7916667 | P15: 500000 | Q15: 95 | R15: =Q15/P15 -> 0.00019 | T15: 6 | X15: 3
B16: 4 | C16: 19 | D16: 4077 | E16: 800 | G16: 4000 | I16: 9600 | J16: =SUM(I16:I16) -> 9600 | K16: =IF(J16>$P$14,$R$15,IF(J16>$P$13,$R$14,$R$13))*J16 -> 2.4 | L16: =IF(D16>$P$10,$R$11,IF(D16>$P$9,$R$10,IF(D16>$P$8,$R$9,IF(D16>$P$7,$R$8,IF(D16>$P$6,$R$7,IF(D16>$P$5,$R$6,IF(D16>$P$4,$R$5,IF(D16>$P$3,$R$4,IF(D16>$P$2,$R$3,$R$2))))))))) -> 0.0016666667 | M16: =D16*L16 -> 6.795 | N16: =K16+M16 -> 9.195 | T16: 8 | X16: 4
B17: 5 | C17: 29 | D17: 8256 | E17: 1600 | G17: 8000 | I17: 19200 | J17: =SUM(I17:I17) -> 19200 | K17: =IF(J17>$P$14,$R$15,IF(J17>$P$13,$R$14,$R$13))*J17 -> 4.8 | L17: =IF(D17>$P$10,$R$11,IF(D17>$P$9,$R$10,IF(D17>$P$8,$R$9,IF(D17>$P$7,$R$8,IF(D17>$P$6,$R$7,IF(D17>$P$5,$R$6,IF(D17>$P$4,$R$5,IF(D17>$P$3,$R$4,IF(D17>$P$2,$R$3,$R$2))))))))) -> 0.0016666667 | M17: =D17*L17 -> 13.76 | N17: =K17+M17 -> 18.56 | T17: 10 | X17: 5
B18: 6 | C18: 56 | D18: 16718 | E18: 3200 | G18: 16000 | I18: 38400 | J18: =SUM(I18:I18) -> 38400 | K18: =IF(J18>$P$14,$R$15,IF(J18>$P$13,$R$14,$R$13))*J18 -> 9.6 | L18: =IF(D18>$P$10,$R$11,IF(D18>$P$9,$R$10,IF(D18>$P$8,$R$9,IF(D18>$P$7,$R$8,IF(D18>$P$6,$R$7,IF(D18>$P$5,$R$6,IF(D18>$P$4,$R$5,IF(D18>$P$3,$R$4,IF(D18>$P$2,$R$3,$R$2))))))))) -> 0.0013888889 | M18: =D18*L18 -> 23.219444 | N18: =K18+M18 -> 32.819444 | T18: 12 | X18: 6
B19: 7 | C19: 96 | D19: 33855 | E19: 6400 | G19: 32000 | I19: 76800 | J19: =SUM(I19:I19) -> 76800 | K19: =IF(J19>$P$14,$R$15,IF(J19>$P$13,$R$14,$R$13))*J19 -> 19.2 | L19: =IF(D19>$P$10,$R$11,IF(D19>$P$9,$R$10,IF(D19>$P$8,$R$9,IF(D19>$P$7,$R$8,IF(D19>$P$6,$R$7,IF(D19>$P$5,$R$6,IF(D19>$P$4,$R$5,IF(D19>$P$3,$R$4,IF(D19>$P$2,$R$3,$R$2))))))))) -> 0.0012037037 | M19: =D19*L19 -> 40.751389 | N19: =K19+M19 -> 59.951389 | T19: 14 | X19: 7
B20: 8 | C20: 167 | D20: 68557 | E20: 12800 | G20: 64000 | I20: 153600 | J20: =SUM(I20:I20) -> 153600 | K20: =IF(J20>$P$14,$R$15,IF(J20>$P$13,$R$14,$R$13))*J20 -> 33.792 | L20: =IF(D20>$P$10,$R$11,IF(D20>$P$9,$R$10,IF(D20>$P$8,$R$9,IF(D20>$P$7,$R$8,IF(D20>$P$6,$R$7,IF(D20>$P$5,$R$6,IF(D20>$P$4,$R$5,IF(D20>$P$3,$R$4,IF(D20>$P$2,$R$3,$R$2))))))))) -> 0.001099537 | M20: =D20*L20 -> 75.380961 | N20: =K20+M20 -> 109.17296 | T20: 16 | X20: 8
B21: 9 | C21: 297 | D21: 138829 | E21: 25600 | G21: 128000 | I21: 307200 | J21: =SUM(I21:I21) -> 307200 | K21: =IF(J21>$P$14,$R$15,IF(J21>$P$13,$R$14,$R$13))*J21 -> 58.368 | L21: =IF(D21>$P$10,$R$11,IF(D21>$P$9,$R$10,IF(D21>$P$8,$R$9,IF(D21>$P$7,$R$8,IF(D21>$P$6,$R$7,IF(D21>$P$5,$R$6,IF(D21>$P$4,$R$5,IF(D21>$P$3,$R$4,IF(D21>$P$2,$R$3,$R$2))))))))) -> 0.00097222222 | M21: =D21*L21 -> 134.97264 | N21: =K21+M21 -> 193.34064 | T21: 18 | X21: 9
B22: 10 | C22: 524 | D22: 281129 | E22: 51200 | G22: 256000 | I22: 614400 | J22: =SUM(I22:I22) -> 614400 | K22: =IF(J22>$P$14,$R$15,IF(J22>$P$13,$R$14,$R$13))*J22 -> 116.736 | L22: =IF(D22>$P$10,$R$11,IF(D22>$P$9,$R$10,IF(D22>$P$8,$R$9,IF(D22>$P$7,$R$8,IF(D22>$P$6,$R$7,IF(D22>$P$5,$R$6,IF(D22>$P$4,$R$5,IF(D22>$P$3,$R$4,IF(D22>$P$2,$R$3,$R$2))))))))) -> 0.00079571759 | M22: =D22*L22 -> 223.69929 | N22: =K22+M22 -> 340.43529 | T22: 20 | X22: 10
B23: total | C23: =SUM(C13:C22) -> 1217 | D23: =SUM(D13:D22) -> 554919 | E23: =SUM(E13:E22) -> 102300 | F23: =SUM(F13:F22) -> 0 | G23: =SUM(G13:G22) -> 511500 | H23: =SUM(H13:H22) -> 0 | I23: =SUM(I13:I22) -> 1227600 | J23: =SUM(I23:I23) -> 1227600 | K23: =IF(J23>$P$14,$R$15,IF(J23>$P$13,$R$14,$R$13))*J23 -> 233.244 | L23: =IF(D23>$P$10,$R$11,IF(D23>$P$9,$R$10,IF(D23>$P$8,$R$9,IF(D23>$P$7,$R$8,IF(D23>$P$6,$R$7,IF(D23>$P$5,$R$6,IF(D23>$P$4,$R$5,IF(D23>$P$3,$R$4,IF(D23>$P$2,$R$3,$R$2))))))))) -> 0.00079571759 | M23: =D23*L23 -> 441.55881 | N23: =K23+M23 -> 674.80281
A24: Masonry | B24: 1 | C24: 6 | D24: 529 | E24: 200 | H24: 500 | I24: 1500 | J24: =SUM(I24:I24) -> 1500 | K24: =IF(J24>$P$14,$R$15,IF(J24>$P$13,$R$14,$R$13))*J24 -> 0.375 | L24: =IF(D24>$P$10,$R$11,IF(D24>$P$9,$R$10,IF(D24>$P$8,$R$9,IF(D24>$P$7,$R$8,IF(D24>$P$6,$R$7,IF(D24>$P$5,$R$6,IF(D24>$P$4,$R$5,IF(D24>$P$3,$R$4,IF(D24>$P$2,$R$3,$R$2))))))))) -> 0.0055555556 | M24: =D24*L24 -> 2.9388889 | N24: =K24+M24 -> 3.3138889 | T24: 2 | Y24: 1
B25: 2 | C25: 8 | D25: 1071 | E25: =E24*2 -> 400 | H25: =H24*2 -> 1000 | I25: =I24*2 -> 3000 | J25: =SUM(I25:I25) -> 3000 | K25: =IF(J25>$P$14,$R$15,IF(J25>$P$13,$R$14,$R$13))*J25 -> 0.75 | L25: =IF(D25>$P$10,$R$11,IF(D25>$P$9,$R$10,IF(D25>$P$8,$R$9,IF(D25>$P$7,$R$8,IF(D25>$P$6,$R$7,IF(D25>$P$5,$R$6,IF(D25>$P$4,$R$5,IF(D25>$P$3,$R$4,IF(D25>$P$2,$R$3,$R$2))))))))) -> 0.0027777778 | M25: =D25*L25 -> 2.975 | N25: =K25+M25 -> 3.725 | T25: 4 | Y25: 2
B26: 3 | C26: 12 | D26: 2169 | E26: =E25*2 -> 800 | H26: =H25*2 -> 2000 | I26: =I25*2 -> 6000 | J26: =SUM(I26:I26) -> 6000 | K26: =IF(J26>$P$14,$R$15,IF(J26>$P$13,$R$14,$R$13))*J26 -> 1.5 | L26: =IF(D26>$P$10,$R$11,IF(D26>$P$9,$R$10,IF(D26>$P$8,$R$9,IF(D26>$P$7,$R$8,IF(D26>$P$6,$R$7,IF(D26>$P$5,$R$6,IF(D26>$P$4,$R$5,IF(D26>$P$3,$R$4,IF(D26>$P$2,$R$3,$R$2))))))))) -> 0.0027777778 | M26: =D26*L26 -> 6.025 | N26: =K26+M26 -> 7.525 | T26: 6 | Y26: 3
B27: 4 | C27: 17 | D27: 4392 | E27: =E26*2 -> 1600 | H27: =H26*2 -> 4000 | I27: =I26*2 -> 12000 | J27: =SUM(I27:I27) -> 12000 | K27: =IF(J27>$P$14,$R$15,IF(J27>$P$13,$R$14,$R$13))*J27 -> 3 | L27: =IF(D27>$P$10,$R$11,IF(D27>$P$9,$R$10,IF(D27>$P$8,$R$9,IF(D27>$P$7,$R$8,IF(D27>$P$6,$R$7,IF(D27>$P$5,$R$6,IF(D27>$P$4,$R$5,IF(D27>$P$3,$R$4,IF(D27>$P$2,$R$3,$R$2))))))))) -> 0.0016666667 | M27: =D27*L27 -> 7.32 | N27: =K27+M27 -> 10.32 | T27: 8 | Y27: 4
B28: 5 | C28: 28 | D28: 8895 | E28: =E27*2 -> 3200 | H28: =H27*2 -> 8000 | I28: =I27*2 -> 24000 | J28: =SUM(I28:I28) -> 24000 | K28: =IF(J28>$P$14,$R$15,IF(J28>$P$13,$R$14,$R$13))*J28 -> 6 | L28: =IF(D28>$P$10,$R$11,IF(D28>$P$9,$R$10,IF(D28>$P$8,$R$9,IF(D28>$P$7,$R$8,IF(D28>$P$6,$R$7,IF(D28>$P$5,$R$6,IF(D28>$P$4,$R$5,IF(D28>$P$3,$R$4,IF(D28>$P$2,$R$3,$R$2))))))))) -> 0.0016666667 | M28: =D28*L28 -> 14.825 | N28: =K28+M28 -> 20.825 | T28: 10 | Y28: 5
B29: 6 | C29: 52 | D29: 18012 | E29: =E28*2 -> 6400 | H29: =H28*2 -> 16000 | I29: =I28*2 -> 48000 | J29: =SUM(I29:I29) -> 48000 | K29: =IF(J29>$P$14,$R$15,IF(J29>$P$13,$R$14,$R$13))*J29 -> 12 | L29: =IF(D29>$P$10,$R$11,IF(D29>$P$9,$R$10,IF(D29>$P$8,$R$9,IF(D29>$P$7,$R$8,IF(D29>$P$6,$R$7,IF(D29>$P$5,$R$6,IF(D29>$P$4,$R$5,IF(D29>$P$3,$R$4,IF(D29>$P$2,$R$3,$R$2))))))))) -> 0.0013888889 | M29: =D29*L29 -> 25.016667 | N29: =K29+M29 -> 37.016667 | T29: 12 | Y29: 6
B30: 7 | C30: 99 | D30: 36475 | E30: =E29*2 -> 12800 | H30: =H29*2 -> 32000 | I30: =I29*2 -> 96000 | J30: =SUM(I30:I30) -> 96000 | K30: =IF(J30>$P$14,$R$15,IF(J30>$P$13,$R$14,$R$13))*J30 -> 21.12 | L30: =IF(D30>$P$10,$R$11,IF(D30>$P$9,$R$10,IF(D30>$P$8,$R$9,IF(D30>$P$7,$R$8,IF(D30>$P$6,$R$7,IF(D30>$P$5,$R$6,IF(D30>$P$4,$R$5,IF(D30>$P$3,$R$4,IF(D30>$P$2,$R$3,$R$2))))))))) -> 0.0012037037 | M30: =D30*L30 -> 43.905093 | N30: =K30+M30 -> 65.025093 | T30: 14 | Y30: 7
B31: 8 | C31: 167 | D31: 73863 | E31: =E30*2 -> 25600 | H31: =H30*2 -> 64000 | I31: =I30*2 -> 192000 | J31: =SUM(I31:I31) -> 192000 | K31: =IF(J31>$P$14,$R$15,IF(J31>$P$13,$R$14,$R$13))*J31 -> 42.24 | L31: =IF(D31>$P$10,$R$11,IF(D31>$P$9,$R$10,IF(D31>$P$8,$R$9,IF(D31>$P$7,$R$8,IF(D31>$P$6,$R$7,IF(D31>$P$5,$R$6,IF(D31>$P$4,$R$5,IF(D31>$P$3,$R$4,IF(D31>$P$2,$R$3,$R$2))))))))) -> 0.001099537 | M31: =D31*L31 -> 81.215104 | N31: =K31+M31 -> 123.4551 | T31: 16 | Y31: 8
B32: 9 | C32: 293 | D32: 149573 | E32: =E31*2 -> 51200 | H32: =H31*2 -> 128000 | I32: =I31*2 -> 384000 | J32: =SUM(I32:I32) -> 384000 | K32: =IF(J32>$P$14,$R$15,IF(J32>$P$13,$R$14,$R$13))*J32 -> 72.96 | L32: =IF(D32>$P$10,$R$11,IF(D32>$P$9,$R$10,IF(D32>$P$8,$R$9,IF(D32>$P$7,$R$8,IF(D32>$P$6,$R$7,IF(D32>$P$5,$R$6,IF(D32>$P$4,$R$5,IF(D32>$P$3,$R$4,IF(D32>$P$2,$R$3,$R$2))))))))) -> 0.00097222222 | M32: =D32*L32 -> 145.41819 | N32: =K32+M32 -> 218.37819 | T32: 18 | Y32: 9
B33: 10 | C33: 610 | D33: 302887 | E33: =E32*2 -> 102400 | H33: =H32*2 -> 256000 | I33: =I32*2 -> 768000 | J33: =SUM(I33:I33) -> 768000 | K33: =IF(J33>$P$14,$R$15,IF(J33>$P$13,$R$14,$R$13))*J33 -> 145.92 | L33: =IF(D33>$P$10,$R$11,IF(D33>$P$9,$R$10,IF(D33>$P$8,$R$9,IF(D33>$P$7,$R$8,IF(D33>$P$6,$R$7,IF(D33>$P$5,$R$6,IF(D33>$P$4,$R$5,IF(D33>$P$3,$R$4,IF(D33>$P$2,$R$3,$R$2))))))))) -> 0.00079571759 | M33: =D33*L33 -> 241.01251 | N33: =K33+M33 -> 386.93251 | T33: 20 | Y33: 10
B34: total | C34: =SUM(C24:C33) -> 1292 | D34: =SUM(D24:D33) -> 597866 | E34: =SUM(E24:E33) -> 204600 | F34: =SUM(F24:F33) -> 0 | G34: =SUM(G24:G33) -> 0 | H34: =SUM(H24:H33) -> 511500 | I34: =SUM(I24:I33) -> 1534500 | J34: =SUM(I34:I34) -> 1534500 | K34: =IF(J34>$P$14,$R$15,IF(J34>$P$13,$R$14,$R$13))*J34 -> 291.555 | L34: =IF(D34>$P$10,$R$11,IF(D34>$P$9,$R$10,IF(D34>$P$8,$R$9,IF(D34>$P$7,$R$8,IF(D34>$P$6,$R$7,IF(D34>$P$5,$R$6,IF(D34>$P$4,$R$5,IF(D34>$P$3,$R$4,IF(D34>$P$2,$R$3,$R$2))))))))) -> 0.00079571759 | M34: =D34*L34 -> 475.73249 | N34: =K34+M34 -> 767.28749
A35: Mining | B35: 1 | C35: 6 | D35: 598 | E35: 800 | I35: 2000 | J35: =SUM(I35:I35) -> 2000 | K35: =IF(J35>$P$14,$R$15,IF(J35>$P$13,$R$14,$R$13))*J35 -> 0.5 | L35: =IF(D35>$P$10,$R$11,IF(D35>$P$9,$R$10,IF(D35>$P$8,$R$9,IF(D35>$P$7,$R$8,IF(D35>$P$6,$R$7,IF(D35>$P$5,$R$6,IF(D35>$P$4,$R$5,IF(D35>$P$3,$R$4,IF(D35>$P$2,$R$3,$R$2))))))))) -> 0.0055555556 | M35: =D35*L35 -> 3.3222222 | N35: =K35+M35 -> 3.8222222 | T35: 2 | Z35: 1
B36: 2 | C36: 9 | D36: 1210 | E36: =E35*2 -> 1600 | I36: =I35*2 -> 4000 | J36: =SUM(I36:I36) -> 4000 | K36: =IF(J36>$P$14,$R$15,IF(J36>$P$13,$R$14,$R$13))*J36 -> 1 | L36: =IF(D36>$P$10,$R$11,IF(D36>$P$9,$R$10,IF(D36>$P$8,$R$9,IF(D36>$P$7,$R$8,IF(D36>$P$6,$R$7,IF(D36>$P$5,$R$6,IF(D36>$P$4,$R$5,IF(D36>$P$3,$R$4,IF(D36>$P$2,$R$3,$R$2))))))))) -> 0.0027777778 | M36: =D36*L36 -> 3.3611111 | N36: =K36+M36 -> 4.3611111 | T36: 4 | Z36: 2
B37: 3 | C37: 13 | D37: 2452 | E37: =E36*2 -> 3200 | I37: =I36*2 -> 8000 | J37: =SUM(I37:I37) -> 8000 | K37: =IF(J37>$P$14,$R$15,IF(J37>$P$13,$R$14,$R$13))*J37 -> 2 | L37: =IF(D37>$P$10,$R$11,IF(D37>$P$9,$R$10,IF(D37>$P$8,$R$9,IF(D37>$P$7,$R$8,IF(D37>$P$6,$R$7,IF(D37>$P$5,$R$6,IF(D37>$P$4,$R$5,IF(D37>$P$3,$R$4,IF(D37>$P$2,$R$3,$R$2))))))))) -> 0.0027777778 | M37: =D37*L37 -> 6.8111111 | N37: =K37+M37 -> 8.8111111 | T37: 6 | Z37: 3
B38: 4 | C38: 23 | D38: 4965 | E38: =E37*2 -> 6400 | I38: =I37*2 -> 16000 | J38: =SUM(I38:I38) -> 16000 | K38: =IF(J38>$P$14,$R$15,IF(J38>$P$13,$R$14,$R$13))*J38 -> 4 | L38: =IF(D38>$P$10,$R$11,IF(D38>$P$9,$R$10,IF(D38>$P$8,$R$9,IF(D38>$P$7,$R$8,IF(D38>$P$6,$R$7,IF(D38>$P$5,$R$6,IF(D38>$P$4,$R$5,IF(D38>$P$3,$R$4,IF(D38>$P$2,$R$3,$R$2))))))))) -> 0.0016666667 | M38: =D38*L38 -> 8.275 | N38: =K38+M38 -> 12.275 | T38: 8 | Z38: 4
B39: 5 | C39: 42 | D39: 10055 | E39: =E38*2 -> 12800 | I39: =I38*2 -> 32000 | J39: =SUM(I39:I39) -> 32000 | K39: =IF(J39>$P$14,$R$15,IF(J39>$P$13,$R$14,$R$13))*J39 -> 8 | L39: =IF(D39>$P$10,$R$11,IF(D39>$P$9,$R$10,IF(D39>$P$8,$R$9,IF(D39>$P$7,$R$8,IF(D39>$P$6,$R$7,IF(D39>$P$5,$R$6,IF(D39>$P$4,$R$5,IF(D39>$P$3,$R$4,IF(D39>$P$2,$R$3,$R$2))))))))) -> 0.0013888889 | M39: =D39*L39 -> 13.965278 | N39: =K39+M39 -> 21.965278 | T39: 10 | Z39: 5
B40: 6 | C40: 59 | D40: 20362 | E40: =E39*2 -> 25600 | I40: =I39*2 -> 64000 | J40: =SUM(I40:I40) -> 64000 | K40: =IF(J40>$P$14,$R$15,IF(J40>$P$13,$R$14,$R$13))*J40 -> 16 | L40: =IF(D40>$P$10,$R$11,IF(D40>$P$9,$R$10,IF(D40>$P$8,$R$9,IF(D40>$P$7,$R$8,IF(D40>$P$6,$R$7,IF(D40>$P$5,$R$6,IF(D40>$P$4,$R$5,IF(D40>$P$3,$R$4,IF(D40>$P$2,$R$3,$R$2))))))))) -> 0.0013888889 | M40: =D40*L40 -> 28.280556 | N40: =K40+M40 -> 44.280556 | T40: 12 | Z40: 6
B41: 7 | C41: 103 | D41: 41233 | E41: =E40*2 -> 51200 | I41: =I40*2 -> 128000 | J41: =SUM(I41:I41) -> 128000 | K41: =IF(J41>$P$14,$R$15,IF(J41>$P$13,$R$14,$R$13))*J41 -> 28.16 | L41: =IF(D41>$P$10,$R$11,IF(D41>$P$9,$R$10,IF(D41>$P$8,$R$9,IF(D41>$P$7,$R$8,IF(D41>$P$6,$R$7,IF(D41>$P$5,$R$6,IF(D41>$P$4,$R$5,IF(D41>$P$3,$R$4,IF(D41>$P$2,$R$3,$R$2))))))))) -> 0.0012037037 | M41: =D41*L41 -> 49.632315 | N41: =K41+M41 -> 77.792315 | T41: 14 | Z41: 7
B42: 8 | C42: 197 | D42: 83498 | E42: =E41*2 -> 102400 | I42: =I41*2 -> 256000 | J42: =SUM(I42:I42) -> 256000 | K42: =IF(J42>$P$14,$R$15,IF(J42>$P$13,$R$14,$R$13))*J42 -> 48.64 | L42: =IF(D42>$P$10,$R$11,IF(D42>$P$9,$R$10,IF(D42>$P$8,$R$9,IF(D42>$P$7,$R$8,IF(D42>$P$6,$R$7,IF(D42>$P$5,$R$6,IF(D42>$P$4,$R$5,IF(D42>$P$3,$R$4,IF(D42>$P$2,$R$3,$R$2))))))))) -> 0.001099537 | M42: =D42*L42 -> 91.809144 | N42: =K42+M42 -> 140.44914 | T42: 16 | Z42: 8
B43: 9 | C43: 383 | D43: 169083 | E43: =E42*2 -> 204800 | I43: =I42*2 -> 512000 | J43: =SUM(I43:I43) -> 512000 | K43: =IF(J43>$P$14,$R$15,IF(J43>$P$13,$R$14,$R$13))*J43 -> 97.28 | L43: =IF(D43>$P$10,$R$11,IF(D43>$P$9,$R$10,IF(D43>$P$8,$R$9,IF(D43>$P$7,$R$8,IF(D43>$P$6,$R$7,IF(D43>$P$5,$R$6,IF(D43>$P$4,$R$5,IF(D43>$P$3,$R$4,IF(D43>$P$2,$R$3,$R$2))))))))) -> 0.00097222222 | M43: =D43*L43 -> 164.38625 | N43: =K43+M43 -> 261.66625 | T43: 18 | Z43: 9
B44: 10 | C44: 721 | D44: 342394 | E44: =E43*2 -> 409600 | I44: =I43*2 -> 1024000 | J44: =SUM(I44:I44) -> 1024000 | K44: =IF(J44>$P$14,$R$15,IF(J44>$P$13,$R$14,$R$13))*J44 -> 194.56 | L44: =IF(D44>$P$10,$R$11,IF(D44>$P$9,$R$10,IF(D44>$P$8,$R$9,IF(D44>$P$7,$R$8,IF(D44>$P$6,$R$7,IF(D44>$P$5,$R$6,IF(D44>$P$4,$R$5,IF(D44>$P$3,$R$4,IF(D44>$P$2,$R$3,$R$2))))))))) -> 0.00079571759 | M44: =D44*L44 -> 272.44893 | N44: =K44+M44 -> 467.00893 | T44: 20 | Z44: 10
B45: total | C45: =SUM(C35:C44) -> 1556 | D45: =SUM(D35:D44) -> 675850 | E45: =SUM(E35:E44) -> 818400 | F45: =SUM(F35:F44) -> 0 | G45: =SUM(G35:G44) -> 0 | H45: =SUM(H35:H44) -> 0 | I45: =SUM(I35:I44) -> 2046000 | J45: =SUM(I45:I45) -> 2046000 | K45: =IF(J45>$P$14,$R$15,IF(J45>$P$13,$R$14,$R$13))*J45 -> 388.74 | L45: =IF(D45>$P$10,$R$11,IF(D45>$P$9,$R$10,IF(D45>$P$8,$R$9,IF(D45>$P$7,$R$8,IF(D45>$P$6,$R$7,IF(D45>$P$5,$R$6,IF(D45>$P$4,$R$5,IF(D45>$P$3,$R$4,IF(D45>$P$2,$R$3,$R$2))))))))) -> 0.00079571759 | M45: =D45*L45 -> 537.78573 | N45: =K45+M45 -> 926.52573
A46: Metallurgy | B46: 1 | C46: 8 | D46: 1337 | E46: 3000 | F46: 150 | G46: 800 | H46: 200 | I46: 3500 | J46: =SUM(I46:I46) -> 3500 | K46: =IF(J46>$P$14,$R$15,IF(J46>$P$13,$R$14,$R$13))*J46 -> 0.875 | L46: =IF(D46>$P$10,$R$11,IF(D46>$P$9,$R$10,IF(D46>$P$8,$R$9,IF(D46>$P$7,$R$8,IF(D46>$P$6,$R$7,IF(D46>$P$5,$R$6,IF(D46>$P$4,$R$5,IF(D46>$P$3,$R$4,IF(D46>$P$2,$R$3,$R$2))))))))) -> 0.0027777778 | M46: =D46*L46 -> 3.7138889 | N46: =K46+M46 -> 4.5888889 | T46: 4 | AA46: 2 | AB46: 2 | AC46: 1
B47: 2 | C47: 14 | D47: 2707 | E47: =E46*2 -> 6000 | F47: =F46*2 -> 300 | G47: =G46*2 -> 1600 | H47: =H46*2 -> 400 | I47: =I46*2 -> 7000 | J47: =SUM(I47:I47) -> 7000 | K47: =IF(J47>$P$14,$R$15,IF(J47>$P$13,$R$14,$R$13))*J47 -> 1.75 | L47: =IF(D47>$P$10,$R$11,IF(D47>$P$9,$R$10,IF(D47>$P$8,$R$9,IF(D47>$P$7,$R$8,IF(D47>$P$6,$R$7,IF(D47>$P$5,$R$6,IF(D47>$P$4,$R$5,IF(D47>$P$3,$R$4,IF(D47>$P$2,$R$3,$R$2))))))))) -> 0.0027777778 | M47: =D47*L47 -> 7.5194444 | N47: =K47+M47 -> 9.2694444 | T47: 6 | AA47: 4 | AB47: 4 | AC47: 2
B48: 3 | C48: 20 | D48: 5482 | E48: =E47*2 -> 12000 | F48: =F47*2 -> 600 | G48: =G47*2 -> 3200 | H48: =H47*2 -> 800 | I48: =I47*2 -> 14000 | J48: =SUM(I48:I48) -> 14000 | K48: =IF(J48>$P$14,$R$15,IF(J48>$P$13,$R$14,$R$13))*J48 -> 3.5 | L48: =IF(D48>$P$10,$R$11,IF(D48>$P$9,$R$10,IF(D48>$P$8,$R$9,IF(D48>$P$7,$R$8,IF(D48>$P$6,$R$7,IF(D48>$P$5,$R$6,IF(D48>$P$4,$R$5,IF(D48>$P$3,$R$4,IF(D48>$P$2,$R$3,$R$2))))))))) -> 0.0016666667 | M48: =D48*L48 -> 9.1366667 | N48: =K48+M48 -> 12.636667 | T48: 6 | AA48: 4 | AB48: 6 | AC48: 3
B49: 4 | C49: 35 | D49: 11102 | E49: =E48*2 -> 24000 | F49: =F48*2 -> 1200 | G49: =G48*2 -> 6400 | H49: =H48*2 -> 1600 | I49: =I48*2 -> 28000 | J49: =SUM(I49:I49) -> 28000 | K49: =IF(J49>$P$14,$R$15,IF(J49>$P$13,$R$14,$R$13))*J49 -> 7 | L49: =IF(D49>$P$10,$R$11,IF(D49>$P$9,$R$10,IF(D49>$P$8,$R$9,IF(D49>$P$7,$R$8,IF(D49>$P$6,$R$7,IF(D49>$P$5,$R$6,IF(D49>$P$4,$R$5,IF(D49>$P$3,$R$4,IF(D49>$P$2,$R$3,$R$2))))))))) -> 0.0013888889 | M49: =D49*L49 -> 15.419444 | N49: =K49+M49 -> 22.419444 | T49: 8 | AA49: 4 | AB49: 8 | AC49: 4
B50: 5 | C50: 69 | D50: 22481 | E50: =E49*2 -> 48000 | F50: =F49*2 -> 2400 | G50: =G49*2 -> 12800 | H50: =H49*2 -> 3200 | I50: =I49*2 -> 56000 | J50: =SUM(I50:I50) -> 56000 | K50: =IF(J50>$P$14,$R$15,IF(J50>$P$13,$R$14,$R$13))*J50 -> 14 | L50: =IF(D50>$P$10,$R$11,IF(D50>$P$9,$R$10,IF(D50>$P$8,$R$9,IF(D50>$P$7,$R$8,IF(D50>$P$6,$R$7,IF(D50>$P$5,$R$6,IF(D50>$P$4,$R$5,IF(D50>$P$3,$R$4,IF(D50>$P$2,$R$3,$R$2))))))))) -> 0.0013888889 | M50: =D50*L50 -> 31.223611 | N50: =K50+M50 -> 45.223611 | T50: 10 | AA50: 4 | AB50: 10 | AC50: 5
B51: 6 | C51: 125 | D51: 45525 | E51: =E50*2 -> 96000 | F51: =F50*2 -> 4800 | G51: =G50*2 -> 25600 | H51: =H50*2 -> 6400 | I51: =I50*2 -> 112000 | J51: =SUM(I51:I51) -> 112000 | K51: =IF(J51>$P$14,$R$15,IF(J51>$P$13,$R$14,$R$13))*J51 -> 24.64 | L51: =IF(D51>$P$10,$R$11,IF(D51>$P$9,$R$10,IF(D51>$P$8,$R$9,IF(D51>$P$7,$R$8,IF(D51>$P$6,$R$7,IF(D51>$P$5,$R$6,IF(D51>$P$4,$R$5,IF(D51>$P$3,$R$4,IF(D51>$P$2,$R$3,$R$2))))))))) -> 0.0012037037 | M51: =D51*L51 -> 54.798611 | N51: =K51+M51 -> 79.438611 | T51: 12 | AA51: 4 | AB51: 12 | AC51: 6
B52: 7 | C52: 268 | D52: 92189 | E52: =E51*2 -> 192000 | F52: =F51*2 -> 9600 | G52: =G51*2 -> 51200 | H52: =H51*2 -> 12800 | I52: =I51*2 -> 224000 | J52: =SUM(I52:I52) -> 224000 | K52: =IF(J52>$P$14,$R$15,IF(J52>$P$13,$R$14,$R$13))*J52 -> 49.28 | L52: =IF(D52>$P$10,$R$11,IF(D52>$P$9,$R$10,IF(D52>$P$8,$R$9,IF(D52>$P$7,$R$8,IF(D52>$P$6,$R$7,IF(D52>$P$5,$R$6,IF(D52>$P$4,$R$5,IF(D52>$P$3,$R$4,IF(D52>$P$2,$R$3,$R$2))))))))) -> 0.00097222222 | M52: =D52*L52 -> 89.628194 | N52: =K52+M52 -> 138.90819 | T52: 14 | AA52: 4 | AB52: 14 | AC52: 7
B53: 8 | C53: 456 | D53: 186683 | E53: =E52*2 -> 384000 | F53: =F52*2 -> 19200 | G53: =G52*2 -> 102400 | H53: =H52*2 -> 25600 | I53: =I52*2 -> 448000 | J53: =SUM(I53:I53) -> 448000 | K53: =IF(J53>$P$14,$R$15,IF(J53>$P$13,$R$14,$R$13))*J53 -> 85.12 | L53: =IF(D53>$P$10,$R$11,IF(D53>$P$9,$R$10,IF(D53>$P$8,$R$9,IF(D53>$P$7,$R$8,IF(D53>$P$6,$R$7,IF(D53>$P$5,$R$6,IF(D53>$P$4,$R$5,IF(D53>$P$3,$R$4,IF(D53>$P$2,$R$3,$R$2))))))))) -> 0.00097222222 | M53: =D53*L53 -> 181.49736 | N53: =K53+M53 -> 266.61736 | T53: 16 | AA53: 4 | AB53: 16 | AC53: 8
B54: 9 | C54: 859 | D54: 378034 | E54: =E53*2 -> 768000 | F54: =F53*2 -> 38400 | G54: =G53*2 -> 204800 | H54: =H53*2 -> 51200 | I54: =I53*2 -> 896000 | J54: =SUM(I54:I54) -> 896000 | K54: =IF(J54>$P$14,$R$15,IF(J54>$P$13,$R$14,$R$13))*J54 -> 170.24 | L54: =IF(D54>$P$10,$R$11,IF(D54>$P$9,$R$10,IF(D54>$P$8,$R$9,IF(D54>$P$7,$R$8,IF(D54>$P$6,$R$7,IF(D54>$P$5,$R$6,IF(D54>$P$4,$R$5,IF(D54>$P$3,$R$4,IF(D54>$P$2,$R$3,$R$2))))))))) -> 0.00079571759 | M54: =D54*L54 -> 300.8083 | N54: =K54+M54 -> 471.0483 | T54: 18 | AA54: 4 | AB54: 18 | AC54: 9
B55: 10 | C55: 1827 | D55: 765520 | E55: =E54*2 -> 1536000 | F55: =F54*2 -> 76800 | G55: =G54*2 -> 409600 | H55: =H54*2 -> 102400 | I55: =I54*2 -> 1792000 | J55: =SUM(I55:I55) -> 1792000 | K55: =IF(J55>$P$14,$R$15,IF(J55>$P$13,$R$14,$R$13))*J55 -> 340.48 | L55: =IF(D55>$P$10,$R$11,IF(D55>$P$9,$R$10,IF(D55>$P$8,$R$9,IF(D55>$P$7,$R$8,IF(D55>$P$6,$R$7,IF(D55>$P$5,$R$6,IF(D55>$P$4,$R$5,IF(D55>$P$3,$R$4,IF(D55>$P$2,$R$3,$R$2))))))))) -> 0.00079571759 | M55: =D55*L55 -> 609.13773 | N55: =K55+M55 -> 949.61773 | T55: 20 | AA55: 4 | AB55: 20 | AC55: 10
B56: total | C56: =SUM(C46:C55) -> 3681 | D56: =SUM(D46:D55) -> 1511060 | E56: =SUM(E46:E55) -> 3069000 | F56: =SUM(F46:F55) -> 153450 | G56: =SUM(G46:G55) -> 818400 | H56: =SUM(H46:H55) -> 204600 | I56: =SUM(I46:I55) -> 3580500 | J56: =SUM(I56:I56) -> 3580500 | K56: =IF(J56>$P$14,$R$15,IF(J56>$P$13,$R$14,$R$13))*J56 -> 680.295 | L56: =IF(D56>$P$10,$R$11,IF(D56>$P$9,$R$10,IF(D56>$P$8,$R$9,IF(D56>$P$7,$R$8,IF(D56>$P$6,$R$7,IF(D56>$P$5,$R$6,IF(D56>$P$4,$R$5,IF(D56>$P$3,$R$4,IF(D56>$P$2,$R$3,$R$2))))))))) -> 0.00079571759 | M56: =D56*L56 -> 1202.377 | N56: =K56+M56 -> 1882.672
A57: Clairvoyance | B57: 1 | C57: 5 | D57: 420 | G57: 300 | I57: 2000 | J57: =SUM(I57:I57) -> 2000 | K57: =IF(J57>$P$14,$R$15,IF(J57>$P$13,$R$14,$R$13))*J57 -> 0.5 | L57: =IF(D57>$P$10,$R$11,IF(D57>$P$9,$R$10,IF(D57>$P$8,$R$9,IF(D57>$P$7,$R$8,IF(D57>$P$6,$R$7,IF(D57>$P$5,$R$6,IF(D57>$P$4,$R$5,IF(D57>$P$3,$R$4,IF(D57>$P$2,$R$3,$R$2))))))))) -> 0.0055555556 | M57: =D57*L57 -> 2.3333333 | N57: =K57+M57 -> 2.8333333 | T57: 6
B58: 2 | C58: 7 | D58: 850 | G58: =G57*2 -> 600 | I58: =I57*2 -> 4000 | J58: =SUM(I58:I58) -> 4000 | K58: =IF(J58>$P$14,$R$15,IF(J58>$P$13,$R$14,$R$13))*J58 -> 1 | L58: =IF(D58>$P$10,$R$11,IF(D58>$P$9,$R$10,IF(D58>$P$8,$R$9,IF(D58>$P$7,$R$8,IF(D58>$P$6,$R$7,IF(D58>$P$5,$R$6,IF(D58>$P$4,$R$5,IF(D58>$P$3,$R$4,IF(D58>$P$2,$R$3,$R$2))))))))) -> 0.0055555556 | M58: =D58*L58 -> 4.7222222 | N58: =K58+M58 -> 5.7222222 | T58: 6
B59: 3 | C59: 11 | D59: 1722 | G59: =G58*2 -> 1200 | I59: =I58*2 -> 8000 | J59: =SUM(I59:I59) -> 8000 | K59: =IF(J59>$P$14,$R$15,IF(J59>$P$13,$R$14,$R$13))*J59 -> 2 | L59: =IF(D59>$P$10,$R$11,IF(D59>$P$9,$R$10,IF(D59>$P$8,$R$9,IF(D59>$P$7,$R$8,IF(D59>$P$6,$R$7,IF(D59>$P$5,$R$6,IF(D59>$P$4,$R$5,IF(D59>$P$3,$R$4,IF(D59>$P$2,$R$3,$R$2))))))))) -> 0.0027777778 | M59: =D59*L59 -> 4.7833333 | N59: =K59+M59 -> 6.7833333 | T59: 6
B60: 4 | C60: 19 | D60: 3487 | G60: =G59*2 -> 2400 | I60: =I59*2 -> 16000 | J60: =SUM(I60:I60) -> 16000 | K60: =IF(J60>$P$14,$R$15,IF(J60>$P$13,$R$14,$R$13))*J60 -> 4 | L60: =IF(D60>$P$10,$R$11,IF(D60>$P$9,$R$10,IF(D60>$P$8,$R$9,IF(D60>$P$7,$R$8,IF(D60>$P$6,$R$7,IF(D60>$P$5,$R$6,IF(D60>$P$4,$R$5,IF(D60>$P$3,$R$4,IF(D60>$P$2,$R$3,$R$2))))))))) -> 0.0027777778 | M60: =D60*L60 -> 9.6861111 | N60: =K60+M60 -> 13.686111 | T60: 8
B61: 5 | C61: 33 | D61: 7062 | G61: =G60*2 -> 4800 | I61: =I60*2 -> 32000 | J61: =SUM(I61:I61) -> 32000 | K61: =IF(J61>$P$14,$R$15,IF(J61>$P$13,$R$14,$R$13))*J61 -> 8 | L61: =IF(D61>$P$10,$R$11,IF(D61>$P$9,$R$10,IF(D61>$P$8,$R$9,IF(D61>$P$7,$R$8,IF(D61>$P$6,$R$7,IF(D61>$P$5,$R$6,IF(D61>$P$4,$R$5,IF(D61>$P$3,$R$4,IF(D61>$P$2,$R$3,$R$2))))))))) -> 0.0016666667 | M61: =D61*L61 -> 11.77 | N61: =K61+M61 -> 19.77 | T61: 10
B62: 6 | C62: 49 | D62: 14301 | G62: =G61*2 -> 9600 | I62: =I61*2 -> 64000 | J62: =SUM(I62:I62) -> 64000 | K62: =IF(J62>$P$14,$R$15,IF(J62>$P$13,$R$14,$R$13))*J62 -> 16 | L62: =IF(D62>$P$10,$R$11,IF(D62>$P$9,$R$10,IF(D62>$P$8,$R$9,IF(D62>$P$7,$R$8,IF(D62>$P$6,$R$7,IF(D62>$P$5,$R$6,IF(D62>$P$4,$R$5,IF(D62>$P$3,$R$4,IF(D62>$P$2,$R$3,$R$2))))))))) -> 0.0013888889 | M62: =D62*L62 -> 19.8625 | N62: =K62+M62 -> 35.8625 | T62: 12
B63: 7 | C63: 93 | D63: 28960 | G63: =G62*2 -> 19200 | I63: =I62*2 -> 128000 | J63: =SUM(I63:I63) -> 128000 | K63: =IF(J63>$P$14,$R$15,IF(J63>$P$13,$R$14,$R$13))*J63 -> 28.16 | L63: =IF(D63>$P$10,$R$11,IF(D63>$P$9,$R$10,IF(D63>$P$8,$R$9,IF(D63>$P$7,$R$8,IF(D63>$P$6,$R$7,IF(D63>$P$5,$R$6,IF(D63>$P$4,$R$5,IF(D63>$P$3,$R$4,IF(D63>$P$2,$R$3,$R$2))))))))) -> 0.0012037037 | M63: =D63*L63 -> 34.859259 | N63: =K63+M63 -> 63.019259 | T63: 14
B64: 8 | C64: 168 | D64: 58644 | G64: =G63*2 -> 38400 | I64: =I63*2 -> 256000 | J64: =SUM(I64:I64) -> 256000 | K64: =IF(J64>$P$14,$R$15,IF(J64>$P$13,$R$14,$R$13))*J64 -> 48.64 | L64: =IF(D64>$P$10,$R$11,IF(D64>$P$9,$R$10,IF(D64>$P$8,$R$9,IF(D64>$P$7,$R$8,IF(D64>$P$6,$R$7,IF(D64>$P$5,$R$6,IF(D64>$P$4,$R$5,IF(D64>$P$3,$R$4,IF(D64>$P$2,$R$3,$R$2))))))))) -> 0.001099537 | M64: =D64*L64 -> 64.48125 | N64: =K64+M64 -> 113.12125 | T64: 16
B65: 9 | C65: 348 | D65: 118754 | G65: =G64*2 -> 76800 | I65: =I64*2 -> 512000 | J65: =SUM(I65:I65) -> 512000 | K65: =IF(J65>$P$14,$R$15,IF(J65>$P$13,$R$14,$R$13))*J65 -> 97.28 | L65: =IF(D65>$P$10,$R$11,IF(D65>$P$9,$R$10,IF(D65>$P$8,$R$9,IF(D65>$P$7,$R$8,IF(D65>$P$6,$R$7,IF(D65>$P$5,$R$6,IF(D65>$P$4,$R$5,IF(D65>$P$3,$R$4,IF(D65>$P$2,$R$3,$R$2))))))))) -> 0.00097222222 | M65: =D65*L65 -> 115.45528 | N65: =K65+M65 -> 212.73528 | T65: 18
B66: 10 | C66: 658 | D66: 240477 | G66: =G65*2 -> 153600 | I66: =I65*2 -> 1024000 | J66: =SUM(I66:I66) -> 1024000 | K66: =IF(J66>$P$14,$R$15,IF(J66>$P$13,$R$14,$R$13))*J66 -> 194.56 | L66: =IF(D66>$P$10,$R$11,IF(D66>$P$9,$R$10,IF(D66>$P$8,$R$9,IF(D66>$P$7,$R$8,IF(D66>$P$6,$R$7,IF(D66>$P$5,$R$6,IF(D66>$P$4,$R$5,IF(D66>$P$3,$R$4,IF(D66>$P$2,$R$3,$R$2))))))))) -> 0.00079571759 | M66: =D66*L66 -> 191.35178 | N66: =K66+M66 -> 385.91178 | T66: 20
B67: total | C67: =SUM(C57:C66) -> 1391 | D67: =SUM(D57:D66) -> 474677 | E67: =SUM(E57:E66) -> 0 | F67: =SUM(F57:F66) -> 0 | G67: =SUM(G57:G66) -> 306900 | H67: =SUM(H57:H66) -> 0 | I67: =SUM(I57:I66) -> 2046000 | J67: =SUM(I67:I67) -> 2046000 | K67: =IF(J67>$P$14,$R$15,IF(J67>$P$13,$R$14,$R$13))*J67 -> 388.74 | L67: =IF(D67>$P$10,$R$11,IF(D67>$P$9,$R$10,IF(D67>$P$8,$R$9,IF(D67>$P$7,$R$8,IF(D67>$P$6,$R$7,IF(D67>$P$5,$R$6,IF(D67>$P$4,$R$5,IF(D67>$P$3,$R$4,IF(D67>$P$2,$R$3,$R$2))))))))) -> 0.00079571759 | M67: =D67*L67 -> 377.70884 | N67: =K67+M67 -> 766.44884
A68: RapidDeployment | B68: 1 | C68: 9 | D68: 1776 | G68: 600 | I68: 3000 | J68: =SUM(I68:I68) -> 3000 | K68: =IF(J68>$P$14,$R$15,IF(J68>$P$13,$R$14,$R$13))*J68 -> 0.75 | L68: =IF(D68>$P$10,$R$11,IF(D68>$P$9,$R$10,IF(D68>$P$8,$R$9,IF(D68>$P$7,$R$8,IF(D68>$P$6,$R$7,IF(D68>$P$5,$R$6,IF(D68>$P$4,$R$5,IF(D68>$P$3,$R$4,IF(D68>$P$2,$R$3,$R$2))))))))) -> 0.0027777778 | M68: =D68*L68 -> 4.9333333 | N68: =K68+M68 -> 5.6833333 | T68: 8
B69: 2 | C69: 12 | D69: 3596 | G69: =G68*2 -> 1200 | I69: =I68*2 -> 6000 | J69: =SUM(I69:I69) -> 6000 | K69: =IF(J69>$P$14,$R$15,IF(J69>$P$13,$R$14,$R$13))*J69 -> 1.5 | L69: =IF(D69>$P$10,$R$11,IF(D69>$P$9,$R$10,IF(D69>$P$8,$R$9,IF(D69>$P$7,$R$8,IF(D69>$P$6,$R$7,IF(D69>$P$5,$R$6,IF(D69>$P$4,$R$5,IF(D69>$P$3,$R$4,IF(D69>$P$2,$R$3,$R$2))))))))) -> 0.0027777778 | M69: =D69*L69 -> 9.9888889 | N69: =K69+M69 -> 11.488889 | T69: 8
B70: 3 | C70: 17 | D70: 7282 | G70: =G69*2 -> 2400 | I70: =I69*2 -> 12000 | J70: =SUM(I70:I70) -> 12000 | K70: =IF(J70>$P$14,$R$15,IF(J70>$P$13,$R$14,$R$13))*J70 -> 3 | L70: =IF(D70>$P$10,$R$11,IF(D70>$P$9,$R$10,IF(D70>$P$8,$R$9,IF(D70>$P$7,$R$8,IF(D70>$P$6,$R$7,IF(D70>$P$5,$R$6,IF(D70>$P$4,$R$5,IF(D70>$P$3,$R$4,IF(D70>$P$2,$R$3,$R$2))))))))) -> 0.0016666667 | M70: =D70*L70 -> 12.136667 | N70: =K70+M70 -> 15.136667 | T70: 8
B71: 4 | C71: 27 | D71: 14747 | G71: =G70*2 -> 4800 | I71: =I70*2 -> 24000 | J71: =SUM(I71:I71) -> 24000 | K71: =IF(J71>$P$14,$R$15,IF(J71>$P$13,$R$14,$R$13))*J71 -> 6 | L71: =IF(D71>$P$10,$R$11,IF(D71>$P$9,$R$10,IF(D71>$P$8,$R$9,IF(D71>$P$7,$R$8,IF(D71>$P$6,$R$7,IF(D71>$P$5,$R$6,IF(D71>$P$4,$R$5,IF(D71>$P$3,$R$4,IF(D71>$P$2,$R$3,$R$2))))))))) -> 0.0013888889 | M71: =D71*L71 -> 20.481944 | N71: =K71+M71 -> 26.481944 | T71: 8
B72: 5 | C72: 68 | D72: 29863 | G72: =G71*2 -> 9600 | I72: =I71*2 -> 48000 | J72: =SUM(I72:I72) -> 48000 | K72: =IF(J72>$P$14,$R$15,IF(J72>$P$13,$R$14,$R$13))*J72 -> 12 | L72: =IF(D72>$P$10,$R$11,IF(D72>$P$9,$R$10,IF(D72>$P$8,$R$9,IF(D72>$P$7,$R$8,IF(D72>$P$6,$R$7,IF(D72>$P$5,$R$6,IF(D72>$P$4,$R$5,IF(D72>$P$3,$R$4,IF(D72>$P$2,$R$3,$R$2))))))))) -> 0.0012037037 | M72: =D72*L72 -> 35.946204 | N72: =K72+M72 -> 47.946204 | T72: 10
B73: 6 | C73: 114 | D73: 60473 | G73: =G72*2 -> 19200 | I73: =I72*2 -> 96000 | J73: =SUM(I73:I73) -> 96000 | K73: =IF(J73>$P$14,$R$15,IF(J73>$P$13,$R$14,$R$13))*J73 -> 21.12 | L73: =IF(D73>$P$10,$R$11,IF(D73>$P$9,$R$10,IF(D73>$P$8,$R$9,IF(D73>$P$7,$R$8,IF(D73>$P$6,$R$7,IF(D73>$P$5,$R$6,IF(D73>$P$4,$R$5,IF(D73>$P$3,$R$4,IF(D73>$P$2,$R$3,$R$2))))))))) -> 0.001099537 | M73: =D73*L73 -> 66.492303 | N73: =K73+M73 -> 87.612303 | T73: 12
B74: 7 | C74: 208 | D74: 122459 | G74: =G73*2 -> 38400 | I74: =I73*2 -> 192000 | J74: =SUM(I74:I74) -> 192000 | K74: =IF(J74>$P$14,$R$15,IF(J74>$P$13,$R$14,$R$13))*J74 -> 42.24 | L74: =IF(D74>$P$10,$R$11,IF(D74>$P$9,$R$10,IF(D74>$P$8,$R$9,IF(D74>$P$7,$R$8,IF(D74>$P$6,$R$7,IF(D74>$P$5,$R$6,IF(D74>$P$4,$R$5,IF(D74>$P$3,$R$4,IF(D74>$P$2,$R$3,$R$2))))))))) -> 0.00097222222 | M74: =D74*L74 -> 119.05736 | N74: =K74+M74 -> 161.29736 | T74: 14
B75: 8 | C75: 372 | D75: 247980 | G75: =G74*2 -> 76800 | I75: =I74*2 -> 384000 | J75: =SUM(I75:I75) -> 384000 | K75: =IF(J75>$P$14,$R$15,IF(J75>$P$13,$R$14,$R$13))*J75 -> 72.96 | L75: =IF(D75>$P$10,$R$11,IF(D75>$P$9,$R$10,IF(D75>$P$8,$R$9,IF(D75>$P$7,$R$8,IF(D75>$P$6,$R$7,IF(D75>$P$5,$R$6,IF(D75>$P$4,$R$5,IF(D75>$P$3,$R$4,IF(D75>$P$2,$R$3,$R$2))))))))) -> 0.00079571759 | M75: =D75*L75 -> 197.32205 | N75: =K75+M75 -> 270.28205 | T75: 16
B76: 9 | C76: 803 | D76: 502161 | G76: =G75*2 -> 153600 | I76: =I75*2 -> 768000 | J76: =SUM(I76:I76) -> 768000 | K76: =IF(J76>$P$14,$R$15,IF(J76>$P$13,$R$14,$R$13))*J76 -> 145.92 | L76: =IF(D76>$P$10,$R$11,IF(D76>$P$9,$R$10,IF(D76>$P$8,$R$9,IF(D76>$P$7,$R$8,IF(D76>$P$6,$R$7,IF(D76>$P$5,$R$6,IF(D76>$P$4,$R$5,IF(D76>$P$3,$R$4,IF(D76>$P$2,$R$3,$R$2))))))))) -> 0.00079571759 | M76: =D76*L76 -> 399.57834 | N76: =K76+M76 -> 545.49834 | T76: 18
B77: 10 | C77: 1007 | D77: 1016876 | G77: =G76*2 -> 307200 | I77: =I76*2 -> 1536000 | J77: =SUM(I77:I77) -> 1536000 | K77: =IF(J77>$P$14,$R$15,IF(J77>$P$13,$R$14,$R$13))*J77 -> 291.84 | L77: =IF(D77>$P$10,$R$11,IF(D77>$P$9,$R$10,IF(D77>$P$8,$R$9,IF(D77>$P$7,$R$8,IF(D77>$P$6,$R$7,IF(D77>$P$5,$R$6,IF(D77>$P$4,$R$5,IF(D77>$P$3,$R$4,IF(D77>$P$2,$R$3,$R$2))))))))) -> 0.00079571759 | M77: =D77*L77 -> 809.14612 | N77: =K77+M77 -> 1100.9861 | T77: 20
B78: total | C78: =SUM(C68:C77) -> 2637 | D78: =SUM(D68:D77) -> 2007213 | E78: =SUM(E68:E77) -> 0 | F78: =SUM(F68:F77) -> 0 | G78: =SUM(G68:G77) -> 613800 | H78: =SUM(H68:H77) -> 0 | I78: =SUM(I68:I77) -> 3069000 | J78: =SUM(I78:I78) -> 3069000 | K78: =IF(J78>$P$14,$R$15,IF(J78>$P$13,$R$14,$R$13))*J78 -> 583.11 | L78: =IF(D78>$P$10,$R$11,IF(D78>$P$9,$R$10,IF(D78>$P$8,$R$9,IF(D78>$P$7,$R$8,IF(D78>$P$6,$R$7,IF(D78>$P$5,$R$6,IF(D78>$P$4,$R$5,IF(D78>$P$3,$R$4,IF(D78>$P$2,$R$3,$R$2))))))))) -> 0.00079571759 | M78: =D78*L78 -> 1597.1747 | N78: =K78+M78 -> 2180.2847
A79: Ballistics | B79: 1 | C79: 12 | D79: 2384 | E79: 600 | F79: 800 | H79: 500 | I79: 5000 | J79: =SUM(I79:I79) -> 5000 | K79: =IF(J79>$P$14,$R$15,IF(J79>$P$13,$R$14,$R$13))*J79 -> 1.25 | L79: =IF(D79>$P$10,$R$11,IF(D79>$P$9,$R$10,IF(D79>$P$8,$R$9,IF(D79>$P$7,$R$8,IF(D79>$P$6,$R$7,IF(D79>$P$5,$R$6,IF(D79>$P$4,$R$5,IF(D79>$P$3,$R$4,IF(D79>$P$2,$R$3,$R$2))))))))) -> 0.0027777778 | M79: =D79*L79 -> 6.6222222 | N79: =K79+M79 -> 7.8722222 | T79: 8 | AD79: 4
B80: 2 | C80: 16 | D80: 4827 | E80: =E79*2 -> 1200 | F80: =F79*2 -> 1600 | H80: =H79*2 -> 1000 | I80: =I79*2 -> 10000 | J80: =SUM(I80:I80) -> 10000 | K80: =IF(J80>$P$14,$R$15,IF(J80>$P$13,$R$14,$R$13))*J80 -> 2.5 | L80: =IF(D80>$P$10,$R$11,IF(D80>$P$9,$R$10,IF(D80>$P$8,$R$9,IF(D80>$P$7,$R$8,IF(D80>$P$6,$R$7,IF(D80>$P$5,$R$6,IF(D80>$P$4,$R$5,IF(D80>$P$3,$R$4,IF(D80>$P$2,$R$3,$R$2))))))))) -> 0.0016666667 | M80: =D80*L80 -> 8.045 | N80: =K80+M80 -> 10.545 | T80: 8 | AD80: 4
B81: 3 | C81: 25 | D81: 9775 | E81: =E80*2 -> 2400 | F81: =F80*2 -> 3200 | H81: =H80*2 -> 2000 | I81: =I80*2 -> 20000 | J81: =SUM(I81:I81) -> 20000 | K81: =IF(J81>$P$14,$R$15,IF(J81>$P$13,$R$14,$R$13))*J81 -> 5 | L81: =IF(D81>$P$10,$R$11,IF(D81>$P$9,$R$10,IF(D81>$P$8,$R$9,IF(D81>$P$7,$R$8,IF(D81>$P$6,$R$7,IF(D81>$P$5,$R$6,IF(D81>$P$4,$R$5,IF(D81>$P$3,$R$4,IF(D81>$P$2,$R$3,$R$2))))))))) -> 0.0013888889 | M81: =D81*L81 -> 13.576389 | N81: =K81+M81 -> 18.576389 | T81: 8 | AD81: 4
B82: 4 | C82: 53 | D82: 19796 | E82: =E81*2 -> 4800 | F82: =F81*2 -> 6400 | H82: =H81*2 -> 4000 | I82: =I81*2 -> 40000 | J82: =SUM(I82:I82) -> 40000 | K82: =IF(J82>$P$14,$R$15,IF(J82>$P$13,$R$14,$R$13))*J82 -> 10 | L82: =IF(D82>$P$10,$R$11,IF(D82>$P$9,$R$10,IF(D82>$P$8,$R$9,IF(D82>$P$7,$R$8,IF(D82>$P$6,$R$7,IF(D82>$P$5,$R$6,IF(D82>$P$4,$R$5,IF(D82>$P$3,$R$4,IF(D82>$P$2,$R$3,$R$2))))))))) -> 0.0013888889 | M82: =D82*L82 -> 27.494444 | N82: =K82+M82 -> 37.494444 | T82: 8 | AD82: 4
B83: 5 | C83: 89 | D83: 40087 | E83: =E82*2 -> 9600 | F83: =F82*2 -> 12800 | H83: =H82*2 -> 8000 | I83: =I82*2 -> 80000 | J83: =SUM(I83:I83) -> 80000 | K83: =IF(J83>$P$14,$R$15,IF(J83>$P$13,$R$14,$R$13))*J83 -> 20 | L83: =IF(D83>$P$10,$R$11,IF(D83>$P$9,$R$10,IF(D83>$P$8,$R$9,IF(D83>$P$7,$R$8,IF(D83>$P$6,$R$7,IF(D83>$P$5,$R$6,IF(D83>$P$4,$R$5,IF(D83>$P$3,$R$4,IF(D83>$P$2,$R$3,$R$2))))))))) -> 0.0012037037 | M83: =D83*L83 -> 48.25287 | N83: =K83+M83 -> 68.25287 | T83: 10 | AD83: 4
B84: 6 | C84: 164 | D84: 81176 | E84: =E83*2 -> 19200 | F84: =F83*2 -> 25600 | H84: =H83*2 -> 16000 | I84: =I83*2 -> 160000 | J84: =SUM(I84:I84) -> 160000 | K84: =IF(J84>$P$14,$R$15,IF(J84>$P$13,$R$14,$R$13))*J84 -> 35.2 | L84: =IF(D84>$P$10,$R$11,IF(D84>$P$9,$R$10,IF(D84>$P$8,$R$9,IF(D84>$P$7,$R$8,IF(D84>$P$6,$R$7,IF(D84>$P$5,$R$6,IF(D84>$P$4,$R$5,IF(D84>$P$3,$R$4,IF(D84>$P$2,$R$3,$R$2))))))))) -> 0.001099537 | M84: =D84*L84 -> 89.256019 | N84: =K84+M84 -> 124.45602 | T84: 12 | AD84: 4
B85: 7 | C85: 289 | D85: 164382 | E85: =E84*2 -> 38400 | F85: =F84*2 -> 51200 | H85: =H84*2 -> 32000 | I85: =I84*2 -> 320000 | J85: =SUM(I85:I85) -> 320000 | K85: =IF(J85>$P$14,$R$15,IF(J85>$P$13,$R$14,$R$13))*J85 -> 60.8 | L85: =IF(D85>$P$10,$R$11,IF(D85>$P$9,$R$10,IF(D85>$P$8,$R$9,IF(D85>$P$7,$R$8,IF(D85>$P$6,$R$7,IF(D85>$P$5,$R$6,IF(D85>$P$4,$R$5,IF(D85>$P$3,$R$4,IF(D85>$P$2,$R$3,$R$2))))))))) -> 0.00097222222 | M85: =D85*L85 -> 159.81583 | N85: =K85+M85 -> 220.61583 | T85: 14 | AD85: 4
B86: 8 | C86: 563 | D86: 332875 | E86: =E85*2 -> 76800 | F86: =F85*2 -> 102400 | H86: =H85*2 -> 64000 | I86: =I85*2 -> 640000 | J86: =SUM(I86:I86) -> 640000 | K86: =IF(J86>$P$14,$R$15,IF(J86>$P$13,$R$14,$R$13))*J86 -> 121.6 | L86: =IF(D86>$P$10,$R$11,IF(D86>$P$9,$R$10,IF(D86>$P$8,$R$9,IF(D86>$P$7,$R$8,IF(D86>$P$6,$R$7,IF(D86>$P$5,$R$6,IF(D86>$P$4,$R$5,IF(D86>$P$3,$R$4,IF(D86>$P$2,$R$3,$R$2))))))))) -> 0.00079571759 | M86: =D86*L86 -> 264.87449 | N86: =K86+M86 -> 386.47449 | T86: 16 | AD86: 4
B87: 9 | C87: 1063 | D87: 674072 | E87: =E86*2 -> 153600 | F87: =F86*2 -> 204800 | H87: =H86*2 -> 128000 | I87: =I86*2 -> 1280000 | J87: =SUM(I87:I87) -> 1280000 | K87: =IF(J87>$P$14,$R$15,IF(J87>$P$13,$R$14,$R$13))*J87 -> 243.2 | L87: =IF(D87>$P$10,$R$11,IF(D87>$P$9,$R$10,IF(D87>$P$8,$R$9,IF(D87>$P$7,$R$8,IF(D87>$P$6,$R$7,IF(D87>$P$5,$R$6,IF(D87>$P$4,$R$5,IF(D87>$P$3,$R$4,IF(D87>$P$2,$R$3,$R$2))))))))) -> 0.00079571759 | M87: =D87*L87 -> 536.37095 | N87: =K87+M87 -> 779.57095 | T87: 18 | AD87: 4
B88: 10 | C88: 1298 | D88: 1364996 | E88: =E87*2 -> 307200 | F88: =F87*2 -> 409600 | H88: =H87*2 -> 256000 | I88: =I87*2 -> 2560000 | J88: =SUM(I88:I88) -> 2560000 | K88: =IF(J88>$P$14,$R$15,IF(J88>$P$13,$R$14,$R$13))*J88 -> 486.4 | L88: =IF(D88>$P$10,$R$11,IF(D88>$P$9,$R$10,IF(D88>$P$8,$R$9,IF(D88>$P$7,$R$8,IF(D88>$P$6,$R$7,IF(D88>$P$5,$R$6,IF(D88>$P$4,$R$5,IF(D88>$P$3,$R$4,IF(D88>$P$2,$R$3,$R$2))))))))) -> 0.00079571759 | M88: =D88*L88 -> 1086.1513 | N88: =K88+M88 -> 1572.5513 | T88: 20 | AD88: 4
B89: total | C89: =SUM(C79:C88) -> 3572 | D89: =SUM(D79:D88) -> 2694370 | E89: =SUM(E79:E88) -> 613800 | F89: =SUM(F79:F88) -> 818400 | G89: =SUM(G79:G88) -> 0 | H89: =SUM(H79:H88) -> 511500 | I89: =SUM(I79:I88) -> 5115000 | J89: =SUM(I89:I89) -> 5115000 | K89: =IF(J89>$P$14,$R$15,IF(J89>$P$13,$R$14,$R$13))*J89 -> 971.85 | L89: =IF(D89>$P$10,$R$11,IF(D89>$P$9,$R$10,IF(D89>$P$8,$R$9,IF(D89>$P$7,$R$8,IF(D89>$P$6,$R$7,IF(D89>$P$5,$R$6,IF(D89>$P$4,$R$5,IF(D89>$P$3,$R$4,IF(D89>$P$2,$R$3,$R$2))))))))) -> 0.00079571759 | M89: =D89*L89 -> 2143.9576 | N89: =K89+M89 -> 3115.8076 | AD89: 4
A90: Medicine | B90: 1 | C90: 11 | D90: 1776 | G90: 1500 | I90: 3600 | J90: =SUM(I90:I90) -> 3600 | K90: =IF(J90>$P$14,$R$15,IF(J90>$P$13,$R$14,$R$13))*J90 -> 0.9 | L90: =IF(D90>$P$10,$R$11,IF(D90>$P$9,$R$10,IF(D90>$P$8,$R$9,IF(D90>$P$7,$R$8,IF(D90>$P$6,$R$7,IF(D90>$P$5,$R$6,IF(D90>$P$4,$R$5,IF(D90>$P$3,$R$4,IF(D90>$P$2,$R$3,$R$2))))))))) -> 0.0027777778 | M90: =D90*L90 -> 4.9333333 | N90: =K90+M90 -> 5.8333333 | T90: 12
B91: 2 | C91: 15 | D91: 3596 | G91: =G90*2 -> 3000 | I91: =I90*2 -> 7200 | J91: =SUM(I91:I91) -> 7200 | K91: =IF(J91>$P$14,$R$15,IF(J91>$P$13,$R$14,$R$13))*J91 -> 1.8 | L91: =IF(D91>$P$10,$R$11,IF(D91>$P$9,$R$10,IF(D91>$P$8,$R$9,IF(D91>$P$7,$R$8,IF(D91>$P$6,$R$7,IF(D91>$P$5,$R$6,IF(D91>$P$4,$R$5,IF(D91>$P$3,$R$4,IF(D91>$P$2,$R$3,$R$2))))))))) -> 0.0027777778 | M91: =D91*L91 -> 9.9888889 | N91: =K91+M91 -> 11.788889 | T91: 12
B92: 3 | C92: 22 | D92: 7282 | G92: =G91*2 -> 6000 | I92: =I91*2 -> 14400 | J92: =SUM(I92:I92) -> 14400 | K92: =IF(J92>$P$14,$R$15,IF(J92>$P$13,$R$14,$R$13))*J92 -> 3.6 | L92: =IF(D92>$P$10,$R$11,IF(D92>$P$9,$R$10,IF(D92>$P$8,$R$9,IF(D92>$P$7,$R$8,IF(D92>$P$6,$R$7,IF(D92>$P$5,$R$6,IF(D92>$P$4,$R$5,IF(D92>$P$3,$R$4,IF(D92>$P$2,$R$3,$R$2))))))))) -> 0.0016666667 | M92: =D92*L92 -> 12.136667 | N92: =K92+M92 -> 15.736667 | T92: 12
B93: 4 | C93: 32 | D93: 14747 | G93: =G92*2 -> 12000 | I93: =I92*2 -> 28800 | J93: =SUM(I93:I93) -> 28800 | K93: =IF(J93>$P$14,$R$15,IF(J93>$P$13,$R$14,$R$13))*J93 -> 7.2 | L93: =IF(D93>$P$10,$R$11,IF(D93>$P$9,$R$10,IF(D93>$P$8,$R$9,IF(D93>$P$7,$R$8,IF(D93>$P$6,$R$7,IF(D93>$P$5,$R$6,IF(D93>$P$4,$R$5,IF(D93>$P$3,$R$4,IF(D93>$P$2,$R$3,$R$2))))))))) -> 0.0013888889 | M93: =D93*L93 -> 20.481944 | N93: =K93+M93 -> 27.681944 | T93: 12
B94: 5 | C94: 69 | D94: 29863 | G94: =G93*2 -> 24000 | I94: =I93*2 -> 57600 | J94: =SUM(I94:I94) -> 57600 | K94: =IF(J94>$P$14,$R$15,IF(J94>$P$13,$R$14,$R$13))*J94 -> 14.4 | L94: =IF(D94>$P$10,$R$11,IF(D94>$P$9,$R$10,IF(D94>$P$8,$R$9,IF(D94>$P$7,$R$8,IF(D94>$P$6,$R$7,IF(D94>$P$5,$R$6,IF(D94>$P$4,$R$5,IF(D94>$P$3,$R$4,IF(D94>$P$2,$R$3,$R$2))))))))) -> 0.0012037037 | M94: =D94*L94 -> 35.946204 | N94: =K94+M94 -> 50.346204 | T94: 12
B95: 6 | C95: 133 | D95: 60473 | G95: =G94*2 -> 48000 | I95: =I94*2 -> 115200 | J95: =SUM(I95:I95) -> 115200 | K95: =IF(J95>$P$14,$R$15,IF(J95>$P$13,$R$14,$R$13))*J95 -> 25.344 | L95: =IF(D95>$P$10,$R$11,IF(D95>$P$9,$R$10,IF(D95>$P$8,$R$9,IF(D95>$P$7,$R$8,IF(D95>$P$6,$R$7,IF(D95>$P$5,$R$6,IF(D95>$P$4,$R$5,IF(D95>$P$3,$R$4,IF(D95>$P$2,$R$3,$R$2))))))))) -> 0.001099537 | M95: =D95*L95 -> 66.492303 | N95: =K95+M95 -> 91.836303 | T95: 12
B96: 7 | C96: 242 | D96: 122459 | G96: =G95*2 -> 96000 | I96: =I95*2 -> 230400 | J96: =SUM(I96:I96) -> 230400 | K96: =IF(J96>$P$14,$R$15,IF(J96>$P$13,$R$14,$R$13))*J96 -> 50.688 | L96: =IF(D96>$P$10,$R$11,IF(D96>$P$9,$R$10,IF(D96>$P$8,$R$9,IF(D96>$P$7,$R$8,IF(D96>$P$6,$R$7,IF(D96>$P$5,$R$6,IF(D96>$P$4,$R$5,IF(D96>$P$3,$R$4,IF(D96>$P$2,$R$3,$R$2))))))))) -> 0.00097222222 | M96: =D96*L96 -> 119.05736 | N96: =K96+M96 -> 169.74536 | T96: 14
B97: 8 | C97: 434 | D97: 247980 | G97: =G96*2 -> 192000 | I97: =I96*2 -> 460800 | J97: =SUM(I97:I97) -> 460800 | K97: =IF(J97>$P$14,$R$15,IF(J97>$P$13,$R$14,$R$13))*J97 -> 87.552 | L97: =IF(D97>$P$10,$R$11,IF(D97>$P$9,$R$10,IF(D97>$P$8,$R$9,IF(D97>$P$7,$R$8,IF(D97>$P$6,$R$7,IF(D97>$P$5,$R$6,IF(D97>$P$4,$R$5,IF(D97>$P$3,$R$4,IF(D97>$P$2,$R$3,$R$2))))))))) -> 0.00079571759 | M97: =D97*L97 -> 197.32205 | N97: =K97+M97 -> 284.87405 | T97: 16
B98: 9 | C98: 890 | D98: 502161 | G98: =G97*2 -> 384000 | I98: =I97*2 -> 921600 | J98: =SUM(I98:I98) -> 921600 | K98: =IF(J98>$P$14,$R$15,IF(J98>$P$13,$R$14,$R$13))*J98 -> 175.104 | L98: =IF(D98>$P$10,$R$11,IF(D98>$P$9,$R$10,IF(D98>$P$8,$R$9,IF(D98>$P$7,$R$8,IF(D98>$P$6,$R$7,IF(D98>$P$5,$R$6,IF(D98>$P$4,$R$5,IF(D98>$P$3,$R$4,IF(D98>$P$2,$R$3,$R$2))))))))) -> 0.00079571759 | M98: =D98*L98 -> 399.57834 | N98: =K98+M98 -> 574.68234 | T98: 18
B99: 10 | C99: 1076 | D99: 1016876 | G99: =G98*2 -> 768000 | I99: =I98*2 -> 1843200 | J99: =SUM(I99:I99) -> 1843200 | K99: =IF(J99>$P$14,$R$15,IF(J99>$P$13,$R$14,$R$13))*J99 -> 350.208 | L99: =IF(D99>$P$10,$R$11,IF(D99>$P$9,$R$10,IF(D99>$P$8,$R$9,IF(D99>$P$7,$R$8,IF(D99>$P$6,$R$7,IF(D99>$P$5,$R$6,IF(D99>$P$4,$R$5,IF(D99>$P$3,$R$4,IF(D99>$P$2,$R$3,$R$2))))))))) -> 0.00079571759 | M99: =D99*L99 -> 809.14612 | N99: =K99+M99 -> 1159.3541 | T99: 20
B100: total | C100: =SUM(C90:C99) -> 2924 | D100: =SUM(D90:D99) -> 2007213 | E100: =SUM(E90:E99) -> 0 | F100: =SUM(F90:F99) -> 0 | G100: =SUM(G90:G99) -> 1534500 | H100: =SUM(H90:H99) -> 0 | I100: =SUM(I90:I99) -> 3682800 | J100: =SUM(I100:I100) -> 3682800 | K100: =IF(J100>$P$14,$R$15,IF(J100>$P$13,$R$14,$R$13))*J100 -> 699.732 | L100: =IF(D100>$P$10,$R$11,IF(D100>$P$9,$R$10,IF(D100>$P$8,$R$9,IF(D100>$P$7,$R$8,IF(D100>$P$6,$R$7,IF(D100>$P$5,$R$6,IF(D100>$P$4,$R$5,IF(D100>$P$3,$R$4,IF(D100>$P$2,$R$3,$R$2))))))))) -> 0.00079571759 | M100: =D100*L100 -> 1597.1747 | N100: =K100+M100 -> 2296.9067
...

Sheet 将领
A1: 建筑等级 | B1: 刷新出将领数量 | D1: 将领lv | E1: 需要取胜次数 | F1: 攻击加成百分比 | G1: 防御加成百分比 | H1: 花费价钱 | I1: 出现权重 | J1: 几率 | K1: 20级期望出现个数
A2: 1 | B2: 1 | D2: 1 | E2: 0 | F2: 5 | G2: 10 | H2: 1000 | I2: 50 | J2: =I2/$I$22 -> 0.5 | K2: =$B$21*J2 -> 2.5
A3: 2 | B3: 1 | D3: 2 | E3: 3 | F3: 5.5 | G3: 10.5 | H3: 2000 | I3: 20 | J3: =I3/$I$22 -> 0.2 | K3: =$B$21*J3 -> 1
A4: 3 | B4: 1 | D4: 3 | E4: 8 | F4: 6 | G4: 11 | H4: 3000 | I4: 10 | J4: =I4/$I$22 -> 0.1 | K4: =$B$21*J4 -> 0.5
A5: 4 | B5: 1 | D5: 4 | E5: 15 | F5: 6.5 | G5: 11.5 | H5: 4000 | I5: 5 | J5: =I5/$I$22 -> 0.05 | K5: =$B$21*J5 -> 0.25
A6: 5 | B6: 1 | D6: 5 | E6: 24 | F6: 7 | G6: 12 | H6: 5000 | I6: 4 | J6: =I6/$I$22 -> 0.04 | K6: =$B$21*J6 -> 0.2
A7: 6 | B7: 1 | D7: 6 | E7: 35 | F7: 7.5 | G7: 12.5 | H7: 6000 | I7: 2 | J7: =I7/$I$22 -> 0.02 | K7: =$B$21*J7 -> 0.1
A8: 7 | B8: 2 | D8: 7 | E8: 48 | F8: 8 | G8: 13 | H8: 7000 | I8: 1.8 | J8: =I8/$I$22 -> 0.018 | K8: =$B$21*J8 -> 0.09
A9: 8 | B9: 2 | D9: 8 | E9: 63 | F9: 8.5 | G9: 13.5 | H9: 8000 | I9: 1.5 | J9: =I9/$I$22 -> 0.015 | K9: =$B$21*J9 -> 0.075
A10: 9 | B10: 2 | D10: 9 | E10: 80 | F10: 9 | G10: 14 | H10: 9000 | I10: 1.25 | J10: =I10/$I$22 -> 0.0125 | K10: =$B$21*J10 -> 0.0625
A11: 10 | B11: 2 | D11: 10 | E11: 99 | F11: 9.5 | G11: 14.5 | H11: 10000 | I11: 1 | J11: =I11/$I$22 -> 0.01 | K11: =$B$21*J11 -> 0.05
A12: 11 | B12: 3 | D12: 11 | E12: 120 | F12: 10 | G12: 15 | H12: 12000 | I12: 0.8 | J12: =I12/$I$22 -> 0.008 | K12: =$B$21*J12 -> 0.04
A13: 12 | B13: 3 | D13: 12 | E13: 143 | F13: 11 | G13: 16 | H13: 14000 | I13: 0.7 | J13: =I13/$I$22 -> 0.007 | K13: =$B$21*J13 -> 0.035
... A21: 20 | B21: 5 | D21: 20 | E21: 200000 | F21: 30 | G21: 35 | H21: 500000 | I21: 0.02 | J21: =I21/$I$22 -> 0.0002 | K21: =$B$21*J21 -> 0.001
H22: total | I22: =SUM(I2:I21) -> 100 | J22: =SUM(J2:J21) -> 1 | K22: =SUM(K2:K21) -> 5

Sheet 造兵时间
A1: 1 | B1: =$F$3/A1 -> 2000 | E1: 建造单位 | F1: Fangtooth | H1: Conscript | J1: 兵营数量 | K1: 兵营等级 | L1: v1 | M1: v2 | N1: v1时间 | O1: v2时间
A2: 2 | B2: =$F$3/A2 -> 1000 | E2: 建造数量 | F2: 1 | H2: Porter | I2: 1 | J2: 1 | K2: 1 | L2: =0.9*J2+0.05*K2 -> 0.95 | M2: =0.45+0.4*J2+0.1*K2 -> 0.95 | N2: =1/L2 -> 1.0526316 | O2: =1/M2 -> 1.0526316
A3: 3 | B3: =$F$3/A3 -> 666.66667 | E3: 单位基础建造时间 | F3: =F2*VLOOKUP(F1,兵种!A:K,11,FALSE) -> 2000 | H3: Spy | I3: 2 | J3: 1 | K3: 2 | L3: =0.9*J3+0.05*K3 -> 1 | M3: =0.45+0.4*J3+0.1*K3 -> 1.05 | N3: =1/L3 -> 1 | O3: =1/M3 -> 0.95238095
A4: 4 | B4: =$F$3/A4 -> 500 | E4: 兵营总数量 | F4: 2 | H4: Halberdsman | I4: 3 | J4: 1 | K4: 3 | L4: =0.9*J4+0.05*K4 -> 1.05 | M4: =0.45+0.4*J4+0.1*K4 -> 1.15 | N4: =1/L4 -> 0.95238095 | O4: =1/M4 -> 0.86956522
A5: 5 | B5: =$F$3/A5 -> 400 | E5: 兵营总等级 | F5: 19 | H5: Minotaur | I5: 4 | J5: 1 | K5: 4 | L5: =0.9*J5+0.05*K5 -> 1.1 | M5: =0.45+0.4*J5+0.1*K5 -> 1.25 | N5: =1/L5 -> 0.90909091 | O5: =1/M5 -> 0.8
A6: 6 | B6: =$F$3/A6 -> 333.33333 | E6: 孵化室等级 | F6: 10 | H6: Longbowman | I6: 5 | J6: 1 | K6: 5 | L6: =0.9*J6+0.05*K6 -> 1.15 | M6: =0.45+0.4*J6+0.1*K6 -> 1.35 | N6: =1/L6 -> 0.86956522 | O6: =1/M6 -> 0.74074074
A7: 7 | B7: =$F$3/A7 -> 285.71429 | E7: 是否是龙兵种 | F7: 0 | H7: SwiftStrikeDragon | I7: 6 | J7: 1 | K7: 6 | L7: =0.9*J7+0.05*K7 -> 1.2 | M7: =0.45+0.4*J7+0.1*K7 -> 1.45 | N7: =1/L7 -> 0.83333333 | O7: =1/M7 -> 0.68965517
A8: 8 | B8: =$F$3/A8 -> 250 | E8: 系数 | F8: =(0.9*F4+F5*0.05)*(1+0.005*F6*F7) -> 2.75 | H8: BattleDragon | I8: 7 | J8: 1 | K8: 7 | L8: =0.9*J8+0.05*K8 -> 1.25 | M8: =0.45+0.4*J8+0.1*K8 -> 1.55 | N8: =1/L8 -> 0.8 | O8: =1/M8 -> 0.64516129
A9: 9 | B9: =$F$3/A9 -> 222.22222 | E9: 修正后时间 | F9: =MAX(10,F3/F8) -> 727.27273 | H9: ArmoredTransport | I9: 8 | J9: 1 | K9: 8 | L9: =0.9*J9+0.05*K9 -> 1.3 | M9: =0.45+0.4*J9+0.1*K9 -> 1.65 | N9: =1/L9 -> 0.76923077 | O9: =1/M9 -> 0.60606061
A10: 10 | B10: =$F$3/A10 -> 200 | F10: =F9/3600 -> 0.2020202 | H10: Giant | I10: 9 | J10: 1 | K10: 9 | L10: =0.9*J10+0.05*K10 -> 1.35 | M10: =0.45+0.4*J10+0.1*K10 -> 1.75 | N10: =1/L10 -> 0.74074074 | O10: =1/M10 -> 0.57142857
A11: 11 | B11: =$F$3/A11 -> 181.81818 | H11: FireMirror | I11: 10 | J11: 1 | K11: 10 | L11: =0.9*J11+0.05*K11 -> 1.4 | M11: =0.45+0.4*J11+0.1*K11 -> 1.85 | N11: =1/L11 -> 0.71428571 | O11: =1/M11 -> 0.54054054
A12: 12 | B12: =$F$3/A12 -> 166.66667 | H12: Fangtooth | I12: 11 | J12: 1 | K12: 11 | L12: =0.9*J12+0.05*K12 -> 1.45 | M12: =0.45+0.4*J12+0.1*K12 -> 1.95 | N12: =1/L12 -> 0.68965517 | O12: =1/M12 -> 0.51282051
A13: 13 | B13: =$F$3/A13 -> 153.84615 | E13: 兵营数量 | F13: 12 | I13: 12 | J13: 1 | K13: 12 | L13: =0.9*J13+0.05*K13 -> 1.5 | M13: =0.45+0.4*J13+0.1*K13 -> 2.05 | N13: =1/L13 -> 0.66666667 | O13: =1/M13 -> 0.48780488
A14: 14 | B14: =$F$3/A14 -> 142.85714 | E14: 兵营等级 | F14: 240 | I14: 13 | J14: 1 | K14: 13 | L14: =0.9*J14+0.05*K14 -> 1.55 | M14: =0.45+0.4*J14+0.1*K14 -> 2.15 | N14: =1/L14 -> 0.64516129 | O14: =1/M14 -> 0.46511628
A15: 15 | B15: =$F$3/A15 -> 133.33333 | I15: 14 | J15: 1 | K15: 14 | L15: =0.9*J15+0.05*K15 -> 1.6 | M15: =0.45+0.4*J15+0.1*K15 -> 2.25 | N15: =1/L15 -> 0.625 | O15: =1/M15 -> 0.44444444
A16: 16 | B16: =$F$3/A16 -> 125 | I16: 15 | J16: 1 | K16: 15 | L16: =0.9*J16+0.05*K16 -> 1.65 | M16: =0.45+0.4*J16+0.1*K16 -> 2.35 | N16: =1/L16 -> 0.60606061 | O16: =1/M16 -> 0.42553191
A17: 17 | B17: =$F$3/A17 -> 117.64706 | E17: v1 | F17: 0.9*兵营数量+0.05*兵营等级 | I17: 16 | J17: 1 | K17: 16 | L17: =0.9*J17+0.05*K17 -> 1.7 | M17: =0.45+0.4*J17+0.1*K17 -> 2.45 | N17: =1/L17 -> 0.58823529 | O17: =1/M17 -> 0.40816327
A18: 18 | B18: =$F$3/A18 -> 111.11111 | E18: v2 | F18: 0.45+0.4*兵营数量+0.1*兵营等级 | I18: 17 | J18: 1 | K18: 17 | L18: =0.9*J18+0.05*K18 -> 1.75 | M18: =0.45+0.4*J18+0.1*K18 -> 2.55 | N18: =1/L18 -> 0.57142857 | O18: =1/M18 -> 0.39215686
A19: 19 | B19: =$F$3/A19 -> 105.26316 | I19: 18 | J19: 1 | K19: 18 | L19: =0.9*J19+0.05*K19 -> 1.8 | M19: =0.45+0.4*J19+0.1*K19 -> 2.65 | N19: =1/L19 -> 0.55555556 | O19: =1/M19 -> 0.37735849
A20: 20 | B20: =$F$3/A20 -> 100 | I20: 19 | J20: 1 | K20: 19 | L20: =0.9*J20+0.05*K20 -> 1.85 | M20: =0.45+0.4*J20+0.1*K20 -> 2.75 | N20: =1/L20 -> 0.54054054 | O20: =1/M20 -> 0.36363636
A21: 21 | B21: =$F$3/A21 -> 95.238095 | I21: 20 | J21: 1 | K21: 20 | L21: =0.9*J21+0.05*K21 -> 1.9 | M21: =0.45+0.4*J21+0.1*K21 -> 2.85 | N21: =1/L21 -> 0.52631579 | O21: =1/M21 -> 0.35087719
A22: 22 | B22: =$F$3/A22 -> 90.909091 | I22: =I2 -> 1 | J22: =J2+1 -> 2 | K22: =J22 -> 2 | L22: =0.9*J22+0.05*K22 -> 1.9 | M22: =0.45+0.4*J22+0.1*K22 -> 1.45 | N22: =1/L22 -> 0.52631579 | O22: =1/M22 -> 0.68965517
A23: 23 | B23: =$F$3/A23 -> 86.956522 | I23: =I3 -> 2 | J23: =J3+1 -> 2 | K23: =K22+J22 -> 4 | L23: =0.9*J23+0.05*K23 -> 2 | M23: =0.45+0.4*J23+0.1*K23 -> 1.65 | N23: =1/L23 -> 0.5 | O23: =1/M23 -> 0.60606061
A24: 24 | B24: =$F$3/A24 -> 83.333333 | F24: 727 | I24: =I4 -> 3 | J24: =J4+1 -> 2 | K24: =K23+J23 -> 6 | L24: =0.9*J24+0.05*K24 -> 2.1 | M24: =0.45+0.4*J24+0.1*K24 -> 1.85 | N24: =1/L24 -> 0.47619048 | O24: =1/M24 -> 0.54054054
A25: 25 | B25: =$F$3/A25 -> 80 | I25: =I5 -> 4 | J25: =J5+1 -> 2 | K25: =K24+J24 -> 8 | L25: =0.9*J25+0.05*K25 -> 2.2 | M25: =0.45+0.4*J25+0.1*K25 -> 2.05 | N25: =1/L25 -> 0.45454545 | O25: =1/M25 -> 0.48780488
A26: 26 | B26: =$F$3/A26 -> 76.923077 | I26: =I6 -> 5 | J26: =J6+1 -> 2 | K26: =K25+J25 -> 10 | L26: =0.9*J26+0.05*K26 -> 2.3 | M26: =0.45+0.4*J26+0.1*K26 -> 2.25 | N26: =1/L26 -> 0.43478261 | O26: =1/M26 -> 0.44444444
A27: 27 | B27: =$F$3/A27 -> 74.074074 | I27: =I7 -> 6 | J27: =J7+1 -> 2 | K27: =K26+J26 -> 12 | L27: =0.9*J27+0.05*K27 -> 2.4 | M27: =0.45+0.4*J27+0.1*K27 -> 2.45 | N27: =1/L27 -> 0.41666667 | O27: =1/M27 -> 0.40816327
A28: 28 | B28: =$F$3/A28 -> 71.428571 | I28: =I8 -> 7 | J28: =J8+1 -> 2 | K28: =K27+J27 -> 14 | L28: =0.9*J28+0.05*K28 -> 2.5 | M28: =0.45+0.4*J28+0.1*K28 -> 2.65 | N28: =1/L28 -> 0.4 | O28: =1/M28 -> 0.37735849
A29: 29 | B29: =$F$3/A29 -> 68.965517 | I29: =I9 -> 8 | J29: =J9+1 -> 2 | K29: =K28+J28 -> 16 | L29: =0.9*J29+0.05*K29 -> 2.6 | M29: =0.45+0.4*J29+0.1*K29 -> 2.85 | N29: =1/L29 -> 0.38461538 | O29: =1/M29 -> 0.35087719
A30: 30 | B30: =$F$3/A30 -> 66.666667 | I30: =I10 -> 9 | J30: =J10+1 -> 2 | K30: =K29+J29 -> 18 | L30: =0.9*J30+0.05*K30 -> 2.7 | M30: =0.45+0.4*J30+0.1*K30 -> 3.05 | N30: =1/L30 -> 0.37037037 | O30: =1/M30 -> 0.32786885
A31: 31 | B31: =$F$3/A31 -> 64.516129 | I31: =I11 -> 10 | J31: =J11+1 -> 2 | K31: =K30+J30 -> 20 | L31: =0.9*J31+0.05*K31 -> 2.8 | M31: =0.45+0.4*J31+0.1*K31 -> 3.25 | N31: =1/L31 -> 0.35714286 | O31: =1/M31 -> 0.30769231
A32: 32 | B32: =$F$3/A32 -> 62.5 | I32: =I12 -> 11 | J32: =J12+1 -> 2 | K32: =K31+J31 -> 22 | L32: =0.9*J32+0.05*K32 -> 2.9 | M32: =0.45+0.4*J32+0.1*K32 -> 3.45 | N32: =1/L32 -> 0.34482759 | O32: =1/M32 -> 0.28985507
A33: 33 | B33: =$F$3/A33 -> 60.606061 | I33: =I13 -> 12 | J33: =J13+1 -> 2 | K33: =K32+J32 -> 24 | L33: =0.9*J33+0.05*K33 -> 3 | M33: =0.45+0.4*J33+0.1*K33 -> 3.65 | N33: =1/L33 -> 0.33333333 | O33: =1/M33 -> 0.2739726
A34: 34 | B34: =$F$3/A34 -> 58.823529 | I34: =I14 -> 13 | J34: =J14+1 -> 2 | K34: =K33+J33 -> 26 | L34: =0.9*J34+0.05*K34 -> 3.1 | M34: =0.45+0.4*J34+0.1*K34 -> 3.85 | N34: =1/L34 -> 0.32258065 | O34: =1/M34 -> 0.25974026
A35: 35 | B35: =$F$3/A35 -> 57.142857 | I35: =I15 -> 14 | J35: =J15+1 -> 2 | K35: =K34+J34 -> 28 | L35: =0.9*J35+0.05*K35 -> 3.2 | M35: =0.45+0.4*J35+0.1*K35 -> 4.05 | N35: =1/L35 -> 0.3125 | O35: =1/M35 -> 0.24691358
A36: 36 | B36: =$F$3/A36 -> 55.555556 | I36: =I16 -> 15 | J36: =J16+1 -> 2 | K36: =K35+J35 -> 30 | L36: =0.9*J36+0.05*K36 -> 3.3 | M36: =0.45+0.4*J36+0.1*K36 -> 4.25 | N36: =1/L36 -> 0.3030303 | O36: =1/M36 -> 0.23529412
... A41: 41 | B41: =$F$3/A41 -> 48.780488 | I41: =I21 -> 20 | J41: =J21+1 -> 2 | K41: =K40+J40 -> 40 | L41: =0.9*J41+0.05*K41 -> 3.8 | M41: =0.45+0.4*J41+0.1*K41 -> 5.25 | N41: =1/L41 -> 0.26315789 | O41: =1/M41 -> 0.19047619
A42: 42 | B42: =$F$3/A42 -> 47.619048 | I42: =I22 -> 1 | J42: =J22+1 -> 3 | K42: =J42 -> 3 | L42: =0.9*J42+0.05*K42 -> 2.85 | M42: =0.45+0.4*J42+0.1*K42 -> 1.95 | N42: =1/L42 -> 0.35087719 | O42: =1/M42 -> 0.51282051
A43: 43 | B43: =$F$3/A43 -> 46.511628 | I43: =I23 -> 2 | J43: =J23+1 -> 3 | K43: =K42+J42 -> 6 | L43: =0.9*J43+0.05*K43 -> 3 | M43: =0.45+0.4*J43+0.1*K43 -> 2.25 | N43: =1/L43 -> 0.33333333 | O43: =1/M43 -> 0.44444444
A44: 44 | B44: =$F$3/A44 -> 45.454545 | I44: =I24 -> 3 | J44: =J24+1 -> 3 | K44: =K43+J43 -> 9 | L44: =0.9*J44+0.05*K44 -> 3.15 | M44: =0.45+0.4*J44+0.1*K44 -> 2.55 | N44: =1/L44 -> 0.31746032 | O44: =1/M44 -> 0.39215686
A45: 45 | B45: =$F$3/A45 -> 44.444444 | I45: =I25 -> 4 | J45: =J25+1 -> 3 | K45: =K44+J44 -> 12 | L45: =0.9*J45+0.05*K45 -> 3.3 | M45: =0.45+0.4*J45+0.1*K45 -> 2.85 | N45: =1/L45 -> 0.3030303 | O45: =1/M45 -> 0.35087719
A46: 46 | B46: =$F$3/A46 -> 43.478261 | I46: =I26 -> 5 | J46: =J26+1 -> 3 | K46: =K45+J45 -> 15 | L46: =0.9*J46+0.05*K46 -> 3.45 | M46: =0.45+0.4*J46+0.1*K46 -> 3.15 | N46: =1/L46 -> 0.28985507 | O46: =1/M46 -> 0.31746032
A47: 47 | B47: =$F$3/A47 -> 42.553191 | I47: =I27 -> 6 | J47: =J27+1 -> 3 | K47: =K46+J46 -> 18 | L47: =0.9*J47+0.05*K47 -> 3.6 | M47: =0.45+0.4*J47+0.1*K47 -> 3.45 | N47: =1/L47 -> 0.27777778 | O47: =1/M47 -> 0.28985507
A48: 48 | B48: =$F$3/A48 -> 41.666667 | I48: =I28 -> 7 | J48: =J28+1 -> 3 | K48: =K47+J47 -> 21 | L48: =0.9*J48+0.05*K48 -> 3.75 | M48: =0.45+0.4*J48+0.1*K48 -> 3.75 | N48: =1/L48 -> 0.26666667 | O48: =1/M48 -> 0.26666667
A49: 49 | B49: =$F$3/A49 -> 40.816327 | I49: =I29 -> 8 | J49: =J29+1 -> 3 | K49: =K48+J48 -> 24 | L49: =0.9*J49+0.05*K49 -> 3.9 | M49: =0.45+0.4*J49+0.1*K49 -> 4.05 | N49: =1/L49 -> 0.25641026 | O49: =1/M49 -> 0.24691358
A50: 50 | B50: =$F$3/A50 -> 40 | I50: =I30 -> 9 | J50: =J30+1 -> 3 | K50: =K49+J49 -> 27 | L50: =0.9*J50+0.05*K50 -> 4.05 | M50: =0.45+0.4*J50+0.1*K50 -> 4.35 | N50: =1/L50 -> 0.24691358 | O50: =1/M50 -> 0.22988506
A51: 51 | B51: =$F$3/A51 -> 39.215686 | I51: =I31 -> 10 | J51: =J31+1 -> 3 | K51: =K50+J50 -> 30 | L51: =0.9*J51+0.05*K51 -> 4.2 | M51: =0.45+0.4*J51+0.1*K51 -> 4.65 | N51: =1/L51 -> 0.23809524 | O51: =1/M51 -> 0.21505376
A52: 52 | B52: =$F$3/A52 -> 38.461538 | I52: =I32 -> 11 | J52: =J32+1 -> 3 | K52: =K51+J51 -> 33 | L52: =0.9*J52+0.05*K52 -> 4.35 | M52: =0.45+0.4*J52+0.1*K52 -> 4.95 | N52: =1/L52 -> 0.22988506 | O52: =1/M52 -> 0.2020202
A53: 53 | B53: =$F$3/A53 -> 37.735849 | I53: =I33 -> 12 | J53: =J33+1 -> 3 | K53: =K52+J52 -> 36 | L53: =0.9*J53+0.05*K53 -> 4.5 | M53: =0.45+0.4*J53+0.1*K53 -> 5.25 | N53: =1/L53 -> 0.22222222 | O53: =1/M53 -> 0.19047619
A54: 54 | B54: =$F$3/A54 -> 37.037037 | I54: =I34 -> 13 | J54: =J34+1 -> 3 | K54: =K53+J53 -> 39 | L54: =0.9*J54+0.05*K54 -> 4.65 | M54: =0.45+0.4*J54+0.1*K54 -> 5.55 | N54: =1/L54 -> 0.21505376 | O54: =1/M54 -> 0.18018018
... A61: 61 | B61: =$F$3/A61 -> 32.786885 | I61: =I41 -> 20 | J61: =J41+1 -> 3 | K61: =K60+J60 -> 60 | L61: =0.9*J61+0.05*K61 -> 5.7 | M61: =0.45+0.4*J61+0.1*K61 -> 7.65 | N61: =1/L61 -> 0.1754386 | O61: =1/M61 -> 0.13071895
A62: 62 | B62: =$F$3/A62 -> 32.258065 | I62: =I42 -> 1 | J62: =J42+1 -> 4 | K62: =J62 -> 4 | L62: =0.9*J62+0.05*K62 -> 3.8 | M62: =0.45+0.4*J62+0.1*K62 -> 2.45 | N62: =1/L62 -> 0.26315789 | O62: =1/M62 -> 0.40816327
A63: 63 | B63: =$F$3/A63 -> 31.746032 | I63: =I43 -> 2 | J63: =J43+1 -> 4 | K63: =K62+J62 -> 8 | L63: =0.9*J63+0.05*K63 -> 4 | M63: =0.45+0.4*J63+0.1*K63 -> 2.85 | N63: =1/L63 -> 0.25 | O63: =1/M63 -> 0.35087719
A64: 64 | B64: =$F$3/A64 -> 31.25 | I64: =I44 -> 3 | J64: =J44+1 -> 4 | K64: =K63+J63 -> 12 | L64: =0.9*J64+0.05*K64 -> 4.2 | M64: =0.45+0.4*J64+0.1*K64 -> 3.25 | N64: =1/L64 -> 0.23809524 | O64: =1/M64 -> 0.30769231
A65: 65 | B65: =$F$3/A65 -> 30.769231 | I65: =I45 -> 4 | J65: =J45+1 -> 4 | K65: =K64+J64 -> 16 | L65: =0.9*J65+0.05*K65 -> 4.4 | M65: =0.45+0.4*J65+0.1*K65 -> 3.65 | N65: =1/L65 -> 0.22727273 | O65: =1/M65 -> 0.2739726
A66: 66 | B66: =$F$3/A66 -> 30.30303 | I66: =I46 -> 5 | J66: =J46+1 -> 4 | K66: =K65+J65 -> 20 | L66: =0.9*J66+0.05*K66 -> 4.6 | M66: =0.45+0.4*J66+0.1*K66 -> 4.05 | N66: =1/L66 -> 0.2173913 | O66: =1/M66 -> 0.24691358
A67: 67 | B67: =$F$3/A67 -> 29.850746 | I67: =I47 -> 6 | J67: =J47+1 -> 4 | K67: =K66+J66 -> 24 | L67: =0.9*J67+0.05*K67 -> 4.8 | M67: =0.45+0.4*J67+0.1*K67 -> 4.45 | N67: =1/L67 -> 0.20833333 | O67: =1/M67 -> 0.2247191
A68: 68 | B68: =$F$3/A68 -> 29.411765 | I68: =I48 -> 7 | J68: =J48+1 -> 4 | K68: =K67+J67 -> 28 | L68: =0.9*J68+0.05*K68 -> 5 | M68: =0.45+0.4*J68+0.1*K68 -> 4.85 | N68: =1/L68 -> 0.2 | O68: =1/M68 -> 0.20618557
A69: 69 | B69: =$F$3/A69 -> 28.985507 | I69: =I49 -> 8 | J69: =J49+1 -> 4 | K69: =K68+J68 -> 32 | L69: =0.9*J69+0.05*K69 -> 5.2 | M69: =0.45+0.4*J69+0.1*K69 -> 5.25 | N69: =1/L69 -> 0.19230769 | O69: =1/M69 -> 0.19047619
A70: 70 | B70: =$F$3/A70 -> 28.571429 | I70: =I50 -> 9 | J70: =J50+1 -> 4 | K70: =K69+J69 -> 36 | L70: =0.9*J70+0.05*K70 -> 5.4 | M70: =0.45+0.4*J70+0.1*K70 -> 5.65 | N70: =1/L70 -> 0.18518519 | O70: =1/M70 -> 0.17699115
A71: 71 | B71: =$F$3/A71 -> 28.169014 | I71: =I51 -> 10 | J71: =J51+1 -> 4 | K71: =K70+J70 -> 40 | L71: =0.9*J71+0.05*K71 -> 5.6 | M71: =0.45+0.4*J71+0.1*K71 -> 6.05 | N71: =1/L71 -> 0.17857143 | O71: =1/M71 -> 0.16528926
A72: 72 | B72: =$F$3/A72 -> 27.777778 | I72: =I52 -> 11 | J72: =J52+1 -> 4 | K72: =K71+J71 -> 44 | L72: =0.9*J72+0.05*K72 -> 5.8 | M72: =0.45+0.4*J72+0.1*K72 -> 6.45 | N72: =1/L72 -> 0.17241379 | O72: =1/M72 -> 0.15503876
A73: 73 | B73: =$F$3/A73 -> 27.39726 | I73: =I53 -> 12 | J73: =J53+1 -> 4 | K73: =K72+J72 -> 48 | L73: =0.9*J73+0.05*K73 -> 6 | M73: =0.45+0.4*J73+0.1*K73 -> 6.85 | N73: =1/L73 -> 0.16666667 | O73: =1/M73 -> 0.1459854
A74: 74 | B74: =$F$3/A74 -> 27.027027 | I74: =I54 -> 13 | J74: =J54+1 -> 4 | K74: =K73+J73 -> 52 | L74: =0.9*J74+0.05*K74 -> 6.2 | M74: =0.45+0.4*J74+0.1*K74 -> 7.25 | N74: =1/L74 -> 0.16129032 | O74: =1/M74 -> 0.13793103
... A81: 81 | B81: =$F$3/A81 -> 24.691358 | I81: =I61 -> 20 | J81: =J61+1 -> 4 | K81: =K80+J80 -> 80 | L81: =0.9*J81+0.05*K81 -> 7.6 | M81: =0.45+0.4*J81+0.1*K81 -> 10.05 | N81: =1/L81 -> 0.13157895 | O81: =1/M81 -> 0.099502488
A82: 82 | B82: =$F$3/A82 -> 24.390244 | I82: =I62 -> 1 | J82: =J62+1 -> 5 | K82: =J82 -> 5 | L82: =0.9*J82+0.05*K82 -> 4.75 | M82: =0.45+0.4*J82+0.1*K82 -> 2.95 | N82: =1/L82 -> 0.21052632 | O82: =1/M82 -> 0.33898305
A83: 83 | B83: =$F$3/A83 -> 24.096386 | I83: =I63 -> 2 | J83: =J63+1 -> 5 | K83: =K82+J82 -> 10 | L83: =0.9*J83+0.05*K83 -> 5 | M83: =0.45+0.4*J83+0.1*K83 -> 3.45 | N83: =1/L83 -> 0.2 | O83: =1/M83 -> 0.28985507
A84: 84 | B84: =$F$3/A84 -> 23.809524 | I84: =I64 -> 3 | J84: =J64+1 -> 5 | K84: =K83+J83 -> 15 | L84: =0.9*J84+0.05*K84 -> 5.25 | M84: =0.45+0.4*J84+0.1*K84 -> 3.95 | N84: =1/L84 -> 0.19047619 | O84: =1/M84 -> 0.25316456
A85: 85 | B85: =$F$3/A85 -> 23.529412 | I85: =I65 -> 4 | J85: =J65+1 -> 5 | K85: =K84+J84 -> 20 | L85: =0.9*J85+0.05*K85 -> 5.5 | M85: =0.45+0.4*J85+0.1*K85 -> 4.45 | N85: =1/L85 -> 0.18181818 | O85: =1/M85 -> 0.2247191
A86: 86 | B86: =$F$3/A86 -> 23.255814 | I86: =I66 -> 5 | J86: =J66+1 -> 5 | K86: =K85+J85 -> 25 | L86: =0.9*J86+0.05*K86 -> 5.75 | M86: =0.45+0.4*J86+0.1*K86 -> 4.95 | N86: =1/L86 -> 0.17391304 | O86: =1/M86 -> 0.2020202
A87: 87 | B87: =$F$3/A87 -> 22.988506 | I87: =I67 -> 6 | J87: =J67+1 -> 5 | K87: =K86+J86 -> 30 | L87: =0.9*J87+0.05*K87 -> 6 | M87: =0.45+0.4*J87+0.1*K87 -> 5.45 | N87: =1/L87 -> 0.16666667 | O87: =1/M87 -> 0.18348624
A88: 88 | B88: =$F$3/A88 -> 22.727273 | I88: =I68 -> 7 | J88: =J68+1 -> 5 | K88: =K87+J87 -> 35 | L88: =0.9*J88+0.05*K88 -> 6.25 | M88: =0.45+0.4*J88+0.1*K88 -> 5.95 | N88: =1/L88 -> 0.16 | O88: =1/M88 -> 0.16806723
A89: 89 | B89: =$F$3/A89 -> 22.47191 | I89: =I69 -> 8 | J89: =J69+1 -> 5 | K89: =K88+J88 -> 40 | L89: =0.9*J89+0.05*K89 -> 6.5 | M89: =0.45+0.4*J89+0.1*K89 -> 6.45 | N89: =1/L89 -> 0.15384615 | O89: =1/M89 -> 0.15503876
A90: 90 | B90: =$F$3/A90 -> 22.222222 | I90: =I70 -> 9 | J90: =J70+1 -> 5 | K90: =K89+J89 -> 45 | L90: =0.9*J90+0.05*K90 -> 6.75 | M90: =0.45+0.4*J90+0.1*K90 -> 6.95 | N90: =1/L90 -> 0.14814815 | O90: =1/M90 -> 0.14388489
A91: 91 | B91: =$F$3/A91 -> 21.978022 | I91: =I71 -> 10 | J91: =J71+1 -> 5 | K91: =K90+J90 -> 50 | L91: =0.9*J91+0.05*K91 -> 7 | M91: =0.45+0.4*J91+0.1*K91 -> 7.45 | N91: =1/L91 -> 0.14285714 | O91: =1/M91 -> 0.13422819
A92: 92 | B92: =$F$3/A92 -> 21.73913 | I92: =I72 -> 11 | J92: =J72+1 -> 5 | K92: =K91+J91 -> 55 | L92: =0.9*J92+0.05*K92 -> 7.25 | M92: =0.45+0.4*J92+0.1*K92 -> 7.95 | N92: =1/L92 -> 0.13793103 | O92: =1/M92 -> 0.12578616
A93: 93 | B93: =$F$3/A93 -> 21.505376 | I93: =I73 -> 12 | J93: =J73+1 -> 5 | K93: =K92+J92 -> 60 | L93: =0.9*J93+0.05*K93 -> 7.5 | M93: =0.45+0.4*J93+0.1*K93 -> 8.45 | N93: =1/L93 -> 0.13333333 | O93: =1/M93 -> 0.1183432
A94: 94 | B94: =$F$3/A94 -> 21.276596 | I94: =I74 -> 13 | J94: =J74+1 -> 5 | K94: =K93+J93 -> 65 | L94: =0.9*J94+0.05*K94 -> 7.75 | M94: =0.45+0.4*J94+0.1*K94 -> 8.95 | N94: =1/L94 -> 0.12903226 | O94: =1/M94 -> 0.11173184
... A101: 101 | B101: =$F$3/A101 -> 19.80198 | I101: =I81 -> 20 | J101: =J81+1 -> 5 | K101: =K100+J100 -> 100 | L101: =0.9*J101+0.05*K101 -> 9.5 | M101: =0.45+0.4*J101+0.1*K101 -> 12.45 | N101: =1/L101 -> 0.10526316 | O101: =1/M101 -> 0.080321285
A102: 102 | B102: =$F$3/A102 -> 19.607843 | I102: =I82 -> 1 | J102: =J82+1 -> 6 | K102: =J102 -> 6 | L102: =0.9*J102+0.05*K102 -> 5.7 | M102: =0.45+0.4*J102+0.1*K102 -> 3.45 | N102: =1/L102 -> 0.1754386 | O102: =1/M102 -> 0.28985507
A103: 103 | B103: =$F$3/A103 -> 19.417476 | I103: =I83 -> 2 | J103: =J83+1 -> 6 | K103: =K102+J102 -> 12 | L103: =0.9*J103+0.05*K103 -> 6 | M103: =0.45+0.4*J103+0.1*K103 -> 4.05 | N103: =1/L103 -> 0.16666667 | O103: =1/M103 -> 0.24691358
A104: 104 | B104: =$F$3/A104 -> 19.230769 | I104: =I84 -> 3 | J104: =J84+1 -> 6 | K104: =K103+J103 -> 18 | L104: =0.9*J104+0.05*K104 -> 6.3 | M104: =0.45+0.4*J104+0.1*K104 -> 4.65 | N104: =1/L104 -> 0.15873016 | O104: =1/M104 -> 0.21505376
A105: 105 | B105: =$F$3/A105 -> 19.047619 | I105: =I85 -> 4 | J105: =J85+1 -> 6 | K105: =K104+J104 -> 24 | L105: =0.9*J105+0.05*K105 -> 6.6 | M105: =0.45+0.4*J105+0.1*K105 -> 5.25 | N105: =1/L105 -> 0.15151515 | O105: =1/M105 -> 0.19047619
A106: 106 | B106: =$F$3/A106 -> 18.867925 | I106: =I86 -> 5 | J106: =J86+1 -> 6 | K106: =K105+J105 -> 30 | L106: =0.9*J106+0.05*K106 -> 6.9 | M106: =0.45+0.4*J106+0.1*K106 -> 5.85 | N106: =1/L106 -> 0.14492754 | O106: =1/M106 -> 0.17094017
A107: 107 | B107: =$F$3/A107 -> 18.691589 | I107: =I87 -> 6 | J107: =J87+1 -> 6 | K107: =K106+J106 -> 36 | L107: =0.9*J107+0.05*K107 -> 7.2 | M107: =0.45+0.4*J107+0.1*K107 -> 6.45 | N107: =1/L107 -> 0.13888889 | O107: =1/M107 -> 0.15503876
A108: 108 | B108: =$F$3/A108 -> 18.518519 | I108: =I88 -> 7 | J108: =J88+1 -> 6 | K108: =K107+J107 -> 42 | L108: =0.9*J108+0.05*K108 -> 7.5 | M108: =0.45+0.4*J108+0.1*K108 -> 7.05 | N108: =1/L108 -> 0.13333333 | O108: =1/M108 -> 0.14184397
A109: 109 | B109: =$F$3/A109 -> 18.348624 | I109: =I89 -> 8 | J109: =J89+1 -> 6 | K109: =K108+J108 -> 48 | L109: =0.9*J109+0.05*K109 -> 7.8 | M109: =0.45+0.4*J109+0.1*K109 -> 7.65 | N109: =1/L109 -> 0.12820513 | O109: =1/M109 -> 0.13071895
A110: 110 | B110: =$F$3/A110 -> 18.181818 | I110: =I90 -> 9 | J110: =J90+1 -> 6 | K110: =K109+J109 -> 54 | L110: =0.9*J110+0.05*K110 -> 8.1 | M110: =0.45+0.4*J110+0.1*K110 -> 8.25 | N110: =1/L110 -> 0.12345679 | O110: =1/M110 -> 0.12121212
A111: 111 | B111: =$F$3/A111 -> 18.018018 | I111: =I91 -> 10 | J111: =J91+1 -> 6 | K111: =K110+J110 -> 60 | L111: =0.9*J111+0.05*K111 -> 8.4 | M111: =0.45+0.4*J111+0.1*K111 -> 8.85 | N111: =1/L111 -> 0.11904762 | O111: =1/M111 -> 0.11299435
A112: 112 | B112: =$F$3/A112 -> 17.857143 | I112: =I92 -> 11 | J112: =J92+1 -> 6 | K112: =K111+J111 -> 66 | L112: =0.9*J112+0.05*K112 -> 8.7 | M112: =0.45+0.4*J112+0.1*K112 -> 9.45 | N112: =1/L112 -> 0.11494253 | O112: =1/M112 -> 0.10582011
A113: 113 | B113: =$F$3/A113 -> 17.699115 | I113: =I93 -> 12 | J113: =J93+1 -> 6 | K113: =K112+J112 -> 72 | L113: =0.9*J113+0.05*K113 -> 9 | M113: =0.45+0.4*J113+0.1*K113 -> 10.05 | N113: =1/L113 -> 0.11111111 | O113: =1/M113 -> 0.099502488
A114: 114 | B114: =$F$3/A114 -> 17.54386 | I114: =I94 -> 13 | J114: =J94+1 -> 6 | K114: =K113+J113 -> 78 | L114: =0.9*J114+0.05*K114 -> 9.3 | M114: =0.45+0.4*J114+0.1*K114 -> 10.65 | N114: =1/L114 -> 0.10752688 | O114: =1/M114 -> 0.093896714
... A121: 121 | B121: =$F$3/A121 -> 16.528926 | I121: =I101 -> 20 | J121: =J101+1 -> 6 | K121: =K120+J120 -> 120 | L121: =0.9*J121+0.05*K121 -> 11.4 | M121: =0.45+0.4*J121+0.1*K121 -> 14.85 | N121: =1/L121 -> 0.087719298 | O121: =1/M121 -> 0.067340067
A122: 122 | B122: =$F$3/A122 -> 16.393443 | I122: =I102 -> 1 | J122: =J102+1 -> 7 | K122: =J122 -> 7 | L122: =0.9*J122+0.05*K122 -> 6.65 | M122: =0.45+0.4*J122+0.1*K122 -> 3.95 | N122: =1/L122 -> 0.15037594 | O122: =1/M122 -> 0.25316456
A123: 123 | B123: =$F$3/A123 -> 16.260163 | I123: =I103 -> 2 | J123: =J103+1 -> 7 | K123: =K122+J122 -> 14 | L123: =0.9*J123+0.05*K123 -> 7 | M123: =0.45+0.4*J123+0.1*K123 -> 4.65 | N123: =1/L123 -> 0.14285714 | O123: =1/M123 -> 0.21505376
A124: 124 | B124: =$F$3/A124 -> 16.129032 | I124: =I104 -> 3 | J124: =J104+1 -> 7 | K124: =K123+J123 -> 21 | L124: =0.9*J124+0.05*K124 -> 7.35 | M124: =0.45+0.4*J124+0.1*K124 -> 5.35 | N124: =1/L124 -> 0.13605442 | O124: =1/M124 -> 0.18691589
A125: 125 | B125: =$F$3/A125 -> 16 | I125: =I105 -> 4 | J125: =J105+1 -> 7 | K125: =K124+J124 -> 28 | L125: =0.9*J125+0.05*K125 -> 7.7 | M125: =0.45+0.4*J125+0.1*K125 -> 6.05 | N125: =1/L125 -> 0.12987013 | O125: =1/M125 -> 0.16528926
A126: 126 | B126: =$F$3/A126 -> 15.873016 | I126: =I106 -> 5 | J126: =J106+1 -> 7 | K126: =K125+J125 -> 35 | L126: =0.9*J126+0.05*K126 -> 8.05 | M126: =0.45+0.4*J126+0.1*K126 -> 6.75 | N126: =1/L126 -> 0.1242236 | O126: =1/M126 -> 0.14814815
A127: 127 | B127: =$F$3/A127 -> 15.748031 | I127: =I107 -> 6 | J127: =J107+1 -> 7 | K127: =K126+J126 -> 42 | L127: =0.9*J127+0.05*K127 -> 8.4 | M127: =0.45+0.4*J127+0.1*K127 -> 7.45 | N127: =1/L127 -> 0.11904762 | O127: =1/M127 -> 0.13422819
A128: 128 | B128: =$F$3/A128 -> 15.625 | I128: =I108 -> 7 | J128: =J108+1 -> 7 | K128: =K127+J127 -> 49 | L128: =0.9*J128+0.05*K128 -> 8.75 | M128: =0.45+0.4*J128+0.1*K128 -> 8.15 | N128: =1/L128 -> 0.11428571 | O128: =1/M128 -> 0.12269939
...

Sheet 龙v龙
A1: 兵种 | B1: 生命 | C1: 近战攻击 | D1: 远程攻击 | E1: 防御 | F1: 射程 | G1: 速度 | H1: 加载 | I1: 维持 | L1: 攻击伤害＝兵种数量＊攻击力（科技、将军、物品加成后）＊攻击对比 ＊随机值
A2: 龙1 | B2: =B5*2 -> 485028 | C2: =C5*2 -> 4850 | D2: =D5*2 -> 4850 | E2: =E5*2 -> 4850 | F2: 1400 | G2: 650 | J2: 攻击方 | K2: 龙2
A3: 龙2 | B3: =B7*2 -> 776044.8 | C3: =C7*2 -> 3395 | D3: =D7*2 -> 3395 | E3: =E7*2 -> 5820 | F3: 1800 | G3: 100 | J3: 防守方 | K3: 龙1
J4: 伤害 | K4: =VLOOKUP(K2,A:D,4,FALSE)*MIN(2,MAX(0.5,(VLOOKUP(K2,A:D,4,FALSE)/VLOOKUP(K3,A:E,5,FALSE))))*((RAND()*40+1)/100+0.8)*5 -> 11290.353 | L4: 龙v龙伤害计算公式
B5: 242514 | C5: 2425 | D5: 2425 | E5: 2425 | F5: 1400 | G5: 650 | J5: 所需次数 | K5: =VLOOKUP(K3,A:D,2,FALSE)/K4 -> 42.959506
B6: 242514 | C6: =C5*1.2 -> 2910 | D6: =D5*1.2 -> 2910 | E6: =E5/1.44 -> 1684.0278 | F6: 1800 | G6: 100 | M6: 攻击（加成完）*攻击对比*随机值*5
B7: =B6*1.6 -> 388022.4 | C7: =C5*0.7 -> 1697.5 | D7: =D5*0.7 -> 1697.5 | E7: =E5*1.2 -> 2910 | F7: 700
E8: =C3/E2 -> 0.7
F16: 10 | G16: =2000*INT(F16^2/100)*2 -> 4000
F17: 15 | G17: =2000*INT(F17^2/100)*2 -> 8000
F18: 20 | G18: =2000*INT(F18^2/100)*2 -> 16000
F19: 25 | G19: =2000*INT(F19^2/100)*2 -> 24000
F20: 30 | G20: =2000*INT(F20^2/100)*2 -> 36000
F21: 35 | G21: =2000*INT(F21^2/100)*2 -> 48000
F22: 40 | G22: =2000*INT(F22^2/100)*2 -> 64000
F23: 45 | G23: =2000*INT(F23^2/100)*2 -> 80000
F24: 50 | G24: =2000*INT(F24^2/100)*2 -> 100000

Sheet 兵种
A1: Unit | B1: Ranged Damage | C1: Melee Damage | D1: Defense | E1: Life | F1: Speed | G1: Range | H1: Load | I1: Upkeep | J1: Might | K1: Unit Training Time | L1: instant | N1: recovery cost | O1: population | P1: Garrison | Q1: food | R1: wood | S1: stone | T1: ore | U1: gold | V1: water | W1: seed | X1: new resource | Y1: Clairvoyance | Z1: Metallurgy | AA1: Metalsmith | AB1: Ballistics | AC1: Aerial Combat | AD1: Rookery | AE1: RapidDeployment | AF1: Dragonry | AG1: Factory | AH1: Levitation | AI1: waterdragonkeep | AJ1: Masonry | AK1: seed factory | AL1: new resource building | AM1: medicine
A2: Conscript | B2: 0 | C2: 10 | D2: 10 | E2: 75 | F2: 200 | G2: 0 | H2: 20 | I2: 3 | J2: 1 | K2: 26 | L2: =SUM(Q2:U2)/250000*55+K2/345600*275+O2/20000*55 -> 0.074038657 | N2: =L2 -> 0.074038657 | O2: 1 | P2: 1 | Q2: 80 | R2: 100 | S2: 0 | T2: 50
A3: Porter | B3: 0 | C3: 1 | D3: 10 | E3: 45 | F3: 100 | G3: 0 | H3: 200 | I3: 2 | J3: 1 | K3: 48 | L3: =SUM(Q3:U3)/250000*55+K3/345600*275+O3/20000*55 -> 0.087144444 | N3: =L3 -> 0.087144444 | O3: 1 | P3: 2 | Q3: 50 | R3: 150 | S3: 0 | T3: 10
A4: Spy | B4: 0 | C4: 5 | D4: 5 | E4: 10 | F4: 3000 | G4: 0 | H4: 0 | I4: 5 | J4: 2 | K4: 103 | L4: =SUM(Q4:U4)/250000*55+K4/345600*275+O4/20000*55 -> 0.18810891 | N4: =L4 -> 0.18810891 | O4: 1 | P4: 4 | Q4: 120 | R4: 200 | S4: 0 | T4: 150 | Y4: 1
A5: Halberdsman | B5: 0 | C5: 40 | D5: 40 | E5: 150 | F5: 300 | G5: 0 | H5: 40 | I5: 6 | J5: 2 | K5: 141 | L5: =SUM(Q5:U5)/250000*55+K5/345600*275+O5/20000*55 -> 0.27994618 | N5: =L5 -> 0.27994618 | O5: 1 | P5: 4 | Q5: 150 | R5: 500 | S5: 0 | T5: 100 | Z5: 1
A6: Minotaur | B6: 0 | C6: 70 | D6: 45 | E6: 225 | F6: 275 | G6: 0 | H6: 30 | I6: 7 | J6: 3 | K6: 219 | L6: =SUM(Q6:U6)/250000*55+K6/345600*275+O6/20000*55 -> 0.34201215 | N6: =L6 -> 0.34201215 | O6: 1 | P6: 6 | Q6: 200 | R6: 150 | S6: 0 | T6: 400 | Z6: 1 | AA6: 2
A7: Longbowman | B7: 80 | C7: 5 | D7: 30 | E7: 75 | F7: 250 | G7: 1200 | H7: 25 | I7: 9 | J7: 4 | K7: 343 | L7: =SUM(Q7:U7)/250000*55+K7/345600*275+O7/20000*55 -> 0.48743113 | N7: =L7 -> 0.48743113 | O7: 2 | P7: 8 | Q7: 300 | R7: 350 | S7: 0 | T7: 300 | AB7: 1
A8: SwiftStrikeDragon | B8: 0 | C8: 150 | D8: 60 | E8: 300 | F8: 1000 | G8: 0 | H8: 100 | I8: 18 | J8: 5 | K8: 498 | L8: =SUM(Q8:U8)/250000*55+K8/345600*275+O8/20000*55 -> 0.86651736 | N8: =L8 -> 0.86651736 | O8: 3 | P8: 10 | Q8: 1000 | R8: 600 | S8: 0 | T8: 500 | AD8: 2 | AE8: 1 | AF8: 2
A9: BattleDragon | B9: 0 | C9: 300 | D9: 300 | E9: 1500 | F9: 750 | G9: 0 | H9: 80 | I9: 35 | J9: 7 | K9: 1492 | L9: =SUM(Q9:U9)/250000*55+K9/345600*275+O9/20000*55 -> 2.3037106 | N9: =L9 -> 2.3037106 | O9: 6 | P9: 14 | Q9: 2000 | R9: 500 | S9: 0 | T9: 2500 | AA9: 10 | AD9: 10 | AE9: 5 | AF9: 3
A10: ArmoredTransport | B10: 0 | C10: 5 | D10: 200 | E10: 750 | F10: 150 | G10: 0 | H10: 5000 | I10: 10 | J10: 6 | K10: 975 | L10: =SUM(Q10:U10)/250000*55+K10/345600*275+O10/20000*55 -> 1.3258247 | N10: =L10 -> 1.3258247 | O10: 4 | P10: 12 | Q10: 600 | R10: 1500 | S10: 0 | T10: 350 | AG10: 6 | AH10: 3
A11: Giant | B11: 0 | C11: 1000 | D11: 400 | E11: 4000 | F11: 120 | G11: 0 | H11: 45 | I11: 100 | J11: 9 | K11: 4334 | L11: =SUM(Q11:U11)/250000*55+K11/345600*275+O11/20000*55 -> 6.00064 | N11: =L11 -> 6.00064 | O11: 8 | P11: 18 | Q11: 4000 | R11: 6000 | S11: 0 | T11: 1500 | Y11: 3 | Z11: 8 | AA11: 10 | AG11: 14
A12: FireMirror | B12: 1200 | C12: 20 | D12: 30 | E12: 1500 | F12: 50 | G12: 1500 | H12: 75 | I12: 250 | J12: 10 | K12: 5843 | L12: =SUM(Q12:U12)/250000*55+K12/345600*275+O12/20000*55 -> 8.9008779 | N12: =L12 -> 8.9008779 | O12: 10 | P12: 20 | Q12: 5000 | R12: 5000 | S12: 8000 | T12: 1200 | Z12: 10 | AA12: 14 | AB12: 10 | AG12: 18
A13: Fangtooth | B13: 800 | C13: 1600 | D13: 300 | E13: 3000 | F13: 500 | G13: 600 | H13: 45 | I13: 125 | J13: 10 | K13: 2000 | L13: =SUM(Q13:U13)/250000*55+K13/345600*275+O13/20000*55+SUM(V13:X13)/80000*30 -> 5.8336852 | N13: =L13 -> 5.8336852 | O13: 9 | P13: 18 | Q13: 4000 | R13: 5500 | S13: 7000 | T13: 2500 | V13: 100 | Y13: 0 | AA13: 14 | AE13: 8 | AG13: 14 | AI13: 18 | AJ13: 9
A14: Venge Wyrm | B14: 0 | C14: 3100 | D14: 400 | E14: 250 | F14: 900 | G14: 0 | H14: 0 | I14: 10 | J14: 10 | K14: 2504 | L14: =SUM(Q14:U14)/250000*55+K14/345600*275+O14/20000*55+SUM(V14:X14)/80000*30 -> 4.8772269 | N14: =L14 -> 4.8772269 | O14: 9 | P14: 20 | Q14: 1000 | R14: 3000 | S14: 1000 | T14: 4000 | U14: 4000 | Z14: 10 | AA14: 20 | AC14: 7 | AE14: 10
A15: nightshadetroop | B15: 0 | C15: 2000 | D15: 500 | E15: 5000 | F15: 150 | G15: 0 | H15: 60 | I15: 125 | J15: 10 | K15: 2000 | L15: =SUM(Q15:U15)/250000*55+K15/345600*275+O15/20000*55+SUM(V15:X15)/80000*30 -> 6.0536852 | N15: =L15 -> 6.0536852 | O15: 9 | P15: 18 | Q15: 1000 | R15: 4000 | S15: 8000 | T15: 2000 | U15: 5000 | W15: 100 | Y15: 8 | AA15: 18 | AE15: 9 | AK15: 9 | AM15: 8
A16: granite ogre | B16: 0 | C16: 650 | D16: 900 | E16: 15000 | F16: 350 | G16: 0 | H16: 30 | I16: 110 | J16: 9 | K16: 2000 | L16: =SUM(Q16:U16)/250000*55+K16/345600*275+O16/20000*55+SUM(V16:X16)/80000*30 -> 5.3909352 | N16: =L16 -> 5.3909352 | O16: 8 | P16: 18 | Q16: 3000 | R16: 4000 | S16: 8000 | T16: 2000 | X16: 100 | Y16: 5 | Z16: 9 | AA16: 18 | AJ16: 9 | AL16: 9
A18: BlackholeOne | B18: 0 | C18: 8000 | D18: 0 | E18: 1 | F18: 750 | G18: 0 | H18: 0 | I18: 0 | J18: 0
A19: Shredder | B19: 0 | C19: 150 | D19: 60 | E19: 300 | F19: 1000 | G19: 0 | H19: 100 | I19: 18 | J19: 5 | K19: 498 | M19: 打龙装备消耗战力 | Q19: =12*5+1*16 -> 76 | S19: points
A20: Rager | B20: 1200 | C20: 20 | D20: 30 | E20: 1500 | F20: 50 | G20: 1500 | H20: 75 | I20: 250 | J20: 10 | K20: 5843 | M20: Conscript | N20: 1600000 | O20: =$N$20/(E2*1.35) -> 15802.469 | P20: =O20*J2 -> 15802.469 | Q20: =O20*K2 -> 410864.2 | R20: =K2/J2 -> 26 | S20: =CEILING(R20/$R$20,1) -> 1
A21: Cannibal | B21: 0 | C21: 10 | D21: 10 | E21: 75 | F21: 200 | G21: 0 | H21: 20 | I21: 3 | J21: 1 | K21: 26 | M21: Porter | O21: =$N$20/(E3*1.35) -> 26337.449 | P21: =O21*J3 -> 26337.449 | Q21: =O21*K3 -> 1264197.5 | R21: =K3/J3 -> 48 | S21: =CEILING(R21/$R$20,1) -> 2
A22: Chieftan | B22: 0 | C22: 300 | D22: 300 | E22: 1500 | F22: 750 | G22: 0 | H22: 80 | I22: 35 | J22: 7 | K22: 1492 | M22: Spy | O22: =$N$20/(E4*1.35) -> 118518.52 | P22: =O22*J4 -> 237037.04 | Q22: =O22*K4 -> 12207407 | R22: =K4/J4 -> 51.5 | S22: =CEILING(R22/$R$20,1) -> 2
A23: Brat | B23: 0 | C23: 1 | D23: 10 | E23: 45 | F23: 100 | G23: 0 | H23: 200 | I23: 2 | J23: 1 | K23: 48 | M23: Halberdsman | O23: =$N$20/(E5*1.35) -> 7901.2346 | P23: =O23*J5 -> 15802.469 | Q23: =O23*K5 -> 1114074.1 | R23: =K5/J5 -> 70.5 | S23: =CEILING(R23/$R$20,1) -> 3
A24: SheDevil | B24: 0 | C24: 40 | D24: 40 | E24: 150 | F24: 300 | G24: 0 | H24: 40 | I24: 6 | J24: 2 | K24: 141 | M24: Minotaur | O24: =$N$20/(E6*1.35) -> 5267.4897 | P24: =O24*J6 -> 15802.469 | Q24: =O24*K6 -> 1153580.2 | R24: =K6/J6 -> 73 | S24: =CEILING(R24/$R$20,1) -> 3
A25: Clubber | B25: 0 | C25: 70 | D25: 45 | E25: 225 | F25: 275 | G25: 0 | H25: 30 | I25: 7 | J25: 3 | K25: 219 | M25: Longbowman | O25: =$N$20/(E7*1.35) -> 15802.469 | P25: =O25*J7 -> 63209.877 | Q25: =O25*K7 -> 5420246.9 | R25: =K7/J7 -> 85.75 | S25: =CEILING(R25/$R$20,1) -> 4
A26: Blood | B26: 0 | C26: 1000 | D26: 400 | E26: 4000 | F26: 120 | G26: 0 | H26: 45 | I26: 100 | J26: 9 | K26: 4334 | M26: SwiftStrikeDragon | O26: =$N$20/(E8*1.35) -> 3950.6173 | P26: =O26*J8 -> 19753.086 | Q26: =O26*K8 -> 1967407.4 | R26: =K8/J8 -> 99.6 | S26: =CEILING(R26/$R$20,1) -> 4
A27: Hurler | B27: 80 | C27: 5 | D27: 30 | E27: 75 | F27: 250 | G27: 1200 | H27: 25 | I27: 9 | J27: 4 | K27: 343 | M27: BattleDragon | O27: =$N$20/(E9*1.35) -> 790.12346 | P27: =O27*J9 -> 5530.8642 | Q27: =O27*K9 -> 1178864.2 | R27: =K9/J9 -> 213.14286 | S27: =CEILING(R27/$R$20,1) -> 9
A28: Stench | B28: 0 | C28: 5 | D28: 5 | E28: 10 | F28: 3000 | G28: 0 | H28: 0 | I28: 5 | J28: 2 | K28: 103 | M28: ArmoredTransport | O28: =$N$20/(E10*1.35) -> 1580.2469 | P28: =O28*J10 -> 9481.4815 | Q28: =O28*K10 -> 1540740.7 | R28: =K10/J10 -> 162.5 | S28: =CEILING(R28/$R$20,1) -> 7
A29: Great Dragon1 | B29: 1 | C29: 0 | D29: 0 | E29: 0 | F29: 0 | G29: 375 | H29: 650 | I29: 0 | J29: 0 | K29: 0 | M29: Giant | O29: =$N$20/(E11*1.35) -> 296.2963 | P29: =O29*J11 -> 2666.6667 | Q29: =O29*K11 -> 1284148.1 | R29: =K11/J11 -> 481.55556 | S29: =CEILING(R29/$R$20,1) -> 19
A30: Great Dragon2 | B30: 0 | C30: 0 | D30: 0 | E30: 0 | F30: 650 | G30: 1400 | H30: 0 | I30: 0 | J30: 0 | M30: FireMirror | O30: =$N$20/(E12*1.35) -> 790.12346 | P30: =O30*J12 -> 7901.2346 | Q30: =O30*K12 -> 4616691.4 | R30: =K12/J12 -> 584.3 | S30: =CEILING(R30/$R$20,1) -> 23
A31: Great Dragon3 | B31: 50 | C31: 50 | D31: 50 | E31: 5000 | F31: 650 | G31: 1400 | H31: 0 | I31: 50 | J31: 0
A32: Great Dragon4 | B32: 100 | C32: 100 | D32: 100 | E32: 10000 | F32: 650 | G32: 1400 | H32: 0 | I32: 100 | J32: 0
A33: Great Dragon5 | B33: 150 | C33: 150 | D33: 150 | E33: 14000 | F33: 650 | G33: 1400 | H33: 0 | I33: 150 | J33: 0
A34: Great Dragon6 | B34: 200 | C34: 200 | D34: 200 | E34: 20000 | F34: 650 | G34: 1400 | H34: 0 | I34: 200 | J34: 0
A35: Great Dragon7 | B35: 329 | C35: 329 | D35: 329 | E35: 32973 | F35: 650 | G35: 1400 | H35: 0 | I35: 300 | J35: 0
A36: Great Dragon8 | B36: 459 | C36: 459 | D36: 459 | E36: 45947 | F36: 650 | G36: 1400 | H36: 0 | I36: 400 | J36: 0
A37: Great Dragon9 | B37: 603 | C37: 603 | D37: 603 | E37: 60345 | F37: 650 | G37: 1400 | H37: 0 | I37: 500 | J37: 0
A38: Great Dragon10 | B38: 747 | C38: 747 | D38: 747 | E38: 74743 | F38: 650 | G38: 1400 | H38: 0 | I38: 600 | J38: 0
A39: Great Dragon11 | B39: 901 | C39: 901 | D39: 901 | E39: 90151 | F39: 650 | G39: 1400 | H39: 0 | I39: 700 | J39: 0
A40: Great Dragon12 | B40: 1055 | C40: 1055 | D40: 1055 | E40: 105560 | F40: 650 | G40: 1400 | H40: 0 | I40: 800 | J40: 0
A41: Great Dragon13 | B41: 1217 | C41: 1217 | D41: 1217 | E41: 121766 | F41: 650 | G41: 1400 | H41: 0 | I41: 900 | J41: 0
A42: Great Dragon14 | B42: 1379 | C42: 1379 | D42: 1379 | E42: 137972 | F42: 650 | G42: 1400 | H42: 0 | I42: 1000 | J42: 0
... A50: Water Dragon2 | B50: 40 | C50: 40 | D50: 20 | E50: 3333 | F50: 900 | G50: 1800 | H50: 0 | I50: 0 | J50: 0
A51: Water Dragon3 | B51: =INT(B31*1.2) -> 60 | C51: =INT(C31*1.2) -> 60 | D51: =INT(D31/1.44) -> 34 | E51: =E31 -> 5000 | F51: 900 | G51: 1800 | H51: 0 | I51: 50 | J51: 0
A52: Water Dragon4 | B52: =INT(B32*1.2) -> 120 | C52: =INT(C32*1.2) -> 120 | D52: =INT(D32/1.44) -> 69 | E52: =E32 -> 10000 | F52: 900 | G52: 1800 | H52: 0 | I52: 100 | J52: 0
A53: Water Dragon5 | B53: =INT(B33*1.2) -> 180 | C53: =INT(C33*1.2) -> 180 | D53: =INT(D33/1.44) -> 104 | E53: =E33 -> 14000 | F53: 900 | G53: 1800 | H53: 0 | I53: 150 | J53: 0
A54: Water Dragon6 | B54: =INT(B34*1.2) -> 240 | C54: =INT(C34*1.2) -> 240 | D54: =INT(D34/1.44) -> 138 | E54: =E34 -> 20000 | F54: 900 | G54: 1800 | H54: 0 | I54: 200 | J54: 0
A55: Water Dragon7 | B55: =INT(B35*1.2) -> 394 | C55: =INT(C35*1.2) -> 394 | D55: =INT(D35/1.44) -> 228 | E55: =E35 -> 32973 | F55: 900 | G55: 1800 | H55: 0 | I55: 300 | J55: 0
A56: Water Dragon8 | B56: =INT(B36*1.2) -> 550 | C56: =INT(C36*1.2) -> 550 | D56: =INT(D36/1.44) -> 318 | E56: =E36 -> 45947 | F56: 900 | G56: 1800 | H56: 0 | I56: 400 | J56: 0
A57: Water Dragon9 | B57: =INT(B37*1.2) -> 723 | C57: =INT(C37*1.2) -> 723 | D57: =INT(D37/1.44) -> 418 | E57: =E37 -> 60345 | F57: 900 | G57: 1800 | H57: 0 | I57: 500 | J57: 0
A58: Water Dragon10 | B58: =INT(B38*1.2) -> 896 | C58: =INT(C38*1.2) -> 896 | D58: =INT(D38/1.44) -> 518 | E58: =E38 -> 74743 | F58: 900 | G58: 1800 | H58: 0 | I58: 600 | J58: 0
A59: Water Dragon11 | B59: =INT(B39*1.2) -> 1081 | C59: =INT(C39*1.2) -> 1081 | D59: =INT(D39/1.44) -> 625 | E59: =E39 -> 90151 | F59: 900 | G59: 1800 | H59: 0 | I59: 700 | J59: 0
A60: Water Dragon12 | B60: =INT(B40*1.2) -> 1266 | C60: =INT(C40*1.2) -> 1266 | D60: =INT(D40/1.44) -> 732 | E60: =E40 -> 105560 | F60: 900 | G60: 1800 | H60: 0 | I60: 800 | J60: 0
A61: Water Dragon13 | B61: =INT(B41*1.2) -> 1460 | C61: =INT(C41*1.2) -> 1460 | D61: =INT(D41/1.44) -> 845 | E61: =E41 -> 121766 | F61: 900 | G61: 1800 | H61: 0 | I61: 900 | J61: 0
A62: Water Dragon14 | B62: =INT(B42*1.2) -> 1654 | C62: =INT(C42*1.2) -> 1654 | D62: =INT(D42/1.44) -> 957 | E62: =E42 -> 137972 | F62: 900 | G62: 1800 | H62: 0 | I62: 1000 | J62: 0
... A68: Water Dragon20 | B68: =INT(B48*1.2) -> 2910 | C68: =INT(C48*1.2) -> 2910 | D68: =INT(D48/1.44) -> 1684 | E68: =E48 -> 242514 | F68: 900 | G68: 1800 | H68: 0 | I68: 1600 | J68: 0
A69: Nightshade dragon1 | B69: 0 | C69: 0 | D69: 0 | E69: 0 | F69: 1000 | G69: 700 | H69: 0 | I69: 0 | J69: 0
A70: Nightshade dragon2 | B70: 17 | C70: 32 | D70: 20 | E70: 3750 | F70: 1000 | G70: 700 | H70: 0 | I70: 0 | J70: 0 | K70: 优点 | L70: load
A71: Nightshade dragon3 | B71: =INT(B31*0.7) -> 35 | C71: =INT(C31*1.3) -> 65 | D71: =INT(D31*0.8) -> 40 | E71: =INT(E31*1.5) -> 7500 | F71: 1000 | G71: 700 | H71: 0 | I71: 50 | J71: 0 | L71: melee attack
A72: Nightshade dragon4 | B72: =INT(B32*0.7) -> 70 | C72: =INT(C32*1.3) -> 130 | D72: =INT(D32*0.8) -> 80 | E72: =INT(E32*1.5) -> 15000 | F72: 1000 | G72: 700 | H72: 0 | I72: 100 | J72: 0 | L72: life
A73: Nightshade dragon5 | B73: =INT(B33*0.7) -> 105 | C73: =INT(C33*1.3) -> 195 | D73: =INT(D33*0.8) -> 120 | E73: =INT(E33*1.5) -> 21000 | F73: 1000 | G73: 700 | H73: 0 | I73: 150 | J73: 0 | L73: speed
A74: Nightshade dragon6 | B74: =INT(B34*0.7) -> 140 | C74: =INT(C34*1.3) -> 260 | D74: =INT(D34*0.8) -> 160 | E74: =INT(E34*1.5) -> 30000 | F74: 1000 | G74: 700 | H74: 0 | I74: 200 | J74: 0
A75: Nightshade dragon7 | B75: =INT(B35*0.7) -> 230 | C75: =INT(C35*1.3) -> 427 | D75: =INT(D35*0.8) -> 263 | E75: =INT(E35*1.5) -> 49459 | F75: 1000 | G75: 700 | H75: 0 | I75: 300 | J75: 0 | K75: 龙带新兵的加成 | L75: 生命 0.025*lv
A76: Nightshade dragon8 | B76: =INT(B36*0.7) -> 321 | C76: =INT(C36*1.3) -> 596 | D76: =INT(D36*0.8) -> 367 | E76: =INT(E36*1.5) -> 68920 | F76: 1000 | G76: 700 | H76: 0 | I76: 400 | J76: 0
A77: Nightshade dragon9 | B77: =INT(B37*0.7) -> 422 | C77: =INT(C37*1.3) -> 783 | D77: =INT(D37*0.8) -> 482 | E77: =INT(E37*1.5) -> 90517 | F77: 1000 | G77: 700 | H77: 10000 | I77: 500 | J77: 0 | K77: 龙skill | L77: fake army | M77: 敌人侦查错误，防守兵力翻倍
A78: Nightshade dragon10 | B78: =INT(B38*0.7) -> 522 | C78: =INT(C38*1.3) -> 971 | D78: =INT(D38*0.8) -> 597 | E78: =INT(E38*1.5) -> 112114 | F78: 1000 | G78: 700 | H78: 30000 | I78: 600 | J78: 0 | L78: 增加复活兵的上限
A79: Nightshade dragon11 | B79: =INT(B39*0.7) -> 630 | C79: =INT(C39*1.3) -> 1171 | D79: =INT(D39*0.8) -> 720 | E79: =INT(E39*1.5) -> 135226 | F79: 1000 | G79: 700 | H79: 60000 | I79: 700 | J79: 0
A80: Nightshade dragon12 | B80: =INT(B40*0.7) -> 738 | C80: =INT(C40*1.3) -> 1371 | D80: =INT(D40*0.8) -> 844 | E80: =INT(E40*1.5) -> 158340 | F80: 1000 | G80: 700 | H80: 100000 | I80: 800 | J80: 0
A81: Nightshade dragon13 | B81: =INT(B41*0.7) -> 851 | C81: =INT(C41*1.3) -> 1582 | D81: =INT(D41*0.8) -> 973 | E81: =INT(E41*1.5) -> 182649 | F81: 1000 | G81: 700 | H81: 150000 | I81: 900 | J81: 0
A82: Nightshade dragon14 | B82: =INT(B42*0.7) -> 965 | C82: =INT(C42*1.3) -> 1792 | D82: =INT(D42*0.8) -> 1103 | E82: =INT(E42*1.5) -> 206958 | F82: 1000 | G82: 700 | H82: 200000 | I82: 1000 | J82: 0
A83: Nightshade dragon15 | B83: =INT(B43*0.7) -> 1083 | C83: =INT(C43*1.3) -> 2012 | D83: =INT(D43*0.8) -> 1238 | E83: =INT(E43*1.5) -> 232266 | F83: 1000 | G83: 700 | H83: 300000 | I83: 1100 | J83: 0
A84: Nightshade dragon16 | B84: =INT(B44*0.7) -> 1201 | C84: =INT(C44*1.3) -> 2232 | D84: =INT(D44*0.8) -> 1373 | E84: =INT(E44*1.5) -> 257574 | F84: 1000 | G84: 700 | H84: 400000 | I84: 1200 | J84: 0
A85: Nightshade dragon17 | B85: =INT(B45*0.7) -> 1323 | C85: =INT(C45*1.3) -> 2458 | D85: =INT(D45*0.8) -> 1512 | E85: =INT(E45*1.5) -> 283743 | F85: 1000 | G85: 700 | H85: 500000 | I85: 1300 | J85: 0
A86: Nightshade dragon18 | B86: =INT(B46*0.7) -> 1446 | C86: =INT(C46*1.3) -> 2685 | D86: =INT(D46*0.8) -> 1652 | E86: =INT(E46*1.5) -> 309912 | F86: 1000 | G86: 700 | H86: 600000 | I86: 1400 | J86: 0
A87: Nightshade dragon19 | B87: =INT(B47*0.7) -> 1571 | C87: =INT(C47*1.3) -> 2918 | D87: =INT(D47*0.8) -> 1796 | E87: =INT(E47*1.5) -> 336841 | F87: 1000 | G87: 700 | H87: 800000 | I87: 1400 | J87: 0
A88: Nightshade dragon20 | B88: =INT(B48*0.7) -> 1697 | C88: =INT(C48*1.3) -> 3152 | D88: =INT(D48*0.8) -> 1940 | E88: =INT(E48*1.5) -> 363771 | F88: 1000 | G88: 700 | H88: 1000000 | I88: 1600 | J88: 0
A89: Stone dragon1 | B89: =INT(B29*0.7) -> 0 | C89: =INT(C29*0.7) -> 0 | D89: =INT(D29*1.2) -> 0 | E89: =INT(E29*1.6) -> 0 | F89: 650 | G89: 1700 | H89: 0 | I89: 0
A90: Stone dragon2 | B90: =INT(B91/2) -> 17 | C90: =INT(C91/2) -> 17 | D90: =INT(D91/2) -> 30 | E90: =INT(E91/2) -> 4000 | F90: 650 | G90: 1700 | H90: 0 | I90: 0
A91: Stone dragon3 | B91: =INT(B31*0.7) -> 35 | C91: =INT(C31*0.7) -> 35 | D91: =INT(D31*1.2) -> 60 | E91: =INT(E31*1.6) -> 8000 | F91: 650 | G91: 1700 | H91: 0 | I91: 50
A92: Stone dragon4 | B92: =INT(B32*0.7) -> 70 | C92: =INT(C32*0.7) -> 70 | D92: =INT(D32*1.2) -> 120 | E92: =INT(E32*1.6) -> 16000 | F92: 650 | G92: 1700 | H92: 0 | I92: 100
A93: Stone dragon5 | B93: =INT(B33*0.7) -> 105 | C93: =INT(C33*0.7) -> 105 | D93: =INT(D33*1.2) -> 180 | E93: =INT(E33*1.6) -> 22400 | F93: 650 | G93: 1700 | H93: 0 | I93: 150
A94: Stone dragon6 | B94: =INT(B34*0.7) -> 140 | C94: =INT(C34*0.7) -> 140 | D94: =INT(D34*1.2) -> 240 | E94: =INT(E34*1.6) -> 32000 | F94: 650 | G94: 1700 | H94: 0 | I94: 200
A95: Stone dragon7 | B95: =INT(B35*0.7) -> 230 | C95: =INT(C35*0.7) -> 230 | D95: =INT(D35*1.2) -> 394 | E95: =INT(E35*1.6) -> 52756 | F95: 650 | G95: 1700 | H95: 0 | I95: 300
A96: Stone dragon8 | B96: =INT(B36*0.7) -> 321 | C96: =INT(C36*0.7) -> 321 | D96: =INT(D36*1.2) -> 550 | E96: =INT(E36*1.6) -> 73515 | F96: 650 | G96: 1700 | H96: 0 | I96: 400
A97: Stone dragon9 | B97: =INT(B37*0.7) -> 422 | C97: =INT(C37*0.7) -> 422 | D97: =INT(D37*1.2) -> 723 | E97: =INT(E37*1.6) -> 96552 | F97: 650 | G97: 1700 | H97: 0 | I97: 500
A98: Stone dragon10 | B98: =INT(B38*0.7) -> 522 | C98: =INT(C38*0.7) -> 522 | D98: =INT(D38*1.2) -> 896 | E98: =INT(E38*1.6) -> 119588 | F98: 650 | G98: 1700 | H98: 0 | I98: 600
A99: Stone dragon11 | B99: =INT(B39*0.7) -> 630 | C99: =INT(C39*0.7) -> 630 | D99: =INT(D39*1.2) -> 1081 | E99: =INT(E39*1.6) -> 144241 | F99: 650 | G99: 1700 | H99: 0 | I99: 700
A100: Stone dragon12 | B100: =INT(B40*0.7) -> 738 | C100: =INT(C40*0.7) -> 738 | D100: =INT(D40*1.2) -> 1266 | E100: =INT(E40*1.6) -> 168896 | F100: 650 | G100: 1700 | H100: 0 | I100: 800
A101: Stone dragon13 | B101: =INT(B41*0.7) -> 851 | C101: =INT(C41*0.7) -> 851 | D101: =INT(D41*1.2) -> 1460 | E101: =INT(E41*1.6) -> 194825 | F101: 650 | G101: 1700 | H101: 0 | I101: 900
A102: Stone dragon14 | B102: =INT(B42*0.7) -> 965 | C102: =INT(C42*0.7) -> 965 | D102: =INT(D42*1.2) -> 1654 | E102: =INT(E42*1.6) -> 220755 | F102: 650 | G102: 1700 | H102: 0 | I102: 1000
... A108: Stone dragon20 | B108: =INT(B48*0.7) -> 1697 | C108: =INT(C48*0.7) -> 1697 | D108: =INT(D48*1.2) -> 2910 | E108: =INT(E48*1.6) -> 388022 | F108: 650 | G108: 1700 | H108: 0 | I108: 1600

Sheet 物品价格
B1: item | C1: quantity | D1: price | E1: 单价
A2: 1 | B2: 1m | C2: 60 | D2: 1 | E2: =D2/C2 -> 0.016666667
A3: 2 | B3: 5m | C3: 300 | D3: 3 | E3: =D3/C3 -> 0.01
A4: 3 | B4: 15m | C4: =15*60 -> 900 | D4: 5 | E4: =D4/C4 -> 0.0055555556
A5: 4 | B5: 1h | C5: =3600 -> 3600 | D5: 10 | E5: =D5/C5 -> 0.0027777778
A6: 5 | B6: 2.5h | C6: =2.5*3600 -> 9000 | D6: 15 | E6: =D6/C6 -> 0.0016666667
A7: 6 | B7: 8h | C7: =8*3600 -> 28800 | D7: 40 | E7: =D7/C7 -> 0.0013888889
A8: 7 | B8: 15hr | C8: =15*3600 -> 54000 | D8: 65 | E8: =D8/C8 -> 0.0012037037
A9: 8 | B9: 24h | C9: =24*3600 -> 86400 | D9: 95 | E9: =D9/C9 -> 0.001099537
A10: 9 | B10: 2.5d | C10: =2.5*24*3600 -> 216000 | D10: 210 | E10: =D10/C10 -> 0.00097222222
A11: 10 | B11: 4d | C11: =4*24*3600 -> 345600 | D11: 275 | E11: =D11/C11 -> 0.00079571759
A13: 1 | B13: resource | C13: 80000 | D13: 20 | E13: =D13/C13 -> 0.00025
A14: 2 | C14: 250000 | D14: 55 | E14: =D14/C14 -> 0.00022
A15: 3 | C15: 500000 | D15: 95 | E15: =D15/C15 -> 0.00019

Sheet 各兵种资源消耗产出详细计算
C1: food | D1: wood | E1: stone | F1: ore | G1: newresource | J1: 兵营数量 | K1: 16 | L1: home数量 | M1: =34-K1-12 -> 6
B2: 建筑数量 | C2: 3 | D2: 14 | E2: 7 | F2: 14 | G2: 8 | H2: =IF(SUM(C2:F2)>38,"FALSE","TRUE") -> TRUE | J2: 兵营等级 | K2: 300 | L2: 人口上限 | M2: =M1*金币产出!F21 -> 33000
B3: 建筑级别 | C3: 10 | D3: 10 | E3: 10 | F3: 10 | G3: 9 | J3: 加速倍数 | K3: =0.9*K1+0.05*K2 -> 29.4 | L3: 雇佣人口 | M3: =VLOOKUP(C3,资源产出!A2:B11,2,FALSE)*(SUM(C2:F2)+G2*2) -> 29700
B4: 对应科技等级 | C4: 10 | D4: 10 | E4: 10 | F4: 10 | G4: 0 | J4: 孵化室等级 | K4: 20 | L4: 幸福指数 | M4: 0.6
B5: 野外点总级别 | C5: 0 | D5: 40 | E5: 30 | F5: 30 | G5: 0 | H5: =IF(SUM(C5:F5)>100,"FALSE","TRUE") -> TRUE | J5: 龙兵种加速倍数 | K5: =K3*(1+K4*0.005) -> 32.34 | L5: 空闲人口 | M5: =(M2-M3)*M4 -> 1980
B6: 是否有道具 | C6: 0 | D6: 0 | E6: 0 | F6: 0 | G6: 0
B7: 产量每小时 | C7: =(100+VLOOKUP(C3,资源产出!$A$2:$D$11,3,FALSE)*C2)*(1+C4*0.1+C5*0.05+C6*0.25) -> 33200 | D7: =(100+VLOOKUP(D3,资源产出!$A$2:$D$11,3,FALSE)*D2)*(1+D4*0.1+D5*0.05+D6*0.25) -> 308400 | E7: =(100+VLOOKUP(E3,资源产出!$A$2:$D$11,3,FALSE)*E2)*(1+E4*0.1+E5*0.05+E6*0.25) -> 135100 | F7: =(100+VLOOKUP(F3,资源产出!$A$2:$D$11,3,FALSE)*F2)*(1+F4*0.1+F5*0.05+F6*0.25) -> 269850 | G7: =VLOOKUP(G3,资源产出!A18:D27,3,FALSE)*8 -> 1440
B8: 上限 | C8: =VLOOKUP(C3,资源产出!$A$2:$D$11,4,FALSE)*C2 -> 1650000 | D8: =VLOOKUP(D3,资源产出!$A$2:$D$11,4,FALSE)*D2 -> 7700000 | E8: =VLOOKUP(E3,资源产出!$A$2:$D$11,4,FALSE)*E2 -> 3850000 | F8: =VLOOKUP(F3,资源产出!$A$2:$D$11,4,FALSE)*F2 -> 7700000 | G8: =VLOOKUP(G3,资源产出!A18:D27,4,FALSE)*8 -> 69120
B9: 24小时产量 | C9: =MIN(C7*24,C8) -> 796800 | D9: =MIN(D7*24,D8) -> 7401600 | E9: =MIN(E7*24,E8) -> 3242400 | F9: =MIN(F7*24,F8) -> 6476400 | G9: =MIN(G7*24,G8) -> 34560
I11: 消耗资源 | N11: 消耗/产出 | S11: total
A12: 兵种 | B12: 单个时间 | C12: food | D12: wood | E12: stone | F12: ore | G12: newresource | H12: 24小时可造数量 | I12: food | J12: wood | K12: stone | L12: ore | M12: newresource | N12: food | O12: wood | P12: stone | Q12: ore | R12: newresource | T12: 单个might | U12: 一天获得might | V12: 单个需人口 | W12: 需空闲人口
A13: =兵种!A2 -> Conscript | B13: =兵种!K2 -> 26 | C13: =兵种!Q2 -> 80 | D13: =兵种!R2 -> 100 | E13: =兵种!S2 -> 0 | F13: =兵种!T2 -> 50 | G13: =兵种!V2 -> 0 | H13: =24*3600*$K$3/B13 -> 97698.462 | I13: =C13*$H13 -> 7815876.9 | J13: =D13*$H13 -> 9769846.2 | K13: =E13*$H13 -> 0 | L13: =F13*$H13 -> 4884923.1 | M13: =G13*$H13 -> 0 | N13: =I13/C$9 -> 9.8090825 | O13: =J13/D$9 -> 1.3199641 | P13: =K13/E$9 -> 0 | Q13: =L13/F$9 -> 0.75426519 | R13: =M13/G$9 -> 0 | S13: =SUM(O13:R13) -> 2.0742293 | T13: =兵种!J2 -> 1 | U13: =T13*H13 -> 97698.462 | V13: =兵种!O2 -> 1 | W13: =V13*H13 -> 97698.462
A14: =兵种!A3 -> Porter | B14: =兵种!K3 -> 48 | C14: =兵种!Q3 -> 50 | D14: =兵种!R3 -> 150 | E14: =兵种!S3 -> 0 | F14: =兵种!T3 -> 10 | G14: =兵种!V3 -> 0 | H14: =24*3600*$K$3/B14 -> 52920 | I14: =C14*$H14 -> 2646000 | J14: =D14*$H14 -> 7938000 | K14: =E14*$H14 -> 0 | L14: =F14*$H14 -> 529200 | M14: =G14*$H14 -> 0 | N14: =I14/C$9 -> 3.3207831 | O14: =J14/D$9 -> 1.0724708 | P14: =K14/E$9 -> 0 | Q14: =L14/F$9 -> 0.081712062 | R14: =M14/G$9 -> 0 | S14: =SUM(O14:R14) -> 1.1541829 | T14: =兵种!J3 -> 1 | U14: =T14*H14 -> 52920 | V14: =兵种!O3 -> 1 | W14: =V14*H14 -> 52920
A15: =兵种!A4 -> Spy | B15: =兵种!K4 -> 103 | C15: =兵种!Q4 -> 120 | D15: =兵种!R4 -> 200 | E15: =兵种!S4 -> 0 | F15: =兵种!T4 -> 150 | G15: =兵种!V4 -> 0 | H15: =24*3600*$K$3/B15 -> 24661.748 | I15: =C15*$H15 -> 2959409.7 | J15: =D15*$H15 -> 4932349.5 | K15: =E15*$H15 -> 0 | L15: =F15*$H15 -> 3699262.1 | M15: =G15*$H15 -> 0 | N15: =I15/C$9 -> 3.7141186 | O15: =J15/D$9 -> 0.66638963 | P15: =K15/E$9 -> 0 | Q15: =L15/F$9 -> 0.57119111 | R15: =M15/G$9 -> 0 | S15: =SUM(O15:R15) -> 1.2375807 | T15: =兵种!J4 -> 2 | U15: =T15*H15 -> 49323.495 | V15: =兵种!O4 -> 1 | W15: =V15*H15 -> 24661.748
A16: =兵种!A5 -> Halberdsman | B16: =兵种!K5 -> 141 | C16: =兵种!Q5 -> 150 | D16: =兵种!R5 -> 500 | E16: =兵种!S5 -> 0 | F16: =兵种!T5 -> 100 | G16: =兵种!V5 -> 0 | H16: =24*3600*$K$3/B16 -> 18015.319 | I16: =C16*$H16 -> 2702297.9 | J16: =D16*$H16 -> 9007659.6 | K16: =E16*$H16 -> 0 | L16: =F16*$H16 -> 1801531.9 | M16: =G16*$H16 -> 0 | N16: =I16/C$9 -> 3.3914381 | O16: =J16/D$9 -> 1.2169882 | P16: =K16/E$9 -> 0 | Q16: =L16/F$9 -> 0.27816872 | R16: =M16/G$9 -> 0 | S16: =SUM(O16:R16) -> 1.4951569 | T16: =兵种!J5 -> 2 | U16: =T16*H16 -> 36030.638 | V16: =兵种!O5 -> 1 | W16: =V16*H16 -> 18015.319 | X16: =U16/(24*3600) -> 0.41702128
A17: =兵种!A6 -> Minotaur | B17: =兵种!K6 -> 219 | C17: =兵种!Q6 -> 200 | D17: =兵种!R6 -> 150 | E17: =兵种!S6 -> 0 | F17: =兵种!T6 -> 400 | G17: =兵种!V6 -> 0 | H17: =24*3600*$K$3/B17 -> 11598.904 | I17: =C17*$H17 -> 2319780.8 | J17: =D17*$H17 -> 1739835.6 | K17: =E17*$H17 -> 0 | L17: =F17*$H17 -> 4639561.6 | M17: =G17*$H17 -> 0 | N17: =I17/C$9 -> 2.9113715 | O17: =J17/D$9 -> 0.2350621 | P17: =K17/E$9 -> 0 | Q17: =L17/F$9 -> 0.71637972 | R17: =M17/G$9 -> 0 | S17: =SUM(O17:R17) -> 0.95144182 | T17: =兵种!J6 -> 3 | U17: =T17*H17 -> 34796.712 | V17: =兵种!O6 -> 1 | W17: =V17*H17 -> 11598.904 | X17: =U17/(24*3600) -> 0.40273973
A18: =兵种!A7 -> Longbowman | B18: =兵种!K7 -> 343 | C18: =兵种!Q7 -> 300 | D18: =兵种!R7 -> 350 | E18: =兵种!S7 -> 0 | F18: =兵种!T7 -> 300 | G18: =兵种!V7 -> 0 | H18: =24*3600*$K$3/B18 -> 7405.7143 | I18: =C18*$H18 -> 2221714.3 | J18: =D18*$H18 -> 2592000 | K18: =E18*$H18 -> 0 | L18: =F18*$H18 -> 2221714.3 | M18: =G18*$H18 -> 0 | N18: =I18/C$9 -> 2.788296 | O18: =J18/D$9 -> 0.35019455 | P18: =K18/E$9 -> 0 | Q18: =L18/F$9 -> 0.34304772 | R18: =M18/G$9 -> 0 | S18: =SUM(O18:R18) -> 0.69324228 | T18: =兵种!J7 -> 4 | U18: =T18*H18 -> 29622.857 | V18: =兵种!O7 -> 2 | W18: =V18*H18 -> 14811.429 | X18: =U18/(24*3600) -> 0.34285714
A19: =兵种!A8 -> SwiftStrikeDragon | B19: =兵种!K8 -> 498 | C19: =兵种!Q8 -> 1000 | D19: =兵种!R8 -> 600 | E19: =兵种!S8 -> 0 | F19: =兵种!T8 -> 500 | G19: =兵种!V8 -> 0 | H19: =24*3600*$K$5/B19 -> 5610.7952 | I19: =C19*$H19 -> 5610795.2 | J19: =D19*$H19 -> 3366477.1 | K19: =E19*$H19 -> 0 | L19: =F19*$H19 -> 2805397.6 | M19: =G19*$H19 -> 0 | N19: =I19/C$9 -> 7.0416606 | O19: =J19/D$9 -> 0.454831 | P19: =K19/E$9 -> 0 | Q19: =L19/F$9 -> 0.43317238 | R19: =M19/G$9 -> 0 | S19: =SUM(O19:R19) -> 0.88800338 | T19: =兵种!J8 -> 5 | U19: =T19*H19 -> 28053.976 | V19: =兵种!O8 -> 3 | W19: =V19*H19 -> 16832.386 | X19: =U19/(24*3600) -> 0.3246988
A20: =兵种!A9 -> BattleDragon | B20: =兵种!K9 -> 1492 | C20: =兵种!Q9 -> 2000 | D20: =兵种!R9 -> 500 | E20: =兵种!S9 -> 0 | F20: =兵种!T9 -> 2500 | G20: =兵种!V9 -> 0 | H20: =24*3600*$K$5/B20 -> 1872.7721 | I20: =C20*$H20 -> 3745544.2 | J20: =D20*$H20 -> 936386.06 | K20: =E20*$H20 -> 0 | L20: =F20*$H20 -> 4681930.3 | M20: =G20*$H20 -> 0 | N20: =I20/C$9 -> 4.7007332 | O20: =J20/D$9 -> 0.1265113 | P20: =K20/E$9 -> 0 | Q20: =L20/F$9 -> 0.72292173 | R20: =M20/G$9 -> 0 | S20: =SUM(O20:R20) -> 0.84943303 | T20: =兵种!J9 -> 7 | U20: =T20*H20 -> 13109.405 | V20: =兵种!O9 -> 6 | W20: =V20*H20 -> 11236.633 | X20: =U20/(24*3600) -> 0.15172922
A21: =兵种!A10 -> ArmoredTransport | B21: =兵种!K10 -> 975 | C21: =兵种!Q10 -> 600 | D21: =兵种!R10 -> 1500 | E21: =兵种!S10 -> 0 | F21: =兵种!T10 -> 350 | G21: =兵种!V10 -> 0 | H21: =24*3600*$K$3/B21 -> 2605.2923 | I21: =C21*$H21 -> 1563175.4 | J21: =D21*$H21 -> 3907938.5 | K21: =E21*$H21 -> 0 | L21: =F21*$H21 -> 911852.31 | M21: =G21*$H21 -> 0 | N21: =I21/C$9 -> 1.9618165 | O21: =J21/D$9 -> 0.52798563 | P21: =K21/E$9 -> 0 | Q21: =L21/F$9 -> 0.14079617 | R21: =M21/G$9 -> 0 | S21: =SUM(O21:R21) -> 0.6687818 | T21: =兵种!J10 -> 6 | U21: =T21*H21 -> 15631.754 | V21: =兵种!O10 -> 4 | W21: =V21*H21 -> 10421.169 | X21: =U21/(24*3600) -> 0.18092308
A22: =兵种!A11 -> Giant | B22: =兵种!K11 -> 4334 | C22: =兵种!Q11 -> 4000 | D22: =兵种!R11 -> 6000 | E22: =兵种!S11 -> 0 | F22: =兵种!T11 -> 1500 | G22: =兵种!V11 -> 0 | H22: =24*3600*$K$3/B22 -> 586.1006 | I22: =C22*$H22 -> 2344402.4 | J22: =D22*$H22 -> 3516603.6 | K22: =E22*$H22 -> 0 | L22: =F22*$H22 -> 879150.9 | M22: =G22*$H22 -> 0 | N22: =I22/C$9 -> 2.9422721 | O22: =J22/D$9 -> 0.47511398 | P22: =K22/E$9 -> 0 | Q22: =L22/F$9 -> 0.13574685 | R22: =M22/G$9 -> 0 | S22: =SUM(O22:R22) -> 0.61086083 | T22: =兵种!J11 -> 9 | U22: =T22*H22 -> 5274.9054 | V22: =兵种!O11 -> 8 | W22: =V22*H22 -> 4688.8048 | X22: =U22/(24*3600) -> 0.061052146
A23: =兵种!A12 -> FireMirror | B23: =兵种!K12 -> 5843 | C23: =兵种!Q12 -> 5000 | D23: =兵种!R12 -> 5000 | E23: =兵种!S12 -> 8000 | F23: =兵种!T12 -> 1200 | G23: =兵种!V12 -> 0 | H23: =24*3600*$K$3/B23 -> 434.73558 | I23: =C23*$H23 -> 2173677.9 | J23: =D23*$H23 -> 2173677.9 | K23: =E23*$H23 -> 3477884.6 | L23: =F23*$H23 -> 521682.7 | M23: =G23*$H23 -> 0 | N23: =I23/C$9 -> 2.7280094 | O23: =J23/D$9 -> 0.29367676 | P23: =K23/E$9 -> 1.0726266 | Q23: =L23/F$9 -> 0.08055134 | R23: =M23/G$9 -> 0 | S23: =SUM(O23:R23) -> 1.4468547 | T23: =兵种!J12 -> 10 | U23: =T23*H23 -> 4347.3558 | V23: =兵种!O12 -> 10 | W23: =V23*H23 -> 4347.3558 | X23: =U23/(24*3600) -> 0.050316618
A24: =兵种!A13 -> Fangtooth | B24: =兵种!K13 -> 2000 | C24: =兵种!Q13 -> 4000 | D24: =兵种!R13 -> 5500 | E24: =兵种!S13 -> 7000 | F24: =兵种!T13 -> 2500 | G24: =兵种!V13 -> 100 | H24: =24*3600*$K$3/B24 -> 1270.08 | I24: =C24*$H24 -> 5080320 | J24: =D24*$H24 -> 6985440 | K24: =E24*$H24 -> 8890560 | L24: =F24*$H24 -> 3175200 | M24: =G24*$H24 -> 127008 | N24: =I24/C$9 -> 6.3759036 | O24: =J24/D$9 -> 0.94377432 | P24: =K24/E$9 -> 2.7419689 | Q24: =L24/F$9 -> 0.49027237 | R24: =M24/G$9 -> 3.675 | S24: =SUM(O24:R24) -> 7.8510156 | T24: =兵种!J13 -> 10 | U24: =T24*H24 -> 12700.8 | V24: =兵种!O13 -> 9 | W24: =V24*H24 -> 11430.72 | X24: =U24/(24*3600) -> 0.147
A25: =兵种!A18 -> BlackholeOne | B25: =兵种!K18 -> 0 | G25: =兵种!V18 -> 0 | H25: =24*3600*$K$3/B25 -> #DIV/0! | I25: =C25*$H25 -> #DIV/0! | J25: =D25*$H25 -> #DIV/0! | K25: =E25*$H25 -> #DIV/0! | L25: =F25*$H25 -> #DIV/0! | M25: =G25*$H25 -> #DIV/0! | N25: =I25/C$9 -> #DIV/0! | O25: =J25/D$9 -> #DIV/0! | P25: =K25/E$9 -> #DIV/0! | Q25: =L25/F$9 -> #DIV/0! | R25: =M25/G$9 -> #DIV/0! | S25: =SUM(O25:R25) -> #DIV/0! | T25: =兵种!J18 -> 0 | U25: =T25*H25 -> #DIV/0!
A26: =兵种!A19 -> Shredder | B26: =兵种!K19 -> 498 | G26: =兵种!V19 -> 0 | H26: =24*3600*$K$3/B26 -> 5100.7229 | I26: =C26*$H26 -> 0 | J26: =D26*$H26 -> 0 | K26: =E26*$H26 -> 0 | L26: =F26*$H26 -> 0 | M26: =G26*$H26 -> 0 | N26: =I26/C$9 -> 0 | O26: =J26/D$9 -> 0 | P26: =K26/E$9 -> 0 | Q26: =L26/F$9 -> 0 | R26: =M26/G$9 -> 0 | S26: =SUM(O26:R26) -> 0 | T26: =兵种!J19 -> 5 | U26: =T26*H26 -> 25503.614
A27: =兵种!A20 -> Rager | B27: =兵种!K20 -> 5843 | G27: =兵种!V20 -> 0 | H27: =24*3600*$K$3/B27 -> 434.73558 | I27: =C27*$H27 -> 0 | J27: =D27*$H27 -> 0 | K27: =E27*$H27 -> 0 | L27: =F27*$H27 -> 0 | M27: =G27*$H27 -> 0 | N27: =I27/C$9 -> 0 | O27: =J27/D$9 -> 0 | P27: =K27/E$9 -> 0 | Q27: =L27/F$9 -> 0 | R27: =M27/G$9 -> 0 | S27: =SUM(O27:R27) -> 0 | T27: =兵种!J20 -> 10 | U27: =T27*H27 -> 4347.3558
A28: =兵种!A21 -> Cannibal | B28: =兵种!K21 -> 26 | G28: =兵种!V21 -> 0 | H28: =24*3600*$K$3/B28 -> 97698.462 | I28: =C28*$H28 -> 0 | J28: =D28*$H28 -> 0 | K28: =E28*$H28 -> 0 | L28: =F28*$H28 -> 0 | M28: =G28*$H28 -> 0 | N28: =I28/C$9 -> 0 | O28: =J28/D$9 -> 0 | P28: =K28/E$9 -> 0 | Q28: =L28/F$9 -> 0 | R28: =M28/G$9 -> 0 | S28: =SUM(O28:R28) -> 0 | T28: =兵种!J21 -> 1 | U28: =T28*H28 -> 97698.462
A29: =兵种!A22 -> Chieftan | B29: =兵种!K22 -> 1492 | G29: =兵种!V22 -> 0 | H29: =24*3600*$K$3/B29 -> 1702.5201 | I29: =C29*$H29 -> 0 | J29: =D29*$H29 -> 0 | K29: =E29*$H29 -> 0 | L29: =F29*$H29 -> 0 | M29: =G29*$H29 -> 0 | N29: =I29/C$9 -> 0 | O29: =J29/D$9 -> 0 | P29: =K29/E$9 -> 0 | Q29: =L29/F$9 -> 0 | R29: =M29/G$9 -> 0 | S29: =SUM(O29:R29) -> 0 | T29: =兵种!J22 -> 7 | U29: =T29*H29 -> 11917.641
A30: =兵种!A23 -> Brat | B30: =兵种!K23 -> 48 | G30: =兵种!V23 -> 0 | H30: =24*3600*$K$3/B30 -> 52920 | I30: =C30*$H30 -> 0 | J30: =D30*$H30 -> 0 | K30: =E30*$H30 -> 0 | L30: =F30*$H30 -> 0 | M30: =G30*$H30 -> 0 | N30: =I30/C$9 -> 0 | O30: =J30/D$9 -> 0 | P30: =K30/E$9 -> 0 | Q30: =L30/F$9 -> 0 | R30: =M30/G$9 -> 0 | S30: =SUM(O30:R30) -> 0 | T30: =兵种!J23 -> 1 | U30: =T30*H30 -> 52920
A31: =兵种!A24 -> SheDevil | B31: =兵种!K24 -> 141 | G31: =兵种!V24 -> 0 | H31: =24*3600*$K$3/B31 -> 18015.319 | I31: =C31*$H31 -> 0 | J31: =D31*$H31 -> 0 | K31: =E31*$H31 -> 0 | L31: =F31*$H31 -> 0 | M31: =G31*$H31 -> 0 | N31: =I31/C$9 -> 0 | O31: =J31/D$9 -> 0 | P31: =K31/E$9 -> 0 | Q31: =L31/F$9 -> 0 | R31: =M31/G$9 -> 0 | S31: =SUM(O31:R31) -> 0 | T31: =兵种!J24 -> 2 | U31: =T31*H31 -> 36030.638
A32: =兵种!A25 -> Clubber | B32: =兵种!K25 -> 219 | G32: =兵种!V25 -> 0 | H32: =24*3600*$K$3/B32 -> 11598.904 | I32: =C32*$H32 -> 0 | J32: =D32*$H32 -> 0 | K32: =E32*$H32 -> 0 | L32: =F32*$H32 -> 0 | M32: =G32*$H32 -> 0 | N32: =I32/C$9 -> 0 | O32: =J32/D$9 -> 0 | P32: =K32/E$9 -> 0 | Q32: =L32/F$9 -> 0 | R32: =M32/G$9 -> 0 | S32: =SUM(O32:R32) -> 0 | T32: =兵种!J25 -> 3 | U32: =T32*H32 -> 34796.712
A33: =兵种!A26 -> Blood | B33: =兵种!K26 -> 4334 | G33: =兵种!V26 -> 0 | H33: =24*3600*$K$3/B33 -> 586.1006 | I33: =C33*$H33 -> 0 | J33: =D33*$H33 -> 0 | K33: =E33*$H33 -> 0 | L33: =F33*$H33 -> 0 | M33: =G33*$H33 -> 0 | N33: =I33/C$9 -> 0 | O33: =J33/D$9 -> 0 | P33: =K33/E$9 -> 0 | Q33: =L33/F$9 -> 0 | R33: =M33/G$9 -> 0 | S33: =SUM(O33:R33) -> 0 | T33: =兵种!J26 -> 9 | U33: =T33*H33 -> 5274.9054
A34: =兵种!A27 -> Hurler | B34: =兵种!K27 -> 343 | G34: =兵种!V27 -> 0 | H34: =24*3600*$K$3/B34 -> 7405.7143 | I34: =C34*$H34 -> 0 | J34: =D34*$H34 -> 0 | K34: =E34*$H34 -> 0 | L34: =F34*$H34 -> 0 | M34: =G34*$H34 -> 0 | N34: =I34/C$9 -> 0 | O34: =J34/D$9 -> 0 | P34: =K34/E$9 -> 0 | Q34: =L34/F$9 -> 0 | R34: =M34/G$9 -> 0 | S34: =SUM(O34:R34) -> 0 | T34: =兵种!J27 -> 4 | U34: =T34*H34 -> 29622.857
A35: =兵种!A28 -> Stench | B35: =兵种!K28 -> 103 | G35: =兵种!V28 -> 0 | H35: =24*3600*$K$3/B35 -> 24661.748 | I35: =C35*$H35 -> 0 | J35: =D35*$H35 -> 0 | K35: =E35*$H35 -> 0 | L35: =F35*$H35 -> 0 | M35: =G35*$H35 -> 0 | N35: =I35/C$9 -> 0 | O35: =J35/D$9 -> 0 | P35: =K35/E$9 -> 0 | Q35: =L35/F$9 -> 0 | R35: =M35/G$9 -> 0 | S35: =SUM(O35:R35) -> 0 | T35: =兵种!J28 -> 2 | U35: =T35*H35 -> 49323.495

Sheet buff加成
A1: 单层 | C1: unit | I1: guard dragon | Q1: 0
B2: max lv | C2: Ranged Damage | D2: Melee Damage | E2: Defense | F2: Life | G2: Speed | H2: Range | I2: Ranged | J2: Melee | K2: Defense | L2: Life | M2: Speed | N2: Range | Q2: 1
A3: player | B3: 1 | C3: 0.2 | D3: 0.2 | E3: 0.2 | I3: 0.2 | J3: 0.2 | K3: 0.2 | Q3: 2
A4: AerialCombat | B4: 10 | I4: 0.05 | J4: 0.05 | Q4: 3
A5: wall | B5: 20 | E5: 0.025 | K5: 0.025 | Q5: 4
A6: dragon_attack | B6: 1 | I6: 0.2 | J6: 0.2 | Q6: 5
A7: dragon_defence | B7: 1 | K7: 0.2 | Q7: 6
A8: dragon hearts | B8: 1 | C8: 0.2 | D8: 0.2 | Q8: 7
A9: glowing shields | B9: 1 | E9: 0.2 | Q9: 8
A10: general attack | B10: 20 | C10: =LOOKUP(B10,将领!D:D,将领!F:F)/100 -> 0.3 | D10: =C10 -> 0.3 | Q10: 9
A11: general defence | B11: 20 | E11: =LOOKUP(B11,将领!D:D,将领!G:G)/100 -> 0.35 | Q11: 10
A12: Metallurgy | B12: 10 | C12: 0.05 | D12: 0.05 | E12: 0.05 | Q12: 11
A13: with_dragon | B13: 20 | C13: 0.05 | D13: 0.05 | Q13: 12
A14: RapidDeployment | B14: 10 | G14: 0.05 | Q14: 13
A15: Dragonry | B15: 10 | G15: 0.05 | Q15: 14
A16: medicine | B16: 10 | F16: 0.05 | Q16: 15
A17: Ballistics | B17: 10 | H17: 0.05 | Q17: 16
A19: 最大 | C19: unit | I19: guard dragon | Q19: 17
B20: max lv | C20: Ranged Damage | D20: Melee Damage | E20: Defense | F20: Life | G20: Speed | H20: Range | I20: Ranged | J20: Melee | K20: Defense | L20: Life | M20: Speed | N20: Range | Q20: 18
A21: player | B21: 1 | C21: =$B3*C3 -> 0.2 | D21: =$B3*D3 -> 0.2 | E21: =$B3*E3 -> 0.2 | F21: =$B3*F3 -> 0 | G21: =$B3*G3 -> 0 | H21: =$B3*H3 -> 0 | I21: =$B3*I3 -> 0.2 | J21: =$B3*J3 -> 0.2 | ... N21: =$B3*N3 -> 0 | Q21: 19
A22: AerialCombat | B22: 10 | C22: =$B4*C4 -> 0 | D22: =$B4*D4 -> 0 | E22: =$B4*E4 -> 0 | F22: =$B4*F4 -> 0 | G22: =$B4*G4 -> 0 | H22: =$B4*H4 -> 0 | I22: =$B4*I4 -> 0.5 | J22: =$B4*J4 -> 0.5 | ... N22: =$B4*N4 -> 0 | Q22: 20
A23: wall | B23: 20 | C23: =$B5*C5 -> 0 | D23: =$B5*D5 -> 0 | E23: =$B5*E5 -> 0.5 | F23: =$B5*F5 -> 0 | G23: =$B5*G5 -> 0 | H23: =$B5*H5 -> 0 | I23: =$B5*I5 -> 0 | J23: =$B5*J5 -> 0 | ... N23: =$B5*N5 -> 0
A24: dragon_attack | B24: 1 | C24: =$B6*C6 -> 0 | D24: =$B6*D6 -> 0 | E24: =$B6*E6 -> 0 | F24: =$B6*F6 -> 0 | G24: =$B6*G6 -> 0 | H24: =$B6*H6 -> 0 | I24: =$B6*I6 -> 0.2 | J24: =$B6*J6 -> 0.2 | ... N24: =$B6*N6 -> 0
A25: dragon_defence | B25: 1 | C25: =$B7*C7 -> 0 | D25: =$B7*D7 -> 0 | E25: =$B7*E7 -> 0 | F25: =$B7*F7 -> 0 | G25: =$B7*G7 -> 0 | H25: =$B7*H7 -> 0 | I25: =$B7*I7 -> 0 | J25: =$B7*J7 -> 0 | ... N25: =$B7*N7 -> 0
A26: dragon hearts | B26: 1 | C26: =$B8*C8 -> 0.2 | D26: =$B8*D8 -> 0.2 | E26: =$B8*E8 -> 0 | F26: =$B8*F8 -> 0 | G26: =$B8*G8 -> 0 | H26: =$B8*H8 -> 0 | I26: =$B8*I8 -> 0 | J26: =$B8*J8 -> 0 | ... N26: =$B8*N8 -> 0
A27: glowing shields | B27: 1 | C27: =$B9*C9 -> 0 | D27: =$B9*D9 -> 0 | E27: =$B9*E9 -> 0.2 | F27: =$B9*F9 -> 0 | G27: =$B9*G9 -> 0 | H27: =$B9*H9 -> 0 | I27: =$B9*I9 -> 0 | J27: =$B9*J9 -> 0 | ... N27: =$B9*N9 -> 0
A28: general attack | B28: 20 | C28: =C10 -> 0.3 | D28: =D10 -> 0.3 | E28: =E10 -> 0 | F28: =F10 -> 0 | G28: =G10 -> 0 | H28: =H10 -> 0 | I28: =I10 -> 0 | J28: =J10 -> 0 | ... N28: =N10 -> 0
A29: general defence | B29: 20 | C29: =C11 -> 0 | D29: =D11 -> 0 | E29: =E11 -> 0.35 | F29: =F11 -> 0 | G29: =G11 -> 0 | H29: =H11 -> 0 | I29: =I11 -> 0 | J29: =J11 -> 0 | ... N29: =N11 -> 0
A30: Metallurgy | B30: 10 | C30: =$B12*C12 -> 0.5 | D30: =$B12*D12 -> 0.5 | E30: =$B12*E12 -> 0.5 | F30: =$B12*F12 -> 0 | G30: =$B12*G12 -> 0 | H30: =$B12*H12 -> 0 | I30: =$B12*I12 -> 0 | J30: =$B12*J12 -> 0 | ... N30: =$B12*N12 -> 0
A31: with_dragon | B31: 20 | C31: =$B13*C13 -> 1 | D31: =$B13*D13 -> 1 | E31: =$B13*E13 -> 0 | F31: =$B13*F13 -> 0 | G31: =$B13*G13 -> 0 | H31: =$B13*H13 -> 0 | I31: =$B13*I13 -> 0 | J31: =$B13*J13 -> 0 | ... N31: =$B13*N13 -> 0
A32: RapidDeployment | B32: 10 | C32: =$B14*C14 -> 0 | D32: =$B14*D14 -> 0 | E32: =$B14*E14 -> 0 | F32: =$B14*F14 -> 0 | G32: =$B14*G14 -> 0.5 | H32: =$B14*H14 -> 0 | I32: =$B14*I14 -> 0 | J32: =$B14*J14 -> 0 | ... N32: =$B14*N14 -> 0
A33: Dragonry（BD SSD） | B33: 10 | C33: =$B15*C15 -> 0 | D33: =$B15*D15 -> 0 | E33: =$B15*E15 -> 0 | F33: =$B15*F15 -> 0 | G33: =$B15*G15 -> 0.5 | H33: =$B15*H15 -> 0 | I33: =$B15*I15 -> 0 | J33: =$B15*J15 -> 0 | ... N33: =$B15*N15 -> 0
A34: medicine | B34: 10 | C34: =$B16*C16 -> 0 | D34: =$B16*D16 -> 0 | E34: =$B16*E16 -> 0 | F34: =$B16*F16 -> 0.5 | G34: =$B16*G16 -> 0 | H34: =$B16*H16 -> 0 | I34: =$B16*I16 -> 0 | J34: =$B16*J16 -> 0 | ... N34: =$B16*N16 -> 0
A35: Ballistics | B35: 10 | C35: =$B17*C17 -> 0 | D35: =$B17*D17 -> 0 | E35: =$B17*E17 -> 0 | F35: =$B17*F17 -> 0 | G35: =$B17*G17 -> 0 | H35: =$B17*H17 -> 0.5 | I35: =$B17*I17 -> 0 | J35: =$B17*J17 -> 0 | ... N35: =$B17*N17 -> 0
A37: total | C37: =SUM(C21:C35) -> 2.2 | D37: =SUM(D21:D35) -> 2.2 | E37: =SUM(E21:E35) -> 1.75 | F37: =SUM(F21:F35) -> 0.5 | G37: =SUM(G21:G35) -> 1 | H37: =SUM(H21:H35) -> 0.5 | I37: =SUM(I21:I35) -> 0.9 | J37: =SUM(J21:J35) -> 0.9 | ... N37: =SUM(N21:N35) -> 0

Sheet 军队资源点等
A1: 集结点 | B1: 可派出军队支数 | C1: 每只军队数量上限 | E1: 城堡等级 | F1: 可占据资源点数量 | G1: 可接受援军 | H1: 开启资源点 | J1: 仓库 | K1: 保护资源
A2: 1 | B2: 1 | C2: 10000 | E2: 1 | F2: 1 | G2: 1 | H2: 11 | J2: 1 | K2: 50000
A3: 2 | B3: 1 | C3: 15000 | E3: 2 | F3: 1 | G3: 1 | H3: 2 | J3: 2 | K3: 100000 | M3: 间谍科技效果 | O3: 岗哨效果
A4: 3 | B4: =B2+1 -> 2 | C4: 20000 | E4: 3 | F4: 2 | G4: 2 | H4: 1 | J4: 3 | K4: 150000 | M4: clairvoyance | N4: Info Gathered | O4: Level | P4: Sentinel Reports
A5: 4 | B5: =B3+1 -> 2 | C5: 25000 | E5: 4 | F5: 2 | G5: 2 | H5: 2 | J5: 4 | K5: 200000 | M5: 1 | N5: Idea of Resources | O5: 2 | P5: Enemy approaching
A6: 5 | B6: =B4+1 -> 3 | C6: 30000 | E6: 5 | F6: 3 | G6: 3 | H6: 1 | J6: 5 | K6: 250000 | M6: 2 | N6: Exact # of Resources | O6: 4 | P6: Spy or Attack
A7: 6 | B7: =B5+1 -> 3 | C7: 35000 | E7: 6 | F7: 3 | G7: 3 | H7: 2 | J7: 6 | K7: 300000 | M7: 3 | N7: Idea of Troops | O7: 6 | P7: Knows the time of attack
A8: 7 | B8: =B6+1 -> 4 | C8: 40000 | E8: 7 | F8: 4 | G8: 4 | H8: 1 | J8: 7 | K8: 350000 | M8: 4 | N8: Exact # of Troops | O8: 8 | P8: Title and Alliance of attacker
A9: 8 | B9: =B7+1 -> 4 | C9: 45000 | E9: 8 | F9: 4 | G9: 4 | H9: 2 | J9: 8 | K9: 400000 | M9: 5 | N9: Type of troops | O9: 10 | P9: Strength of General
A10: 9 | B10: =B8+1 -> 5 | C10: 50000 | E10: 9 | F10: 5 | G10: 5 | H10: 1 | J10: 9 | K10: 450000 | M10: 6 | N10: Wilderness Owner | O10: 12 | P10: Approx. how many troops
A11: 10 | B11: =B9+1 -> 5 | C11: 55000 | E11: 10 | F11: 5 | G11: 5 | H11: 2 | J11: 10 | K11: 500000 | M11: 7 | N11: Idea of Researches | O11: 14 | P11: Troop types
A12: 11 | B12: =B10+1 -> 6 | C12: 60000 | E12: 11 | F12: 6 | G12: 5 | H12: 1 | J12: 11 | K12: 550000 | M12: 8 | N12: Exact Researches | O12: 16 | P12: Approx. # of troops in type
A13: 12 | B13: =B11+1 -> 6 | C13: 65000 | E13: 12 | F13: 6 | G13: 6 | H13: 2 | J13: 12 | K13: 600000 | M13: 9 | N13: Exact # of Gold | O13: 18 | P13: Exact # of troops
A14: 13 | B14: =B12+1 -> 7 | C14: 70000 | E14: 13 | F14: 7 | G14: 6 | H14: 1 | J14: 13 | K14: 650000 | M14: 10 | N14: Last Login time/date | O14: 20 | P14: Attacker's name
A15: 14 | B15: =B13+1 -> 7 | C15: 75000 | E15: 14 | F15: 7 | G15: 7 | H15: 2 | J15: 14 | K15: 700000
A16: 15 | B16: =B14+1 -> 8 | C16: 80000 | E16: 15 | F16: 7 | G16: 7 | H16: 1 | J16: 15 | K16: 750000
A17: 16 | B17: =B15+1 -> 8 | C17: 85000 | E17: 16 | F17: 8 | G17: 8 | H17: 2 | J17: 16 | K17: 800000 | N17: 0 => [],
A18: 17 | B18: =B16+1 -> 9 | C18: 90000 | E18: 17 | F18: 8 | G18: 8 | H18: 1 | J18: 17 | K18: 850000 | M18: 1 | N18: 1 => [:resources_estimate], # estimated: true
A19: 18 | B19: =B17+1 -> 9 | C19: 93000 | E19: 18 | F19: 9 | G19: 9 | H19: 1 | J19: 18 | K19: 900000 | M19: 2 | N19: 2 => [:resources], # estimated: false
A20: 19 | B20: 9 | C20: 96000 | E20: 19 | F20: 9 | G20: 9 | H20: 1 | J20: 19 | K20: 950000 | M20: 3 | N20: 3 => [:resources, :defender_types], # -1 in array, estimated: false
A21: 20 | B21: =B19+1 -> 10 | C21: 100000 | E21: 20 | F21: 10 | G21: 10 | H21: 1 | J21: 20 | K21: 1000000 | M21: 4 | N21: 4 => [:resources, :defenders_estimate], # estimated: true
M22: 5 | N22: 5 => [:resources, :defenders_estimate],
M23: 6 | N23: 6 => [:resources, :defenders], # estimated: false
M24: 7 | N24: 7 => [:resources, :defenders, :research_without_level],
M25: 8 | N25: 8 => [:resources, :defenders, :research],
M26: 9 | N26: 9 => [:resources, :defenders, :research],
M27: 10 | N27: 10 => [:resources, :defenders, :research, :last_login]

Sheet recovery
B1: instant ruby | C1: recovery ruby | F1: 复活数量 | G1: 折扣系数
A2: Porter | B2: 1 | C2: 0.6 | F2: 1-1000 | G2: 0.7
A3: Conscript | B3: 1 | C3: 0.7 | F3: 1001-20000 | G3: 0.6
A4: Spy | B4: 2 | C4: 0.6 | F4: 20001-50000 | G4: 0.55
A5: Halberdsman | B5: 4 | C5: 2 | F5: 50000- | G5: 0.5
A6: Minotaur | B6: 3 | C6: 2
A7: Longbowman | B7: 5 | C7: 3
A8: SwiftStrikeDragon | B8: 5 | C8: 3 | F8: 实际recovery单价=recovery ruby*折扣系数
A9: BattleDragon | B9: 7 | C9: 4
A10: ArmoredTransport | B10: 6 | C10: 3.5
A11: Giant | B11: 15 | C11: 8.5
A12: FireMirror | B12: 17 | C12: 10
A13: Fangtooth | B13: 15 | C13: 8.5

Sheet 龙属性json用
A1: { | E1: =A1&C1&B1&D1 -> { | H1: {
A2: "1" | B2: { | C2: : | E2: =A2&C2&B2&D2 -> "1": { | H2: "1": {
A3: "level" | B3: 1 | C3: : | D3: , | E3: =A3&C3&B3&D3 -> "level": 1, | H3: "level": 1,
A4: "ranged" | B4: 20 | C4: : | D4: , | E4: =A4&C4&B4&D4 -> "ranged": 20, | H4: "ranged": 0,
A5: "melee" | B5: 20 | C5: : | D5: , | E5: =A5&C5&B5&D5 -> "melee": 20, | H5: "melee": 0,
A6: "defense" | B6: 10 | C6: : | D6: , | E6: =A6&C6&B6&D6 -> "defense": 10, | H6: "defense": 0,
A7: "life" | B7: 1666 | C7: : | D7: , | E7: =A7&C7&B7&D7 -> "life": 1666, | H7: "life": 0,
A8: "speed" | B8: 300 | C8: : | D8: , | E8: =A8&C8&B8&D8 -> "speed": 300, | H8: "speed": 375,
A9: "range" | B9: 1800 | C9: : | D9: , | E9: =A9&C9&B9&D9 -> "range": 1800, | H9: "range": 650,
A10: "load" | B10: 0 | C10: : | D10: , | E10: =A10&C10&B10&D10 -> "load": 0, | H10: "load": 0,
A11: "upkeep" | B11: 0 | C11: : | D11: , | E11: =A11&C11&B11&D11 -> "upkeep": 0, | H11: "upkeep": 0,
A12: "might" | B12: 0 | C12: : | D12: , | E12: =A12&C12&B12&D12 -> "might": 0, | H12: "might": 0,
A13: "transform" | B13: 0 | C13: : | E13: =A13&C13&B13&D13 -> "transform": 0 | H13: "transform": 0
A14: }, | E14: =A14&C14&B14&D14 -> }, | H14: },
A15: "2" | B15: { | C15: : | E15: =A15&C15&B15&D15 -> "2": { | H15: "2": {
A16: "level" | B16: 2 | C16: : | D16: , | E16: =A16&C16&B16&D16 -> "level": 2, | H16: "level": 2,
A17: "ranged" | B17: 40 | C17: : | D17: , | E17: =A17&C17&B17&D17 -> "ranged": 40, | H17: "ranged": 0,
A18: "melee" | B18: 40 | C18: : | D18: , | E18: =A18&C18&B18&D18 -> "melee": 40, | H18: "melee": 0,
A19: "defense" | B19: 20 | C19: : | D19: , | E19: =A19&C19&B19&D19 -> "defense": 20, | H19: "defense": 0,
A20: "life" | B20: 3333 | C20: : | D20: , | E20: =A20&C20&B20&D20 -> "life": 3333, | H20: "life": 0,
A21: "speed" | B21: 300 | C21: : | D21: , | E21: =A21&C21&B21&D21 -> "speed": 300, | H21: "speed": 650,
A22: "range" | B22: 1800 | C22: : | D22: , | E22: =A22&C22&B22&D22 -> "range": 1800, | H22: "range": 1400,
A23: "load" | B23: 0 | C23: : | D23: , | E23: =A23&C23&B23&D23 -> "load": 0, | H23: "load": 0,
A24: "upkeep" | B24: 0 | C24: : | D24: , | E24: =A24&C24&B24&D24 -> "upkeep": 0, | H24: "upkeep": 0,
A25: "might" | B25: 0 | C25: : | D25: , | E25: =A25&C25&B25&D25 -> "might": 0, | H25: "might": 0,
A26: "transform" | B26: 0 | C26: : | E26: =A26&C26&B26&D26 -> "transform": 0 | H26: "transform": 0
A27: }, | E27: =A27&C27&B27&D27 -> }, | H27: },
A28: "3" | B28: { | C28: : | E28: =A28&C28&B28&D28 -> "3": { | H28: "3": {
A29: "level" | B29: 3 | C29: : | D29: , | E29: =A29&C29&B29&D29 -> "level": 3, | H29: "level": 3,
A30: "ranged" | B30: 60 | C30: : | D30: , | E30: =A30&C30&B30&D30 -> "ranged": 60, | H30: "ranged": 50,
A31: "melee" | B31: 60 | C31: : | D31: , | E31: =A31&C31&B31&D31 -> "melee": 60, | H31: "melee": 50,
A32: "defense" | B32: 34 | C32: : | D32: , | E32: =A32&C32&B32&D32 -> "defense": 34, | H32: "defense": 50,
A33: "life" | B33: 5000 | C33: : | D33: , | E33: =A33&C33&B33&D33 -> "life": 5000, | H33: "life": 5000,
A34: "speed" | B34: 300 | C34: : | D34: , | E34: =A34&C34&B34&D34 -> "speed": 300, | H34: "speed": 650,
A35: "range" | B35: 1800 | C35: : | D35: , | E35: =A35&C35&B35&D35 -> "range": 1800, | H35: "range": 1400,
A36: "load" | B36: 0 | C36: : | D36: , | E36: =A36&C36&B36&D36 -> "load": 0, | H36: "load": 0,
A37: "upkeep" | B37: 50 | C37: : | D37: , | E37: =A37&C37&B37&D37 -> "upkeep": 50, | H37: "upkeep": 50,
A38: "might" | B38: 0 | C38: : | D38: , | E38: =A38&C38&B38&D38 -> "might": 0, | H38: "might": 0,
A39: "transform" | B39: 0 | C39: : | E39: =A39&C39&B39&D39 -> "transform": 0 | H39: "transform": 0
A40: }, | E40: =A40&C40&B40&D40 -> }, | H40: },
A41: "4" | B41: { | C41: : | E41: =A41&C41&B41&D41 -> "4": { | H41: "4": {
A42: "level" | B42: 4 | C42: : | D42: , | E42: =A42&C42&B42&D42 -> "level": 4, | H42: "level": 4,
A43: "ranged" | B43: 120 | C43: : | D43: , | E43: =A43&C43&B43&D43 -> "ranged": 120, | H43: "ranged": 100,
A44: "melee" | B44: 120 | C44: : | D44: , | E44: =A44&C44&B44&D44 -> "melee": 120, | H44: "melee": 100,
A45: "defense" | B45: 69 | C45: : | D45: , | E45: =A45&C45&B45&D45 -> "defense": 69, | H45: "defense": 100,
A46: "life" | B46: 10000 | C46: : | D46: , | E46: =A46&C46&B46&D46 -> "life": 10000, | H46: "life": 10000,
A47: "speed" | B47: 300 | C47: : | D47: , | E47: =A47&C47&B47&D47 -> "speed": 300, | H47: "speed": 650,
A48: "range" | B48: 1800 | C48: : | D48: , | E48: =A48&C48&B48&D48 -> "range": 1800, | H48: "range": 1400,
A49: "load" | B49: 0 | C49: : | D49: , | E49: =A49&C49&B49&D49 -> "load": 0, | H49: "load": 0,
A50: "upkeep" | B50: 100 | C50: : | D50: , | E50: =A50&C50&B50&D50 -> "upkeep": 100, | H50: "upkeep": 100,
A51: "might" | B51: 0 | C51: : | D51: , | E51: =A51&C51&B51&D51 -> "might": 0, | H51: "might": 0,
A52: "transform" | B52: 0 | C52: : | E52: =A52&C52&B52&D52 -> "transform": 0 | H52: "transform": 0
A53: }, | E53: =A53&C53&B53&D53 -> }, | H53: },
A54: "5" | B54: { | C54: : | E54: =A54&C54&B54&D54 -> "5": { | H54: "5": {
A55: "level" | B55: 5 | C55: : | D55: , | E55: =A55&C55&B55&D55 -> "level": 5, | H55: "level": 5,
A56: "ranged" | B56: 180 | C56: : | D56: , | E56: =A56&C56&B56&D56 -> "ranged": 180, | H56: "ranged": 150,
A57: "melee" | B57: 180 | C57: : | D57: , | E57: =A57&C57&B57&D57 -> "melee": 180, | H57: "melee": 150,
A58: "defense" | B58: 104 | C58: : | D58: , | E58: =A58&C58&B58&D58 -> "defense": 104, | H58: "defense": 150,
A59: "life" | B59: 14000 | C59: : | D59: , | E59: =A59&C59&B59&D59 -> "life": 14000, | H59: "life": 14000,
A60: "speed" | B60: 300 | C60: : | D60: , | E60: =A60&C60&B60&D60 -> "speed": 300, | H60: "speed": 650,
A61: "range" | B61: 1800 | C61: : | D61: , | E61: =A61&C61&B61&D61 -> "range": 1800, | H61: "range": 1400,
A62: "load" | B62: 0 | C62: : | D62: , | E62: =A62&C62&B62&D62 -> "load": 0, | H62: "load": 0,
A63: "upkeep" | B63: 150 | C63: : | D63: , | E63: =A63&C63&B63&D63 -> "upkeep": 150, | H63: "upkeep": 150,
A64: "might" | B64: 0 | C64: : | D64: , | E64: =A64&C64&B64&D64 -> "might": 0, | H64: "might": 0,
A65: "transform" | B65: 0 | C65: : | E65: =A65&C65&B65&D65 -> "transform": 0 | H65: "transform": 0
A66: }, | E66: =A66&C66&B66&D66 -> }, | H66: },
A67: "6" | B67: { | C67: : | E67: =A67&C67&B67&D67 -> "6": { | H67: "6": {
A68: "level" | B68: 6 | C68: : | D68: , | E68: =A68&C68&B68&D68 -> "level": 6, | H68: "level": 6,
A69: "ranged" | B69: 240 | C69: : | D69: , | E69: =A69&C69&B69&D69 -> "ranged": 240, | H69: "ranged": 200,
A70: "melee" | B70: 240 | C70: : | D70: , | E70: =A70&C70&B70&D70 -> "melee": 240, | H70: "melee": 200,
A71: "defense" | B71: 138 | C71: : | D71: , | E71: =A71&C71&B71&D71 -> "defense": 138, | H71: "defense": 200,
A72: "life" | B72: 20000 | C72: : | D72: , | E72: =A72&C72&B72&D72 -> "life": 20000, | H72: "life": 20000,
A73: "speed" | B73: 300 | C73: : | D73: , | E73: =A73&C73&B73&D73 -> "speed": 300, | H73: "speed": 650,
A74: "range" | B74: 1800 | C74: : | D74: , | E74: =A74&C74&B74&D74 -> "range": 1800, | H74: "range": 1400,
A75: "load" | B75: 0 | C75: : | D75: , | E75: =A75&C75&B75&D75 -> "load": 0, | H75: "load": 0,
A76: "upkeep" | B76: 200 | C76: : | D76: , | E76: =A76&C76&B76&D76 -> "upkeep": 200, | H76: "upkeep": 200,
A77: "might" | B77: 0 | C77: : | D77: , | E77: =A77&C77&B77&D77 -> "might": 0, | H77: "might": 0,
A78: "transform" | B78: 0 | C78: : | E78: =A78&C78&B78&D78 -> "transform": 0 | H78: "transform": 0
A79: }, | E79: =A79&C79&B79&D79 -> }, | H79: },
A80: "7" | B80: { | C80: : | E80: =A80&C80&B80&D80 -> "7": { | H80: "7": {
A81: "level" | B81: 7 | C81: : | D81: , | E81: =A81&C81&B81&D81 -> "level": 7, | H81: "level": 7,
A82: "ranged" | B82: 394 | C82: : | D82: , | E82: =A82&C82&B82&D82 -> "ranged": 394, | H82: "ranged": 329,
A83: "melee" | B83: 394 | C83: : | D83: , | E83: =A83&C83&B83&D83 -> "melee": 394, | H83: "melee": 329,
A84: "defense" | B84: 228 | C84: : | D84: , | E84: =A84&C84&B84&D84 -> "defense": 228, | H84: "defense": 329,
A85: "life" | B85: 32973 | C85: : | D85: , | E85: =A85&C85&B85&D85 -> "life": 32973, | H85: "life": 32973,
A86: "speed" | B86: 300 | C86: : | D86: , | E86: =A86&C86&B86&D86 -> "speed": 300, | H86: "speed": 650,
A87: "range" | B87: 1800 | C87: : | D87: , | E87: =A87&C87&B87&D87 -> "range": 1800, | H87: "range": 1400,
A88: "load" | B88: 0 | C88: : | D88: , | E88: =A88&C88&B88&D88 -> "load": 0, | H88: "load": 0,
A89: "upkeep" | B89: 300 | C89: : | D89: , | E89: =A89&C89&B89&D89 -> "upkeep": 300, | H89: "upkeep": 300,
A90: "might" | B90: 0 | C90: : | D90: , | E90: =A90&C90&B90&D90 -> "might": 0, | H90: "might": 0,
A91: "transform" | B91: 0 | C91: : | E91: =A91&C91&B91&D91 -> "transform": 0 | H91: "transform": 0
A92: }, | E92: =A92&C92&B92&D92 -> }, | H92: },
A93: "8" | B93: { | C93: : | E93: =A93&C93&B93&D93 -> "8": { | H93: "8": {
A94: "level" | B94: 8 | C94: : | D94: , | E94: =A94&C94&B94&D94 -> "level": 8, | H94: "level": 8,
A95: "ranged" | B95: 550 | C95: : | D95: , | E95: =A95&C95&B95&D95 -> "ranged": 550, | H95: "ranged": 459,
A96: "melee" | B96: 550 | C96: : | D96: , | E96: =A96&C96&B96&D96 -> "melee": 550, | H96: "melee": 459,
A97: "defense" | B97: 318 | C97: : | D97: , | E97: =A97&C97&B97&D97 -> "defense": 318, | H97: "defense": 459,
A98: "life" | B98: 45947 | C98: : | D98: , | E98: =A98&C98&B98&D98 -> "life": 45947, | H98: "life": 45947,
A99: "speed" | B99: 300 | C99: : | D99: , | E99: =A99&C99&B99&D99 -> "speed": 300, | H99: "speed": 650,
A100: "range" | B100: 1800 | C100: : | D100: , | E100: =A100&C100&B100&D100 -> "range": 1800, | H100: "range": 1400,
...

Sheet 运营活动
A1: Item Title | K1: ruby档次 | L1: alliance gift品级 | M1: 价值ruby
A2: 1 Day Food Nanos | C2: 日购买ruby达到 | D2: 物品 | E2: 数量 | F2: 物品单价 | G2: 总价值 | H2: 该档赠送价值 | I2: 折扣 | K2: 30 | L2: 1 | M2: 1
A3: 1 Week Food Nanos | C3: 30 | D3: 1 Minute Speedup | E3: 1 | F3: =VLOOKUP(D3,道具列表!$B:$F,5,FALSE) -> 1 | G3: =E3*F3 -> 1 | K3: 65 | L3: 2 | M3: 2
A4: Beginner's Chest | C4: 30 | D4: 5-Minute Speedup | E4: 1 | F4: =VLOOKUP(D4,道具列表!$B:$F,5,FALSE) -> 3 | G4: =E4*F4 -> 3 | K4: 155 | L4: 3 | M4: 4
A5: translation missing: en.items.beginnerofferchest.name | C5: 30 | D5: General Refresh | E5: 1 | F5: =VLOOKUP(D5,道具列表!$B:$F,5,FALSE) -> 10 | G5: =E5*F5 -> 10 | H5: =SUM(G3:G5) -> 14 | I5: =C5/(C5+H5) -> 0.68181818 | K5: 240 | L5: 4 | M5: 6
A6: 2.5 Day Speedup | C6: 65 | D6: 1 Minute Speedup | E6: 1 | F6: =VLOOKUP(D6,道具列表!$B:$F,5,FALSE) -> 1 | G6: =E6*F6 -> 1 | K6: 425 | L6: 5 | M6: 8
A7: 1 Minute Speedup | C7: 65 | D7: 5-Minute Speedup | E7: 1 | F7: =VLOOKUP(D7,道具列表!$B:$F,5,FALSE) -> 3 | G7: =E7*F7 -> 3 | K7: 1100 | L7: 6 | M7: 10
A8: 4 Day Speedup | C8: 65 | D8: 15-Minute Speedup | E8: 1 | F8: =VLOOKUP(D8,道具列表!$B:$F,5,FALSE) -> 5 | G8: =E8*F8 -> 5 | K8: 50 | L8: 5 | M8: 320 | N8: =K8*(1+M8/100) -> 210
A9: 24-Hour Speedup | C9: 65 | D9: General Refresh | E9: 1 | F9: =VLOOKUP(D9,道具列表!$B:$F,5,FALSE) -> 10 | G9: =E9*F9 -> 10 | H9: =SUM(G3:G9) -> 33 | I9: =C9/(C9+H9) -> 0.66326531 | K9: 100 | L9: 10 | M9: 280 | N9: =K9*(1+M9/100) -> 380
A10: 15-Hour Speedup | C10: 155 | D10: 1 Minute Speedup | E10: 1 | F10: =VLOOKUP(D10,道具列表!$B:$F,5,FALSE) -> 1 | G10: =E10*F10 -> 1 | K10: 240 | L10: 20 | M10: 360 | N10: =K10*(1+M10/100) -> 1104
A11: 8-Hour Speedup | C11: 155 | D11: 5-Minute Speedup | E11: 1 | F11: =VLOOKUP(D11,道具列表!$B:$F,5,FALSE) -> 3 | G11: =E11*F11 -> 3 | K11: 665 | L11: 50 | M11: 240 | N11: =K11*(1+M11/100) -> 2261
A12: Fire | C12: 155 | D12: 15-Minute Speedup | E12: 1 | F12: =VLOOKUP(D12,道具列表!$B:$F,5,FALSE) -> 5 | G12: =E12*F12 -> 5 | K12: 1600 | L12: 100 | M12: 200 | N12: =K12*(1+M12/100) -> 4800
A13: Ceasefire Treaty | C13: 155 | D13: 1-hour speedup | E13: 1 | F13: =VLOOKUP(D13,道具列表!$B:$F,5,FALSE) -> 10 | G13: =E13*F13 -> 10
A14: Charted Warp Device | C14: 155 | D14: General Refresh | E14: 1 | F14: =VLOOKUP(D14,道具列表!$B:$F,5,FALSE) -> 10 | G14: =E14*F14 -> 10 | H14: =SUM(G3:G14) -> 62 | I14: =C14/(C14+H14) -> 0.71428571
A15: Completion Grant | C15: 240 | D15: 1 Minute Speedup | E15: 1 | F15: =VLOOKUP(D15,道具列表!$B:$F,5,FALSE) -> 1 | G15: =E15*F15 -> 1
A16: Completion Portfolio | C16: 240 | D16: 5-Minute Speedup | E16: 1 | F16: =VLOOKUP(D16,道具列表!$B:$F,5,FALSE) -> 3 | G16: =E16*F16 -> 3
A17: Crimson Bull | C17: 240 | D17: 15-Minute Speedup | E17: 1 | F17: =VLOOKUP(D17,道具列表!$B:$F,5,FALSE) -> 5 | G17: =E17*F17 -> 5
A18: Dark Warp Device | C18: 240 | D18: 1-hour speedup | E18: 1 | F18: =VLOOKUP(D18,道具列表!$B:$F,5,FALSE) -> 10 | G18: =E18*F18 -> 10
A19: Double Tax Day Writ | C19: 240 | D19: 2.5-hour speedup | E19: 1 | F19: =VLOOKUP(D19,道具列表!$B:$F,5,FALSE) -> 15 | G19: =E19*F19 -> 15
A20: Double Tax Week Writ | C20: 240 | D20: General Refresh | E20: 1 | F20: =VLOOKUP(D20,道具列表!$B:$F,5,FALSE) -> 10 | G20: =E20*F20 -> 10
A21: Dragon Hearts | C21: 240 | D21: Crimson Bull | E21: 1 | F21: =VLOOKUP(D21,道具列表!$B:$F,5,FALSE) -> 10 | G21: =E21*F21 -> 10
A22: Roar | C22: 240 | D22: Purple Bones | E22: 1 | F22: =VLOOKUP(D22,道具列表!$B:$F,5,FALSE) -> 10 | G22: =E22*F22 -> 10 | H22: =SUM(G3:G22) -> 126 | I22: =C22/(C22+H22) -> 0.6557377
A23: Transform | C23: 425 | D23: 1 Minute Speedup | E23: 1 | F23: =VLOOKUP(D23,道具列表!$B:$F,5,FALSE) -> 1 | G23: =E23*F23 -> 1
A24: 1 Day Wood Nanos | C24: 425 | D24: 5-Minute Speedup | E24: 1 | F24: =VLOOKUP(D24,道具列表!$B:$F,5,FALSE) -> 3 | G24: =E24*F24 -> 3
A25: 1 Week Wood Nanos | C25: 425 | D25: 15-Minute Speedup | E25: 1 | F25: =VLOOKUP(D25,道具列表!$B:$F,5,FALSE) -> 5 | G25: =E25*F25 -> 5
A26: 1 Day Metals Nanos | C26: 425 | D26: 1-hour speedup | E26: 1 | F26: =VLOOKUP(D26,道具列表!$B:$F,5,FALSE) -> 10 | G26: =E26*F26 -> 10
A27: 1 Week Metals Nanos | C27: 425 | D27: 2.5-hour speedup | E27: 1 | F27: =VLOOKUP(D27,道具列表!$B:$F,5,FALSE) -> 15 | G27: =E27*F27 -> 15
A28: 250,000 Food | C28: 425 | D28: 8-hour speedup | E28: 1 | F28: =VLOOKUP(D28,道具列表!$B:$F,5,FALSE) -> 40 | G28: =E28*F28 -> 40
A29: 80,000 Food | C29: 425 | D29: General Refresh | E29: 1 | F29: =VLOOKUP(D29,道具列表!$B:$F,5,FALSE) -> 10 | G29: =E29*F29 -> 10
A30: Forced March Drops | C30: 425 | D30: Crimson Bull | E30: 1 | F30: =VLOOKUP(D30,道具列表!$B:$F,5,FALSE) -> 10 | G30: =E30*F30 -> 10
A31: Identity Alternator | C31: 425 | D31: Purple Bones | E31: 1 | F31: =VLOOKUP(D31,道具列表!$B:$F,5,FALSE) -> 10 | G31: =E31*F31 -> 10 | H31: =SUM(G3:G31) -> 230 | I31: =C31/(C31+H31) -> 0.64885496
A32: Glowing Shields | C32: 1100 | D32: 1 Minute Speedup | E32: 1 | F32: =VLOOKUP(D32,道具列表!$B:$F,5,FALSE) -> 1 | G32: =E32*F32 -> 1
A33: 250,000 Gold | C33: 1100 | D33: 5-Minute Speedup | E33: 1 | F33: =VLOOKUP(D33,道具列表!$B:$F,5,FALSE) -> 3 | G33: =E33*F33 -> 3
A34: 80,000 Gold | C34: 1100 | D34: 15-Minute Speedup | E34: 1 | F34: =VLOOKUP(D34,道具列表!$B:$F,5,FALSE) -> 5 | G34: =E34*F34 -> 5
A35: Great Dragon Armor Chest | C35: 1100 | D35: 1-hour speedup | E35: 1 | F35: =VLOOKUP(D35,道具列表!$B:$F,5,FALSE) -> 10 | G35: =E35*F35 -> 10
A36: Great Dragon Chest | C36: 1100 | D36: 2.5-hour speedup | E36: 1 | F36: =VLOOKUP(D36,道具列表!$B:$F,5,FALSE) -> 15 | G36: =E36*F36 -> 15
A37: Hold and Warp Chest | C37: 1100 | D37: 8-hour speedup | E37: 1 | F37: =VLOOKUP(D37,道具列表!$B:$F,5,FALSE) -> 40 | G37: =E37*F37 -> 40
A38: 5-Minute Speedup | C38: 1100 | D38: 15-hour speedup | E38: 1 | F38: =VLOOKUP(D38,道具列表!$B:$F,5,FALSE) -> 65 | G38: =E38*F38 -> 65
A39: 1-Hour Speedup | C39: 1100 | D39: General Refresh | E39: 1 | F39: =VLOOKUP(D39,道具列表!$B:$F,5,FALSE) -> 10 | G39: =E39*F39 -> 10
A40: 2.5-Hour Speedup | C40: 1100 | D40: Crimson Bull | E40: 1 | F40: =VLOOKUP(D40,道具列表!$B:$F,5,FALSE) -> 10 | G40: =E40*F40 -> 10
A41: Mass Nullifier | C41: 1100 | D41: Purple Bones | E41: 1 | F41: =VLOOKUP(D41,道具列表!$B:$F,5,FALSE) -> 10 | G41: =E41*F41 -> 10
A42: Nano Canisters | C42: 1100 | D42: Dragon Hearts | E42: 1 | F42: =VLOOKUP(D42,道具列表!$B:$F,5,FALSE) -> 10 | G42: =E42*F42 -> 10
A43: Nano Crates | C43: 1100 | D43: Glowing Shields | E43: 1 | F43: =VLOOKUP(D43,道具列表!$B:$F,5,FALSE) -> 10 | G43: =E43*F43 -> 10
A44: translation missing: en.items.newplayerprotection.name | C44: 1100 | D44: Dark Warp Device | E44: 1 | F44: =VLOOKUP(D44,道具列表!$B:$F,5,FALSE) -> 30 | G44: =E44*F44 -> 30 | H44: =SUM(G3:G44) -> 449 | I44: =C44/(C44+H44) -> 0.71013557
A45: Dragon's Call | C45: 5000 | D45: 1 Minute Speedup | E45: 1 | F45: =VLOOKUP(D45,道具列表!$B:$F,5,FALSE) -> 1 | G45: =E45*F45 -> 1
C46: 5000 | D46: 5-Minute Speedup | E46: 1 | F46: =VLOOKUP(D46,道具列表!$B:$F,5,FALSE) -> 3 | G46: =E46*F46 -> 3
A47: 250,000 Metals | C47: 5000 | D47: 15-Minute Speedup | E47: 1 | F47: =VLOOKUP(D47,道具列表!$B:$F,5,FALSE) -> 5 | G47: =E47*F47 -> 5
A48: 80,000 Metals | C48: 5000 | D48: 1-hour speedup | E48: 1 | F48: =VLOOKUP(D48,道具列表!$B:$F,5,FALSE) -> 10 | G48: =E48*F48 -> 10
A49: 1 Day Stone Nanos | C49: 5000 | D49: 2.5-hour speedup | E49: 1 | F49: =VLOOKUP(D49,道具列表!$B:$F,5,FALSE) -> 15 | G49: =E49*F49 -> 15
A50: 1 Week Stone Nanos | C50: 5000 | D50: 8-hour speedup | E50: 1 | F50: =VLOOKUP(D50,道具列表!$B:$F,5,FALSE) -> 40 | G50: =E50*F50 -> 40
A51: Purple Bones | C51: 5000 | D51: 15-hour speedup | E51: 1 | F51: =VLOOKUP(D51,道具列表!$B:$F,5,FALSE) -> 65 | G51: =E51*F51 -> 65
A52: General Refresh | C52: 5000 | D52: 24-hour speedup | E52: 1 | F52: =VLOOKUP(D52,道具列表!$B:$F,5,FALSE) -> 95 | G52: =E52*F52 -> 95
A53: Resource Chest | C53: 5000 | D53: General Refresh | E53: 1 | F53: =VLOOKUP(D53,道具列表!$B:$F,5,FALSE) -> 10 | G53: =E53*F53 -> 10
A54: 15-Minute Speedup | C54: 5000 | D54: Crimson Bull | E54: 1 | F54: =VLOOKUP(D54,道具列表!$B:$F,5,FALSE) -> 10 | G54: =E54*F54 -> 10
A55: 250,000 Stone | C55: 5000 | D55: Purple Bones | E55: 1 | F55: =VLOOKUP(D55,道具列表!$B:$F,5,FALSE) -> 10 | G55: =E55*F55 -> 10
A56: 80,000 Stone | C56: 5000 | D56: Dragon Hearts | E56: 1 | F56: =VLOOKUP(D56,道具列表!$B:$F,5,FALSE) -> 10 | G56: =E56*F56 -> 10
A57: Testronius Powder | C57: 5000 | D57: Glowing Shields | E57: 1 | F57: =VLOOKUP(D57,道具列表!$B:$F,5,FALSE) -> 10 | G57: =E57*F57 -> 10
A58: Chronos Bag | C58: 5000 | D58: Charted Warp Device | E58: 1 | F58: =VLOOKUP(D58,道具列表!$B:$F,5,FALSE) -> 75 | G58: =E58*F58 -> 75
A59: Trance March Drops | C59: 5000 | D59: Resource Chest | E59: 5 | F59: =VLOOKUP(D59,道具列表!$B:$F,5,FALSE) -> 250 | G59: =E59*F59 -> 1250 | H59: =SUM(G3:G59) -> 2058 | I59: =C59/(C59+H59) -> 0.70841598
A60: 250,000 Wood | C60: 10000 | D60: 1 Minute Speedup | E60: 1 | F60: =VLOOKUP(D60,道具列表!$B:$F,5,FALSE) -> 1 | G60: =E60*F60 -> 1
A61: 80,000 Wood | C61: 10000 | D61: 5-Minute Speedup | E61: 1 | F61: =VLOOKUP(D61,道具列表!$B:$F,5,FALSE) -> 3 | G61: =E61*F61 -> 3
C62: 10000 | D62: 15-Minute Speedup | E62: 1 | F62: =VLOOKUP(D62,道具列表!$B:$F,5,FALSE) -> 5 | G62: =E62*F62 -> 5
C63: 10000 | D63: 1-hour speedup | E63: 1 | F63: =VLOOKUP(D63,道具列表!$B:$F,5,FALSE) -> 10 | G63: =E63*F63 -> 10
C64: 10000 | D64: 2.5-hour speedup | E64: 1 | F64: =VLOOKUP(D64,道具列表!$B:$F,5,FALSE) -> 15 | G64: =E64*F64 -> 15
C65: 10000 | D65: 8-hour speedup | E65: 1 | F65: =VLOOKUP(D65,道具列表!$B:$F,5,FALSE) -> 40 | G65: =E65*F65 -> 40
C66: 10000 | D66: 15-hour speedup | E66: 1 | F66: =VLOOKUP(D66,道具列表!$B:$F,5,FALSE) -> 65 | G66: =E66*F66 -> 65
C67: 10000 | D67: 24-hour speedup | E67: 1 | F67: =VLOOKUP(D67,道具列表!$B:$F,5,FALSE) -> 95 | G67: =E67*F67 -> 95
C68: 10000 | D68: 2.5 Day Speedup | E68: 1 | F68: =VLOOKUP(D68,道具列表!$B:$F,5,FALSE) -> 210 | G68: =E68*F68 -> 210
C69: 10000 | D69: General Refresh | E69: 1 | F69: =VLOOKUP(D69,道具列表!$B:$F,5,FALSE) -> 10 | G69: =E69*F69 -> 10
