Workbook
Name Alliance: 'Reward and Cost'!$DC$4:$DC$7
Name Battle: 'Reward and Cost'!$CZ$4:$CZ$10
Name Casino: 'Reward and Cost'!$CX$4:$CX$5
Name CATEGORY: 'Reward and Cost'!$CS$4:$CS$18
Name Construction: 'Reward and Cost'!$CV$4:$CV$7
Name Construction_BuildingCost_Food: Construction!$J$3
Name Construction_BuildingCost_Ore: Construction!$I$3
Name Construction_BuildingCost_Stone: Construction!$G$3
Name Construction_BuildingCost_Wood: Construction!$H$3
Name Construction_BuildingReward_HeroXP: Construction!$E$2
Name Construction_BuildingReward_Power: Construction!$F$2
Name Construction_Name_and_Level: Construction!$B$2
Name Construction_ProtectedAmountOfEachRssByStorehouse: Construction!$Y$3
Name Construction_QuestReward_Food: Construction!$P$3
Name Construction_QuestReward_HeroXP: Construction!$K$3
Name Construction_QuestReward_Ore: Construction!$O$3
Name Construction_QuestReward_Power: Construction!$L$3
Name Construction_QuestReward_Silver: Construction!$Q$3
Name Construction_QuestReward_Stone: Construction!$M$3
Name Construction_QuestReward_Wood: Construction!$N$3
Name Construction_Time: Construction!$C$2
Name Craft: 'Reward and Cost'!$DA$4:$DA$9
Name Event: 'Reward and Cost'!$DE$4:$DE$6
Name Friend: 'Reward and Cost'!$DD$4:$DD$6
Name Gift: 'Reward and Cost'!$CU$4:$CU$8
Name Level_Up: 'Reward and Cost'!$DB$4:$DB$5
Name Quest: 'Reward and Cost'!$CT$4:$CT$15
Name Research: 'Reward and Cost'!$CW$4:$CW$10
Name Research_Name_and_Level: Research!$C$2
Name Research_QuestReward_Food: Research!$R$3
Name Research_QuestReward_HeroXP: Research!$M$3
Name Research_QuestReward_Ore: Research!$Q$3
Name Research_QuestReward_Power: Research!$N$3
Name Research_QuestReward_Silver: Research!$S$3
Name Research_QuestReward_Stone: Research!$O$3
Name Research_QuestReward_Wood: Research!$P$3
Name Research_Research_Name_and_Level: Research!$C$2
Name Research_ResearchCost_Food: Research!$K$3
Name Research_ResearchCost_Ore: Research!$J$3
Name Research_ResearchCost_Silver: Research!$L$3
Name Research_ResearchCost_Stone: Research!$H$3
Name Research_ResearchCost_Wood: Research!$I$3
Name Research_ResearchReward_HeroXP: Research!$F$3
Name Research_ResearchReward_Power: Research!$G$3
Name Research_Time: Research!$D$2
Name Store: 'Reward and Cost'!$DF$4:$DF$8
Name Training: 'Reward and Cost'!$CY$4:$CY$30
Name Troop_Name: Troop!$B$2
Name Troop_TrainingCost_Food: Troop!$O$3
Name Troop_TrainingCost_Ore: Troop!$N$3
Name Troop_TrainingCost_Silver: Troop!$P$3
Name Troop_TrainingCost_Stone: Troop!$L$3
Name Troop_TrainingCost_Wood: Troop!$M$3
Name Troop_TrainingReward_Power: Troop!$AK$3

Sheet Reward and Cost
D1: 0.019212963
B2: CATEGORY | C2: CLASS | D2: DETAIL | E2: Hero | J2: Power Gained | K2: VIP | N2: Currency - Gold | Q2: Free Time | R2: Help Time | S2: Speed Up Gained or Possessed | AF2: Accumulative Speed Up Time Got | AI2: Accumulative Speed Up Time Used | AJ2: Speed Up Time Left | AK2: Construction Time | AN2: Speed Up Time Used | AO2: Construction Time - Free Time - Help Time - Speed Up Time | AP2: Research Time | AS2: Speed Up Time Used | AT2: Research Time - Help Time - Speed Up Time | AU2: Resources Gained or Consumed | AZ2: Resources Output (1/Hour) | BE2: Upkeep | BF2: City Capacity | BK2: Core Constructions | BM2: Resource Constructions | BX2: Battle Constructions | CC2: Technology Constructions | CD2: Crafting Constructions | CE2: Alliance Constructions | CH2: Hero Constructions | CK2: Gold Construction | CL2: Alliance Currencies | CN2: Casino | CR2: Pull Down Menu | CS2: CATEGORY | CT2: CLASS
E3: Level | F3: Exp Modifier | G3: Original Exp | H3: Exp Actually Gained | I3: Skill Points | K3: Level | L3: Point | M3: Amount of Time | N3: Possessing Gold | O3: Cumulatively Used Gold | P3: Cumulatively Got Gold | S3: 0.00069444444 | T3: 0.0020833333 | U3: 0.0034722222 | V3: 0.0069444444 | W3: 0.010416667 | X3: 0.041666667 | Y3: 0.125 | Z3: 0.33333333 | AA3: 0.625 | AB3: 1 | AC3: 3 | AD3: 25% Time Off | AE3: 50% Time Off | AF3: Got for Free | AG3: Bought | AH3: Sum | AK3: Construction Acceleration | AL3: Original Time | AM3: Actual Time | AP3: Research Acceleration | AQ3: Original Time | AR3: Actual Time | AU3: Stone | AV3: Wood | AW3: Ore | AX3: Food | AY3: Silver | AZ3: Stone | BA3: Wood | BB3: Ore | BC3: Food | BD3: Silver | BE3: Food | BF3: Stone | BG3: Wood | BH3: Ore | BI3: Food | BJ3: Silver | BK3: Stronghold Lv. | BL3: Walls Lv. | BM3: Storehouse Lv. | BN3: Farm Max Lv. | BO3: Farm Num | BP3: Logging Camp Max Lv. | BQ3: Logging Camp Num | BR3: Quarry Max Lv. | BS3: Quarry Num | BT3: Mine Max Lv. | BU3: Mine Num | BV3: Villa Max Lv. | BW3: Villa Num | BX3: Barracks Max Lv. | BY3: Barracks Num | BZ3: Hospital Max Lv. | CA3: Hospital Num | CB3: Watchtower Lv. | CC3: Academy | CD3: Forge | CE3: Marketplace | CF3: Embassy Lv. | CG3: Hall of War Lv. | CH3: Gymnos Lv. | CI3: Prison Lv. | CJ3: Altar Lv. | CK3: Gold Mine | CL3: Loyalty | CM3: Funds | CN3: Chips | CT3: Quest | CU3: Gift | CV3: Construction | CW3: Research | CX3: Casino | CY3: Training | CZ3: Battle | DA3: Craft | DB3: Level_Up | DC3: Alliance | DD3: Friend | DE3: Event | DF3: Store
B4: Initial | D4: Hero Level 1 | E4: 1 | F4: 0 | G4: — | H4: 0 | I4: 1 | J4: 30 | K4: 1 | M4: 0 | N4: 100 | O4: 0 | P4: 100 | Q4: 0.0034722222 | R4: 0.0034722222 | S4: 0 | T4: 0 | U4: 0 | V4: 0 | W4: 0 | X4: 0 | Y4: 0 | Z4: 0 | AA4: 0 | AB4: 0 | AC4: 0 | AD4: 0 | AE4: 0 | AF4: 0 | AG4: 0 | AH4: =AF4+AG4 -> 0 | AI4: 0 | AJ4: =S$3*S4+T$3*T4+U$3*U4+V$3*V4+W$3*W4+X$3*X4+Y$3*Y4+Z$3*Z4+AA$3*AA4+AB$3*AB4+AC$3*AC4 -> 0 | AK4: 0 | AL4: — | AM4: — | AN4: — | AO4: — | AP4: 0 | AQ4: — | AR4: — | AS4: — | AT4: — | AU4: 20000 | AV4: 20000 | AW4: 20000 | AX4: 20000 | AY4: 20000 | AZ4: 0 | BA4: 0 | BB4: 0 | BC4: 0 | BD4: 0 | BE4: 0 | BF4: 0 | BG4: 0 | BH4: 0 | BI4: 0 | BJ4: 0 | BK4: 1 | BL4: 1 | BM4: 1 | BN4: 0 | BO4: 0 | BP4: 0 | BQ4: 0 | BR4: 0 | BS4: 0 | BT4: 0 | BU4: 0 | BV4: 0 | BW4: 0 | BX4: 0 | BY4: 0 | BZ4: 1 | CA4: 1 | CB4: 1 | CC4: 0 | CD4: 0 | CL4: 0 | CN4: — | CS4: Quest | CT4: Initially Completed | CU4: Special | CV4: by Quest | CW4: by Quest | CY4: Swordsmen | CZ4: Field Occupy | DA4: Weapons | DC4: Alliance Gift | DD4: Gold from Friends | DE4: Building Traps | DF4: Buy Speed Ups
B5: Construction | C5: by Quest | D5: Farm 1 | E5: 1 | F5: 0 | G5: =VLOOKUP($D5,Construction!$B:$E,(COLUMN(Construction_BuildingReward_HeroXP)-COLUMN(Construction_Name_and_Level)+1),FALSE) -> 10 | H5: =G5*(1+F5) -> 10 | J5: =VLOOKUP($D5,Construction!$B:$F,(COLUMN(Construction_BuildingReward_Power)-COLUMN(Construction_Name_and_Level)+1),FALSE) -> 5 | Q5: 0.0034722222 | R5: 0.0034722222 | AJ5: =AJ4+(S$3*S5+T$3*T5+U$3*U5+V$3*V5+W$3*W5+X$3*X5+Y$3*Y5+Z$3*Z5+AA$3*AA5+AB$3*AB5+AC$3*AC5) -> 0 | AK5: 0 | AL5: =VLOOKUP($D5,Construction!$B:$C,(COLUMN(Construction_Time)-COLUMN(Construction_Name_and_Level)+1),FALSE) -> 0.00069444444 | AM5: =AL5/(1+AK5) -> 0.00069444444 | AN5: =(S$3*S5+T$3*T5+V$3*V5+W$3*W5+X$3*X5+Y$3*Y5+Z$3*Z5+AA$3*AA5+AB$3*AB5+AC$3*AC5)*(-1) -> 0 | AO5: =IF((AM5-Q5-R5-AN5)>=0,AM5-Q5-R5-AN5,0) -> 0 | AU5: =VLOOKUP($D5,Construction!$B:$J,(COLUMN(Construction_BuildingCost_Stone)-COLUMN(Construction_Name_and_Level)+1),FALSE)*(-1) -> -100 | AV5: =VLOOKUP($D5,Construction!$B:$J,(COLUMN(Construction_BuildingCost_Wood)-COLUMN(Construction_Name_and_Level)+1),FALSE)*(-1) -> -100 | AW5: =VLOOKUP($D5,Construction!$B:$J,(COLUMN(Construction_BuildingCost_Ore)-COLUMN(Construction_Name_and_Level)+1),FALSE)*(-1) -> -100 | AX5: =VLOOKUP($D5,Construction!$B:$J,(COLUMN(Construction_BuildingCost_Food)-COLUMN(Construction_Name_and_Level)+1),FALSE)*(-1) -> 0 | CS5: Gift | CT5: Special | CU5: Online Reward | CV5: at Will | CW5: at Will | CY5: Slingers | CZ5: Scouting | DA5: Helmets | DC5: Alliance Store | DF5: Buy Resources
B6: Quest | C6: Construction Recommended | D6: Farm 1 | E6: 1 | F6: 0 | G6: =VLOOKUP($D6,Construction!$B:$L,(COLUMN(Construction_QuestReward_HeroXP)-COLUMN(Construction_Name_and_Level)+1),FALSE) -> 2525 | H6: =G6*(1+F6) -> 2525 | J6: =VLOOKUP($D6,Construction!$B:$L,(COLUMN(Construction_QuestReward_Power)-COLUMN(Construction_Name_and_Level)+1),FALSE) -> 2 | AJ6: =AJ5+(S$3*S6+T$3*T6+U$3*U6+V$3*V6+W$3*W6+X$3*X6+Y$3*Y6+Z$3*Z6+AA$3*AA6+AB$3*AB6+AC$3*AC6) -> 0 | AU6: =VLOOKUP($D6,Construction!$B:$Q,(COLUMN(Construction_QuestReward_Stone)-COLUMN(Construction_Name_and_Level)+1),FALSE) -> 0 | AV6: =VLOOKUP($D6,Construction!$B:$Q,(COLUMN(Construction_QuestReward_Wood)-COLUMN(Construction_Name_and_Level)+1),FALSE) -> 0 | AW6: =VLOOKUP($D6,Construction!$B:$Q,(COLUMN(Construction_QuestReward_Ore)-COLUMN(Construction_Name_and_Level)+1),FALSE) -> 0 | AX6: =VLOOKUP($D6,Construction!$B:$Q,(COLUMN(Construction_QuestReward_Food)-COLUMN(Construction_Name_and_Level)+1),FALSE) -> 3000 | AY6: =VLOOKUP($D6,Construction!$B:$Q,(COLUMN(Construction_QuestReward_Silver)-COLUMN(Construction_Name_and_Level)+1),FALSE) -> 0 | CS6: Construction | CT6: Daily Quest | CU6: Stronghold upgrade Event | CV6: Deconstruct | CY6: Outriders | CZ6: Attack Players | DA6: Armors | DC6: Resource Help | DF6: Buy Special
B7: Construction | C7: by Quest | D7: Stronghold 2 | E7: 1 | F7: 0 | G7: =VLOOKUP($D7,Construction!$B:$E,(COLUMN(Construction_BuildingReward_HeroXP)-COLUMN(Construction_Name_and_Level)+1),FALSE) -> 5000 | H7: =G7*(1+F7) -> 5000 | J7: =VLOOKUP($D7,Construction!$B:$F,(COLUMN(Construction_BuildingReward_Power)-COLUMN(Construction_Name_and_Level)+1),FALSE) -> 150 | Q7: 0.0034722222 | R7: 0.0041666667 | AJ7: =AJ6+(S$3*S7+T$3*T7+U$3*U7+V$3*V7+W$3*W7+X$3*X7+Y$3*Y7+Z$3*Z7+AA$3*AA7+AB$3*AB7+AC$3*AC7) -> 0 | AK7: 0 | AL7: =VLOOKUP($D7,Construction!$B:$C,(COLUMN(Construction_Time)-COLUMN(Construction_Name_and_Level)+1),FALSE) -> 0.0032407407 | AM7: =AL7/(1+AK7) -> 0.0032407407 | AN7: =(S$3*S7+T$3*T7+V$3*V7+W$3*W7+X$3*X7+Y$3*Y7+Z$3*Z7+AA$3*AA7+AB$3*AB7+AC$3*AC7)*(-1) -> 0 | AO7: =IF((AM7-Q7-R7-AN7)>=0,AM7-Q7-R7-AN7,0) -> 0 | AU7: =VLOOKUP($D7,Construction!$B:$J,(COLUMN(Construction_BuildingCost_Stone)-COLUMN(Construction_Name_and_Level)+1),FALSE)*(-1) -> -1800 | AV7: =VLOOKUP($D7,Construction!$B:$J,(COLUMN(Construction_BuildingCost_Wood)-COLUMN(Construction_Name_and_Level)+1),FALSE)*(-1) -> -1800 | AW7: =VLOOKUP($D7,Construction!$B:$J,(COLUMN(Construction_BuildingCost_Ore)-COLUMN(Construction_Name_and_Level)+1),FALSE)*(-1) -> -720 | AX7: =VLOOKUP($D7,Construction!$B:$J,(COLUMN(Construction_BuildingCost_Food)-COLUMN(Construction_Name_and_Level)+1),FALSE)*(-1) -> -900 | CS7: Research | CT7: Construction Recommended | CU7: Stronghold upgrade Chest | CY7: Battering Ram | CZ7: Attacked by Players | DA7: Accessories | DC7: Alliance Quest | DF7: Buy War Items
B8: Gift | C8: Stronghold upgrade Event | D8: Stronghold 1->2 Event | E8: 1 | AJ8: =AJ7+(S$3*S8+T$3*T8+U$3*U8+V$3*V8+W$3*W8+X$3*X8+Y$3*Y8+Z$3*Z8+AA$3*AA8+AB$3*AB8+AC$3*AC8) -> 0 | AU8: 1900 | AV8: 1900 | AW8: 1900 | AX8: 1500 | AY8: 1600 | CS8: Casino | CT8: Construction at Will | CU8: Hero Level Up | CY8: Hoplites | CZ8: Healing | DA8: Foot Armor | DF8: Buy Treasures
B9: Gift | C9: Special | D9: Beginner's Chest | E9: 1 | V9: 1 | W9: 1 | AF9: =$S$3*$S9+$T$3*$T9+$U$3*$U9+$V$3*$V9+$W$3*$W9+$X$3*$X9+$Y$3*$Y9+$Z$3*$Z9+$AA$3*$AA9+$AB$3*$AB9+$AC$3*$AC9 -> 0.017361111 | AJ9: =AJ8+(S$3*S9+T$3*T9+U$3*U9+V$3*V9+W$3*W9+X$3*X9+Y$3*Y9+Z$3*Z9+AA$3*AA9+AB$3*AB9+AC$3*AC9) -> 0.017361111 | AX9: 5000 | CS9: Training | CT9: Research Recommended | CY9: Skirmish Archers | CZ9: Hero In Jail | DA9: Special Event Gear
B10: Gift | C10: Online Reward | D10: 0.00069444444 | E10: 1 | T10: 1 | AF10: =$S$3*$S10+$T$3*$T10+$U$3*$U10+$V$3*$V10+$W$3*$W10+$X$3*$X10+$Y$3*$Y10+$Z$3*$Z10+$AA$3*$AA10+$AB$3*$AB10+$AC$3*$AC10 -> 0.0020833333 | AJ10: =AJ9+(S$3*S10+T$3*T10+U$3*U10+V$3*V10+W$3*W10+X$3*X10+Y$3*Y10+Z$3*Z10+AA$3*AA10+AB$3*AB10+AC$3*AC10) -> 0.019444444 | CS10: Battle | CT10: Research at Will | CY10: Light Cavalry
B11: Gift | C11: Online Reward | D11: 0.0027777778 | E11: 1 | L11: 100 | AJ11: =AJ10+(S$3*S11+T$3*T11+U$3*U11+V$3*V11+W$3*W11+X$3*X11+Y$3*Y11+Z$3*Z11+AA$3*AA11+AB$3*AB11+AC$3*AC11) -> 0.019444444 | CS11: Craft | CT11: Training Recommended | CY11: Ballista
B12: Casino | E12: 1 | AJ12: =AJ11+(S$3*S12+T$3*T12+U$3*U12+V$3*V12+W$3*W12+X$3*X12+Y$3*Y12+Z$3*Z12+AA$3*AA12+AB$3*AB12+AC$3*AC12) -> 0.019444444 | AY12: 750 | CS12: Friend | CT12: Training at Will | CY12: Armored Pikemen
B13: Gift | C13: Stronghold upgrade Chest | D13: Stronghold 1 Chest | E13: 1 | V13: 1 | W13: 1 | AF13: =$S$3*$S13+$T$3*$T13+$U$3*$U13+$V$3*$V13+$W$3*$W13+$X$3*$X13+$Y$3*$Y13+$Z$3*$Z13+$AA$3*$AA13+$AB$3*$AB13+$AC$3*$AC13 -> 0.017361111 | AJ13: =AJ12+(S$3*S13+T$3*T13+U$3*U13+V$3*V13+W$3*W13+X$3*X13+Y$3*Y13+Z$3*Z13+AA$3*AA13+AB$3*AB13+AC$3*AC13) -> 0.036805556 | AX13: 5000 | CS13: Level_Up | CT13: Increase Production | CY13: Guardians
B14: Gift | C14: Stronghold upgrade Chest | D14: Stronghold 2 Chest | E14: 1 | M14: 0.020833333 | W14: 1 | AF14: =$S$3*$S14+$T$3*$T14+$U$3*$U14+$V$3*$V14+$W$3*$W14+$X$3*$X14+$Y$3*$Y14+$Z$3*$Z14+$AA$3*$AA14+$AB$3*$AB14+$AC$3*$AC14 -> 0.010416667 | AJ14: =AJ13+(S$3*S14+T$3*T14+U$3*U14+V$3*V14+W$3*W14+X$3*X14+Y$3*Y14+Z$3*Z14+AA$3*AA14+AB$3*AB14+AC$3*AC14) -> 0.047222222 | AU14: 1000 | AV14: 1000 | AW14: 1000 | CS14: Alliance | CT14: Hero Upgrade Milestone | CY14: Companion Cavalry
B15: Quest | C15: Construction Recommended | D15: Hospital 1 | E15: 1 | F15: 0 | G15: =VLOOKUP($D15,Construction!$B:$L,(COLUMN(Construction_QuestReward_HeroXP)-COLUMN(Construction_Name_and_Level)+1),FALSE) -> 2525 | H15: =G15*(1+F15) -> 2525 | J15: =VLOOKUP($D15,Construction!$B:$L,(COLUMN(Construction_QuestReward_Power)-COLUMN(Construction_Name_and_Level)+1),FALSE) -> 2 | AJ15: =AJ14+(S$3*S15+T$3*T15+U$3*U15+V$3*V15+W$3*W15+X$3*X15+Y$3*Y15+Z$3*Z15+AA$3*AA15+AB$3*AB15+AC$3*AC15) -> 0.047222222 | AU15: =VLOOKUP($D15,Construction!$B:$Q,(COLUMN(Construction_QuestReward_Stone)-COLUMN(Construction_Name_and_Level)+1),FALSE) -> 5400 | AV15: =VLOOKUP($D15,Construction!$B:$Q,(COLUMN(Construction_QuestReward_Wood)-COLUMN(Construction_Name_and_Level)+1),FALSE) -> 4300 | AW15: =VLOOKUP($D15,Construction!$B:$Q,(COLUMN(Construction_QuestReward_Ore)-COLUMN(Construction_Name_and_Level)+1),FALSE) -> 3300 | AX15: =VLOOKUP($D15,Construction!$B:$Q,(COLUMN(Construction_QuestReward_Food)-COLUMN(Construction_Name_and_Level)+1),FALSE) -> 2700 | AY15: =VLOOKUP($D15,Construction!$B:$Q,(COLUMN(Construction_QuestReward_Silver)-COLUMN(Construction_Name_and_Level)+1),FALSE) -> 50 | CS15: Event | CY15: Siege Tower
B16: Gift | C16: Hero Level Up | D16: Hero 1->2 | E16: 2 | I16: 1 | J16: 57 | AJ16: =AJ15+(S$3*S16+T$3*T16+U$3*U16+V$3*V16+W$3*W16+X$3*X16+Y$3*Y16+Z$3*Z16+AA$3*AA16+AB$3*AB16+AC$3*AC16) -> 0.047222222 | CS16: Store | CY16: Immortals
B17: Level_Up | D17: Hero Level 2 | E17: 2 | F17: 0 | G17: — | H17: 10060 | I17: 2 | J17: 246 | K17: 2 | M17: 0.020833333 | N17: 100 | O17: =SUMIF($B$4:$B16,"<>"&$CS$13,O$4:O16) -> 0 | P17: =SUMIF($B$4:$B16,"<>"&$CS$13,N$4:N16) -> 100 | Q17: 0.0034722222 | R17: 0.0041666667 | S17: 0 | T17: 1 | U17: 0 | V17: 2 | W17: 3 | X17: 0 | Y17: 0 | Z17: 0 | AA17: 0 | AB17: 0 | AC17: 0 | AD17: 0 | AE17: 0 | AF17: =SUMIF($B$4:$B16,"<>"&$CS$13,AF$4:AF16) -> 0.047222222 | AG17: =SUMIF($B$4:$B16,"<>"&$CS$13,AG$4:AG16) -> 0 | AH17: =AF17+AG17 -> 0.047222222 | AI17: =SUMIF($B$4:$B16,"<>"&$CS$13,AI$4:AI16) -> 0 | AJ17: =S$3*S17+T$3*T17+U$3*U17+V$3*V17+W$3*W17+X$3*X17+Y$3*Y17+Z$3*Z17+AA$3*AA17+AB$3*AB17+AC$3*AC17 -> 0.047222222 | AK17: 0 | AL17: — | AM17: — | AN17: — | AO17: — | AP17: 0 | AQ17: — | AR17: — | AS17: — | AT17: — | AU17: 26500 | AV17: 25400 | AW17: 25480 | AX17: 37200 | AY17: 22400 | AZ17: 0 | BA17: 0 | BB17: 0 | BC17: 52 | BD17: 0 | BE17: 0 | BF17: 15000 | BG17: 15000 | BH17: 15000 | BI17: 17500 | BJ17: 15000 | BK17: 2 | BL17: 1 | BM17: 1 | BN17: 1 | BO17: 1 | BP17: 0 | BQ17: 0 | BR17: 0 | BS17: 0 | BT17: 0 | BU17: 0 | BV17: 0 | BW17: 0 | BX17: 0 | BY17: 0 | BZ17: 1 | CA17: 1 | CB17: 1 | CC17: 0 | CD17: 0 | CL17: 0 | CN17: — | CY17: Marksmen
B18: Quest | C18: Initially Completed | D18: Storehouse 1 | E18: 2 | F18: 0 | G18: =VLOOKUP($D18,Construction!$B:$L,(COLUMN(Construction_QuestReward_HeroXP)-COLUMN(Construction_Name_and_Level)+1),FALSE) -> 2525 | H18: =G18*(1+F18) -> 2525 | J18: =VLOOKUP($D18,Construction!$B:$L,(COLUMN(Construction_QuestReward_Power)-COLUMN(Construction_Name_and_Level)+1),FALSE) -> 2 | AJ18: =AJ17+(S$3*S18+T$3*T18+U$3*U18+V$3*V18+W$3*W18+X$3*X18+Y$3*Y18+Z$3*Z18+AA$3*AA18+AB$3*AB18+AC$3*AC18) -> 0.047222222 | AU18: =VLOOKUP($D18,Construction!$B:$Q,(COLUMN(Construction_QuestReward_Stone)-COLUMN(Construction_Name_and_Level)+1),FALSE) -> 4000 | AV18: =VLOOKUP($D18,Construction!$B:$Q,(COLUMN(Construction_QuestReward_Wood)-COLUMN(Construction_Name_and_Level)+1),FALSE) -> 4000 | AW18: =VLOOKUP($D18,Construction!$B:$Q,(COLUMN(Construction_QuestReward_Ore)-COLUMN(Construction_Name_and_Level)+1),FALSE) -> 3000 | AX18: =VLOOKUP($D18,Construction!$B:$Q,(COLUMN(Construction_QuestReward_Food)-COLUMN(Construction_Name_and_Level)+1),FALSE) -> 2100 | AY18: =VLOOKUP($D18,Construction!$B:$Q,(COLUMN(Construction_QuestReward_Silver)-COLUMN(Construction_Name_and_Level)+1),FALSE) -> 100 | CY18: War Elephant
B19: Quest | C19: Initially Completed | D19: Watchtower 1 | E19: 2 | F19: 0 | G19: =VLOOKUP($D19,Construction!$B:$L,(COLUMN(Construction_QuestReward_HeroXP)-COLUMN(Construction_Name_and_Level)+1),FALSE) -> 2525 | H19: =G19*(1+F19) -> 2525 | J19: =VLOOKUP($D19,Construction!$B:$L,(COLUMN(Construction_QuestReward_Power)-COLUMN(Construction_Name_and_Level)+1),FALSE) -> 2 | AJ19: =AJ18+(S$3*S19+T$3*T19+U$3*U19+V$3*V19+W$3*W19+X$3*X19+Y$3*Y19+Z$3*Z19+AA$3*AA19+AB$3*AB19+AC$3*AC19) -> 0.047222222 | AU19: =VLOOKUP($D19,Construction!$B:$Q,(COLUMN(Construction_QuestReward_Stone)-COLUMN(Construction_Name_and_Level)+1),FALSE) -> 2500 | AV19: =VLOOKUP($D19,Construction!$B:$Q,(COLUMN(Construction_QuestReward_Wood)-COLUMN(Construction_Name_and_Level)+1),FALSE) -> 2100 | AW19: =VLOOKUP($D19,Construction!$B:$Q,(COLUMN(Construction_QuestReward_Ore)-COLUMN(Construction_Name_and_Level)+1),FALSE) -> 500 | AX19: =VLOOKUP($D19,Construction!$B:$Q,(COLUMN(Construction_QuestReward_Food)-COLUMN(Construction_Name_and_Level)+1),FALSE) -> 1100 | AY19: =VLOOKUP($D19,Construction!$B:$Q,(COLUMN(Construction_QuestReward_Silver)-COLUMN(Construction_Name_and_Level)+1),FALSE) -> 50 | CY19: Onager
B20: Quest | C20: Construction Recommended | D20: Stronghold 2 | E20: 2 | F20: 0 | G20: =VLOOKUP($D20,Construction!$B:$L,(COLUMN(Construction_QuestReward_HeroXP)-COLUMN(Construction_Name_and_Level)+1),FALSE) -> 2575 | H20: =G20*(1+F20) -> 2575 | J20: =VLOOKUP($D20,Construction!$B:$L,(COLUMN(Construction_QuestReward_Power)-COLUMN(Construction_Name_and_Level)+1),FALSE) -> 30 | W20: 1 | AF20: =$S$3*$S20+$T$3*$T20+$U$3*$U20+$V$3*$V20+$W$3*$W20+$X$3*$X20+$Y$3*$Y20+$Z$3*$Z20+$AA$3*$AA20+$AB$3*$AB20+$AC$3*$AC20 -> 0.010416667 | AJ20: =AJ19+(S$3*S20+T$3*T20+U$3*U20+V$3*V20+W$3*W20+X$3*X20+Y$3*Y20+Z$3*Z20+AA$3*AA20+AB$3*AB20+AC$3*AC20) -> 0.057638889 | AU20: =VLOOKUP($D20,Construction!$B:$Q,(COLUMN(Construction_QuestReward_Stone)-COLUMN(Construction_Name_and_Level)+1),FALSE) -> 4600 | AV20: =VLOOKUP($D20,Construction!$B:$Q,(COLUMN(Construction_QuestReward_Wood)-COLUMN(Construction_Name_and_Level)+1),FALSE) -> 4600 | AW20: =VLOOKUP($D20,Construction!$B:$Q,(COLUMN(Construction_QuestReward_Ore)-COLUMN(Construction_Name_and_Level)+1),FALSE) -> 1800 | AX20: =VLOOKUP($D20,Construction!$B:$Q,(COLUMN(Construction_QuestReward_Food)-COLUMN(Construction_Name_and_Level)+1),FALSE) -> 2300 | AY20: =VLOOKUP($D20,Construction!$B:$Q,(COLUMN(Construction_QuestReward_Silver)-COLUMN(Construction_Name_and_Level)+1),FALSE) -> 400 | CY20: War Bricks
B21: Construction | C21: by Quest | D21: Logging Camp 1 | E21: 2 | F21: 0 | G21: =VLOOKUP($D21,Construction!$B:$E,(COLUMN(Construction_BuildingReward_HeroXP)-COLUMN(Construction_Name_and_Level)+1),FALSE) -> 10 | H21: =G21*(1+F21) -> 10 | J21: =VLOOKUP($D21,Construction!$B:$F,(COLUMN(Construction_BuildingReward_Power)-COLUMN(Construction_Name_and_Level)+1),FALSE) -> 5 | Q21: 0.0034722222 | R21: 0.0041666667 | AJ21: =AJ20+(S$3*S21+T$3*T21+U$3*U21+V$3*V21+W$3*W21+X$3*X21+Y$3*Y21+Z$3*Z21+AA$3*AA21+AB$3*AB21+AC$3*AC21) -> 0.057638889 | AK21: 0 | AL21: =VLOOKUP($D21,Construction!$B:$C,(COLUMN(Construction_Time)-COLUMN(Construction_Name_and_Level)+1),FALSE) -> 0.00069444444 | AM21: =AL21/(1+AK21) -> 0.00069444444 | AN21: =(S$3*S21+T$3*T21+V$3*V21+W$3*W21+X$3*X21+Y$3*Y21+Z$3*Z21+AA$3*AA21+AB$3*AB21+AC$3*AC21)*(-1) -> 0 | AO21: =IF((AM21-Q21-R21-AN21)>=0,AM21-Q21-R21-AN21,0) -> 0 | AU21: =VLOOKUP($D21,Construction!$B:$J,(COLUMN(Construction_BuildingCost_Stone)-COLUMN(Construction_Name_and_Level)+1),FALSE)*(-1) -> -100 | AV21: =VLOOKUP($D21,Construction!$B:$J,(COLUMN(Construction_BuildingCost_Wood)-COLUMN(Construction_Name_and_Level)+1),FALSE)*(-1) -> 0 | AW21: =VLOOKUP($D21,Construction!$B:$J,(COLUMN(Construction_BuildingCost_Ore)-COLUMN(Construction_Name_and_Level)+1),FALSE)*(-1) -> -100 | AX21: =VLOOKUP($D21,Construction!$B:$J,(COLUMN(Construction_BuildingCost_Food)-COLUMN(Construction_Name_and_Level)+1),FALSE)*(-1) -> -100 | CY21: Archer Tower
B22: Quest | C22: Construction Recommended | D22: Logging Camp 1 | E22: 2 | F22: 0 | G22: =VLOOKUP($D22,Construction!$B:$L,(COLUMN(Construction_QuestReward_HeroXP)-COLUMN(Construction_Name_and_Level)+1),FALSE) -> 2525 | H22: =G22*(1+F22) -> 2525 | J22: =VLOOKUP($D22,Construction!$B:$L,(COLUMN(Construction_QuestReward_Power)-COLUMN(Construction_Name_and_Level)+1),FALSE) -> 2 | AJ22: =AJ21+(S$3*S22+T$3*T22+U$3*U22+V$3*V22+W$3*W22+X$3*X22+Y$3*Y22+Z$3*Z22+AA$3*AA22+AB$3*AB22+AC$3*AC22) -> 0.057638889 | AU22: =VLOOKUP($D22,Construction!$B:$Q,(COLUMN(Construction_QuestReward_Stone)-COLUMN(Construction_Name_and_Level)+1),FALSE) -> 0 | AV22: =VLOOKUP($D22,Construction!$B:$Q,(COLUMN(Construction_QuestReward_Wood)-COLUMN(Construction_Name_and_Level)+1),FALSE) -> 3000 | AW22: =VLOOKUP($D22,Construction!$B:$Q,(COLUMN(Construction_QuestReward_Ore)-COLUMN(Construction_Name_and_Level)+1),FALSE) -> 0 | AX22: =VLOOKUP($D22,Construction!$B:$Q,(COLUMN(Construction_QuestReward_Food)-COLUMN(Construction_Name_and_Level)+1),FALSE) -> 0 | AY22: =VLOOKUP($D22,Construction!$B:$Q,(COLUMN(Construction_QuestReward_Silver)-COLUMN(Construction_Name_and_Level)+1),FALSE) -> 0 | CY22: Spikes
B23: Construction | C23: by Quest | D23: Academy 1 | E23: 2 | F23: 0 | G23: =VLOOKUP($D23,Construction!$B:$E,(COLUMN(Construction_BuildingReward_HeroXP)-COLUMN(Construction_Name_and_Level)+1),FALSE) -> 10 | H23: =G23*(1+F23) -> 10 | J23: =VLOOKUP($D23,Construction!$B:$F,(COLUMN(Construction_BuildingReward_Power)-COLUMN(Construction_Name_and_Level)+1),FALSE) -> 35 | Q23: 0.0034722222 | R23: 0.0041666667 | AJ23: =AJ22+(S$3*S23+T$3*T23+U$3*U23+V$3*V23+W$3*W23+X$3*X23+Y$3*Y23+Z$3*Z23+AA$3*AA23+AB$3*AB23+AC$3*AC23) -> 0.057638889 | AK23: 0 | AL23: =VLOOKUP($D23,Construction!$B:$C,(COLUMN(Construction_Time)-COLUMN(Construction_Name_and_Level)+1),FALSE) -> 0.0011574074 | AM23: =AL23/(1+AK23) -> 0.0011574074 | AN23: =(S$3*S23+T$3*T23+V$3*V23+W$3*W23+X$3*X23+Y$3*Y23+Z$3*Z23+AA$3*AA23+AB$3*AB23+AC$3*AC23)*(-1) -> 0 | AO23: =IF((AM23-Q23-R23-AN23)>=0,AM23-Q23-R23-AN23,0) -> 0 | AP23: 0.01 | AU23: =VLOOKUP($D23,Construction!$B:$J,(COLUMN(Construction_BuildingCost_Stone)-COLUMN(Construction_Name_and_Level)+1),FALSE)*(-1) -> -500 | AV23: =VLOOKUP($D23,Construction!$B:$J,(COLUMN(Construction_BuildingCost_Wood)-COLUMN(Construction_Name_and_Level)+1),FALSE)*(-1) -> -500 | AW23: =VLOOKUP($D23,Construction!$B:$J,(COLUMN(Construction_BuildingCost_Ore)-COLUMN(Construction_Name_and_Level)+1),FALSE)*(-1) -> -200 | AX23: =VLOOKUP($D23,Construction!$B:$J,(COLUMN(Construction_BuildingCost_Food)-COLUMN(Construction_Name_and_Level)+1),FALSE)*(-1) -> -300 | CY23: Boiling Tar
B24: Quest | C24: Construction Recommended | D24: Academy 1 | E24: 2 | F24: 0 | G24: =VLOOKUP($D24,Construction!$B:$L,(COLUMN(Construction_QuestReward_HeroXP)-COLUMN(Construction_Name_and_Level)+1),FALSE) -> 2525 | H24: =G24*(1+F24) -> 2525 | J24: =VLOOKUP($D24,Construction!$B:$L,(COLUMN(Construction_QuestReward_Power)-COLUMN(Construction_Name_and_Level)+1),FALSE) -> 5 | AJ24: =AJ23+(S$3*S24+T$3*T24+U$3*U24+V$3*V24+W$3*W24+X$3*X24+Y$3*Y24+Z$3*Z24+AA$3*AA24+AB$3*AB24+AC$3*AC24) -> 0.057638889 | AU24: =VLOOKUP($D24,Construction!$B:$Q,(COLUMN(Construction_QuestReward_Stone)-COLUMN(Construction_Name_and_Level)+1),FALSE) -> 2500 | AV24: =VLOOKUP($D24,Construction!$B:$Q,(COLUMN(Construction_QuestReward_Wood)-COLUMN(Construction_Name_and_Level)+1),FALSE) -> 2500 | AW24: =VLOOKUP($D24,Construction!$B:$Q,(COLUMN(Construction_QuestReward_Ore)-COLUMN(Construction_Name_and_Level)+1),FALSE) -> 1100 | AX24: =VLOOKUP($D24,Construction!$B:$Q,(COLUMN(Construction_QuestReward_Food)-COLUMN(Construction_Name_and_Level)+1),FALSE) -> 1500 | AY24: =VLOOKUP($D24,Construction!$B:$Q,(COLUMN(Construction_QuestReward_Silver)-COLUMN(Construction_Name_and_Level)+1),FALSE) -> 100
B25: Research | C25: by Quest | D25: Scouting 1 | E25: 2 | F25: 0 | G25: =VLOOKUP($D25,Research!$C:$F,(COLUMN(Research_ResearchReward_HeroXP)-COLUMN(Research_Name_and_Level)+1),FALSE) -> 48000 | H25: =G25*(1+F25) -> 48000 | J25: 31 | AJ25: =AJ24+(S$3*S25+T$3*T25+U$3*U25+V$3*V25+W$3*W25+X$3*X25+Y$3*Y25+Z$3*Z25+AA$3*AA25+AB$3*AB25+AC$3*AC25) -> 0.057638889 | AU25: =VLOOKUP($D25,Research!$C:$L,(COLUMN(Research_ResearchCost_Stone)-COLUMN(Research_Name_and_Level)+1),FALSE)*(-1) -> 0 | AV25: =VLOOKUP($D25,Research!$C:$L,(COLUMN(Research_ResearchCost_Wood)-COLUMN(Research_Name_and_Level)+1),FALSE)*(-1) -> 0 | AW25: =VLOOKUP($D25,Research!$C:$L,(COLUMN(Research_ResearchCost_Ore)-COLUMN(Research_Name_and_Level)+1),FALSE)*(-1) -> 0 | AX25: =VLOOKUP($D25,Research!$C:$L,(COLUMN(Research_ResearchCost_Food)-COLUMN(Research_Name_and_Level)+1),FALSE)*(-1) -> 0 | AY25: =VLOOKUP($D25,Research!$C:$L,(COLUMN(Research_ResearchCost_Silver)-COLUMN(Research_Name_and_Level)+1),FALSE)*(-1) -> -225
B26: Gift | C26: Hero Level Up | D26: Hero 2->3 | E26: 3 | I26: 1 | J26: 29 | AJ26: =AJ25+(S$3*S26+T$3*T26+U$3*U26+V$3*V26+W$3*W26+X$3*X26+Y$3*Y26+Z$3*Z26+AA$3*AA26+AB$3*AB26+AC$3*AC26) -> 0.057638889
B27: Level_Up | D27: Hero Level 3 | E27: 3 | F27: 0 | G27: — | H27: 60000 | I27: 3 | J27: 338 | K27: 2 | M27: 0.020833333 | N27: 100 | O27: =SUMIF($B$4:$B26,"<>"&$CS$13,O$4:O26) -> 0 | P27: =SUMIF($B$4:$B26,"<>"&$CS$13,N$4:N26) -> 100 | Q27: 0.0034722222 | R27: 0.0041666667 | S27: 0 | T27: 1 | U27: 0 | V27: 2 | W27: 4 | X27: 0 | Y27: 0 | Z27: 0 | AA27: 0 | AB27: 0 | AC27: 0 | AD27: 0 | AE27: 0 | AF27: =SUMIF($B$4:$B26,"<>"&$CS$13,AF$4:AF26) -> 0.057638889 | AG27: =SUMIF($B$4:$B26,"<>"&$CS$13,AG$4:AG26) -> 0 | AH27: =AF27+AG27 -> 0.057638889 | AI27: =SUMIF($B$4:$B26,"<>"&$CS$13,AI$4:AI26) -> 0 | AJ27: =S$3*S27+T$3*T27+U$3*U27+V$3*V27+W$3*W27+X$3*X27+Y$3*Y27+Z$3*Z27+AA$3*AA27+AB$3*AB27+AC$3*AC27 -> 0.057638889 | AK27: 0 | AL27: — | AM27: — | AN27: — | AO27: — | AP27: 0.01 | AQ27: — | AR27: — | AS27: — | AT27: — | AU27: 39500 | AV27: 41100 | AW27: 31580 | AX27: 43800 | AY27: 23820 | AZ27: 0 | BA27: 42 | BB27: 0 | BC27: 52 | BD27: 0 | BE27: 0 | BF27: 15000 | BG27: 17000 | BH27: 15000 | BI27: 17500 | BJ27: 15000 | BK27: 2 | BL27: 1 | BM27: 1 | BN27: 1 | BO27: 1 | BP27: 1 | BQ27: 1 | BR27: 0 | BS27: 0 | BT27: 0 | BU27: 0 | BV27: 0 | BW27: 0 | BX27: 0 | BY27: 0 | BZ27: 1 | CA27: 1 | CB27: 1 | CC27: 1 | CD27: 0 | CL27: 0 | CN27: —
B28: Gift | C28: Hero Level Up | D28: Hero 3->4 | E28: 4 | I28: 1 | J28: 29 | AJ28: =AJ27+(S$3*S28+T$3*T28+U$3*U28+V$3*V28+W$3*W28+X$3*X28+Y$3*Y28+Z$3*Z28+AA$3*AA28+AB$3*AB28+AC$3*AC28) -> 0.057638889
B29: Level_Up | D29: Hero Level 4 | E29: 4 | F29: 0 | G29: — | H29: 70755 | I29: 4 | J29: 396 | K29: 2 | M29: 0.020833333 | N29: 100 | O29: =SUMIF($B$4:$B28,"<>"&$CS$13,O$4:O28) -> 0 | P29: =SUMIF($B$4:$B28,"<>"&$CS$13,N$4:N28) -> 100 | Q29: 0.0034722222 | R29: 0.0041666667 | S29: 0 | T29: 1 | U29: 0 | V29: 2 | W29: 4 | X29: 0 | Y29: 0 | Z29: 0 | AA29: 0 | AB29: 0 | AC29: 0 | AD29: 0 | AE29: 0 | AF29: =SUMIF($B$4:$B28,"<>"&$CS$13,AF$4:AF28) -> 0.057638889 | AG29: =SUMIF($B$4:$B28,"<>"&$CS$13,AG$4:AG28) -> 0 | AH29: =AF29+AG29 -> 0.057638889 | AI29: =SUMIF($B$4:$B28,"<>"&$CS$13,AI$4:AI28) -> 0 | AJ29: =S$3*S29+T$3*T29+U$3*U29+V$3*V29+W$3*W29+X$3*X29+Y$3*Y29+Z$3*Z29+AA$3*AA29+AB$3*AB29+AC$3*AC29 -> 0.057638889 | AK29: 0 | AL29: — | AM29: — | AN29: — | AO29: — | AP29: 0.01 | AQ29: — | AR29: — | AS29: — | AT29: — | AU29: 39500 | AV29: 41100 | AW29: 31580 | AX29: 43800 | AY29: 23820 | AZ29: 0 | BA29: 42 | BB29: 0 | BC29: 52 | BD29: 0 | BE29: 0 | BF29: 15000 | BG29: 17000 | BH29: 15000 | BI29: 17500 | BJ29: 15000 | BK29: 2 | BL29: 1 | BM29: 1 | BN29: 1 | BO29: 1 | BP29: 1 | BQ29: 1 | BR29: 0 | BS29: 0 | BT29: 0 | BU29: 0 | BV29: 0 | BW29: 0 | BX29: 0 | BY29: 0 | BZ29: 1 | CA29: 1 | CB29: 1 | CC29: 1 | CD29: 0 | CL29: 0 | CN29: —
B30: Quest | C30: Research Recommended | D30: Scouting 1 | E30: 4 | F30: 0 | G30: =VLOOKUP($D30,Research!$C:$M,(COLUMN(Research_QuestReward_HeroXP)-COLUMN(Research_Name_and_Level)+1),FALSE) -> 1000 | H30: =G30*(1+F30) -> 1000 | J30: =VLOOKUP($D30,Research!$C:$N,(COLUMN(Research_QuestReward_Power)-COLUMN(Research_Name_and_Level)+1),FALSE) -> 75 | AJ30: =AJ29+(S$3*S30+T$3*T30+U$3*U30+V$3*V30+W$3*W30+X$3*X30+Y$3*Y30+Z$3*Z30+AA$3*AA30+AB$3*AB30+AC$3*AC30) -> 0.057638889 | AU30: =VLOOKUP($D30,Research!$C:$S,(COLUMN(Research_QuestReward_Stone)-COLUMN(Research_Name_and_Level)+1),FALSE) -> 0 | AV30: =VLOOKUP($D30,Research!$C:$S,(COLUMN(Research_QuestReward_Wood)-COLUMN(Research_Name_and_Level)+1),FALSE) -> 0 | AW30: =VLOOKUP($D30,Research!$C:$S,(COLUMN(Research_QuestReward_Ore)-COLUMN(Research_Name_and_Level)+1),FALSE) -> 0 | AX30: =VLOOKUP($D30,Research!$C:$S,(COLUMN(Research_QuestReward_Food)-COLUMN(Research_Name_and_Level)+1),FALSE) -> 0 | AY30: =VLOOKUP($D30,Research!$C:$S,(COLUMN(Research_QuestReward_Silver)-COLUMN(Research_Name_and_Level)+1),FALSE) -> 387
B31: Construction | C31: at Will | D31: Barracks 1 | E31: 4 | F31: 0 | G31: =VLOOKUP($D31,Construction!$B:$E,(COLUMN(Construction_BuildingReward_HeroXP)-COLUMN(Construction_Name_and_Level)+1),FALSE) -> 10 | H31: =G31*(1+F31) -> 10 | J31: =VLOOKUP($D31,Construction!$B:$F,(COLUMN(Construction_BuildingReward_Power)-COLUMN(Construction_Name_and_Level)+1),FALSE) -> 20 | Q31: 0.0034722222 | R31: 0.0041666667 | AJ31: =AJ30+(S$3*S31+T$3*T31+U$3*U31+V$3*V31+W$3*W31+X$3*X31+Y$3*Y31+Z$3*Z31+AA$3*AA31+AB$3*AB31+AC$3*AC31) -> 0.057638889 | AK31: 0 | AL31: =VLOOKUP($D31,Construction!$B:$C,(COLUMN(Construction_Time)-COLUMN(Construction_Name_and_Level)+1),FALSE) -> 0.0010416667 | AM31: =AL31/(1+AK31) -> 0.0010416667 | AN31: =(S$3*S31+T$3*T31+V$3*V31+W$3*W31+X$3*X31+Y$3*Y31+Z$3*Z31+AA$3*AA31+AB$3*AB31+AC$3*AC31)*(-1) -> 0 | AO31: =IF((AM31-Q31-R31-AN31)>=0,AM31-Q31-R31-AN31,0) -> 0 | AU31: =VLOOKUP($D31,Construction!$B:$J,(COLUMN(Construction_BuildingCost_Stone)-COLUMN(Construction_Name_and_Level)+1),FALSE)*(-1) -> -500 | AV31: =VLOOKUP($D31,Construction!$B:$J,(COLUMN(Construction_BuildingCost_Wood)-COLUMN(Construction_Name_and_Level)+1),FALSE)*(-1) -> -400 | AW31: =VLOOKUP($D31,Construction!$B:$J,(COLUMN(Construction_BuildingCost_Ore)-COLUMN(Construction_Name_and_Level)+1),FALSE)*(-1) -> -300 | AX31: =VLOOKUP($D31,Construction!$B:$J,(COLUMN(Construction_BuildingCost_Food)-COLUMN(Construction_Name_and_Level)+1),FALSE)*(-1) -> -250
B32: Training | C32: Swordsmen | D32: 20 | E32: 4 | J32: =VLOOKUP($C32,Troop!$B:$AK,(COLUMN(Troop_TrainingReward_Power)-COLUMN(Troop_Name)+1),FALSE)*$D32 -> 40 | AJ32: =AJ31+(S$3*S32+T$3*T32+U$3*U32+V$3*V32+W$3*W32+X$3*X32+Y$3*Y32+Z$3*Z32+AA$3*AA32+AB$3*AB32+AC$3*AC32) -> 0.057638889 | AU32: =VLOOKUP($C32,Troop!$B:$P,(COLUMN(Troop_TrainingCost_Stone)-COLUMN(Troop_Name)+1),FALSE)*$D32*(-1) -> 0 | AV32: =VLOOKUP($C32,Troop!$B:$P,(COLUMN(Troop_TrainingCost_Wood)-COLUMN(Troop_Name)+1),FALSE)*$D32*(-1) -> -1000 | AW32: =VLOOKUP($C32,Troop!$B:$P,(COLUMN(Troop_TrainingCost_Ore)-COLUMN(Troop_Name)+1),FALSE)*$D32*(-1) -> -760 | AX32: =VLOOKUP($C32,Troop!$B:$P,(COLUMN(Troop_TrainingCost_Food)-COLUMN(Troop_Name)+1),FALSE)*$D32*(-1) -> -1000 | AY32: =VLOOKUP($C32,Troop!$B:$P,(COLUMN(Troop_TrainingCost_Silver)-COLUMN(Troop_Name)+1),FALSE)*$D32*(-1) -> 0
B33: Quest | C33: Construction Recommended | D33: Barracks 1 | E33: 4 | F33: 0 | G33: =VLOOKUP($D33,Construction!$B:$L,(COLUMN(Construction_QuestReward_HeroXP)-COLUMN(Construction_Name_and_Level)+1),FALSE) -> 2525 | H33: =G33*(1+F33) -> 2525 | J33: =VLOOKUP($D33,Construction!$B:$L,(COLUMN(Construction_QuestReward_Power)-COLUMN(Construction_Name_and_Level)+1),FALSE) -> 2 | AJ33: =AJ32+(S$3*S33+T$3*T33+U$3*U33+V$3*V33+W$3*W33+X$3*X33+Y$3*Y33+Z$3*Z33+AA$3*AA33+AB$3*AB33+AC$3*AC33) -> 0.057638889 | AU33: =VLOOKUP($D33,Construction!$B:$Q,(COLUMN(Construction_QuestReward_Stone)-COLUMN(Construction_Name_and_Level)+1),FALSE) -> 5000 | AV33: =VLOOKUP($D33,Construction!$B:$Q,(COLUMN(Construction_QuestReward_Wood)-COLUMN(Construction_Name_and_Level)+1),FALSE) -> 4000 | AW33: =VLOOKUP($D33,Construction!$B:$Q,(COLUMN(Construction_QuestReward_Ore)-COLUMN(Construction_Name_and_Level)+1),FALSE) -> 3000 | AX33: =VLOOKUP($D33,Construction!$B:$Q,(COLUMN(Construction_QuestReward_Food)-COLUMN(Construction_Name_and_Level)+1),FALSE) -> 2500 | AY33: =VLOOKUP($D33,Construction!$B:$Q,(COLUMN(Construction_QuestReward_Silver)-COLUMN(Construction_Name_and_Level)+1),FALSE) -> 100
B34: Quest | C34: Training Recommended | D34: Swordsmen 20 | E34: 4 | F34: 0 | G34: 2500 | H34: =G34*(1+F34) -> 2500 | J34: 25 | AJ34: =AJ33+(S$3*S34+T$3*T34+U$3*U34+V$3*V34+W$3*W34+X$3*X34+Y$3*Y34+Z$3*Z34+AA$3*AA34+AB$3*AB34+AC$3*AC34) -> 0.057638889 | AU34: 0 | AV34: 2100 | AW34: 1500 | AX34: 2100 | AY34: 0
B35: Quest | C35: Special | D35: Participate an Event | E35: 4 | F35: 0 | G35: 10000 | H35: =G35*(1+F35) -> 10000 | J35: 25 | M35: 0.041666667 | AJ35: =AJ34+(S$3*S35+T$3*T35+U$3*U35+V$3*V35+W$3*W35+X$3*X35+Y$3*Y35+Z$3*Z35+AA$3*AA35+AB$3*AB35+AC$3*AC35) -> 0.057638889
B36: Quest | C36: Special | D36: Join an Alliance | E36: 4 | N36: 100 | AJ36: =AJ35+(S$3*S36+T$3*T36+U$3*U36+V$3*V36+W$3*W36+X$3*X36+Y$3*Y36+Z$3*Z36+AA$3*AA36+AB$3*AB36+AC$3*AC36) -> 0.057638889
B37: Construction | C37: at Will | D37: Storehouse 2 | E37: 4 | F37: 0 | G37: =VLOOKUP($D37,Construction!$B:$E,(COLUMN(Construction_BuildingReward_HeroXP)-COLUMN(Construction_Name_and_Level)+1),FALSE) -> 25 | H37: =G37*(1+F37) -> 25 | J37: =VLOOKUP($D37,Construction!$B:$F,(COLUMN(Construction_BuildingReward_Power)-COLUMN(Construction_Name_and_Level)+1),FALSE) -> 20 | Q37: 0.0034722222 | R37: 0.0041666667 | AJ37: =AJ36+(S$3*S37+T$3*T37+U$3*U37+V$3*V37+W$3*W37+X$3*X37+Y$3*Y37+Z$3*Z37+AA$3*AA37+AB$3*AB37+AC$3*AC37) -> 0.057638889 | AK37: 0 | AL37: =VLOOKUP($D37,Construction!$B:$C,(COLUMN(Construction_Time)-COLUMN(Construction_Name_and_Level)+1),FALSE) -> 0.0013888889 | AM37: =AL37/(1+AK37) -> 0.0013888889 | AN37: =(S$3*S37+T$3*T37+V$3*V37+W$3*W37+X$3*X37+Y$3*Y37+Z$3*Z37+AA$3*AA37+AB$3*AB37+AC$3*AC37)*(-1) -> 0 | AO37: =IF((AM37-Q37-R37-AN37)>=0,AM37-Q37-R37-AN37,0) -> 0 | AU37: =VLOOKUP($D37,Construction!$B:$J,(COLUMN(Construction_BuildingCost_Stone)-COLUMN(Construction_Name_and_Level)+1),FALSE)*(-1) -> -680 | AV37: =VLOOKUP($D37,Construction!$B:$J,(COLUMN(Construction_BuildingCost_Wood)-COLUMN(Construction_Name_and_Level)+1),FALSE)*(-1) -> -680 | AW37: =VLOOKUP($D37,Construction!$B:$J,(COLUMN(Construction_BuildingCost_Ore)-COLUMN(Construction_Name_and_Level)+1),FALSE)*(-1) -> -510 | AX37: =VLOOKUP($D37,Construction!$B:$J,(COLUMN(Construction_BuildingCost_Food)-COLUMN(Construction_Name_and_Level)+1),FALSE)*(-1) -> -340
B38: Construction | C38: at Will | D38: Walls 2 | E38: 4 | F38: 0 | G38: =VLOOKUP($D38,Construction!$B:$E,(COLUMN(Construction_BuildingReward_HeroXP)-COLUMN(Construction_Name_and_Level)+1),FALSE) -> 5000 | H38: =G38*(1+F38) -> 5000 | J38: =VLOOKUP($D38,Construction!$B:$F,(COLUMN(Construction_BuildingReward_Power)-COLUMN(Construction_Name_and_Level)+1),FALSE) -> 90 | Q38: 0.0034722222 | R38: 0.0041666667 | AJ38: =AJ37+(S$3*S38+T$3*T38+U$3*U38+V$3*V38+W$3*W38+X$3*X38+Y$3*Y38+Z$3*Z38+AA$3*AA38+AB$3*AB38+AC$3*AC38) -> 0.057638889 | AK38: 0 | AL38: =VLOOKUP($D38,Construction!$B:$C,(COLUMN(Construction_Time)-COLUMN(Construction_Name_and_Level)+1),FALSE) -> 0.0024305556 | AM38: =AL38/(1+AK38) -> 0.0024305556 | AN38: =(S$3*S38+T$3*T38+V$3*V38+W$3*W38+X$3*X38+Y$3*Y38+Z$3*Z38+AA$3*AA38+AB$3*AB38+AC$3*AC38)*(-1) -> 0 | AO38: =IF((AM38-Q38-R38-AN38)>=0,AM38-Q38-R38-AN38,0) -> 0 | AU38: =VLOOKUP($D38,Construction!$B:$J,(COLUMN(Construction_BuildingCost_Stone)-COLUMN(Construction_Name_and_Level)+1),FALSE)*(-1) -> -1800 | AV38: =VLOOKUP($D38,Construction!$B:$J,(COLUMN(Construction_BuildingCost_Wood)-COLUMN(Construction_Name_and_Level)+1),FALSE)*(-1) -> -1440 | AW38: =VLOOKUP($D38,Construction!$B:$J,(COLUMN(Construction_BuildingCost_Ore)-COLUMN(Construction_Name_and_Level)+1),FALSE)*(-1) -> -540 | AX38: =VLOOKUP($D38,Construction!$B:$J,(COLUMN(Construction_BuildingCost_Food)-COLUMN(Construction_Name_and_Level)+1),FALSE)*(-1) -> -900
B39: Construction | C39: at Will | D39: Stronghold 3 | E39: 4 | F39: 0 | G39: =VLOOKUP($D39,Construction!$B:$E,(COLUMN(Construction_BuildingReward_HeroXP)-COLUMN(Construction_Name_and_Level)+1),FALSE) -> 10000 | H39: =G39*(1+F39) -> 10000 | J39: =VLOOKUP($D39,Construction!$B:$F,(COLUMN(Construction_BuildingReward_Power)-COLUMN(Construction_Name_and_Level)+1),FALSE) -> 150 | Q39: 0.0034722222 | R39: 0.0048611111 | T39: -1 | AI39: =(-1)*($S$3*$S39+$T$3*$T39+$U$3*$U39+$V$3*$V39+$W$3*$W39+$X$3*$X39+$Y$3*$Y39+$Z$3*$Z39+$AA$3*$AA39+$AB$3*$AB39+$AC$3*$AC39) -> 0.0020833333 | AJ39: =AJ38+(S$3*S39+T$3*T39+U$3*U39+V$3*V39+W$3*W39+X$3*X39+Y$3*Y39+Z$3*Z39+AA$3*AA39+AB$3*AB39+AC$3*AC39) -> 0.055555556 | AK39: 0 | AL39: =VLOOKUP($D39,Construction!$B:$C,(COLUMN(Construction_Time)-COLUMN(Construction_Name_and_Level)+1),FALSE) -> 0.013888889 | AM39: =AL39/(1+AK39) -> 0.013888889 | AN39: =(S$3*S39+T$3*T39+V$3*V39+W$3*W39+X$3*X39+Y$3*Y39+Z$3*Z39+AA$3*AA39+AB$3*AB39+AC$3*AC39)*(-1) -> 0.0020833333 | AO39: =IF((AM39-Q39-R39-AN39)>=0,AM39-Q39-R39-AN39,0) -> 0.0034722222 | AU39: =VLOOKUP($D39,Construction!$B:$J,(COLUMN(Construction_BuildingCost_Stone)-COLUMN(Construction_Name_and_Level)+1),FALSE)*(-1) -> -3240 | AV39: =VLOOKUP($D39,Construction!$B:$J,(COLUMN(Construction_BuildingCost_Wood)-COLUMN(Construction_Name_and_Level)+1),FALSE)*(-1) -> -3240 | AW39: =VLOOKUP($D39,Construction!$B:$J,(COLUMN(Construction_BuildingCost_Ore)-COLUMN(Construction_Name_and_Level)+1),FALSE)*(-1) -> -1296 | AX39: =VLOOKUP($D39,Construction!$B:$J,(COLUMN(Construction_BuildingCost_Food)-COLUMN(Construction_Name_and_Level)+1),FALSE)*(-1) -> -1620
B40: Gift | C40: Stronghold upgrade Event | D40: Stronghold 2->3 Event | E40: 4 | W40: 2 | AF40: =$S$3*$S40+$T$3*$T40+$U$3*$U40+$V$3*$V40+$W$3*$W40+$X$3*$X40+$Y$3*$Y40+$Z$3*$Z40+$AA$3*$AA40+$AB$3*$AB40+$AC$3*$AC40 -> 0.020833333 | AJ40: =AJ39+(S$3*S40+T$3*T40+U$3*U40+V$3*V40+W$3*W40+X$3*X40+Y$3*Y40+Z$3*Z40+AA$3*AA40+AB$3*AB40+AC$3*AC40) -> 0.076388889 | AU40: 2800 | AV40: 3600 | AW40: 3600 | AX40: 4200 | AY40: 2800
B41: Gift | C41: Hero Level Up | D41: Hero 4->5 | E41: 5 | I41: 2 | J41: 29 | AJ41: =AJ40+(S$3*S41+T$3*T41+U$3*U41+V$3*V41+W$3*W41+X$3*X41+Y$3*Y41+Z$3*Z41+AA$3*AA41+AB$3*AB41+AC$3*AC41) -> 0.076388889
B42: Level_Up | D42: Hero Level 5 | E42: 5 | F42: 0 | G42: — | H42: 101815 | I42: 6 | J42: 872 | K42: 2 | M42: 0.0625 | N42: 200 | O42: =SUMIF($B$4:$B41,"<>"&$CS$13,O$4:O41) -> 0 | P42: =SUMIF($B$4:$B41,"<>"&$CS$13,N$4:N41) -> 200 | Q42: 0.0034722222 | R42: 0.0048611111 | S42: 0 | T42: 0 | U42: 0 | V42: 2 | W42: 6 | X42: 0 | Y42: 0 | Z42: 0 | AA42: 0 | AB42: 0 | AC42: 0 | AD42: 0 | AE42: 0 | AF42: =SUMIF($B$4:$B41,"<>"&$CS$13,AF$4:AF41) -> 0.078472222 | AG42: =SUMIF($B$4:$B41,"<>"&$CS$13,AG$4:AG41) -> 0 | AH42: =AF42+AG42 -> 0.078472222 | AI42: =SUMIF($B$4:$B41,"<>"&$CS$13,AI$4:AI41) -> 0.0020833333 | AJ42: =S$3*S42+T$3*T42+U$3*U42+V$3*V42+W$3*W42+X$3*X42+Y$3*Y42+Z$3*Z42+AA$3*AA42+AB$3*AB42+AC$3*AC42 -> 0.076388889 | AK42: 0 | AL42: — | AM42: — | AN42: — | AO42: — | AP42: 0.01 | AQ42: — | AR42: — | AS42: — | AT42: — | AU42: 41880 | AV42: 45500 | AW42: 37770 | AX42: 49990 | AY42: 27110 | AZ42: 0 | BA42: 40 | BB42: 0 | BC42: 54 | BD42: 0 | BE42: -20 | BF42: 15000 | BG42: 17000 | BH42: 15000 | BI42: 17500 | BJ42: 15000 | BK42: 3 | BL42: 2 | BM42: 2 | BN42: 1 | BO42: 1 | BP42: 1 | BQ42: 1 | BR42: 0 | BS42: 0 | BT42: 0 | BU42: 0 | BV42: 0 | BW42: 0 | BX42: 1 | BY42: 1 | BZ42: 1 | CA42: 1 | CB42: 1 | CC42: 1 | CD42: 0 | CL42: 1000 | CN42: —
B43: Construction | C43: at Will | D43: Storehouse 3 | E43: 5 | F43: 0 | G43: =VLOOKUP($D43,Construction!$B:$E,(COLUMN(Construction_BuildingReward_HeroXP)-COLUMN(Construction_Name_and_Level)+1),FALSE) -> 50 | H43: =G43*(1+F43) -> 50 | J43: =VLOOKUP($D43,Construction!$B:$F,(COLUMN(Construction_BuildingReward_Power)-COLUMN(Construction_Name_and_Level)+1),FALSE) -> 30 | Q43: 0.0034722222 | R43: 0.0048611111 | AJ43: =AJ42+(S$3*S43+T$3*T43+U$3*U43+V$3*V43+W$3*W43+X$3*X43+Y$3*Y43+Z$3*Z43+AA$3*AA43+AB$3*AB43+AC$3*AC43) -> 0.076388889 | AK43: 0 | AL43: =VLOOKUP($D43,Construction!$B:$C,(COLUMN(Construction_Time)-COLUMN(Construction_Name_and_Level)+1),FALSE) -> 0.0027777778 | AM43: =AL43/(1+AK43) -> 0.0027777778 | AN43: =(S$3*S43+T$3*T43+V$3*V43+W$3*W43+X$3*X43+Y$3*Y43+Z$3*Z43+AA$3*AA43+AB$3*AB43+AC$3*AC43)*(-1) -> 0 | AO43: =IF((AM43-Q43-R43-AN43)>=0,AM43-Q43-R43-AN43,0) -> 0 | AU43: =VLOOKUP($D43,Construction!$B:$J,(COLUMN(Construction_BuildingCost_Stone)-COLUMN(Construction_Name_and_Level)+1),FALSE)*(-1) -> -1156 | AV43: =VLOOKUP($D43,Construction!$B:$J,(COLUMN(Construction_BuildingCost_Wood)-COLUMN(Construction_Name_and_Level)+1),FALSE)*(-1) -> -1156 | AW43: =VLOOKUP($D43,Construction!$B:$J,(COLUMN(Construction_BuildingCost_Ore)-COLUMN(Construction_Name_and_Level)+1),FALSE)*(-1) -> -867 | AX43: =VLOOKUP($D43,Construction!$B:$J,(COLUMN(Construction_BuildingCost_Food)-COLUMN(Construction_Name_and_Level)+1),FALSE)*(-1) -> -578
B44: Construction | C44: at Will | D44: Stronghold 4 | E44: 5 | F44: 0 | G44: =VLOOKUP($D44,Construction!$B:$E,(COLUMN(Construction_BuildingReward_HeroXP)-COLUMN(Construction_Name_and_Level)+1),FALSE) -> 10000 | H44: =G44*(1+F44) -> 10000 | J44: =VLOOKUP($D44,Construction!$B:$F,(COLUMN(Construction_BuildingReward_Power)-COLUMN(Construction_Name_and_Level)+1),FALSE) -> 250 | Q44: 0.0034722222 | R44: 0.0055555556 | V44: -2 | W44: -1 | AI44: =(-1)*($S$3*$S44+$T$3*$T44+$U$3*$U44+$V$3*$V44+$W$3*$W44+$X$3*$X44+$Y$3*$Y44+$Z$3*$Z44+$AA$3*$AA44+$AB$3*$AB44+$AC$3*$AC44) -> 0.024305556 | AJ44: =AJ43+(S$3*S44+T$3*T44+U$3*U44+V$3*V44+W$3*W44+X$3*X44+Y$3*Y44+Z$3*Z44+AA$3*AA44+AB$3*AB44+AC$3*AC44) -> 0.052083333 | AK44: 0 | AL44: =VLOOKUP($D44,Construction!$B:$C,(COLUMN(Construction_Time)-COLUMN(Construction_Name_and_Level)+1),FALSE) -> 0.027777778 | AM44: =AL44/(1+AK44) -> 0.027777778 | AN44: =(S$3*S44+T$3*T44+V$3*V44+W$3*W44+X$3*X44+Y$3*Y44+Z$3*Z44+AA$3*AA44+AB$3*AB44+AC$3*AC44)*(-1) -> 0.024305556 | AO44: =IF((AM44-Q44-R44-AN44)>=0,AM44-Q44-R44-AN44,0) -> 0 | AU44: =VLOOKUP($D44,Construction!$B:$J,(COLUMN(Construction_BuildingCost_Stone)-COLUMN(Construction_Name_and_Level)+1),FALSE)*(-1) -> -5832 | AV44: =VLOOKUP($D44,Construction!$B:$J,(COLUMN(Construction_BuildingCost_Wood)-COLUMN(Construction_Name_and_Level)+1),FALSE)*(-1) -> -5832 | AW44: =VLOOKUP($D44,Construction!$B:$J,(COLUMN(Construction_BuildingCost_Ore)-COLUMN(Construction_Name_and_Level)+1),FALSE)*(-1) -> -2333 | AX44: =VLOOKUP($D44,Construction!$B:$J,(COLUMN(Construction_BuildingCost_Food)-COLUMN(Construction_Name_and_Level)+1),FALSE)*(-1) -> -2916
B45: Gift | C45: Stronghold upgrade Event | D45: Stronghold 3->4 Event | E45: 5 | W45: 3 | AF45: =$S$3*$S45+$T$3*$T45+$U$3*$U45+$V$3*$V45+$W$3*$W45+$X$3*$X45+$Y$3*$Y45+$Z$3*$Z45+$AA$3*$AA45+$AB$3*$AB45+$AC$3*$AC45 -> 0.03125 | AJ45: =AJ44+(S$3*S45+T$3*T45+U$3*U45+V$3*V45+W$3*W45+X$3*X45+Y$3*Y45+Z$3*Z45+AA$3*AA45+AB$3*AB45+AC$3*AC45) -> 0.083333333 | AU45: 5200 | AV45: 5200 | AW45: 5200 | AX45: 6000 | AY45: 4000
B46: Construction | C46: at Will | D46: Storehouse 4 | E46: 5 | F46: 0 | G46: =VLOOKUP($D46,Construction!$B:$E,(COLUMN(Construction_BuildingReward_HeroXP)-COLUMN(Construction_Name_and_Level)+1),FALSE) -> 200 | H46: =G46*(1+F46) -> 200 | J46: =VLOOKUP($D46,Construction!$B:$F,(COLUMN(Construction_BuildingReward_Power)-COLUMN(Construction_Name_and_Level)+1),FALSE) -> 50 | Q46: 0.0034722222 | R46: 0.0055555556 | AJ46: =AJ45+(S$3*S46+T$3*T46+U$3*U46+V$3*V46+W$3*W46+X$3*X46+Y$3*Y46+Z$3*Z46+AA$3*AA46+AB$3*AB46+AC$3*AC46) -> 0.083333333 | AK46: 0 | AL46: =VLOOKUP($D46,Construction!$B:$C,(COLUMN(Construction_Time)-COLUMN(Construction_Name_and_Level)+1),FALSE) -> 0.0055555556 | AM46: =AL46/(1+AK46) -> 0.0055555556 | AN46: =(S$3*S46+T$3*T46+V$3*V46+W$3*W46+X$3*X46+Y$3*Y46+Z$3*Z46+AA$3*AA46+AB$3*AB46+AC$3*AC46)*(-1) -> 0 | AO46: =IF((AM46-Q46-R46-AN46)>=0,AM46-Q46-R46-AN46,0) -> 0 | AU46: =VLOOKUP($D46,Construction!$B:$J,(COLUMN(Construction_BuildingCost_Stone)-COLUMN(Construction_Name_and_Level)+1),FALSE)*(-1) -> -1966 | AV46: =VLOOKUP($D46,Construction!$B:$J,(COLUMN(Construction_BuildingCost_Wood)-COLUMN(Construction_Name_and_Level)+1),FALSE)*(-1) -> -1966 | AW46: =VLOOKUP($D46,Construction!$B:$J,(COLUMN(Construction_BuildingCost_Ore)-COLUMN(Construction_Name_and_Level)+1),FALSE)*(-1) -> -1474 | AX46: =VLOOKUP($D46,Construction!$B:$J,(COLUMN(Construction_BuildingCost_Food)-COLUMN(Construction_Name_and_Level)+1),FALSE)*(-1) -> -983
B47: Construction | C47: at Will | D47: Walls 3 | E47: 5 | F47: 0 | G47: =VLOOKUP($D47,Construction!$B:$E,(COLUMN(Construction_BuildingReward_HeroXP)-COLUMN(Construction_Name_and_Level)+1),FALSE) -> 5000 | H47: =G47*(1+F47) -> 5000 | J47: =VLOOKUP($D47,Construction!$B:$F,(COLUMN(Construction_BuildingReward_Power)-COLUMN(Construction_Name_and_Level)+1),FALSE) -> 100 | Q47: 0.0034722222 | R47: 0.0055555556 | AJ47: =AJ46+(S$3*S47+T$3*T47+U$3*U47+V$3*V47+W$3*W47+X$3*X47+Y$3*Y47+Z$3*Z47+AA$3*AA47+AB$3*AB47+AC$3*AC47) -> 0.083333333 | AK47: 0 | AL47: =VLOOKUP($D47,Construction!$B:$C,(COLUMN(Construction_Time)-COLUMN(Construction_Name_and_Level)+1),FALSE) -> 0.0048611111 | AM47: =AL47/(1+AK47) -> 0.0048611111 | AN47: =(S$3*S47+T$3*T47+V$3*V47+W$3*W47+X$3*X47+Y$3*Y47+Z$3*Z47+AA$3*AA47+AB$3*AB47+AC$3*AC47)*(-1) -> 0 | AO47: =IF((AM47-Q47-R47-AN47)>=0,AM47-Q47-R47-AN47,0) -> 0 | AU47: =VLOOKUP($D47,Construction!$B:$J,(COLUMN(Construction_BuildingCost_Stone)-COLUMN(Construction_Name_and_Level)+1),FALSE)*(-1) -> -3240 | AV47: =VLOOKUP($D47,Construction!$B:$J,(COLUMN(Construction_BuildingCost_Wood)-COLUMN(Construction_Name_and_Level)+1),FALSE)*(-1) -> -2592 | AW47: =VLOOKUP($D47,Construction!$B:$J,(COLUMN(Construction_BuildingCost_Ore)-COLUMN(Construction_Name_and_Level)+1),FALSE)*(-1) -> -972 | AX47: =VLOOKUP($D47,Construction!$B:$J,(COLUMN(Construction_BuildingCost_Food)-COLUMN(Construction_Name_and_Level)+1),FALSE)*(-1) -> -1620
B48: Research | C48: at Will | D48: Construction 1 | E48: 5 | F48: 0 | G48: =VLOOKUP($D48,Research!$C:$F,(COLUMN(Research_ResearchReward_HeroXP)-COLUMN(Research_Name_and_Level)+1),FALSE) -> 50000 | H48: =G48*(1+F48) -> 50000 | J48: =VLOOKUP($D48,Research!$C:$G,(COLUMN(Research_ResearchReward_Power)-COLUMN(Research_Name_and_Level)+1),FALSE) -> 1000 | R48: 0.0055555556 | AJ48: =AJ47+(S$3*S48+T$3*T48+U$3*U48+V$3*V48+W$3*W48+X$3*X48+Y$3*Y48+Z$3*Z48+AA$3*AA48+AB$3*AB48+AC$3*AC48) -> 0.083333333 | AK48: 0.01 | AP48: 0.01 | AQ48: =VLOOKUP($D48,Research!$C:$D,(COLUMN(Research_Time)-COLUMN(Research_Name_and_Level)+1),FALSE) -> 0.125 | AR48: =AQ48/(1+AP48) -> 0.12376238 | AS48: =(S$3*S48+T$3*T48+V$3*V48+W$3*W48+X$3*X48+Y$3*Y48+Z$3*Z48+AA$3*AA48+AB$3*AB48+AC$3*AC48)*(-1) -> 0 | AT48: =IF(AR48-R48-AS48>=0,AR48-R48-AS48,0) -> 0.11820682 | AU48: =VLOOKUP($D48,Research!$C:$L,(COLUMN(Research_ResearchCost_Stone)-COLUMN(Research_Name_and_Level)+1),FALSE)*(-1) -> -20000 | AV48: =VLOOKUP($D48,Research!$C:$L,(COLUMN(Research_ResearchCost_Wood)-COLUMN(Research_Name_and_Level)+1),FALSE)*(-1) -> -20000 | AW48: =VLOOKUP($D48,Research!$C:$L,(COLUMN(Research_ResearchCost_Ore)-COLUMN(Research_Name_and_Level)+1),FALSE)*(-1) -> -20000 | AX48: =VLOOKUP($D48,Research!$C:$L,(COLUMN(Research_ResearchCost_Food)-COLUMN(Research_Name_and_Level)+1),FALSE)*(-1) -> -20000 | AY48: =VLOOKUP($D48,Research!$C:$L,(COLUMN(Research_ResearchCost_Silver)-COLUMN(Research_Name_and_Level)+1),FALSE)*(-1) -> -20000
B49: Gift | C49: Hero Level Up | D49: Hero 5->6 | E49: 6 | I49: 2 | J49: 29 | AJ49: =AJ48+(S$3*S49+T$3*T49+U$3*U49+V$3*V49+W$3*W49+X$3*X49+Y$3*Y49+Z$3*Z49+AA$3*AA49+AB$3*AB49+AC$3*AC49) -> 0.083333333
B50: Level_Up | D50: Hero Level 6 | E50: 6 | F50: 0 | G50: — | H50: 167065 | I50: 8 | J50: 2331 | K50: 3 | M50: 0.0625 | N50: 200 | O50: =SUMIF($B$4:$B49,"<>"&$CS$13,O$4:O49) -> 0 | P50: =SUMIF($B$4:$B49,"<>"&$CS$13,N$4:N49) -> 200 | Q50: 0.0034722222 | R50: 0.0055555556 | S50: 0 | T50: 0 | U50: 0 | V50: 0 | W50: 8 | X50: 0 | Y50: 0 | Z50: 0 | AA50: 0 | AB50: 0 | AC50: 0 | AD50: 0 | AE50: 0 | AF50: =SUMIF($B$4:$B49,"<>"&$CS$13,AF$4:AF49) -> 0.10972222 | AG50: =SUMIF($B$4:$B49,"<>"&$CS$13,AG$4:AG49) -> 0 | AH50: =AF50+AG50 -> 0.10972222 | AI50: =SUMIF($B$4:$B49,"<>"&$CS$13,AI$4:AI49) -> 0.026388889 | AJ50: =S$3*S50+T$3*T50+U$3*U50+V$3*V50+W$3*W50+X$3*X50+Y$3*Y50+Z$3*Z50+AA$3*AA50+AB$3*AB50+AC$3*AC50 -> 0.083333333 | AK50: 0.01 | AL50: — | AM50: — | AN50: — | AO50: — | AP50: 0.01 | AQ50: — | AR50: — | AS50: — | AT50: — | AU50: 14880 | AV50: 19190 | AW50: 17320 | AX50: 29890 | AY50: 11110 | AZ50: 0 | BA50: 42 | BB50: 0 | BC50: 57 | BD50: 0 | BE50: -20 | BF50: 15000 | BG50: 17000 | BH50: 15000 | BI50: 17500 | BJ50: 15000 | BK50: 4 | BL50: 3 | BM50: 4 | BN50: 1 | BO50: 1 | BP50: 1 | BQ50: 1 | BR50: 0 | BS50: 0 | BT50: 0 | BU50: 0 | BV50: 0 | BW50: 0 | BX50: 1 | BY50: 1 | BZ50: 1 | CA50: 1 | CB50: 1 | CC50: 1 | CD50: 0 | CL50: 3000 | CN50: —
B51: Quest | C51: Construction at Will | D51: Stronghold 3 | E51: 6 | F51: 0 | G51: =VLOOKUP($D51,Construction!$B:$L,(COLUMN(Construction_QuestReward_HeroXP)-COLUMN(Construction_Name_and_Level)+1),FALSE) -> 2600 | H51: =G51*(1+F51) -> 2600 | J51: =VLOOKUP($D51,Construction!$B:$L,(COLUMN(Construction_QuestReward_Power)-COLUMN(Construction_Name_and_Level)+1),FALSE) -> 60 | M51: 0.020833333 | AJ51: =AJ50+(S$3*S51+T$3*T51+U$3*U51+V$3*V51+W$3*W51+X$3*X51+Y$3*Y51+Z$3*Z51+AA$3*AA51+AB$3*AB51+AC$3*AC51) -> 0.083333333 | AU51: =VLOOKUP($D51,Construction!$B:$Q,(COLUMN(Construction_QuestReward_Stone)-COLUMN(Construction_Name_and_Level)+1),FALSE) -> 5400 | AV51: =VLOOKUP($D51,Construction!$B:$Q,(COLUMN(Construction_QuestReward_Wood)-COLUMN(Construction_Name_and_Level)+1),FALSE) -> 5400 | AW51: =VLOOKUP($D51,Construction!$B:$Q,(COLUMN(Construction_QuestReward_Ore)-COLUMN(Construction_Name_and_Level)+1),FALSE) -> 2200 | AX51: =VLOOKUP($D51,Construction!$B:$Q,(COLUMN(Construction_QuestReward_Food)-COLUMN(Construction_Name_and_Level)+1),FALSE) -> 2800 | AY51: =VLOOKUP($D51,Construction!$B:$Q,(COLUMN(Construction_QuestReward_Silver)-COLUMN(Construction_Name_and_Level)+1),FALSE) -> 550
B52: Quest | C52: Construction at Will | D52: Stronghold 4 | E52: 6 | F52: 0 | G52: =VLOOKUP($D52,Construction!$B:$L,(COLUMN(Construction_QuestReward_HeroXP)-COLUMN(Construction_Name_and_Level)+1),FALSE) -> 2650 | H52: =G52*(1+F52) -> 2650 | J52: =VLOOKUP($D52,Construction!$B:$L,(COLUMN(Construction_QuestReward_Power)-COLUMN(Construction_Name_and_Level)+1),FALSE) -> 110 | AJ52: =AJ51+(S$3*S52+T$3*T52+U$3*U52+V$3*V52+W$3*W52+X$3*X52+Y$3*Y52+Z$3*Z52+AA$3*AA52+AB$3*AB52+AC$3*AC52) -> 0.083333333 | AU52: =VLOOKUP($D52,Construction!$B:$Q,(COLUMN(Construction_QuestReward_Stone)-COLUMN(Construction_Name_and_Level)+1),FALSE) -> 7400 | AV52: =VLOOKUP($D52,Construction!$B:$Q,(COLUMN(Construction_QuestReward_Wood)-COLUMN(Construction_Name_and_Level)+1),FALSE) -> 7400 | AW52: =VLOOKUP($D52,Construction!$B:$Q,(COLUMN(Construction_QuestReward_Ore)-COLUMN(Construction_Name_and_Level)+1),FALSE) -> 2900 | AX52: =VLOOKUP($D52,Construction!$B:$Q,(COLUMN(Construction_QuestReward_Food)-COLUMN(Construction_Name_and_Level)+1),FALSE) -> 3700 | AY52: =VLOOKUP($D52,Construction!$B:$Q,(COLUMN(Construction_QuestReward_Silver)-COLUMN(Construction_Name_and_Level)+1),FALSE) -> 700
B53: Quest | C53: Construction at Will | D53: Storehouse 2 | E53: 6 | F53: 0 | G53: =VLOOKUP($D53,Construction!$B:$L,(COLUMN(Construction_QuestReward_HeroXP)-COLUMN(Construction_Name_and_Level)+1),FALSE) -> 2575 | H53: =G53*(1+F53) -> 2575 | J53: =VLOOKUP($D53,Construction!$B:$L,(COLUMN(Construction_QuestReward_Power)-COLUMN(Construction_Name_and_Level)+1),FALSE) -> 5 | AJ53: =AJ52+(S$3*S53+T$3*T53+U$3*U53+V$3*V53+W$3*W53+X$3*X53+Y$3*Y53+Z$3*Z53+AA$3*AA53+AB$3*AB53+AC$3*AC53) -> 0.083333333 | AU53: =VLOOKUP($D53,Construction!$B:$Q,(COLUMN(Construction_QuestReward_Stone)-COLUMN(Construction_Name_and_Level)+1),FALSE) -> 1800 | AV53: =VLOOKUP($D53,Construction!$B:$Q,(COLUMN(Construction_QuestReward_Wood)-COLUMN(Construction_Name_and_Level)+1),FALSE) -> 1800 | AW53: =VLOOKUP($D53,Construction!$B:$Q,(COLUMN(Construction_QuestReward_Ore)-COLUMN(Construction_Name_and_Level)+1),FALSE) -> 1400 | AX53: =VLOOKUP($D53,Construction!$B:$Q,(COLUMN(Construction_QuestReward_Food)-COLUMN(Construction_Name_and_Level)+1),FALSE) -> 900 | AY53: =VLOOKUP($D53,Construction!$B:$Q,(COLUMN(Construction_QuestReward_Silver)-COLUMN(Construction_Name_and_Level)+1),FALSE) -> 200
B54: Quest | C54: Construction at Will | D54: Storehouse 3 | E54: 6 | F54: 0 | G54: =VLOOKUP($D54,Construction!$B:$L,(COLUMN(Construction_QuestReward_HeroXP)-COLUMN(Construction_Name_and_Level)+1),FALSE) -> 2600 | H54: =G54*(1+F54) -> 2600 | J54: =VLOOKUP($D54,Construction!$B:$L,(COLUMN(Construction_QuestReward_Power)-COLUMN(Construction_Name_and_Level)+1),FALSE) -> 10 | AJ54: =AJ53+(S$3*S54+T$3*T54+U$3*U54+V$3*V54+W$3*W54+X$3*X54+Y$3*Y54+Z$3*Z54+AA$3*AA54+AB$3*AB54+AC$3*AC54) -> 0.083333333 | AU54: =VLOOKUP($D54,Construction!$B:$Q,(COLUMN(Construction_QuestReward_Stone)-COLUMN(Construction_Name_and_Level)+1),FALSE) -> 1900 | AV54: =VLOOKUP($D54,Construction!$B:$Q,(COLUMN(Construction_QuestReward_Wood)-COLUMN(Construction_Name_and_Level)+1),FALSE) -> 1900 | AW54: =VLOOKUP($D54,Construction!$B:$Q,(COLUMN(Construction_QuestReward_Ore)-COLUMN(Construction_Name_and_Level)+1),FALSE) -> 1500 | AX54: =VLOOKUP($D54,Construction!$B:$Q,(COLUMN(Construction_QuestReward_Food)-COLUMN(Construction_Name_and_Level)+1),FALSE) -> 900 | AY54: =VLOOKUP($D54,Construction!$B:$Q,(COLUMN(Construction_QuestReward_Silver)-COLUMN(Construction_Name_and_Level)+1),FALSE) -> 200
B55: Quest | C55: Construction at Will | D55: Storehouse 4 | E55: 6 | F55: 0 | G55: =VLOOKUP($D55,Construction!$B:$L,(COLUMN(Construction_QuestReward_HeroXP)-COLUMN(Construction_Name_and_Level)+1),FALSE) -> 2650 | H55: =G55*(1+F55) -> 2650 | J55: =VLOOKUP($D55,Construction!$B:$L,(COLUMN(Construction_QuestReward_Power)-COLUMN(Construction_Name_and_Level)+1),FALSE) -> 20 | AJ55: =AJ54+(S$3*S55+T$3*T55+U$3*U55+V$3*V55+W$3*W55+X$3*X55+Y$3*Y55+Z$3*Z55+AA$3*AA55+AB$3*AB55+AC$3*AC55) -> 0.083333333 | AU55: =VLOOKUP($D55,Construction!$B:$Q,(COLUMN(Construction_QuestReward_Stone)-COLUMN(Construction_Name_and_Level)+1),FALSE) -> 6900 | AV55: =VLOOKUP($D55,Construction!$B:$Q,(COLUMN(Construction_QuestReward_Wood)-COLUMN(Construction_Name_and_Level)+1),FALSE) -> 2500 | AW55: =VLOOKUP($D55,Construction!$B:$Q,(COLUMN(Construction_QuestReward_Ore)-COLUMN(Construction_Name_and_Level)+1),FALSE) -> 1900 | AX55: =VLOOKUP($D55,Construction!$B:$Q,(COLUMN(Construction_QuestReward_Food)-COLUMN(Construction_Name_and_Level)+1),FALSE) -> 1200 | AY55: =VLOOKUP($D55,Construction!$B:$Q,(COLUMN(Construction_QuestReward_Silver)-COLUMN(Construction_Name_and_Level)+1),FALSE) -> 1900
B56: Quest | C56: Construction at Will | D56: Walls 2 | E56: 6 | F56: 0 | G56: =VLOOKUP($D56,Construction!$B:$L,(COLUMN(Construction_QuestReward_HeroXP)-COLUMN(Construction_Name_and_Level)+1),FALSE) -> 2575 | H56: =G56*(1+F56) -> 2575 | J56: =VLOOKUP($D56,Construction!$B:$L,(COLUMN(Construction_QuestReward_Power)-COLUMN(Construction_Name_and_Level)+1),FALSE) -> 17 | AJ56: =AJ55+(S$3*S56+T$3*T56+U$3*U56+V$3*V56+W$3*W56+X$3*X56+Y$3*Y56+Z$3*Z56+AA$3*AA56+AB$3*AB56+AC$3*AC56) -> 0.083333333 | AU56: =VLOOKUP($D56,Construction!$B:$Q,(COLUMN(Construction_QuestReward_Stone)-COLUMN(Construction_Name_and_Level)+1),FALSE) -> 4600 | AV56: =VLOOKUP($D56,Construction!$B:$Q,(COLUMN(Construction_QuestReward_Wood)-COLUMN(Construction_Name_and_Level)+1),FALSE) -> 3600 | AW56: =VLOOKUP($D56,Construction!$B:$Q,(COLUMN(Construction_QuestReward_Ore)-COLUMN(Construction_Name_and_Level)+1),FALSE) -> 1400 | AX56: =VLOOKUP($D56,Construction!$B:$Q,(COLUMN(Construction_QuestReward_Food)-COLUMN(Construction_Name_and_Level)+1),FALSE) -> 2300 | AY56: =VLOOKUP($D56,Construction!$B:$Q,(COLUMN(Construction_QuestReward_Silver)-COLUMN(Construction_Name_and_Level)+1),FALSE) -> 350
B57: Quest | C57: Construction at Will | D57: Walls 3 | E57: 6 | F57: 0 | G57: =VLOOKUP($D57,Construction!$B:$L,(COLUMN(Construction_QuestReward_HeroXP)-COLUMN(Construction_Name_and_Level)+1),FALSE) -> 2600 | H57: =G57*(1+F57) -> 2600 | J57: =VLOOKUP($D57,Construction!$B:$L,(COLUMN(Construction_QuestReward_Power)-COLUMN(Construction_Name_and_Level)+1),FALSE) -> 35 | AJ57: =AJ56+(S$3*S57+T$3*T57+U$3*U57+V$3*V57+W$3*W57+X$3*X57+Y$3*Y57+Z$3*Z57+AA$3*AA57+AB$3*AB57+AC$3*AC57) -> 0.083333333 | AU57: =VLOOKUP($D57,Construction!$B:$Q,(COLUMN(Construction_QuestReward_Stone)-COLUMN(Construction_Name_and_Level)+1),FALSE) -> 5400 | AV57: =VLOOKUP($D57,Construction!$B:$Q,(COLUMN(Construction_QuestReward_Wood)-COLUMN(Construction_Name_and_Level)+1),FALSE) -> 4400 | AW57: =VLOOKUP($D57,Construction!$B:$Q,(COLUMN(Construction_QuestReward_Ore)-COLUMN(Construction_Name_and_Level)+1),FALSE) -> 1600 | AX57: =VLOOKUP($D57,Construction!$B:$Q,(COLUMN(Construction_QuestReward_Food)-COLUMN(Construction_Name_and_Level)+1),FALSE) -> 2800 | AY57: =VLOOKUP($D57,Construction!$B:$Q,(COLUMN(Construction_QuestReward_Silver)-COLUMN(Construction_Name_and_Level)+1),FALSE) -> 450
B58: Quest | C58: Research at Will | D58: Construction 1 | E58: 6 | F58: 0 | G58: =VLOOKUP($D58,Research!$C:$S,(COLUMN(Research_QuestReward_HeroXP)-COLUMN(Research_Name_and_Level)+1),FALSE) -> 20000 | H58: =G58*(1+F58) -> 20000 | J58: =VLOOKUP($D58,Research!$C:$S,(COLUMN(Research_QuestReward_Power)-COLUMN(Research_Name_and_Level)+1),FALSE) -> 25 | AJ58: =AJ57+(S$3*S58+T$3*T58+U$3*U58+V$3*V58+W$3*W58+X$3*X58+Y$3*Y58+Z$3*Z58+AA$3*AA58+AB$3*AB58+AC$3*AC58) -> 0.083333333 | AU58: =VLOOKUP($D58,Research!$C:$S,(COLUMN(Research_QuestReward_Stone)-COLUMN(Research_Name_and_Level)+1),FALSE) -> 24000 | AV58: =VLOOKUP($D58,Research!$C:$S,(COLUMN(Research_QuestReward_Wood)-COLUMN(Research_Name_and_Level)+1),FALSE) -> 24000 | AW58: =VLOOKUP($D58,Research!$C:$S,(COLUMN(Research_QuestReward_Ore)-COLUMN(Research_Name_and_Level)+1),FALSE) -> 24000 | AX58: =VLOOKUP($D58,Research!$C:$S,(COLUMN(Research_QuestReward_Food)-COLUMN(Research_Name_and_Level)+1),FALSE) -> 24000 | AY58: =VLOOKUP($D58,Research!$C:$S,(COLUMN(Research_QuestReward_Silver)-COLUMN(Research_Name_and_Level)+1),FALSE) -> 12000
B59: Quest | C59: Special | D59: Join an Alliance2 | E59: 6 | F59: 0 | G59: 10000 | H59: =G59*(1+F59) -> 10000 | J59: 25 | AJ59: =AJ58+(S$3*S59+T$3*T59+U$3*U59+V$3*V59+W$3*W59+X$3*X59+Y$3*Y59+Z$3*Z59+AA$3*AA59+AB$3*AB59+AC$3*AC59) -> 0.083333333 | CL59: 10000
B60: Gift | C60: Hero Level Up | D60: Hero 6->7 | E60: 7 | I60: 2 | J60: 49 | AJ60: =AJ59+(S$3*S60+T$3*T60+U$3*U60+V$3*V60+W$3*W60+X$3*X60+Y$3*Y60+Z$3*Z60+AA$3*AA60+AB$3*AB60+AC$3*AC60) -> 0.083333333
B61: Level_Up | D61: Hero Level 7 | E61: 7 | F61: 0 | G61: — | H61: 215315 | I61: 10 | J61: 2687 | K61: 3 | L61: 460 | M61: 0.083333333 | N61: 200 | O61: =SUMIF($B$4:$B60,"<>"&$CS$13,O$4:O60) -> 0 | P61: =SUMIF($B$4:$B60,"<>"&$CS$13,N$4:N60) -> 200 | Q61: 0.0034722222 | R61: 0.0055555556 | S61: 0 | T61: 0 | U61: 0 | V61: 0 | W61: 8 | X61: 0 | Y61: 0 | Z61: 0 | AA61: 0 | AB61: 0 | AC61: 0 | AD61: 0 | AE61: 0 | AF61: =SUMIF($B$4:$B60,"<>"&$CS$13,AF$4:AF60) -> 0.10972222 | AG61: =SUMIF($B$4:$B60,"<>"&$CS$13,AG$4:AG60) -> 0 | AH61: =AF61+AG61 -> 0.10972222 | AI61: =SUMIF($B$4:$B60,"<>"&$CS$13,AI$4:AI60) -> 0.026388889 | AJ61: =S$3*S61+T$3*T61+U$3*U61+V$3*V61+W$3*W61+X$3*X61+Y$3*Y61+Z$3*Z61+AA$3*AA61+AB$3*AB61+AC$3*AC61 -> 0.083333333 | AK61: 0.01 | AL61: — | AM61: — | AN61: — | AO61: — | AP61: 0.01 | AQ61: — | AR61: — | AS61: — | AT61: — | AU61: 72280 | AV61: 70190 | AW61: 54220 | AX61: 68490 | AY61: 27460 | AZ61: 0 | BA61: 40 | BB61: 0 | BC61: 59 | BD61: 0 | BE61: -20 | BF61: 15000 | BG61: 17000 | BH61: 15000 | BI61: 17500 | BJ61: 15000 | BK61: 4 | BL61: 3 | BM61: 4 | BN61: 1 | BO61: 1 | BP61: 1 | BQ61: 1 | BR61: 0 | BS61: 0 | BT61: 0 | BU61: 0 | BV61: 0 | BW61: 0 | BX61: 1 | BY61: 1 | BZ61: 1 | CA61: 1 | CB61: 1 | CC61: 1 | CD61: 0 | CL61: 15300 | CN61: —
B62: Gift | C62: Online Reward | D62: 0.0041666667 | E62: 7 | AJ62: =AJ61+(S$3*S62+T$3*T62+U$3*U62+V$3*V62+W$3*W62+X$3*X62+Y$3*Y62+Z$3*Z62+AA$3*AA62+AB$3*AB62+AC$3*AC62) -> 0.083333333 | AU62: 10000 | AV62: 10000 | AW62: 10000 | AX62: 30000 | AY62: 3000
B63: Casino | E63: 7 | AJ63: =AJ62+(S$3*S63+T$3*T63+U$3*U63+V$3*V63+W$3*W63+X$3*X63+Y$3*Y63+Z$3*Z63+AA$3*AA63+AB$3*AB63+AC$3*AC63) -> 0.083333333 | AW63: 3750
B64: Gift | C64: Stronghold upgrade Chest | D64: Stronghold 3 Chest | E64: 7 | M64: 0.020833333 | W64: 1 | AF64: =$S$3*$S64+$T$3*$T64+$U$3*$U64+$V$3*$V64+$W$3*$W64+$X$3*$X64+$Y$3*$Y64+$Z$3*$Z64+$AA$3*$AA64+$AB$3*$AB64+$AC$3*$AC64 -> 0.010416667 | AJ64: =AJ63+(S$3*S64+T$3*T64+U$3*U64+V$3*V64+W$3*W64+X$3*X64+Y$3*Y64+Z$3*Z64+AA$3*AA64+AB$3*AB64+AC$3*AC64) -> 0.09375 | AY64: 500 | CN64: 7000
B65: Gift | C65: Stronghold upgrade Chest | D65: Stronghold 4 Chest | E65: 7 | V65: 1 | W65: 1 | AF65: =$S$3*$S65+$T$3*$T65+$U$3*$U65+$V$3*$V65+$W$3*$W65+$X$3*$X65+$Y$3*$Y65+$Z$3*$Z65+$AA$3*$AA65+$AB$3*$AB65+$AC$3*$AC65 -> 0.017361111 | AJ65: =AJ64+(S$3*S65+T$3*T65+U$3*U65+V$3*V65+W$3*W65+X$3*X65+Y$3*Y65+Z$3*Z65+AA$3*AA65+AB$3*AB65+AC$3*AC65) -> 0.11111111 | AU65: 3000 | AX65: 5000
B66: Casino | E66: 7 | AJ66: =AJ65+(S$3*S66+T$3*T66+U$3*U66+V$3*V66+W$3*W66+X$3*X66+Y$3*Y66+Z$3*Z66+AA$3*AA66+AB$3*AB66+AC$3*AC66) -> 0.11111111 | AV66: 3750
B67: Gift | C67: Online Reward | D67: 0.0027777778 | E67: 7 | V67: 1 | AF67: =$S$3*$S67+$T$3*$T67+$U$3*$U67+$V$3*$V67+$W$3*$W67+$X$3*$X67+$Y$3*$Y67+$Z$3*$Z67+$AA$3*$AA67+$AB$3*$AB67+$AC$3*$AC67 -> 0.0069444444 | AJ67: =AJ66+(S$3*S67+T$3*T67+U$3*U67+V$3*V67+W$3*W67+X$3*X67+Y$3*Y67+Z$3*Z67+AA$3*AA67+AB$3*AB67+AC$3*AC67) -> 0.11805556
B68: Quest | C68: Special | D68: Receive Help from Alliance Members to Speed Up | E68: 7 | F68: 0 | G68: 10000 | H68: =G68*(1+F68) -> 10000 | J68: 250 | V68: 1 | AF68: =$S$3*$S68+$T$3*$T68+$U$3*$U68+$V$3*$V68+$W$3*$W68+$X$3*$X68+$Y$3*$Y68+$Z$3*$Z68+$AA$3*$AA68+$AB$3*$AB68+$AC$3*$AC68 -> 0.0069444444 | AJ68: =AJ67+(S$3*S68+T$3*T68+U$3*U68+V$3*V68+W$3*W68+X$3*X68+Y$3*Y68+Z$3*Z68+AA$3*AA68+AB$3*AB68+AC$3*AC68) -> 0.125 | AU68: 2000 | AV68: 2000
B69: Quest | C69: Special | D69: Help an Alliance Member with their Build or Research | E69: 7 | F69: 0 | G69: 10000 | H69: =G69*(1+F69) -> 10000 | J69: 250 | AJ69: =AJ68+(S$3*S69+T$3*T69+U$3*U69+V$3*V69+W$3*W69+X$3*X69+Y$3*Y69+Z$3*Z69+AA$3*AA69+AB$3*AB69+AC$3*AC69) -> 0.125 | AU69: 1200 | AV69: 1200 | AW69: 1200 | AX69: 1200 | AY69: 100
B70: Construction | C70: by Quest | D70: Quarry 1 | E70: 7 | F70: 0 | G70: =VLOOKUP($D70,Construction!$B:$E,(COLUMN(Construction_BuildingReward_HeroXP)-COLUMN(Construction_Name_and_Level)+1),FALSE) -> 10 | H70: =G70*(1+F70) -> 10 | J70: =VLOOKUP($D70,Construction!$B:$F,(COLUMN(Construction_BuildingReward_Power)-COLUMN(Construction_Name_and_Level)+1),FALSE) -> 5 | Q70: 0.0034722222 | R70: 0.0055555556 | AJ70: =AJ69+(S$3*S70+T$3*T70+U$3*U70+V$3*V70+W$3*W70+X$3*X70+Y$3*Y70+Z$3*Z70+AA$3*AA70+AB$3*AB70+AC$3*AC70) -> 0.125 | AK70: 0.01 | AL70: =VLOOKUP($D70,Construction!$B:$C,(COLUMN(Construction_Time)-COLUMN(Construction_Name_and_Level)+1),FALSE) -> 0.00069444444 | AM70: =AL70/(1+AK70) -> 0.00068756876 | AN70: =(S$3*S70+T$3*T70+V$3*V70+W$3*W70+X$3*X70+Y$3*Y70+Z$3*Z70+AA$3*AA70+AB$3*AB70+AC$3*AC70)*(-1) -> 0 | AO70: =IF((AM70-Q70-R70-AN70)>=0,AM70-Q70-R70-AN70,0) -> 0 | AU70: =VLOOKUP($D70,Construction!$B:$J,(COLUMN(Construction_BuildingCost_Stone)-COLUMN(Construction_Name_and_Level)+1),FALSE)*(-1) -> 0 | AV70: =VLOOKUP($D70,Construction!$B:$J,(COLUMN(Construction_BuildingCost_Wood)-COLUMN(Construction_Name_and_Level)+1),FALSE)*(-1) -> -100 | AW70: =VLOOKUP($D70,Construction!$B:$J,(COLUMN(Construction_BuildingCost_Ore)-COLUMN(Construction_Name_and_Level)+1),FALSE)*(-1) -> -100 | AX70: =VLOOKUP($D70,Construction!$B:$J,(COLUMN(Construction_BuildingCost_Food)-COLUMN(Construction_Name_and_Level)+1),FALSE)*(-1) -> -100
B71: Quest | C71: Construction Recommended | D71: Quarry 1 | E71: 7 | F71: 0 | G71: =VLOOKUP($D71,Construction!$B:$L,(COLUMN(Construction_QuestReward_HeroXP)-COLUMN(Construction_Name_and_Level)+1),FALSE) -> 2525 | H71: =G71*(1+F71) -> 2525 | J71: =VLOOKUP($D71,Construction!$B:$L,(COLUMN(Construction_QuestReward_Power)-COLUMN(Construction_Name_and_Level)+1),FALSE) -> 2 | AJ71: =AJ70+(S$3*S71+T$3*T71+U$3*U71+V$3*V71+W$3*W71+X$3*X71+Y$3*Y71+Z$3*Z71+AA$3*AA71+AB$3*AB71+AC$3*AC71) -> 0.125 | AU71: =VLOOKUP($D71,Construction!$B:$Q,(COLUMN(Construction_QuestReward_Stone)-COLUMN(Construction_Name_and_Level)+1),FALSE) -> 3000 | AV71: =VLOOKUP($D71,Construction!$B:$Q,(COLUMN(Construction_QuestReward_Wood)-COLUMN(Construction_Name_and_Level)+1),FALSE) -> 0 | AW71: =VLOOKUP($D71,Construction!$B:$Q,(COLUMN(Construction_QuestReward_Ore)-COLUMN(Construction_Name_and_Level)+1),FALSE) -> 0 | AX71: =VLOOKUP($D71,Construction!$B:$Q,(COLUMN(Construction_QuestReward_Food)-COLUMN(Construction_Name_and_Level)+1),FALSE) -> 0 | AY71: =VLOOKUP($D71,Construction!$B:$Q,(COLUMN(Construction_QuestReward_Silver)-COLUMN(Construction_Name_and_Level)+1),FALSE) -> 0
B72: Construction | C72: by Quest | D72: Mine 1 | E72: 7 | F72: 0 | G72: =VLOOKUP($D72,Construction!$B:$E,(COLUMN(Construction_BuildingReward_HeroXP)-COLUMN(Construction_Name_and_Level)+1),FALSE) -> 10 | H72: =G72*(1+F72) -> 10 | J72: =VLOOKUP($D72,Construction!$B:$F,(COLUMN(Construction_BuildingReward_Power)-COLUMN(Construction_Name_and_Level)+1),FALSE) -> 5 | Q72: 0.0034722222 | R72: 0.0055555556 | AJ72: =AJ71+(S$3*S72+T$3*T72+U$3*U72+V$3*V72+W$3*W72+X$3*X72+Y$3*Y72+Z$3*Z72+AA$3*AA72+AB$3*AB72+AC$3*AC72) -> 0.125 | AK72: 0.01 | AL72: =VLOOKUP($D72,Construction!$B:$C,(COLUMN(Construction_Time)-COLUMN(Construction_Name_and_Level)+1),FALSE) -> 0.00069444444 | AM72: =AL72/(1+AK72) -> 0.00068756876 | AN72: =(S$3*S72+T$3*T72+V$3*V72+W$3*W72+X$3*X72+Y$3*Y72+Z$3*Z72+AA$3*AA72+AB$3*AB72+AC$3*AC72)*(-1) -> 0 | AO72: =IF((AM72-Q72-R72-AN72)>=0,AM72-Q72-R72-AN72,0) -> 0 | AU72: =VLOOKUP($D72,Construction!$B:$J,(COLUMN(Construction_BuildingCost_Stone)-COLUMN(Construction_Name_and_Level)+1),FALSE)*(-1) -> -100 | AV72: =VLOOKUP($D72,Construction!$B:$J,(COLUMN(Construction_BuildingCost_Wood)-COLUMN(Construction_Name_and_Level)+1),FALSE)*(-1) -> -100 | AW72: =VLOOKUP($D72,Construction!$B:$J,(COLUMN(Construction_BuildingCost_Ore)-COLUMN(Construction_Name_and_Level)+1),FALSE)*(-1) -> 0 | AX72: =VLOOKUP($D72,Construction!$B:$J,(COLUMN(Construction_BuildingCost_Food)-COLUMN(Construction_Name_and_Level)+1),FALSE)*(-1) -> -100
B73: Quest | C73: Construction Recommended | D73: Mine 1 | E73: 7 | F73: 0 | G73: =VLOOKUP($D73,Construction!$B:$L,(COLUMN(Construction_QuestReward_HeroXP)-COLUMN(Construction_Name_and_Level)+1),FALSE) -> 2525 | H73: =G73*(1+F73) -> 2525 | J73: =VLOOKUP($D73,Construction!$B:$L,(COLUMN(Construction_QuestReward_Power)-COLUMN(Construction_Name_and_Level)+1),FALSE) -> 2 | AJ73: =AJ72+(S$3*S73+T$3*T73+U$3*U73+V$3*V73+W$3*W73+X$3*X73+Y$3*Y73+Z$3*Z73+AA$3*AA73+AB$3*AB73+AC$3*AC73) -> 0.125 | AU73: =VLOOKUP($D73,Construction!$B:$Q,(COLUMN(Construction_QuestReward_Stone)-COLUMN(Construction_Name_and_Level)+1),FALSE) -> 0 | AV73: =VLOOKUP($D73,Construction!$B:$Q,(COLUMN(Construction_QuestReward_Wood)-COLUMN(Construction_Name_and_Level)+1),FALSE) -> 0 | AW73: =VLOOKUP($D73,Construction!$B:$Q,(COLUMN(Construction_QuestReward_Ore)-COLUMN(Construction_Name_and_Level)+1),FALSE) -> 3000 | AX73: =VLOOKUP($D73,Construction!$B:$Q,(COLUMN(Construction_QuestReward_Food)-COLUMN(Construction_Name_and_Level)+1),FALSE) -> 0 | AY73: =VLOOKUP($D73,Construction!$B:$Q,(COLUMN(Construction_QuestReward_Silver)-COLUMN(Construction_Name_and_Level)+1),FALSE) -> 0
B74: Construction | C74: by Quest | D74: Villa 1 | E74: 7 | F74: 0 | G74: =VLOOKUP($D74,Construction!$B:$E,(COLUMN(Construction_BuildingReward_HeroXP)-COLUMN(Construction_Name_and_Level)+1),FALSE) -> 10 | H74: =G74*(1+F74) -> 10 | J74: =VLOOKUP($D74,Construction!$B:$F,(COLUMN(Construction_BuildingReward_Power)-COLUMN(Construction_Name_and_Level)+1),FALSE) -> 10 | Q74: 0.0034722222 | R74: 0.0055555556 | AJ74: =AJ73+(S$3*S74+T$3*T74+U$3*U74+V$3*V74+W$3*W74+X$3*X74+Y$3*Y74+Z$3*Z74+AA$3*AA74+AB$3*AB74+AC$3*AC74) -> 0.125 | AK74: 0.01 | AL74: =VLOOKUP($D74,Construction!$B:$C,(COLUMN(Construction_Time)-COLUMN(Construction_Name_and_Level)+1),FALSE) -> 0.00069444444 | AM74: =AL74/(1+AK74) -> 0.00068756876 | AN74: =(S$3*S74+T$3*T74+V$3*V74+W$3*W74+X$3*X74+Y$3*Y74+Z$3*Z74+AA$3*AA74+AB$3*AB74+AC$3*AC74)*(-1) -> 0 | AO74: =IF((AM74-Q74-R74-AN74)>=0,AM74-Q74-R74-AN74,0) -> 0 | AU74: =VLOOKUP($D74,Construction!$B:$J,(COLUMN(Construction_BuildingCost_Stone)-COLUMN(Construction_Name_and_Level)+1),FALSE)*(-1) -> -200 | AV74: =VLOOKUP($D74,Construction!$B:$J,(COLUMN(Construction_BuildingCost_Wood)-COLUMN(Construction_Name_and_Level)+1),FALSE)*(-1) -> -200 | AW74: =VLOOKUP($D74,Construction!$B:$J,(COLUMN(Construction_BuildingCost_Ore)-COLUMN(Construction_Name_and_Level)+1),FALSE)*(-1) -> -50 | AX74: =VLOOKUP($D74,Construction!$B:$J,(COLUMN(Construction_BuildingCost_Food)-COLUMN(Construction_Name_and_Level)+1),FALSE)*(-1) -> -500
B75: Quest | C75: Construction Recommended | D75: Villa 1 | E75: 7 | F75: 0 | G75: =VLOOKUP($D75,Construction!$B:$L,(COLUMN(Construction_QuestReward_HeroXP)-COLUMN(Construction_Name_and_Level)+1),FALSE) -> 2525 | H75: =G75*(1+F75) -> 2525 | J75: =VLOOKUP($D75,Construction!$B:$L,(COLUMN(Construction_QuestReward_Power)-COLUMN(Construction_Name_and_Level)+1),FALSE) -> 2 | AJ75: =AJ74+(S$3*S75+T$3*T75+U$3*U75+V$3*V75+W$3*W75+X$3*X75+Y$3*Y75+Z$3*Z75+AA$3*AA75+AB$3*AB75+AC$3*AC75) -> 0.125 | AU75: =VLOOKUP($D75,Construction!$B:$Q,(COLUMN(Construction_QuestReward_Stone)-COLUMN(Construction_Name_and_Level)+1),FALSE) -> 0 | AV75: =VLOOKUP($D75,Construction!$B:$Q,(COLUMN(Construction_QuestReward_Wood)-COLUMN(Construction_Name_and_Level)+1),FALSE) -> 0 | AW75: =VLOOKUP($D75,Construction!$B:$Q,(COLUMN(Construction_QuestReward_Ore)-COLUMN(Construction_Name_and_Level)+1),FALSE) -> 0 | AX75: =VLOOKUP($D75,Construction!$B:$Q,(COLUMN(Construction_QuestReward_Food)-COLUMN(Construction_Name_and_Level)+1),FALSE) -> 0 | AY75: =VLOOKUP($D75,Construction!$B:$Q,(COLUMN(Construction_QuestReward_Silver)-COLUMN(Construction_Name_and_Level)+1),FALSE) -> 550
B76: Quest | C76: Special | D76: Complete 25 Quests | E76: 7 | J76: 25 | L76: 100 | AJ76: =AJ75+(S$3*S76+T$3*T76+U$3*U76+V$3*V76+W$3*W76+X$3*X76+Y$3*Y76+Z$3*Z76+AA$3*AA76+AB$3*AB76+AC$3*AC76) -> 0.125 | AU76: 2500 | AV76: 2500 | AW76: 2500 | AX76: 5000 | AY76: 200
B77: Construction | C77: by Quest | D77: Forge 1 | E77: 7 | F77: 0 | G77: =VLOOKUP($D77,Construction!$B:$E,(COLUMN(Construction_BuildingReward_HeroXP)-COLUMN(Construction_Name_and_Level)+1),FALSE) -> 10 | H77: =G77*(1+F77) -> 10 | J77: =VLOOKUP($D77,Construction!$B:$F,(COLUMN(Construction_BuildingReward_Power)-COLUMN(Construction_Name_and_Level)+1),FALSE) -> 10 | Q77: 0.0034722222 | R77: 0.0055555556 | AJ77: =AJ76+(S$3*S77+T$3*T77+U$3*U77+V$3*V77+W$3*W77+X$3*X77+Y$3*Y77+Z$3*Z77+AA$3*AA77+AB$3*AB77+AC$3*AC77) -> 0.125 | AK77: 0.01 | AL77: =VLOOKUP($D77,Construction!$B:$C,(COLUMN(Construction_Time)-COLUMN(Construction_Name_and_Level)+1),FALSE) -> 0.00086805556 | AM77: =AL77/(1+AK77) -> 0.00085946095 | AN77: =(S$3*S77+T$3*T77+V$3*V77+W$3*W77+X$3*X77+Y$3*Y77+Z$3*Z77+AA$3*AA77+AB$3*AB77+AC$3*AC77)*(-1) -> 0 | AO77: =IF((AM77-Q77-R77-AN77)>=0,AM77-Q77-R77-AN77,0) -> 0 | AU77: =VLOOKUP($D77,Construction!$B:$J,(COLUMN(Construction_BuildingCost_Stone)-COLUMN(Construction_Name_and_Level)+1),FALSE)*(-1) -> -300 | AV77: =VLOOKUP($D77,Construction!$B:$J,(COLUMN(Construction_BuildingCost_Wood)-COLUMN(Construction_Name_and_Level)+1),FALSE)*(-1) -> -400 | AW77: =VLOOKUP($D77,Construction!$B:$J,(COLUMN(Construction_BuildingCost_Ore)-COLUMN(Construction_Name_and_Level)+1),FALSE)*(-1) -> -800 | AX77: =VLOOKUP($D77,Construction!$B:$J,(COLUMN(Construction_BuildingCost_Food)-COLUMN(Construction_Name_and_Level)+1),FALSE)*(-1) -> -300
B78: Quest | C78: Construction Recommended | D78: Forge 1 | E78: 7 | F78: 0 | G78: =VLOOKUP($D78,Construction!$B:$L,(COLUMN(Construction_QuestReward_HeroXP)-COLUMN(Construction_Name_and_Level)+1),FALSE) -> 2525 | H78: =G78*(1+F78) -> 2525 | J78: =VLOOKUP($D78,Construction!$B:$L,(COLUMN(Construction_QuestReward_Power)-COLUMN(Construction_Name_and_Level)+1),FALSE) -> 2 | AJ78: =AJ77+(S$3*S78+T$3*T78+U$3*U78+V$3*V78+W$3*W78+X$3*X78+Y$3*Y78+Z$3*Z78+AA$3*AA78+AB$3*AB78+AC$3*AC78) -> 0.125 | AU78: =VLOOKUP($D78,Construction!$B:$Q,(COLUMN(Construction_QuestReward_Stone)-COLUMN(Construction_Name_and_Level)+1),FALSE) -> 500 | AV78: =VLOOKUP($D78,Construction!$B:$Q,(COLUMN(Construction_QuestReward_Wood)-COLUMN(Construction_Name_and_Level)+1),FALSE) -> 800 | AW78: =VLOOKUP($D78,Construction!$B:$Q,(COLUMN(Construction_QuestReward_Ore)-COLUMN(Construction_Name_and_Level)+1),FALSE) -> 1500 | AX78: =VLOOKUP($D78,Construction!$B:$Q,(COLUMN(Construction_QuestReward_Food)-COLUMN(Construction_Name_and_Level)+1),FALSE) -> 500 | AY78: =VLOOKUP($D78,Construction!$B:$Q,(COLUMN(Construction_QuestReward_Silver)-COLUMN(Construction_Name_and_Level)+1),FALSE) -> 600
B79: Gift | C79: Online Reward | D79: 0.0020833333 | E79: 7 | AJ79: =AJ78+(S$3*S79+T$3*T79+U$3*U79+V$3*V79+W$3*W79+X$3*X79+Y$3*Y79+Z$3*Z79+AA$3*AA79+AB$3*AB79+AC$3*AC79) -> 0.125 | CN79: 7000
B80: Research | C80: at Will | D80: Food Production 1 | E80: 7 | F80: 0 | G80: =VLOOKUP($D80,Research!$C:$F,(COLUMN(Research_ResearchReward_HeroXP)-COLUMN(Research_Name_and_Level)+1),FALSE) -> 12000 | H80: =G80*(1+F80) -> 12000 | J80: =VLOOKUP($D80,Research!$C:$G,(COLUMN(Research_ResearchReward_Power)-COLUMN(Research_Name_and_Level)+1),FALSE) -> 125 | R80: 0.0055555556 | AJ80: =AJ79+(S$3*S80+T$3*T80+U$3*U80+V$3*V80+W$3*W80+X$3*X80+Y$3*Y80+Z$3*Z80+AA$3*AA80+AB$3*AB80+AC$3*AC80) -> 0.125 | AP80: 0.01 | AQ80: =VLOOKUP($D80,Research!$C:$D,(COLUMN(Research_Time)-COLUMN(Research_Name_and_Level)+1),FALSE) -> 0.010416667 | AR80: =AQ80/(1+AP80) -> 0.010313531 | AS80: =(S$3*S80+T$3*T80+V$3*V80+W$3*W80+X$3*X80+Y$3*Y80+Z$3*Z80+AA$3*AA80+AB$3*AB80+AC$3*AC80)*(-1) -> 0 | AT80: =IF(AR80-R80-AS80>=0,AR80-R80-AS80,0) -> 0.0047579758 | AU80: =VLOOKUP($D80,Research!$C:$L,(COLUMN(Research_ResearchCost_Stone)-COLUMN(Research_Name_and_Level)+1),FALSE)*(-1) -> -300 | AV80: =VLOOKUP($D80,Research!$C:$L,(COLUMN(Research_ResearchCost_Wood)-COLUMN(Research_Name_and_Level)+1),FALSE)*(-1) -> -500 | AW80: =VLOOKUP($D80,Research!$C:$L,(COLUMN(Research_ResearchCost_Ore)-COLUMN(Research_Name_and_Level)+1),FALSE)*(-1) -> -400 | AX80: =VLOOKUP($D80,Research!$C:$L,(COLUMN(Research_ResearchCost_Food)-COLUMN(Research_Name_and_Level)+1),FALSE)*(-1) -> -25 | AY80: =VLOOKUP($D80,Research!$C:$L,(COLUMN(Research_ResearchCost_Silver)-COLUMN(Research_Name_and_Level)+1),FALSE)*(-1) -> -2500
B81: Quest | C81: Research at Will | D81: Food Production 1 | E81: 7 | F81: 0 | G81: =VLOOKUP($D81,Research!$C:$S,(COLUMN(Research_QuestReward_HeroXP)-COLUMN(Research_Name_and_Level)+1),FALSE) -> 2000 | H81: =G81*(1+F81) -> 2000 | J81: =VLOOKUP($D81,Research!$C:$S,(COLUMN(Research_QuestReward_Power)-COLUMN(Research_Name_and_Level)+1),FALSE) -> 25 | AJ81: =AJ80+(S$3*S81+T$3*T81+U$3*U81+V$3*V81+W$3*W81+X$3*X81+Y$3*Y81+Z$3*Z81+AA$3*AA81+AB$3*AB81+AC$3*AC81) -> 0.125 | AU81: =VLOOKUP($D81,Research!$C:$S,(COLUMN(Research_QuestReward_Stone)-COLUMN(Research_Name_and_Level)+1),FALSE) -> 0 | AV81: =VLOOKUP($D81,Research!$C:$S,(COLUMN(Research_QuestReward_Wood)-COLUMN(Research_Name_and_Level)+1),FALSE) -> 0 | AW81: =VLOOKUP($D81,Research!$C:$S,(COLUMN(Research_QuestReward_Ore)-COLUMN(Research_Name_and_Level)+1),FALSE) -> 0 | AX81: =VLOOKUP($D81,Research!$C:$S,(COLUMN(Research_QuestReward_Food)-COLUMN(Research_Name_and_Level)+1),FALSE) -> 0 | AY81: =VLOOKUP($D81,Research!$C:$S,(COLUMN(Research_QuestReward_Silver)-COLUMN(Research_Name_and_Level)+1),FALSE) -> 1500
B82: Construction | C82: by Quest | D82: Farm 2 | E82: 7 | F82: 0 | G82: =VLOOKUP($D82,Construction!$B:$E,(COLUMN(Construction_BuildingReward_HeroXP)-COLUMN(Construction_Name_and_Level)+1),FALSE) -> 25 | H82: =G82*(1+F82) -> 25 | J82: =VLOOKUP($D82,Construction!$B:$F,(COLUMN(Construction_BuildingReward_Power)-COLUMN(Construction_Name_and_Level)+1),FALSE) -> 10 | Q82: 0.0034722222 | R82: 0.0055555556 | AJ82: =AJ81+(S$3*S82+T$3*T82+U$3*U82+V$3*V82+W$3*W82+X$3*X82+Y$3*Y82+Z$3*Z82+AA$3*AA82+AB$3*AB82+AC$3*AC82) -> 0.125 | AK82: 0.01 | AL82: =VLOOKUP($D82,Construction!$B:$C,(COLUMN(Construction_Time)-COLUMN(Construction_Name_and_Level)+1),FALSE) -> 0.0011574074 | AM82: =AL82/(1+AK82) -> 0.0011459479 | AN82: =(S$3*S82+T$3*T82+V$3*V82+W$3*W82+X$3*X82+Y$3*Y82+Z$3*Z82+AA$3*AA82+AB$3*AB82+AC$3*AC82)*(-1) -> 0 | AO82: =IF((AM82-Q82-R82-AN82)>=0,AM82-Q82-R82-AN82,0) -> 0 | AU82: =VLOOKUP($D82,Construction!$B:$J,(COLUMN(Construction_BuildingCost_Stone)-COLUMN(Construction_Name_and_Level)+1),FALSE)*(-1) -> -170 | AV82: =VLOOKUP($D82,Construction!$B:$J,(COLUMN(Construction_BuildingCost_Wood)-COLUMN(Construction_Name_and_Level)+1),FALSE)*(-1) -> -170 | AW82: =VLOOKUP($D82,Construction!$B:$J,(COLUMN(Construction_BuildingCost_Ore)-COLUMN(Construction_Name_and_Level)+1),FALSE)*(-1) -> -170 | AX82: =VLOOKUP($D82,Construction!$B:$J,(COLUMN(Construction_BuildingCost_Food)-COLUMN(Construction_Name_and_Level)+1),FALSE)*(-1) -> 0
B83: Quest | C83: Construction Recommended | D83: Farm 2 | E83: 7 | F83: 0 | G83: =VLOOKUP($D83,Construction!$B:$L,(COLUMN(Construction_QuestReward_HeroXP)-COLUMN(Construction_Name_and_Level)+1),FALSE) -> 2575 | H83: =G83*(1+F83) -> 2575 | J83: =VLOOKUP($D83,Construction!$B:$L,(COLUMN(Construction_QuestReward_Power)-COLUMN(Construction_Name_and_Level)+1),FALSE) -> 2 | AJ83: =AJ82+(S$3*S83+T$3*T83+U$3*U83+V$3*V83+W$3*W83+X$3*X83+Y$3*Y83+Z$3*Z83+AA$3*AA83+AB$3*AB83+AC$3*AC83) -> 0.125 | AU83: =VLOOKUP($D83,Construction!$B:$Q,(COLUMN(Construction_QuestReward_Stone)-COLUMN(Construction_Name_and_Level)+1),FALSE) -> 0 | AV83: =VLOOKUP($D83,Construction!$B:$Q,(COLUMN(Construction_QuestReward_Wood)-COLUMN(Construction_Name_and_Level)+1),FALSE) -> 0 | AW83: =VLOOKUP($D83,Construction!$B:$Q,(COLUMN(Construction_QuestReward_Ore)-COLUMN(Construction_Name_and_Level)+1),FALSE) -> 0 | AX83: =VLOOKUP($D83,Construction!$B:$Q,(COLUMN(Construction_QuestReward_Food)-COLUMN(Construction_Name_and_Level)+1),FALSE) -> 5000 | AY83: =VLOOKUP($D83,Construction!$B:$Q,(COLUMN(Construction_QuestReward_Silver)-COLUMN(Construction_Name_and_Level)+1),FALSE) -> 0
B84: Quest | C84: Increase Production | D84: Food Supply 100 | E84: 7 | F84: 0 | G84: 0 | H84: =G84*(1+F84) -> 0 | J84: 25 | AJ84: =AJ83+(S$3*S84+T$3*T84+U$3*U84+V$3*V84+W$3*W84+X$3*X84+Y$3*Y84+Z$3*Z84+AA$3*AA84+AB$3*AB84+AC$3*AC84) -> 0.125 | AX84: 2500
B85: Casino | E85: 7 | AJ85: =AJ84+(S$3*S85+T$3*T85+U$3*U85+V$3*V85+W$3*W85+X$3*X85+Y$3*Y85+Z$3*Z85+AA$3*AA85+AB$3*AB85+AC$3*AC85) -> 0.125 | AX85: 12500
B86: Research | C86: at Will | D86: Stone Production 1 | E86: 7 | F86: 0 | G86: =VLOOKUP($D86,Research!$C:$F,(COLUMN(Research_ResearchReward_HeroXP)-COLUMN(Research_Name_and_Level)+1),FALSE) -> 12000 | H86: =G86*(1+F86) -> 12000 | J86: =VLOOKUP($D86,Research!$C:$G,(COLUMN(Research_ResearchReward_Power)-COLUMN(Research_Name_and_Level)+1),FALSE) -> 150 | R86: 0.0055555556 | AJ86: =AJ85+(S$3*S86+T$3*T86+U$3*U86+V$3*V86+W$3*W86+X$3*X86+Y$3*Y86+Z$3*Z86+AA$3*AA86+AB$3*AB86+AC$3*AC86) -> 0.125 | AP86: 0.01 | AQ86: =VLOOKUP($D86,Research!$C:$D,(COLUMN(Research_Time)-COLUMN(Research_Name_and_Level)+1),FALSE) -> 0.017361111 | AR86: =AQ86/(1+AP86) -> 0.017189219 | AS86: =(S$3*S86+T$3*T86+V$3*V86+W$3*W86+X$3*X86+Y$3*Y86+Z$3*Z86+AA$3*AA86+AB$3*AB86+AC$3*AC86)*(-1) -> 0 | AT86: =IF(AR86-R86-AS86>=0,AR86-R86-AS86,0) -> 0.011633663 | AU86: =VLOOKUP($D86,Research!$C:$L,(COLUMN(Research_ResearchCost_Stone)-COLUMN(Research_Name_and_Level)+1),FALSE)*(-1) -> -25 | AV86: =VLOOKUP($D86,Research!$C:$L,(COLUMN(Research_ResearchCost_Wood)-COLUMN(Research_Name_and_Level)+1),FALSE)*(-1) -> -400 | AW86: =VLOOKUP($D86,Research!$C:$L,(COLUMN(Research_ResearchCost_Ore)-COLUMN(Research_Name_and_Level)+1),FALSE)*(-1) -> -500 | AX86: =VLOOKUP($D86,Research!$C:$L,(COLUMN(Research_ResearchCost_Food)-COLUMN(Research_Name_and_Level)+1),FALSE)*(-1) -> -300 | AY86: =VLOOKUP($D86,Research!$C:$L,(COLUMN(Research_ResearchCost_Silver)-COLUMN(Research_Name_and_Level)+1),FALSE)*(-1) -> -3000
B87: Quest | C87: Research at Will | D87: Stone Production 1 | E87: 7 | F87: 0 | G87: =VLOOKUP($D87,Research!$C:$S,(COLUMN(Research_QuestReward_HeroXP)-COLUMN(Research_Name_and_Level)+1),FALSE) -> 3000 | H87: =G87*(1+F87) -> 3000 | J87: =VLOOKUP($D87,Research!$C:$S,(COLUMN(Research_QuestReward_Power)-COLUMN(Research_Name_and_Level)+1),FALSE) -> 25 | AJ87: =AJ86+(S$3*S87+T$3*T87+U$3*U87+V$3*V87+W$3*W87+X$3*X87+Y$3*Y87+Z$3*Z87+AA$3*AA87+AB$3*AB87+AC$3*AC87) -> 0.125 | AU87: =VLOOKUP($D87,Research!$C:$S,(COLUMN(Research_QuestReward_Stone)-COLUMN(Research_Name_and_Level)+1),FALSE) -> 0 | AV87: =VLOOKUP($D87,Research!$C:$S,(COLUMN(Research_QuestReward_Wood)-COLUMN(Research_Name_and_Level)+1),FALSE) -> 0 | AW87: =VLOOKUP($D87,Research!$C:$S,(COLUMN(Research_QuestReward_Ore)-COLUMN(Research_Name_and_Level)+1),FALSE) -> 0 | AX87: =VLOOKUP($D87,Research!$C:$S,(COLUMN(Research_QuestReward_Food)-COLUMN(Research_Name_and_Level)+1),FALSE) -> 0 | AY87: =VLOOKUP($D87,Research!$C:$S,(COLUMN(Research_QuestReward_Silver)-COLUMN(Research_Name_and_Level)+1),FALSE) -> 1500
B88: Construction | C88: by Quest | D88: Villa 2 | E88: 7 | F88: 0 | G88: =VLOOKUP($D88,Construction!$B:$E,(COLUMN(Construction_BuildingReward_HeroXP)-COLUMN(Construction_Name_and_Level)+1),FALSE) -> 25 | H88: =G88*(1+F88) -> 25 | J88: =VLOOKUP($D88,Construction!$B:$F,(COLUMN(Construction_BuildingReward_Power)-COLUMN(Construction_Name_and_Level)+1),FALSE) -> 25 | Q88: 0.0034722222 | R88: 0.0055555556 | AJ88: =AJ87+(S$3*S88+T$3*T88+U$3*U88+V$3*V88+W$3*W88+X$3*X88+Y$3*Y88+Z$3*Z88+AA$3*AA88+AB$3*AB88+AC$3*AC88) -> 0.125 | AK88: 0.01 | AL88: =VLOOKUP($D88,Construction!$B:$C,(COLUMN(Construction_Time)-COLUMN(Construction_Name_and_Level)+1),FALSE) -> 0.0011574074 | AM88: =AL88/(1+AK88) -> 0.0011459479 | AN88: =(S$3*S88+T$3*T88+V$3*V88+W$3*W88+X$3*X88+Y$3*Y88+Z$3*Z88+AA$3*AA88+AB$3*AB88+AC$3*AC88)*(-1) -> 0 | AO88: =IF((AM88-Q88-R88-AN88)>=0,AM88-Q88-R88-AN88,0) -> 0 | AU88: =VLOOKUP($D88,Construction!$B:$J,(COLUMN(Construction_BuildingCost_Stone)-COLUMN(Construction_Name_and_Level)+1),FALSE)*(-1) -> -340 | AV88: =VLOOKUP($D88,Construction!$B:$J,(COLUMN(Construction_BuildingCost_Wood)-COLUMN(Construction_Name_and_Level)+1),FALSE)*(-1) -> -340 | AW88: =VLOOKUP($D88,Construction!$B:$J,(COLUMN(Construction_BuildingCost_Ore)-COLUMN(Construction_Name_and_Level)+1),FALSE)*(-1) -> -85 | AX88: =VLOOKUP($D88,Construction!$B:$J,(COLUMN(Construction_BuildingCost_Food)-COLUMN(Construction_Name_and_Level)+1),FALSE)*(-1) -> -850
B89: Quest | C89: Construction Recommended | D89: Villa 2 | E89: 7 | F89: 0 | G89: =VLOOKUP($D89,Construction!$B:$L,(COLUMN(Construction_QuestReward_HeroXP)-COLUMN(Construction_Name_and_Level)+1),FALSE) -> 2575 | H89: =G89*(1+F89) -> 2575 | J89: =VLOOKUP($D89,Construction!$B:$L,(COLUMN(Construction_QuestReward_Power)-COLUMN(Construction_Name_and_Level)+1),FALSE) -> 5 | AJ89: =AJ88+(S$3*S89+T$3*T89+U$3*U89+V$3*V89+W$3*W89+X$3*X89+Y$3*Y89+Z$3*Z89+AA$3*AA89+AB$3*AB89+AC$3*AC89) -> 0.125 | AU89: =VLOOKUP($D89,Construction!$B:$Q,(COLUMN(Construction_QuestReward_Stone)-COLUMN(Construction_Name_and_Level)+1),FALSE) -> 0 | AV89: =VLOOKUP($D89,Construction!$B:$Q,(COLUMN(Construction_QuestReward_Wood)-COLUMN(Construction_Name_and_Level)+1),FALSE) -> 0 | AW89: =VLOOKUP($D89,Construction!$B:$Q,(COLUMN(Construction_QuestReward_Ore)-COLUMN(Construction_Name_and_Level)+1),FALSE) -> 0 | AX89: =VLOOKUP($D89,Construction!$B:$Q,(COLUMN(Construction_QuestReward_Food)-COLUMN(Construction_Name_and_Level)+1),FALSE) -> 0 | AY89: =VLOOKUP($D89,Construction!$B:$Q,(COLUMN(Construction_QuestReward_Silver)-COLUMN(Construction_Name_and_Level)+1),FALSE) -> 750
B90: Alliance | C90: Alliance Gift | E90: 7 | AJ90: =AJ89+(S$3*S90+T$3*T90+U$3*U90+V$3*V90+W$3*W90+X$3*X90+Y$3*Y90+Z$3*Z90+AA$3*AA90+AB$3*AB90+AC$3*AC90) -> 0.125 | AY90: 3000
B91: Construction | C91: by Quest | D91: Logging Camp 2 | E91: 7 | F91: 0 | G91: =VLOOKUP($D91,Construction!$B:$E,(COLUMN(Construction_BuildingReward_HeroXP)-COLUMN(Construction_Name_and_Level)+1),FALSE) -> 25 | H91: =G91*(1+F91) -> 25 | J91: =VLOOKUP($D91,Construction!$B:$F,(COLUMN(Construction_BuildingReward_Power)-COLUMN(Construction_Name_and_Level)+1),FALSE) -> 10 | Q91: 0.0034722222 | R91: 0.0055555556 | AJ91: =AJ90+(S$3*S91+T$3*T91+U$3*U91+V$3*V91+W$3*W91+X$3*X91+Y$3*Y91+Z$3*Z91+AA$3*AA91+AB$3*AB91+AC$3*AC91) -> 0.125 | AK91: 0.01 | AL91: =VLOOKUP($D91,Construction!$B:$C,(COLUMN(Construction_Time)-COLUMN(Construction_Name_and_Level)+1),FALSE) -> 0.0013888889 | AM91: =AL91/(1+AK91) -> 0.0013751375 | AN91: =(S$3*S91+T$3*T91+V$3*V91+W$3*W91+X$3*X91+Y$3*Y91+Z$3*Z91+AA$3*AA91+AB$3*AB91+AC$3*AC91)*(-1) -> 0 | AO91: =IF((AM91-Q91-R91-AN91)>=0,AM91-Q91-R91-AN91,0) -> 0 | AU91: =VLOOKUP($D91,Construction!$B:$J,(COLUMN(Construction_BuildingCost_Stone)-COLUMN(Construction_Name_and_Level)+1),FALSE)*(-1) -> -170 | AV91: =VLOOKUP($D91,Construction!$B:$J,(COLUMN(Construction_BuildingCost_Wood)-COLUMN(Construction_Name_and_Level)+1),FALSE)*(-1) -> 0 | AW91: =VLOOKUP($D91,Construction!$B:$J,(COLUMN(Construction_BuildingCost_Ore)-COLUMN(Construction_Name_and_Level)+1),FALSE)*(-1) -> -170 | AX91: =VLOOKUP($D91,Construction!$B:$J,(COLUMN(Construction_BuildingCost_Food)-COLUMN(Construction_Name_and_Level)+1),FALSE)*(-1) -> -170
B92: Quest | C92: Construction Recommended | D92: Logging Camp 2 | E92: 7 | F92: 0 | G92: =VLOOKUP($D92,Construction!$B:$L,(COLUMN(Construction_QuestReward_HeroXP)-COLUMN(Construction_Name_and_Level)+1),FALSE) -> 2575 | H92: =G92*(1+F92) -> 2575 | J92: =VLOOKUP($D92,Construction!$B:$L,(COLUMN(Construction_QuestReward_Power)-COLUMN(Construction_Name_and_Level)+1),FALSE) -> 2 | AJ92: =AJ91+(S$3*S92+T$3*T92+U$3*U92+V$3*V92+W$3*W92+X$3*X92+Y$3*Y92+Z$3*Z92+AA$3*AA92+AB$3*AB92+AC$3*AC92) -> 0.125 | AU92: =VLOOKUP($D92,Construction!$B:$Q,(COLUMN(Construction_QuestReward_Stone)-COLUMN(Construction_Name_and_Level)+1),FALSE) -> 0 | AV92: =VLOOKUP($D92,Construction!$B:$Q,(COLUMN(Construction_QuestReward_Wood)-COLUMN(Construction_Name_and_Level)+1),FALSE) -> 5000 | AW92: =VLOOKUP($D92,Construction!$B:$Q,(COLUMN(Construction_QuestReward_Ore)-COLUMN(Construction_Name_and_Level)+1),FALSE) -> 0 | AX92: =VLOOKUP($D92,Construction!$B:$Q,(COLUMN(Construction_QuestReward_Food)-COLUMN(Construction_Name_and_Level)+1),FALSE) -> 0 | AY92: =VLOOKUP($D92,Construction!$B:$Q,(COLUMN(Construction_QuestReward_Silver)-COLUMN(Construction_Name_and_Level)+1),FALSE) -> 0
B93: Gift | C93: Hero Level Up | D93: Hero 7->8 | E93: 8 | I93: 2 | J93: 62 | AJ93: =AJ92+(S$3*S93+T$3*T93+U$3*U93+V$3*V93+W$3*W93+X$3*X93+Y$3*Y93+Z$3*Z93+AA$3*AA93+AB$3*AB93+AC$3*AC93) -> 0.125
B94: Level_Up | D94: Hero Level 8 | E94: 8 | F94: 0 | G94: — | H94: 282255 | I94: 12 | J94: 3716 | K94: 3 | L94: 770 | M94: 0.10416667 | N94: 200 | O94: =SUMIF($B$4:$B93,"<>"&$CS$13,O$4:O93) -> 0 | P94: =SUMIF($B$4:$B93,"<>"&$CS$13,N$4:N93) -> 200 | Q94: 0.0034722222 | R94: 0.0055555556 | S94: 0 | T94: 0 | U94: 0 | V94: 3 | W94: 10 | X94: 0 | Y94: 0 | Z94: 0 | AA94: 0 | AB94: 0 | AC94: 0 | AD94: 0 | AE94: 0 | AF94: =SUMIF($B$4:$B93,"<>"&$CS$13,AF$4:AF93) -> 0.15138889 | AG94: =SUMIF($B$4:$B93,"<>"&$CS$13,AG$4:AG93) -> 0 | AH94: =AF94+AG94 -> 0.15138889 | AI94: =SUMIF($B$4:$B93,"<>"&$CS$13,AI$4:AI93) -> 0.026388889 | AJ94: =S$3*S94+T$3*T94+U$3*U94+V$3*V94+W$3*W94+X$3*X94+Y$3*Y94+Z$3*Z94+AA$3*AA94+AB$3*AB94+AC$3*AC94 -> 0.125 | AK94: 0.01 | AL94: — | AM94: — | AN94: — | AO94: — | AP94: 0.01 | AQ94: — | AR94: — | AS94: — | AT94: — | AU94: 92880 | AV94: 93230 | AW94: 73900 | AX94: 127800 | AY94: 33660 | AZ94: 41 | BA94: 120 | BB94: 30 | BC94: 178 | BD94: 60 | BE94: -20 | BF94: 17000 | BG94: 21000 | BH94: 16500 | BI94: 22500 | BJ94: 18000 | BK94: 4 | BL94: 3 | BM94: 4 | BN94: 2 | BO94: 1 | BP94: 2 | BQ94: 1 | BR94: 1 | BS94: 1 | BT94: 1 | BU94: 1 | BV94: 2 | BW94: 1 | BX94: 1 | BY94: 1 | BZ94: 1 | CA94: 1 | CB94: 1 | CC94: 1 | CD94: 1 | CL94: 25100 | CN94: —
B95: Quest | C95: Increase Production | D95: Wood Production 100 | E95: 8 | F95: 0 | G95: 0 | H95: =G95*(1+F95) -> 0 | J95: 25 | AJ95: =AJ94+(S$3*S95+T$3*T95+U$3*U95+V$3*V95+W$3*W95+X$3*X95+Y$3*Y95+Z$3*Z95+AA$3*AA95+AB$3*AB95+AC$3*AC95) -> 0.125 | AV95: 2500
B96: Gift | C96: Online Reward | D96: 0.0055555556 | E96: 8 | AJ96: =AJ95+(S$3*S96+T$3*T96+U$3*U96+V$3*V96+W$3*W96+X$3*X96+Y$3*Y96+Z$3*Z96+AA$3*AA96+AB$3*AB96+AC$3*AC96) -> 0.125 | AY96: 500
B97: Casino | E97: 8 | AJ97: =AJ96+(S$3*S97+T$3*T97+U$3*U97+V$3*V97+W$3*W97+X$3*X97+Y$3*Y97+Z$3*Z97+AA$3*AA97+AB$3*AB97+AC$3*AC97) -> 0.125 | AX97: 12500
B98: Research | C98: at Will | D98: Trap Building 1 | E98: 8 | F98: 0 | G98: =VLOOKUP($D98,Research!$C:$F,(COLUMN(Research_ResearchReward_HeroXP)-COLUMN(Research_Name_and_Level)+1),FALSE) -> 10000 | H98: =G98*(1+F98) -> 10000 | J98: =VLOOKUP($D98,Research!$C:$G,(COLUMN(Research_ResearchReward_Power)-COLUMN(Research_Name_and_Level)+1),FALSE) -> 250 | R98: 0.0055555556 | AJ98: =AJ97+(S$3*S98+T$3*T98+U$3*U98+V$3*V98+W$3*W98+X$3*X98+Y$3*Y98+Z$3*Z98+AA$3*AA98+AB$3*AB98+AC$3*AC98) -> 0.125 | AP98: 0.01 | AQ98: =VLOOKUP($D98,Research!$C:$D,(COLUMN(Research_Time)-COLUMN(Research_Name_and_Level)+1),FALSE) -> 0.0069444444 | AR98: =AQ98/(1+AP98) -> 0.0068756876 | AS98: =(S$3*S98+T$3*T98+V$3*V98+W$3*W98+X$3*X98+Y$3*Y98+Z$3*Z98+AA$3*AA98+AB$3*AB98+AC$3*AC98)*(-1) -> 0 | AT98: =IF(AR98-R98-AS98>=0,AR98-R98-AS98,0) -> 0.001320132 | AU98: =VLOOKUP($D98,Research!$C:$L,(COLUMN(Research_ResearchCost_Stone)-COLUMN(Research_Name_and_Level)+1),FALSE)*(-1) -> -5000 | AV98: =VLOOKUP($D98,Research!$C:$L,(COLUMN(Research_ResearchCost_Wood)-COLUMN(Research_Name_and_Level)+1),FALSE)*(-1) -> -5000 | AW98: =VLOOKUP($D98,Research!$C:$L,(COLUMN(Research_ResearchCost_Ore)-COLUMN(Research_Name_and_Level)+1),FALSE)*(-1) -> -5000 | AX98: =VLOOKUP($D98,Research!$C:$L,(COLUMN(Research_ResearchCost_Food)-COLUMN(Research_Name_and_Level)+1),FALSE)*(-1) -> -5000 | AY98: =VLOOKUP($D98,Research!$C:$L,(COLUMN(Research_ResearchCost_Silver)-COLUMN(Research_Name_and_Level)+1),FALSE)*(-1) -> -5000
B99: Quest | C99: Research at Will | D99: Trap Building 1 | E99: 8 | F99: 0 | G99: =VLOOKUP($D99,Research!$C:$S,(COLUMN(Research_QuestReward_HeroXP)-COLUMN(Research_Name_and_Level)+1),FALSE) -> 5000 | H99: =G99*(1+F99) -> 5000 | J99: =VLOOKUP($D99,Research!$C:$S,(COLUMN(Research_QuestReward_Power)-COLUMN(Research_Name_and_Level)+1),FALSE) -> 25 | AJ99: =AJ98+(S$3*S99+T$3*T99+U$3*U99+V$3*V99+W$3*W99+X$3*X99+Y$3*Y99+Z$3*Z99+AA$3*AA99+AB$3*AB99+AC$3*AC99) -> 0.125 | AU99: =VLOOKUP($D99,Research!$C:$S,(COLUMN(Research_QuestReward_Stone)-COLUMN(Research_Name_and_Level)+1),FALSE) -> 6000 | AV99: =VLOOKUP($D99,Research!$C:$S,(COLUMN(Research_QuestReward_Wood)-COLUMN(Research_Name_and_Level)+1),FALSE) -> 6000 | AW99: =VLOOKUP($D99,Research!$C:$S,(COLUMN(Research_QuestReward_Ore)-COLUMN(Research_Name_and_Level)+1),FALSE) -> 6000 | AX99: =VLOOKUP($D99,Research!$C:$S,(COLUMN(Research_QuestReward_Food)-COLUMN(Research_Name_and_Level)+1),FALSE) -> 6000 | AY99: =VLOOKUP($D99,Research!$C:$S,(COLUMN(Research_QuestReward_Silver)-COLUMN(Research_Name_and_Level)+1),FALSE) -> 3000
B100: Construction | C100: by Quest | D100: Quarry 2 | E100: 8 | F100: 0 | G100: =VLOOKUP($D100,Construction!$B:$E,(COLUMN(Construction_BuildingReward_HeroXP)-COLUMN(Construction_Name_and_Level)+1),FALSE) -> 25 | H100: =G100*(1+F100) -> 25 | J100: =VLOOKUP($D100,Construction!$B:$F,(COLUMN(Construction_BuildingReward_Power)-COLUMN(Construction_Name_and_Level)+1),FALSE) -> 10 | Q100: 0.0034722222 | R100: 0.0055555556 | AJ100: =AJ99+(S$3*S100+T$3*T100+U$3*U100+V$3*V100+W$3*W100+X$3*X100+Y$3*Y100+Z$3*Z100+AA$3*AA100+AB$3*AB100+AC$3*AC100) -> 0.125 | AK100: 0.01 | AL100: =VLOOKUP($D100,Construction!$B:$C,(COLUMN(Construction_Time)-COLUMN(Construction_Name_and_Level)+1),FALSE) -> 0.0016203704 | AM100: =AL100/(1+AK100) -> 0.0016043271 | AN100: =(S$3*S100+T$3*T100+V$3*V100+W$3*W100+X$3*X100+Y$3*Y100+Z$3*Z100+AA$3*AA100+AB$3*AB100+AC$3*AC100)*(-1) -> 0 | AO100: =IF((AM100-Q100-R100-AN100)>=0,AM100-Q100-R100-AN100,0) -> 0 | AU100: =VLOOKUP($D100,Construction!$B:$J,(COLUMN(Construction_BuildingCost_Stone)-COLUMN(Construction_Name_and_Level)+1),FALSE)*(-1) -> 0 | AV100: =VLOOKUP($D100,Construction!$B:$J,(COLUMN(Construction_BuildingCost_Wood)-COLUMN(Construction_Name_and_Level)+1),FALSE)*(-1) -> -170 | AW100: =VLOOKUP($D100,Construction!$B:$J,(COLUMN(Construction_BuildingCost_Ore)-COLUMN(Construction_Name_and_Level)+1),FALSE)*(-1) -> -170 | AX100: =VLOOKUP($D100,Construction!$B:$J,(COLUMN(Construction_BuildingCost_Food)-COLUMN(Construction_Name_and_Level)+1),FALSE)*(-1) -> -170
...

Sheet Construction Sequence
B2: CATEGORY | C2: CLASS | D2: DETAIL | E2: Hero | J2: Power Gained | K2: VIP | N2: Currency | O2: Free Time | P2: Help Time | Q2: Speed Up Gained or Possessed | AD2: Total Amount of Speed Up Time | AE2: Construction Time | AH2: Speed Up Time Used | AI2: Construction Time - Free Time - Help Time - Speed Up Time | AJ2: Saved Time | AK2: Resources Gained or Consumed
E3: Level | F3: Exp Modifier | G3: Original Exp | H3: Exp Actually Gained | I3: Skill Points | K3: Level | L3: Point | M3: Amount of Time | N3: Gold | Q3: 0.00069444444 | R3: 0.0020833333 | S3: 0.0034722222 | T3: 0.0069444444 | U3: 0.010416667 | V3: 0.041666667 | W3: 0.125 | X3: 0.33333333 | Y3: 0.625 | Z3: 1 | AA3: 3 | AB3: 25% Time Off | AC3: 50% Time Off | AE3: Construction Acceleration | AF3: Original Time | AG3: Actual Time | AK3: Stone | AL3: Wood | AM3: Ore | AN3: Food | AO3: Silver
B4: Construction | C4: by Quest | D4: Farm 1 | E4: 1 | F4: 0 | G4: =VLOOKUP($D4,Construction!$B:$E,(COLUMN(Construction_BuildingReward_HeroXP)-COLUMN(Construction_Name_and_Level)+1),FALSE) -> 10 | H4: =G4*(1+F4) -> 10 | J4: =VLOOKUP($D4,Construction!$B:$F,(COLUMN(Construction_BuildingReward_Power)-COLUMN(Construction_Name_and_Level)+1),FALSE) -> 5 | O4: 0.0034722222 | P4: 0.0034722222 | AD4: =#REF!+(Q$3*Q4+R$3*R4+S$3*S4+T$3*T4+U$3*U4+V$3*V4+W$3*W4+X$3*X4+Y$3*Y4+Z$3*Z4+AA$3*AA4) -> #REF! | AE4: 0 | AF4: =VLOOKUP($D4,Construction!$B:$C,(COLUMN(Construction_Time)-COLUMN(Construction_Name_and_Level)+1),FALSE) -> 0.00069444444 | AG4: =AF4/(1+AE4) -> 0.00069444444 | AH4: =(Q$3*Q4+R$3*R4+T$3*T4+U$3*U4+V$3*V4+W$3*W4+X$3*X4+Y$3*Y4+Z$3*Z4+AA$3*AA4)*(-1) -> 0 | AI4: =IF((AG4-O4-P4-AH4)>=0,AG4-O4-P4-AH4,0) -> 0 | AJ4: =AF4-AI4 -> 0.00069444444 | AK4: =VLOOKUP($D4,Construction!$B:$J,(COLUMN(Construction_BuildingCost_Stone)-COLUMN(Construction_Name_and_Level)+1),FALSE)*(-1) -> -100 | AL4: =VLOOKUP($D4,Construction!$B:$J,(COLUMN(Construction_BuildingCost_Wood)-COLUMN(Construction_Name_and_Level)+1),FALSE)*(-1) -> -100 | AM4: =VLOOKUP($D4,Construction!$B:$J,(COLUMN(Construction_BuildingCost_Ore)-COLUMN(Construction_Name_and_Level)+1),FALSE)*(-1) -> -100 | AN4: =VLOOKUP($D4,Construction!$B:$J,(COLUMN(Construction_BuildingCost_Food)-COLUMN(Construction_Name_and_Level)+1),FALSE)*(-1) -> 0
B5: Construction | C5: by Quest | D5: Stronghold 2 | E5: 1 | F5: 0 | G5: =VLOOKUP($D5,Construction!$B:$E,(COLUMN(Construction_BuildingReward_HeroXP)-COLUMN(Construction_Name_and_Level)+1),FALSE) -> 5000 | H5: =G5*(1+F5) -> 5000 | J5: =VLOOKUP($D5,Construction!$B:$F,(COLUMN(Construction_BuildingReward_Power)-COLUMN(Construction_Name_and_Level)+1),FALSE) -> 150 | O5: 0.0034722222 | P5: 0.0041666667 | AD5: =AD4+(Q$3*Q5+R$3*R5+S$3*S5+T$3*T5+U$3*U5+V$3*V5+W$3*W5+X$3*X5+Y$3*Y5+Z$3*Z5+AA$3*AA5) -> #REF! | AE5: 0 | AF5: =VLOOKUP($D5,Construction!$B:$C,(COLUMN(Construction_Time)-COLUMN(Construction_Name_and_Level)+1),FALSE) -> 0.0032407407 | AG5: =AF5/(1+AE5) -> 0.0032407407 | AH5: =(Q$3*Q5+R$3*R5+T$3*T5+U$3*U5+V$3*V5+W$3*W5+X$3*X5+Y$3*Y5+Z$3*Z5+AA$3*AA5)*(-1) -> 0 | AI5: =IF((AG5-O5-P5-AH5)>=0,AG5-O5-P5-AH5,0) -> 0 | AJ5: =AF5-AI5 -> 0.0032407407 | AK5: =VLOOKUP($D5,Construction!$B:$J,(COLUMN(Construction_BuildingCost_Stone)-COLUMN(Construction_Name_and_Level)+1),FALSE)*(-1) -> -1800 | AL5: =VLOOKUP($D5,Construction!$B:$J,(COLUMN(Construction_BuildingCost_Wood)-COLUMN(Construction_Name_and_Level)+1),FALSE)*(-1) -> -1800 | AM5: =VLOOKUP($D5,Construction!$B:$J,(COLUMN(Construction_BuildingCost_Ore)-COLUMN(Construction_Name_and_Level)+1),FALSE)*(-1) -> -720 | AN5: =VLOOKUP($D5,Construction!$B:$J,(COLUMN(Construction_BuildingCost_Food)-COLUMN(Construction_Name_and_Level)+1),FALSE)*(-1) -> -900
B6: Construction | C6: by Quest | D6: Logging Camp 1 | E6: 2 | F6: 0 | G6: =VLOOKUP($D6,Construction!$B:$E,(COLUMN(Construction_BuildingReward_HeroXP)-COLUMN(Construction_Name_and_Level)+1),FALSE) -> 10 | H6: =G6*(1+F6) -> 10 | J6: =VLOOKUP($D6,Construction!$B:$F,(COLUMN(Construction_BuildingReward_Power)-COLUMN(Construction_Name_and_Level)+1),FALSE) -> 5 | O6: 0.0034722222 | P6: 0.0041666667 | AD6: =AD5+(Q$3*Q6+R$3*R6+S$3*S6+T$3*T6+U$3*U6+V$3*V6+W$3*W6+X$3*X6+Y$3*Y6+Z$3*Z6+AA$3*AA6) -> #REF! | AE6: 0 | AF6: =VLOOKUP($D6,Construction!$B:$C,(COLUMN(Construction_Time)-COLUMN(Construction_Name_and_Level)+1),FALSE) -> 0.00069444444 | AG6: =AF6/(1+AE6) -> 0.00069444444 | AH6: =(Q$3*Q6+R$3*R6+T$3*T6+U$3*U6+V$3*V6+W$3*W6+X$3*X6+Y$3*Y6+Z$3*Z6+AA$3*AA6)*(-1) -> 0 | AI6: =IF((AG6-O6-P6-AH6)>=0,AG6-O6-P6-AH6,0) -> 0 | AJ6: =AF6-AI6 -> 0.00069444444 | AK6: =VLOOKUP($D6,Construction!$B:$J,(COLUMN(Construction_BuildingCost_Stone)-COLUMN(Construction_Name_and_Level)+1),FALSE)*(-1) -> -100 | AL6: =VLOOKUP($D6,Construction!$B:$J,(COLUMN(Construction_BuildingCost_Wood)-COLUMN(Construction_Name_and_Level)+1),FALSE)*(-1) -> 0 | AM6: =VLOOKUP($D6,Construction!$B:$J,(COLUMN(Construction_BuildingCost_Ore)-COLUMN(Construction_Name_and_Level)+1),FALSE)*(-1) -> -100 | AN6: =VLOOKUP($D6,Construction!$B:$J,(COLUMN(Construction_BuildingCost_Food)-COLUMN(Construction_Name_and_Level)+1),FALSE)*(-1) -> -100
B7: Construction | C7: by Quest | D7: Academy 1 | E7: 2 | F7: 0 | G7: =VLOOKUP($D7,Construction!$B:$E,(COLUMN(Construction_BuildingReward_HeroXP)-COLUMN(Construction_Name_and_Level)+1),FALSE) -> 10 | H7: =G7*(1+F7) -> 10 | J7: =VLOOKUP($D7,Construction!$B:$F,(COLUMN(Construction_BuildingReward_Power)-COLUMN(Construction_Name_and_Level)+1),FALSE) -> 35 | O7: 0.0034722222 | P7: 0.0041666667 | AD7: =AD6+(Q$3*Q7+R$3*R7+S$3*S7+T$3*T7+U$3*U7+V$3*V7+W$3*W7+X$3*X7+Y$3*Y7+Z$3*Z7+AA$3*AA7) -> #REF! | AE7: 0 | AF7: =VLOOKUP($D7,Construction!$B:$C,(COLUMN(Construction_Time)-COLUMN(Construction_Name_and_Level)+1),FALSE) -> 0.0011574074 | AG7: =AF7/(1+AE7) -> 0.0011574074 | AH7: =(Q$3*Q7+R$3*R7+T$3*T7+U$3*U7+V$3*V7+W$3*W7+X$3*X7+Y$3*Y7+Z$3*Z7+AA$3*AA7)*(-1) -> 0 | AI7: =IF((AG7-O7-P7-AH7)>=0,AG7-O7-P7-AH7,0) -> 0 | AJ7: =AF7-AI7 -> 0.0011574074 | AK7: =VLOOKUP($D7,Construction!$B:$J,(COLUMN(Construction_BuildingCost_Stone)-COLUMN(Construction_Name_and_Level)+1),FALSE)*(-1) -> -500 | AL7: =VLOOKUP($D7,Construction!$B:$J,(COLUMN(Construction_BuildingCost_Wood)-COLUMN(Construction_Name_and_Level)+1),FALSE)*(-1) -> -500 | AM7: =VLOOKUP($D7,Construction!$B:$J,(COLUMN(Construction_BuildingCost_Ore)-COLUMN(Construction_Name_and_Level)+1),FALSE)*(-1) -> -200 | AN7: =VLOOKUP($D7,Construction!$B:$J,(COLUMN(Construction_BuildingCost_Food)-COLUMN(Construction_Name_and_Level)+1),FALSE)*(-1) -> -300
B8: Construction | C8: at Will | D8: Barracks 1 | E8: 4 | F8: 0 | G8: =VLOOKUP($D8,Construction!$B:$E,(COLUMN(Construction_BuildingReward_HeroXP)-COLUMN(Construction_Name_and_Level)+1),FALSE) -> 10 | H8: =G8*(1+F8) -> 10 | J8: =VLOOKUP($D8,Construction!$B:$F,(COLUMN(Construction_BuildingReward_Power)-COLUMN(Construction_Name_and_Level)+1),FALSE) -> 20 | O8: 0.0034722222 | P8: 0.0041666667 | AD8: =AD7+(Q$3*Q8+R$3*R8+S$3*S8+T$3*T8+U$3*U8+V$3*V8+W$3*W8+X$3*X8+Y$3*Y8+Z$3*Z8+AA$3*AA8) -> #REF! | AE8: 0 | AF8: =VLOOKUP($D8,Construction!$B:$C,(COLUMN(Construction_Time)-COLUMN(Construction_Name_and_Level)+1),FALSE) -> 0.0010416667 | AG8: =AF8/(1+AE8) -> 0.0010416667 | AH8: =(Q$3*Q8+R$3*R8+T$3*T8+U$3*U8+V$3*V8+W$3*W8+X$3*X8+Y$3*Y8+Z$3*Z8+AA$3*AA8)*(-1) -> 0 | AI8: =IF((AG8-O8-P8-AH8)>=0,AG8-O8-P8-AH8,0) -> 0 | AJ8: =AF8-AI8 -> 0.0010416667 | AK8: =VLOOKUP($D8,Construction!$B:$J,(COLUMN(Construction_BuildingCost_Stone)-COLUMN(Construction_Name_and_Level)+1),FALSE)*(-1) -> -500 | AL8: =VLOOKUP($D8,Construction!$B:$J,(COLUMN(Construction_BuildingCost_Wood)-COLUMN(Construction_Name_and_Level)+1),FALSE)*(-1) -> -400 | AM8: =VLOOKUP($D8,Construction!$B:$J,(COLUMN(Construction_BuildingCost_Ore)-COLUMN(Construction_Name_and_Level)+1),FALSE)*(-1) -> -300 | AN8: =VLOOKUP($D8,Construction!$B:$J,(COLUMN(Construction_BuildingCost_Food)-COLUMN(Construction_Name_and_Level)+1),FALSE)*(-1) -> -250
B9: Construction | C9: at Will | D9: Storehouse 2 | E9: 4 | F9: 0 | G9: =VLOOKUP($D9,Construction!$B:$E,(COLUMN(Construction_BuildingReward_HeroXP)-COLUMN(Construction_Name_and_Level)+1),FALSE) -> 25 | H9: =G9*(1+F9) -> 25 | J9: =VLOOKUP($D9,Construction!$B:$F,(COLUMN(Construction_BuildingReward_Power)-COLUMN(Construction_Name_and_Level)+1),FALSE) -> 20 | O9: 0.0034722222 | P9: 0.0041666667 | AD9: =AD8+(Q$3*Q9+R$3*R9+S$3*S9+T$3*T9+U$3*U9+V$3*V9+W$3*W9+X$3*X9+Y$3*Y9+Z$3*Z9+AA$3*AA9) -> #REF! | AE9: 0 | AF9: =VLOOKUP($D9,Construction!$B:$C,(COLUMN(Construction_Time)-COLUMN(Construction_Name_and_Level)+1),FALSE) -> 0.0013888889 | AG9: =AF9/(1+AE9) -> 0.0013888889 | AH9: =(Q$3*Q9+R$3*R9+T$3*T9+U$3*U9+V$3*V9+W$3*W9+X$3*X9+Y$3*Y9+Z$3*Z9+AA$3*AA9)*(-1) -> 0 | AI9: =IF((AG9-O9-P9-AH9)>=0,AG9-O9-P9-AH9,0) -> 0 | AJ9: =AF9-AI9 -> 0.0013888889 | AK9: =VLOOKUP($D9,Construction!$B:$J,(COLUMN(Construction_BuildingCost_Stone)-COLUMN(Construction_Name_and_Level)+1),FALSE)*(-1) -> -680 | AL9: =VLOOKUP($D9,Construction!$B:$J,(COLUMN(Construction_BuildingCost_Wood)-COLUMN(Construction_Name_and_Level)+1),FALSE)*(-1) -> -680 | AM9: =VLOOKUP($D9,Construction!$B:$J,(COLUMN(Construction_BuildingCost_Ore)-COLUMN(Construction_Name_and_Level)+1),FALSE)*(-1) -> -510 | AN9: =VLOOKUP($D9,Construction!$B:$J,(COLUMN(Construction_BuildingCost_Food)-COLUMN(Construction_Name_and_Level)+1),FALSE)*(-1) -> -340
B10: Construction | C10: at Will | D10: Walls 2 | E10: 4 | F10: 0 | G10: =VLOOKUP($D10,Construction!$B:$E,(COLUMN(Construction_BuildingReward_HeroXP)-COLUMN(Construction_Name_and_Level)+1),FALSE) -> 5000 | H10: =G10*(1+F10) -> 5000 | J10: =VLOOKUP($D10,Construction!$B:$F,(COLUMN(Construction_BuildingReward_Power)-COLUMN(Construction_Name_and_Level)+1),FALSE) -> 90 | O10: 0.0034722222 | P10: 0.0041666667 | AD10: =AD9+(Q$3*Q10+R$3*R10+S$3*S10+T$3*T10+U$3*U10+V$3*V10+W$3*W10+X$3*X10+Y$3*Y10+Z$3*Z10+AA$3*AA10) -> #REF! | AE10: 0 | AF10: =VLOOKUP($D10,Construction!$B:$C,(COLUMN(Construction_Time)-COLUMN(Construction_Name_and_Level)+1),FALSE) -> 0.0024305556 | AG10: =AF10/(1+AE10) -> 0.0024305556 | AH10: =(Q$3*Q10+R$3*R10+T$3*T10+U$3*U10+V$3*V10+W$3*W10+X$3*X10+Y$3*Y10+Z$3*Z10+AA$3*AA10)*(-1) -> 0 | AI10: =IF((AG10-O10-P10-AH10)>=0,AG10-O10-P10-AH10,0) -> 0 | AJ10: =AF10-AI10 -> 0.0024305556 | AK10: =VLOOKUP($D10,Construction!$B:$J,(COLUMN(Construction_BuildingCost_Stone)-COLUMN(Construction_Name_and_Level)+1),FALSE)*(-1) -> -1800 | AL10: =VLOOKUP($D10,Construction!$B:$J,(COLUMN(Construction_BuildingCost_Wood)-COLUMN(Construction_Name_and_Level)+1),FALSE)*(-1) -> -1440 | AM10: =VLOOKUP($D10,Construction!$B:$J,(COLUMN(Construction_BuildingCost_Ore)-COLUMN(Construction_Name_and_Level)+1),FALSE)*(-1) -> -540 | AN10: =VLOOKUP($D10,Construction!$B:$J,(COLUMN(Construction_BuildingCost_Food)-COLUMN(Construction_Name_and_Level)+1),FALSE)*(-1) -> -900
B11: Construction | C11: at Will | D11: Stronghold 3 | E11: 4 | F11: 0 | G11: =VLOOKUP($D11,Construction!$B:$E,(COLUMN(Construction_BuildingReward_HeroXP)-COLUMN(Construction_Name_and_Level)+1),FALSE) -> 10000 | H11: =G11*(1+F11) -> 10000 | J11: =VLOOKUP($D11,Construction!$B:$F,(COLUMN(Construction_BuildingReward_Power)-COLUMN(Construction_Name_and_Level)+1),FALSE) -> 150 | O11: 0.0034722222 | P11: 0.0048611111 | R11: -1 | AD11: =AD10+(Q$3*Q11+R$3*R11+S$3*S11+T$3*T11+U$3*U11+V$3*V11+W$3*W11+X$3*X11+Y$3*Y11+Z$3*Z11+AA$3*AA11) -> #REF! | AE11: 0 | AF11: =VLOOKUP($D11,Construction!$B:$C,(COLUMN(Construction_Time)-COLUMN(Construction_Name_and_Level)+1),FALSE) -> 0.013888889 | AG11: =AF11/(1+AE11) -> 0.013888889 | AH11: =(Q$3*Q11+R$3*R11+T$3*T11+U$3*U11+V$3*V11+W$3*W11+X$3*X11+Y$3*Y11+Z$3*Z11+AA$3*AA11)*(-1) -> 0.0020833333 | AI11: =IF((AG11-O11-P11-AH11)>=0,AG11-O11-P11-AH11,0) -> 0.0034722222 | AJ11: =AF11-AI11 -> 0.010416667 | AK11: =VLOOKUP($D11,Construction!$B:$J,(COLUMN(Construction_BuildingCost_Stone)-COLUMN(Construction_Name_and_Level)+1),FALSE)*(-1) -> -3240 | AL11: =VLOOKUP($D11,Construction!$B:$J,(COLUMN(Construction_BuildingCost_Wood)-COLUMN(Construction_Name_and_Level)+1),FALSE)*(-1) -> -3240 | AM11: =VLOOKUP($D11,Construction!$B:$J,(COLUMN(Construction_BuildingCost_Ore)-COLUMN(Construction_Name_and_Level)+1),FALSE)*(-1) -> -1296 | AN11: =VLOOKUP($D11,Construction!$B:$J,(COLUMN(Construction_BuildingCost_Food)-COLUMN(Construction_Name_and_Level)+1),FALSE)*(-1) -> -1620
B12: Construction | C12: at Will | D12: Storehouse 3 | E12: 5 | F12: 0 | G12: =VLOOKUP($D12,Construction!$B:$E,(COLUMN(Construction_BuildingReward_HeroXP)-COLUMN(Construction_Name_and_Level)+1),FALSE) -> 50 | H12: =G12*(1+F12) -> 50 | J12: =VLOOKUP($D12,Construction!$B:$F,(COLUMN(Construction_BuildingReward_Power)-COLUMN(Construction_Name_and_Level)+1),FALSE) -> 30 | O12: 0.0034722222 | P12: 0.0048611111 | AD12: =AD11+(Q$3*Q12+R$3*R12+S$3*S12+T$3*T12+U$3*U12+V$3*V12+W$3*W12+X$3*X12+Y$3*Y12+Z$3*Z12+AA$3*AA12) -> #REF! | AE12: 0 | AF12: =VLOOKUP($D12,Construction!$B:$C,(COLUMN(Construction_Time)-COLUMN(Construction_Name_and_Level)+1),FALSE) -> 0.0027777778 | AG12: =AF12/(1+AE12) -> 0.0027777778 | AH12: =(Q$3*Q12+R$3*R12+T$3*T12+U$3*U12+V$3*V12+W$3*W12+X$3*X12+Y$3*Y12+Z$3*Z12+AA$3*AA12)*(-1) -> 0 | AI12: =IF((AG12-O12-P12-AH12)>=0,AG12-O12-P12-AH12,0) -> 0 | AJ12: =AF12-AI12 -> 0.0027777778 | AK12: =VLOOKUP($D12,Construction!$B:$J,(COLUMN(Construction_BuildingCost_Stone)-COLUMN(Construction_Name_and_Level)+1),FALSE)*(-1) -> -1156 | AL12: =VLOOKUP($D12,Construction!$B:$J,(COLUMN(Construction_BuildingCost_Wood)-COLUMN(Construction_Name_and_Level)+1),FALSE)*(-1) -> -1156 | AM12: =VLOOKUP($D12,Construction!$B:$J,(COLUMN(Construction_BuildingCost_Ore)-COLUMN(Construction_Name_and_Level)+1),FALSE)*(-1) -> -867 | AN12: =VLOOKUP($D12,Construction!$B:$J,(COLUMN(Construction_BuildingCost_Food)-COLUMN(Construction_Name_and_Level)+1),FALSE)*(-1) -> -578
B13: Construction | C13: at Will | D13: Stronghold 4 | E13: 5 | F13: 0 | G13: =VLOOKUP($D13,Construction!$B:$E,(COLUMN(Construction_BuildingReward_HeroXP)-COLUMN(Construction_Name_and_Level)+1),FALSE) -> 10000 | H13: =G13*(1+F13) -> 10000 | J13: =VLOOKUP($D13,Construction!$B:$F,(COLUMN(Construction_BuildingReward_Power)-COLUMN(Construction_Name_and_Level)+1),FALSE) -> 250 | O13: 0.0034722222 | P13: 0.0055555556 | T13: -2 | U13: -1 | AD13: =AD12+(Q$3*Q13+R$3*R13+S$3*S13+T$3*T13+U$3*U13+V$3*V13+W$3*W13+X$3*X13+Y$3*Y13+Z$3*Z13+AA$3*AA13) -> #REF! | AE13: 0 | AF13: =VLOOKUP($D13,Construction!$B:$C,(COLUMN(Construction_Time)-COLUMN(Construction_Name_and_Level)+1),FALSE) -> 0.027777778 | AG13: =AF13/(1+AE13) -> 0.027777778 | AH13: =(Q$3*Q13+R$3*R13+T$3*T13+U$3*U13+V$3*V13+W$3*W13+X$3*X13+Y$3*Y13+Z$3*Z13+AA$3*AA13)*(-1) -> 0.024305556 | AI13: =IF((AG13-O13-P13-AH13)>=0,AG13-O13-P13-AH13,0) -> 0 | AJ13: =AF13-AI13 -> 0.027777778 | AK13: =VLOOKUP($D13,Construction!$B:$J,(COLUMN(Construction_BuildingCost_Stone)-COLUMN(Construction_Name_and_Level)+1),FALSE)*(-1) -> -5832 | AL13: =VLOOKUP($D13,Construction!$B:$J,(COLUMN(Construction_BuildingCost_Wood)-COLUMN(Construction_Name_and_Level)+1),FALSE)*(-1) -> -5832 | AM13: =VLOOKUP($D13,Construction!$B:$J,(COLUMN(Construction_BuildingCost_Ore)-COLUMN(Construction_Name_and_Level)+1),FALSE)*(-1) -> -2333 | AN13: =VLOOKUP($D13,Construction!$B:$J,(COLUMN(Construction_BuildingCost_Food)-COLUMN(Construction_Name_and_Level)+1),FALSE)*(-1) -> -2916
B14: Construction | C14: at Will | D14: Storehouse 4 | E14: 5 | F14: 0 | G14: =VLOOKUP($D14,Construction!$B:$E,(COLUMN(Construction_BuildingReward_HeroXP)-COLUMN(Construction_Name_and_Level)+1),FALSE) -> 200 | H14: =G14*(1+F14) -> 200 | J14: =VLOOKUP($D14,Construction!$B:$F,(COLUMN(Construction_BuildingReward_Power)-COLUMN(Construction_Name_and_Level)+1),FALSE) -> 50 | O14: 0.0034722222 | P14: 0.0055555556 | AD14: =AD13+(Q$3*Q14+R$3*R14+S$3*S14+T$3*T14+U$3*U14+V$3*V14+W$3*W14+X$3*X14+Y$3*Y14+Z$3*Z14+AA$3*AA14) -> #REF! | AE14: 0 | AF14: =VLOOKUP($D14,Construction!$B:$C,(COLUMN(Construction_Time)-COLUMN(Construction_Name_and_Level)+1),FALSE) -> 0.0055555556 | AG14: =AF14/(1+AE14) -> 0.0055555556 | AH14: =(Q$3*Q14+R$3*R14+T$3*T14+U$3*U14+V$3*V14+W$3*W14+X$3*X14+Y$3*Y14+Z$3*Z14+AA$3*AA14)*(-1) -> 0 | AI14: =IF((AG14-O14-P14-AH14)>=0,AG14-O14-P14-AH14,0) -> 0 | AJ14: =AF14-AI14 -> 0.0055555556 | AK14: =VLOOKUP($D14,Construction!$B:$J,(COLUMN(Construction_BuildingCost_Stone)-COLUMN(Construction_Name_and_Level)+1),FALSE)*(-1) -> -1966 | AL14: =VLOOKUP($D14,Construction!$B:$J,(COLUMN(Construction_BuildingCost_Wood)-COLUMN(Construction_Name_and_Level)+1),FALSE)*(-1) -> -1966 | AM14: =VLOOKUP($D14,Construction!$B:$J,(COLUMN(Construction_BuildingCost_Ore)-COLUMN(Construction_Name_and_Level)+1),FALSE)*(-1) -> -1474 | AN14: =VLOOKUP($D14,Construction!$B:$J,(COLUMN(Construction_BuildingCost_Food)-COLUMN(Construction_Name_and_Level)+1),FALSE)*(-1) -> -983
B15: Construction | C15: at Will | D15: Walls 3 | E15: 5 | F15: 0 | G15: =VLOOKUP($D15,Construction!$B:$E,(COLUMN(Construction_BuildingReward_HeroXP)-COLUMN(Construction_Name_and_Level)+1),FALSE) -> 5000 | H15: =G15*(1+F15) -> 5000 | J15: =VLOOKUP($D15,Construction!$B:$F,(COLUMN(Construction_BuildingReward_Power)-COLUMN(Construction_Name_and_Level)+1),FALSE) -> 100 | O15: 0.0034722222 | P15: 0.0055555556 | AD15: =AD14+(Q$3*Q15+R$3*R15+S$3*S15+T$3*T15+U$3*U15+V$3*V15+W$3*W15+X$3*X15+Y$3*Y15+Z$3*Z15+AA$3*AA15) -> #REF! | AE15: 0 | AF15: =VLOOKUP($D15,Construction!$B:$C,(COLUMN(Construction_Time)-COLUMN(Construction_Name_and_Level)+1),FALSE) -> 0.0048611111 | AG15: =AF15/(1+AE15) -> 0.0048611111 | AH15: =(Q$3*Q15+R$3*R15+T$3*T15+U$3*U15+V$3*V15+W$3*W15+X$3*X15+Y$3*Y15+Z$3*Z15+AA$3*AA15)*(-1) -> 0 | AI15: =IF((AG15-O15-P15-AH15)>=0,AG15-O15-P15-AH15,0) -> 0 | AJ15: =AF15-AI15 -> 0.0048611111 | AK15: =VLOOKUP($D15,Construction!$B:$J,(COLUMN(Construction_BuildingCost_Stone)-COLUMN(Construction_Name_and_Level)+1),FALSE)*(-1) -> -3240 | AL15: =VLOOKUP($D15,Construction!$B:$J,(COLUMN(Construction_BuildingCost_Wood)-COLUMN(Construction_Name_and_Level)+1),FALSE)*(-1) -> -2592 | AM15: =VLOOKUP($D15,Construction!$B:$J,(COLUMN(Construction_BuildingCost_Ore)-COLUMN(Construction_Name_and_Level)+1),FALSE)*(-1) -> -972 | AN15: =VLOOKUP($D15,Construction!$B:$J,(COLUMN(Construction_BuildingCost_Food)-COLUMN(Construction_Name_and_Level)+1),FALSE)*(-1) -> -1620
B16: Construction | C16: by Quest | D16: Quarry 1 | E16: 7 | F16: 0 | G16: =VLOOKUP($D16,Construction!$B:$E,(COLUMN(Construction_BuildingReward_HeroXP)-COLUMN(Construction_Name_and_Level)+1),FALSE) -> 10 | H16: =G16*(1+F16) -> 10 | J16: =VLOOKUP($D16,Construction!$B:$F,(COLUMN(Construction_BuildingReward_Power)-COLUMN(Construction_Name_and_Level)+1),FALSE) -> 5 | O16: 0.0034722222 | P16: 0.0055555556 | AD16: =AD15+(Q$3*Q16+R$3*R16+S$3*S16+T$3*T16+U$3*U16+V$3*V16+W$3*W16+X$3*X16+Y$3*Y16+Z$3*Z16+AA$3*AA16) -> #REF! | AE16: 0.01 | AF16: =VLOOKUP($D16,Construction!$B:$C,(COLUMN(Construction_Time)-COLUMN(Construction_Name_and_Level)+1),FALSE) -> 0.00069444444 | AG16: =AF16/(1+AE16) -> 0.00068756876 | AH16: =(Q$3*Q16+R$3*R16+T$3*T16+U$3*U16+V$3*V16+W$3*W16+X$3*X16+Y$3*Y16+Z$3*Z16+AA$3*AA16)*(-1) -> 0 | AI16: =IF((AG16-O16-P16-AH16)>=0,AG16-O16-P16-AH16,0) -> 0 | AJ16: =AF16-AI16 -> 0.00069444444 | AK16: =VLOOKUP($D16,Construction!$B:$J,(COLUMN(Construction_BuildingCost_Stone)-COLUMN(Construction_Name_and_Level)+1),FALSE)*(-1) -> 0 | AL16: =VLOOKUP($D16,Construction!$B:$J,(COLUMN(Construction_BuildingCost_Wood)-COLUMN(Construction_Name_and_Level)+1),FALSE)*(-1) -> -100 | AM16: =VLOOKUP($D16,Construction!$B:$J,(COLUMN(Construction_BuildingCost_Ore)-COLUMN(Construction_Name_and_Level)+1),FALSE)*(-1) -> -100 | AN16: =VLOOKUP($D16,Construction!$B:$J,(COLUMN(Construction_BuildingCost_Food)-COLUMN(Construction_Name_and_Level)+1),FALSE)*(-1) -> -100
B17: Construction | C17: by Quest | D17: Mine 1 | E17: 7 | F17: 0 | G17: =VLOOKUP($D17,Construction!$B:$E,(COLUMN(Construction_BuildingReward_HeroXP)-COLUMN(Construction_Name_and_Level)+1),FALSE) -> 10 | H17: =G17*(1+F17) -> 10 | J17: =VLOOKUP($D17,Construction!$B:$F,(COLUMN(Construction_BuildingReward_Power)-COLUMN(Construction_Name_and_Level)+1),FALSE) -> 5 | O17: 0.0034722222 | P17: 0.0055555556 | AD17: =AD16+(Q$3*Q17+R$3*R17+S$3*S17+T$3*T17+U$3*U17+V$3*V17+W$3*W17+X$3*X17+Y$3*Y17+Z$3*Z17+AA$3*AA17) -> #REF! | AE17: 0.01 | AF17: =VLOOKUP($D17,Construction!$B:$C,(COLUMN(Construction_Time)-COLUMN(Construction_Name_and_Level)+1),FALSE) -> 0.00069444444 | AG17: =AF17/(1+AE17) -> 0.00068756876 | AH17: =(Q$3*Q17+R$3*R17+T$3*T17+U$3*U17+V$3*V17+W$3*W17+X$3*X17+Y$3*Y17+Z$3*Z17+AA$3*AA17)*(-1) -> 0 | AI17: =IF((AG17-O17-P17-AH17)>=0,AG17-O17-P17-AH17,0) -> 0 | AJ17: =AF17-AI17 -> 0.00069444444 | AK17: =VLOOKUP($D17,Construction!$B:$J,(COLUMN(Construction_BuildingCost_Stone)-COLUMN(Construction_Name_and_Level)+1),FALSE)*(-1) -> -100 | AL17: =VLOOKUP($D17,Construction!$B:$J,(COLUMN(Construction_BuildingCost_Wood)-COLUMN(Construction_Name_and_Level)+1),FALSE)*(-1) -> -100 | AM17: =VLOOKUP($D17,Construction!$B:$J,(COLUMN(Construction_BuildingCost_Ore)-COLUMN(Construction_Name_and_Level)+1),FALSE)*(-1) -> 0 | AN17: =VLOOKUP($D17,Construction!$B:$J,(COLUMN(Construction_BuildingCost_Food)-COLUMN(Construction_Name_and_Level)+1),FALSE)*(-1) -> -100
B18: Construction | C18: by Quest | D18: Villa 1 | E18: 7 | F18: 0 | G18: =VLOOKUP($D18,Construction!$B:$E,(COLUMN(Construction_BuildingReward_HeroXP)-COLUMN(Construction_Name_and_Level)+1),FALSE) -> 10 | H18: =G18*(1+F18) -> 10 | J18: =VLOOKUP($D18,Construction!$B:$F,(COLUMN(Construction_BuildingReward_Power)-COLUMN(Construction_Name_and_Level)+1),FALSE) -> 10 | O18: 0.0034722222 | P18: 0.0055555556 | AD18: =AD17+(Q$3*Q18+R$3*R18+S$3*S18+T$3*T18+U$3*U18+V$3*V18+W$3*W18+X$3*X18+Y$3*Y18+Z$3*Z18+AA$3*AA18) -> #REF! | AE18: 0.01 | AF18: =VLOOKUP($D18,Construction!$B:$C,(COLUMN(Construction_Time)-COLUMN(Construction_Name_and_Level)+1),FALSE) -> 0.00069444444 | AG18: =AF18/(1+AE18) -> 0.00068756876 | AH18: =(Q$3*Q18+R$3*R18+T$3*T18+U$3*U18+V$3*V18+W$3*W18+X$3*X18+Y$3*Y18+Z$3*Z18+AA$3*AA18)*(-1) -> 0 | AI18: =IF((AG18-O18-P18-AH18)>=0,AG18-O18-P18-AH18,0) -> 0 | AJ18: =AF18-AI18 -> 0.00069444444 | AK18: =VLOOKUP($D18,Construction!$B:$J,(COLUMN(Construction_BuildingCost_Stone)-COLUMN(Construction_Name_and_Level)+1),FALSE)*(-1) -> -200 | AL18: =VLOOKUP($D18,Construction!$B:$J,(COLUMN(Construction_BuildingCost_Wood)-COLUMN(Construction_Name_and_Level)+1),FALSE)*(-1) -> -200 | AM18: =VLOOKUP($D18,Construction!$B:$J,(COLUMN(Construction_BuildingCost_Ore)-COLUMN(Construction_Name_and_Level)+1),FALSE)*(-1) -> -50 | AN18: =VLOOKUP($D18,Construction!$B:$J,(COLUMN(Construction_BuildingCost_Food)-COLUMN(Construction_Name_and_Level)+1),FALSE)*(-1) -> -500
B19: Construction | C19: by Quest | D19: Forge 1 | E19: 7 | F19: 0 | G19: =VLOOKUP($D19,Construction!$B:$E,(COLUMN(Construction_BuildingReward_HeroXP)-COLUMN(Construction_Name_and_Level)+1),FALSE) -> 10 | H19: =G19*(1+F19) -> 10 | J19: =VLOOKUP($D19,Construction!$B:$F,(COLUMN(Construction_BuildingReward_Power)-COLUMN(Construction_Name_and_Level)+1),FALSE) -> 10 | O19: 0.0034722222 | P19: 0.0055555556 | AD19: =AD18+(Q$3*Q19+R$3*R19+S$3*S19+T$3*T19+U$3*U19+V$3*V19+W$3*W19+X$3*X19+Y$3*Y19+Z$3*Z19+AA$3*AA19) -> #REF! | AE19: 0.01 | AF19: =VLOOKUP($D19,Construction!$B:$C,(COLUMN(Construction_Time)-COLUMN(Construction_Name_and_Level)+1),FALSE) -> 0.00086805556 | AG19: =AF19/(1+AE19) -> 0.00085946095 | AH19: =(Q$3*Q19+R$3*R19+T$3*T19+U$3*U19+V$3*V19+W$3*W19+X$3*X19+Y$3*Y19+Z$3*Z19+AA$3*AA19)*(-1) -> 0 | AI19: =IF((AG19-O19-P19-AH19)>=0,AG19-O19-P19-AH19,0) -> 0 | AJ19: =AF19-AI19 -> 0.00086805556 | AK19: =VLOOKUP($D19,Construction!$B:$J,(COLUMN(Construction_BuildingCost_Stone)-COLUMN(Construction_Name_and_Level)+1),FALSE)*(-1) -> -300 | AL19: =VLOOKUP($D19,Construction!$B:$J,(COLUMN(Construction_BuildingCost_Wood)-COLUMN(Construction_Name_and_Level)+1),FALSE)*(-1) -> -400 | AM19: =VLOOKUP($D19,Construction!$B:$J,(COLUMN(Construction_BuildingCost_Ore)-COLUMN(Construction_Name_and_Level)+1),FALSE)*(-1) -> -800 | AN19: =VLOOKUP($D19,Construction!$B:$J,(COLUMN(Construction_BuildingCost_Food)-COLUMN(Construction_Name_and_Level)+1),FALSE)*(-1) -> -300
B20: Construction | C20: by Quest | D20: Farm 2 | E20: 7 | F20: 0 | G20: =VLOOKUP($D20,Construction!$B:$E,(COLUMN(Construction_BuildingReward_HeroXP)-COLUMN(Construction_Name_and_Level)+1),FALSE) -> 25 | H20: =G20*(1+F20) -> 25 | J20: =VLOOKUP($D20,Construction!$B:$F,(COLUMN(Construction_BuildingReward_Power)-COLUMN(Construction_Name_and_Level)+1),FALSE) -> 10 | O20: 0.0034722222 | P20: 0.0055555556 | AD20: =AD19+(Q$3*Q20+R$3*R20+S$3*S20+T$3*T20+U$3*U20+V$3*V20+W$3*W20+X$3*X20+Y$3*Y20+Z$3*Z20+AA$3*AA20) -> #REF! | AE20: 0.01 | AF20: =VLOOKUP($D20,Construction!$B:$C,(COLUMN(Construction_Time)-COLUMN(Construction_Name_and_Level)+1),FALSE) -> 0.0011574074 | AG20: =AF20/(1+AE20) -> 0.0011459479 | AH20: =(Q$3*Q20+R$3*R20+T$3*T20+U$3*U20+V$3*V20+W$3*W20+X$3*X20+Y$3*Y20+Z$3*Z20+AA$3*AA20)*(-1) -> 0 | AI20: =IF((AG20-O20-P20-AH20)>=0,AG20-O20-P20-AH20,0) -> 0 | AJ20: =AF20-AI20 -> 0.0011574074 | AK20: =VLOOKUP($D20,Construction!$B:$J,(COLUMN(Construction_BuildingCost_Stone)-COLUMN(Construction_Name_and_Level)+1),FALSE)*(-1) -> -170 | AL20: =VLOOKUP($D20,Construction!$B:$J,(COLUMN(Construction_BuildingCost_Wood)-COLUMN(Construction_Name_and_Level)+1),FALSE)*(-1) -> -170 | AM20: =VLOOKUP($D20,Construction!$B:$J,(COLUMN(Construction_BuildingCost_Ore)-COLUMN(Construction_Name_and_Level)+1),FALSE)*(-1) -> -170 | AN20: =VLOOKUP($D20,Construction!$B:$J,(COLUMN(Construction_BuildingCost_Food)-COLUMN(Construction_Name_and_Level)+1),FALSE)*(-1) -> 0
B21: Construction | C21: by Quest | D21: Villa 2 | E21: 7 | F21: 0 | G21: =VLOOKUP($D21,Construction!$B:$E,(COLUMN(Construction_BuildingReward_HeroXP)-COLUMN(Construction_Name_and_Level)+1),FALSE) -> 25 | H21: =G21*(1+F21) -> 25 | J21: =VLOOKUP($D21,Construction!$B:$F,(COLUMN(Construction_BuildingReward_Power)-COLUMN(Construction_Name_and_Level)+1),FALSE) -> 25 | O21: 0.0034722222 | P21: 0.0055555556 | AD21: =AD20+(Q$3*Q21+R$3*R21+S$3*S21+T$3*T21+U$3*U21+V$3*V21+W$3*W21+X$3*X21+Y$3*Y21+Z$3*Z21+AA$3*AA21) -> #REF! | AE21: 0.01 | AF21: =VLOOKUP($D21,Construction!$B:$C,(COLUMN(Construction_Time)-COLUMN(Construction_Name_and_Level)+1),FALSE) -> 0.0011574074 | AG21: =AF21/(1+AE21) -> 0.0011459479 | AH21: =(Q$3*Q21+R$3*R21+T$3*T21+U$3*U21+V$3*V21+W$3*W21+X$3*X21+Y$3*Y21+Z$3*Z21+AA$3*AA21)*(-1) -> 0 | AI21: =IF((AG21-O21-P21-AH21)>=0,AG21-O21-P21-AH21,0) -> 0 | AJ21: =AF21-AI21 -> 0.0011574074 | AK21: =VLOOKUP($D21,Construction!$B:$J,(COLUMN(Construction_BuildingCost_Stone)-COLUMN(Construction_Name_and_Level)+1),FALSE)*(-1) -> -340 | AL21: =VLOOKUP($D21,Construction!$B:$J,(COLUMN(Construction_BuildingCost_Wood)-COLUMN(Construction_Name_and_Level)+1),FALSE)*(-1) -> -340 | AM21: =VLOOKUP($D21,Construction!$B:$J,(COLUMN(Construction_BuildingCost_Ore)-COLUMN(Construction_Name_and_Level)+1),FALSE)*(-1) -> -85 | AN21: =VLOOKUP($D21,Construction!$B:$J,(COLUMN(Construction_BuildingCost_Food)-COLUMN(Construction_Name_and_Level)+1),FALSE)*(-1) -> -850
B22: Construction | C22: by Quest | D22: Logging Camp 2 | E22: 7 | F22: 0 | G22: =VLOOKUP($D22,Construction!$B:$E,(COLUMN(Construction_BuildingReward_HeroXP)-COLUMN(Construction_Name_and_Level)+1),FALSE) -> 25 | H22: =G22*(1+F22) -> 25 | J22: =VLOOKUP($D22,Construction!$B:$F,(COLUMN(Construction_BuildingReward_Power)-COLUMN(Construction_Name_and_Level)+1),FALSE) -> 10 | O22: 0.0034722222 | P22: 0.0055555556 | AD22: =AD21+(Q$3*Q22+R$3*R22+S$3*S22+T$3*T22+U$3*U22+V$3*V22+W$3*W22+X$3*X22+Y$3*Y22+Z$3*Z22+AA$3*AA22) -> #REF! | AE22: 0.01 | AF22: =VLOOKUP($D22,Construction!$B:$C,(COLUMN(Construction_Time)-COLUMN(Construction_Name_and_Level)+1),FALSE) -> 0.0013888889 | AG22: =AF22/(1+AE22) -> 0.0013751375 | AH22: =(Q$3*Q22+R$3*R22+T$3*T22+U$3*U22+V$3*V22+W$3*W22+X$3*X22+Y$3*Y22+Z$3*Z22+AA$3*AA22)*(-1) -> 0 | AI22: =IF((AG22-O22-P22-AH22)>=0,AG22-O22-P22-AH22,0) -> 0 | AJ22: =AF22-AI22 -> 0.0013888889 | AK22: =VLOOKUP($D22,Construction!$B:$J,(COLUMN(Construction_BuildingCost_Stone)-COLUMN(Construction_Name_and_Level)+1),FALSE)*(-1) -> -170 | AL22: =VLOOKUP($D22,Construction!$B:$J,(COLUMN(Construction_BuildingCost_Wood)-COLUMN(Construction_Name_and_Level)+1),FALSE)*(-1) -> 0 | AM22: =VLOOKUP($D22,Construction!$B:$J,(COLUMN(Construction_BuildingCost_Ore)-COLUMN(Construction_Name_and_Level)+1),FALSE)*(-1) -> -170 | AN22: =VLOOKUP($D22,Construction!$B:$J,(COLUMN(Construction_BuildingCost_Food)-COLUMN(Construction_Name_and_Level)+1),FALSE)*(-1) -> -170
B23: Construction | C23: by Quest | D23: Quarry 2 | E23: 8 | F23: 0 | G23: =VLOOKUP($D23,Construction!$B:$E,(COLUMN(Construction_BuildingReward_HeroXP)-COLUMN(Construction_Name_and_Level)+1),FALSE) -> 25 | H23: =G23*(1+F23) -> 25 | J23: =VLOOKUP($D23,Construction!$B:$F,(COLUMN(Construction_BuildingReward_Power)-COLUMN(Construction_Name_and_Level)+1),FALSE) -> 10 | O23: 0.0034722222 | P23: 0.0055555556 | AD23: =AD22+(Q$3*Q23+R$3*R23+S$3*S23+T$3*T23+U$3*U23+V$3*V23+W$3*W23+X$3*X23+Y$3*Y23+Z$3*Z23+AA$3*AA23) -> #REF! | AE23: 0.01 | AF23: =VLOOKUP($D23,Construction!$B:$C,(COLUMN(Construction_Time)-COLUMN(Construction_Name_and_Level)+1),FALSE) -> 0.0016203704 | AG23: =AF23/(1+AE23) -> 0.0016043271 | AH23: =(Q$3*Q23+R$3*R23+T$3*T23+U$3*U23+V$3*V23+W$3*W23+X$3*X23+Y$3*Y23+Z$3*Z23+AA$3*AA23)*(-1) -> 0 | AI23: =IF((AG23-O23-P23-AH23)>=0,AG23-O23-P23-AH23,0) -> 0 | AJ23: =AF23-AI23 -> 0.0016203704 | AK23: =VLOOKUP($D23,Construction!$B:$J,(COLUMN(Construction_BuildingCost_Stone)-COLUMN(Construction_Name_and_Level)+1),FALSE)*(-1) -> 0 | AL23: =VLOOKUP($D23,Construction!$B:$J,(COLUMN(Construction_BuildingCost_Wood)-COLUMN(Construction_Name_and_Level)+1),FALSE)*(-1) -> -170 | AM23: =VLOOKUP($D23,Construction!$B:$J,(COLUMN(Construction_BuildingCost_Ore)-COLUMN(Construction_Name_and_Level)+1),FALSE)*(-1) -> -170 | AN23: =VLOOKUP($D23,Construction!$B:$J,(COLUMN(Construction_BuildingCost_Food)-COLUMN(Construction_Name_and_Level)+1),FALSE)*(-1) -> -170
B24: Construction | C24: by Quest | D24: Mine 2 | E24: 8 | F24: 0 | G24: =VLOOKUP($D24,Construction!$B:$E,(COLUMN(Construction_BuildingReward_HeroXP)-COLUMN(Construction_Name_and_Level)+1),FALSE) -> 25 | H24: =G24*(1+F24) -> 25 | J24: =VLOOKUP($D24,Construction!$B:$F,(COLUMN(Construction_BuildingReward_Power)-COLUMN(Construction_Name_and_Level)+1),FALSE) -> 10 | O24: 0.0034722222 | P24: 0.0055555556 | AD24: =AD23+(Q$3*Q24+R$3*R24+S$3*S24+T$3*T24+U$3*U24+V$3*V24+W$3*W24+X$3*X24+Y$3*Y24+Z$3*Z24+AA$3*AA24) -> #REF! | AE24: 0.01 | AF24: =VLOOKUP($D24,Construction!$B:$C,(COLUMN(Construction_Time)-COLUMN(Construction_Name_and_Level)+1),FALSE) -> 0.0018518519 | AG24: =AF24/(1+AE24) -> 0.0018335167 | AH24: =(Q$3*Q24+R$3*R24+T$3*T24+U$3*U24+V$3*V24+W$3*W24+X$3*X24+Y$3*Y24+Z$3*Z24+AA$3*AA24)*(-1) -> 0 | AI24: =IF((AG24-O24-P24-AH24)>=0,AG24-O24-P24-AH24,0) -> 0 | AJ24: =AF24-AI24 -> 0.0018518519 | AK24: =VLOOKUP($D24,Construction!$B:$J,(COLUMN(Construction_BuildingCost_Stone)-COLUMN(Construction_Name_and_Level)+1),FALSE)*(-1) -> -170 | AL24: =VLOOKUP($D24,Construction!$B:$J,(COLUMN(Construction_BuildingCost_Wood)-COLUMN(Construction_Name_and_Level)+1),FALSE)*(-1) -> -170 | AM24: =VLOOKUP($D24,Construction!$B:$J,(COLUMN(Construction_BuildingCost_Ore)-COLUMN(Construction_Name_and_Level)+1),FALSE)*(-1) -> 0 | AN24: =VLOOKUP($D24,Construction!$B:$J,(COLUMN(Construction_BuildingCost_Food)-COLUMN(Construction_Name_and_Level)+1),FALSE)*(-1) -> -170
B25: Construction | C25: by Quest | D25: Villa 3 | E25: 8 | F25: 0 | G25: =VLOOKUP($D25,Construction!$B:$E,(COLUMN(Construction_BuildingReward_HeroXP)-COLUMN(Construction_Name_and_Level)+1),FALSE) -> 50 | H25: =G25*(1+F25) -> 50 | J25: =VLOOKUP($D25,Construction!$B:$F,(COLUMN(Construction_BuildingReward_Power)-COLUMN(Construction_Name_and_Level)+1),FALSE) -> 40 | O25: 0.0034722222 | P25: 0.0055555556 | AD25: =AD24+(Q$3*Q25+R$3*R25+S$3*S25+T$3*T25+U$3*U25+V$3*V25+W$3*W25+X$3*X25+Y$3*Y25+Z$3*Z25+AA$3*AA25) -> #REF! | AE25: 0.01 | AF25: =VLOOKUP($D25,Construction!$B:$C,(COLUMN(Construction_Time)-COLUMN(Construction_Name_and_Level)+1),FALSE) -> 0.0023148148 | AG25: =AF25/(1+AE25) -> 0.0022918959 | AH25: =(Q$3*Q25+R$3*R25+T$3*T25+U$3*U25+V$3*V25+W$3*W25+X$3*X25+Y$3*Y25+Z$3*Z25+AA$3*AA25)*(-1) -> 0 | AI25: =IF((AG25-O25-P25-AH25)>=0,AG25-O25-P25-AH25,0) -> 0 | AJ25: =AF25-AI25 -> 0.0023148148 | AK25: =VLOOKUP($D25,Construction!$B:$J,(COLUMN(Construction_BuildingCost_Stone)-COLUMN(Construction_Name_and_Level)+1),FALSE)*(-1) -> -578 | AL25: =VLOOKUP($D25,Construction!$B:$J,(COLUMN(Construction_BuildingCost_Wood)-COLUMN(Construction_Name_and_Level)+1),FALSE)*(-1) -> -578 | AM25: =VLOOKUP($D25,Construction!$B:$J,(COLUMN(Construction_BuildingCost_Ore)-COLUMN(Construction_Name_and_Level)+1),FALSE)*(-1) -> -145 | AN25: =VLOOKUP($D25,Construction!$B:$J,(COLUMN(Construction_BuildingCost_Food)-COLUMN(Construction_Name_and_Level)+1),FALSE)*(-1) -> -1445
... B32: Construction | C32: at Will | D32: Academy 3 | E32: 8 | F32: 0 | G32: =VLOOKUP($D32,Construction!$B:$E,(COLUMN(Construction_BuildingReward_HeroXP)-COLUMN(Construction_Name_and_Level)+1),FALSE) -> 50 | H32: =G32*(1+F32) -> 50 | J32: =VLOOKUP($D32,Construction!$B:$F,(COLUMN(Construction_BuildingReward_Power)-COLUMN(Construction_Name_and_Level)+1),FALSE) -> 105 | O32: 0.0034722222 | P32: 0.0055555556 | AD32: =AD31+(Q$3*Q32+R$3*R32+S$3*S32+T$3*T32+U$3*U32+V$3*V32+W$3*W32+X$3*X32+Y$3*Y32+Z$3*Z32+AA$3*AA32) -> #REF! | AE32: 0.01 | AF32: =VLOOKUP($D32,Construction!$B:$C,(COLUMN(Construction_Time)-COLUMN(Construction_Name_and_Level)+1),FALSE) -> 0.0046296296 | AG32: =AF32/(1+AE32) -> 0.0045837917 | AH32: =(Q$3*Q32+R$3*R32+T$3*T32+U$3*U32+V$3*V32+W$3*W32+X$3*X32+Y$3*Y32+Z$3*Z32+AA$3*AA32)*(-1) -> 0 | AI32: =IF((AG32-O32-P32-AH32)>=0,AG32-O32-P32-AH32,0) -> 0 | AJ32: =AF32-AI32 -> 0.0046296296 | AK32: =VLOOKUP($D32,Construction!$B:$J,(COLUMN(Construction_BuildingCost_Stone)-COLUMN(Construction_Name_and_Level)+1),FALSE)*(-1) -> -1620 | AL32: =VLOOKUP($D32,Construction!$B:$J,(COLUMN(Construction_BuildingCost_Wood)-COLUMN(Construction_Name_and_Level)+1),FALSE)*(-1) -> -1620 | AM32: =VLOOKUP($D32,Construction!$B:$J,(COLUMN(Construction_BuildingCost_Ore)-COLUMN(Construction_Name_and_Level)+1),FALSE)*(-1) -> -648 | AN32: =VLOOKUP($D32,Construction!$B:$J,(COLUMN(Construction_BuildingCost_Food)-COLUMN(Construction_Name_and_Level)+1),FALSE)*(-1) -> -972
B33: Construction | C33: at Will | D33: Academy 1 | E33: 8 | F33: 0 | G33: =VLOOKUP($D33,Construction!$B:$E,(COLUMN(Construction_BuildingReward_HeroXP)-COLUMN(Construction_Name_and_Level)+1),FALSE) -> 10 | H33: =G33*(1+F33) -> 10 | J33: =VLOOKUP($D33,Construction!$B:$F,(COLUMN(Construction_BuildingReward_Power)-COLUMN(Construction_Name_and_Level)+1),FALSE) -> 35 | O33: 0.0034722222 | P33: 0.0055555556 | AD33: =#REF!+(Q$3*Q33+R$3*R33+S$3*S33+T$3*T33+U$3*U33+V$3*V33+W$3*W33+X$3*X33+Y$3*Y33+Z$3*Z33+AA$3*AA33) -> #REF! | AE33: 0.01 | AF33: =VLOOKUP($D33,Construction!$B:$C,(COLUMN(Construction_Time)-COLUMN(Construction_Name_and_Level)+1),FALSE) -> 0.0011574074 | AG33: =AF33/(1+AE33) -> 0.0011459479 | AH33: =(Q$3*Q33+R$3*R33+T$3*T33+U$3*U33+V$3*V33+W$3*W33+X$3*X33+Y$3*Y33+Z$3*Z33+AA$3*AA33)*(-1) -> 0 | AI33: =IF((AG33-O33-P33-AH33)>=0,AG33-O33-P33-AH33,0) -> 0 | AJ33: =AF33-AI33 -> 0.0011574074 | AK33: =VLOOKUP($D33,Construction!$B:$J,(COLUMN(Construction_BuildingCost_Stone)-COLUMN(Construction_Name_and_Level)+1),FALSE)*(-1) -> -500 | AL33: =VLOOKUP($D33,Construction!$B:$J,(COLUMN(Construction_BuildingCost_Wood)-COLUMN(Construction_Name_and_Level)+1),FALSE)*(-1) -> -500 | AM33: =VLOOKUP($D33,Construction!$B:$J,(COLUMN(Construction_BuildingCost_Ore)-COLUMN(Construction_Name_and_Level)+1),FALSE)*(-1) -> -200 | AN33: =VLOOKUP($D33,Construction!$B:$J,(COLUMN(Construction_BuildingCost_Food)-COLUMN(Construction_Name_and_Level)+1),FALSE)*(-1) -> -300
B34: Construction | C34: at Will | D34: Academy 2 | E34: 8 | F34: 0 | G34: =VLOOKUP($D34,Construction!$B:$E,(COLUMN(Construction_BuildingReward_HeroXP)-COLUMN(Construction_Name_and_Level)+1),FALSE) -> 25 | H34: =G34*(1+F34) -> 25 | J34: =VLOOKUP($D34,Construction!$B:$F,(COLUMN(Construction_BuildingReward_Power)-COLUMN(Construction_Name_and_Level)+1),FALSE) -> 70 | O34: 0.0034722222 | P34: 0.0055555556 | AD34: =AD33+(Q$3*Q34+R$3*R34+S$3*S34+T$3*T34+U$3*U34+V$3*V34+W$3*W34+X$3*X34+Y$3*Y34+Z$3*Z34+AA$3*AA34) -> #REF! | AE34: 0.01 | AF34: =VLOOKUP($D34,Construction!$B:$C,(COLUMN(Construction_Time)-COLUMN(Construction_Name_and_Level)+1),FALSE) -> 0.0023148148 | AG34: =AF34/(1+AE34) -> 0.0022918959 | AH34: =(Q$3*Q34+R$3*R34+T$3*T34+U$3*U34+V$3*V34+W$3*W34+X$3*X34+Y$3*Y34+Z$3*Z34+AA$3*AA34)*(-1) -> 0 | AI34: =IF((AG34-O34-P34-AH34)>=0,AG34-O34-P34-AH34,0) -> 0 | AJ34: =AF34-AI34 -> 0.0023148148 | AK34: =VLOOKUP($D34,Construction!$B:$J,(COLUMN(Construction_BuildingCost_Stone)-COLUMN(Construction_Name_and_Level)+1),FALSE)*(-1) -> -900 | AL34: =VLOOKUP($D34,Construction!$B:$J,(COLUMN(Construction_BuildingCost_Wood)-COLUMN(Construction_Name_and_Level)+1),FALSE)*(-1) -> -900 | AM34: =VLOOKUP($D34,Construction!$B:$J,(COLUMN(Construction_BuildingCost_Ore)-COLUMN(Construction_Name_and_Level)+1),FALSE)*(-1) -> -360 | AN34: =VLOOKUP($D34,Construction!$B:$J,(COLUMN(Construction_BuildingCost_Food)-COLUMN(Construction_Name_and_Level)+1),FALSE)*(-1) -> -540
B35: Construction | C35: at Will | D35: Academy 3 | E35: 8 | F35: 0 | G35: =VLOOKUP($D35,Construction!$B:$E,(COLUMN(Construction_BuildingReward_HeroXP)-COLUMN(Construction_Name_and_Level)+1),FALSE) -> 50 | H35: =G35*(1+F35) -> 50 | J35: =VLOOKUP($D35,Construction!$B:$F,(COLUMN(Construction_BuildingReward_Power)-COLUMN(Construction_Name_and_Level)+1),FALSE) -> 105 | O35: 0.0034722222 | P35: 0.0055555556 | AD35: =AD34+(Q$3*Q35+R$3*R35+S$3*S35+T$3*T35+U$3*U35+V$3*V35+W$3*W35+X$3*X35+Y$3*Y35+Z$3*Z35+AA$3*AA35) -> #REF! | AE35: 0.01 | AF35: =VLOOKUP($D35,Construction!$B:$C,(COLUMN(Construction_Time)-COLUMN(Construction_Name_and_Level)+1),FALSE) -> 0.0046296296 | AG35: =AF35/(1+AE35) -> 0.0045837917 | AH35: =(Q$3*Q35+R$3*R35+T$3*T35+U$3*U35+V$3*V35+W$3*W35+X$3*X35+Y$3*Y35+Z$3*Z35+AA$3*AA35)*(-1) -> 0 | AI35: =IF((AG35-O35-P35-AH35)>=0,AG35-O35-P35-AH35,0) -> 0 | AJ35: =AF35-AI35 -> 0.0046296296 | AK35: =VLOOKUP($D35,Construction!$B:$J,(COLUMN(Construction_BuildingCost_Stone)-COLUMN(Construction_Name_and_Level)+1),FALSE)*(-1) -> -1620 | AL35: =VLOOKUP($D35,Construction!$B:$J,(COLUMN(Construction_BuildingCost_Wood)-COLUMN(Construction_Name_and_Level)+1),FALSE)*(-1) -> -1620 | AM35: =VLOOKUP($D35,Construction!$B:$J,(COLUMN(Construction_BuildingCost_Ore)-COLUMN(Construction_Name_and_Level)+1),FALSE)*(-1) -> -648 | AN35: =VLOOKUP($D35,Construction!$B:$J,(COLUMN(Construction_BuildingCost_Food)-COLUMN(Construction_Name_and_Level)+1),FALSE)*(-1) -> -972
B36: Construction | C36: at Will | D36: Hospital 1 | E36: 8 | F36: 0 | G36: =VLOOKUP($D36,Construction!$B:$E,(COLUMN(Construction_BuildingReward_HeroXP)-COLUMN(Construction_Name_and_Level)+1),FALSE) -> 10 | H36: =G36*(1+F36) -> 10 | J36: =VLOOKUP($D36,Construction!$B:$F,(COLUMN(Construction_BuildingReward_Power)-COLUMN(Construction_Name_and_Level)+1),FALSE) -> 10 | O36: 0.0034722222 | P36: 0.0055555556 | AD36: =#REF!+(Q$3*Q36+R$3*R36+S$3*S36+T$3*T36+U$3*U36+V$3*V36+W$3*W36+X$3*X36+Y$3*Y36+Z$3*Z36+AA$3*AA36) -> #REF! | AE36: 0.01 | AF36: =VLOOKUP($D36,Construction!$B:$C,(COLUMN(Construction_Time)-COLUMN(Construction_Name_and_Level)+1),FALSE) -> 0.0010416667 | AG36: =AF36/(1+AE36) -> 0.0010313531 | AH36: =(Q$3*Q36+R$3*R36+T$3*T36+U$3*U36+V$3*V36+W$3*W36+X$3*X36+Y$3*Y36+Z$3*Z36+AA$3*AA36)*(-1) -> 0 | AI36: =IF((AG36-O36-P36-AH36)>=0,AG36-O36-P36-AH36,0) -> 0 | AJ36: =AF36-AI36 -> 0.0010416667 | AK36: =VLOOKUP($D36,Construction!$B:$J,(COLUMN(Construction_BuildingCost_Stone)-COLUMN(Construction_Name_and_Level)+1),FALSE)*(-1) -> -500 | AL36: =VLOOKUP($D36,Construction!$B:$J,(COLUMN(Construction_BuildingCost_Wood)-COLUMN(Construction_Name_and_Level)+1),FALSE)*(-1) -> -400 | AM36: =VLOOKUP($D36,Construction!$B:$J,(COLUMN(Construction_BuildingCost_Ore)-COLUMN(Construction_Name_and_Level)+1),FALSE)*(-1) -> -300 | AN36: =VLOOKUP($D36,Construction!$B:$J,(COLUMN(Construction_BuildingCost_Food)-COLUMN(Construction_Name_and_Level)+1),FALSE)*(-1) -> -250
B37: Construction | C37: at Will | D37: Hospital 2 | E37: 8 | F37: 0 | G37: =VLOOKUP($D37,Construction!$B:$E,(COLUMN(Construction_BuildingReward_HeroXP)-COLUMN(Construction_Name_and_Level)+1),FALSE) -> 25 | H37: =G37*(1+F37) -> 25 | J37: =VLOOKUP($D37,Construction!$B:$F,(COLUMN(Construction_BuildingReward_Power)-COLUMN(Construction_Name_and_Level)+1),FALSE) -> 20 | O37: 0.0034722222 | P37: 0.0055555556 | AD37: =AD36+(Q$3*Q37+R$3*R37+S$3*S37+T$3*T37+U$3*U37+V$3*V37+W$3*W37+X$3*X37+Y$3*Y37+Z$3*Z37+AA$3*AA37) -> #REF! | AE37: 0.01 | AF37: =VLOOKUP($D37,Construction!$B:$C,(COLUMN(Construction_Time)-COLUMN(Construction_Name_and_Level)+1),FALSE) -> 0.0020833333 | AG37: =AF37/(1+AE37) -> 0.0020627063 | AH37: =(Q$3*Q37+R$3*R37+T$3*T37+U$3*U37+V$3*V37+W$3*W37+X$3*X37+Y$3*Y37+Z$3*Z37+AA$3*AA37)*(-1) -> 0 | AI37: =IF((AG37-O37-P37-AH37)>=0,AG37-O37-P37-AH37,0) -> 0 | AJ37: =AF37-AI37 -> 0.0020833333 | AK37: =VLOOKUP($D37,Construction!$B:$J,(COLUMN(Construction_BuildingCost_Stone)-COLUMN(Construction_Name_and_Level)+1),FALSE)*(-1) -> -850 | AL37: =VLOOKUP($D37,Construction!$B:$J,(COLUMN(Construction_BuildingCost_Wood)-COLUMN(Construction_Name_and_Level)+1),FALSE)*(-1) -> -680 | AM37: =VLOOKUP($D37,Construction!$B:$J,(COLUMN(Construction_BuildingCost_Ore)-COLUMN(Construction_Name_and_Level)+1),FALSE)*(-1) -> -510 | AN37: =VLOOKUP($D37,Construction!$B:$J,(COLUMN(Construction_BuildingCost_Food)-COLUMN(Construction_Name_and_Level)+1),FALSE)*(-1) -> -425
B38: Construction | C38: by Quest | D38: Logging Camp 1 | E38: 8 | F38: 0 | G38: =VLOOKUP($D38,Construction!$B:$E,(COLUMN(Construction_BuildingReward_HeroXP)-COLUMN(Construction_Name_and_Level)+1),FALSE) -> 10 | H38: =G38*(1+F38) -> 10 | J38: =VLOOKUP($D38,Construction!$B:$F,(COLUMN(Construction_BuildingReward_Power)-COLUMN(Construction_Name_and_Level)+1),FALSE) -> 5 | O38: 0.0034722222 | P38: 0.0055555556 | AD38: =AD37+(Q$3*Q38+R$3*R38+S$3*S38+T$3*T38+U$3*U38+V$3*V38+W$3*W38+X$3*X38+Y$3*Y38+Z$3*Z38+AA$3*AA38) -> #REF! | AE38: 0.01 | AF38: =VLOOKUP($D38,Construction!$B:$C,(COLUMN(Construction_Time)-COLUMN(Construction_Name_and_Level)+1),FALSE) -> 0.00069444444 | AG38: =AF38/(1+AE38) -> 0.00068756876 | AH38: =(Q$3*Q38+R$3*R38+T$3*T38+U$3*U38+V$3*V38+W$3*W38+X$3*X38+Y$3*Y38+Z$3*Z38+AA$3*AA38)*(-1) -> 0 | AI38: =IF((AG38-O38-P38-AH38)>=0,AG38-O38-P38-AH38,0) -> 0 | AJ38: =AF38-AI38 -> 0.00069444444 | AK38: =VLOOKUP($D38,Construction!$B:$J,(COLUMN(Construction_BuildingCost_Stone)-COLUMN(Construction_Name_and_Level)+1),FALSE)*(-1) -> -100 | AL38: =VLOOKUP($D38,Construction!$B:$J,(COLUMN(Construction_BuildingCost_Wood)-COLUMN(Construction_Name_and_Level)+1),FALSE)*(-1) -> 0 | AM38: =VLOOKUP($D38,Construction!$B:$J,(COLUMN(Construction_BuildingCost_Ore)-COLUMN(Construction_Name_and_Level)+1),FALSE)*(-1) -> -100 | AN38: =VLOOKUP($D38,Construction!$B:$J,(COLUMN(Construction_BuildingCost_Food)-COLUMN(Construction_Name_and_Level)+1),FALSE)*(-1) -> -100
B39: Construction | C39: by Quest | D39: Logging Camp 1 | E39: 8 | F39: 0 | G39: =VLOOKUP($D39,Construction!$B:$E,(COLUMN(Construction_BuildingReward_HeroXP)-COLUMN(Construction_Name_and_Level)+1),FALSE) -> 10 | H39: =G39*(1+F39) -> 10 | J39: =VLOOKUP($D39,Construction!$B:$F,(COLUMN(Construction_BuildingReward_Power)-COLUMN(Construction_Name_and_Level)+1),FALSE) -> 5 | O39: 0.0034722222 | P39: 0.0055555556 | AD39: =AD38+(Q$3*Q39+R$3*R39+S$3*S39+T$3*T39+U$3*U39+V$3*V39+W$3*W39+X$3*X39+Y$3*Y39+Z$3*Z39+AA$3*AA39) -> #REF! | AE39: 0.01 | AF39: =VLOOKUP($D39,Construction!$B:$C,(COLUMN(Construction_Time)-COLUMN(Construction_Name_and_Level)+1),FALSE) -> 0.00069444444 | AG39: =AF39/(1+AE39) -> 0.00068756876 | AH39: =(Q$3*Q39+R$3*R39+T$3*T39+U$3*U39+V$3*V39+W$3*W39+X$3*X39+Y$3*Y39+Z$3*Z39+AA$3*AA39)*(-1) -> 0 | AI39: =IF((AG39-O39-P39-AH39)>=0,AG39-O39-P39-AH39,0) -> 0 | AJ39: =AF39-AI39 -> 0.00069444444 | AK39: =VLOOKUP($D39,Construction!$B:$J,(COLUMN(Construction_BuildingCost_Stone)-COLUMN(Construction_Name_and_Level)+1),FALSE)*(-1) -> -100 | AL39: =VLOOKUP($D39,Construction!$B:$J,(COLUMN(Construction_BuildingCost_Wood)-COLUMN(Construction_Name_and_Level)+1),FALSE)*(-1) -> 0 | AM39: =VLOOKUP($D39,Construction!$B:$J,(COLUMN(Construction_BuildingCost_Ore)-COLUMN(Construction_Name_and_Level)+1),FALSE)*(-1) -> -100 | AN39: =VLOOKUP($D39,Construction!$B:$J,(COLUMN(Construction_BuildingCost_Food)-COLUMN(Construction_Name_and_Level)+1),FALSE)*(-1) -> -100
B40: Construction | C40: by Quest | D40: Logging Camp 1 | E40: 8 | F40: 0 | G40: =VLOOKUP($D40,Construction!$B:$E,(COLUMN(Construction_BuildingReward_HeroXP)-COLUMN(Construction_Name_and_Level)+1),FALSE) -> 10 | H40: =G40*(1+F40) -> 10 | J40: =VLOOKUP($D40,Construction!$B:$F,(COLUMN(Construction_BuildingReward_Power)-COLUMN(Construction_Name_and_Level)+1),FALSE) -> 5 | O40: 0.0034722222 | P40: 0.0055555556 | AD40: =AD39+(Q$3*Q40+R$3*R40+S$3*S40+T$3*T40+U$3*U40+V$3*V40+W$3*W40+X$3*X40+Y$3*Y40+Z$3*Z40+AA$3*AA40) -> #REF! | AE40: 0.01 | AF40: =VLOOKUP($D40,Construction!$B:$C,(COLUMN(Construction_Time)-COLUMN(Construction_Name_and_Level)+1),FALSE) -> 0.00069444444 | AG40: =AF40/(1+AE40) -> 0.00068756876 | AH40: =(Q$3*Q40+R$3*R40+T$3*T40+U$3*U40+V$3*V40+W$3*W40+X$3*X40+Y$3*Y40+Z$3*Z40+AA$3*AA40)*(-1) -> 0 | AI40: =IF((AG40-O40-P40-AH40)>=0,AG40-O40-P40-AH40,0) -> 0 | AJ40: =AF40-AI40 -> 0.00069444444 | AK40: =VLOOKUP($D40,Construction!$B:$J,(COLUMN(Construction_BuildingCost_Stone)-COLUMN(Construction_Name_and_Level)+1),FALSE)*(-1) -> -100 | AL40: =VLOOKUP($D40,Construction!$B:$J,(COLUMN(Construction_BuildingCost_Wood)-COLUMN(Construction_Name_and_Level)+1),FALSE)*(-1) -> 0 | AM40: =VLOOKUP($D40,Construction!$B:$J,(COLUMN(Construction_BuildingCost_Ore)-COLUMN(Construction_Name_and_Level)+1),FALSE)*(-1) -> -100 | AN40: =VLOOKUP($D40,Construction!$B:$J,(COLUMN(Construction_BuildingCost_Food)-COLUMN(Construction_Name_and_Level)+1),FALSE)*(-1) -> -100
B41: Construction | C41: by Quest | D41: Forge 2 | E41: 10 | F41: 0 | G41: =VLOOKUP($D41,Construction!$B:$E,(COLUMN(Construction_BuildingReward_HeroXP)-COLUMN(Construction_Name_and_Level)+1),FALSE) -> 25 | H41: =G41*(1+F41) -> 25 | J41: =VLOOKUP($D41,Construction!$B:$F,(COLUMN(Construction_BuildingReward_Power)-COLUMN(Construction_Name_and_Level)+1),FALSE) -> 25 | O41: 0.0034722222 | P41: 0.0055555556 | AD41: =AD40+(Q$3*Q41+R$3*R41+S$3*S41+T$3*T41+U$3*U41+V$3*V41+W$3*W41+X$3*X41+Y$3*Y41+Z$3*Z41+AA$3*AA41) -> #REF! | AE41: 0.1 | AF41: =VLOOKUP($D41,Construction!$B:$C,(COLUMN(Construction_Time)-COLUMN(Construction_Name_and_Level)+1),FALSE) -> 0.0017361111 | AG41: =AF41/(1+AE41) -> 0.0015782828 | AH41: =(Q$3*Q41+R$3*R41+T$3*T41+U$3*U41+V$3*V41+W$3*W41+X$3*X41+Y$3*Y41+Z$3*Z41+AA$3*AA41)*(-1) -> 0 | AI41: =IF((AG41-O41-P41-AH41)>=0,AG41-O41-P41-AH41,0) -> 0 | AJ41: =AF41-AI41 -> 0.0017361111 | AK41: =VLOOKUP($D41,Construction!$B:$J,(COLUMN(Construction_BuildingCost_Stone)-COLUMN(Construction_Name_and_Level)+1),FALSE)*(-1) -> -510 | AL41: =VLOOKUP($D41,Construction!$B:$J,(COLUMN(Construction_BuildingCost_Wood)-COLUMN(Construction_Name_and_Level)+1),FALSE)*(-1) -> -680 | AM41: =VLOOKUP($D41,Construction!$B:$J,(COLUMN(Construction_BuildingCost_Ore)-COLUMN(Construction_Name_and_Level)+1),FALSE)*(-1) -> -1360 | AN41: =VLOOKUP($D41,Construction!$B:$J,(COLUMN(Construction_BuildingCost_Food)-COLUMN(Construction_Name_and_Level)+1),FALSE)*(-1) -> -510
B42: Construction | C42: at Will | D42: Quarry 3 | E42: 10 | F42: 0 | G42: =VLOOKUP($D42,Construction!$B:$E,(COLUMN(Construction_BuildingReward_HeroXP)-COLUMN(Construction_Name_and_Level)+1),FALSE) -> 50 | H42: =G42*(1+F42) -> 50 | J42: =VLOOKUP($D42,Construction!$B:$F,(COLUMN(Construction_BuildingReward_Power)-COLUMN(Construction_Name_and_Level)+1),FALSE) -> 15 | O42: 0.0034722222 | P42: 0.0055555556 | AD42: =AD41+(Q$3*Q42+R$3*R42+S$3*S42+T$3*T42+U$3*U42+V$3*V42+W$3*W42+X$3*X42+Y$3*Y42+Z$3*Z42+AA$3*AA42) -> #REF! | AE42: 0.1 | AF42: =VLOOKUP($D42,Construction!$B:$C,(COLUMN(Construction_Time)-COLUMN(Construction_Name_and_Level)+1),FALSE) -> 0.0032407407 | AG42: =AF42/(1+AE42) -> 0.0029461279 | AH42: =(Q$3*Q42+R$3*R42+T$3*T42+U$3*U42+V$3*V42+W$3*W42+X$3*X42+Y$3*Y42+Z$3*Z42+AA$3*AA42)*(-1) -> 0 | AI42: =IF((AG42-O42-P42-AH42)>=0,AG42-O42-P42-AH42,0) -> 0 | AJ42: =AF42-AI42 -> 0.0032407407 | AK42: =VLOOKUP($D42,Construction!$B:$J,(COLUMN(Construction_BuildingCost_Stone)-COLUMN(Construction_Name_and_Level)+1),FALSE)*(-1) -> 0 | AL42: =VLOOKUP($D42,Construction!$B:$J,(COLUMN(Construction_BuildingCost_Wood)-COLUMN(Construction_Name_and_Level)+1),FALSE)*(-1) -> -289 | AM42: =VLOOKUP($D42,Construction!$B:$J,(COLUMN(Construction_BuildingCost_Ore)-COLUMN(Construction_Name_and_Level)+1),FALSE)*(-1) -> -289 | AN42: =VLOOKUP($D42,Construction!$B:$J,(COLUMN(Construction_BuildingCost_Food)-COLUMN(Construction_Name_and_Level)+1),FALSE)*(-1) -> -289
B43: Construction | C43: at Will | D43: Mine 3 | E43: 10 | F43: 0 | G43: =VLOOKUP($D43,Construction!$B:$E,(COLUMN(Construction_BuildingReward_HeroXP)-COLUMN(Construction_Name_and_Level)+1),FALSE) -> 50 | H43: =G43*(1+F43) -> 50 | J43: =VLOOKUP($D43,Construction!$B:$F,(COLUMN(Construction_BuildingReward_Power)-COLUMN(Construction_Name_and_Level)+1),FALSE) -> 15 | O43: 0.0034722222 | P43: 0.0055555556 | AD43: =AD42+(Q$3*Q43+R$3*R43+S$3*S43+T$3*T43+U$3*U43+V$3*V43+W$3*W43+X$3*X43+Y$3*Y43+Z$3*Z43+AA$3*AA43) -> #REF! | AE43: 0.1 | AF43: =VLOOKUP($D43,Construction!$B:$C,(COLUMN(Construction_Time)-COLUMN(Construction_Name_and_Level)+1),FALSE) -> 0.0037037037 | AG43: =AF43/(1+AE43) -> 0.0033670034 | AH43: =(Q$3*Q43+R$3*R43+T$3*T43+U$3*U43+V$3*V43+W$3*W43+X$3*X43+Y$3*Y43+Z$3*Z43+AA$3*AA43)*(-1) -> 0 | AI43: =IF((AG43-O43-P43-AH43)>=0,AG43-O43-P43-AH43,0) -> 0 | AJ43: =AF43-AI43 -> 0.0037037037 | AK43: =VLOOKUP($D43,Construction!$B:$J,(COLUMN(Construction_BuildingCost_Stone)-COLUMN(Construction_Name_and_Level)+1),FALSE)*(-1) -> -289 | AL43: =VLOOKUP($D43,Construction!$B:$J,(COLUMN(Construction_BuildingCost_Wood)-COLUMN(Construction_Name_and_Level)+1),FALSE)*(-1) -> -289 | AM43: =VLOOKUP($D43,Construction!$B:$J,(COLUMN(Construction_BuildingCost_Ore)-COLUMN(Construction_Name_and_Level)+1),FALSE)*(-1) -> 0 | AN43: =VLOOKUP($D43,Construction!$B:$J,(COLUMN(Construction_BuildingCost_Food)-COLUMN(Construction_Name_and_Level)+1),FALSE)*(-1) -> -289
B44: Construction | C44: at Will | D44: Mine 4 | E44: 10 | F44: 0 | G44: =VLOOKUP($D44,Construction!$B:$E,(COLUMN(Construction_BuildingReward_HeroXP)-COLUMN(Construction_Name_and_Level)+1),FALSE) -> 200 | H44: =G44*(1+F44) -> 200 | J44: =VLOOKUP($D44,Construction!$B:$F,(COLUMN(Construction_BuildingReward_Power)-COLUMN(Construction_Name_and_Level)+1),FALSE) -> 25 | O44: 0.0034722222 | P44: 0.0055555556 | AD44: =AD43+(Q$3*Q44+R$3*R44+S$3*S44+T$3*T44+U$3*U44+V$3*V44+W$3*W44+X$3*X44+Y$3*Y44+Z$3*Z44+AA$3*AA44) -> #REF! | AE44: 0.1 | AF44: =VLOOKUP($D44,Construction!$B:$C,(COLUMN(Construction_Time)-COLUMN(Construction_Name_and_Level)+1),FALSE) -> 0.0074074074 | AG44: =AF44/(1+AE44) -> 0.0067340067 | AH44: =(Q$3*Q44+R$3*R44+T$3*T44+U$3*U44+V$3*V44+W$3*W44+X$3*X44+Y$3*Y44+Z$3*Z44+AA$3*AA44)*(-1) -> 0 | AI44: =IF((AG44-O44-P44-AH44)>=0,AG44-O44-P44-AH44,0) -> 0 | AJ44: =AF44-AI44 -> 0.0074074074 | AK44: =VLOOKUP($D44,Construction!$B:$J,(COLUMN(Construction_BuildingCost_Stone)-COLUMN(Construction_Name_and_Level)+1),FALSE)*(-1) -> -492 | AL44: =VLOOKUP($D44,Construction!$B:$J,(COLUMN(Construction_BuildingCost_Wood)-COLUMN(Construction_Name_and_Level)+1),FALSE)*(-1) -> -492 | AM44: =VLOOKUP($D44,Construction!$B:$J,(COLUMN(Construction_BuildingCost_Ore)-COLUMN(Construction_Name_and_Level)+1),FALSE)*(-1) -> 0 | AN44: =VLOOKUP($D44,Construction!$B:$J,(COLUMN(Construction_BuildingCost_Food)-COLUMN(Construction_Name_and_Level)+1),FALSE)*(-1) -> -492
B45: Construction | C45: at Will | D45: Mine 5 | E45: 10 | F45: 0 | G45: =VLOOKUP($D45,Construction!$B:$E,(COLUMN(Construction_BuildingReward_HeroXP)-COLUMN(Construction_Name_and_Level)+1),FALSE) -> 400 | H45: =G45*(1+F45) -> 400 | J45: =VLOOKUP($D45,Construction!$B:$F,(COLUMN(Construction_BuildingReward_Power)-COLUMN(Construction_Name_and_Level)+1),FALSE) -> 35 | O45: 0.0034722222 | P45: 0.0055555556 | AD45: =AD44+(Q$3*Q45+R$3*R45+S$3*S45+T$3*T45+U$3*U45+V$3*V45+W$3*W45+X$3*X45+Y$3*Y45+Z$3*Z45+AA$3*AA45) -> #REF! | AE45: 0.1 | AF45: =VLOOKUP($D45,Construction!$B:$C,(COLUMN(Construction_Time)-COLUMN(Construction_Name_and_Level)+1),FALSE) -> 0.014814815 | AG45: =AF45/(1+AE45) -> 0.013468013 | AH45: =(Q$3*Q45+R$3*R45+T$3*T45+U$3*U45+V$3*V45+W$3*W45+X$3*X45+Y$3*Y45+Z$3*Z45+AA$3*AA45)*(-1) -> 0 | AI45: =IF((AG45-O45-P45-AH45)>=0,AG45-O45-P45-AH45,0) -> 0.0044402357 | AJ45: =AF45-AI45 -> 0.010374579 | AK45: =VLOOKUP($D45,Construction!$B:$J,(COLUMN(Construction_BuildingCost_Stone)-COLUMN(Construction_Name_and_Level)+1),FALSE)*(-1) -> -837 | AL45: =VLOOKUP($D45,Construction!$B:$J,(COLUMN(Construction_BuildingCost_Wood)-COLUMN(Construction_Name_and_Level)+1),FALSE)*(-1) -> -837 | AM45: =VLOOKUP($D45,Construction!$B:$J,(COLUMN(Construction_BuildingCost_Ore)-COLUMN(Construction_Name_and_Level)+1),FALSE)*(-1) -> 0 | AN45: =VLOOKUP($D45,Construction!$B:$J,(COLUMN(Construction_BuildingCost_Food)-COLUMN(Construction_Name_and_Level)+1),FALSE)*(-1) -> -837
B46: Construction | C46: by Quest | D46: Mine 1 | E46: 10 | F46: 0 | G46: =VLOOKUP($D46,Construction!$B:$E,(COLUMN(Construction_BuildingReward_HeroXP)-COLUMN(Construction_Name_and_Level)+1),FALSE) -> 10 | H46: =G46*(1+F46) -> 10 | J46: =VLOOKUP($D46,Construction!$B:$F,(COLUMN(Construction_BuildingReward_Power)-COLUMN(Construction_Name_and_Level)+1),FALSE) -> 5 | O46: 0.0034722222 | P46: 0.0055555556 | AD46: =AD45+(Q$3*Q46+R$3*R46+S$3*S46+T$3*T46+U$3*U46+V$3*V46+W$3*W46+X$3*X46+Y$3*Y46+Z$3*Z46+AA$3*AA46) -> #REF! | AE46: 0.1 | AF46: =VLOOKUP($D46,Construction!$B:$C,(COLUMN(Construction_Time)-COLUMN(Construction_Name_and_Level)+1),FALSE) -> 0.00069444444 | AG46: =AF46/(1+AE46) -> 0.00063131313 | AH46: =(Q$3*Q46+R$3*R46+T$3*T46+U$3*U46+V$3*V46+W$3*W46+X$3*X46+Y$3*Y46+Z$3*Z46+AA$3*AA46)*(-1) -> 0 | AI46: =IF((AG46-O46-P46-AH46)>=0,AG46-O46-P46-AH46,0) -> 0 | AJ46: =AF46-AI46 -> 0.00069444444 | AK46: =VLOOKUP($D46,Construction!$B:$J,(COLUMN(Construction_BuildingCost_Stone)-COLUMN(Construction_Name_and_Level)+1),FALSE)*(-1) -> -100 | AL46: =VLOOKUP($D46,Construction!$B:$J,(COLUMN(Construction_BuildingCost_Wood)-COLUMN(Construction_Name_and_Level)+1),FALSE)*(-1) -> -100 | AM46: =VLOOKUP($D46,Construction!$B:$J,(COLUMN(Construction_BuildingCost_Ore)-COLUMN(Construction_Name_and_Level)+1),FALSE)*(-1) -> 0 | AN46: =VLOOKUP($D46,Construction!$B:$J,(COLUMN(Construction_BuildingCost_Food)-COLUMN(Construction_Name_and_Level)+1),FALSE)*(-1) -> -100
B47: Construction | C47: by Quest | D47: Mine 1 | E47: 10 | F47: 0 | G47: =VLOOKUP($D47,Construction!$B:$E,(COLUMN(Construction_BuildingReward_HeroXP)-COLUMN(Construction_Name_and_Level)+1),FALSE) -> 10 | H47: =G47*(1+F47) -> 10 | J47: =VLOOKUP($D47,Construction!$B:$F,(COLUMN(Construction_BuildingReward_Power)-COLUMN(Construction_Name_and_Level)+1),FALSE) -> 5 | O47: 0.0034722222 | P47: 0.0055555556 | AD47: =AD46+(Q$3*Q47+R$3*R47+S$3*S47+T$3*T47+U$3*U47+V$3*V47+W$3*W47+X$3*X47+Y$3*Y47+Z$3*Z47+AA$3*AA47) -> #REF! | AE47: 0.1 | AF47: =VLOOKUP($D47,Construction!$B:$C,(COLUMN(Construction_Time)-COLUMN(Construction_Name_and_Level)+1),FALSE) -> 0.00069444444 | AG47: =AF47/(1+AE47) -> 0.00063131313 | AH47: =(Q$3*Q47+R$3*R47+T$3*T47+U$3*U47+V$3*V47+W$3*W47+X$3*X47+Y$3*Y47+Z$3*Z47+AA$3*AA47)*(-1) -> 0 | AI47: =IF((AG47-O47-P47-AH47)>=0,AG47-O47-P47-AH47,0) -> 0 | AJ47: =AF47-AI47 -> 0.00069444444 | AK47: =VLOOKUP($D47,Construction!$B:$J,(COLUMN(Construction_BuildingCost_Stone)-COLUMN(Construction_Name_and_Level)+1),FALSE)*(-1) -> -100 | AL47: =VLOOKUP($D47,Construction!$B:$J,(COLUMN(Construction_BuildingCost_Wood)-COLUMN(Construction_Name_and_Level)+1),FALSE)*(-1) -> -100 | AM47: =VLOOKUP($D47,Construction!$B:$J,(COLUMN(Construction_BuildingCost_Ore)-COLUMN(Construction_Name_and_Level)+1),FALSE)*(-1) -> 0 | AN47: =VLOOKUP($D47,Construction!$B:$J,(COLUMN(Construction_BuildingCost_Food)-COLUMN(Construction_Name_and_Level)+1),FALSE)*(-1) -> -100
B48: Construction | C48: by Quest | D48: Mine 1 | E48: 10 | F48: 0 | G48: =VLOOKUP($D48,Construction!$B:$E,(COLUMN(Construction_BuildingReward_HeroXP)-COLUMN(Construction_Name_and_Level)+1),FALSE) -> 10 | H48: =G48*(1+F48) -> 10 | J48: =VLOOKUP($D48,Construction!$B:$F,(COLUMN(Construction_BuildingReward_Power)-COLUMN(Construction_Name_and_Level)+1),FALSE) -> 5 | O48: 0.0034722222 | P48: 0.0055555556 | AD48: =AD47+(Q$3*Q48+R$3*R48+S$3*S48+T$3*T48+U$3*U48+V$3*V48+W$3*W48+X$3*X48+Y$3*Y48+Z$3*Z48+AA$3*AA48) -> #REF! | AE48: 0.1 | AF48: =VLOOKUP($D48,Construction!$B:$C,(COLUMN(Construction_Time)-COLUMN(Construction_Name_and_Level)+1),FALSE) -> 0.00069444444 | AG48: =AF48/(1+AE48) -> 0.00063131313 | AH48: =(Q$3*Q48+R$3*R48+T$3*T48+U$3*U48+V$3*V48+W$3*W48+X$3*X48+Y$3*Y48+Z$3*Z48+AA$3*AA48)*(-1) -> 0 | AI48: =IF((AG48-O48-P48-AH48)>=0,AG48-O48-P48-AH48,0) -> 0 | AJ48: =AF48-AI48 -> 0.00069444444 | AK48: =VLOOKUP($D48,Construction!$B:$J,(COLUMN(Construction_BuildingCost_Stone)-COLUMN(Construction_Name_and_Level)+1),FALSE)*(-1) -> -100 | AL48: =VLOOKUP($D48,Construction!$B:$J,(COLUMN(Construction_BuildingCost_Wood)-COLUMN(Construction_Name_and_Level)+1),FALSE)*(-1) -> -100 | AM48: =VLOOKUP($D48,Construction!$B:$J,(COLUMN(Construction_BuildingCost_Ore)-COLUMN(Construction_Name_and_Level)+1),FALSE)*(-1) -> 0 | AN48: =VLOOKUP($D48,Construction!$B:$J,(COLUMN(Construction_BuildingCost_Food)-COLUMN(Construction_Name_and_Level)+1),FALSE)*(-1) -> -100
... B67: Construction | C67: at Will | D67: Walls 4 | E67: 11 | F67: 0.1 | G67: =VLOOKUP($D67,Construction!$B:$E,(COLUMN(Construction_BuildingReward_HeroXP)-COLUMN(Construction_Name_and_Level)+1),FALSE) -> 5000 | H67: =G67*(1+F67) -> 5500 | J67: =VLOOKUP($D67,Construction!$B:$F,(COLUMN(Construction_BuildingReward_Power)-COLUMN(Construction_Name_and_Level)+1),FALSE) -> 150 | O67: 0.0034722222 | P67: 0.0055555556 | AD67: =AD66+(Q$3*Q67+R$3*R67+S$3*S67+T$3*T67+U$3*U67+V$3*V67+W$3*W67+X$3*X67+Y$3*Y67+Z$3*Z67+AA$3*AA67) -> #REF! | AE67: 0.25 | AF67: =VLOOKUP($D67,Construction!$B:$C,(COLUMN(Construction_Time)-COLUMN(Construction_Name_and_Level)+1),FALSE) -> 0.0097222222 | AG67: =AF67/(1+AE67) -> 0.0077777778 | AH67: =(Q$3*Q67+R$3*R67+T$3*T67+U$3*U67+V$3*V67+W$3*W67+X$3*X67+Y$3*Y67+Z$3*Z67+AA$3*AA67)*(-1) -> 0 | AI67: =IF((AG67-O67-P67-AH67)>=0,AG67-O67-P67-AH67,0) -> 0 | AJ67: =AF67-AI67 -> 0.0097222222 | AK67: =VLOOKUP($D67,Construction!$B:$J,(COLUMN(Construction_BuildingCost_Stone)-COLUMN(Construction_Name_and_Level)+1),FALSE)*(-1) -> -5832 | AL67: =VLOOKUP($D67,Construction!$B:$J,(COLUMN(Construction_BuildingCost_Wood)-COLUMN(Construction_Name_and_Level)+1),FALSE)*(-1) -> -4666 | AM67: =VLOOKUP($D67,Construction!$B:$J,(COLUMN(Construction_BuildingCost_Ore)-COLUMN(Construction_Name_and_Level)+1),FALSE)*(-1) -> -1750 | AN67: =VLOOKUP($D67,Construction!$B:$J,(COLUMN(Construction_BuildingCost_Food)-COLUMN(Construction_Name_and_Level)+1),FALSE)*(-1) -> -2916
B68: Construction | C68: at Will | D68: Stronghold 5 | E68: 11 | F68: 0.1 | G68: =VLOOKUP($D68,Construction!$B:$E,(COLUMN(Construction_BuildingReward_HeroXP)-COLUMN(Construction_Name_and_Level)+1),FALSE) -> 10000 | H68: =G68*(1+F68) -> 11000 | J68: =VLOOKUP($D68,Construction!$B:$F,(COLUMN(Construction_BuildingReward_Power)-COLUMN(Construction_Name_and_Level)+1),FALSE) -> 350 | O68: 0.0034722222 | P68: 0.00625 | U68: -4 | AD68: =AD67+(Q$3*Q68+R$3*R68+S$3*S68+T$3*T68+U$3*U68+V$3*V68+W$3*W68+X$3*X68+Y$3*Y68+Z$3*Z68+AA$3*AA68) -> #REF! | AE68: 0.25 | AF68: =VLOOKUP($D68,Construction!$B:$C,(COLUMN(Construction_Time)-COLUMN(Construction_Name_and_Level)+1),FALSE) -> 0.055555556 | AG68: =AF68/(1+AE68) -> 0.044444444 | AH68: =(Q$3*Q68+R$3*R68+T$3*T68+U$3*U68+V$3*V68+W$3*W68+X$3*X68+Y$3*Y68+Z$3*Z68+AA$3*AA68)*(-1) -> 0.041666667 | AI68: =IF((AG68-O68-P68-AH68)>=0,AG68-O68-P68-AH68,0) -> 0 | AJ68: =AF68-AI68 -> 0.055555556 | AK68: =VLOOKUP($D68,Construction!$B:$J,(COLUMN(Construction_BuildingCost_Stone)-COLUMN(Construction_Name_and_Level)+1),FALSE)*(-1) -> -10498 | AL68: =VLOOKUP($D68,Construction!$B:$J,(COLUMN(Construction_BuildingCost_Wood)-COLUMN(Construction_Name_and_Level)+1),FALSE)*(-1) -> -10498 | AM68: =VLOOKUP($D68,Construction!$B:$J,(COLUMN(Construction_BuildingCost_Ore)-COLUMN(Construction_Name_and_Level)+1),FALSE)*(-1) -> -4200 | AN68: =VLOOKUP($D68,Construction!$B:$J,(COLUMN(Construction_BuildingCost_Food)-COLUMN(Construction_Name_and_Level)+1),FALSE)*(-1) -> -5249
B69: Construction | C69: at Will | D69: Gymnos 3 | E69: 11 | F69: 0.1 | G69: =VLOOKUP($D69,Construction!$B:$E,(COLUMN(Construction_BuildingReward_HeroXP)-COLUMN(Construction_Name_and_Level)+1),FALSE) -> 50 | H69: =G69*(1+F69) -> 55 | J69: =VLOOKUP($D69,Construction!$B:$F,(COLUMN(Construction_BuildingReward_Power)-COLUMN(Construction_Name_and_Level)+1),FALSE) -> 40 | O69: 0.0034722222 | P69: 0.00625 | AD69: =AD68+(Q$3*Q69+R$3*R69+S$3*S69+T$3*T69+U$3*U69+V$3*V69+W$3*W69+X$3*X69+Y$3*Y69+Z$3*Z69+AA$3*AA69) -> #REF! | AE69: 0.25 | AF69: =VLOOKUP($D69,Construction!$B:$C,(COLUMN(Construction_Time)-COLUMN(Construction_Name_and_Level)+1),FALSE) -> 0.0046296296 | AG69: =AF69/(1+AE69) -> 0.0037037037 | AH69: =(Q$3*Q69+R$3*R69+T$3*T69+U$3*U69+V$3*V69+W$3*W69+X$3*X69+Y$3*Y69+Z$3*Z69+AA$3*AA69)*(-1) -> 0 | AI69: =IF((AG69-O69-P69-AH69)>=0,AG69-O69-P69-AH69,0) -> 0 | AJ69: =AF69-AI69 -> 0.0046296296 | AK69: =VLOOKUP($D69,Construction!$B:$J,(COLUMN(Construction_BuildingCost_Stone)-COLUMN(Construction_Name_and_Level)+1),FALSE)*(-1) -> -648 | AL69: =VLOOKUP($D69,Construction!$B:$J,(COLUMN(Construction_BuildingCost_Wood)-COLUMN(Construction_Name_and_Level)+1),FALSE)*(-1) -> -324 | AM69: =VLOOKUP($D69,Construction!$B:$J,(COLUMN(Construction_BuildingCost_Ore)-COLUMN(Construction_Name_and_Level)+1),FALSE)*(-1) -> -324 | AN69: =VLOOKUP($D69,Construction!$B:$J,(COLUMN(Construction_BuildingCost_Food)-COLUMN(Construction_Name_and_Level)+1),FALSE)*(-1) -> -972
B70: Construction | C70: at Will | D70: Gymnos 4 | E70: 11 | F70: 0.15 | G70: =VLOOKUP($D70,Construction!$B:$E,(COLUMN(Construction_BuildingReward_HeroXP)-COLUMN(Construction_Name_and_Level)+1),FALSE) -> 200 | H70: =G70*(1+F70) -> 230 | J70: =VLOOKUP($D70,Construction!$B:$F,(COLUMN(Construction_BuildingReward_Power)-COLUMN(Construction_Name_and_Level)+1),FALSE) -> 60 | O70: 0.0034722222 | P70: 0.00625 | AD70: =AD69+(Q$3*Q70+R$3*R70+S$3*S70+T$3*T70+U$3*U70+V$3*V70+W$3*W70+X$3*X70+Y$3*Y70+Z$3*Z70+AA$3*AA70) -> #REF! | AE70: 0.25 | AF70: =VLOOKUP($D70,Construction!$B:$C,(COLUMN(Construction_Time)-COLUMN(Construction_Name_and_Level)+1),FALSE) -> 0.0092592593 | AG70: =AF70/(1+AE70) -> 0.0074074074 | AH70: =(Q$3*Q70+R$3*R70+T$3*T70+U$3*U70+V$3*V70+W$3*W70+X$3*X70+Y$3*Y70+Z$3*Z70+AA$3*AA70)*(-1) -> 0 | AI70: =IF((AG70-O70-P70-AH70)>=0,AG70-O70-P70-AH70,0) -> 0 | AJ70: =AF70-AI70 -> 0.0092592593 | AK70: =VLOOKUP($D70,Construction!$B:$J,(COLUMN(Construction_BuildingCost_Stone)-COLUMN(Construction_Name_and_Level)+1),FALSE)*(-1) -> -1167 | AL70: =VLOOKUP($D70,Construction!$B:$J,(COLUMN(Construction_BuildingCost_Wood)-COLUMN(Construction_Name_and_Level)+1),FALSE)*(-1) -> -584 | AM70: =VLOOKUP($D70,Construction!$B:$J,(COLUMN(Construction_BuildingCost_Ore)-COLUMN(Construction_Name_and_Level)+1),FALSE)*(-1) -> -584 | AN70: =VLOOKUP($D70,Construction!$B:$J,(COLUMN(Construction_BuildingCost_Food)-COLUMN(Construction_Name_and_Level)+1),FALSE)*(-1) -> -1750
B71: Construction | C71: at Will | D71: Villa 4 | E71: 11 | F71: 0.2 | G71: =VLOOKUP($D71,Construction!$B:$E,(COLUMN(Construction_BuildingReward_HeroXP)-COLUMN(Construction_Name_and_Level)+1),FALSE) -> 200 | H71: =G71*(1+F71) -> 240 | J71: =VLOOKUP($D71,Construction!$B:$F,(COLUMN(Construction_BuildingReward_Power)-COLUMN(Construction_Name_and_Level)+1),FALSE) -> 60 | O71: 0.0034722222 | P71: 0.00625 | AD71: =AD70+(Q$3*Q71+R$3*R71+S$3*S71+T$3*T71+U$3*U71+V$3*V71+W$3*W71+X$3*X71+Y$3*Y71+Z$3*Z71+AA$3*AA71) -> #REF! | AE71: 0.25 | AF71: =VLOOKUP($D71,Construction!$B:$C,(COLUMN(Construction_Time)-COLUMN(Construction_Name_and_Level)+1),FALSE) -> 0.0046296296 | AG71: =AF71/(1+AE71) -> 0.0037037037 | AH71: =(Q$3*Q71+R$3*R71+T$3*T71+U$3*U71+V$3*V71+W$3*W71+X$3*X71+Y$3*Y71+Z$3*Z71+AA$3*AA71)*(-1) -> 0 | AI71: =IF((AG71-O71-P71-AH71)>=0,AG71-O71-P71-AH71,0) -> 0 | AJ71: =AF71-AI71 -> 0.0046296296 | AK71: =VLOOKUP($D71,Construction!$B:$J,(COLUMN(Construction_BuildingCost_Stone)-COLUMN(Construction_Name_and_Level)+1),FALSE)*(-1) -> -983 | AL71: =VLOOKUP($D71,Construction!$B:$J,(COLUMN(Construction_BuildingCost_Wood)-COLUMN(Construction_Name_and_Level)+1),FALSE)*(-1) -> -983 | AM71: =VLOOKUP($D71,Construction!$B:$J,(COLUMN(Construction_BuildingCost_Ore)-COLUMN(Construction_Name_and_Level)+1),FALSE)*(-1) -> -247 | AN71: =VLOOKUP($D71,Construction!$B:$J,(COLUMN(Construction_BuildingCost_Food)-COLUMN(Construction_Name_and_Level)+1),FALSE)*(-1) -> -2457
B72: Construction | C72: at Will | D72: Villa 5 | E72: 11 | F72: 0.2 | G72: =VLOOKUP($D72,Construction!$B:$E,(COLUMN(Construction_BuildingReward_HeroXP)-COLUMN(Construction_Name_and_Level)+1),FALSE) -> 400 | H72: =G72*(1+F72) -> 480 | J72: =VLOOKUP($D72,Construction!$B:$F,(COLUMN(Construction_BuildingReward_Power)-COLUMN(Construction_Name_and_Level)+1),FALSE) -> 90 | O72: 0.0034722222 | P72: 0.00625 | AD72: =AD71+(Q$3*Q72+R$3*R72+S$3*S72+T$3*T72+U$3*U72+V$3*V72+W$3*W72+X$3*X72+Y$3*Y72+Z$3*Z72+AA$3*AA72) -> #REF! | AE72: 0.25 | AF72: =VLOOKUP($D72,Construction!$B:$C,(COLUMN(Construction_Time)-COLUMN(Construction_Name_and_Level)+1),FALSE) -> 0.0092592593 | AG72: =AF72/(1+AE72) -> 0.0074074074 | AH72: =(Q$3*Q72+R$3*R72+T$3*T72+U$3*U72+V$3*V72+W$3*W72+X$3*X72+Y$3*Y72+Z$3*Z72+AA$3*AA72)*(-1) -> 0 | AI72: =IF((AG72-O72-P72-AH72)>=0,AG72-O72-P72-AH72,0) -> 0 | AJ72: =AF72-AI72 -> 0.0092592593 | AK72: =VLOOKUP($D72,Construction!$B:$J,(COLUMN(Construction_BuildingCost_Stone)-COLUMN(Construction_Name_and_Level)+1),FALSE)*(-1) -> -1672 | AL72: =VLOOKUP($D72,Construction!$B:$J,(COLUMN(Construction_BuildingCost_Wood)-COLUMN(Construction_Name_and_Level)+1),FALSE)*(-1) -> -1672 | AM72: =VLOOKUP($D72,Construction!$B:$J,(COLUMN(Construction_BuildingCost_Ore)-COLUMN(Construction_Name_and_Level)+1),FALSE)*(-1) -> -420 | AN72: =VLOOKUP($D72,Construction!$B:$J,(COLUMN(Construction_BuildingCost_Food)-COLUMN(Construction_Name_and_Level)+1),FALSE)*(-1) -> -4177
B73: Construction | C73: at Will | D73: Gymnos 5 | E73: 11 | F73: 0.2 | G73: =VLOOKUP($D73,Construction!$B:$E,(COLUMN(Construction_BuildingReward_HeroXP)-COLUMN(Construction_Name_and_Level)+1),FALSE) -> 400 | H73: =G73*(1+F73) -> 480 | J73: =VLOOKUP($D73,Construction!$B:$F,(COLUMN(Construction_BuildingReward_Power)-COLUMN(Construction_Name_and_Level)+1),FALSE) -> 90 | O73: 0.0034722222 | P73: 0.00625 | U73: -1 | AD73: =AD72+(Q$3*Q73+R$3*R73+S$3*S73+T$3*T73+U$3*U73+V$3*V73+W$3*W73+X$3*X73+Y$3*Y73+Z$3*Z73+AA$3*AA73) -> #REF! | AE73: 0.25 | AF73: =VLOOKUP($D73,Construction!$B:$C,(COLUMN(Construction_Time)-COLUMN(Construction_Name_and_Level)+1),FALSE) -> 0.018518519 | AG73: =AF73/(1+AE73) -> 0.014814815 | AH73: =(Q$3*Q73+R$3*R73+T$3*T73+U$3*U73+V$3*V73+W$3*W73+X$3*X73+Y$3*Y73+Z$3*Z73+AA$3*AA73)*(-1) -> 0.010416667 | AI73: =IF((AG73-O73-P73-AH73)>=0,AG73-O73-P73-AH73,0) -> 0 | AJ73: =AF73-AI73 -> 0.018518519 | AK73: =VLOOKUP($D73,Construction!$B:$J,(COLUMN(Construction_BuildingCost_Stone)-COLUMN(Construction_Name_and_Level)+1),FALSE)*(-1) -> -2101 | AL73: =VLOOKUP($D73,Construction!$B:$J,(COLUMN(Construction_BuildingCost_Wood)-COLUMN(Construction_Name_and_Level)+1),FALSE)*(-1) -> -1052 | AM73: =VLOOKUP($D73,Construction!$B:$J,(COLUMN(Construction_BuildingCost_Ore)-COLUMN(Construction_Name_and_Level)+1),FALSE)*(-1) -> -1052 | AN73: =VLOOKUP($D73,Construction!$B:$J,(COLUMN(Construction_BuildingCost_Food)-COLUMN(Construction_Name_and_Level)+1),FALSE)*(-1) -> -3150
B74: Construction | C74: at Will | D74: Academy 5 | E74: 12 | F74: 0.25 | G74: =VLOOKUP($D74,Construction!$B:$E,(COLUMN(Construction_BuildingReward_HeroXP)-COLUMN(Construction_Name_and_Level)+1),FALSE) -> 400 | H74: =G74*(1+F74) -> 500 | J74: =VLOOKUP($D74,Construction!$B:$F,(COLUMN(Construction_BuildingReward_Power)-COLUMN(Construction_Name_and_Level)+1),FALSE) -> 245 | O74: 0.0034722222 | P74: 0.00625 | U74: -1 | AD74: =AD73+(Q$3*Q74+R$3*R74+S$3*S74+T$3*T74+U$3*U74+V$3*V74+W$3*W74+X$3*X74+Y$3*Y74+Z$3*Z74+AA$3*AA74) -> #REF! | AE74: 0.41 | AF74: =VLOOKUP($D74,Construction!$B:$C,(COLUMN(Construction_Time)-COLUMN(Construction_Name_and_Level)+1),FALSE) -> 0.018518519 | AG74: =AF74/(1+AE74) -> 0.013133701 | AH74: =(Q$3*Q74+R$3*R74+T$3*T74+U$3*U74+V$3*V74+W$3*W74+X$3*X74+Y$3*Y74+Z$3*Z74+AA$3*AA74)*(-1) -> 0.010416667 | AI74: =IF((AG74-O74-P74-AH74)>=0,AG74-O74-P74-AH74,0) -> 0 | AJ74: =AF74-AI74 -> 0.018518519 | AK74: =VLOOKUP($D74,Construction!$B:$J,(COLUMN(Construction_BuildingCost_Stone)-COLUMN(Construction_Name_and_Level)+1),FALSE)*(-1) -> -5249 | AL74: =VLOOKUP($D74,Construction!$B:$J,(COLUMN(Construction_BuildingCost_Wood)-COLUMN(Construction_Name_and_Level)+1),FALSE)*(-1) -> -5249 | AM74: =VLOOKUP($D74,Construction!$B:$J,(COLUMN(Construction_BuildingCost_Ore)-COLUMN(Construction_Name_and_Level)+1),FALSE)*(-1) -> -2101 | AN74: =VLOOKUP($D74,Construction!$B:$J,(COLUMN(Construction_BuildingCost_Food)-COLUMN(Construction_Name_and_Level)+1),FALSE)*(-1) -> -3150
B75: Construction | C75: at Will | D75: Quarry 5 | E75: 12 | F75: 0.25 | G75: =VLOOKUP($D75,Construction!$B:$E,(COLUMN(Construction_BuildingReward_HeroXP)-COLUMN(Construction_Name_and_Level)+1),FALSE) -> 400 | H75: =G75*(1+F75) -> 500 | J75: =VLOOKUP($D75,Construction!$B:$F,(COLUMN(Construction_BuildingReward_Power)-COLUMN(Construction_Name_and_Level)+1),FALSE) -> 35 | O75: 0.0034722222 | P75: 0.00625 | AD75: =AD74+(Q$3*Q75+R$3*R75+S$3*S75+T$3*T75+U$3*U75+V$3*V75+W$3*W75+X$3*X75+Y$3*Y75+Z$3*Z75+AA$3*AA75) -> #REF! | AE75: 0.41 | AF75: =VLOOKUP($D75,Construction!$B:$C,(COLUMN(Construction_Time)-COLUMN(Construction_Name_and_Level)+1),FALSE) -> 0.012962963 | AG75: =AF75/(1+AE75) -> 0.0091935908 | AH75: =(Q$3*Q75+R$3*R75+T$3*T75+U$3*U75+V$3*V75+W$3*W75+X$3*X75+Y$3*Y75+Z$3*Z75+AA$3*AA75)*(-1) -> 0 | AI75: =IF((AG75-O75-P75-AH75)>=0,AG75-O75-P75-AH75,0) -> 0 | AJ75: =AF75-AI75 -> 0.012962963 | AK75: =VLOOKUP($D75,Construction!$B:$J,(COLUMN(Construction_BuildingCost_Stone)-COLUMN(Construction_Name_and_Level)+1),FALSE)*(-1) -> 0 | AL75: =VLOOKUP($D75,Construction!$B:$J,(COLUMN(Construction_BuildingCost_Wood)-COLUMN(Construction_Name_and_Level)+1),FALSE)*(-1) -> -837 | AM75: =VLOOKUP($D75,Construction!$B:$J,(COLUMN(Construction_BuildingCost_Ore)-COLUMN(Construction_Name_and_Level)+1),FALSE)*(-1) -> -837 | AN75: =VLOOKUP($D75,Construction!$B:$J,(COLUMN(Construction_BuildingCost_Food)-COLUMN(Construction_Name_and_Level)+1),FALSE)*(-1) -> -837
B76: Construction | C76: at Will | D76: Barracks 1 | E76: 12 | F76: 0.25 | G76: =VLOOKUP($D76,Construction!$B:$E,(COLUMN(Construction_BuildingReward_HeroXP)-COLUMN(Construction_Name_and_Level)+1),FALSE) -> 10 | H76: =G76*(1+F76) -> 12.5 | J76: =VLOOKUP($D76,Construction!$B:$F,(COLUMN(Construction_BuildingReward_Power)-COLUMN(Construction_Name_and_Level)+1),FALSE) -> 20 | O76: 0.0034722222 | P76: 0.00625 | AD76: =AD75+(Q$3*Q76+R$3*R76+S$3*S76+T$3*T76+U$3*U76+V$3*V76+W$3*W76+X$3*X76+Y$3*Y76+Z$3*Z76+AA$3*AA76) -> #REF! | AE76: 0.41 | AF76: =VLOOKUP($D76,Construction!$B:$C,(COLUMN(Construction_Time)-COLUMN(Construction_Name_and_Level)+1),FALSE) -> 0.0010416667 | AG76: =AF76/(1+AE76) -> 0.00073877069 | AH76: =(Q$3*Q76+R$3*R76+T$3*T76+U$3*U76+V$3*V76+W$3*W76+X$3*X76+Y$3*Y76+Z$3*Z76+AA$3*AA76)*(-1) -> 0 | AI76: =IF((AG76-O76-P76-AH76)>=0,AG76-O76-P76-AH76,0) -> 0 | AJ76: =AF76-AI76 -> 0.0010416667 | AK76: =VLOOKUP($D76,Construction!$B:$J,(COLUMN(Construction_BuildingCost_Stone)-COLUMN(Construction_Name_and_Level)+1),FALSE)*(-1) -> -500 | AL76: =VLOOKUP($D76,Construction!$B:$J,(COLUMN(Construction_BuildingCost_Wood)-COLUMN(Construction_Name_and_Level)+1),FALSE)*(-1) -> -400 | AM76: =VLOOKUP($D76,Construction!$B:$J,(COLUMN(Construction_BuildingCost_Ore)-COLUMN(Construction_Name_and_Level)+1),FALSE)*(-1) -> -300 | AN76: =VLOOKUP($D76,Construction!$B:$J,(COLUMN(Construction_BuildingCost_Food)-COLUMN(Construction_Name_and_Level)+1),FALSE)*(-1) -> -250
B77: Construction | C77: at Will | D77: Barracks 5 | E77: 12 | F77: 0.25 | G77: =VLOOKUP($D77,Construction!$B:$E,(COLUMN(Construction_BuildingReward_HeroXP)-COLUMN(Construction_Name_and_Level)+1),FALSE) -> 400 | H77: =G77*(1+F77) -> 500 | J77: =VLOOKUP($D77,Construction!$B:$F,(COLUMN(Construction_BuildingReward_Power)-COLUMN(Construction_Name_and_Level)+1),FALSE) -> 140 | O77: 0.0034722222 | P77: 0.00625 | AD77: =AD76+(Q$3*Q77+R$3*R77+S$3*S77+T$3*T77+U$3*U77+V$3*V77+W$3*W77+X$3*X77+Y$3*Y77+Z$3*Z77+AA$3*AA77) -> #REF! | AE77: 0.41 | AF77: =VLOOKUP($D77,Construction!$B:$C,(COLUMN(Construction_Time)-COLUMN(Construction_Name_and_Level)+1),FALSE) -> 0.016666667 | AG77: =AF77/(1+AE77) -> 0.011820331 | AH77: =(Q$3*Q77+R$3*R77+T$3*T77+U$3*U77+V$3*V77+W$3*W77+X$3*X77+Y$3*Y77+Z$3*Z77+AA$3*AA77)*(-1) -> 0 | AI77: =IF((AG77-O77-P77-AH77)>=0,AG77-O77-P77-AH77,0) -> 0.0020981087 | AJ77: =AF77-AI77 -> 0.014568558 | AK77: =VLOOKUP($D77,Construction!$B:$J,(COLUMN(Construction_BuildingCost_Stone)-COLUMN(Construction_Name_and_Level)+1),FALSE)*(-1) -> -4177 | AL77: =VLOOKUP($D77,Construction!$B:$J,(COLUMN(Construction_BuildingCost_Wood)-COLUMN(Construction_Name_and_Level)+1),FALSE)*(-1) -> -3343 | AM77: =VLOOKUP($D77,Construction!$B:$J,(COLUMN(Construction_BuildingCost_Ore)-COLUMN(Construction_Name_and_Level)+1),FALSE)*(-1) -> -2506 | AN77: =VLOOKUP($D77,Construction!$B:$J,(COLUMN(Construction_BuildingCost_Food)-COLUMN(Construction_Name_and_Level)+1),FALSE)*(-1) -> -2091
B78: Construction | C78: at Will | D78: Forge 5 | E78: 12 | F78: 0.25 | G78: =VLOOKUP($D78,Construction!$B:$E,(COLUMN(Construction_BuildingReward_HeroXP)-COLUMN(Construction_Name_and_Level)+1),FALSE) -> 400 | H78: =G78*(1+F78) -> 500 | J78: =VLOOKUP($D78,Construction!$B:$F,(COLUMN(Construction_BuildingReward_Power)-COLUMN(Construction_Name_and_Level)+1),FALSE) -> 90 | O78: 0.0034722222 | P78: 0.00625 | AD78: =AD77+(Q$3*Q78+R$3*R78+S$3*S78+T$3*T78+U$3*U78+V$3*V78+W$3*W78+X$3*X78+Y$3*Y78+Z$3*Z78+AA$3*AA78) -> #REF! | AE78: 0.41 | AF78: =VLOOKUP($D78,Construction!$B:$C,(COLUMN(Construction_Time)-COLUMN(Construction_Name_and_Level)+1),FALSE) -> 0.013888889 | AG78: =AF78/(1+AE78) -> 0.0098502758 | AH78: =(Q$3*Q78+R$3*R78+T$3*T78+U$3*U78+V$3*V78+W$3*W78+X$3*X78+Y$3*Y78+Z$3*Z78+AA$3*AA78)*(-1) -> 0 | AI78: =IF((AG78-O78-P78-AH78)>=0,AG78-O78-P78-AH78,0) -> 0.00012805359 | AJ78: =AF78-AI78 -> 0.013760835 | AK78: =VLOOKUP($D78,Construction!$B:$J,(COLUMN(Construction_BuildingCost_Stone)-COLUMN(Construction_Name_and_Level)+1),FALSE)*(-1) -> -2506 | AL78: =VLOOKUP($D78,Construction!$B:$J,(COLUMN(Construction_BuildingCost_Wood)-COLUMN(Construction_Name_and_Level)+1),FALSE)*(-1) -> -3343 | AM78: =VLOOKUP($D78,Construction!$B:$J,(COLUMN(Construction_BuildingCost_Ore)-COLUMN(Construction_Name_and_Level)+1),FALSE)*(-1) -> -6683 | AN78: =VLOOKUP($D78,Construction!$B:$J,(COLUMN(Construction_BuildingCost_Food)-COLUMN(Construction_Name_and_Level)+1),FALSE)*(-1) -> -2506
B79: Construction | C79: at Will | D79: Walls 5 | E79: 12 | F79: 0.25 | G79: =VLOOKUP($D79,Construction!$B:$E,(COLUMN(Construction_BuildingReward_HeroXP)-COLUMN(Construction_Name_and_Level)+1),FALSE) -> 5000 | H79: =G79*(1+F79) -> 6250 | J79: =VLOOKUP($D79,Construction!$B:$F,(COLUMN(Construction_BuildingReward_Power)-COLUMN(Construction_Name_and_Level)+1),FALSE) -> 210 | O79: 0.0034722222 | P79: 0.00625 | AD79: =AD78+(Q$3*Q79+R$3*R79+S$3*S79+T$3*T79+U$3*U79+V$3*V79+W$3*W79+X$3*X79+Y$3*Y79+Z$3*Z79+AA$3*AA79) -> #REF! | AE79: 0.41 | AF79: =VLOOKUP($D79,Construction!$B:$C,(COLUMN(Construction_Time)-COLUMN(Construction_Name_and_Level)+1),FALSE) -> 0.019444444 | AG79: =AF79/(1+AE79) -> 0.013790386 | AH79: =(Q$3*Q79+R$3*R79+T$3*T79+U$3*U79+V$3*V79+W$3*W79+X$3*X79+Y$3*Y79+Z$3*Z79+AA$3*AA79)*(-1) -> 0 | AI79: =IF((AG79-O79-P79-AH79)>=0,AG79-O79-P79-AH79,0) -> 0.0040681639 | AJ79: =AF79-AI79 -> 0.015376281 | AK79: =VLOOKUP($D79,Construction!$B:$J,(COLUMN(Construction_BuildingCost_Stone)-COLUMN(Construction_Name_and_Level)+1),FALSE)*(-1) -> -10498 | AL79: =VLOOKUP($D79,Construction!$B:$J,(COLUMN(Construction_BuildingCost_Wood)-COLUMN(Construction_Name_and_Level)+1),FALSE)*(-1) -> -8399 | AM79: =VLOOKUP($D79,Construction!$B:$J,(COLUMN(Construction_BuildingCost_Ore)-COLUMN(Construction_Name_and_Level)+1),FALSE)*(-1) -> -3150 | AN79: =VLOOKUP($D79,Construction!$B:$J,(COLUMN(Construction_BuildingCost_Food)-COLUMN(Construction_Name_and_Level)+1),FALSE)*(-1) -> -5249
B80: Construction | C80: at Will | D80: Storehouse 5 | E80: 13 | F80: 0.25 | G80: =VLOOKUP($D80,Construction!$B:$E,(COLUMN(Construction_BuildingReward_HeroXP)-COLUMN(Construction_Name_and_Level)+1),FALSE) -> 400 | H80: =G80*(1+F80) -> 500 | J80: =VLOOKUP($D80,Construction!$B:$F,(COLUMN(Construction_BuildingReward_Power)-COLUMN(Construction_Name_and_Level)+1),FALSE) -> 70 | O80: 0.0034722222 | P80: 0.00625 | AD80: =AD79+(Q$3*Q80+R$3*R80+S$3*S80+T$3*T80+U$3*U80+V$3*V80+W$3*W80+X$3*X80+Y$3*Y80+Z$3*Z80+AA$3*AA80) -> #REF! | AE80: 0.41 | AF80: =VLOOKUP($D80,Construction!$B:$C,(COLUMN(Construction_Time)-COLUMN(Construction_Name_and_Level)+1),FALSE) -> 0.011111111 | AG80: =AF80/(1+AE80) -> 0.0078802206 | AH80: =(Q$3*Q80+R$3*R80+T$3*T80+U$3*U80+V$3*V80+W$3*W80+X$3*X80+Y$3*Y80+Z$3*Z80+AA$3*AA80)*(-1) -> 0 | AI80: =IF((AG80-O80-P80-AH80)>=0,AG80-O80-P80-AH80,0) -> 0 | AJ80: =AF80-AI80 -> 0.011111111 | AK80: =VLOOKUP($D80,Construction!$B:$J,(COLUMN(Construction_BuildingCost_Stone)-COLUMN(Construction_Name_and_Level)+1),FALSE)*(-1) -> -3343 | AL80: =VLOOKUP($D80,Construction!$B:$J,(COLUMN(Construction_BuildingCost_Wood)-COLUMN(Construction_Name_and_Level)+1),FALSE)*(-1) -> -3343 | AM80: =VLOOKUP($D80,Construction!$B:$J,(COLUMN(Construction_BuildingCost_Ore)-COLUMN(Construction_Name_and_Level)+1),FALSE)*(-1) -> -2506 | AN80: =VLOOKUP($D80,Construction!$B:$J,(COLUMN(Construction_BuildingCost_Food)-COLUMN(Construction_Name_and_Level)+1),FALSE)*(-1) -> -1672
B81: Construction | C81: at Will | D81: Mine 6 | E81: 13 | F81: 0.25 | G81: =VLOOKUP($D81,Construction!$B:$E,(COLUMN(Construction_BuildingReward_HeroXP)-COLUMN(Construction_Name_and_Level)+1),FALSE) -> 500 | H81: =G81*(1+F81) -> 625 | J81: =VLOOKUP($D81,Construction!$B:$F,(COLUMN(Construction_BuildingReward_Power)-COLUMN(Construction_Name_and_Level)+1),FALSE) -> 55 | O81: 0.0034722222 | P81: 0.0069444444 | U81: -1 | AD81: =#REF!+(Q$3*Q81+R$3*R81+S$3*S81+T$3*T81+U$3*U81+V$3*V81+W$3*W81+X$3*X81+Y$3*Y81+Z$3*Z81+AA$3*AA81) -> #REF! | AE81: 0.41 | AF81: =VLOOKUP($D81,Construction!$B:$C,(COLUMN(Construction_Time)-COLUMN(Construction_Name_and_Level)+1),FALSE) -> 0.02962963 | AG81: =AF81/(1+AE81) -> 0.021013922 | AH81: =(Q$3*Q81+R$3*R81+T$3*T81+U$3*U81+V$3*V81+W$3*W81+X$3*X81+Y$3*Y81+Z$3*Z81+AA$3*AA81)*(-1) -> 0.010416667 | AI81: =IF((AG81-O81-P81-AH81)>=0,AG81-O81-P81-AH81,0) -> 0.00018058839 | AJ81: =AF81-AI81 -> 0.029449041 | AK81: =VLOOKUP($D81,Construction!$B:$J,(COLUMN(Construction_BuildingCost_Stone)-COLUMN(Construction_Name_and_Level)+1),FALSE)*(-1) -> -1674 | AL81: =VLOOKUP($D81,Construction!$B:$J,(COLUMN(Construction_BuildingCost_Wood)-COLUMN(Construction_Name_and_Level)+1),FALSE)*(-1) -> -1674 | AM81: =VLOOKUP($D81,Construction!$B:$J,(COLUMN(Construction_BuildingCost_Ore)-COLUMN(Construction_Name_and_Level)+1),FALSE)*(-1) -> 0 | AN81: =VLOOKUP($D81,Construction!$B:$J,(COLUMN(Construction_BuildingCost_Food)-COLUMN(Construction_Name_and_Level)+1),FALSE)*(-1) -> -1674
B82: Construction | C82: at Will | D82: Forge 6 | E82: 13 | F82: 0.25 | G82: =VLOOKUP($D82,Construction!$B:$E,(COLUMN(Construction_BuildingReward_HeroXP)-COLUMN(Construction_Name_and_Level)+1),FALSE) -> 500 | H82: =G82*(1+F82) -> 625 | J82: =VLOOKUP($D82,Construction!$B:$F,(COLUMN(Construction_BuildingReward_Power)-COLUMN(Construction_Name_and_Level)+1),FALSE) -> 135 | O82: 0.0034722222 | P82: 0.0069444444 | U82: -1 | AD82: =AD81+(Q$3*Q82+R$3*R82+S$3*S82+T$3*T82+U$3*U82+V$3*V82+W$3*W82+X$3*X82+Y$3*Y82+Z$3*Z82+AA$3*AA82) -> #REF! | AE82: 0.41 | AF82: =VLOOKUP($D82,Construction!$B:$C,(COLUMN(Construction_Time)-COLUMN(Construction_Name_and_Level)+1),FALSE) -> 0.027777778 | AG82: =AF82/(1+AE82) -> 0.019700552 | AH82: =(Q$3*Q82+R$3*R82+T$3*T82+U$3*U82+V$3*V82+W$3*W82+X$3*X82+Y$3*Y82+Z$3*Z82+AA$3*AA82)*(-1) -> 0.010416667 | AI82: =IF((AG82-O82-P82-AH82)>=0,AG82-O82-P82-AH82,0) -> 0 | AJ82: =AF82-AI82 -> 0.027777778 | AK82: =VLOOKUP($D82,Construction!$B:$J,(COLUMN(Construction_BuildingCost_Stone)-COLUMN(Construction_Name_and_Level)+1),FALSE)*(-1) -> -5012 | AL82: =VLOOKUP($D82,Construction!$B:$J,(COLUMN(Construction_BuildingCost_Wood)-COLUMN(Construction_Name_and_Level)+1),FALSE)*(-1) -> -6686 | AM82: =VLOOKUP($D82,Construction!$B:$J,(COLUMN(Construction_BuildingCost_Ore)-COLUMN(Construction_Name_and_Level)+1),FALSE)*(-1) -> -13366 | AN82: =VLOOKUP($D82,Construction!$B:$J,(COLUMN(Construction_BuildingCost_Food)-COLUMN(Construction_Name_and_Level)+1),FALSE)*(-1) -> -5012
B83: Construction | C83: at Will | D83: Walls 6 | E83: 13 | F83: 0.25 | G83: =VLOOKUP($D83,Construction!$B:$E,(COLUMN(Construction_BuildingReward_HeroXP)-COLUMN(Construction_Name_and_Level)+1),FALSE) -> 5000 | H83: =G83*(1+F83) -> 6250 | J83: =VLOOKUP($D83,Construction!$B:$F,(COLUMN(Construction_BuildingReward_Power)-COLUMN(Construction_Name_and_Level)+1),FALSE) -> 330 | O83: 0.0034722222 | P83: 0.0069444444 | AD83: =AD82+(Q$3*Q83+R$3*R83+S$3*S83+T$3*T83+U$3*U83+V$3*V83+W$3*W83+X$3*X83+Y$3*Y83+Z$3*Z83+AA$3*AA83) -> #REF! | AE83: 0.41 | AF83: =VLOOKUP($D83,Construction!$B:$C,(COLUMN(Construction_Time)-COLUMN(Construction_Name_and_Level)+1),FALSE) -> 0.038888889 | AG83: =AF83/(1+AE83) -> 0.027580772 | AH83: =(Q$3*Q83+R$3*R83+T$3*T83+U$3*U83+V$3*V83+W$3*W83+X$3*X83+Y$3*Y83+Z$3*Z83+AA$3*AA83)*(-1) -> 0 | AI83: =IF((AG83-O83-P83-AH83)>=0,AG83-O83-P83-AH83,0) -> 0.017164106 | AJ83: =AF83-AI83 -> 0.021724783 | AK83: =VLOOKUP($D83,Construction!$B:$J,(COLUMN(Construction_BuildingCost_Stone)-COLUMN(Construction_Name_and_Level)+1),FALSE)*(-1) -> -20996 | AL83: =VLOOKUP($D83,Construction!$B:$J,(COLUMN(Construction_BuildingCost_Wood)-COLUMN(Construction_Name_and_Level)+1),FALSE)*(-1) -> -16798 | AM83: =VLOOKUP($D83,Construction!$B:$J,(COLUMN(Construction_BuildingCost_Ore)-COLUMN(Construction_Name_and_Level)+1),FALSE)*(-1) -> -6300 | AN83: =VLOOKUP($D83,Construction!$B:$J,(COLUMN(Construction_BuildingCost_Food)-COLUMN(Construction_Name_and_Level)+1),FALSE)*(-1) -> -10498
B84: Construction | C84: at Will | D84: Storehouse 6 | E84: 13 | F84: 0.25 | G84: =VLOOKUP($D84,Construction!$B:$E,(COLUMN(Construction_BuildingReward_HeroXP)-COLUMN(Construction_Name_and_Level)+1),FALSE) -> 500 | H84: =G84*(1+F84) -> 625 | J84: =VLOOKUP($D84,Construction!$B:$F,(COLUMN(Construction_BuildingReward_Power)-COLUMN(Construction_Name_and_Level)+1),FALSE) -> 110 | O84: 0.0034722222 | P84: 0.0069444444 | AD84: =AD83+(Q$3*Q84+R$3*R84+S$3*S84+T$3*T84+U$3*U84+V$3*V84+W$3*W84+X$3*X84+Y$3*Y84+Z$3*Z84+AA$3*AA84) -> #REF! | AE84: 0.41 | AF84: =VLOOKUP($D84,Construction!$B:$C,(COLUMN(Construction_Time)-COLUMN(Construction_Name_and_Level)+1),FALSE) -> 0.022222222 | AG84: =AF84/(1+AE84) -> 0.015760441 | AH84: =(Q$3*Q84+R$3*R84+T$3*T84+U$3*U84+V$3*V84+W$3*W84+X$3*X84+Y$3*Y84+Z$3*Z84+AA$3*AA84)*(-1) -> 0 | AI84: =IF((AG84-O84-P84-AH84)>=0,AG84-O84-P84-AH84,0) -> 0.0053437746 | AJ84: =AF84-AI84 -> 0.016878448 | AK84: =VLOOKUP($D84,Construction!$B:$J,(COLUMN(Construction_BuildingCost_Stone)-COLUMN(Construction_Name_and_Level)+1),FALSE)*(-1) -> -6686 | AL84: =VLOOKUP($D84,Construction!$B:$J,(COLUMN(Construction_BuildingCost_Wood)-COLUMN(Construction_Name_and_Level)+1),FALSE)*(-1) -> -6686 | AM84: =VLOOKUP($D84,Construction!$B:$J,(COLUMN(Construction_BuildingCost_Ore)-COLUMN(Construction_Name_and_Level)+1),FALSE)*(-1) -> -5012 | AN84: =VLOOKUP($D84,Construction!$B:$J,(COLUMN(Construction_BuildingCost_Food)-COLUMN(Construction_Name_and_Level)+1),FALSE)*(-1) -> -3344
B85: Construction | C85: by Quest | D85: Hospital 3 | E85: 13 | F85: 0.25 | G85: =VLOOKUP($D85,Construction!$B:$E,(COLUMN(Construction_BuildingReward_HeroXP)-COLUMN(Construction_Name_and_Level)+1),FALSE) -> 50 | H85: =G85*(1+F85) -> 62.5 | J85: =VLOOKUP($D85,Construction!$B:$F,(COLUMN(Construction_BuildingReward_Power)-COLUMN(Construction_Name_and_Level)+1),FALSE) -> 30 | O85: 0.0034722222 | P85: 0.0069444444 | AD85: =AD84+(Q$3*Q85+R$3*R85+S$3*S85+T$3*T85+U$3*U85+V$3*V85+W$3*W85+X$3*X85+Y$3*Y85+Z$3*Z85+AA$3*AA85) -> #REF! | AE85: 0.41 | AF85: =VLOOKUP($D85,Construction!$B:$C,(COLUMN(Construction_Time)-COLUMN(Construction_Name_and_Level)+1),FALSE) -> 0.0041666667 | AG85: =AF85/(1+AE85) -> 0.0029550827 | AH85: =(Q$3*Q85+R$3*R85+T$3*T85+U$3*U85+V$3*V85+W$3*W85+X$3*X85+Y$3*Y85+Z$3*Z85+AA$3*AA85)*(-1) -> 0 | AI85: =IF((AG85-O85-P85-AH85)>=0,AG85-O85-P85-AH85,0) -> 0 | AJ85: =AF85-AI85 -> 0.0041666667 | AK85: =VLOOKUP($D85,Construction!$B:$J,(COLUMN(Construction_BuildingCost_Stone)-COLUMN(Construction_Name_and_Level)+1),FALSE)*(-1) -> -1445 | AL85: =VLOOKUP($D85,Construction!$B:$J,(COLUMN(Construction_BuildingCost_Wood)-COLUMN(Construction_Name_and_Level)+1),FALSE)*(-1) -> -1156 | AM85: =VLOOKUP($D85,Construction!$B:$J,(COLUMN(Construction_BuildingCost_Ore)-COLUMN(Construction_Name_and_Level)+1),FALSE)*(-1) -> -867 | AN85: =VLOOKUP($D85,Construction!$B:$J,(COLUMN(Construction_BuildingCost_Food)-COLUMN(Construction_Name_and_Level)+1),FALSE)*(-1) -> -723
B86: Construction | C86: by Quest | D86: Watchtower 3 | E86: 13 | F86: 0.25 | G86: =VLOOKUP($D86,Construction!$B:$E,(COLUMN(Construction_BuildingReward_HeroXP)-COLUMN(Construction_Name_and_Level)+1),FALSE) -> 50 | H86: =G86*(1+F86) -> 62.5 | J86: =VLOOKUP($D86,Construction!$B:$F,(COLUMN(Construction_BuildingReward_Power)-COLUMN(Construction_Name_and_Level)+1),FALSE) -> 35 | O86: 0.0034722222 | P86: 0.0069444444 | AD86: =AD85+(Q$3*Q86+R$3*R86+S$3*S86+T$3*T86+U$3*U86+V$3*V86+W$3*W86+X$3*X86+Y$3*Y86+Z$3*Z86+AA$3*AA86) -> #REF! | AE86: 0.41 | AF86: =VLOOKUP($D86,Construction!$B:$C,(COLUMN(Construction_Time)-COLUMN(Construction_Name_and_Level)+1),FALSE) -> 0.0032407407 | AG86: =AF86/(1+AE86) -> 0.0022983977 | AH86: =(Q$3*Q86+R$3*R86+T$3*T86+U$3*U86+V$3*V86+W$3*W86+X$3*X86+Y$3*Y86+Z$3*Z86+AA$3*AA86)*(-1) -> 0 | AI86: =IF((AG86-O86-P86-AH86)>=0,AG86-O86-P86-AH86,0) -> 0 | AJ86: =AF86-AI86 -> 0.0032407407 | AK86: =VLOOKUP($D86,Construction!$B:$J,(COLUMN(Construction_BuildingCost_Stone)-COLUMN(Construction_Name_and_Level)+1),FALSE)*(-1) -> -1445 | AL86: =VLOOKUP($D86,Construction!$B:$J,(COLUMN(Construction_BuildingCost_Wood)-COLUMN(Construction_Name_and_Level)+1),FALSE)*(-1) -> -1156 | AM86: =VLOOKUP($D86,Construction!$B:$J,(COLUMN(Construction_BuildingCost_Ore)-COLUMN(Construction_Name_and_Level)+1),FALSE)*(-1) -> -289 | AN86: =VLOOKUP($D86,Construction!$B:$J,(COLUMN(Construction_BuildingCost_Food)-COLUMN(Construction_Name_and_Level)+1),FALSE)*(-1) -> -578
B87: Construction | C87: by Quest | D87: Barracks 1 | E87: 13 | F87: 0.25 | G87: =VLOOKUP($D87,Construction!$B:$E,(COLUMN(Construction_BuildingReward_HeroXP)-COLUMN(Construction_Name_and_Level)+1),FALSE) -> 10 | H87: =G87*(1+F87) -> 12.5 | J87: =VLOOKUP($D87,Construction!$B:$F,(COLUMN(Construction_BuildingReward_Power)-COLUMN(Construction_Name_and_Level)+1),FALSE) -> 20 | O87: 0.0034722222 | P87: 0.0069444444 | AD87: =AD86+(Q$3*Q87+R$3*R87+S$3*S87+T$3*T87+U$3*U87+V$3*V87+W$3*W87+X$3*X87+Y$3*Y87+Z$3*Z87+AA$3*AA87) -> #REF! | AE87: 0.41 | AF87: =VLOOKUP($D87,Construction!$B:$C,(COLUMN(Construction_Time)-COLUMN(Construction_Name_and_Level)+1),FALSE) -> 0.0010416667 | AG87: =AF87/(1+AE87) -> 0.00073877069 | AH87: =(Q$3*Q87+R$3*R87+T$3*T87+U$3*U87+V$3*V87+W$3*W87+X$3*X87+Y$3*Y87+Z$3*Z87+AA$3*AA87)*(-1) -> 0 | AI87: =IF((AG87-O87-P87-AH87)>=0,AG87-O87-P87-AH87,0) -> 0 | AJ87: =AF87-AI87 -> 0.0010416667 | AK87: =VLOOKUP($D87,Construction!$B:$J,(COLUMN(Construction_BuildingCost_Stone)-COLUMN(Construction_Name_and_Level)+1),FALSE)*(-1) -> -500 | AL87: =VLOOKUP($D87,Construction!$B:$J,(COLUMN(Construction_BuildingCost_Wood)-COLUMN(Construction_Name_and_Level)+1),FALSE)*(-1) -> -400 | AM87: =VLOOKUP($D87,Construction!$B:$J,(COLUMN(Construction_BuildingCost_Ore)-COLUMN(Construction_Name_and_Level)+1),FALSE)*(-1) -> -300 | AN87: =VLOOKUP($D87,Construction!$B:$J,(COLUMN(Construction_BuildingCost_Food)-COLUMN(Construction_Name_and_Level)+1),FALSE)*(-1) -> -250
B88: Construction | C88: by Quest | D88: Barracks 1 | E88: 13 | F88: 0.25 | G88: =VLOOKUP($D88,Construction!$B:$E,(COLUMN(Construction_BuildingReward_HeroXP)-COLUMN(Construction_Name_and_Level)+1),FALSE) -> 10 | H88: =G88*(1+F88) -> 12.5 | J88: =VLOOKUP($D88,Construction!$B:$F,(COLUMN(Construction_BuildingReward_Power)-COLUMN(Construction_Name_and_Level)+1),FALSE) -> 20 | O88: 0.0034722222 | P88: 0.0069444444 | AD88: =AD87+(Q$3*Q88+R$3*R88+S$3*S88+T$3*T88+U$3*U88+V$3*V88+W$3*W88+X$3*X88+Y$3*Y88+Z$3*Z88+AA$3*AA88) -> #REF! | AE88: 0.41 | AF88: =VLOOKUP($D88,Construction!$B:$C,(COLUMN(Construction_Time)-COLUMN(Construction_Name_and_Level)+1),FALSE) -> 0.0010416667 | AG88: =AF88/(1+AE88) -> 0.00073877069 | AH88: =(Q$3*Q88+R$3*R88+T$3*T88+U$3*U88+V$3*V88+W$3*W88+X$3*X88+Y$3*Y88+Z$3*Z88+AA$3*AA88)*(-1) -> 0 | AI88: =IF((AG88-O88-P88-AH88)>=0,AG88-O88-P88-AH88,0) -> 0 | AJ88: =AF88-AI88 -> 0.0010416667 | AK88: =VLOOKUP($D88,Construction!$B:$J,(COLUMN(Construction_BuildingCost_Stone)-COLUMN(Construction_Name_and_Level)+1),FALSE)*(-1) -> -500 | AL88: =VLOOKUP($D88,Construction!$B:$J,(COLUMN(Construction_BuildingCost_Wood)-COLUMN(Construction_Name_and_Level)+1),FALSE)*(-1) -> -400 | AM88: =VLOOKUP($D88,Construction!$B:$J,(COLUMN(Construction_BuildingCost_Ore)-COLUMN(Construction_Name_and_Level)+1),FALSE)*(-1) -> -300 | AN88: =VLOOKUP($D88,Construction!$B:$J,(COLUMN(Construction_BuildingCost_Food)-COLUMN(Construction_Name_and_Level)+1),FALSE)*(-1) -> -250
B89: Construction | C89: by Quest | D89: Hospital 1 | E89: 13 | F89: 0.25 | G89: =VLOOKUP($D89,Construction!$B:$E,(COLUMN(Construction_BuildingReward_HeroXP)-COLUMN(Construction_Name_and_Level)+1),FALSE) -> 10 | H89: =G89*(1+F89) -> 12.5 | J89: =VLOOKUP($D89,Construction!$B:$F,(COLUMN(Construction_BuildingReward_Power)-COLUMN(Construction_Name_and_Level)+1),FALSE) -> 10 | O89: 0.0034722222 | P89: 0.0069444444 | AD89: =AD88+(Q$3*Q89+R$3*R89+S$3*S89+T$3*T89+U$3*U89+V$3*V89+W$3*W89+X$3*X89+Y$3*Y89+Z$3*Z89+AA$3*AA89) -> #REF! | AE89: 0.41 | AF89: =VLOOKUP($D89,Construction!$B:$C,(COLUMN(Construction_Time)-COLUMN(Construction_Name_and_Level)+1),FALSE) -> 0.0010416667 | AG89: =AF89/(1+AE89) -> 0.00073877069 | AH89: =(Q$3*Q89+R$3*R89+T$3*T89+U$3*U89+V$3*V89+W$3*W89+X$3*X89+Y$3*Y89+Z$3*Z89+AA$3*AA89)*(-1) -> 0 | AI89: =IF((AG89-O89-P89-AH89)>=0,AG89-O89-P89-AH89,0) -> 0 | AJ89: =AF89-AI89 -> 0.0010416667 | AK89: =VLOOKUP($D89,Construction!$B:$J,(COLUMN(Construction_BuildingCost_Stone)-COLUMN(Construction_Name_and_Level)+1),FALSE)*(-1) -> -500 | AL89: =VLOOKUP($D89,Construction!$B:$J,(COLUMN(Construction_BuildingCost_Wood)-COLUMN(Construction_Name_and_Level)+1),FALSE)*(-1) -> -400 | AM89: =VLOOKUP($D89,Construction!$B:$J,(COLUMN(Construction_BuildingCost_Ore)-COLUMN(Construction_Name_and_Level)+1),FALSE)*(-1) -> -300 | AN89: =VLOOKUP($D89,Construction!$B:$J,(COLUMN(Construction_BuildingCost_Food)-COLUMN(Construction_Name_and_Level)+1),FALSE)*(-1) -> -250
B90: Construction | C90: by Quest | D90: Hospital 1 | E90: 13 | F90: 0.25 | G90: =VLOOKUP($D90,Construction!$B:$E,(COLUMN(Construction_BuildingReward_HeroXP)-COLUMN(Construction_Name_and_Level)+1),FALSE) -> 10 | H90: =G90*(1+F90) -> 12.5 | J90: =VLOOKUP($D90,Construction!$B:$F,(COLUMN(Construction_BuildingReward_Power)-COLUMN(Construction_Name_and_Level)+1),FALSE) -> 10 | O90: 0.0034722222 | P90: 0.0069444444 | AD90: =#REF!+(Q$3*Q90+R$3*R90+S$3*S90+T$3*T90+U$3*U90+V$3*V90+W$3*W90+X$3*X90+Y$3*Y90+Z$3*Z90+AA$3*AA90) -> #REF! | AE90: 0.41 | AF90: =VLOOKUP($D90,Construction!$B:$C,(COLUMN(Construction_Time)-COLUMN(Construction_Name_and_Level)+1),FALSE) -> 0.0010416667 | AG90: =AF90/(1+AE90) -> 0.00073877069 | AH90: =(Q$3*Q90+R$3*R90+T$3*T90+U$3*U90+V$3*V90+W$3*W90+X$3*X90+Y$3*Y90+Z$3*Z90+AA$3*AA90)*(-1) -> 0 | AI90: =IF((AG90-O90-P90-AH90)>=0,AG90-O90-P90-AH90,0) -> 0 | AJ90: =AF90-AI90 -> 0.0010416667 | AK90: =VLOOKUP($D90,Construction!$B:$J,(COLUMN(Construction_BuildingCost_Stone)-COLUMN(Construction_Name_and_Level)+1),FALSE)*(-1) -> -500 | AL90: =VLOOKUP($D90,Construction!$B:$J,(COLUMN(Construction_BuildingCost_Wood)-COLUMN(Construction_Name_and_Level)+1),FALSE)*(-1) -> -400 | AM90: =VLOOKUP($D90,Construction!$B:$J,(COLUMN(Construction_BuildingCost_Ore)-COLUMN(Construction_Name_and_Level)+1),FALSE)*(-1) -> -300 | AN90: =VLOOKUP($D90,Construction!$B:$J,(COLUMN(Construction_BuildingCost_Food)-COLUMN(Construction_Name_and_Level)+1),FALSE)*(-1) -> -250
B91: Construction | C91: by Quest | D91: Hospital 1 | E91: 13 | F91: 0.25 | G91: =VLOOKUP($D91,Construction!$B:$E,(COLUMN(Construction_BuildingReward_HeroXP)-COLUMN(Construction_Name_and_Level)+1),FALSE) -> 10 | H91: =G91*(1+F91) -> 12.5 | J91: =VLOOKUP($D91,Construction!$B:$F,(COLUMN(Construction_BuildingReward_Power)-COLUMN(Construction_Name_and_Level)+1),FALSE) -> 10 | O91: 0.0034722222 | P91: 0.0069444444 | AD91: =AD90+(Q$3*Q91+R$3*R91+S$3*S91+T$3*T91+U$3*U91+V$3*V91+W$3*W91+X$3*X91+Y$3*Y91+Z$3*Z91+AA$3*AA91) -> #REF! | AE91: 0.41 | AF91: =VLOOKUP($D91,Construction!$B:$C,(COLUMN(Construction_Time)-COLUMN(Construction_Name_and_Level)+1),FALSE) -> 0.0010416667 | AG91: =AF91/(1+AE91) -> 0.00073877069 | AH91: =(Q$3*Q91+R$3*R91+T$3*T91+U$3*U91+V$3*V91+W$3*W91+X$3*X91+Y$3*Y91+Z$3*Z91+AA$3*AA91)*(-1) -> 0 | AI91: =IF((AG91-O91-P91-AH91)>=0,AG91-O91-P91-AH91,0) -> 0 | AJ91: =AF91-AI91 -> 0.0010416667 | AK91: =VLOOKUP($D91,Construction!$B:$J,(COLUMN(Construction_BuildingCost_Stone)-COLUMN(Construction_Name_and_Level)+1),FALSE)*(-1) -> -500 | AL91: =VLOOKUP($D91,Construction!$B:$J,(COLUMN(Construction_BuildingCost_Wood)-COLUMN(Construction_Name_and_Level)+1),FALSE)*(-1) -> -400 | AM91: =VLOOKUP($D91,Construction!$B:$J,(COLUMN(Construction_BuildingCost_Ore)-COLUMN(Construction_Name_and_Level)+1),FALSE)*(-1) -> -300 | AN91: =VLOOKUP($D91,Construction!$B:$J,(COLUMN(Construction_BuildingCost_Food)-COLUMN(Construction_Name_and_Level)+1),FALSE)*(-1) -> -250
B92: Construction | C92: by Quest | D92: Hospital 1 | E92: 13 | F92: 0.25 | G92: =VLOOKUP($D92,Construction!$B:$E,(COLUMN(Construction_BuildingReward_HeroXP)-COLUMN(Construction_Name_and_Level)+1),FALSE) -> 10 | H92: =G92*(1+F92) -> 12.5 | J92: =VLOOKUP($D92,Construction!$B:$F,(COLUMN(Construction_BuildingReward_Power)-COLUMN(Construction_Name_and_Level)+1),FALSE) -> 10 | O92: 0.0034722222 | P92: 0.0069444444 | AD92: =AD91+(Q$3*Q92+R$3*R92+S$3*S92+T$3*T92+U$3*U92+V$3*V92+W$3*W92+X$3*X92+Y$3*Y92+Z$3*Z92+AA$3*AA92) -> #REF! | AE92: 0.41 | AF92: =VLOOKUP($D92,Construction!$B:$C,(COLUMN(Construction_Time)-COLUMN(Construction_Name_and_Level)+1),FALSE) -> 0.0010416667 | AG92: =AF92/(1+AE92) -> 0.00073877069 | AH92: =(Q$3*Q92+R$3*R92+T$3*T92+U$3*U92+V$3*V92+W$3*W92+X$3*X92+Y$3*Y92+Z$3*Z92+AA$3*AA92)*(-1) -> 0 | AI92: =IF((AG92-O92-P92-AH92)>=0,AG92-O92-P92-AH92,0) -> 0 | AJ92: =AF92-AI92 -> 0.0010416667 | AK92: =VLOOKUP($D92,Construction!$B:$J,(COLUMN(Construction_BuildingCost_Stone)-COLUMN(Construction_Name_and_Level)+1),FALSE)*(-1) -> -500 | AL92: =VLOOKUP($D92,Construction!$B:$J,(COLUMN(Construction_BuildingCost_Wood)-COLUMN(Construction_Name_and_Level)+1),FALSE)*(-1) -> -400 | AM92: =VLOOKUP($D92,Construction!$B:$J,(COLUMN(Construction_BuildingCost_Ore)-COLUMN(Construction_Name_and_Level)+1),FALSE)*(-1) -> -300 | AN92: =VLOOKUP($D92,Construction!$B:$J,(COLUMN(Construction_BuildingCost_Food)-COLUMN(Construction_Name_and_Level)+1),FALSE)*(-1) -> -250
B93: Construction | C93: by Quest | D93: Logging Camp 4 | E93: 14 | F93: 0.25 | G93: =VLOOKUP($D93,Construction!$B:$E,(COLUMN(Construction_BuildingReward_HeroXP)-COLUMN(Construction_Name_and_Level)+1),FALSE) -> 200 | H93: =G93*(1+F93) -> 250 | J93: =VLOOKUP($D93,Construction!$B:$F,(COLUMN(Construction_BuildingReward_Power)-COLUMN(Construction_Name_and_Level)+1),FALSE) -> 25 | O93: 0.0034722222 | P93: 0.0069444444 | AD93: =AD92+(Q$3*Q93+R$3*R93+S$3*S93+T$3*T93+U$3*U93+V$3*V93+W$3*W93+X$3*X93+Y$3*Y93+Z$3*Z93+AA$3*AA93) -> #REF! | AE93: 0.41 | AF93: =VLOOKUP($D93,Construction!$B:$C,(COLUMN(Construction_Time)-COLUMN(Construction_Name_and_Level)+1),FALSE) -> 0.0055555556 | AG93: =AF93/(1+AE93) -> 0.0039401103 | AH93: =(Q$3*Q93+R$3*R93+T$3*T93+U$3*U93+V$3*V93+W$3*W93+X$3*X93+Y$3*Y93+Z$3*Z93+AA$3*AA93)*(-1) -> 0 | AI93: =IF((AG93-O93-P93-AH93)>=0,AG93-O93-P93-AH93,0) -> 0 | AJ93: =AF93-AI93 -> 0.0055555556 | AK93: =VLOOKUP($D93,Construction!$B:$J,(COLUMN(Construction_BuildingCost_Stone)-COLUMN(Construction_Name_and_Level)+1),FALSE)*(-1) -> -492 | AL93: =VLOOKUP($D93,Construction!$B:$J,(COLUMN(Construction_BuildingCost_Wood)-COLUMN(Construction_Name_and_Level)+1),FALSE)*(-1) -> 0 | AM93: =VLOOKUP($D93,Construction!$B:$J,(COLUMN(Construction_BuildingCost_Ore)-COLUMN(Construction_Name_and_Level)+1),FALSE)*(-1) -> -492 | AN93: =VLOOKUP($D93,Construction!$B:$J,(COLUMN(Construction_BuildingCost_Food)-COLUMN(Construction_Name_and_Level)+1),FALSE)*(-1) -> -492
B94: Construction | C94: at Will | D94: Logging Camp 5 | E94: 14 | F94: 0.25 | G94: =VLOOKUP($D94,Construction!$B:$E,(COLUMN(Construction_BuildingReward_HeroXP)-COLUMN(Construction_Name_and_Level)+1),FALSE) -> 400 | H94: =G94*(1+F94) -> 500 | J94: =VLOOKUP($D94,Construction!$B:$F,(COLUMN(Construction_BuildingReward_Power)-COLUMN(Construction_Name_and_Level)+1),FALSE) -> 35 | O94: 0.0034722222 | P94: 0.0069444444 | AD94: =AD93+(Q$3*Q94+R$3*R94+S$3*S94+T$3*T94+U$3*U94+V$3*V94+W$3*W94+X$3*X94+Y$3*Y94+Z$3*Z94+AA$3*AA94) -> #REF! | AE94: 0.41 | AF94: =VLOOKUP($D94,Construction!$B:$C,(COLUMN(Construction_Time)-COLUMN(Construction_Name_and_Level)+1),FALSE) -> 0.011111111 | AG94: =AF94/(1+AE94) -> 0.0078802206 | AH94: =(Q$3*Q94+R$3*R94+T$3*T94+U$3*U94+V$3*V94+W$3*W94+X$3*X94+Y$3*Y94+Z$3*Z94+AA$3*AA94)*(-1) -> 0 | AI94: =IF((AG94-O94-P94-AH94)>=0,AG94-O94-P94-AH94,0) -> 0 | AJ94: =AF94-AI94 -> 0.011111111 | AK94: =VLOOKUP($D94,Construction!$B:$J,(COLUMN(Construction_BuildingCost_Stone)-COLUMN(Construction_Name_and_Level)+1),FALSE)*(-1) -> -837 | AL94: =VLOOKUP($D94,Construction!$B:$J,(COLUMN(Construction_BuildingCost_Wood)-COLUMN(Construction_Name_and_Level)+1),FALSE)*(-1) -> 0 | AM94: =VLOOKUP($D94,Construction!$B:$J,(COLUMN(Construction_BuildingCost_Ore)-COLUMN(Construction_Name_and_Level)+1),FALSE)*(-1) -> -837 | AN94: =VLOOKUP($D94,Construction!$B:$J,(COLUMN(Construction_BuildingCost_Food)-COLUMN(Construction_Name_and_Level)+1),FALSE)*(-1) -> -837
B95: Construction | C95: at Will | D95: Logging Camp 6 | E95: 14 | F95: 0.25 | G95: =VLOOKUP($D95,Construction!$B:$E,(COLUMN(Construction_BuildingReward_HeroXP)-COLUMN(Construction_Name_and_Level)+1),FALSE) -> 500 | H95: =G95*(1+F95) -> 625 | J95: =VLOOKUP($D95,Construction!$B:$F,(COLUMN(Construction_BuildingReward_Power)-COLUMN(Construction_Name_and_Level)+1),FALSE) -> 55 | O95: 0.0034722222 | P95: 0.0069444444 | AD95: =AD94+(Q$3*Q95+R$3*R95+S$3*S95+T$3*T95+U$3*U95+V$3*V95+W$3*W95+X$3*X95+Y$3*Y95+Z$3*Z95+AA$3*AA95) -> #REF! | AE95: 0.41 | AF95: =VLOOKUP($D95,Construction!$B:$C,(COLUMN(Construction_Time)-COLUMN(Construction_Name_and_Level)+1),FALSE) -> 0.022222222 | AG95: =AF95/(1+AE95) -> 0.015760441 | AH95: =(Q$3*Q95+R$3*R95+T$3*T95+U$3*U95+V$3*V95+W$3*W95+X$3*X95+Y$3*Y95+Z$3*Z95+AA$3*AA95)*(-1) -> 0 | AI95: =IF((AG95-O95-P95-AH95)>=0,AG95-O95-P95-AH95,0) -> 0.0053437746 | AJ95: =AF95-AI95 -> 0.016878448 | AK95: =VLOOKUP($D95,Construction!$B:$J,(COLUMN(Construction_BuildingCost_Stone)-COLUMN(Construction_Name_and_Level)+1),FALSE)*(-1) -> -1674 | AL95: =VLOOKUP($D95,Construction!$B:$J,(COLUMN(Construction_BuildingCost_Wood)-COLUMN(Construction_Name_and_Level)+1),FALSE)*(-1) -> 0 | AM95: =VLOOKUP($D95,Construction!$B:$J,(COLUMN(Construction_BuildingCost_Ore)-COLUMN(Construction_Name_and_Level)+1),FALSE)*(-1) -> -1674 | AN95: =VLOOKUP($D95,Construction!$B:$J,(COLUMN(Construction_BuildingCost_Food)-COLUMN(Construction_Name_and_Level)+1),FALSE)*(-1) -> -1674
B96: Construction | C96: by Quest | D96: Hospital 4 | E96: 14 | F96: 0.25 | G96: =VLOOKUP($D96,Construction!$B:$E,(COLUMN(Construction_BuildingReward_HeroXP)-COLUMN(Construction_Name_and_Level)+1),FALSE) -> 200 | H96: =G96*(1+F96) -> 250 | J96: =VLOOKUP($D96,Construction!$B:$F,(COLUMN(Construction_BuildingReward_Power)-COLUMN(Construction_Name_and_Level)+1),FALSE) -> 50 | O96: 0.0034722222 | P96: 0.0069444444 | AD96: =AD95+(Q$3*Q96+R$3*R96+S$3*S96+T$3*T96+U$3*U96+V$3*V96+W$3*W96+X$3*X96+Y$3*Y96+Z$3*Z96+AA$3*AA96) -> #REF! | AE96: 0.41 | AF96: =VLOOKUP($D96,Construction!$B:$C,(COLUMN(Construction_Time)-COLUMN(Construction_Name_and_Level)+1),FALSE) -> 0.0083333333 | AG96: =AF96/(1+AE96) -> 0.0059101655 | AH96: =(Q$3*Q96+R$3*R96+T$3*T96+U$3*U96+V$3*V96+W$3*W96+X$3*X96+Y$3*Y96+Z$3*Z96+AA$3*AA96)*(-1) -> 0 | AI96: =IF((AG96-O96-P96-AH96)>=0,AG96-O96-P96-AH96,0) -> 0 | AJ96: =AF96-AI96 -> 0.0083333333 | AK96: =VLOOKUP($D96,Construction!$B:$J,(COLUMN(Construction_BuildingCost_Stone)-COLUMN(Construction_Name_and_Level)+1),FALSE)*(-1) -> -2457 | AL96: =VLOOKUP($D96,Construction!$B:$J,(COLUMN(Construction_BuildingCost_Wood)-COLUMN(Construction_Name_and_Level)+1),FALSE)*(-1) -> -1966 | AM96: =VLOOKUP($D96,Construction!$B:$J,(COLUMN(Construction_BuildingCost_Ore)-COLUMN(Construction_Name_and_Level)+1),FALSE)*(-1) -> -1474 | AN96: =VLOOKUP($D96,Construction!$B:$J,(COLUMN(Construction_BuildingCost_Food)-COLUMN(Construction_Name_and_Level)+1),FALSE)*(-1) -> -1230
B97: Construction | C97: by Quest | D97: Hospital 5 | E97: 14 | F97: 0.25 | G97: =VLOOKUP($D97,Construction!$B:$E,(COLUMN(Construction_BuildingReward_HeroXP)-COLUMN(Construction_Name_and_Level)+1),FALSE) -> 400 | H97: =G97*(1+F97) -> 500 | J97: =VLOOKUP($D97,Construction!$B:$F,(COLUMN(Construction_BuildingReward_Power)-COLUMN(Construction_Name_and_Level)+1),FALSE) -> 70 | O97: 0.0034722222 | P97: 0.0069444444 | AD97: =AD96+(Q$3*Q97+R$3*R97+S$3*S97+T$3*T97+U$3*U97+V$3*V97+W$3*W97+X$3*X97+Y$3*Y97+Z$3*Z97+AA$3*AA97) -> #REF! | AE97: 0.41 | AF97: =VLOOKUP($D97,Construction!$B:$C,(COLUMN(Construction_Time)-COLUMN(Construction_Name_and_Level)+1),FALSE) -> 0.016666667 | AG97: =AF97/(1+AE97) -> 0.011820331 | AH97: =(Q$3*Q97+R$3*R97+T$3*T97+U$3*U97+V$3*V97+W$3*W97+X$3*X97+Y$3*Y97+Z$3*Z97+AA$3*AA97)*(-1) -> 0 | AI97: =IF((AG97-O97-P97-AH97)>=0,AG97-O97-P97-AH97,0) -> 0.0014036643 | AJ97: =AF97-AI97 -> 0.015263002 | AK97: =VLOOKUP($D97,Construction!$B:$J,(COLUMN(Construction_BuildingCost_Stone)-COLUMN(Construction_Name_and_Level)+1),FALSE)*(-1) -> -4177 | AL97: =VLOOKUP($D97,Construction!$B:$J,(COLUMN(Construction_BuildingCost_Wood)-COLUMN(Construction_Name_and_Level)+1),FALSE)*(-1) -> -3343 | AM97: =VLOOKUP($D97,Construction!$B:$J,(COLUMN(Construction_BuildingCost_Ore)-COLUMN(Construction_Name_and_Level)+1),FALSE)*(-1) -> -2506 | AN97: =VLOOKUP($D97,Construction!$B:$J,(COLUMN(Construction_BuildingCost_Food)-COLUMN(Construction_Name_and_Level)+1),FALSE)*(-1) -> -2091
B98: Construction | C98: at Will | D98: Quarry 6 | E98: 14 | F98: 0.25 | G98: =VLOOKUP($D98,Construction!$B:$E,(COLUMN(Construction_BuildingReward_HeroXP)-COLUMN(Construction_Name_and_Level)+1),FALSE) -> 500 | H98: =G98*(1+F98) -> 625 | J98: =VLOOKUP($D98,Construction!$B:$F,(COLUMN(Construction_BuildingReward_Power)-COLUMN(Construction_Name_and_Level)+1),FALSE) -> 55 | O98: 0.0034722222 | P98: 0.0069444444 | AD98: =AD97+(Q$3*Q98+R$3*R98+S$3*S98+T$3*T98+U$3*U98+V$3*V98+W$3*W98+X$3*X98+Y$3*Y98+Z$3*Z98+AA$3*AA98) -> #REF! | AE98: 0.41 | AF98: =VLOOKUP($D98,Construction!$B:$C,(COLUMN(Construction_Time)-COLUMN(Construction_Name_and_Level)+1),FALSE) -> 0.026041667 | AG98: =AF98/(1+AE98) -> 0.018469267 | AH98: =(Q$3*Q98+R$3*R98+T$3*T98+U$3*U98+V$3*V98+W$3*W98+X$3*X98+Y$3*Y98+Z$3*Z98+AA$3*AA98)*(-1) -> 0 | AI98: =IF((AG98-O98-P98-AH98)>=0,AG98-O98-P98-AH98,0) -> 0.0080526005 | AJ98: =AF98-AI98 -> 0.017989066 | AK98: =VLOOKUP($D98,Construction!$B:$J,(COLUMN(Construction_BuildingCost_Stone)-COLUMN(Construction_Name_and_Level)+1),FALSE)*(-1) -> 0 | AL98: =VLOOKUP($D98,Construction!$B:$J,(COLUMN(Construction_BuildingCost_Wood)-COLUMN(Construction_Name_and_Level)+1),FALSE)*(-1) -> -1674 | AM98: =VLOOKUP($D98,Construction!$B:$J,(COLUMN(Construction_BuildingCost_Ore)-COLUMN(Construction_Name_and_Level)+1),FALSE)*(-1) -> -1674 | AN98: =VLOOKUP($D98,Construction!$B:$J,(COLUMN(Construction_BuildingCost_Food)-COLUMN(Construction_Name_and_Level)+1),FALSE)*(-1) -> -1674
B99: Construction | C99: at Will | D99: Barracks 6 | E99: 14 | F99: 0.25 | G99: =VLOOKUP($D99,Construction!$B:$E,(COLUMN(Construction_BuildingReward_HeroXP)-COLUMN(Construction_Name_and_Level)+1),FALSE) -> 500 | H99: =G99*(1+F99) -> 625 | J99: =VLOOKUP($D99,Construction!$B:$F,(COLUMN(Construction_BuildingReward_Power)-COLUMN(Construction_Name_and_Level)+1),FALSE) -> 220 | O99: 0.0034722222 | P99: 0.0069444444 | T99: -1 | U99: -1 | AD99: =AD98+(Q$3*Q99+R$3*R99+S$3*S99+T$3*T99+U$3*U99+V$3*V99+W$3*W99+X$3*X99+Y$3*Y99+Z$3*Z99+AA$3*AA99) -> #REF! | AE99: 0.41 | AF99: =VLOOKUP($D99,Construction!$B:$C,(COLUMN(Construction_Time)-COLUMN(Construction_Name_and_Level)+1),FALSE) -> 0.033333333 | AG99: =AF99/(1+AE99) -> 0.023640662 | AH99: =(Q$3*Q99+R$3*R99+T$3*T99+U$3*U99+V$3*V99+W$3*W99+X$3*X99+Y$3*Y99+Z$3*Z99+AA$3*AA99)*(-1) -> 0.017361111 | AI99: =IF((AG99-O99-P99-AH99)>=0,AG99-O99-P99-AH99,0) -> 0 | AJ99: =AF99-AI99 -> 0.033333333 | AK99: =VLOOKUP($D99,Construction!$B:$J,(COLUMN(Construction_BuildingCost_Stone)-COLUMN(Construction_Name_and_Level)+1),FALSE)*(-1) -> -8354 | AL99: =VLOOKUP($D99,Construction!$B:$J,(COLUMN(Construction_BuildingCost_Wood)-COLUMN(Construction_Name_and_Level)+1),FALSE)*(-1) -> -6686 | AM99: =VLOOKUP($D99,Construction!$B:$J,(COLUMN(Construction_BuildingCost_Ore)-COLUMN(Construction_Name_and_Level)+1),FALSE)*(-1) -> -5012 | AN99: =VLOOKUP($D99,Construction!$B:$J,(COLUMN(Construction_BuildingCost_Food)-COLUMN(Construction_Name_and_Level)+1),FALSE)*(-1) -> -4182
