Workbook
Name activechart1: army!$M$198:$M$202
Name buffvalue: hero!$I$19:$P$36
Name goldvalue: research!$DC$3:$DJ$16
Name n: hero!$I$19:$Q$36
Name resourcevalue: building!$V$6:$AC$21
Name selectchart: CHOOSE(army!$I$221,resourcevalue,timevalue,buffvalue,goldvalue,threecompare)
Name threecompare: hero!$AC$17:$AJ$34
Name timevalue: hero!$R$19:$Y$36

Sheet brief
M1: Troop Benefit | N1: Troop Benefit | O1: Troop Benefit | P1: Troop Benefit | Q1: Troop Benefit | R1: Troop Benefit | S1: Troop Benefit | T1: Troop Benefit | U1: Building Benefit | V1: Training Benefit | W1: Training Benefit | X1: Training Benefit | Y1: Knight Benefit | Z1: March Benefit | AA1: March Benefit | AB1: March Benefit | AC1: March Benefit | AD1: March Benefit | AE1: March Benefit | AF1: March Benefit | AG1: March Benefit | AH1: March Benefit | AI1: March Benefit | AJ1: March Benefit | AK1: Population Benefit | AL1: Population Benefit | AM1: Population Benefit | AN1: Population Benefit | AO1: Resource Benefit | AP1: Resource Benefit | AQ1: Resource Benefit | AR1: Resource Benefit | AS1: Resource Benefit | AT1: Resource Benefit | AU1: Resource Benefit | AV1: Resource Benefit | AW1: Resource Benefit | AX1: Resource Benefit | AY1: Resource Benefit | AZ1: Resource Benefit | BA1: Resource Benefit
A2: Building / Research | C2: Type | D2: Level ID | E2: Prestige Level | F2: Building Level | G2: Comment | H2: UI Changes | I2: Prestige Bonus | J2: Might | K2: Previous strings | L2: New strings | M2: Trap, Caltrops, Crossbow slots | N2: Boiling Oil, Spiked Barrier, Trebuchet slots | O2: Greek Fire, Sulfur, Hellfire Thrower slots | P2: % buff to attack | Q2: % buff to health | R2: % buff to load | S2: % buff to health to troops reinforcing you | T2: % debuff attacking player attack | U2: % increase in construction speed | V2: Training Time Speed Increase (Infantry) | W2: Training Time Speed Increase (Horse) | X2: Training Time Speed Increase (Artillery) | Y2: Knights unlocked | Z2: % debuff attacking player march speed | AA2: Scout Time Speed Increase | AB2: Attack March Time Speed Increase (Infantry) | AC2: Attack March Time Speed Increase (Horse) | AD2: Attack March Time Speed Increase (Artillery) | AE2: Support March Time Speed Increase (Infantry) | AF2: Support March Time Speed Increase (Horse) | AG2: Support March Time Speed Increase (Artillery) | AH2: Scout March Time Speed Increase | AI2: # of marches | AJ2: # of troops per march | AK2: Workers | AL2: Population Cap | AM2: Population | AN2: Labor Population | AO2: Gold Protection | AP2: Food Protection | AQ2: Wood Protection | AR2: Stone Protection | AS2: Ore Protection | AT2: Food Production | AU2: Wood Production | AV2: Stone Production | AW2: Ore Production | AX2: Food Capacity | AY2: Wood Capacity | AZ2: Stone Capacity | BA2: Ore Capacity
A3: Alchemy Lab | B3: =VLOOKUP(A3,'name convert'!$A$1:$B$39,2,FALSE) -> Academy | C3: Building | D3: 1 | E3: 1 | F3: 1 | J3: 0 | K3: Level 1 research | L3: Level 1 research
A4: Alchemy Lab | B4: =VLOOKUP(A4,'name convert'!$A$1:$B$39,2,FALSE) -> Academy | C4: Building | D4: 2 | E4: 1 | F4: 2 | J4: 0 | K4: Level 2 research | L4: Level 2 research
A5: Alchemy Lab | B5: =VLOOKUP(A5,'name convert'!$A$1:$B$39,2,FALSE) -> Academy | C5: Building | D5: 3 | E5: 1 | F5: 3 | J5: 0 | K5: Level 3 research | L5: Level 3 research
A6: Alchemy Lab | B6: =VLOOKUP(A6,'name convert'!$A$1:$B$39,2,FALSE) -> Academy | C6: Building | D6: 4 | E6: 1 | F6: 4 | J6: 0 | K6: Level 4 research | L6: Level 4 research
A7: Alchemy Lab | B7: =VLOOKUP(A7,'name convert'!$A$1:$B$39,2,FALSE) -> Academy | C7: Building | D7: 5 | E7: 1 | F7: 5 | J7: 0 | K7: Level 5 research | L7: Level 5 research
A8: Alchemy Lab | B8: =VLOOKUP(A8,'name convert'!$A$1:$B$39,2,FALSE) -> Academy | C8: Building | D8: 6 | E8: 1 | F8: 6 | J8: 0 | K8: Level 6 research | L8: Level 6 research
A9: Alchemy Lab | B9: =VLOOKUP(A9,'name convert'!$A$1:$B$39,2,FALSE) -> Academy | C9: Building | D9: 7 | E9: 1 | F9: 7 | J9: 0 | K9: Level 7 research | L9: Level 7 research
A10: Alchemy Lab | B10: =VLOOKUP(A10,'name convert'!$A$1:$B$39,2,FALSE) -> Academy | C10: Building | D10: 8 | E10: 1 | F10: 8 | J10: 0 | K10: Level 8 research | L10: Level 8 research
A11: Alchemy Lab | B11: =VLOOKUP(A11,'name convert'!$A$1:$B$39,2,FALSE) -> Academy | C11: Building | D11: 9 | E11: 1 | F11: 9 | J11: 0 | K11: Level 9 research | L11: Level 9 research
A12: Alchemy Lab | B12: =VLOOKUP(A12,'name convert'!$A$1:$B$39,2,FALSE) -> Academy | C12: Building | D12: 10 | E12: 1 | F12: 10 | J12: 0 | K12: Level 10 research | L12: Level 10 research
A13: Alchemy Lab | B13: =VLOOKUP(A13,'name convert'!$A$1:$B$39,2,FALSE) -> Academy | C13: Building | D13: 11 | E13: 2 | F13: 1 | J13: 0 | L13: Level 11 research
A14: Alchemy Lab | B14: =VLOOKUP(A14,'name convert'!$A$1:$B$39,2,FALSE) -> Academy | C14: Building | D14: 12 | E14: 2 | F14: 2 | J14: 0 | L14: Level 12 research
A15: Alchemy Lab | B15: =VLOOKUP(A15,'name convert'!$A$1:$B$39,2,FALSE) -> Academy | C15: Building | D15: 13 | E15: 2 | F15: 3 | J15: 0 | L15: Level 13 research
A16: Alchemy Lab | B16: =VLOOKUP(A16,'name convert'!$A$1:$B$39,2,FALSE) -> Academy | C16: Building | D16: 14 | E16: 2 | F16: 4 | J16: 0 | L16: Level 14 research
A17: Alchemy Lab | B17: =VLOOKUP(A17,'name convert'!$A$1:$B$39,2,FALSE) -> Academy | C17: Building | D17: 15 | E17: 2 | F17: 5 | J17: 0 | L17: Level 15 research
A18: Alchemy Lab | B18: =VLOOKUP(A18,'name convert'!$A$1:$B$39,2,FALSE) -> Academy | C18: Building | D18: 16 | E18: 2 | F18: 6 | J18: 0 | L18: Level 16 research
A19: Alchemy Lab | B19: =VLOOKUP(A19,'name convert'!$A$1:$B$39,2,FALSE) -> Academy | C19: Building | D19: 17 | E19: 2 | F19: 7 | J19: 0 | L19: Level 17 research
A20: Alchemy Lab | B20: =VLOOKUP(A20,'name convert'!$A$1:$B$39,2,FALSE) -> Academy | C20: Building | D20: 18 | E20: 2 | F20: 8 | J20: 0 | L20: Level 18 research
A21: Alchemy Lab | B21: =VLOOKUP(A21,'name convert'!$A$1:$B$39,2,FALSE) -> Academy | C21: Building | D21: 19 | E21: 2 | F21: 9 | J21: 0 | L21: Level 19 research
A22: Alchemy Lab | B22: =VLOOKUP(A22,'name convert'!$A$1:$B$39,2,FALSE) -> Academy | C22: Building | D22: 20 | E22: 2 | F22: 10 | J22: 0 | L22: Level 20 research
A23: Alchemy Lab | B23: =VLOOKUP(A23,'name convert'!$A$1:$B$39,2,FALSE) -> Academy | C23: Building | D23: 21 | E23: 2 | F23: 11 | J23: 0 | L23: Level 21 research
A24: Barracks | B24: =VLOOKUP(A24,'name convert'!$A$1:$B$39,2,FALSE) -> Barracks | C24: Building | D24: 1 | E24: 1 | F24: 1 | G24: Need speed benefit | J24: 0 | K24: Train Supply Troops; train light cavalry; training speed increase | L24: Train Supply Troops; train light cavalry; training speed increase | V24: NEED | W24: NEED | X24: NEED
A25: Barracks | B25: =VLOOKUP(A25,'name convert'!$A$1:$B$39,2,FALSE) -> Barracks | C25: Building | D25: 2 | E25: 1 | F25: 2 | G25: Need speed benefit | J25: 0 | K25: Train Militiamen; training speed decrease | L25: Train Militiamen; training speed increase | V25: NEED | W25: NEED | X25: NEED
A26: Barracks | B26: =VLOOKUP(A26,'name convert'!$A$1:$B$39,2,FALSE) -> Barracks | C26: Building | D26: 3 | E26: 1 | F26: 3 | G26: Need speed benefit | J26: 0 | K26: Train Archers; training speed decrease | L26: Train Archers; training speed increase | V26: NEED | W26: NEED | X26: NEED
A27: Barracks | B27: =VLOOKUP(A27,'name convert'!$A$1:$B$39,2,FALSE) -> Barracks | C27: Building | D27: 4 | E27: 1 | F27: 4 | G27: Need speed benefit | J27: 0 | K27: Train Supply Cart; train Calavry; training speed decrease | L27: Train Supply Cart; train Calavry; training speed increase | V27: NEED | W27: NEED | X27: NEED
A28: Barracks | B28: =VLOOKUP(A28,'name convert'!$A$1:$B$39,2,FALSE) -> Barracks | C28: Building | D28: 5 | E28: 1 | F28: 5 | G28: Need speed benefit | J28: 0 | K28: Train Swordsmen; training speed decrease | L28: Train Swordsmen; training speed increase | V28: NEED | W28: NEED | X28: NEED
A29: Barracks | B29: =VLOOKUP(A29,'name convert'!$A$1:$B$39,2,FALSE) -> Barracks | C29: Building | D29: 6 | E29: 1 | F29: 6 | G29: Need speed benefit | J29: 0 | K29: Train Ballistae; training speed decrease | L29: Train Ballistae; training speed increase | V29: NEED | W29: NEED | X29: NEED
A30: Barracks | B30: =VLOOKUP(A30,'name convert'!$A$1:$B$39,2,FALSE) -> Barracks | C30: Building | D30: 7 | E30: 1 | F30: 7 | G30: Need speed benefit | J30: 0 | K30: Train Supply Wagon; training speed decrease | L30: Train Supply Wagon; training speed increase | V30: NEED | W30: NEED | X30: NEED
A31: Barracks | B31: =VLOOKUP(A31,'name convert'!$A$1:$B$39,2,FALSE) -> Barracks | C31: Building | D31: 8 | E31: 1 | F31: 8 | G31: Need speed benefit | J31: 0 | K31: Train Heavy Cavalry; training speed decrease | L31: Train Heavy Cavalry; training speed increase | V31: NEED | W31: NEED | X31: NEED
A32: Barracks | B32: =VLOOKUP(A32,'name convert'!$A$1:$B$39,2,FALSE) -> Barracks | C32: Building | D32: 9 | E32: 1 | F32: 9 | G32: Need speed benefit | J32: 0 | K32: Train Battering Rams; training speed decrease | L32: Train Battering Rams; training speed increase | V32: NEED | W32: NEED | X32: NEED
A33: Barracks | B33: =VLOOKUP(A33,'name convert'!$A$1:$B$39,2,FALSE) -> Barracks | C33: Building | D33: 10 | E33: 1 | F33: 10 | G33: Need speed benefit | J33: 0 | K33: Train Catapults; training speed decrease | L33: Train Catapults; training speed increase | V33: NEED | W33: NEED | X33: NEED
A34: Barracks | B34: =VLOOKUP(A34,'name convert'!$A$1:$B$39,2,FALSE) -> Barracks | C34: Building | D34: 11 | E34: 2 | F34: 1 | I34: NEED | J34: 0 | L34: Training speed increase | V34: =V24+(V24*$I34) -> #VALUE! | W34: =W24+(W24*$I34) -> #VALUE! | X34: =X24+(X24*$I34) -> #VALUE!
A35: Barracks | B35: =VLOOKUP(A35,'name convert'!$A$1:$B$39,2,FALSE) -> Barracks | C35: Building | D35: 12 | E35: 2 | F35: 2 | I35: NEED | J35: 0 | L35: Training speed increase | V35: =V25+(V25*$I35) -> #VALUE! | W35: =W25+(W25*$I35) -> #VALUE! | X35: =X25+(X25*$I35) -> #VALUE!
A36: Barracks | B36: =VLOOKUP(A36,'name convert'!$A$1:$B$39,2,FALSE) -> Barracks | C36: Building | D36: 13 | E36: 2 | F36: 3 | I36: NEED | J36: 0 | L36: Training speed increase | V36: =V26+(V26*$I36) -> #VALUE! | W36: =W26+(W26*$I36) -> #VALUE! | X36: =X26+(X26*$I36) -> #VALUE!
A37: Barracks | B37: =VLOOKUP(A37,'name convert'!$A$1:$B$39,2,FALSE) -> Barracks | C37: Building | D37: 14 | E37: 2 | F37: 4 | I37: NEED | J37: 0 | L37: Training speed increase | V37: =V27+(V27*$I37) -> #VALUE! | W37: =W27+(W27*$I37) -> #VALUE! | X37: =X27+(X27*$I37) -> #VALUE!
A38: Barracks | B38: =VLOOKUP(A38,'name convert'!$A$1:$B$39,2,FALSE) -> Barracks | C38: Building | D38: 15 | E38: 2 | F38: 5 | I38: NEED | J38: 0 | L38: Training speed increase | V38: =V28+(V28*$I38) -> #VALUE! | W38: =W28+(W28*$I38) -> #VALUE! | X38: =X28+(X28*$I38) -> #VALUE!
A39: Barracks | B39: =VLOOKUP(A39,'name convert'!$A$1:$B$39,2,FALSE) -> Barracks | C39: Building | D39: 16 | E39: 2 | F39: 6 | I39: NEED | J39: 0 | L39: Training speed increase | V39: =V29+(V29*$I39) -> #VALUE! | W39: =W29+(W29*$I39) -> #VALUE! | X39: =X29+(X29*$I39) -> #VALUE!
A40: Barracks | B40: =VLOOKUP(A40,'name convert'!$A$1:$B$39,2,FALSE) -> Barracks | C40: Building | D40: 17 | E40: 2 | F40: 7 | I40: NEED | J40: 0 | L40: Training speed increase | V40: =V30+(V30*$I40) -> #VALUE! | W40: =W30+(W30*$I40) -> #VALUE! | X40: =X30+(X30*$I40) -> #VALUE!
A41: Barracks | B41: =VLOOKUP(A41,'name convert'!$A$1:$B$39,2,FALSE) -> Barracks | C41: Building | D41: 18 | E41: 2 | F41: 8 | I41: NEED | J41: 0 | L41: Training speed increase | V41: =V31+(V31*$I41) -> #VALUE! | W41: =W31+(W31*$I41) -> #VALUE! | X41: =X31+(X31*$I41) -> #VALUE!
A42: Barracks | B42: =VLOOKUP(A42,'name convert'!$A$1:$B$39,2,FALSE) -> Barracks | C42: Building | D42: 19 | E42: 2 | F42: 9 | I42: NEED | J42: 0 | L42: Training speed increase | V42: =V32+(V32*$I42) -> #VALUE! | W42: =W32+(W32*$I42) -> #VALUE! | X42: =X32+(X32*$I42) -> #VALUE!
A43: Barracks | B43: =VLOOKUP(A43,'name convert'!$A$1:$B$39,2,FALSE) -> Barracks | C43: Building | D43: 20 | E43: 2 | F43: 10 | I43: NEED | J43: 0 | L43: Training speed increase | V43: =V33+(V33*$I43) -> #VALUE! | W43: =W33+(W33*$I43) -> #VALUE! | X43: =X33+(X33*$I43) -> #VALUE!
A44: Barracks | B44: =VLOOKUP(A44,'name convert'!$A$1:$B$39,2,FALSE) -> Barracks | C44: Building | D44: 21 | E44: 2 | F44: 11 | I44: NEED | J44: 0 | L44: Training speed increase | V44: =V34+(V34*$I44) -> #VALUE! | W44: =W34+(W34*$I44) -> #VALUE! | X44: =X34+(X34*$I44) -> #VALUE!
A45: Blacksmith | B45: =VLOOKUP(A45,'name convert'!$A$1:$B$39,2,FALSE) -> Forge | C45: Building | D45: 1 | E45: 1 | F45: 1 | G45: Need speed benefit | J45: 0 | K45: Gate building | L45: Gate building; train Ground troops faster | V45: NEED
A46: Blacksmith | B46: =VLOOKUP(A46,'name convert'!$A$1:$B$39,2,FALSE) -> Forge | C46: Building | D46: 2 | E46: 1 | F46: 2 | G46: Need speed benefit | J46: 0 | K46: Gate building | L46: Gate building; train Ground troops faster | V46: NEED
A47: Blacksmith | B47: =VLOOKUP(A47,'name convert'!$A$1:$B$39,2,FALSE) -> Forge | C47: Building | D47: 3 | E47: 1 | F47: 3 | G47: Need speed benefit | J47: 0 | K47: Gate building | L47: Gate building; train Ground troops faster | V47: NEED
A48: Blacksmith | B48: =VLOOKUP(A48,'name convert'!$A$1:$B$39,2,FALSE) -> Forge | C48: Building | D48: 4 | E48: 1 | F48: 4 | G48: Need speed benefit | J48: 0 | K48: Gate building | L48: Gate building; train Ground troops faster | V48: NEED
A49: Blacksmith | B49: =VLOOKUP(A49,'name convert'!$A$1:$B$39,2,FALSE) -> Forge | C49: Building | D49: 5 | E49: 1 | F49: 5 | G49: Need speed benefit | J49: 0 | K49: Gate building | L49: Gate building; train Ground troops faster | V49: NEED
A50: Blacksmith | B50: =VLOOKUP(A50,'name convert'!$A$1:$B$39,2,FALSE) -> Forge | C50: Building | D50: 6 | E50: 1 | F50: 6 | G50: Need speed benefit | J50: 0 | K50: Gate building | L50: Gate building; train Ground troops faster | V50: NEED
A51: Blacksmith | B51: =VLOOKUP(A51,'name convert'!$A$1:$B$39,2,FALSE) -> Forge | C51: Building | D51: 7 | E51: 1 | F51: 7 | G51: Need speed benefit | J51: 0 | K51: Gate building | L51: Gate building; train Ground troops faster | V51: NEED
A52: Blacksmith | B52: =VLOOKUP(A52,'name convert'!$A$1:$B$39,2,FALSE) -> Forge | C52: Building | D52: 8 | E52: 1 | F52: 8 | G52: Need speed benefit | J52: 0 | K52: Gate building | L52: Gate building; train Ground troops faster | V52: NEED
A53: Blacksmith | B53: =VLOOKUP(A53,'name convert'!$A$1:$B$39,2,FALSE) -> Forge | C53: Building | D53: 9 | E53: 1 | F53: 9 | G53: Need speed benefit | J53: 0 | K53: Gate building | L53: Gate building; train Ground troops faster | V53: NEED
A54: Blacksmith | B54: =VLOOKUP(A54,'name convert'!$A$1:$B$39,2,FALSE) -> Forge | C54: Building | D54: 10 | E54: 1 | F54: 10 | G54: Need speed benefit | J54: 0 | K54: Gate building | L54: Gate building; train Ground troops faster | V54: NEED
A55: Blacksmith | B55: =VLOOKUP(A55,'name convert'!$A$1:$B$39,2,FALSE) -> Forge | C55: Building | D55: 11 | E55: 2 | F55: 1 | I55: NEED | J55: 0 | L55: Gate building; train Ground troops faster | V55: =V45+(V45*$I55) -> #VALUE!
A56: Blacksmith | B56: =VLOOKUP(A56,'name convert'!$A$1:$B$39,2,FALSE) -> Forge | C56: Building | D56: 12 | E56: 2 | F56: 2 | I56: NEED | J56: 0 | L56: Gate building; train Ground troops faster | V56: =V46+(V46*$I56) -> #VALUE!
A57: Blacksmith | B57: =VLOOKUP(A57,'name convert'!$A$1:$B$39,2,FALSE) -> Forge | C57: Building | D57: 13 | E57: 2 | F57: 3 | I57: NEED | J57: 0 | L57: Gate building; train Ground troops faster | V57: =V47+(V47*$I57) -> #VALUE!
A58: Blacksmith | B58: =VLOOKUP(A58,'name convert'!$A$1:$B$39,2,FALSE) -> Forge | C58: Building | D58: 14 | E58: 2 | F58: 4 | I58: NEED | J58: 0 | L58: Gate building; train Ground troops faster | V58: =V48+(V48*$I58) -> #VALUE!
A59: Blacksmith | B59: =VLOOKUP(A59,'name convert'!$A$1:$B$39,2,FALSE) -> Forge | C59: Building | D59: 15 | E59: 2 | F59: 5 | I59: NEED | J59: 0 | L59: Gate building; train Ground troops faster | V59: =V49+(V49*$I59) -> #VALUE!
A60: Blacksmith | B60: =VLOOKUP(A60,'name convert'!$A$1:$B$39,2,FALSE) -> Forge | C60: Building | D60: 16 | E60: 2 | F60: 6 | I60: NEED | J60: 0 | L60: Gate building; train Ground troops faster | V60: =V50+(V50*$I60) -> #VALUE!
A61: Blacksmith | B61: =VLOOKUP(A61,'name convert'!$A$1:$B$39,2,FALSE) -> Forge | C61: Building | D61: 17 | E61: 2 | F61: 7 | I61: NEED | J61: 0 | L61: Gate building; train Ground troops faster | V61: =V51+(V51*$I61) -> #VALUE!
A62: Blacksmith | B62: =VLOOKUP(A62,'name convert'!$A$1:$B$39,2,FALSE) -> Forge | C62: Building | D62: 18 | E62: 2 | F62: 8 | I62: NEED | J62: 0 | L62: Gate building; train Ground troops faster | V62: =V52+(V52*$I62) -> #VALUE!
A63: Blacksmith | B63: =VLOOKUP(A63,'name convert'!$A$1:$B$39,2,FALSE) -> Forge | C63: Building | D63: 19 | E63: 2 | F63: 9 | I63: NEED | J63: 0 | L63: Gate building; train Ground troops faster | V63: =V53+(V53*$I63) -> #VALUE!
A64: Blacksmith | B64: =VLOOKUP(A64,'name convert'!$A$1:$B$39,2,FALSE) -> Forge | C64: Building | D64: 20 | E64: 2 | F64: 10 | I64: NEED | J64: 0 | L64: Gate building; train Ground troops faster | V64: =V54+(V54*$I64) -> #VALUE!
A65: Blacksmith | B65: =VLOOKUP(A65,'name convert'!$A$1:$B$39,2,FALSE) -> Forge | C65: Building | D65: 21 | E65: 2 | F65: 11 | I65: NEED | J65: 0 | L65: Gate building; train Ground troops faster | V65: =V55+(V55*$I65) -> #VALUE!
A66: Castle | B66: =VLOOKUP(A66,'name convert'!$A$1:$B$39,2,FALSE) -> keep | C66: Building | D66: 1 | E66: 1 | F66: 1 | J66: 0 | K66: Control 1 wild; 13 resource plots | L66: Control 1 wild; 13 resource plots
A67: Castle | B67: =VLOOKUP(A67,'name convert'!$A$1:$B$39,2,FALSE) -> keep | C67: Building | D67: 2 | E67: 1 | F67: 2 | J67: 0 | K67: Control 2 wilds; 16 resource plots | L67: Control 2 wilds; 16 resource plots
A68: Castle | B68: =VLOOKUP(A68,'name convert'!$A$1:$B$39,2,FALSE) -> keep | C68: Building | D68: 3 | E68: 1 | F68: 3 | J68: 0 | K68: Control 3 wilds; 19 resource plots | L68: Control 3 wilds; 19 resource plots
A69: Castle | B69: =VLOOKUP(A69,'name convert'!$A$1:$B$39,2,FALSE) -> keep | C69: Building | D69: 4 | E69: 1 | F69: 4 | J69: 0 | K69: Control 4 wilds; 22 resource plots | L69: Control 4 wilds; 22 resource plots
A70: Castle | B70: =VLOOKUP(A70,'name convert'!$A$1:$B$39,2,FALSE) -> keep | C70: Building | D70: 5 | E70: 1 | F70: 5 | J70: 0 | K70: Control 5 wilds; 25 resource plots | L70: Control 5 wilds; 25 resource plots
A71: Castle | B71: =VLOOKUP(A71,'name convert'!$A$1:$B$39,2,FALSE) -> keep | C71: Building | D71: 6 | E71: 1 | F71: 6 | J71: 0 | K71: Control 6 wilds; 28 resource plots | L71: Control 6 wilds; 28 resource plots
A72: Castle | B72: =VLOOKUP(A72,'name convert'!$A$1:$B$39,2,FALSE) -> keep | C72: Building | D72: 7 | E72: 1 | F72: 7 | J72: 0 | K72: Control 7 wilds; 31 resource plots | L72: Control 7 wilds; 31 resource plots
A73: Castle | B73: =VLOOKUP(A73,'name convert'!$A$1:$B$39,2,FALSE) -> keep | C73: Building | D73: 8 | E73: 1 | F73: 8 | J73: 0 | K73: Control 8 wilds; 34 resource plots | L73: Control 8 wilds; 34 resource plots
A74: Castle | B74: =VLOOKUP(A74,'name convert'!$A$1:$B$39,2,FALSE) -> keep | C74: Building | D74: 9 | E74: 1 | F74: 9 | J74: 0 | K74: Control 9 wilds; 37 resource plots | L74: Control 9 wilds; 37 resource plots
A75: Castle | B75: =VLOOKUP(A75,'name convert'!$A$1:$B$39,2,FALSE) -> keep | C75: Building | D75: 10 | E75: 1 | F75: 10 | J75: 0 | K75: Control 10 wilds; 40 resource plots | L75: Control 10 wilds; 40 resource plots
A76: Castle | B76: =VLOOKUP(A76,'name convert'!$A$1:$B$39,2,FALSE) -> keep | C76: Building | D76: 11 | E76: 2 | F76: 1 | J76: 0 | L76: Control 10 wilds; 40 resource plots
A77: Castle | B77: =VLOOKUP(A77,'name convert'!$A$1:$B$39,2,FALSE) -> keep | C77: Building | D77: 12 | E77: 2 | F77: 2 | J77: 0 | L77: Control 10 wilds; 40 resource plots
A78: Castle | B78: =VLOOKUP(A78,'name convert'!$A$1:$B$39,2,FALSE) -> keep | C78: Building | D78: 13 | E78: 2 | F78: 3 | J78: 0 | L78: Control 10 wilds; 40 resource plots
A79: Castle | B79: =VLOOKUP(A79,'name convert'!$A$1:$B$39,2,FALSE) -> keep | C79: Building | D79: 14 | E79: 2 | F79: 4 | J79: 0 | L79: Control 10 wilds; 40 resource plots
A80: Castle | B80: =VLOOKUP(A80,'name convert'!$A$1:$B$39,2,FALSE) -> keep | C80: Building | D80: 15 | E80: 2 | F80: 5 | J80: 0 | L80: Control 10 wilds; 40 resource plots
A81: Castle | B81: =VLOOKUP(A81,'name convert'!$A$1:$B$39,2,FALSE) -> keep | C81: Building | D81: 16 | E81: 2 | F81: 6 | J81: 0 | L81: Control 10 wilds; 40 resource plots
A82: Castle | B82: =VLOOKUP(A82,'name convert'!$A$1:$B$39,2,FALSE) -> keep | C82: Building | D82: 17 | E82: 2 | F82: 7 | J82: 0 | L82: Control 10 wilds; 40 resource plots
A83: Castle | B83: =VLOOKUP(A83,'name convert'!$A$1:$B$39,2,FALSE) -> keep | C83: Building | D83: 18 | E83: 2 | F83: 8 | J83: 0 | L83: Control 10 wilds; 40 resource plots
A84: Castle | B84: =VLOOKUP(A84,'name convert'!$A$1:$B$39,2,FALSE) -> keep | C84: Building | D84: 19 | E84: 2 | F84: 9 | J84: 0 | L84: Control 10 wilds; 40 resource plots
A85: Castle | B85: =VLOOKUP(A85,'name convert'!$A$1:$B$39,2,FALSE) -> keep | C85: Building | D85: 20 | E85: 2 | F85: 10 | J85: 0 | L85: Control 10 wilds; 40 resource plots
A86: Castle | B86: =VLOOKUP(A86,'name convert'!$A$1:$B$39,2,FALSE) -> keep | C86: Building | D86: 21 | E86: 2 | F86: 11 | J86: 0 | L86: Control 10 wilds; 40 resource plots
A87: Cottage | B87: =VLOOKUP(A87,'name convert'!$A$1:$B$39,2,FALSE) -> home | C87: Building | D87: 1 | E87: 1 | F87: 1 | J87: 0 | K87: Increase population rate; increase population cap | L87: Increase population rate; increase population cap | AL87: =D87*100 -> 100 | AM87: =D87*50 -> 50
A88: Cottage | B88: =VLOOKUP(A88,'name convert'!$A$1:$B$39,2,FALSE) -> home | C88: Building | D88: 2 | E88: 1 | F88: 2 | J88: 0 | K88: Increase population rate; increase population cap | L88: Increase population rate; increase population cap | AL88: =D88*100 -> 200 | AM88: =D88*50 -> 100
A89: Cottage | B89: =VLOOKUP(A89,'name convert'!$A$1:$B$39,2,FALSE) -> home | C89: Building | D89: 3 | E89: 1 | F89: 3 | J89: 0 | K89: Increase population rate; increase population cap | L89: Increase population rate; increase population cap | AL89: =D89*100 -> 300 | AM89: =D89*50 -> 150
A90: Cottage | B90: =VLOOKUP(A90,'name convert'!$A$1:$B$39,2,FALSE) -> home | C90: Building | D90: 4 | E90: 1 | F90: 4 | J90: 0 | K90: Increase population rate; increase population cap | L90: Increase population rate; increase population cap | AL90: =D90*100 -> 400 | AM90: =D90*50 -> 200
A91: Cottage | B91: =VLOOKUP(A91,'name convert'!$A$1:$B$39,2,FALSE) -> home | C91: Building | D91: 5 | E91: 1 | F91: 5 | J91: 0 | K91: Increase population rate; increase population cap | L91: Increase population rate; increase population cap | AL91: =D91*100 -> 500 | AM91: =D91*50 -> 250
A92: Cottage | B92: =VLOOKUP(A92,'name convert'!$A$1:$B$39,2,FALSE) -> home | C92: Building | D92: 6 | E92: 1 | F92: 6 | J92: 0 | K92: Increase population rate; increase population cap | L92: Increase population rate; increase population cap | AL92: =D92*100 -> 600 | AM92: =D92*50 -> 300
A93: Cottage | B93: =VLOOKUP(A93,'name convert'!$A$1:$B$39,2,FALSE) -> home | C93: Building | D93: 7 | E93: 1 | F93: 7 | J93: 0 | K93: Increase population rate; increase population cap | L93: Increase population rate; increase population cap | AL93: =D93*100 -> 700 | AM93: =D93*50 -> 350
A94: Cottage | B94: =VLOOKUP(A94,'name convert'!$A$1:$B$39,2,FALSE) -> home | C94: Building | D94: 8 | E94: 1 | F94: 8 | J94: 0 | K94: Increase population rate; increase population cap | L94: Increase population rate; increase population cap | AL94: =D94*100 -> 800 | AM94: =D94*50 -> 400
A95: Cottage | B95: =VLOOKUP(A95,'name convert'!$A$1:$B$39,2,FALSE) -> home | C95: Building | D95: 9 | E95: 1 | F95: 9 | J95: 0 | K95: Increase population rate; increase population cap | L95: Increase population rate; increase population cap | AL95: =D95*100 -> 900 | AM95: =D95*50 -> 450
A96: Cottage | B96: =VLOOKUP(A96,'name convert'!$A$1:$B$39,2,FALSE) -> home | C96: Building | D96: 10 | E96: 1 | F96: 10 | J96: 0 | K96: Increase population rate; increase population cap | L96: Increase population rate; increase population cap | AL96: =D96*100 -> 1000 | AM96: =D96*50 -> 500
A97: Cottage | B97: =VLOOKUP(A97,'name convert'!$A$1:$B$39,2,FALSE) -> home | C97: Building | D97: 11 | E97: 2 | F97: 1 | I97: 0.2 | J97: 0 | L97: Increase population rate; increase population cap | AL97: =AL87+(AL87*$I97) -> 120 | AM97: =AM87+(AM87*$I97) -> 60
A98: Cottage | B98: =VLOOKUP(A98,'name convert'!$A$1:$B$39,2,FALSE) -> home | C98: Building | D98: 12 | E98: 2 | F98: 2 | I98: 0.2 | J98: 0 | L98: Increase population rate; increase population cap | AL98: =AL88+(AL88*$I98) -> 240 | AM98: =AM88+(AM88*$I98) -> 120
A99: Cottage | B99: =VLOOKUP(A99,'name convert'!$A$1:$B$39,2,FALSE) -> home | C99: Building | D99: 13 | E99: 2 | F99: 3 | I99: 0.2 | J99: 0 | L99: Increase population rate; increase population cap | AL99: =AL89+(AL89*$I99) -> 360 | AM99: =AM89+(AM89*$I99) -> 180
A100: Cottage | B100: =VLOOKUP(A100,'name convert'!$A$1:$B$39,2,FALSE) -> home | C100: Building | D100: 14 | E100: 2 | F100: 4 | I100: 0.2 | J100: 0 | L100: Increase population rate; increase population cap | AL100: =AL90+(AL90*$I100) -> 480 | AM100: =AM90+(AM90*$I100) -> 240
...

Sheet Current
S1: Level Requirements | T1: Gate Requirement | U1: Time Requirements | X1: Resource Requirements | AB1: Building Requirements | AU1: Research Requirements
A2: Building / Research | B2: Type | C2: Level | D2: Might | E2: Bonus | F2: Training Time Decrease | G2: Workers | H2: Population Cap | I2: Population | J2: Labor Population | K2: Food Production | L2: Wood Production | M2: Stone Production | N2: Ore Production | O2: Food Capacity | P2: Wood Capacity | Q2: Stone Capacity | R2: Ore Capacity | S2: Player Level | T2: Item | U2: Build Time (sec) | V2: Build Time (min) | W2: Gold | X2: Food | Y2: Wood | Z2: Stone | AA2: Ore | AB2: Castle | AC2: Alchemy Lab | AD2: Cottage | AE2: Barracks | AF2: Knight's Hall | AG2: Storehouse | AH2: Rally Point | AI2: Embassy | AJ2: Blacksmith | AK2: Workshop | AL2: Watch Tower | AM2: Stable | AN2: Relief Station | AO2: Round Tower | AP2: Wall | AQ2: Farm | AR2: Sawmill | AS2: Quarry | AT2: Mine | AU2: Fertilizer | AV2: Logging | AW2: Stoneworking | AX2: Smelting | AY2: Geometry | AZ2: Eagle Eyes | BA2: Poisoned Edge | BB2: Metal Alloys | BC2: Featherweight Powder | BD2: Magical Mapping | BE2: Alloy Horseshoes | BF2: Fletching | BG2: Shrinking Powder | BH2: Healing Potions | BI2: Giant's Stength
A3: Castle | B3: Building | C3: 1 | D3: 0 | E3: Control 1 wild; 13 resource plots | S3: 0 | U3: 900 | V3: =U3/60 -> 15 | W3: 0 | X3: 200 | Y3: 3000 | Z3: 2500 | AA3: 100 | AP3: 0
A4: Castle | B4: Building | C4: =C3+1 -> 2 | D4: 0 | E4: Control 2 wilds; 16 resource plots | S4: 0 | U4: =U3*2 -> 1800 | V4: =U4/60 -> 30 | W4: 0 | X4: =X3*2 -> 400 | Y4: =Y3*2 -> 6000 | Z4: =Z3*2 -> 5000 | AA4: =AA3*2 -> 200 | AB4: 1 | AP4: 0
A5: Castle | B5: Building | C5: =C4+1 -> 3 | D5: 0 | E5: Control 3 wilds; 19 resource plots | S5: 0 | U5: =U4*2 -> 3600 | V5: =U5/60 -> 60 | W5: 0 | X5: =X4*2 -> 800 | Y5: =Y4*2 -> 12000 | Z5: =Z4*2 -> 10000 | AA5: =AA4*2 -> 400 | AB5: =AB4+1 -> 2 | AP5: 1
A6: Castle | B6: Building | C6: =C5+1 -> 4 | D6: 0 | E6: Control 4 wilds; 22 resource plots | S6: 0 | U6: =U5*2 -> 7200 | V6: =U6/60 -> 120 | W6: 0 | X6: =X5*2 -> 1600 | Y6: =Y5*2 -> 24000 | Z6: =Z5*2 -> 20000 | AA6: =AA5*2 -> 800 | AB6: =AB5+1 -> 3 | AP6: =AP5+1 -> 2
A7: Castle | B7: Building | C7: =C6+1 -> 5 | D7: 0 | E7: Control 5 wilds; 25 resource plots | S7: 0 | U7: =U6*2 -> 14400 | V7: =U7/60 -> 240 | W7: 0 | X7: =X6*2 -> 3200 | Y7: =Y6*2 -> 48000 | Z7: =Z6*2 -> 40000 | AA7: =AA6*2 -> 1600 | AB7: =AB6+1 -> 4 | AP7: =AP6+1 -> 3
A8: Castle | B8: Building | C8: =C7+1 -> 6 | D8: 0 | E8: Control 6 wilds; 28 resource plots | S8: 0 | U8: =U7*2 -> 28800 | V8: =U8/60 -> 480 | W8: 0 | X8: =X7*2 -> 6400 | Y8: =Y7*2 -> 96000 | Z8: =Z7*2 -> 80000 | AA8: =AA7*2 -> 3200 | AB8: =AB7+1 -> 5 | AP8: =AP7+1 -> 4
A9: Castle | B9: Building | C9: =C8+1 -> 7 | D9: 0 | E9: Control 7 wilds; 31 resource plots | S9: 0 | U9: =U8*2 -> 57600 | V9: =U9/60 -> 960 | W9: 0 | X9: =X8*2 -> 12800 | Y9: =Y8*2 -> 192000 | Z9: =Z8*2 -> 160000 | AA9: =AA8*2 -> 6400 | AB9: =AB8+1 -> 6 | AP9: =AP8+1 -> 5
A10: Castle | B10: Building | C10: =C9+1 -> 8 | D10: 0 | E10: Control 8 wilds; 34 resource plots | S10: 0 | U10: =U9*2 -> 115200 | V10: =U10/60 -> 1920 | W10: 0 | X10: =X9*2 -> 25600 | Y10: =Y9*2 -> 384000 | Z10: =Z9*2 -> 320000 | AA10: =AA9*2 -> 12800 | AB10: =AB9+1 -> 7 | AP10: =AP9+1 -> 6
A11: Castle | B11: Building | C11: =C10+1 -> 9 | D11: 0 | E11: Control 9 wilds; 37 resource plots | S11: 0 | U11: =U10*2 -> 230400 | V11: =U11/60 -> 3840 | W11: 0 | X11: =X10*2 -> 51200 | Y11: =Y10*2 -> 768000 | Z11: =Z10*2 -> 640000 | AA11: =AA10*2 -> 25600 | AB11: =AB10+1 -> 8 | AP11: =AP10+1 -> 7
A12: Castle | B12: Building | C12: =C11+1 -> 10 | D12: 0 | E12: Control 10 wilds; 40 resource plots | S12: 0 | T12: Divine Inspiration | U12: =U11*2 -> 460800 | V12: =U12/60 -> 7680 | W12: 0 | X12: =X11*2 -> 102400 | Y12: =Y11*2 -> 1536000 | Z12: =Z11*2 -> 1280000 | AA12: =AA11*2 -> 51200 | AB12: =AB11+1 -> 9 | AP12: =AP11+1 -> 8
A13: Castle | B13: Building | C13: =C12+1 -> 11 | V13: =U13/60 -> 0 | W13: 0
A14: Castle | B14: Building | C14: =C13+1 -> 12 | V14: =U14/60 -> 0 | W14: 0
A15: Castle | B15: Building | C15: =C14+1 -> 13 | V15: =U15/60 -> 0 | W15: 0
A16: Castle | B16: Building | C16: =C15+1 -> 14 | V16: =U16/60 -> 0 | W16: 0
A17: Castle | B17: Building | C17: =C16+1 -> 15 | V17: =U17/60 -> 0 | W17: 0
A18: Castle | B18: Building | C18: =C17+1 -> 16 | V18: =U18/60 -> 0 | W18: 0
A19: Castle | B19: Building | C19: =C18+1 -> 17 | V19: =U19/60 -> 0 | W19: 0
A20: Castle | B20: Building | C20: =C19+1 -> 18 | V20: =U20/60 -> 0 | W20: 0
A21: Castle | B21: Building | C21: =C20+1 -> 19 | V21: =U21/60 -> 0 | W21: 0
A22: Castle | B22: Building | C22: =C21+1 -> 20 | T22: Divine Blah | V22: =U22/60 -> 0 | W22: 0
A23: Alchemy Lab | B23: Building | C23: 1 | D23: 0 | S23: 2 | U23: 15 | V23: =U23/60 -> 0.25 | W23: 0 | X23: 120 | Y23: 2500 | Z23: 1500 | AA23: 200
A24: Alchemy Lab | B24: Building | C24: =C23+1 -> 2 | D24: 0 | S24: 2 | U24: 960 | V24: =U24/60 -> 16 | W24: 0 | X24: =X23*2 -> 240 | Y24: =Y23*2 -> 5000 | Z24: =Z23*2 -> 3000 | AA24: =AA23*2 -> 400 | AC24: 1
A25: Alchemy Lab | B25: Building | C25: =C24+1 -> 3 | D25: 0 | S25: 2 | U25: =U24*2 -> 1920 | V25: =U25/60 -> 32 | W25: 0 | X25: =X24*2 -> 480 | Y25: =Y24*2 -> 10000 | Z25: =Z24*2 -> 6000 | AA25: =AA24*2 -> 800 | AC25: =AC24+1 -> 2
A26: Alchemy Lab | B26: Building | C26: =C25+1 -> 4 | D26: 0 | S26: 2 | U26: =U25*2 -> 3840 | V26: =U26/60 -> 64 | W26: 0 | X26: =X25*2 -> 960 | Y26: =Y25*2 -> 20000 | Z26: =Z25*2 -> 12000 | AA26: =AA25*2 -> 1600 | AC26: =AC25+1 -> 3
A27: Alchemy Lab | B27: Building | C27: =C26+1 -> 5 | D27: 0 | S27: 2 | U27: =U26*2 -> 7680 | V27: =U27/60 -> 128 | W27: 0 | X27: =X26*2 -> 1920 | Y27: =Y26*2 -> 40000 | Z27: =Z26*2 -> 24000 | AA27: =AA26*2 -> 3200 | AC27: =AC26+1 -> 4
A28: Alchemy Lab | B28: Building | C28: =C27+1 -> 6 | D28: 0 | S28: 2 | U28: =U27*2 -> 15360 | V28: =U28/60 -> 256 | W28: 0 | X28: =X27*2 -> 3840 | Y28: =Y27*2 -> 80000 | Z28: =Z27*2 -> 48000 | AA28: =AA27*2 -> 6400 | AC28: =AC27+1 -> 5
A29: Alchemy Lab | B29: Building | C29: =C28+1 -> 7 | D29: 0 | S29: 2 | U29: =U28*2 -> 30720 | V29: =U29/60 -> 512 | W29: 0 | X29: =X28*2 -> 7680 | Y29: =Y28*2 -> 160000 | Z29: =Z28*2 -> 96000 | AA29: =AA28*2 -> 12800 | AC29: =AC28+1 -> 6
A30: Alchemy Lab | B30: Building | C30: =C29+1 -> 8 | D30: 0 | S30: 2 | U30: =U29*2 -> 61440 | V30: =U30/60 -> 1024 | W30: 0 | X30: =X29*2 -> 15360 | Y30: =Y29*2 -> 320000 | Z30: =Z29*2 -> 192000 | AA30: =AA29*2 -> 25600 | AC30: =AC29+1 -> 7
A31: Alchemy Lab | B31: Building | C31: =C30+1 -> 9 | D31: 0 | S31: 2 | U31: =U30*2 -> 122880 | V31: =U31/60 -> 2048 | W31: 0 | X31: =X30*2 -> 30720 | Y31: =Y30*2 -> 640000 | Z31: =Z30*2 -> 384000 | AA31: =AA30*2 -> 51200 | AC31: =AC30+1 -> 8
A32: Alchemy Lab | B32: Building | C32: =C31+1 -> 10 | D32: 0 | S32: 2 | T32: Divine Inspiration | U32: =U31*2 -> 245760 | V32: =U32/60 -> 4096 | W32: 0 | X32: =X31*2 -> 61440 | Y32: =Y31*2 -> 1280000 | Z32: =Z31*2 -> 768000 | AA32: =AA31*2 -> 102400 | AC32: =AC31+1 -> 9
A33: Alchemy Lab | B33: Building | C33: =C32+1 -> 11 | V33: =U33/60 -> 0 | W33: 0
A34: Alchemy Lab | B34: Building | C34: =C33+1 -> 12 | V34: =U34/60 -> 0 | W34: 0
A35: Alchemy Lab | B35: Building | C35: =C34+1 -> 13 | V35: =U35/60 -> 0 | W35: 0
A36: Alchemy Lab | B36: Building | C36: =C35+1 -> 14 | V36: =U36/60 -> 0 | W36: 0
A37: Alchemy Lab | B37: Building | C37: =C36+1 -> 15 | V37: =U37/60 -> 0 | W37: 0
A38: Alchemy Lab | B38: Building | C38: =C37+1 -> 16 | V38: =U38/60 -> 0 | W38: 0
A39: Alchemy Lab | B39: Building | C39: =C38+1 -> 17 | V39: =U39/60 -> 0 | W39: 0
A40: Alchemy Lab | B40: Building | C40: =C39+1 -> 18 | V40: =U40/60 -> 0 | W40: 0
A41: Alchemy Lab | B41: Building | C41: =C40+1 -> 19 | V41: =U41/60 -> 0 | W41: 0
A42: Alchemy Lab | B42: Building | C42: =C41+1 -> 20 | T42: Divine Blah | V42: =U42/60 -> 0 | W42: 0
A43: Cottage | B43: Building | C43: 1 | D43: 0 | H43: =C43*100 -> 100 | I43: =C43*50 -> 50 | S43: 0 | U43: 5 | V43: =U43/60 -> 0.083333333 | W43: 0 | X43: 100 | Y43: 500 | Z43: 100 | AA43: 50
A44: Cottage | B44: Building | C44: =C43+1 -> 2 | D44: 0 | H44: =C44*100 -> 200 | I44: =C44*50 -> 100 | S44: 0 | U44: 30 | V44: =U44/60 -> 0.5 | W44: 0 | X44: =X43*2 -> 200 | Y44: =Y43*2 -> 1000 | Z44: =Z43*2 -> 200 | AA44: =AA43*2 -> 100 | AB44: 1 | AD44: 1
A45: Cottage | B45: Building | C45: =C44+1 -> 3 | D45: 0 | H45: =C45*100 -> 300 | I45: =C45*50 -> 150 | S45: 0 | U45: 120 | V45: =U45/60 -> 2 | W45: 0 | X45: =X44*2 -> 400 | Y45: =Y44*2 -> 2000 | Z45: =Z44*2 -> 400 | AA45: =AA44*2 -> 200 | AB45: =AB44+1 -> 2 | AD45: =AD44+1 -> 2
A46: Cottage | B46: Building | C46: =C45+1 -> 4 | D46: 0 | H46: =C46*100 -> 400 | I46: =C46*50 -> 200 | S46: 0 | U46: =U45*2 -> 240 | V46: =U46/60 -> 4 | W46: 0 | X46: =X45*2 -> 800 | Y46: =Y45*2 -> 4000 | Z46: =Z45*2 -> 800 | AA46: =AA45*2 -> 400 | AB46: =AB45+1 -> 3 | AD46: =AD45+1 -> 3
A47: Cottage | B47: Building | C47: =C46+1 -> 5 | D47: 0 | H47: =C47*100 -> 500 | I47: =C47*50 -> 250 | S47: 0 | U47: =U46*2 -> 480 | V47: =U47/60 -> 8 | W47: 0 | X47: =X46*2 -> 1600 | Y47: =Y46*2 -> 8000 | Z47: =Z46*2 -> 1600 | AA47: =AA46*2 -> 800 | AB47: =AB46+1 -> 4 | AD47: =AD46+1 -> 4
A48: Cottage | B48: Building | C48: =C47+1 -> 6 | D48: 0 | H48: =C48*100 -> 600 | I48: =C48*50 -> 300 | S48: 0 | U48: =U47*2 -> 960 | V48: =U48/60 -> 16 | W48: 0 | X48: =X47*2 -> 3200 | Y48: =Y47*2 -> 16000 | Z48: =Z47*2 -> 3200 | AA48: =AA47*2 -> 1600 | AB48: =AB47+1 -> 5 | AD48: =AD47+1 -> 5
A49: Cottage | B49: Building | C49: =C48+1 -> 7 | D49: 0 | H49: =C49*100 -> 700 | I49: =C49*50 -> 350 | S49: 0 | U49: =U48*2 -> 1920 | V49: =U49/60 -> 32 | W49: 0 | X49: =X48*2 -> 6400 | Y49: =Y48*2 -> 32000 | Z49: =Z48*2 -> 6400 | AA49: =AA48*2 -> 3200 | AB49: =AB48+1 -> 6 | AD49: =AD48+1 -> 6
A50: Cottage | B50: Building | C50: =C49+1 -> 8 | D50: 0 | H50: =C50*100 -> 800 | I50: =C50*50 -> 400 | S50: 0 | U50: =U49*2 -> 3840 | V50: =U50/60 -> 64 | W50: 0 | X50: =X49*2 -> 12800 | Y50: =Y49*2 -> 64000 | Z50: =Z49*2 -> 12800 | AA50: =AA49*2 -> 6400 | AB50: =AB49+1 -> 7 | AD50: =AD49+1 -> 7
A51: Cottage | B51: Building | C51: =C50+1 -> 9 | D51: 0 | H51: =C51*100 -> 900 | I51: =C51*50 -> 450 | S51: 0 | U51: =U50*2 -> 7680 | V51: =U51/60 -> 128 | W51: 0 | X51: =X50*2 -> 25600 | Y51: =Y50*2 -> 128000 | Z51: =Z50*2 -> 25600 | AA51: =AA50*2 -> 12800 | AB51: =AB50+1 -> 8 | AD51: =AD50+1 -> 8
A52: Cottage | B52: Building | C52: =C51+1 -> 10 | D52: 0 | H52: =C52*100 -> 1000 | I52: =C52*50 -> 500 | S52: 0 | T52: Divine Inspiration | U52: =U51*2 -> 15360 | V52: =U52/60 -> 256 | W52: 0 | X52: =X51*2 -> 51200 | Y52: =Y51*2 -> 256000 | Z52: =Z51*2 -> 51200 | AA52: =AA51*2 -> 25600 | AB52: =AB51+1 -> 9 | AD52: =AD51+1 -> 9
A53: Cottage | B53: Building | C53: =C52+1 -> 11 | V53: =U53/60 -> 0 | W53: 0
A54: Cottage | B54: Building | C54: =C53+1 -> 12 | V54: =U54/60 -> 0 | W54: 0
A55: Cottage | B55: Building | C55: =C54+1 -> 13 | V55: =U55/60 -> 0 | W55: 0
A56: Cottage | B56: Building | C56: =C55+1 -> 14 | V56: =U56/60 -> 0 | W56: 0
A57: Cottage | B57: Building | C57: =C56+1 -> 15 | V57: =U57/60 -> 0 | W57: 0
A58: Cottage | B58: Building | C58: =C57+1 -> 16 | V58: =U58/60 -> 0 | W58: 0
A59: Cottage | B59: Building | C59: =C58+1 -> 17 | V59: =U59/60 -> 0 | W59: 0
A60: Cottage | B60: Building | C60: =C59+1 -> 18 | V60: =U60/60 -> 0 | W60: 0
A61: Cottage | B61: Building | C61: =C60+1 -> 19 | V61: =U61/60 -> 0 | W61: 0
A62: Cottage | B62: Building | C62: =C61+1 -> 20 | T62: Divine Blah | V62: =U62/60 -> 0 | W62: 0
A63: Barracks | B63: Building | C63: 1 | D63: 0 | S63: 2 | U63: 300 | V63: =U63/60 -> 5 | W63: 0 | X63: 250 | Y63: 1200 | Z63: 1500 | AA63: 500
A64: Barracks | B64: Building | C64: =C63+1 -> 2 | D64: 0 | S64: 2 | U64: =U63*2 -> 600 | V64: =U64/60 -> 10 | W64: 0 | X64: =X63*2 -> 500 | Y64: =Y63*2 -> 2400 | Z64: =Z63*2 -> 3000 | AA64: =AA63*2 -> 1000 | AE64: 1
A65: Barracks | B65: Building | C65: =C64+1 -> 3 | D65: 0 | S65: 2 | U65: =U64*2 -> 1200 | V65: =U65/60 -> 20 | W65: 0 | X65: =X64*2 -> 1000 | Y65: =Y64*2 -> 4800 | Z65: =Z64*2 -> 6000 | AA65: =AA64*2 -> 2000 | AE65: =AE64+1 -> 2
A66: Barracks | B66: Building | C66: =C65+1 -> 4 | D66: 0 | S66: 2 | U66: =U65*2 -> 2400 | V66: =U66/60 -> 40 | W66: 0 | X66: =X65*2 -> 2000 | Y66: =Y65*2 -> 9600 | Z66: =Z65*2 -> 12000 | AA66: =AA65*2 -> 4000 | AE66: =AE65+1 -> 3
A67: Barracks | B67: Building | C67: =C66+1 -> 5 | D67: 0 | S67: 2 | U67: =U66*2 -> 4800 | V67: =U67/60 -> 80 | W67: 0 | X67: =X66*2 -> 4000 | Y67: =Y66*2 -> 19200 | Z67: =Z66*2 -> 24000 | AA67: =AA66*2 -> 8000 | AE67: =AE66+1 -> 4
A68: Barracks | B68: Building | C68: =C67+1 -> 6 | D68: 0 | S68: 2 | U68: =U67*2 -> 9600 | V68: =U68/60 -> 160 | W68: 0 | X68: =X67*2 -> 8000 | Y68: =Y67*2 -> 38400 | Z68: =Z67*2 -> 48000 | AA68: =AA67*2 -> 16000 | AE68: =AE67+1 -> 5
A69: Barracks | B69: Building | C69: =C68+1 -> 7 | D69: 0 | S69: 2 | U69: =U68*2 -> 19200 | V69: =U69/60 -> 320 | W69: 0 | X69: =X68*2 -> 16000 | Y69: =Y68*2 -> 76800 | Z69: =Z68*2 -> 96000 | AA69: =AA68*2 -> 32000 | AE69: =AE68+1 -> 6
A70: Barracks | B70: Building | C70: =C69+1 -> 8 | D70: 0 | S70: 2 | U70: =U69*2 -> 38400 | V70: =U70/60 -> 640 | W70: 0 | X70: =X69*2 -> 32000 | Y70: =Y69*2 -> 153600 | Z70: =Z69*2 -> 192000 | AA70: =AA69*2 -> 64000 | AE70: =AE69+1 -> 7
A71: Barracks | B71: Building | C71: =C70+1 -> 9 | D71: 0 | S71: 2 | U71: =U70*2 -> 76800 | V71: =U71/60 -> 1280 | W71: 0 | X71: =X70*2 -> 64000 | Y71: =Y70*2 -> 307200 | Z71: =Z70*2 -> 384000 | AA71: =AA70*2 -> 128000 | AE71: =AE70+1 -> 8
A72: Barracks | B72: Building | C72: =C71+1 -> 10 | D72: 0 | S72: 2 | T72: Divine Inspiration | U72: =U71*2 -> 153600 | V72: =U72/60 -> 2560 | W72: 0 | X72: =X71*2 -> 128000 | Y72: =Y71*2 -> 614400 | Z72: =Z71*2 -> 768000 | AA72: =AA71*2 -> 256000 | AE72: =AE71+1 -> 9
A73: Barracks | B73: Building | C73: =C72+1 -> 11 | V73: =U73/60 -> 0 | W73: 0
A74: Barracks | B74: Building | C74: =C73+1 -> 12 | V74: =U74/60 -> 0 | W74: 0
A75: Barracks | B75: Building | C75: =C74+1 -> 13 | V75: =U75/60 -> 0 | W75: 0
A76: Barracks | B76: Building | C76: =C75+1 -> 14 | V76: =U76/60 -> 0 | W76: 0
A77: Barracks | B77: Building | C77: =C76+1 -> 15 | V77: =U77/60 -> 0 | W77: 0
A78: Barracks | B78: Building | C78: =C77+1 -> 16 | V78: =U78/60 -> 0 | W78: 0
A79: Barracks | B79: Building | C79: =C78+1 -> 17 | V79: =U79/60 -> 0 | W79: 0
A80: Barracks | B80: Building | C80: =C79+1 -> 18 | V80: =U80/60 -> 0 | W80: 0
A81: Barracks | B81: Building | C81: =C80+1 -> 19 | V81: =U81/60 -> 0 | W81: 0
A82: Barracks | B82: Building | C82: =C81+1 -> 20 | T82: Divine Blah | V82: =U82/60 -> 0 | W82: 0
A83: Knight's Hall | B83: Building | C83: 1 | D83: 0 | S83: 3 | U83: 360 | V83: =U83/60 -> 6 | W83: 0 | X83: 400 | Y83: 2500 | Z83: 1200 | AA83: 700
A84: Knight's Hall | B84: Building | C84: =C83+1 -> 2 | D84: 0 | S84: 3 | U84: =U83*2 -> 720 | V84: =U84/60 -> 12 | W84: 0 | X84: =X83*2 -> 800 | Y84: =Y83*2 -> 5000 | Z84: =Z83*2 -> 2400 | AA84: =AA83*2 -> 1400 | AF84: 1
A85: Knight's Hall | B85: Building | C85: =C84+1 -> 3 | D85: 0 | S85: 3 | U85: =U84*2 -> 1440 | V85: =U85/60 -> 24 | W85: 0 | X85: =X84*2 -> 1600 | Y85: =Y84*2 -> 10000 | Z85: =Z84*2 -> 4800 | AA85: =AA84*2 -> 2800 | AF85: =AF84+1 -> 2
A86: Knight's Hall | B86: Building | C86: =C85+1 -> 4 | D86: 0 | S86: 3 | U86: =U85*2 -> 2880 | V86: =U86/60 -> 48 | W86: 0 | X86: =X85*2 -> 3200 | Y86: =Y85*2 -> 20000 | Z86: =Z85*2 -> 9600 | AA86: =AA85*2 -> 5600 | AF86: =AF85+1 -> 3
A87: Knight's Hall | B87: Building | C87: =C86+1 -> 5 | D87: 0 | S87: 3 | U87: =U86*2 -> 5760 | V87: =U87/60 -> 96 | W87: 0 | X87: =X86*2 -> 6400 | Y87: =Y86*2 -> 40000 | Z87: =Z86*2 -> 19200 | AA87: =AA86*2 -> 11200 | AF87: =AF86+1 -> 4
A88: Knight's Hall | B88: Building | C88: =C87+1 -> 6 | D88: 0 | S88: 3 | U88: =U87*2 -> 11520 | V88: =U88/60 -> 192 | W88: 0 | X88: =X87*2 -> 12800 | Y88: =Y87*2 -> 80000 | Z88: =Z87*2 -> 38400 | AA88: =AA87*2 -> 22400 | AF88: =AF87+1 -> 5
A89: Knight's Hall | B89: Building | C89: =C88+1 -> 7 | D89: 0 | S89: 3 | U89: =U88*2 -> 23040 | V89: =U89/60 -> 384 | W89: 0 | X89: =X88*2 -> 25600 | Y89: =Y88*2 -> 160000 | Z89: =Z88*2 -> 76800 | AA89: =AA88*2 -> 44800 | AF89: =AF88+1 -> 6
A90: Knight's Hall | B90: Building | C90: =C89+1 -> 8 | D90: 0 | S90: 3 | U90: =U89*2 -> 46080 | V90: =U90/60 -> 768 | W90: 0 | X90: =X89*2 -> 51200 | Y90: =Y89*2 -> 320000 | Z90: =Z89*2 -> 153600 | AA90: =AA89*2 -> 89600 | AF90: =AF89+1 -> 7
A91: Knight's Hall | B91: Building | C91: =C90+1 -> 9 | D91: 0 | S91: 3 | U91: =U90*2 -> 92160 | V91: =U91/60 -> 1536 | W91: 0 | X91: =X90*2 -> 102400 | Y91: =Y90*2 -> 640000 | Z91: =Z90*2 -> 307200 | AA91: =AA90*2 -> 179200 | AF91: =AF90+1 -> 8
A92: Knight's Hall | B92: Building | C92: =C91+1 -> 10 | D92: 0 | S92: 3 | T92: Divine Inspiration | U92: =U91*2 -> 184320 | V92: =U92/60 -> 3072 | W92: 0 | X92: =X91*2 -> 204800 | Y92: =Y91*2 -> 1280000 | Z92: =Z91*2 -> 614400 | AA92: =AA91*2 -> 358400 | AF92: =AF91+1 -> 9
A93: Knight's Hall | B93: Building | C93: =C92+1 -> 11 | V93: =U93/60 -> 0 | W93: 0
A94: Knight's Hall | B94: Building | C94: =C93+1 -> 12 | V94: =U94/60 -> 0 | W94: 0
A95: Knight's Hall | B95: Building | C95: =C94+1 -> 13 | V95: =U95/60 -> 0 | W95: 0
A96: Knight's Hall | B96: Building | C96: =C95+1 -> 14 | V96: =U96/60 -> 0 | W96: 0
A97: Knight's Hall | B97: Building | C97: =C96+1 -> 15 | V97: =U97/60 -> 0 | W97: 0
A98: Knight's Hall | B98: Building | C98: =C97+1 -> 16 | V98: =U98/60 -> 0 | W98: 0
A99: Knight's Hall | B99: Building | C99: =C98+1 -> 17 | V99: =U99/60 -> 0 | W99: 0
A100: Knight's Hall | B100: Building | C100: =C99+1 -> 18 | V100: =U100/60 -> 0 | W100: 0
...

Sheet requirements
E1: 3 | G1: Level Requirements | H1: Gate Requirement | I1: Time Requirements | J1: Time Requirements | K1: Resource Requirements | L1: Resource Requirements | M1: Resource Requirements | N1: Resource Requirements | O1: Resource Requirements | P1: Building Requirements | Q1: Building Requirements | R1: Building Requirements | S1: Building Requirements | T1: Building Requirements | U1: Building Requirements | V1: Building Requirements | W1: Building Requirements | X1: Building Requirements | Y1: Building Requirements | Z1: Building Requirements | AA1: Building Requirements | AB1: Building Requirements | AC1: Building Requirements | AD1: Building Requirements | AE1: Building Requirements | AF1: Building Requirements | AG1: Building Requirements | AH1: Building Requirements | AI1: Research Requirements | AJ1: Research Requirements | AK1: Research Requirements | AL1: Research Requirements | AM1: Research Requirements | AN1: Research Requirements | AO1: Research Requirements | AP1: Research Requirements | AQ1: Research Requirements | AR1: Research Requirements | AS1: Research Requirements | AT1: Research Requirements | AU1: Research Requirements | AV1: Research Requirements | AW1: Research Requirements
A2: Building / Research | B2: Building / Research | C2: Type | D2: Level ID | E2: Prestige Level | F2: Building Level | G2: Player Level | H2: Item | I2: Build Time (sec) | J2: Build Time (min) | K2: Gold | L2: Food | M2: Wood | N2: Stone | O2: Ore | P2: Castle | Q2: Alchemy Lab | R2: Cottage | S2: Barracks | T2: Knight's Hall | U2: Storehouse | V2: Rally Point | W2: Embassy | X2: Blacksmith | Y2: Workshop | Z2: Watch Tower | AA2: Stable | AB2: Relief Station | AC2: Round Tower | AD2: Wall | AE2: Farm | AF2: Sawmill | AG2: Quarry | AH2: Mine | AI2: Fertilizer | AJ2: Logging | AK2: Stoneworking | AL2: Smelting | AM2: Geometry | AN2: Eagle Eyes | AO2: Poisoned Edge | AP2: Metal Alloys | AQ2: Featherweight Powder | AR2: Magical Mapping | AS2: Alloy Horseshoes | AT2: Fletching | AU2: Shrinking Powder | AV2: Healing Potions | AW2: Giant's Stength
A3: Building / Research | B3: Building / Research | C3: Type | D3: Level ID | E3: Prestige Level | F3: Building Level | G3: Player Level | H3: Item | I3: Build Time (sec) | J3: Build Time (min) | K3: Gold | L3: Food | M3: Wood | N3: Stone | O3: Ore | P3: =VLOOKUP(P2,'name convert'!$A$1:$B$39,2,FALSE) -> keep | Q3: =VLOOKUP(Q2,'name convert'!$A$1:$B$39,2,FALSE) -> Academy | R3: =VLOOKUP(R2,'name convert'!$A$1:$B$39,2,FALSE) -> home | S3: =VLOOKUP(S2,'name convert'!$A$1:$B$39,2,FALSE) -> Barracks | T3: =VLOOKUP(T2,'name convert'!$A$1:$B$39,2,FALSE) -> Great hall | U3: =VLOOKUP(U2,'name convert'!$A$1:$B$39,2,FALSE) -> vault | V3: =VLOOKUP(V2,'name convert'!$A$1:$B$39,2,FALSE) -> Muster Field | W3: =VLOOKUP(W2,'name convert'!$A$1:$B$39,2,FALSE) -> Embassy | ... AW3: =VLOOKUP(AW2,'name convert'!$A$1:$B$39,2,FALSE) -> Engineering
A4: Alchemy Lab | B4: =VLOOKUP(A4,'name convert'!$A$1:$B$50,2,FALSE) -> Academy | C4: Building | D4: 1 | E4: 1 | F4: 1 | G4: 2 | I4: 15 | J4: =I4/60 -> 0.25 | K4: 0 | L4: 120 | M4: 2500 | N4: 1500 | O4: 200
A5: Alchemy Lab | B5: =VLOOKUP(A5,'name convert'!$A$1:$B$50,2,FALSE) -> Academy | C5: Building | D5: 2 | E5: 1 | F5: 2 | G5: 2 | I5: 960 | J5: =I5/60 -> 16 | K5: 0 | L5: =L4*2 -> 240 | M5: =M4*2 -> 5000 | N5: =N4*2 -> 3000 | O5: =O4*2 -> 400 | Q5: 1
A6: Alchemy Lab | B6: =VLOOKUP(A6,'name convert'!$A$1:$B$50,2,FALSE) -> Academy | C6: Building | D6: 3 | E6: 1 | F6: 3 | G6: 2 | I6: =I5*2 -> 1920 | J6: =I6/60 -> 32 | K6: 0 | L6: =L5*2 -> 480 | M6: =M5*2 -> 10000 | N6: =N5*2 -> 6000 | O6: =O5*2 -> 800 | Q6: =Q5+1 -> 2
A7: Alchemy Lab | B7: =VLOOKUP(A7,'name convert'!$A$1:$B$50,2,FALSE) -> Academy | C7: Building | D7: 4 | E7: 1 | F7: 4 | G7: 2 | I7: =I6*2 -> 3840 | J7: =I7/60 -> 64 | K7: 0 | L7: =L6*2 -> 960 | M7: =M6*2 -> 20000 | N7: =N6*2 -> 12000 | O7: =O6*2 -> 1600 | Q7: =Q6+1 -> 3
A8: Alchemy Lab | B8: =VLOOKUP(A8,'name convert'!$A$1:$B$50,2,FALSE) -> Academy | C8: Building | D8: 5 | E8: 1 | F8: 5 | G8: 2 | I8: =I7*2 -> 7680 | J8: =I8/60 -> 128 | K8: 0 | L8: =L7*2 -> 1920 | M8: =M7*2 -> 40000 | N8: =N7*2 -> 24000 | O8: =O7*2 -> 3200 | Q8: =Q7+1 -> 4
A9: Alchemy Lab | B9: =VLOOKUP(A9,'name convert'!$A$1:$B$50,2,FALSE) -> Academy | C9: Building | D9: 6 | E9: 1 | F9: 6 | G9: 2 | I9: =I8*2 -> 15360 | J9: =I9/60 -> 256 | K9: 0 | L9: =L8*2 -> 3840 | M9: =M8*2 -> 80000 | N9: =N8*2 -> 48000 | O9: =O8*2 -> 6400 | Q9: =Q8+1 -> 5
A10: Alchemy Lab | B10: =VLOOKUP(A10,'name convert'!$A$1:$B$50,2,FALSE) -> Academy | C10: Building | D10: 7 | E10: 1 | F10: 7 | G10: 2 | I10: =I9*2 -> 30720 | J10: =I10/60 -> 512 | K10: 0 | L10: =L9*2 -> 7680 | M10: =M9*2 -> 160000 | N10: =N9*2 -> 96000 | O10: =O9*2 -> 12800 | Q10: =Q9+1 -> 6
A11: Alchemy Lab | B11: =VLOOKUP(A11,'name convert'!$A$1:$B$50,2,FALSE) -> Academy | C11: Building | D11: 8 | E11: 1 | F11: 8 | G11: 2 | I11: =I10*2 -> 61440 | J11: =I11/60 -> 1024 | K11: 0 | L11: =L10*2 -> 15360 | M11: =M10*2 -> 320000 | N11: =N10*2 -> 192000 | O11: =O10*2 -> 25600 | Q11: =Q10+1 -> 7
A12: Alchemy Lab | B12: =VLOOKUP(A12,'name convert'!$A$1:$B$50,2,FALSE) -> Academy | C12: Building | D12: 9 | E12: 1 | F12: 9 | G12: 2 | I12: =I11*2 -> 122880 | J12: =I12/60 -> 2048 | K12: 0 | L12: =L11*2 -> 30720 | M12: =M11*2 -> 640000 | N12: =N11*2 -> 384000 | O12: =O11*2 -> 51200 | Q12: =Q11+1 -> 8
A13: Alchemy Lab | B13: =VLOOKUP(A13,'name convert'!$A$1:$B$50,2,FALSE) -> Academy | C13: Building | D13: 10 | E13: 1 | F13: 10 | G13: 2 | H13: Divine Inspiration | I13: =I12*2 -> 245760 | J13: =I13/60 -> 4096 | K13: 0 | L13: =L12*2 -> 61440 | M13: =M12*2 -> 1280000 | N13: =N12*2 -> 768000 | O13: =O12*2 -> 102400 | Q13: =Q12+1 -> 9
A14: Alchemy Lab | B14: =VLOOKUP(A14,'name convert'!$A$1:$B$50,2,FALSE) -> Academy | C14: Building | D14: 11 | E14: 2 | F14: 1 | G14: 2 | I14: 0 | J14: =I14/60 -> 0 | K14: 0 | L14: 0 | M14: 0 | N14: 0 | O14: 0 | P14: 11 | Q14: =Q13+1 -> 10
A15: Alchemy Lab | B15: =VLOOKUP(A15,'name convert'!$A$1:$B$50,2,FALSE) -> Academy | C15: Building | D15: 12 | E15: 2 | F15: 2 | G15: 2 | I15: =(I5)*3 -> 2880 | J15: =I15/60 -> 48 | K15: 0 | L15: =L5 -> 240 | M15: =M5 -> 5000 | N15: =N5 -> 3000 | O15: =O5 -> 400 | P15: =P14+1 -> 12 | Q15: =Q14+1 -> 11
A16: Alchemy Lab | B16: =VLOOKUP(A16,'name convert'!$A$1:$B$50,2,FALSE) -> Academy | C16: Building | D16: 13 | E16: 2 | F16: 3 | G16: 2 | I16: =(I6)*3 -> 5760 | J16: =I16/60 -> 96 | K16: 0 | L16: =L6 -> 480 | M16: =M6 -> 10000 | N16: =N6 -> 6000 | O16: =O6 -> 800 | P16: =P15+1 -> 13 | Q16: =Q15+1 -> 12
A17: Alchemy Lab | B17: =VLOOKUP(A17,'name convert'!$A$1:$B$50,2,FALSE) -> Academy | C17: Building | D17: 14 | E17: 2 | F17: 4 | G17: 2 | I17: =(I7)*3 -> 11520 | J17: =I17/60 -> 192 | K17: 0 | L17: =L7 -> 960 | M17: =M7 -> 20000 | N17: =N7 -> 12000 | O17: =O7 -> 1600 | P17: =P16+1 -> 14 | Q17: =Q16+1 -> 13
A18: Alchemy Lab | B18: =VLOOKUP(A18,'name convert'!$A$1:$B$50,2,FALSE) -> Academy | C18: Building | D18: 15 | E18: 2 | F18: 5 | G18: 2 | I18: =(I8)*3 -> 23040 | J18: =I18/60 -> 384 | K18: 0 | L18: =L8 -> 1920 | M18: =M8 -> 40000 | N18: =N8 -> 24000 | O18: =O8 -> 3200 | P18: =P17+1 -> 15 | Q18: =Q17+1 -> 14
A19: Alchemy Lab | B19: =VLOOKUP(A19,'name convert'!$A$1:$B$50,2,FALSE) -> Academy | C19: Building | D19: 16 | E19: 2 | F19: 6 | G19: 2 | I19: =(I9)*3 -> 46080 | J19: =I19/60 -> 768 | K19: 0 | L19: =L9 -> 3840 | M19: =M9 -> 80000 | N19: =N9 -> 48000 | O19: =O9 -> 6400 | P19: =P18+1 -> 16 | Q19: =Q18+1 -> 15
A20: Alchemy Lab | B20: =VLOOKUP(A20,'name convert'!$A$1:$B$50,2,FALSE) -> Academy | C20: Building | D20: 17 | E20: 2 | F20: 7 | G20: 2 | I20: =(I10)*3 -> 92160 | J20: =I20/60 -> 1536 | K20: 0 | L20: =L10 -> 7680 | M20: =M10 -> 160000 | N20: =N10 -> 96000 | O20: =O10 -> 12800 | P20: =P19+1 -> 17 | Q20: =Q19+1 -> 16
A21: Alchemy Lab | B21: =VLOOKUP(A21,'name convert'!$A$1:$B$50,2,FALSE) -> Academy | C21: Building | D21: 18 | E21: 2 | F21: 8 | G21: 2 | I21: =(I11)*3 -> 184320 | J21: =I21/60 -> 3072 | K21: 0 | L21: =L11 -> 15360 | M21: =M11 -> 320000 | N21: =N11 -> 192000 | O21: =O11 -> 25600 | P21: =P20+1 -> 18 | Q21: =Q20+1 -> 17
A22: Alchemy Lab | B22: =VLOOKUP(A22,'name convert'!$A$1:$B$50,2,FALSE) -> Academy | C22: Building | D22: 19 | E22: 2 | F22: 9 | G22: 2 | I22: =(I12)*3 -> 368640 | J22: =I22/60 -> 6144 | K22: 0 | L22: =L12 -> 30720 | M22: =M12 -> 640000 | N22: =N12 -> 384000 | O22: =O12 -> 51200 | P22: =P21+1 -> 19 | Q22: =Q21+1 -> 18
A23: Alchemy Lab | B23: =VLOOKUP(A23,'name convert'!$A$1:$B$50,2,FALSE) -> Academy | C23: Building | D23: 20 | E23: 2 | F23: 10 | G23: 2 | I23: =(I13)*3 -> 737280 | J23: =I23/60 -> 12288 | K23: 0 | L23: =L13 -> 61440 | M23: =M13 -> 1280000 | N23: =N13 -> 768000 | O23: =O13 -> 102400 | P23: =P22+1 -> 20 | Q23: =Q22+1 -> 19
A24: Alchemy Lab | B24: =VLOOKUP(A24,'name convert'!$A$1:$B$50,2,FALSE) -> Academy | C24: Building | D24: 21 | E24: 2 | F24: 11 | G24: 2 | H24: Divine Blah | I24: 737280 | J24: 4096 | K24: 0 | L24: 61440 | M24: 1280000 | N24: 768000 | O24: 102400 | P24: =P23+1 -> 21 | Q24: =Q23+1 -> 20
A25: Barracks | B25: =VLOOKUP(A25,'name convert'!$A$1:$B$50,2,FALSE) -> Barracks | C25: Building | D25: 1 | E25: 1 | F25: 1 | G25: 2 | I25: 300 | J25: =I25/60 -> 5 | K25: 0 | L25: 250 | M25: 1200 | N25: 1500 | O25: 500
A26: Barracks | B26: =VLOOKUP(A26,'name convert'!$A$1:$B$50,2,FALSE) -> Barracks | C26: Building | D26: 2 | E26: 1 | F26: 2 | G26: 2 | I26: =I25*2 -> 600 | J26: =I26/60 -> 10 | K26: 0 | L26: =L25*2 -> 500 | M26: =M25*2 -> 2400 | N26: =N25*2 -> 3000 | O26: =O25*2 -> 1000 | S26: 1
A27: Barracks | B27: =VLOOKUP(A27,'name convert'!$A$1:$B$50,2,FALSE) -> Barracks | C27: Building | D27: 3 | E27: 1 | F27: 3 | G27: 2 | I27: =I26*2 -> 1200 | J27: =I27/60 -> 20 | K27: 0 | L27: =L26*2 -> 1000 | M27: =M26*2 -> 4800 | N27: =N26*2 -> 6000 | O27: =O26*2 -> 2000 | S27: =S26+1 -> 2
A28: Barracks | B28: =VLOOKUP(A28,'name convert'!$A$1:$B$50,2,FALSE) -> Barracks | C28: Building | D28: 4 | E28: 1 | F28: 4 | G28: 2 | I28: =I27*2 -> 2400 | J28: =I28/60 -> 40 | K28: 0 | L28: =L27*2 -> 2000 | M28: =M27*2 -> 9600 | N28: =N27*2 -> 12000 | O28: =O27*2 -> 4000 | S28: =S27+1 -> 3
A29: Barracks | B29: =VLOOKUP(A29,'name convert'!$A$1:$B$50,2,FALSE) -> Barracks | C29: Building | D29: 5 | E29: 1 | F29: 5 | G29: 2 | I29: =I28*2 -> 4800 | J29: =I29/60 -> 80 | K29: 0 | L29: =L28*2 -> 4000 | M29: =M28*2 -> 19200 | N29: =N28*2 -> 24000 | O29: =O28*2 -> 8000 | S29: =S28+1 -> 4
A30: Barracks | B30: =VLOOKUP(A30,'name convert'!$A$1:$B$50,2,FALSE) -> Barracks | C30: Building | D30: 6 | E30: 1 | F30: 6 | G30: 2 | I30: =I29*2 -> 9600 | J30: =I30/60 -> 160 | K30: 0 | L30: =L29*2 -> 8000 | M30: =M29*2 -> 38400 | N30: =N29*2 -> 48000 | O30: =O29*2 -> 16000 | S30: =S29+1 -> 5
A31: Barracks | B31: =VLOOKUP(A31,'name convert'!$A$1:$B$50,2,FALSE) -> Barracks | C31: Building | D31: 7 | E31: 1 | F31: 7 | G31: 2 | I31: =I30*2 -> 19200 | J31: =I31/60 -> 320 | K31: 0 | L31: =L30*2 -> 16000 | M31: =M30*2 -> 76800 | N31: =N30*2 -> 96000 | O31: =O30*2 -> 32000 | S31: =S30+1 -> 6
A32: Barracks | B32: =VLOOKUP(A32,'name convert'!$A$1:$B$50,2,FALSE) -> Barracks | C32: Building | D32: 8 | E32: 1 | F32: 8 | G32: 2 | I32: =I31*2 -> 38400 | J32: =I32/60 -> 640 | K32: 0 | L32: =L31*2 -> 32000 | M32: =M31*2 -> 153600 | N32: =N31*2 -> 192000 | O32: =O31*2 -> 64000 | S32: =S31+1 -> 7
A33: Barracks | B33: =VLOOKUP(A33,'name convert'!$A$1:$B$50,2,FALSE) -> Barracks | C33: Building | D33: 9 | E33: 1 | F33: 9 | G33: 2 | I33: =I32*2 -> 76800 | J33: =I33/60 -> 1280 | K33: 0 | L33: =L32*2 -> 64000 | M33: =M32*2 -> 307200 | N33: =N32*2 -> 384000 | O33: =O32*2 -> 128000 | S33: =S32+1 -> 8
A34: Barracks | B34: =VLOOKUP(A34,'name convert'!$A$1:$B$50,2,FALSE) -> Barracks | C34: Building | D34: 10 | E34: 1 | F34: 10 | G34: 2 | H34: Divine Inspiration | I34: =I33*2 -> 153600 | J34: =I34/60 -> 2560 | K34: 0 | L34: =L33*2 -> 128000 | M34: =M33*2 -> 614400 | N34: =N33*2 -> 768000 | O34: =O33*2 -> 256000 | S34: =S33+1 -> 9
A35: Barracks | B35: =VLOOKUP(A35,'name convert'!$A$1:$B$50,2,FALSE) -> Barracks | C35: Building | D35: 11 | E35: 2 | F35: 1 | G35: 15 | I35: 0 | J35: =I35/60 -> 0 | K35: 0 | L35: 0 | M35: 0 | N35: 0 | O35: 0 | P35: 11 | S35: =S34+1 -> 10
A36: Barracks | B36: =VLOOKUP(A36,'name convert'!$A$1:$B$50,2,FALSE) -> Barracks | C36: Building | D36: 12 | E36: 2 | F36: 2 | G36: 15 | I36: 1800 | J36: =I36/60 -> 30 | K36: 0 | L36: =L26 -> 500 | M36: =M26 -> 2400 | N36: =N26 -> 3000 | O36: =O26 -> 1000 | P36: =P35+1 -> 12 | S36: =S35+1 -> 11
A37: Barracks | B37: =VLOOKUP(A37,'name convert'!$A$1:$B$50,2,FALSE) -> Barracks | C37: Building | D37: 13 | E37: 2 | F37: 3 | G37: 15 | I37: 3600 | J37: =I37/60 -> 60 | K37: 0 | L37: =L27 -> 1000 | M37: =M27 -> 4800 | N37: =N27 -> 6000 | O37: =O27 -> 2000 | P37: =P36+1 -> 13 | S37: =S36+1 -> 12
A38: Barracks | B38: =VLOOKUP(A38,'name convert'!$A$1:$B$50,2,FALSE) -> Barracks | C38: Building | D38: 14 | E38: 2 | F38: 4 | G38: 15 | I38: 7200 | J38: =I38/60 -> 120 | K38: 0 | L38: =L28 -> 2000 | M38: =M28 -> 9600 | N38: =N28 -> 12000 | O38: =O28 -> 4000 | P38: =P37+1 -> 14 | S38: =S37+1 -> 13
A39: Barracks | B39: =VLOOKUP(A39,'name convert'!$A$1:$B$50,2,FALSE) -> Barracks | C39: Building | D39: 15 | E39: 2 | F39: 5 | G39: 15 | I39: 14400 | J39: =I39/60 -> 240 | K39: 0 | L39: =L29 -> 4000 | M39: =M29 -> 19200 | N39: =N29 -> 24000 | O39: =O29 -> 8000 | P39: =P38+1 -> 15 | S39: =S38+1 -> 14
A40: Barracks | B40: =VLOOKUP(A40,'name convert'!$A$1:$B$50,2,FALSE) -> Barracks | C40: Building | D40: 16 | E40: 2 | F40: 6 | G40: 15 | I40: 28800 | J40: =I40/60 -> 480 | K40: 0 | L40: =L30 -> 8000 | M40: =M30 -> 38400 | N40: =N30 -> 48000 | O40: =O30 -> 16000 | P40: =P39+1 -> 16 | S40: =S39+1 -> 15
A41: Barracks | B41: =VLOOKUP(A41,'name convert'!$A$1:$B$50,2,FALSE) -> Barracks | C41: Building | D41: 17 | E41: 2 | F41: 7 | G41: 15 | I41: 57600 | J41: =I41/60 -> 960 | K41: 0 | L41: =L31 -> 16000 | M41: =M31 -> 76800 | N41: =N31 -> 96000 | O41: =O31 -> 32000 | P41: =P40+1 -> 17 | S41: =S40+1 -> 16
A42: Barracks | B42: =VLOOKUP(A42,'name convert'!$A$1:$B$50,2,FALSE) -> Barracks | C42: Building | D42: 18 | E42: 2 | F42: 8 | G42: 15 | I42: 115200 | J42: =I42/60 -> 1920 | K42: 0 | L42: =L32 -> 32000 | M42: =M32 -> 153600 | N42: =N32 -> 192000 | O42: =O32 -> 64000 | P42: =P41+1 -> 18 | S42: =S41+1 -> 17
A43: Barracks | B43: =VLOOKUP(A43,'name convert'!$A$1:$B$50,2,FALSE) -> Barracks | C43: Building | D43: 19 | E43: 2 | F43: 9 | G43: 15 | I43: 230400 | J43: =I43/60 -> 3840 | K43: 0 | L43: =L33 -> 64000 | M43: =M33 -> 307200 | N43: =N33 -> 384000 | O43: =O33 -> 128000 | P43: =P42+1 -> 19 | S43: =S42+1 -> 18
A44: Barracks | B44: =VLOOKUP(A44,'name convert'!$A$1:$B$50,2,FALSE) -> Barracks | C44: Building | D44: 20 | E44: 2 | F44: 10 | G44: 15 | I44: 460800 | J44: =I44/60 -> 7680 | K44: 0 | L44: =L34 -> 128000 | M44: =M34 -> 614400 | N44: =N34 -> 768000 | O44: =O34 -> 256000 | P44: =P43+1 -> 20 | S44: =S43+1 -> 19
A45: Barracks | B45: =VLOOKUP(A45,'name convert'!$A$1:$B$50,2,FALSE) -> Barracks | C45: Building | D45: 21 | E45: 2 | F45: 11 | G45: 15 | H45: Divine Blah | I45: 921600 | J45: 2560 | K45: 0 | L45: 128000 | M45: 614400 | N45: 768000 | O45: 256000 | P45: =P44+1 -> 21 | S45: =S44+1 -> 20
A46: Blacksmith | B46: =VLOOKUP(A46,'name convert'!$A$1:$B$50,2,FALSE) -> Forge | C46: Building | D46: 1 | E46: 1 | F46: 1 | G46: 3 | I46: 180 | J46: =I46/60 -> 3 | K46: 0 | L46: 125 | M46: 1000 | N46: 600 | O46: 1200 | AH46: 3
A47: Blacksmith | B47: =VLOOKUP(A47,'name convert'!$A$1:$B$50,2,FALSE) -> Forge | C47: Building | D47: 2 | E47: 1 | F47: 2 | G47: 3 | I47: =I46*2 -> 360 | J47: =I47/60 -> 6 | K47: 0 | L47: =L46*2 -> 250 | M47: =M46*2 -> 2000 | N47: =N46*2 -> 1200 | O47: =O46*2 -> 2400 | X47: 1 | AH47: 3
A48: Blacksmith | B48: =VLOOKUP(A48,'name convert'!$A$1:$B$50,2,FALSE) -> Forge | C48: Building | D48: 3 | E48: 1 | F48: 3 | G48: 3 | I48: =I47*2 -> 720 | J48: =I48/60 -> 12 | K48: 0 | L48: =L47*2 -> 500 | M48: =M47*2 -> 4000 | N48: =N47*2 -> 2400 | O48: =O47*2 -> 4800 | X48: =X47+1 -> 2 | AH48: 3
A49: Blacksmith | B49: =VLOOKUP(A49,'name convert'!$A$1:$B$50,2,FALSE) -> Forge | C49: Building | D49: 4 | E49: 1 | F49: 4 | G49: 3 | I49: =I48*2 -> 1440 | J49: =I49/60 -> 24 | K49: 0 | L49: =L48*2 -> 1000 | M49: =M48*2 -> 8000 | N49: =N48*2 -> 4800 | O49: =O48*2 -> 9600 | X49: =X48+1 -> 3 | AH49: 3
A50: Blacksmith | B50: =VLOOKUP(A50,'name convert'!$A$1:$B$50,2,FALSE) -> Forge | C50: Building | D50: 5 | E50: 1 | F50: 5 | G50: 3 | I50: =I49*2 -> 2880 | J50: =I50/60 -> 48 | K50: 0 | L50: =L49*2 -> 2000 | M50: =M49*2 -> 16000 | N50: =N49*2 -> 9600 | O50: =O49*2 -> 19200 | X50: =X49+1 -> 4 | AH50: 3
A51: Blacksmith | B51: =VLOOKUP(A51,'name convert'!$A$1:$B$50,2,FALSE) -> Forge | C51: Building | D51: 6 | E51: 1 | F51: 6 | G51: 3 | I51: =I50*2 -> 5760 | J51: =I51/60 -> 96 | K51: 0 | L51: =L50*2 -> 4000 | M51: =M50*2 -> 32000 | N51: =N50*2 -> 19200 | O51: =O50*2 -> 38400 | X51: =X50+1 -> 5 | AH51: 3
A52: Blacksmith | B52: =VLOOKUP(A52,'name convert'!$A$1:$B$50,2,FALSE) -> Forge | C52: Building | D52: 7 | E52: 1 | F52: 7 | G52: 3 | I52: =I51*2 -> 11520 | J52: =I52/60 -> 192 | K52: 0 | L52: =L51*2 -> 8000 | M52: =M51*2 -> 64000 | N52: =N51*2 -> 38400 | O52: =O51*2 -> 76800 | X52: =X51+1 -> 6 | AH52: 3
A53: Blacksmith | B53: =VLOOKUP(A53,'name convert'!$A$1:$B$50,2,FALSE) -> Forge | C53: Building | D53: 8 | E53: 1 | F53: 8 | G53: 3 | I53: =I52*2 -> 23040 | J53: =I53/60 -> 384 | K53: 0 | L53: =L52*2 -> 16000 | M53: =M52*2 -> 128000 | N53: =N52*2 -> 76800 | O53: =O52*2 -> 153600 | X53: =X52+1 -> 7 | AH53: 3
A54: Blacksmith | B54: =VLOOKUP(A54,'name convert'!$A$1:$B$50,2,FALSE) -> Forge | C54: Building | D54: 9 | E54: 1 | F54: 9 | G54: 3 | I54: =I53*2 -> 46080 | J54: =I54/60 -> 768 | K54: 0 | L54: =L53*2 -> 32000 | M54: =M53*2 -> 256000 | N54: =N53*2 -> 153600 | O54: =O53*2 -> 307200 | X54: =X53+1 -> 8 | AH54: 3
A55: Blacksmith | B55: =VLOOKUP(A55,'name convert'!$A$1:$B$50,2,FALSE) -> Forge | C55: Building | D55: 10 | E55: 1 | F55: 10 | G55: 3 | H55: Divine Inspiration | I55: =I54*2 -> 92160 | J55: =I55/60 -> 1536 | K55: 0 | L55: =L54*2 -> 64000 | M55: =M54*2 -> 512000 | N55: =N54*2 -> 307200 | O55: =O54*2 -> 614400 | X55: =X54+1 -> 9 | AH55: 3
A56: Blacksmith | B56: =VLOOKUP(A56,'name convert'!$A$1:$B$50,2,FALSE) -> Forge | C56: Building | D56: 11 | E56: 2 | F56: 1 | G56: 3 | I56: 0 | J56: =I56/60 -> 0 | K56: 0 | L56: 0 | M56: 0 | N56: 0 | O56: 0 | P56: 11 | X56: =X55+1 -> 10 | AH56: =AH46+10 -> 13
A57: Blacksmith | B57: =VLOOKUP(A57,'name convert'!$A$1:$B$50,2,FALSE) -> Forge | C57: Building | D57: 12 | E57: 2 | F57: 2 | G57: 3 | I57: =(I47)*3 -> 1080 | J57: =I57/60 -> 18 | K57: 0 | L57: =L47 -> 250 | M57: =M47 -> 2000 | N57: =N47 -> 1200 | O57: =O47 -> 2400 | P57: =P56+1 -> 12 | X57: =X56+1 -> 11 | AH57: =AH47+10 -> 13
A58: Blacksmith | B58: =VLOOKUP(A58,'name convert'!$A$1:$B$50,2,FALSE) -> Forge | C58: Building | D58: 13 | E58: 2 | F58: 3 | G58: 3 | I58: =(I48)*3 -> 2160 | J58: =I58/60 -> 36 | K58: 0 | L58: =L48 -> 500 | M58: =M48 -> 4000 | N58: =N48 -> 2400 | O58: =O48 -> 4800 | P58: =P57+1 -> 13 | X58: =X57+1 -> 12 | AH58: =AH48+10 -> 13
A59: Blacksmith | B59: =VLOOKUP(A59,'name convert'!$A$1:$B$50,2,FALSE) -> Forge | C59: Building | D59: 14 | E59: 2 | F59: 4 | G59: 3 | I59: =(I49)*3 -> 4320 | J59: =I59/60 -> 72 | K59: 0 | L59: =L49 -> 1000 | M59: =M49 -> 8000 | N59: =N49 -> 4800 | O59: =O49 -> 9600 | P59: =P58+1 -> 14 | X59: =X58+1 -> 13 | AH59: =AH49+10 -> 13
A60: Blacksmith | B60: =VLOOKUP(A60,'name convert'!$A$1:$B$50,2,FALSE) -> Forge | C60: Building | D60: 15 | E60: 2 | F60: 5 | G60: 3 | I60: =(I50)*3 -> 8640 | J60: =I60/60 -> 144 | K60: 0 | L60: =L50 -> 2000 | M60: =M50 -> 16000 | N60: =N50 -> 9600 | O60: =O50 -> 19200 | P60: =P59+1 -> 15 | X60: =X59+1 -> 14 | AH60: =AH50+10 -> 13
A61: Blacksmith | B61: =VLOOKUP(A61,'name convert'!$A$1:$B$50,2,FALSE) -> Forge | C61: Building | D61: 16 | E61: 2 | F61: 6 | G61: 3 | I61: =(I51)*3 -> 17280 | J61: =I61/60 -> 288 | K61: 0 | L61: =L51 -> 4000 | M61: =M51 -> 32000 | N61: =N51 -> 19200 | O61: =O51 -> 38400 | P61: =P60+1 -> 16 | X61: =X60+1 -> 15 | AH61: =AH51+10 -> 13
A62: Blacksmith | B62: =VLOOKUP(A62,'name convert'!$A$1:$B$50,2,FALSE) -> Forge | C62: Building | D62: 17 | E62: 2 | F62: 7 | G62: 3 | I62: =(I52)*3 -> 34560 | J62: =I62/60 -> 576 | K62: 0 | L62: =L52 -> 8000 | M62: =M52 -> 64000 | N62: =N52 -> 38400 | O62: =O52 -> 76800 | P62: =P61+1 -> 17 | X62: =X61+1 -> 16 | AH62: =AH52+10 -> 13
A63: Blacksmith | B63: =VLOOKUP(A63,'name convert'!$A$1:$B$50,2,FALSE) -> Forge | C63: Building | D63: 18 | E63: 2 | F63: 8 | G63: 3 | I63: =(I53)*3 -> 69120 | J63: =I63/60 -> 1152 | K63: 0 | L63: =L53 -> 16000 | M63: =M53 -> 128000 | N63: =N53 -> 76800 | O63: =O53 -> 153600 | P63: =P62+1 -> 18 | X63: =X62+1 -> 17 | AH63: =AH53+10 -> 13
A64: Blacksmith | B64: =VLOOKUP(A64,'name convert'!$A$1:$B$50,2,FALSE) -> Forge | C64: Building | D64: 19 | E64: 2 | F64: 9 | G64: 3 | I64: =(I54)*3 -> 138240 | J64: =I64/60 -> 2304 | K64: 0 | L64: =L54 -> 32000 | M64: =M54 -> 256000 | N64: =N54 -> 153600 | O64: =O54 -> 307200 | P64: =P63+1 -> 19 | X64: =X63+1 -> 18 | AH64: =AH54+10 -> 13
A65: Blacksmith | B65: =VLOOKUP(A65,'name convert'!$A$1:$B$50,2,FALSE) -> Forge | C65: Building | D65: 20 | E65: 2 | F65: 10 | G65: 3 | I65: =(I55)*3 -> 276480 | J65: =I65/60 -> 4608 | K65: 0 | L65: =L55 -> 64000 | M65: =M55 -> 512000 | N65: =N55 -> 307200 | O65: =O55 -> 614400 | P65: =P64+1 -> 20 | X65: =X64+1 -> 19 | AH65: =AH55+10 -> 13
A66: Blacksmith | B66: =VLOOKUP(A66,'name convert'!$A$1:$B$50,2,FALSE) -> Forge | C66: Building | D66: 21 | E66: 2 | F66: 11 | G66: 3 | H66: Divine Blah | I66: 276480 | J66: 1536 | K66: 0 | L66: 64000 | M66: 512000 | N66: 307200 | O66: 614400 | P66: =P65+1 -> 21 | X66: =X65+1 -> 20 | AH66: 13
A67: Castle | B67: =VLOOKUP(A67,'name convert'!$A$1:$B$50,2,FALSE) -> keep | C67: Building | D67: 1 | E67: 1 | F67: 1 | G67: 0 | I67: 900 | J67: =I67/60 -> 15 | K67: 0 | L67: 200 | M67: 3000 | N67: 2500 | O67: 100 | AD67: 0
A68: Castle | B68: =VLOOKUP(A68,'name convert'!$A$1:$B$50,2,FALSE) -> keep | C68: Building | D68: 2 | E68: 1 | F68: 2 | G68: 0 | I68: =I67*2 -> 1800 | J68: =I68/60 -> 30 | K68: 0 | L68: =L67*2 -> 400 | M68: =M67*2 -> 6000 | N68: =N67*2 -> 5000 | O68: =O67*2 -> 200 | P68: 1 | AD68: 0
A69: Castle | B69: =VLOOKUP(A69,'name convert'!$A$1:$B$50,2,FALSE) -> keep | C69: Building | D69: 3 | E69: 1 | F69: 3 | G69: 0 | I69: =I68*2 -> 3600 | J69: =I69/60 -> 60 | K69: 0 | L69: =L68*2 -> 800 | M69: =M68*2 -> 12000 | N69: =N68*2 -> 10000 | O69: =O68*2 -> 400 | P69: =P68+1 -> 2 | AD69: 1
A70: Castle | B70: =VLOOKUP(A70,'name convert'!$A$1:$B$50,2,FALSE) -> keep | C70: Building | D70: 4 | E70: 1 | F70: 4 | G70: 0 | I70: =I69*2 -> 7200 | J70: =I70/60 -> 120 | K70: 0 | L70: =L69*2 -> 1600 | M70: =M69*2 -> 24000 | N70: =N69*2 -> 20000 | O70: =O69*2 -> 800 | P70: =P69+1 -> 3 | AD70: =AD69+1 -> 2
A71: Castle | B71: =VLOOKUP(A71,'name convert'!$A$1:$B$50,2,FALSE) -> keep | C71: Building | D71: 5 | E71: 1 | F71: 5 | G71: 0 | I71: =I70*2 -> 14400 | J71: =I71/60 -> 240 | K71: 0 | L71: =L70*2 -> 3200 | M71: =M70*2 -> 48000 | N71: =N70*2 -> 40000 | O71: =O70*2 -> 1600 | P71: =P70+1 -> 4 | AD71: =AD70+1 -> 3
A72: Castle | B72: =VLOOKUP(A72,'name convert'!$A$1:$B$50,2,FALSE) -> keep | C72: Building | D72: 6 | E72: 1 | F72: 6 | G72: 0 | I72: =I71*2 -> 28800 | J72: =I72/60 -> 480 | K72: 0 | L72: =L71*2 -> 6400 | M72: =M71*2 -> 96000 | N72: =N71*2 -> 80000 | O72: =O71*2 -> 3200 | P72: =P71+1 -> 5 | AD72: =AD71+1 -> 4
A73: Castle | B73: =VLOOKUP(A73,'name convert'!$A$1:$B$50,2,FALSE) -> keep | C73: Building | D73: 7 | E73: 1 | F73: 7 | G73: 0 | I73: =I72*2 -> 57600 | J73: =I73/60 -> 960 | K73: 0 | L73: =L72*2 -> 12800 | M73: =M72*2 -> 192000 | N73: =N72*2 -> 160000 | O73: =O72*2 -> 6400 | P73: =P72+1 -> 6 | AD73: =AD72+1 -> 5
A74: Castle | B74: =VLOOKUP(A74,'name convert'!$A$1:$B$50,2,FALSE) -> keep | C74: Building | D74: 8 | E74: 1 | F74: 8 | G74: 0 | I74: =I73*2 -> 115200 | J74: =I74/60 -> 1920 | K74: 0 | L74: =L73*2 -> 25600 | M74: =M73*2 -> 384000 | N74: =N73*2 -> 320000 | O74: =O73*2 -> 12800 | P74: =P73+1 -> 7 | AD74: =AD73+1 -> 6
A75: Castle | B75: =VLOOKUP(A75,'name convert'!$A$1:$B$50,2,FALSE) -> keep | C75: Building | D75: 9 | E75: 1 | F75: 9 | G75: 0 | I75: =I74*2 -> 230400 | J75: =I75/60 -> 3840 | K75: 0 | L75: =L74*2 -> 51200 | M75: =M74*2 -> 768000 | N75: =N74*2 -> 640000 | O75: =O74*2 -> 25600 | P75: =P74+1 -> 8 | AD75: =AD74+1 -> 7
A76: Castle | B76: =VLOOKUP(A76,'name convert'!$A$1:$B$50,2,FALSE) -> keep | C76: Building | D76: 10 | E76: 1 | F76: 10 | G76: 0 | H76: Divine Inspiration | I76: =I75*2 -> 460800 | J76: =I76/60 -> 7680 | K76: 0 | L76: =L75*2 -> 102400 | M76: =M75*2 -> 1536000 | N76: =N75*2 -> 1280000 | O76: =O75*2 -> 51200 | P76: =P75+1 -> 9 | AD76: =AD75+1 -> 8
A77: Castle | B77: =VLOOKUP(A77,'name convert'!$A$1:$B$50,2,FALSE) -> keep | C77: Building | D77: 11 | E77: 2 | F77: 1 | G77: 0 | I77: 0 | J77: =I77/60 -> 0 | K77: 0 | L77: 0 | M77: 0 | N77: 0 | O77: 0 | P77: =P76+1 -> 10 | AD77: =AD76+1 -> 9
A78: Castle | B78: =VLOOKUP(A78,'name convert'!$A$1:$B$50,2,FALSE) -> keep | C78: Building | D78: 12 | E78: 2 | F78: 2 | G78: 0 | I78: 3600 | J78: =I78/60 -> 60 | K78: 0 | L78: 600 | M78: 9000 | N78: 8250 | O78: 300 | P78: =P77+1 -> 11 | AD78: =AD77+1 -> 10
A79: Castle | B79: =VLOOKUP(A79,'name convert'!$A$1:$B$50,2,FALSE) -> keep | C79: Building | D79: 13 | E79: 2 | F79: 3 | G79: 0 | I79: 7200 | J79: =I79/60 -> 120 | K79: 0 | L79: 1200 | M79: 18000 | N79: 16500 | O79: 600 | P79: =P78+1 -> 12 | AD79: =AD78+1 -> 11
A80: Castle | B80: =VLOOKUP(A80,'name convert'!$A$1:$B$50,2,FALSE) -> keep | C80: Building | D80: 14 | E80: 2 | F80: 4 | G80: 0 | I80: 14400 | J80: =I80/60 -> 240 | K80: 0 | L80: 2400 | M80: 36000 | N80: 33000 | O80: 1200 | P80: =P79+1 -> 13 | AD80: =AD79+1 -> 12
A81: Castle | B81: =VLOOKUP(A81,'name convert'!$A$1:$B$50,2,FALSE) -> keep | C81: Building | D81: 15 | E81: 2 | F81: 5 | G81: 0 | I81: 28800 | J81: =I81/60 -> 480 | K81: 0 | L81: 4800 | M81: 72000 | N81: 66000 | O81: 2400 | P81: =P80+1 -> 14 | AD81: =AD80+1 -> 13
A82: Castle | B82: =VLOOKUP(A82,'name convert'!$A$1:$B$50,2,FALSE) -> keep | C82: Building | D82: 16 | E82: 2 | F82: 6 | G82: 0 | I82: 57600 | J82: =I82/60 -> 960 | K82: 0 | L82: 9600 | M82: 144000 | N82: 132000 | O82: 4800 | P82: =P81+1 -> 15 | AD82: =AD81+1 -> 14
A83: Castle | B83: =VLOOKUP(A83,'name convert'!$A$1:$B$50,2,FALSE) -> keep | C83: Building | D83: 17 | E83: 2 | F83: 7 | G83: 0 | I83: 115200 | J83: =I83/60 -> 1920 | K83: 0 | L83: 19200 | M83: 288000 | N83: 264000 | O83: 9600 | P83: =P82+1 -> 16 | AD83: =AD82+1 -> 15
A84: Castle | B84: =VLOOKUP(A84,'name convert'!$A$1:$B$50,2,FALSE) -> keep | C84: Building | D84: 18 | E84: 2 | F84: 8 | G84: 0 | I84: 230400 | J84: =I84/60 -> 3840 | K84: 0 | L84: 38400 | M84: 576000 | N84: 528000 | O84: 19200 | P84: =P83+1 -> 17 | AD84: =AD83+1 -> 16
A85: Castle | B85: =VLOOKUP(A85,'name convert'!$A$1:$B$50,2,FALSE) -> keep | C85: Building | D85: 19 | E85: 2 | F85: 9 | G85: 0 | I85: 460800 | J85: =I85/60 -> 7680 | K85: 0 | L85: 76800 | M85: 1152000 | N85: 1056000 | O85: 38400 | P85: =P84+1 -> 18 | AD85: =AD84+1 -> 17
A86: Castle | B86: =VLOOKUP(A86,'name convert'!$A$1:$B$50,2,FALSE) -> keep | C86: Building | D86: 20 | E86: 2 | F86: 10 | G86: 0 | I86: 921600 | J86: =I86/60 -> 15360 | K86: 0 | L86: 153600 | M86: 2304000 | N86: 2112000 | O86: 76800 | P86: =P85+1 -> 19 | AD86: =AD85+1 -> 18
A87: Castle | B87: =VLOOKUP(A87,'name convert'!$A$1:$B$50,2,FALSE) -> keep | C87: Building | D87: 21 | E87: 2 | F87: 11 | G87: 0 | H87: Divine Blah | I87: 1843200 | J87: 7680 | K87: 0 | L87: 307200 | M87: 4608000 | N87: 4224000 | O87: 153600 | P87: =P86+1 -> 20 | AD87: =AD86+1 -> 19
A88: Cottage | B88: =VLOOKUP(A88,'name convert'!$A$1:$B$50,2,FALSE) -> home | C88: Building | D88: 1 | E88: 1 | F88: 1 | G88: 0 | I88: 5 | J88: =I88/60 -> 0.083333333 | K88: 0 | L88: 100 | M88: 500 | N88: 100 | O88: 50
A89: Cottage | B89: =VLOOKUP(A89,'name convert'!$A$1:$B$50,2,FALSE) -> home | C89: Building | D89: 2 | E89: 1 | F89: 2 | G89: 0 | I89: 30 | J89: =I89/60 -> 0.5 | K89: 0 | L89: =L88*2 -> 200 | M89: =M88*2 -> 1000 | N89: =N88*2 -> 200 | O89: =O88*2 -> 100 | P89: 1 | R89: 1
A90: Cottage | B90: =VLOOKUP(A90,'name convert'!$A$1:$B$50,2,FALSE) -> home | C90: Building | D90: 3 | E90: 1 | F90: 3 | G90: 0 | I90: 120 | J90: =I90/60 -> 2 | K90: 0 | L90: =L89*2 -> 400 | M90: =M89*2 -> 2000 | N90: =N89*2 -> 400 | O90: =O89*2 -> 200 | P90: =P89+1 -> 2 | R90: =R89+1 -> 2
A91: Cottage | B91: =VLOOKUP(A91,'name convert'!$A$1:$B$50,2,FALSE) -> home | C91: Building | D91: 4 | E91: 1 | F91: 4 | G91: 0 | I91: =I90*2 -> 240 | J91: =I91/60 -> 4 | K91: 0 | L91: =L90*2 -> 800 | M91: =M90*2 -> 4000 | N91: =N90*2 -> 800 | O91: =O90*2 -> 400 | P91: =P90+1 -> 3 | R91: =R90+1 -> 3
A92: Cottage | B92: =VLOOKUP(A92,'name convert'!$A$1:$B$50,2,FALSE) -> home | C92: Building | D92: 5 | E92: 1 | F92: 5 | G92: 0 | I92: =I91*2 -> 480 | J92: =I92/60 -> 8 | K92: 0 | L92: =L91*2 -> 1600 | M92: =M91*2 -> 8000 | N92: =N91*2 -> 1600 | O92: =O91*2 -> 800 | P92: =P91+1 -> 4 | R92: =R91+1 -> 4
A93: Cottage | B93: =VLOOKUP(A93,'name convert'!$A$1:$B$50,2,FALSE) -> home | C93: Building | D93: 6 | E93: 1 | F93: 6 | G93: 0 | I93: =I92*2 -> 960 | J93: =I93/60 -> 16 | K93: 0 | L93: =L92*2 -> 3200 | M93: =M92*2 -> 16000 | N93: =N92*2 -> 3200 | O93: =O92*2 -> 1600 | P93: =P92+1 -> 5 | R93: =R92+1 -> 5
A94: Cottage | B94: =VLOOKUP(A94,'name convert'!$A$1:$B$50,2,FALSE) -> home | C94: Building | D94: 7 | E94: 1 | F94: 7 | G94: 0 | I94: =I93*2 -> 1920 | J94: =I94/60 -> 32 | K94: 0 | L94: =L93*2 -> 6400 | M94: =M93*2 -> 32000 | N94: =N93*2 -> 6400 | O94: =O93*2 -> 3200 | P94: =P93+1 -> 6 | R94: =R93+1 -> 6
A95: Cottage | B95: =VLOOKUP(A95,'name convert'!$A$1:$B$50,2,FALSE) -> home | C95: Building | D95: 8 | E95: 1 | F95: 8 | G95: 0 | I95: =I94*2 -> 3840 | J95: =I95/60 -> 64 | K95: 0 | L95: =L94*2 -> 12800 | M95: =M94*2 -> 64000 | N95: =N94*2 -> 12800 | O95: =O94*2 -> 6400 | P95: =P94+1 -> 7 | R95: =R94+1 -> 7
A96: Cottage | B96: =VLOOKUP(A96,'name convert'!$A$1:$B$50,2,FALSE) -> home | C96: Building | D96: 9 | E96: 1 | F96: 9 | G96: 0 | I96: =I95*2 -> 7680 | J96: =I96/60 -> 128 | K96: 0 | L96: =L95*2 -> 25600 | M96: =M95*2 -> 128000 | N96: =N95*2 -> 25600 | O96: =O95*2 -> 12800 | P96: =P95+1 -> 8 | R96: =R95+1 -> 8
A97: Cottage | B97: =VLOOKUP(A97,'name convert'!$A$1:$B$50,2,FALSE) -> home | C97: Building | D97: 10 | E97: 1 | F97: 10 | G97: 0 | H97: Divine Inspiration | I97: =I96*2 -> 15360 | J97: =I97/60 -> 256 | K97: 0 | L97: =L96*2 -> 51200 | M97: =M96*2 -> 256000 | N97: =N96*2 -> 51200 | O97: =O96*2 -> 25600 | P97: =P96+1 -> 9 | R97: =R96+1 -> 9
A98: Cottage | B98: =VLOOKUP(A98,'name convert'!$A$1:$B$50,2,FALSE) -> home | C98: Building | D98: 11 | E98: 2 | F98: 1 | G98: 0 | I98: 0 | J98: =I98/60 -> 0 | K98: 0 | L98: 0 | M98: 0 | N98: 0 | O98: 0 | P98: 11 | R98: =R97+1 -> 10
A99: Cottage | B99: =VLOOKUP(A99,'name convert'!$A$1:$B$50,2,FALSE) -> home | C99: Building | D99: 12 | E99: 2 | F99: 2 | G99: 0 | I99: 90 | J99: =I99/60 -> 1.5 | K99: 0 | L99: 500 | M99: 2500 | N99: 550 | O99: 250 | P99: =P98+1 -> 12 | R99: =R98+1 -> 11
A100: Cottage | B100: =VLOOKUP(A100,'name convert'!$A$1:$B$50,2,FALSE) -> home | C100: Building | D100: 13 | E100: 2 | F100: 3 | G100: 0 | I100: 360 | J100: =I100/60 -> 6 | K100: 0 | L100: 1000 | M100: 5000 | N100: 1100 | O100: 500 | P100: =P99+1 -> 13 | R100: =R99+1 -> 12
...

Sheet building_require
C1: buildings name | D1: building required | E1: research required | F1: now | G1: prestige
A2: 2 | B2: doing | C2: castle | D2: wall | F2: Control wild; unlock resource plots | G2: Control more wild;unlock resource plots
A3: 2 | B3: done | C3: cottage | D3: castle | F3: Increase population rate; increase population cap | G3: Increase population rate; increase population cap
A4: 2 | C4: wall | D4: quarry | F4: Build defensive troops； increases # of defense slots | G4: increases # of defense slots,queue
C5: workshop | F5: combine stone | G5: combine high level stones
A6: 1 | B6: done | C6: storehouse | F6: Protects resources from PvP attacks | G6: Protects resources from PvP attacks,Gold
A7: 1 | B7: doing | C7: barracks | F7: unlock Train troops; training speed decrease | G7: unlock T4 T5 T6 Train troops; training speed decrease
C8: relief station | D8: stable | E8: alloy horseshoes | F8: Raises speed for support marches | G8: Raises speed for support marches
A9: 确定功能 | C9: embassy | F9: Can join/create alliance; the number of reinforcing army | G9: alliance help need gems,view alliacen members
A10: 确定功能 | C10: RoundTower
A11: 工作量大 | C11: alchemy lab | F11: Level # research
A12: 星级将军 | C12: knights hall | F12: Unlocks knights
A13: 2 | C13: quarry
A14: 2 | C14: sawmill
A15: 2 | C15: farm
A16: 2 | C16: mine
A17: 确定功能 | C17: watchtower
A18: 1 | C18: rallly point | F18: Increases number of marches and troop cap per march | G18: troop cap per march
C19: stable | D19: farm | F19: train mounted troops faster
C20: blacksmith | D20: mine

Sheet name convert
A1: Castle | B1: keep
A2: Alchemy Lab | B2: Academy
A3: Barracks | B3: Barracks
A4: Knight's Hall | B4: Great hall
A5: Satellite Station | B5: Satellite Station
A6: Cottage | B6: home
A7: Embassy | B7: Embassy
A8: Trading Post | B8: Trading Post
A9: Rally Point | B9: Muster Field
A10: Relief Station | B10: Traven
A11: Stable | B11: Stables
A12: Perimeter | B12: Perimeter
... A40: Logistics Center | B40: Tavern

Sheet hobbits requirement
AY1: levelneeded | CJ1: army money cost
A2: ` | B2: Type | C2: Level ID | D2: Prestige Level | E2: Building Level | F2: Player Level | G2: Item | H2: Build Time (sec) | I2: Build Time (min) | J2: experience gained | K2: Gold | L2: Food | M2: Wood | N2: Stone | O2: Ore | P2: peopleused | Q2: keep | R2: Academy | S2: home | T2: Barracks | U2: Great hall | V2: vault | W2: Muster Field | X2: Embassy | Y2: Forge | Z2: Armory | AA2: Watch tower | AB2: Stables | AC2: Tavern | AD2: Sage's Tower | AE2: City wall | AF2: Farm | AG2: Arboretum | AH2: Quarry | AI2: MINE/ore vein | AJ2: Fertilizer | AK2: Arbors | AL2: Masonry | AM2: Smelting | AN2: Siege Weapons | AO2: Far Seeing | AP2: Honed Blades | AQ2: Metal Alloys | AR2: Saddlebags | AS2: Catorgraphy | AT2: Horseshoes | AU2: Fletching | AV2: StrongBox | AW2: Vigor | AX2: Engineering | AY2: keep | AZ2: Academy | BA2: home | BB2: Barracks | BC2: Great hall | BD2: vault | BE2: Muster Field | BF2: Embassy | BG2: Forge | BH2: Armory | BI2: Watch tower | BJ2: Stables | BK2: tavern | BL2: Sage's Tower | BM2: City wall | BN2: Farm | BO2: Arboretum | BP2: Quarry | BQ2: MINE/ore vein | BR2: Fertilizer | BS2: Arbors | BT2: Masonry | BU2: Smelting | BV2: Siege Weapons | BW2: Far Seeing | BX2: Honed Blades | BY2: Metal Alloys | BZ2: Saddlebags | CA2: Catorgraphy | CB2: Horseshoes | CC2: Fletching | CD2: StrongBox | CE2: Vigor | CF2: Engineering | CG2: totalrequired | CH2: maxrequiredlevel | CI2: gold(total l) | CJ2: Fertilizer | CK2: Arbors | CL2: Masonry | CM2: Smelting | CN2: Siege Weapons | CO2: Far Seeing | CP2: Honed Blades | CQ2: Metal Alloys | CR2: Saddlebags | CS2: Catorgraphy | CT2: Horseshoes | CU2: Fletching | CV2: StrongBox | CW2: Vigor | CX2: Engineering | CY2: total cost
A3: keep | B3: Building | C3: 1 | D3: 1 | E3: 1 | F3: 0 | H3: 900 | I3: 15 | J3: =ROUNDUP(H3/30,0) -> 30 | K3: 0 | L3: 200 | M3: 3000 | N3: 2500 | O3: 100 | AE3: 0 | AY3: =SUMIFS($F$3:$F$341,$A$3:$A$341,Q$2,$C$3:$C$341,Q3) -> 0 | AZ3: =SUMIFS($F$3:$F$341,$A$3:$A$341,R$2,$C$3:$C$341,R3) -> 0 | BA3: =SUMIFS($F$3:$F$341,$A$3:$A$341,S$2,$C$3:$C$341,S3) -> 0 | BB3: =SUMIFS($F$3:$F$341,$A$3:$A$341,T$2,$C$3:$C$341,T3) -> 0 | BC3: =SUMIFS($F$3:$F$341,$A$3:$A$341,U$2,$C$3:$C$341,U3) -> 0 | BD3: =SUMIFS($F$3:$F$341,$A$3:$A$341,V$2,$C$3:$C$341,V3) -> 0 | BE3: =SUMIFS($F$3:$F$341,$A$3:$A$341,W$2,$C$3:$C$341,W3) -> 0 | BF3: =SUMIFS($F$3:$F$341,$A$3:$A$341,X$2,$C$3:$C$341,X3) -> 0 | ... CF3: =SUMIFS($F$3:$F$341,$A$3:$A$341,AX$2,$C$3:$C$341,AX3) -> 0 | CG3: =MAX(AY3:CF3) -> 0 | CH3: =MAX(F3,CG3) -> 0
A4: keep | B4: Building | C4: 2 | D4: 1 | E4: 2 | F4: 0 | H4: 1800 | I4: 30 | J4: =ROUNDUP(H4/30,0) -> 60 | K4: 0 | L4: 400 | M4: 6000 | N4: 5000 | O4: 200 | Q4: 1 | AE4: 0 | AY4: =SUMIFS($F$3:$F$341,$A$3:$A$341,Q$2,$C$3:$C$341,Q4) -> 0 | AZ4: =SUMIFS($F$3:$F$341,$A$3:$A$341,R$2,$C$3:$C$341,R4) -> 0 | BA4: =SUMIFS($F$3:$F$341,$A$3:$A$341,S$2,$C$3:$C$341,S4) -> 0 | BB4: =SUMIFS($F$3:$F$341,$A$3:$A$341,T$2,$C$3:$C$341,T4) -> 0 | BC4: =SUMIFS($F$3:$F$341,$A$3:$A$341,U$2,$C$3:$C$341,U4) -> 0 | BD4: =SUMIFS($F$3:$F$341,$A$3:$A$341,V$2,$C$3:$C$341,V4) -> 0 | BE4: =SUMIFS($F$3:$F$341,$A$3:$A$341,W$2,$C$3:$C$341,W4) -> 0 | BF4: =SUMIFS($F$3:$F$341,$A$3:$A$341,X$2,$C$3:$C$341,X4) -> 0 | ... CF4: =SUMIFS($F$3:$F$341,$A$3:$A$341,AX$2,$C$3:$C$341,AX4) -> 0 | CG4: =MAX(AY4:CF4) -> 0 | CH4: =MAX(F4,CG4) -> 0
A5: home | B5: Building | C5: 1 | D5: 1 | E5: 1 | F5: 0 | H5: 5 | I5: 0.083333333 | J5: =ROUNDUP(H5/30,0) -> 1 | K5: 0 | L5: 100 | M5: 500 | N5: 100 | O5: 50 | AY5: =SUMIFS($CH$3:$CH$341,$A$3:$A$341,Q$2,$C$3:$C$341,Q5) -> 0 | AZ5: =SUMIFS($CH$3:$CH$341,$A$3:$A$341,R$2,$C$3:$C$341,R5) -> 0 | BA5: =SUMIFS($CH$3:$CH$341,$A$3:$A$341,S$2,$C$3:$C$341,S5) -> 0 | BB5: =SUMIFS($CH$3:$CH$341,$A$3:$A$341,T$2,$C$3:$C$341,T5) -> 0 | BC5: =SUMIFS($CH$3:$CH$341,$A$3:$A$341,U$2,$C$3:$C$341,U5) -> 0 | BD5: =SUMIFS($CH$3:$CH$341,$A$3:$A$341,V$2,$C$3:$C$341,V5) -> 0 | BE5: =SUMIFS($CH$3:$CH$341,$A$3:$A$341,W$2,$C$3:$C$341,W5) -> 0 | BF5: =SUMIFS($CH$3:$CH$341,$A$3:$A$341,X$2,$C$3:$C$341,X5) -> 0 | ... CF5: =SUMIFS($CH$3:$CH$341,$A$3:$A$341,AX$2,$C$3:$C$341,AX5) -> 0 | CG5: =MAX(AY5:CF5) -> 0 | CH5: =MAX(F5,CG5) -> 0
A6: home | B6: Building | C6: 2 | D6: 1 | E6: 2 | F6: 0 | H6: 30 | I6: 0.5 | J6: =ROUNDUP(H6/30,0) -> 1 | K6: 0 | L6: 200 | M6: 1000 | N6: 200 | O6: 100 | Q6: 1 | S6: 1 | AY6: =SUMIFS($CH$3:$CH$341,$A$3:$A$341,Q$2,$C$3:$C$341,Q6) -> 0 | AZ6: =SUMIFS($CH$3:$CH$341,$A$3:$A$341,R$2,$C$3:$C$341,R6) -> 0 | BA6: =SUMIFS($CH$3:$CH$341,$A$3:$A$341,S$2,$C$3:$C$341,S6) -> 0 | BB6: =SUMIFS($CH$3:$CH$341,$A$3:$A$341,T$2,$C$3:$C$341,T6) -> 0 | BC6: =SUMIFS($CH$3:$CH$341,$A$3:$A$341,U$2,$C$3:$C$341,U6) -> 0 | BD6: =SUMIFS($CH$3:$CH$341,$A$3:$A$341,V$2,$C$3:$C$341,V6) -> 0 | BE6: =SUMIFS($CH$3:$CH$341,$A$3:$A$341,W$2,$C$3:$C$341,W6) -> 0 | BF6: =SUMIFS($CH$3:$CH$341,$A$3:$A$341,X$2,$C$3:$C$341,X6) -> 0 | ... CF6: =SUMIFS($CH$3:$CH$341,$A$3:$A$341,AX$2,$C$3:$C$341,AX6) -> 0 | CG6: =MAX(AY6:CF6) -> 0 | CH6: =MAX(F6,CG6) -> 0
A7: home | B7: Building | C7: 3 | D7: 1 | E7: 3 | F7: 0 | H7: 120 | I7: 2 | J7: =ROUNDUP(H7/30,0) -> 4 | K7: 0 | L7: 400 | M7: 2000 | N7: 400 | O7: 200 | Q7: 2 | S7: 2 | AY7: =SUMIFS($CH$3:$CH$341,$A$3:$A$341,Q$2,$C$3:$C$341,Q7) -> 0 | AZ7: =SUMIFS($CH$3:$CH$341,$A$3:$A$341,R$2,$C$3:$C$341,R7) -> 0 | BA7: =SUMIFS($CH$3:$CH$341,$A$3:$A$341,S$2,$C$3:$C$341,S7) -> 0 | BB7: =SUMIFS($CH$3:$CH$341,$A$3:$A$341,T$2,$C$3:$C$341,T7) -> 0 | BC7: =SUMIFS($CH$3:$CH$341,$A$3:$A$341,U$2,$C$3:$C$341,U7) -> 0 | BD7: =SUMIFS($CH$3:$CH$341,$A$3:$A$341,V$2,$C$3:$C$341,V7) -> 0 | BE7: =SUMIFS($CH$3:$CH$341,$A$3:$A$341,W$2,$C$3:$C$341,W7) -> 0 | BF7: =SUMIFS($CH$3:$CH$341,$A$3:$A$341,X$2,$C$3:$C$341,X7) -> 0 | ... CF7: =SUMIFS($CH$3:$CH$341,$A$3:$A$341,AX$2,$C$3:$C$341,AX7) -> 0 | CG7: =MAX(AY7:CF7) -> 0 | CH7: =MAX(F7,CG7) -> 0
A8: Farm | B8: Building | C8: 1 | D8: 1 | E8: 1 | F8: 0 | H8: 5 | I8: 0.083333333 | J8: =ROUNDUP(H8/30,0) -> 1 | K8: 0 | L8: 50 | M8: 300 | N8: 200 | O8: 150 | P8: 10 | AY8: =SUMIFS($CH$3:$CH$341,$A$3:$A$341,Q$2,$C$3:$C$341,Q8) -> 0 | AZ8: =SUMIFS($CH$3:$CH$341,$A$3:$A$341,R$2,$C$3:$C$341,R8) -> 0 | BA8: =SUMIFS($CH$3:$CH$341,$A$3:$A$341,S$2,$C$3:$C$341,S8) -> 0 | BB8: =SUMIFS($CH$3:$CH$341,$A$3:$A$341,T$2,$C$3:$C$341,T8) -> 0 | BC8: =SUMIFS($CH$3:$CH$341,$A$3:$A$341,U$2,$C$3:$C$341,U8) -> 0 | BD8: =SUMIFS($CH$3:$CH$341,$A$3:$A$341,V$2,$C$3:$C$341,V8) -> 0 | BE8: =SUMIFS($CH$3:$CH$341,$A$3:$A$341,W$2,$C$3:$C$341,W8) -> 0 | BF8: =SUMIFS($CH$3:$CH$341,$A$3:$A$341,X$2,$C$3:$C$341,X8) -> 0 | ... CF8: =SUMIFS($CH$3:$CH$341,$A$3:$A$341,AX$2,$C$3:$C$341,AX8) -> 0 | CG8: =MAX(AY8:CF8) -> 0 | CH8: =MAX(F8,CG8) -> 0
A9: Farm | B9: Building | C9: 2 | D9: 1 | E9: 2 | F9: 0 | H9: 30 | I9: 0.5 | J9: =ROUNDUP(H9/30,0) -> 1 | K9: 0 | L9: 100 | M9: 600 | N9: 400 | O9: 300 | P9: 30 | AF9: 1 | AY9: =SUMIFS($CH$3:$CH$341,$A$3:$A$341,Q$2,$C$3:$C$341,Q9) -> 0 | AZ9: =SUMIFS($CH$3:$CH$341,$A$3:$A$341,R$2,$C$3:$C$341,R9) -> 0 | BA9: =SUMIFS($CH$3:$CH$341,$A$3:$A$341,S$2,$C$3:$C$341,S9) -> 0 | BB9: =SUMIFS($CH$3:$CH$341,$A$3:$A$341,T$2,$C$3:$C$341,T9) -> 0 | BC9: =SUMIFS($CH$3:$CH$341,$A$3:$A$341,U$2,$C$3:$C$341,U9) -> 0 | BD9: =SUMIFS($CH$3:$CH$341,$A$3:$A$341,V$2,$C$3:$C$341,V9) -> 0 | BE9: =SUMIFS($CH$3:$CH$341,$A$3:$A$341,W$2,$C$3:$C$341,W9) -> 0 | BF9: =SUMIFS($CH$3:$CH$341,$A$3:$A$341,X$2,$C$3:$C$341,X9) -> 0 | ... CF9: =SUMIFS($CH$3:$CH$341,$A$3:$A$341,AX$2,$C$3:$C$341,AX9) -> 0 | CG9: =MAX(AY9:CF9) -> 0 | CH9: =MAX(F9,CG9) -> 0
A10: Farm | B10: Building | C10: 3 | D10: 1 | E10: 3 | F10: 0 | H10: 120 | I10: 2 | J10: =ROUNDUP(H10/30,0) -> 4 | K10: 0 | L10: 200 | M10: 1200 | N10: 800 | O10: 600 | P10: 60 | AF10: 2 | AY10: =SUMIFS($CH$3:$CH$341,$A$3:$A$341,Q$2,$C$3:$C$341,Q10) -> 0 | AZ10: =SUMIFS($CH$3:$CH$341,$A$3:$A$341,R$2,$C$3:$C$341,R10) -> 0 | BA10: =SUMIFS($CH$3:$CH$341,$A$3:$A$341,S$2,$C$3:$C$341,S10) -> 0 | BB10: =SUMIFS($CH$3:$CH$341,$A$3:$A$341,T$2,$C$3:$C$341,T10) -> 0 | BC10: =SUMIFS($CH$3:$CH$341,$A$3:$A$341,U$2,$C$3:$C$341,U10) -> 0 | BD10: =SUMIFS($CH$3:$CH$341,$A$3:$A$341,V$2,$C$3:$C$341,V10) -> 0 | BE10: =SUMIFS($CH$3:$CH$341,$A$3:$A$341,W$2,$C$3:$C$341,W10) -> 0 | BF10: =SUMIFS($CH$3:$CH$341,$A$3:$A$341,X$2,$C$3:$C$341,X10) -> 0 | ... CF10: =SUMIFS($CH$3:$CH$341,$A$3:$A$341,AX$2,$C$3:$C$341,AX10) -> 0 | CG10: =MAX(AY10:CF10) -> 0 | CH10: =MAX(F10,CG10) -> 0
A11: Farm | B11: Building | C11: 4 | D11: 1 | E11: 4 | F11: 0 | H11: 240 | I11: 4 | J11: =ROUNDUP(H11/30,0) -> 8 | K11: 0 | L11: 400 | M11: 2400 | N11: 1600 | O11: 1200 | P11: 100 | AF11: 3 | AY11: =SUMIFS($CH$3:$CH$341,$A$3:$A$341,Q$2,$C$3:$C$341,Q11) -> 0 | AZ11: =SUMIFS($CH$3:$CH$341,$A$3:$A$341,R$2,$C$3:$C$341,R11) -> 0 | BA11: =SUMIFS($CH$3:$CH$341,$A$3:$A$341,S$2,$C$3:$C$341,S11) -> 0 | BB11: =SUMIFS($CH$3:$CH$341,$A$3:$A$341,T$2,$C$3:$C$341,T11) -> 0 | BC11: =SUMIFS($CH$3:$CH$341,$A$3:$A$341,U$2,$C$3:$C$341,U11) -> 0 | BD11: =SUMIFS($CH$3:$CH$341,$A$3:$A$341,V$2,$C$3:$C$341,V11) -> 0 | BE11: =SUMIFS($CH$3:$CH$341,$A$3:$A$341,W$2,$C$3:$C$341,W11) -> 0 | BF11: =SUMIFS($CH$3:$CH$341,$A$3:$A$341,X$2,$C$3:$C$341,X11) -> 0 | ... CF11: =SUMIFS($CH$3:$CH$341,$A$3:$A$341,AX$2,$C$3:$C$341,AX11) -> 0 | CG11: =MAX(AY11:CF11) -> 0 | CH11: =MAX(F11,CG11) -> 0
A12: Farm | B12: Building | C12: 5 | D12: 1 | E12: 5 | F12: 0 | H12: 480 | I12: 8 | J12: =ROUNDUP(H12/30,0) -> 16 | K12: 0 | L12: 800 | M12: 4800 | N12: 3200 | O12: 2400 | P12: 150 | AF12: 4 | AY12: =SUMIFS($CH$3:$CH$341,$A$3:$A$341,Q$2,$C$3:$C$341,Q12) -> 0 | AZ12: =SUMIFS($CH$3:$CH$341,$A$3:$A$341,R$2,$C$3:$C$341,R12) -> 0 | BA12: =SUMIFS($CH$3:$CH$341,$A$3:$A$341,S$2,$C$3:$C$341,S12) -> 0 | BB12: =SUMIFS($CH$3:$CH$341,$A$3:$A$341,T$2,$C$3:$C$341,T12) -> 0 | BC12: =SUMIFS($CH$3:$CH$341,$A$3:$A$341,U$2,$C$3:$C$341,U12) -> 0 | BD12: =SUMIFS($CH$3:$CH$341,$A$3:$A$341,V$2,$C$3:$C$341,V12) -> 0 | BE12: =SUMIFS($CH$3:$CH$341,$A$3:$A$341,W$2,$C$3:$C$341,W12) -> 0 | BF12: =SUMIFS($CH$3:$CH$341,$A$3:$A$341,X$2,$C$3:$C$341,X12) -> 0 | ... CF12: =SUMIFS($CH$3:$CH$341,$A$3:$A$341,AX$2,$C$3:$C$341,AX12) -> 0 | CG12: =MAX(AY12:CF12) -> 0 | CH12: =MAX(F12,CG12) -> 0
A13: Farm | B13: Building | C13: 6 | D13: 1 | E13: 6 | F13: 0 | H13: 960 | I13: 16 | J13: =ROUNDUP(H13/30,0) -> 32 | K13: 0 | L13: 1600 | M13: 9600 | N13: 6400 | O13: 4800 | P13: 210 | AF13: 5 | AY13: =SUMIFS($CH$3:$CH$341,$A$3:$A$341,Q$2,$C$3:$C$341,Q13) -> 0 | AZ13: =SUMIFS($CH$3:$CH$341,$A$3:$A$341,R$2,$C$3:$C$341,R13) -> 0 | BA13: =SUMIFS($CH$3:$CH$341,$A$3:$A$341,S$2,$C$3:$C$341,S13) -> 0 | BB13: =SUMIFS($CH$3:$CH$341,$A$3:$A$341,T$2,$C$3:$C$341,T13) -> 0 | BC13: =SUMIFS($CH$3:$CH$341,$A$3:$A$341,U$2,$C$3:$C$341,U13) -> 0 | BD13: =SUMIFS($CH$3:$CH$341,$A$3:$A$341,V$2,$C$3:$C$341,V13) -> 0 | BE13: =SUMIFS($CH$3:$CH$341,$A$3:$A$341,W$2,$C$3:$C$341,W13) -> 0 | BF13: =SUMIFS($CH$3:$CH$341,$A$3:$A$341,X$2,$C$3:$C$341,X13) -> 0 | ... CF13: =SUMIFS($CH$3:$CH$341,$A$3:$A$341,AX$2,$C$3:$C$341,AX13) -> 0 | CG13: =MAX(AY13:CF13) -> 0 | CH13: =MAX(F13,CG13) -> 0
A14: Farm | B14: Building | C14: 7 | D14: 1 | E14: 7 | F14: 0 | H14: 1920 | I14: 32 | J14: =ROUNDUP(H14/30,0) -> 64 | K14: 0 | L14: 3200 | M14: 19200 | N14: 12800 | O14: 9600 | P14: 280 | AF14: 6 | AY14: =SUMIFS($CH$3:$CH$341,$A$3:$A$341,Q$2,$C$3:$C$341,Q14) -> 0 | AZ14: =SUMIFS($CH$3:$CH$341,$A$3:$A$341,R$2,$C$3:$C$341,R14) -> 0 | BA14: =SUMIFS($CH$3:$CH$341,$A$3:$A$341,S$2,$C$3:$C$341,S14) -> 0 | BB14: =SUMIFS($CH$3:$CH$341,$A$3:$A$341,T$2,$C$3:$C$341,T14) -> 0 | BC14: =SUMIFS($CH$3:$CH$341,$A$3:$A$341,U$2,$C$3:$C$341,U14) -> 0 | BD14: =SUMIFS($CH$3:$CH$341,$A$3:$A$341,V$2,$C$3:$C$341,V14) -> 0 | BE14: =SUMIFS($CH$3:$CH$341,$A$3:$A$341,W$2,$C$3:$C$341,W14) -> 0 | BF14: =SUMIFS($CH$3:$CH$341,$A$3:$A$341,X$2,$C$3:$C$341,X14) -> 0 | ... CF14: =SUMIFS($CH$3:$CH$341,$A$3:$A$341,AX$2,$C$3:$C$341,AX14) -> 0 | CG14: =MAX(AY14:CF14) -> 0 | CH14: =MAX(F14,CG14) -> 0
A15: Farm | B15: Building | C15: 8 | D15: 1 | E15: 8 | F15: 0 | H15: 3840 | I15: 64 | J15: =ROUNDUP(H15/30,0) -> 128 | K15: 0 | L15: 6400 | M15: 38400 | N15: 25600 | O15: 19200 | P15: 360 | AF15: 7 | AY15: =SUMIFS($CH$3:$CH$341,$A$3:$A$341,Q$2,$C$3:$C$341,Q15) -> 0 | AZ15: =SUMIFS($CH$3:$CH$341,$A$3:$A$341,R$2,$C$3:$C$341,R15) -> 0 | BA15: =SUMIFS($CH$3:$CH$341,$A$3:$A$341,S$2,$C$3:$C$341,S15) -> 0 | BB15: =SUMIFS($CH$3:$CH$341,$A$3:$A$341,T$2,$C$3:$C$341,T15) -> 0 | BC15: =SUMIFS($CH$3:$CH$341,$A$3:$A$341,U$2,$C$3:$C$341,U15) -> 0 | BD15: =SUMIFS($CH$3:$CH$341,$A$3:$A$341,V$2,$C$3:$C$341,V15) -> 0 | BE15: =SUMIFS($CH$3:$CH$341,$A$3:$A$341,W$2,$C$3:$C$341,W15) -> 0 | BF15: =SUMIFS($CH$3:$CH$341,$A$3:$A$341,X$2,$C$3:$C$341,X15) -> 0 | ... CF15: =SUMIFS($CH$3:$CH$341,$A$3:$A$341,AX$2,$C$3:$C$341,AX15) -> 0 | CG15: =MAX(AY15:CF15) -> 0 | CH15: =MAX(F15,CG15) -> 0
A16: Farm | B16: Building | C16: 9 | D16: 1 | E16: 9 | F16: 0 | H16: 7680 | I16: 128 | J16: =ROUNDUP(H16/30,0) -> 256 | K16: 0 | L16: 12800 | M16: 76800 | N16: 51200 | O16: 38400 | AF16: 8 | AY16: =SUMIFS($CH$3:$CH$341,$A$3:$A$341,Q$2,$C$3:$C$341,Q16) -> 0 | AZ16: =SUMIFS($CH$3:$CH$341,$A$3:$A$341,R$2,$C$3:$C$341,R16) -> 0 | BA16: =SUMIFS($CH$3:$CH$341,$A$3:$A$341,S$2,$C$3:$C$341,S16) -> 0 | BB16: =SUMIFS($CH$3:$CH$341,$A$3:$A$341,T$2,$C$3:$C$341,T16) -> 0 | BC16: =SUMIFS($CH$3:$CH$341,$A$3:$A$341,U$2,$C$3:$C$341,U16) -> 0 | BD16: =SUMIFS($CH$3:$CH$341,$A$3:$A$341,V$2,$C$3:$C$341,V16) -> 0 | BE16: =SUMIFS($CH$3:$CH$341,$A$3:$A$341,W$2,$C$3:$C$341,W16) -> 0 | BF16: =SUMIFS($CH$3:$CH$341,$A$3:$A$341,X$2,$C$3:$C$341,X16) -> 0 | ... CF16: =SUMIFS($CH$3:$CH$341,$A$3:$A$341,AX$2,$C$3:$C$341,AX16) -> 0 | CG16: =MAX(AY16:CF16) -> 0 | CH16: =MAX(F16,CG16) -> 0
A17: Farm | B17: Building | C17: 10 | D17: 1 | E17: 10 | F17: 0 | G17: Divine Inspiration | H17: 15360 | I17: 256 | J17: =ROUNDUP(H17/30,0) -> 512 | K17: 0 | L17: 25600 | M17: 153600 | N17: 102400 | O17: 76800 | P17: 550 | AF17: 9 | AY17: =SUMIFS($CH$3:$CH$341,$A$3:$A$341,Q$2,$C$3:$C$341,Q17) -> 0 | AZ17: =SUMIFS($CH$3:$CH$341,$A$3:$A$341,R$2,$C$3:$C$341,R17) -> 0 | BA17: =SUMIFS($CH$3:$CH$341,$A$3:$A$341,S$2,$C$3:$C$341,S17) -> 0 | BB17: =SUMIFS($CH$3:$CH$341,$A$3:$A$341,T$2,$C$3:$C$341,T17) -> 0 | BC17: =SUMIFS($CH$3:$CH$341,$A$3:$A$341,U$2,$C$3:$C$341,U17) -> 0 | BD17: =SUMIFS($CH$3:$CH$341,$A$3:$A$341,V$2,$C$3:$C$341,V17) -> 0 | BE17: =SUMIFS($CH$3:$CH$341,$A$3:$A$341,W$2,$C$3:$C$341,W17) -> 0 | BF17: =SUMIFS($CH$3:$CH$341,$A$3:$A$341,X$2,$C$3:$C$341,X17) -> 0 | ... CF17: =SUMIFS($CH$3:$CH$341,$A$3:$A$341,AX$2,$C$3:$C$341,AX17) -> 0 | CG17: =MAX(AY17:CF17) -> 0 | CH17: =MAX(F17,CG17) -> 0
A18: MINE/ore vein | B18: Building | C18: 1 | D18: 1 | E18: 1 | F18: 0 | H18: 5 | I18: 0.083333333 | J18: =ROUNDUP(H18/30,0) -> 1 | K18: 0 | L18: 210 | M18: 600 | N18: 500 | O18: 200 | P18: 25 | AY18: =SUMIFS($CH$3:$CH$341,$A$3:$A$341,Q$2,$C$3:$C$341,Q18) -> 0 | AZ18: =SUMIFS($CH$3:$CH$341,$A$3:$A$341,R$2,$C$3:$C$341,R18) -> 0 | BA18: =SUMIFS($CH$3:$CH$341,$A$3:$A$341,S$2,$C$3:$C$341,S18) -> 0 | BB18: =SUMIFS($CH$3:$CH$341,$A$3:$A$341,T$2,$C$3:$C$341,T18) -> 0 | BC18: =SUMIFS($CH$3:$CH$341,$A$3:$A$341,U$2,$C$3:$C$341,U18) -> 0 | BD18: =SUMIFS($CH$3:$CH$341,$A$3:$A$341,V$2,$C$3:$C$341,V18) -> 0 | BE18: =SUMIFS($CH$3:$CH$341,$A$3:$A$341,W$2,$C$3:$C$341,W18) -> 0 | BF18: =SUMIFS($CH$3:$CH$341,$A$3:$A$341,X$2,$C$3:$C$341,X18) -> 0 | ... CF18: =SUMIFS($CH$3:$CH$341,$A$3:$A$341,AX$2,$C$3:$C$341,AX18) -> 0 | CG18: =MAX(AY18:CF18) -> 0 | CH18: =MAX(F18,CG18) -> 0
A19: MINE/ore vein | B19: Building | C19: 2 | D19: 1 | E19: 2 | F19: 0 | H19: 90 | I19: 1.5 | J19: =ROUNDUP(H19/30,0) -> 3 | K19: 0 | L19: 420 | M19: 1200 | N19: 1000 | O19: 400 | P19: 75 | AI19: 1 | AY19: =SUMIFS($CH$3:$CH$341,$A$3:$A$341,Q$2,$C$3:$C$341,Q19) -> 0 | AZ19: =SUMIFS($CH$3:$CH$341,$A$3:$A$341,R$2,$C$3:$C$341,R19) -> 0 | BA19: =SUMIFS($CH$3:$CH$341,$A$3:$A$341,S$2,$C$3:$C$341,S19) -> 0 | BB19: =SUMIFS($CH$3:$CH$341,$A$3:$A$341,T$2,$C$3:$C$341,T19) -> 0 | BC19: =SUMIFS($CH$3:$CH$341,$A$3:$A$341,U$2,$C$3:$C$341,U19) -> 0 | BD19: =SUMIFS($CH$3:$CH$341,$A$3:$A$341,V$2,$C$3:$C$341,V19) -> 0 | BE19: =SUMIFS($CH$3:$CH$341,$A$3:$A$341,W$2,$C$3:$C$341,W19) -> 0 | BF19: =SUMIFS($CH$3:$CH$341,$A$3:$A$341,X$2,$C$3:$C$341,X19) -> 0 | ... CF19: =SUMIFS($CH$3:$CH$341,$A$3:$A$341,AX$2,$C$3:$C$341,AX19) -> 0 | CG19: =MAX(AY19:CF19) -> 0 | CH19: =MAX(F19,CG19) -> 0
A20: MINE/ore vein | B20: Building | C20: 3 | D20: 1 | E20: 3 | F20: 0 | H20: 360 | I20: 6 | J20: =ROUNDUP(H20/30,0) -> 12 | K20: 0 | L20: 840 | M20: 2400 | N20: 2000 | O20: 800 | P20: 150 | AI20: 2 | AY20: =SUMIFS($CH$3:$CH$341,$A$3:$A$341,Q$2,$C$3:$C$341,Q20) -> 0 | AZ20: =SUMIFS($CH$3:$CH$341,$A$3:$A$341,R$2,$C$3:$C$341,R20) -> 0 | BA20: =SUMIFS($CH$3:$CH$341,$A$3:$A$341,S$2,$C$3:$C$341,S20) -> 0 | BB20: =SUMIFS($CH$3:$CH$341,$A$3:$A$341,T$2,$C$3:$C$341,T20) -> 0 | BC20: =SUMIFS($CH$3:$CH$341,$A$3:$A$341,U$2,$C$3:$C$341,U20) -> 0 | BD20: =SUMIFS($CH$3:$CH$341,$A$3:$A$341,V$2,$C$3:$C$341,V20) -> 0 | BE20: =SUMIFS($CH$3:$CH$341,$A$3:$A$341,W$2,$C$3:$C$341,W20) -> 0 | BF20: =SUMIFS($CH$3:$CH$341,$A$3:$A$341,X$2,$C$3:$C$341,X20) -> 0 | ... CF20: =SUMIFS($CH$3:$CH$341,$A$3:$A$341,AX$2,$C$3:$C$341,AX20) -> 0 | CG20: =MAX(AY20:CF20) -> 0 | CH20: =MAX(F20,CG20) -> 0
A21: MINE/ore vein | B21: Building | C21: 4 | D21: 1 | E21: 4 | F21: 0 | H21: 720 | I21: 12 | J21: =ROUNDUP(H21/30,0) -> 24 | K21: 0 | L21: 1680 | M21: 4800 | N21: 4000 | O21: 1600 | P21: 250 | AI21: 3 | AY21: =SUMIFS($CH$3:$CH$341,$A$3:$A$341,Q$2,$C$3:$C$341,Q21) -> 0 | AZ21: =SUMIFS($CH$3:$CH$341,$A$3:$A$341,R$2,$C$3:$C$341,R21) -> 0 | BA21: =SUMIFS($CH$3:$CH$341,$A$3:$A$341,S$2,$C$3:$C$341,S21) -> 0 | BB21: =SUMIFS($CH$3:$CH$341,$A$3:$A$341,T$2,$C$3:$C$341,T21) -> 0 | BC21: =SUMIFS($CH$3:$CH$341,$A$3:$A$341,U$2,$C$3:$C$341,U21) -> 0 | BD21: =SUMIFS($CH$3:$CH$341,$A$3:$A$341,V$2,$C$3:$C$341,V21) -> 0 | BE21: =SUMIFS($CH$3:$CH$341,$A$3:$A$341,W$2,$C$3:$C$341,W21) -> 0 | BF21: =SUMIFS($CH$3:$CH$341,$A$3:$A$341,X$2,$C$3:$C$341,X21) -> 0 | ... CF21: =SUMIFS($CH$3:$CH$341,$A$3:$A$341,AX$2,$C$3:$C$341,AX21) -> 0 | CG21: =MAX(AY21:CF21) -> 0 | CH21: =MAX(F21,CG21) -> 0
A22: MINE/ore vein | B22: Building | C22: 5 | D22: 1 | E22: 5 | F22: 0 | H22: 1440 | I22: 24 | J22: =ROUNDUP(H22/30,0) -> 48 | K22: 0 | L22: 3360 | M22: 9600 | N22: 8000 | O22: 3200 | P22: 375 | AI22: 4 | AY22: =SUMIFS($CH$3:$CH$341,$A$3:$A$341,Q$2,$C$3:$C$341,Q22) -> 0 | AZ22: =SUMIFS($CH$3:$CH$341,$A$3:$A$341,R$2,$C$3:$C$341,R22) -> 0 | BA22: =SUMIFS($CH$3:$CH$341,$A$3:$A$341,S$2,$C$3:$C$341,S22) -> 0 | BB22: =SUMIFS($CH$3:$CH$341,$A$3:$A$341,T$2,$C$3:$C$341,T22) -> 0 | BC22: =SUMIFS($CH$3:$CH$341,$A$3:$A$341,U$2,$C$3:$C$341,U22) -> 0 | BD22: =SUMIFS($CH$3:$CH$341,$A$3:$A$341,V$2,$C$3:$C$341,V22) -> 0 | BE22: =SUMIFS($CH$3:$CH$341,$A$3:$A$341,W$2,$C$3:$C$341,W22) -> 0 | BF22: =SUMIFS($CH$3:$CH$341,$A$3:$A$341,X$2,$C$3:$C$341,X22) -> 0 | ... CF22: =SUMIFS($CH$3:$CH$341,$A$3:$A$341,AX$2,$C$3:$C$341,AX22) -> 0 | CG22: =MAX(AY22:CF22) -> 0 | CH22: =MAX(F22,CG22) -> 0
A23: MINE/ore vein | B23: Building | C23: 6 | D23: 1 | E23: 6 | F23: 0 | H23: 2880 | I23: 48 | J23: =ROUNDUP(H23/30,0) -> 96 | K23: 0 | L23: 6720 | M23: 19200 | N23: 16000 | O23: 6400 | P23: 525 | AI23: 5 | AY23: =SUMIFS($CH$3:$CH$341,$A$3:$A$341,Q$2,$C$3:$C$341,Q23) -> 0 | AZ23: =SUMIFS($CH$3:$CH$341,$A$3:$A$341,R$2,$C$3:$C$341,R23) -> 0 | BA23: =SUMIFS($CH$3:$CH$341,$A$3:$A$341,S$2,$C$3:$C$341,S23) -> 0 | BB23: =SUMIFS($CH$3:$CH$341,$A$3:$A$341,T$2,$C$3:$C$341,T23) -> 0 | BC23: =SUMIFS($CH$3:$CH$341,$A$3:$A$341,U$2,$C$3:$C$341,U23) -> 0 | BD23: =SUMIFS($CH$3:$CH$341,$A$3:$A$341,V$2,$C$3:$C$341,V23) -> 0 | BE23: =SUMIFS($CH$3:$CH$341,$A$3:$A$341,W$2,$C$3:$C$341,W23) -> 0 | BF23: =SUMIFS($CH$3:$CH$341,$A$3:$A$341,X$2,$C$3:$C$341,X23) -> 0 | ... CF23: =SUMIFS($CH$3:$CH$341,$A$3:$A$341,AX$2,$C$3:$C$341,AX23) -> 0 | CG23: =MAX(AY23:CF23) -> 0 | CH23: =MAX(F23,CG23) -> 0
A24: MINE/ore vein | B24: Building | C24: 7 | D24: 1 | E24: 7 | F24: 0 | H24: 5760 | I24: 96 | J24: =ROUNDUP(H24/30,0) -> 192 | K24: 0 | L24: 13440 | M24: 38400 | N24: 32000 | O24: 12800 | P24: 700 | AI24: 6 | AY24: =SUMIFS($CH$3:$CH$341,$A$3:$A$341,Q$2,$C$3:$C$341,Q24) -> 0 | AZ24: =SUMIFS($CH$3:$CH$341,$A$3:$A$341,R$2,$C$3:$C$341,R24) -> 0 | BA24: =SUMIFS($CH$3:$CH$341,$A$3:$A$341,S$2,$C$3:$C$341,S24) -> 0 | BB24: =SUMIFS($CH$3:$CH$341,$A$3:$A$341,T$2,$C$3:$C$341,T24) -> 0 | BC24: =SUMIFS($CH$3:$CH$341,$A$3:$A$341,U$2,$C$3:$C$341,U24) -> 0 | BD24: =SUMIFS($CH$3:$CH$341,$A$3:$A$341,V$2,$C$3:$C$341,V24) -> 0 | BE24: =SUMIFS($CH$3:$CH$341,$A$3:$A$341,W$2,$C$3:$C$341,W24) -> 0 | BF24: =SUMIFS($CH$3:$CH$341,$A$3:$A$341,X$2,$C$3:$C$341,X24) -> 0 | ... CF24: =SUMIFS($CH$3:$CH$341,$A$3:$A$341,AX$2,$C$3:$C$341,AX24) -> 0 | CG24: =MAX(AY24:CF24) -> 0 | CH24: =MAX(F24,CG24) -> 0
A25: MINE/ore vein | B25: Building | C25: 8 | D25: 1 | E25: 8 | F25: 0 | H25: 11520 | I25: 192 | J25: =ROUNDUP(H25/30,0) -> 384 | K25: 0 | L25: 26880 | M25: 76800 | N25: 64000 | O25: 25600 | P25: 900 | AI25: 7 | AY25: =SUMIFS($CH$3:$CH$341,$A$3:$A$341,Q$2,$C$3:$C$341,Q25) -> 0 | AZ25: =SUMIFS($CH$3:$CH$341,$A$3:$A$341,R$2,$C$3:$C$341,R25) -> 0 | BA25: =SUMIFS($CH$3:$CH$341,$A$3:$A$341,S$2,$C$3:$C$341,S25) -> 0 | BB25: =SUMIFS($CH$3:$CH$341,$A$3:$A$341,T$2,$C$3:$C$341,T25) -> 0 | BC25: =SUMIFS($CH$3:$CH$341,$A$3:$A$341,U$2,$C$3:$C$341,U25) -> 0 | BD25: =SUMIFS($CH$3:$CH$341,$A$3:$A$341,V$2,$C$3:$C$341,V25) -> 0 | BE25: =SUMIFS($CH$3:$CH$341,$A$3:$A$341,W$2,$C$3:$C$341,W25) -> 0 | BF25: =SUMIFS($CH$3:$CH$341,$A$3:$A$341,X$2,$C$3:$C$341,X25) -> 0 | ... CF25: =SUMIFS($CH$3:$CH$341,$A$3:$A$341,AX$2,$C$3:$C$341,AX25) -> 0 | CG25: =MAX(AY25:CF25) -> 0 | CH25: =MAX(F25,CG25) -> 0
A26: MINE/ore vein | B26: Building | C26: 9 | D26: 1 | E26: 9 | F26: 0 | H26: 23040 | I26: 384 | J26: =ROUNDUP(H26/30,0) -> 768 | K26: 0 | L26: 53760 | M26: 153600 | N26: 128000 | O26: 51200 | P26: 1125 | AI26: 8 | AY26: =SUMIFS($CH$3:$CH$341,$A$3:$A$341,Q$2,$C$3:$C$341,Q26) -> 0 | AZ26: =SUMIFS($CH$3:$CH$341,$A$3:$A$341,R$2,$C$3:$C$341,R26) -> 0 | BA26: =SUMIFS($CH$3:$CH$341,$A$3:$A$341,S$2,$C$3:$C$341,#REF!) -> 0 | BB26: =SUMIFS($CH$3:$CH$341,$A$3:$A$341,T$2,$C$3:$C$341,T26) -> 0 | BC26: =SUMIFS($CH$3:$CH$341,$A$3:$A$341,U$2,$C$3:$C$341,U26) -> 0 | BD26: =SUMIFS($CH$3:$CH$341,$A$3:$A$341,V$2,$C$3:$C$341,V26) -> 0 | BE26: =SUMIFS($CH$3:$CH$341,$A$3:$A$341,W$2,$C$3:$C$341,W26) -> 0 | BF26: =SUMIFS($CH$3:$CH$341,$A$3:$A$341,X$2,$C$3:$C$341,X26) -> 0 | BG26: =SUMIFS($CH$3:$CH$341,$A$3:$A$341,Y$2,$C$3:$C$341,Y26) -> 0 | BH26: =SUMIFS($CH$3:$CH$341,$A$3:$A$341,Z$2,$C$3:$C$341,Z26) -> 0 | BI26: =SUMIFS($CH$3:$CH$341,$A$3:$A$341,AA$2,$C$3:$C$341,AA26) -> 0 | ... CF26: =SUMIFS($CH$3:$CH$341,$A$3:$A$341,AX$2,$C$3:$C$341,AX26) -> 0 | CG26: =MAX(AY26:CF26) -> 0 | CH26: =MAX(F26,CG26) -> 0
A27: MINE/ore vein | B27: Building | C27: 10 | D27: 1 | E27: 10 | F27: 0 | G27: Divine Inspiration | H27: 46080 | I27: 768 | J27: =ROUNDUP(H27/30,0) -> 1536 | K27: 0 | L27: 107520 | M27: 307200 | N27: 256000 | O27: 102400 | P27: 1375 | AI27: 9 | AY27: =SUMIFS($CH$3:$CH$341,$A$3:$A$341,Q$2,$C$3:$C$341,Q27) -> 0 | AZ27: =SUMIFS($CH$3:$CH$341,$A$3:$A$341,R$2,$C$3:$C$341,R27) -> 0 | BA27: =SUMIFS($CH$3:$CH$341,$A$3:$A$341,S$2,$C$3:$C$341,S27) -> 0 | BB27: =SUMIFS($CH$3:$CH$341,$A$3:$A$341,T$2,$C$3:$C$341,T27) -> 0 | BC27: =SUMIFS($CH$3:$CH$341,$A$3:$A$341,U$2,$C$3:$C$341,U27) -> 0 | BD27: =SUMIFS($CH$3:$CH$341,$A$3:$A$341,V$2,$C$3:$C$341,V27) -> 0 | BE27: =SUMIFS($CH$3:$CH$341,$A$3:$A$341,W$2,$C$3:$C$341,W27) -> 0 | BF27: =SUMIFS($CH$3:$CH$341,$A$3:$A$341,X$2,$C$3:$C$341,X27) -> 0 | ... CF27: =SUMIFS($CH$3:$CH$341,$A$3:$A$341,AX$2,$C$3:$C$341,AX27) -> 0 | CG27: =MAX(AY27:CF27) -> 0 | CH27: =MAX(F27,CG27) -> 0
A28: Quarry | B28: Building | C28: 1 | D28: 1 | E28: 1 | F28: 0 | H28: 5 | I28: 0.083333333 | J28: =ROUNDUP(H28/30,0) -> 1 | K28: 0 | L28: 180 | M28: 500 | N28: 150 | O28: 400 | P28: 20 | AY28: =SUMIFS($CH$3:$CH$341,$A$3:$A$341,Q$2,$C$3:$C$341,Q28) -> 0 | AZ28: =SUMIFS($CH$3:$CH$341,$A$3:$A$341,R$2,$C$3:$C$341,R28) -> 0 | BA28: =SUMIFS($CH$3:$CH$341,$A$3:$A$341,S$2,$C$3:$C$341,S28) -> 0 | BB28: =SUMIFS($CH$3:$CH$341,$A$3:$A$341,T$2,$C$3:$C$341,T28) -> 0 | BC28: =SUMIFS($CH$3:$CH$341,$A$3:$A$341,U$2,$C$3:$C$341,U28) -> 0 | BD28: =SUMIFS($CH$3:$CH$341,$A$3:$A$341,V$2,$C$3:$C$341,V28) -> 0 | BE28: =SUMIFS($CH$3:$CH$341,$A$3:$A$341,W$2,$C$3:$C$341,W28) -> 0 | BF28: =SUMIFS($CH$3:$CH$341,$A$3:$A$341,X$2,$C$3:$C$341,X28) -> 0 | ... CF28: =SUMIFS($CH$3:$CH$341,$A$3:$A$341,AX$2,$C$3:$C$341,AX28) -> 0 | CG28: =MAX(AY28:CF28) -> 0 | CH28: =MAX(F28,CG28) -> 0
A29: Quarry | B29: Building | C29: 2 | D29: 1 | E29: 2 | F29: 0 | H29: 45 | I29: 0.75 | J29: =ROUNDUP(H29/30,0) -> 2 | K29: 0 | L29: 360 | M29: 1000 | N29: 300 | O29: 800 | P29: 60 | AH29: 1 | AY29: =SUMIFS($CH$3:$CH$341,$A$3:$A$341,Q$2,$C$3:$C$341,Q29) -> 0 | AZ29: =SUMIFS($CH$3:$CH$341,$A$3:$A$341,R$2,$C$3:$C$341,R29) -> 0 | BA29: =SUMIFS($CH$3:$CH$341,$A$3:$A$341,S$2,$C$3:$C$341,S29) -> 0 | BB29: =SUMIFS($CH$3:$CH$341,$A$3:$A$341,T$2,$C$3:$C$341,T29) -> 0 | BC29: =SUMIFS($CH$3:$CH$341,$A$3:$A$341,U$2,$C$3:$C$341,U29) -> 0 | BD29: =SUMIFS($CH$3:$CH$341,$A$3:$A$341,V$2,$C$3:$C$341,V29) -> 0 | BE29: =SUMIFS($CH$3:$CH$341,$A$3:$A$341,W$2,$C$3:$C$341,W29) -> 0 | BF29: =SUMIFS($CH$3:$CH$341,$A$3:$A$341,X$2,$C$3:$C$341,X29) -> 0 | ... CF29: =SUMIFS($CH$3:$CH$341,$A$3:$A$341,AX$2,$C$3:$C$341,AX29) -> 0 | CG29: =MAX(AY29:CF29) -> 0 | CH29: =MAX(F29,CG29) -> 0
A30: Quarry | B30: Building | C30: 3 | D30: 1 | E30: 3 | F30: 0 | H30: 240 | I30: 4 | J30: =ROUNDUP(H30/30,0) -> 8 | K30: 0 | L30: 720 | M30: 2000 | N30: 600 | O30: 1600 | P30: 120 | AH30: 2 | AY30: =SUMIFS($CH$3:$CH$341,$A$3:$A$341,Q$2,$C$3:$C$341,Q30) -> 0 | AZ30: =SUMIFS($CH$3:$CH$341,$A$3:$A$341,R$2,$C$3:$C$341,R30) -> 0 | BA30: =SUMIFS($CH$3:$CH$341,$A$3:$A$341,S$2,$C$3:$C$341,S30) -> 0 | BB30: =SUMIFS($CH$3:$CH$341,$A$3:$A$341,T$2,$C$3:$C$341,T30) -> 0 | BC30: =SUMIFS($CH$3:$CH$341,$A$3:$A$341,U$2,$C$3:$C$341,U30) -> 0 | BD30: =SUMIFS($CH$3:$CH$341,$A$3:$A$341,V$2,$C$3:$C$341,V30) -> 0 | BE30: =SUMIFS($CH$3:$CH$341,$A$3:$A$341,W$2,$C$3:$C$341,W30) -> 0 | BF30: =SUMIFS($CH$3:$CH$341,$A$3:$A$341,X$2,$C$3:$C$341,X30) -> 0 | ... CF30: =SUMIFS($CH$3:$CH$341,$A$3:$A$341,AX$2,$C$3:$C$341,AX30) -> 0 | CG30: =MAX(AY30:CF30) -> 0 | CH30: =MAX(F30,CG30) -> 0
A31: Quarry | B31: Building | C31: 4 | D31: 1 | E31: 4 | F31: 0 | H31: 480 | I31: 8 | J31: =ROUNDUP(H31/30,0) -> 16 | K31: 0 | L31: 1440 | M31: 4000 | N31: 1200 | O31: 3200 | P31: 200 | AH31: 3 | AY31: =SUMIFS($CH$3:$CH$341,$A$3:$A$341,Q$2,$C$3:$C$341,Q31) -> 0 | AZ31: =SUMIFS($CH$3:$CH$341,$A$3:$A$341,R$2,$C$3:$C$341,R31) -> 0 | BA31: =SUMIFS($CH$3:$CH$341,$A$3:$A$341,S$2,$C$3:$C$341,S31) -> 0 | BB31: =SUMIFS($CH$3:$CH$341,$A$3:$A$341,T$2,$C$3:$C$341,T31) -> 0 | BC31: =SUMIFS($CH$3:$CH$341,$A$3:$A$341,U$2,$C$3:$C$341,U31) -> 0 | BD31: =SUMIFS($CH$3:$CH$341,$A$3:$A$341,V$2,$C$3:$C$341,V31) -> 0 | BE31: =SUMIFS($CH$3:$CH$341,$A$3:$A$341,W$2,$C$3:$C$341,W31) -> 0 | BF31: =SUMIFS($CH$3:$CH$341,$A$3:$A$341,X$2,$C$3:$C$341,X31) -> 0 | ... CF31: =SUMIFS($CH$3:$CH$341,$A$3:$A$341,AX$2,$C$3:$C$341,AX31) -> 0 | CG31: =MAX(AY31:CF31) -> 0 | CH31: =MAX(F31,CG31) -> 0
A32: Quarry | B32: Building | C32: 5 | D32: 1 | E32: 5 | F32: 0 | H32: 960 | I32: 16 | J32: =ROUNDUP(H32/30,0) -> 32 | K32: 0 | L32: 2880 | M32: 8000 | N32: 2400 | O32: 6400 | P32: 300 | AH32: 4 | AY32: =SUMIFS($CH$3:$CH$341,$A$3:$A$341,Q$2,$C$3:$C$341,Q32) -> 0 | AZ32: =SUMIFS($CH$3:$CH$341,$A$3:$A$341,R$2,$C$3:$C$341,R32) -> 0 | BA32: =SUMIFS($CH$3:$CH$341,$A$3:$A$341,S$2,$C$3:$C$341,S32) -> 0 | BB32: =SUMIFS($CH$3:$CH$341,$A$3:$A$341,T$2,$C$3:$C$341,T32) -> 0 | BC32: =SUMIFS($CH$3:$CH$341,$A$3:$A$341,U$2,$C$3:$C$341,U32) -> 0 | BD32: =SUMIFS($CH$3:$CH$341,$A$3:$A$341,V$2,$C$3:$C$341,V32) -> 0 | BE32: =SUMIFS($CH$3:$CH$341,$A$3:$A$341,W$2,$C$3:$C$341,W32) -> 0 | BF32: =SUMIFS($CH$3:$CH$341,$A$3:$A$341,X$2,$C$3:$C$341,X32) -> 0 | ... CF32: =SUMIFS($CH$3:$CH$341,$A$3:$A$341,AX$2,$C$3:$C$341,AX32) -> 0 | CG32: =MAX(AY32:CF32) -> 0 | CH32: =MAX(F32,CG32) -> 0
A33: Quarry | B33: Building | C33: 6 | D33: 1 | E33: 6 | F33: 0 | H33: 1920 | I33: 32 | J33: =ROUNDUP(H33/30,0) -> 64 | K33: 0 | L33: 5760 | M33: 16000 | N33: 4800 | O33: 12800 | P33: 420 | AH33: 5 | AY33: =SUMIFS($CH$3:$CH$341,$A$3:$A$341,Q$2,$C$3:$C$341,Q33) -> 0 | AZ33: =SUMIFS($CH$3:$CH$341,$A$3:$A$341,R$2,$C$3:$C$341,R33) -> 0 | BA33: =SUMIFS($CH$3:$CH$341,$A$3:$A$341,S$2,$C$3:$C$341,S33) -> 0 | BB33: =SUMIFS($CH$3:$CH$341,$A$3:$A$341,T$2,$C$3:$C$341,T33) -> 0 | BC33: =SUMIFS($CH$3:$CH$341,$A$3:$A$341,U$2,$C$3:$C$341,U33) -> 0 | BD33: =SUMIFS($CH$3:$CH$341,$A$3:$A$341,V$2,$C$3:$C$341,V33) -> 0 | BE33: =SUMIFS($CH$3:$CH$341,$A$3:$A$341,W$2,$C$3:$C$341,W33) -> 0 | BF33: =SUMIFS($CH$3:$CH$341,$A$3:$A$341,X$2,$C$3:$C$341,X33) -> 0 | ... CF33: =SUMIFS($CH$3:$CH$341,$A$3:$A$341,AX$2,$C$3:$C$341,AX33) -> 0 | CG33: =MAX(AY33:CF33) -> 0 | CH33: =MAX(F33,CG33) -> 0
A34: Quarry | B34: Building | C34: 7 | D34: 1 | E34: 7 | F34: 0 | H34: 3840 | I34: 64 | J34: =ROUNDUP(H34/30,0) -> 128 | K34: 0 | L34: 11520 | M34: 32000 | N34: 9600 | O34: 25600 | P34: 560 | AH34: 6 | AY34: =SUMIFS($CH$3:$CH$341,$A$3:$A$341,Q$2,$C$3:$C$341,Q34) -> 0 | AZ34: =SUMIFS($CH$3:$CH$341,$A$3:$A$341,R$2,$C$3:$C$341,R34) -> 0 | BA34: =SUMIFS($CH$3:$CH$341,$A$3:$A$341,S$2,$C$3:$C$341,S34) -> 0 | BB34: =SUMIFS($CH$3:$CH$341,$A$3:$A$341,T$2,$C$3:$C$341,T34) -> 0 | BC34: =SUMIFS($CH$3:$CH$341,$A$3:$A$341,U$2,$C$3:$C$341,U34) -> 0 | BD34: =SUMIFS($CH$3:$CH$341,$A$3:$A$341,V$2,$C$3:$C$341,V34) -> 0 | BE34: =SUMIFS($CH$3:$CH$341,$A$3:$A$341,W$2,$C$3:$C$341,W34) -> 0 | BF34: =SUMIFS($CH$3:$CH$341,$A$3:$A$341,X$2,$C$3:$C$341,X34) -> 0 | ... CF34: =SUMIFS($CH$3:$CH$341,$A$3:$A$341,AX$2,$C$3:$C$341,AX34) -> 0 | CG34: =MAX(AY34:CF34) -> 0 | CH34: =MAX(F34,CG34) -> 0
A35: Quarry | B35: Building | C35: 8 | D35: 1 | E35: 8 | F35: 0 | H35: 7680 | I35: 128 | J35: =ROUNDUP(H35/30,0) -> 256 | K35: 0 | L35: 23040 | M35: 64000 | N35: 19200 | O35: 51200 | P35: 720 | AH35: 7 | AY35: =SUMIFS($CH$3:$CH$341,$A$3:$A$341,Q$2,$C$3:$C$341,Q35) -> 0 | AZ35: =SUMIFS($CH$3:$CH$341,$A$3:$A$341,R$2,$C$3:$C$341,R35) -> 0 | BA35: =SUMIFS($CH$3:$CH$341,$A$3:$A$341,S$2,$C$3:$C$341,S35) -> 0 | BB35: =SUMIFS($CH$3:$CH$341,$A$3:$A$341,T$2,$C$3:$C$341,T35) -> 0 | BC35: =SUMIFS($CH$3:$CH$341,$A$3:$A$341,U$2,$C$3:$C$341,U35) -> 0 | BD35: =SUMIFS($CH$3:$CH$341,$A$3:$A$341,V$2,$C$3:$C$341,V35) -> 0 | BE35: =SUMIFS($CH$3:$CH$341,$A$3:$A$341,W$2,$C$3:$C$341,W35) -> 0 | BF35: =SUMIFS($CH$3:$CH$341,$A$3:$A$341,X$2,$C$3:$C$341,X35) -> 0 | ... CF35: =SUMIFS($CH$3:$CH$341,$A$3:$A$341,AX$2,$C$3:$C$341,AX35) -> 0 | CG35: =MAX(AY35:CF35) -> 0 | CH35: =MAX(F35,CG35) -> 0
A36: Quarry | B36: Building | C36: 9 | D36: 1 | E36: 9 | F36: 0 | H36: 15360 | I36: 256 | J36: =ROUNDUP(H36/30,0) -> 512 | K36: 0 | L36: 46080 | M36: 128000 | N36: 38400 | O36: 102400 | P36: 900 | AH36: 8 | AY36: =SUMIFS($CH$3:$CH$341,$A$3:$A$341,Q$2,$C$3:$C$341,Q36) -> 0 | AZ36: =SUMIFS($CH$3:$CH$341,$A$3:$A$341,R$2,$C$3:$C$341,R36) -> 0 | BA36: =SUMIFS($CH$3:$CH$341,$A$3:$A$341,S$2,$C$3:$C$341,S36) -> 0 | BB36: =SUMIFS($CH$3:$CH$341,$A$3:$A$341,T$2,$C$3:$C$341,T36) -> 0 | BC36: =SUMIFS($CH$3:$CH$341,$A$3:$A$341,U$2,$C$3:$C$341,U36) -> 0 | BD36: =SUMIFS($CH$3:$CH$341,$A$3:$A$341,V$2,$C$3:$C$341,V36) -> 0 | BE36: =SUMIFS($CH$3:$CH$341,$A$3:$A$341,W$2,$C$3:$C$341,W36) -> 0 | BF36: =SUMIFS($CH$3:$CH$341,$A$3:$A$341,X$2,$C$3:$C$341,X36) -> 0 | ... CF36: =SUMIFS($CH$3:$CH$341,$A$3:$A$341,AX$2,$C$3:$C$341,AX36) -> 0 | CG36: =MAX(AY36:CF36) -> 0 | CH36: =MAX(F36,CG36) -> 0
A37: Quarry | B37: Building | C37: 10 | D37: 1 | E37: 10 | F37: 0 | G37: Divine Inspiration | H37: 30720 | I37: 512 | J37: =ROUNDUP(H37/30,0) -> 1024 | K37: 0 | L37: 92160 | M37: 256000 | N37: 76800 | O37: 204800 | P37: 1100 | AH37: 9 | AY37: =SUMIFS($CH$3:$CH$341,$A$3:$A$341,Q$2,$C$3:$C$341,Q37) -> 0 | AZ37: =SUMIFS($CH$3:$CH$341,$A$3:$A$341,R$2,$C$3:$C$341,R37) -> 0 | BA37: =SUMIFS($CH$3:$CH$341,$A$3:$A$341,S$2,$C$3:$C$341,S37) -> 0 | BB37: =SUMIFS($CH$3:$CH$341,$A$3:$A$341,T$2,$C$3:$C$341,T37) -> 0 | BC37: =SUMIFS($CH$3:$CH$341,$A$3:$A$341,U$2,$C$3:$C$341,U37) -> 0 | BD37: =SUMIFS($CH$3:$CH$341,$A$3:$A$341,V$2,$C$3:$C$341,V37) -> 0 | BE37: =SUMIFS($CH$3:$CH$341,$A$3:$A$341,W$2,$C$3:$C$341,W37) -> 0 | BF37: =SUMIFS($CH$3:$CH$341,$A$3:$A$341,X$2,$C$3:$C$341,X37) -> 0 | ... CF37: =SUMIFS($CH$3:$CH$341,$A$3:$A$341,AX$2,$C$3:$C$341,AX37) -> 0 | CG37: =MAX(AY37:CF37) -> 0 | CH37: =MAX(F37,CG37) -> 0
A38: Arboretum | B38: Building | C38: 1 | D38: 1 | E38: 1 | F38: 0 | H38: 5 | I38: 0.083333333 | J38: =ROUNDUP(H38/30,0) -> 1 | K38: 0 | L38: 100 | M38: 100 | N38: 250 | O38: 300 | P38: 10 | AY38: =SUMIFS($CH$3:$CH$341,$A$3:$A$341,Q$2,$C$3:$C$341,Q38) -> 0 | AZ38: =SUMIFS($CH$3:$CH$341,$A$3:$A$341,R$2,$C$3:$C$341,R38) -> 0 | BA38: =SUMIFS($CH$3:$CH$341,$A$3:$A$341,S$2,$C$3:$C$341,S38) -> 0 | BB38: =SUMIFS($CH$3:$CH$341,$A$3:$A$341,T$2,$C$3:$C$341,T38) -> 0 | BC38: =SUMIFS($CH$3:$CH$341,$A$3:$A$341,U$2,$C$3:$C$341,U38) -> 0 | BD38: =SUMIFS($CH$3:$CH$341,$A$3:$A$341,V$2,$C$3:$C$341,V38) -> 0 | BE38: =SUMIFS($CH$3:$CH$341,$A$3:$A$341,W$2,$C$3:$C$341,W38) -> 0 | BF38: =SUMIFS($CH$3:$CH$341,$A$3:$A$341,X$2,$C$3:$C$341,X38) -> 0 | ... CF38: =SUMIFS($CH$3:$CH$341,$A$3:$A$341,AX$2,$C$3:$C$341,AX38) -> 0 | CG38: =MAX(AY38:CF38) -> 0 | CH38: =MAX(F38,CG38) -> 0
A39: Arboretum | B39: Building | C39: 2 | D39: 1 | E39: 2 | F39: 0 | H39: 45 | I39: 0.75 | J39: =ROUNDUP(H39/30,0) -> 2 | K39: 0 | L39: 200 | M39: 200 | N39: 500 | O39: 600 | P39: 30 | AG39: 1 | AY39: =SUMIFS($CH$3:$CH$341,$A$3:$A$341,Q$2,$C$3:$C$341,Q39) -> 0 | AZ39: =SUMIFS($CH$3:$CH$341,$A$3:$A$341,R$2,$C$3:$C$341,R39) -> 0 | BA39: =SUMIFS($CH$3:$CH$341,$A$3:$A$341,S$2,$C$3:$C$341,S39) -> 0 | BB39: =SUMIFS($CH$3:$CH$341,$A$3:$A$341,T$2,$C$3:$C$341,T39) -> 0 | BC39: =SUMIFS($CH$3:$CH$341,$A$3:$A$341,U$2,$C$3:$C$341,U39) -> 0 | BD39: =SUMIFS($CH$3:$CH$341,$A$3:$A$341,V$2,$C$3:$C$341,V39) -> 0 | BE39: =SUMIFS($CH$3:$CH$341,$A$3:$A$341,W$2,$C$3:$C$341,W39) -> 0 | BF39: =SUMIFS($CH$3:$CH$341,$A$3:$A$341,X$2,$C$3:$C$341,X39) -> 0 | ... CF39: =SUMIFS($CH$3:$CH$341,$A$3:$A$341,AX$2,$C$3:$C$341,AX39) -> 0 | CG39: =MAX(AY39:CF39) -> 0 | CH39: =MAX(F39,CG39) -> 0
A40: Arboretum | B40: Building | C40: 3 | D40: 1 | E40: 3 | F40: 0 | H40: 180 | I40: 3 | J40: =ROUNDUP(H40/30,0) -> 6 | K40: 0 | L40: 400 | M40: 400 | N40: 1000 | O40: 1200 | P40: 60 | AG40: 2 | AY40: =SUMIFS($CH$3:$CH$341,$A$3:$A$341,Q$2,$C$3:$C$341,Q40) -> 0 | AZ40: =SUMIFS($CH$3:$CH$341,$A$3:$A$341,R$2,$C$3:$C$341,R40) -> 0 | BA40: =SUMIFS($CH$3:$CH$341,$A$3:$A$341,S$2,$C$3:$C$341,S40) -> 0 | BB40: =SUMIFS($CH$3:$CH$341,$A$3:$A$341,T$2,$C$3:$C$341,T40) -> 0 | BC40: =SUMIFS($CH$3:$CH$341,$A$3:$A$341,U$2,$C$3:$C$341,U40) -> 0 | BD40: =SUMIFS($CH$3:$CH$341,$A$3:$A$341,V$2,$C$3:$C$341,V40) -> 0 | BE40: =SUMIFS($CH$3:$CH$341,$A$3:$A$341,W$2,$C$3:$C$341,W40) -> 0 | BF40: =SUMIFS($CH$3:$CH$341,$A$3:$A$341,X$2,$C$3:$C$341,X40) -> 0 | ... CF40: =SUMIFS($CH$3:$CH$341,$A$3:$A$341,AX$2,$C$3:$C$341,AX40) -> 0 | CG40: =MAX(AY40:CF40) -> 0 | CH40: =MAX(F40,CG40) -> 0
A41: Arboretum | B41: Building | C41: 4 | D41: 1 | E41: 4 | F41: 0 | H41: 360 | I41: 6 | J41: =ROUNDUP(H41/30,0) -> 12 | K41: 0 | L41: 800 | M41: 800 | N41: 2000 | O41: 2400 | P41: 100 | AG41: 3 | AY41: =SUMIFS($CH$3:$CH$341,$A$3:$A$341,Q$2,$C$3:$C$341,Q41) -> 0 | AZ41: =SUMIFS($CH$3:$CH$341,$A$3:$A$341,R$2,$C$3:$C$341,R41) -> 0 | BA41: =SUMIFS($CH$3:$CH$341,$A$3:$A$341,S$2,$C$3:$C$341,S41) -> 0 | BB41: =SUMIFS($CH$3:$CH$341,$A$3:$A$341,T$2,$C$3:$C$341,T41) -> 0 | BC41: =SUMIFS($CH$3:$CH$341,$A$3:$A$341,U$2,$C$3:$C$341,U41) -> 0 | BD41: =SUMIFS($CH$3:$CH$341,$A$3:$A$341,V$2,$C$3:$C$341,V41) -> 0 | BE41: =SUMIFS($CH$3:$CH$341,$A$3:$A$341,W$2,$C$3:$C$341,W41) -> 0 | BF41: =SUMIFS($CH$3:$CH$341,$A$3:$A$341,X$2,$C$3:$C$341,X41) -> 0 | ... CF41: =SUMIFS($CH$3:$CH$341,$A$3:$A$341,AX$2,$C$3:$C$341,AX41) -> 0 | CG41: =MAX(AY41:CF41) -> 0 | CH41: =MAX(F41,CG41) -> 0
A42: Arboretum | B42: Building | C42: 5 | D42: 1 | E42: 5 | F42: 0 | H42: 720 | I42: 12 | J42: =ROUNDUP(H42/30,0) -> 24 | K42: 0 | L42: 1600 | M42: 1600 | N42: 4000 | O42: 4800 | P42: 150 | AG42: 4 | AY42: =SUMIFS($CH$3:$CH$341,$A$3:$A$341,Q$2,$C$3:$C$341,Q42) -> 0 | AZ42: =SUMIFS($CH$3:$CH$341,$A$3:$A$341,R$2,$C$3:$C$341,R42) -> 0 | BA42: =SUMIFS($CH$3:$CH$341,$A$3:$A$341,S$2,$C$3:$C$341,S42) -> 0 | BB42: =SUMIFS($CH$3:$CH$341,$A$3:$A$341,T$2,$C$3:$C$341,T42) -> 0 | BC42: =SUMIFS($CH$3:$CH$341,$A$3:$A$341,U$2,$C$3:$C$341,U42) -> 0 | BD42: =SUMIFS($CH$3:$CH$341,$A$3:$A$341,V$2,$C$3:$C$341,V42) -> 0 | BE42: =SUMIFS($CH$3:$CH$341,$A$3:$A$341,W$2,$C$3:$C$341,W42) -> 0 | BF42: =SUMIFS($CH$3:$CH$341,$A$3:$A$341,X$2,$C$3:$C$341,X42) -> 0 | ... CF42: =SUMIFS($CH$3:$CH$341,$A$3:$A$341,AX$2,$C$3:$C$341,AX42) -> 0 | CG42: =MAX(AY42:CF42) -> 0 | CH42: =MAX(F42,CG42) -> 0
A43: Arboretum | B43: Building | C43: 6 | D43: 1 | E43: 6 | F43: 0 | H43: 1440 | I43: 24 | J43: =ROUNDUP(H43/30,0) -> 48 | K43: 0 | L43: 3200 | M43: 3200 | N43: 8000 | O43: 9600 | P43: 200 | AG43: 5 | AY43: =SUMIFS($CH$3:$CH$341,$A$3:$A$341,Q$2,$C$3:$C$341,Q43) -> 0 | AZ43: =SUMIFS($CH$3:$CH$341,$A$3:$A$341,R$2,$C$3:$C$341,R43) -> 0 | BA43: =SUMIFS($CH$3:$CH$341,$A$3:$A$341,S$2,$C$3:$C$341,S43) -> 0 | BB43: =SUMIFS($CH$3:$CH$341,$A$3:$A$341,T$2,$C$3:$C$341,T43) -> 0 | BC43: =SUMIFS($CH$3:$CH$341,$A$3:$A$341,U$2,$C$3:$C$341,U43) -> 0 | BD43: =SUMIFS($CH$3:$CH$341,$A$3:$A$341,V$2,$C$3:$C$341,V43) -> 0 | BE43: =SUMIFS($CH$3:$CH$341,$A$3:$A$341,W$2,$C$3:$C$341,W43) -> 0 | BF43: =SUMIFS($CH$3:$CH$341,$A$3:$A$341,X$2,$C$3:$C$341,X43) -> 0 | ... CF43: =SUMIFS($CH$3:$CH$341,$A$3:$A$341,AX$2,$C$3:$C$341,AX43) -> 0 | CG43: =MAX(AY43:CF43) -> 0 | CH43: =MAX(F43,CG43) -> 0
A44: Arboretum | B44: Building | C44: 7 | D44: 1 | E44: 7 | F44: 0 | H44: 2880 | I44: 48 | J44: =ROUNDUP(H44/30,0) -> 96 | K44: 0 | L44: 6400 | M44: 6400 | N44: 16000 | O44: 19200 | P44: 280 | AG44: 6 | AY44: =SUMIFS($CH$3:$CH$341,$A$3:$A$341,Q$2,$C$3:$C$341,Q44) -> 0 | AZ44: =SUMIFS($CH$3:$CH$341,$A$3:$A$341,R$2,$C$3:$C$341,R44) -> 0 | BA44: =SUMIFS($CH$3:$CH$341,$A$3:$A$341,S$2,$C$3:$C$341,S44) -> 0 | BB44: =SUMIFS($CH$3:$CH$341,$A$3:$A$341,T$2,$C$3:$C$341,T44) -> 0 | BC44: =SUMIFS($CH$3:$CH$341,$A$3:$A$341,U$2,$C$3:$C$341,U44) -> 0 | BD44: =SUMIFS($CH$3:$CH$341,$A$3:$A$341,V$2,$C$3:$C$341,V44) -> 0 | BE44: =SUMIFS($CH$3:$CH$341,$A$3:$A$341,W$2,$C$3:$C$341,W44) -> 0 | BF44: =SUMIFS($CH$3:$CH$341,$A$3:$A$341,X$2,$C$3:$C$341,X44) -> 0 | ... CF44: =SUMIFS($CH$3:$CH$341,$A$3:$A$341,AX$2,$C$3:$C$341,AX44) -> 0 | CG44: =MAX(AY44:CF44) -> 0 | CH44: =MAX(F44,CG44) -> 0
A45: Arboretum | B45: Building | C45: 8 | D45: 1 | E45: 8 | F45: 0 | H45: 5760 | I45: 96 | J45: =ROUNDUP(H45/30,0) -> 192 | K45: 0 | L45: 12800 | M45: 12800 | N45: 32000 | O45: 38400 | P45: 360 | AG45: 7 | AY45: =SUMIFS($CH$3:$CH$341,$A$3:$A$341,Q$2,$C$3:$C$341,Q45) -> 0 | AZ45: =SUMIFS($CH$3:$CH$341,$A$3:$A$341,R$2,$C$3:$C$341,R45) -> 0 | BA45: =SUMIFS($CH$3:$CH$341,$A$3:$A$341,S$2,$C$3:$C$341,S45) -> 0 | BB45: =SUMIFS($CH$3:$CH$341,$A$3:$A$341,T$2,$C$3:$C$341,T45) -> 0 | BC45: =SUMIFS($CH$3:$CH$341,$A$3:$A$341,U$2,$C$3:$C$341,U45) -> 0 | BD45: =SUMIFS($CH$3:$CH$341,$A$3:$A$341,V$2,$C$3:$C$341,V45) -> 0 | BE45: =SUMIFS($CH$3:$CH$341,$A$3:$A$341,W$2,$C$3:$C$341,W45) -> 0 | BF45: =SUMIFS($CH$3:$CH$341,$A$3:$A$341,X$2,$C$3:$C$341,X45) -> 0 | ... CF45: =SUMIFS($CH$3:$CH$341,$A$3:$A$341,AX$2,$C$3:$C$341,AX45) -> 0 | CG45: =MAX(AY45:CF45) -> 0 | CH45: =MAX(F45,CG45) -> 0
A46: Arboretum | B46: Building | C46: 9 | D46: 1 | E46: 9 | F46: 0 | H46: 11520 | I46: 192 | J46: =ROUNDUP(H46/30,0) -> 384 | K46: 0 | L46: 25600 | M46: 25600 | N46: 64000 | O46: 76800 | P46: 450 | AG46: 8 | AY46: =SUMIFS($CH$3:$CH$341,$A$3:$A$341,Q$2,$C$3:$C$341,Q46) -> 0 | AZ46: =SUMIFS($CH$3:$CH$341,$A$3:$A$341,R$2,$C$3:$C$341,R46) -> 0 | BA46: =SUMIFS($CH$3:$CH$341,$A$3:$A$341,S$2,$C$3:$C$341,S46) -> 0 | BB46: =SUMIFS($CH$3:$CH$341,$A$3:$A$341,T$2,$C$3:$C$341,T46) -> 0 | BC46: =SUMIFS($CH$3:$CH$341,$A$3:$A$341,U$2,$C$3:$C$341,U46) -> 0 | BD46: =SUMIFS($CH$3:$CH$341,$A$3:$A$341,V$2,$C$3:$C$341,V46) -> 0 | BE46: =SUMIFS($CH$3:$CH$341,$A$3:$A$341,W$2,$C$3:$C$341,W46) -> 0 | BF46: =SUMIFS($CH$3:$CH$341,$A$3:$A$341,X$2,$C$3:$C$341,X46) -> 0 | ... CF46: =SUMIFS($CH$3:$CH$341,$A$3:$A$341,AX$2,$C$3:$C$341,AX46) -> 0 | CG46: =MAX(AY46:CF46) -> 0 | CH46: =MAX(F46,CG46) -> 0
A47: Arboretum | B47: Building | C47: 10 | D47: 1 | E47: 10 | F47: 0 | G47: Divine Inspiration | H47: 23040 | I47: 384 | J47: =ROUNDUP(H47/30,0) -> 768 | K47: 0 | L47: 51200 | M47: 51200 | N47: 128000 | O47: 153600 | P47: 550 | AG47: 9 | AY47: =SUMIFS($CH$3:$CH$341,$A$3:$A$341,Q$2,$C$3:$C$341,Q47) -> 0 | AZ47: =SUMIFS($CH$3:$CH$341,$A$3:$A$341,R$2,$C$3:$C$341,R47) -> 0 | BA47: =SUMIFS($CH$3:$CH$341,$A$3:$A$341,S$2,$C$3:$C$341,S47) -> 0 | BB47: =SUMIFS($CH$3:$CH$341,$A$3:$A$341,T$2,$C$3:$C$341,T47) -> 0 | BC47: =SUMIFS($CH$3:$CH$341,$A$3:$A$341,U$2,$C$3:$C$341,U47) -> 0 | BD47: =SUMIFS($CH$3:$CH$341,$A$3:$A$341,V$2,$C$3:$C$341,V47) -> 0 | BE47: =SUMIFS($CH$3:$CH$341,$A$3:$A$341,W$2,$C$3:$C$341,W47) -> 0 | BF47: =SUMIFS($CH$3:$CH$341,$A$3:$A$341,X$2,$C$3:$C$341,X47) -> 0 | ... CF47: =SUMIFS($CH$3:$CH$341,$A$3:$A$341,AX$2,$C$3:$C$341,AX47) -> 0 | CG47: =MAX(AY47:CF47) -> 0 | CH47: =MAX(F47,CG47) -> 0
A48: Academy | B48: Building | C48: 1 | D48: 1 | E48: 1 | F48: 2 | H48: 15 | I48: 0.25 | J48: =ROUNDUP(H48/30,0) -> 1 | K48: 0 | L48: 120 | M48: 2500 | N48: 1500 | O48: 200 | AY48: =SUMIFS($CH$3:$CH$341,$A$3:$A$341,Q$2,$C$3:$C$341,Q48) -> 0 | AZ48: =SUMIFS($CH$3:$CH$341,$A$3:$A$341,R$2,$C$3:$C$341,R48) -> 0 | BA48: =SUMIFS($CH$3:$CH$341,$A$3:$A$341,S$2,$C$3:$C$341,S48) -> 0 | BB48: =SUMIFS($CH$3:$CH$341,$A$3:$A$341,T$2,$C$3:$C$341,T48) -> 0 | BC48: =SUMIFS($CH$3:$CH$341,$A$3:$A$341,U$2,$C$3:$C$341,U48) -> 0 | BD48: =SUMIFS($CH$3:$CH$341,$A$3:$A$341,V$2,$C$3:$C$341,V48) -> 0 | BE48: =SUMIFS($CH$3:$CH$341,$A$3:$A$341,W$2,$C$3:$C$341,W48) -> 0 | BF48: =SUMIFS($CH$3:$CH$341,$A$3:$A$341,X$2,$C$3:$C$341,X48) -> 0 | ... CF48: =SUMIFS($CH$3:$CH$341,$A$3:$A$341,AX$2,$C$3:$C$341,AX48) -> 0 | CG48: =MAX(AY48:CF48) -> 0 | CH48: =MAX(F48,CG48) -> 2
A49: Academy | B49: Building | C49: 2 | D49: 1 | E49: 2 | F49: 2 | H49: 960 | I49: 16 | J49: =ROUNDUP(H49/30,0) -> 32 | K49: 0 | L49: 240 | M49: 5000 | N49: 3000 | O49: 400 | R49: 1 | AY49: =SUMIFS($CH$3:$CH$341,$A$3:$A$341,Q$2,$C$3:$C$341,Q49) -> 0 | AZ49: =SUMIFS($CH$3:$CH$341,$A$3:$A$341,R$2,$C$3:$C$341,R49) -> 2 | BA49: =SUMIFS($CH$3:$CH$341,$A$3:$A$341,S$2,$C$3:$C$341,S49) -> 0 | BB49: =SUMIFS($CH$3:$CH$341,$A$3:$A$341,T$2,$C$3:$C$341,T49) -> 0 | BC49: =SUMIFS($CH$3:$CH$341,$A$3:$A$341,U$2,$C$3:$C$341,U49) -> 0 | BD49: =SUMIFS($CH$3:$CH$341,$A$3:$A$341,V$2,$C$3:$C$341,V49) -> 0 | BE49: =SUMIFS($CH$3:$CH$341,$A$3:$A$341,W$2,$C$3:$C$341,W49) -> 0 | BF49: =SUMIFS($CH$3:$CH$341,$A$3:$A$341,X$2,$C$3:$C$341,X49) -> 0 | ... CF49: =SUMIFS($CH$3:$CH$341,$A$3:$A$341,AX$2,$C$3:$C$341,AX49) -> 0 | CG49: =MAX(AY49:CF49) -> 2 | CH49: =MAX(F49,CG49) -> 2
A50: Academy | B50: Building | C50: 3 | D50: 1 | E50: 3 | F50: 2 | H50: 1920 | I50: 32 | J50: =ROUNDUP(H50/30,0) -> 64 | K50: 0 | L50: 480 | M50: 10000 | N50: 6000 | O50: 800 | R50: 2 | AY50: =SUMIFS($CH$3:$CH$341,$A$3:$A$341,Q$2,$C$3:$C$341,Q50) -> 0 | AZ50: =SUMIFS($CH$3:$CH$341,$A$3:$A$341,R$2,$C$3:$C$341,R50) -> 2 | BA50: =SUMIFS($CH$3:$CH$341,$A$3:$A$341,S$2,$C$3:$C$341,S50) -> 0 | BB50: =SUMIFS($CH$3:$CH$341,$A$3:$A$341,T$2,$C$3:$C$341,T50) -> 0 | BC50: =SUMIFS($CH$3:$CH$341,$A$3:$A$341,U$2,$C$3:$C$341,U50) -> 0 | BD50: =SUMIFS($CH$3:$CH$341,$A$3:$A$341,V$2,$C$3:$C$341,V50) -> 0 | BE50: =SUMIFS($CH$3:$CH$341,$A$3:$A$341,W$2,$C$3:$C$341,W50) -> 0 | BF50: =SUMIFS($CH$3:$CH$341,$A$3:$A$341,X$2,$C$3:$C$341,X50) -> 0 | ... CF50: =SUMIFS($CH$3:$CH$341,$A$3:$A$341,AX$2,$C$3:$C$341,AX50) -> 0 | CG50: =MAX(AY50:CF50) -> 2 | CH50: =MAX(F50,CG50) -> 2
A51: Academy | B51: Building | C51: 4 | D51: 1 | E51: 4 | F51: 2 | H51: 3840 | I51: 64 | J51: =ROUNDUP(H51/30,0) -> 128 | K51: 0 | L51: 960 | M51: 20000 | N51: 12000 | O51: 1600 | R51: 3 | AY51: =SUMIFS($CH$3:$CH$341,$A$3:$A$341,Q$2,$C$3:$C$341,Q51) -> 0 | AZ51: =SUMIFS($CH$3:$CH$341,$A$3:$A$341,R$2,$C$3:$C$341,R51) -> 2 | BA51: =SUMIFS($CH$3:$CH$341,$A$3:$A$341,S$2,$C$3:$C$341,S51) -> 0 | BB51: =SUMIFS($CH$3:$CH$341,$A$3:$A$341,T$2,$C$3:$C$341,T51) -> 0 | BC51: =SUMIFS($CH$3:$CH$341,$A$3:$A$341,U$2,$C$3:$C$341,U51) -> 0 | BD51: =SUMIFS($CH$3:$CH$341,$A$3:$A$341,V$2,$C$3:$C$341,V51) -> 0 | BE51: =SUMIFS($CH$3:$CH$341,$A$3:$A$341,W$2,$C$3:$C$341,W51) -> 0 | BF51: =SUMIFS($CH$3:$CH$341,$A$3:$A$341,X$2,$C$3:$C$341,X51) -> 0 | ... CF51: =SUMIFS($CH$3:$CH$341,$A$3:$A$341,AX$2,$C$3:$C$341,AX51) -> 0 | CG51: =MAX(AY51:CF51) -> 2 | CH51: =MAX(F51,CG51) -> 2
A52: Academy | B52: Building | C52: 5 | D52: 1 | E52: 5 | F52: 2 | H52: 7680 | I52: 128 | J52: =ROUNDUP(H52/30,0) -> 256 | K52: 0 | L52: 1920 | M52: 40000 | N52: 24000 | O52: 3200 | R52: 4 | AY52: =SUMIFS($CH$3:$CH$341,$A$3:$A$341,Q$2,$C$3:$C$341,Q52) -> 0 | AZ52: =SUMIFS($CH$3:$CH$341,$A$3:$A$341,R$2,$C$3:$C$341,R52) -> 2 | BA52: =SUMIFS($CH$3:$CH$341,$A$3:$A$341,S$2,$C$3:$C$341,S52) -> 0 | BB52: =SUMIFS($CH$3:$CH$341,$A$3:$A$341,T$2,$C$3:$C$341,T52) -> 0 | BC52: =SUMIFS($CH$3:$CH$341,$A$3:$A$341,U$2,$C$3:$C$341,U52) -> 0 | BD52: =SUMIFS($CH$3:$CH$341,$A$3:$A$341,V$2,$C$3:$C$341,V52) -> 0 | BE52: =SUMIFS($CH$3:$CH$341,$A$3:$A$341,W$2,$C$3:$C$341,W52) -> 0 | BF52: =SUMIFS($CH$3:$CH$341,$A$3:$A$341,X$2,$C$3:$C$341,X52) -> 0 | ... CF52: =SUMIFS($CH$3:$CH$341,$A$3:$A$341,AX$2,$C$3:$C$341,AX52) -> 0 | CG52: =MAX(AY52:CF52) -> 2 | CH52: =MAX(F52,CG52) -> 2
A53: Academy | B53: Building | C53: 6 | D53: 1 | E53: 6 | F53: 2 | H53: 15360 | I53: 256 | J53: =ROUNDUP(H53/30,0) -> 512 | K53: 0 | L53: 3840 | M53: 80000 | N53: 48000 | O53: 6400 | R53: 5 | AY53: =SUMIFS($CH$3:$CH$341,$A$3:$A$341,Q$2,$C$3:$C$341,Q53) -> 0 | AZ53: =SUMIFS($CH$3:$CH$341,$A$3:$A$341,R$2,$C$3:$C$341,R53) -> 2 | BA53: =SUMIFS($CH$3:$CH$341,$A$3:$A$341,S$2,$C$3:$C$341,S53) -> 0 | BB53: =SUMIFS($CH$3:$CH$341,$A$3:$A$341,T$2,$C$3:$C$341,T53) -> 0 | BC53: =SUMIFS($CH$3:$CH$341,$A$3:$A$341,U$2,$C$3:$C$341,U53) -> 0 | BD53: =SUMIFS($CH$3:$CH$341,$A$3:$A$341,V$2,$C$3:$C$341,V53) -> 0 | BE53: =SUMIFS($CH$3:$CH$341,$A$3:$A$341,W$2,$C$3:$C$341,W53) -> 0 | BF53: =SUMIFS($CH$3:$CH$341,$A$3:$A$341,X$2,$C$3:$C$341,X53) -> 0 | ... CF53: =SUMIFS($CH$3:$CH$341,$A$3:$A$341,AX$2,$C$3:$C$341,AX53) -> 0 | CG53: =MAX(AY53:CF53) -> 2 | CH53: =MAX(F53,CG53) -> 2
A54: Academy | B54: Building | C54: 7 | D54: 1 | E54: 7 | F54: 2 | H54: 30720 | I54: 512 | J54: =ROUNDUP(H54/30,0) -> 1024 | K54: 0 | L54: 7680 | M54: 160000 | N54: 96000 | O54: 12800 | R54: 6 | AY54: =SUMIFS($CH$3:$CH$341,$A$3:$A$341,Q$2,$C$3:$C$341,Q54) -> 0 | AZ54: =SUMIFS($CH$3:$CH$341,$A$3:$A$341,R$2,$C$3:$C$341,R54) -> 2 | BA54: =SUMIFS($CH$3:$CH$341,$A$3:$A$341,S$2,$C$3:$C$341,S54) -> 0 | BB54: =SUMIFS($CH$3:$CH$341,$A$3:$A$341,T$2,$C$3:$C$341,T54) -> 0 | BC54: =SUMIFS($CH$3:$CH$341,$A$3:$A$341,U$2,$C$3:$C$341,U54) -> 0 | BD54: =SUMIFS($CH$3:$CH$341,$A$3:$A$341,V$2,$C$3:$C$341,V54) -> 0 | BE54: =SUMIFS($CH$3:$CH$341,$A$3:$A$341,W$2,$C$3:$C$341,W54) -> 0 | BF54: =SUMIFS($CH$3:$CH$341,$A$3:$A$341,X$2,$C$3:$C$341,X54) -> 0 | ... CF54: =SUMIFS($CH$3:$CH$341,$A$3:$A$341,AX$2,$C$3:$C$341,AX54) -> 0 | CG54: =MAX(AY54:CF54) -> 2 | CH54: =MAX(F54,CG54) -> 2
A55: Academy | B55: Building | C55: 8 | D55: 1 | E55: 8 | F55: 2 | H55: 61440 | I55: 1024 | J55: =ROUNDUP(H55/30,0) -> 2048 | K55: 0 | L55: 15360 | M55: 320000 | N55: 192000 | O55: 25600 | R55: 7 | AY55: =SUMIFS($CH$3:$CH$341,$A$3:$A$341,Q$2,$C$3:$C$341,Q55) -> 0 | AZ55: =SUMIFS($CH$3:$CH$341,$A$3:$A$341,R$2,$C$3:$C$341,R55) -> 2 | BA55: =SUMIFS($CH$3:$CH$341,$A$3:$A$341,S$2,$C$3:$C$341,S55) -> 0 | BB55: =SUMIFS($CH$3:$CH$341,$A$3:$A$341,T$2,$C$3:$C$341,T55) -> 0 | BC55: =SUMIFS($CH$3:$CH$341,$A$3:$A$341,U$2,$C$3:$C$341,U55) -> 0 | BD55: =SUMIFS($CH$3:$CH$341,$A$3:$A$341,V$2,$C$3:$C$341,V55) -> 0 | BE55: =SUMIFS($CH$3:$CH$341,$A$3:$A$341,W$2,$C$3:$C$341,W55) -> 0 | BF55: =SUMIFS($CH$3:$CH$341,$A$3:$A$341,X$2,$C$3:$C$341,X55) -> 0 | ... CF55: =SUMIFS($CH$3:$CH$341,$A$3:$A$341,AX$2,$C$3:$C$341,AX55) -> 0 | CG55: =MAX(AY55:CF55) -> 2 | CH55: =MAX(F55,CG55) -> 2
A56: Academy | B56: Building | C56: 9 | D56: 1 | E56: 9 | F56: 2 | H56: 122880 | I56: 2048 | J56: =ROUNDUP(H56/30,0) -> 4096 | K56: 0 | L56: 30720 | M56: 640000 | N56: 384000 | O56: 51200 | R56: 8 | AY56: =SUMIFS($CH$3:$CH$341,$A$3:$A$341,Q$2,$C$3:$C$341,Q56) -> 0 | AZ56: =SUMIFS($CH$3:$CH$341,$A$3:$A$341,R$2,$C$3:$C$341,R56) -> 2 | BA56: =SUMIFS($CH$3:$CH$341,$A$3:$A$341,S$2,$C$3:$C$341,S56) -> 0 | BB56: =SUMIFS($CH$3:$CH$341,$A$3:$A$341,T$2,$C$3:$C$341,T56) -> 0 | BC56: =SUMIFS($CH$3:$CH$341,$A$3:$A$341,U$2,$C$3:$C$341,U56) -> 0 | BD56: =SUMIFS($CH$3:$CH$341,$A$3:$A$341,V$2,$C$3:$C$341,V56) -> 0 | BE56: =SUMIFS($CH$3:$CH$341,$A$3:$A$341,W$2,$C$3:$C$341,W56) -> 0 | BF56: =SUMIFS($CH$3:$CH$341,$A$3:$A$341,X$2,$C$3:$C$341,X56) -> 0 | ... CF56: =SUMIFS($CH$3:$CH$341,$A$3:$A$341,AX$2,$C$3:$C$341,AX56) -> 0 | CG56: =MAX(AY56:CF56) -> 2 | CH56: =MAX(F56,CG56) -> 2
A57: Academy | B57: Building | C57: 10 | D57: 1 | E57: 10 | F57: 2 | G57: Divine Inspiration | H57: 245760 | I57: 4096 | J57: =ROUNDUP(H57/30,0) -> 8192 | K57: 0 | L57: 61440 | M57: 1280000 | N57: 768000 | O57: 102400 | R57: 9 | AY57: =SUMIFS($CH$3:$CH$341,$A$3:$A$341,Q$2,$C$3:$C$341,Q57) -> 0 | AZ57: =SUMIFS($CH$3:$CH$341,$A$3:$A$341,R$2,$C$3:$C$341,R57) -> 2 | BA57: =SUMIFS($CH$3:$CH$341,$A$3:$A$341,S$2,$C$3:$C$341,S57) -> 0 | BB57: =SUMIFS($CH$3:$CH$341,$A$3:$A$341,T$2,$C$3:$C$341,T57) -> 0 | BC57: =SUMIFS($CH$3:$CH$341,$A$3:$A$341,U$2,$C$3:$C$341,U57) -> 0 | BD57: =SUMIFS($CH$3:$CH$341,$A$3:$A$341,V$2,$C$3:$C$341,V57) -> 0 | BE57: =SUMIFS($CH$3:$CH$341,$A$3:$A$341,W$2,$C$3:$C$341,W57) -> 0 | BF57: =SUMIFS($CH$3:$CH$341,$A$3:$A$341,X$2,$C$3:$C$341,X57) -> 0 | ... CF57: =SUMIFS($CH$3:$CH$341,$A$3:$A$341,AX$2,$C$3:$C$341,AX57) -> 0 | CG57: =MAX(AY57:CF57) -> 2 | CH57: =MAX(F57,CG57) -> 2
A58: Barracks | B58: Building | C58: 1 | D58: 1 | E58: 1 | F58: 2 | H58: 300 | I58: 5 | J58: =ROUNDUP(H58/30,0) -> 10 | K58: 0 | L58: 250 | M58: 1200 | N58: 1500 | O58: 500 | AY58: =SUMIFS($CH$3:$CH$341,$A$3:$A$341,Q$2,$C$3:$C$341,Q58) -> 0 | AZ58: =SUMIFS($CH$3:$CH$341,$A$3:$A$341,R$2,$C$3:$C$341,R58) -> 0 | BA58: =SUMIFS($CH$3:$CH$341,$A$3:$A$341,S$2,$C$3:$C$341,S58) -> 0 | BB58: =SUMIFS($CH$3:$CH$341,$A$3:$A$341,T$2,$C$3:$C$341,T58) -> 0 | BC58: =SUMIFS($CH$3:$CH$341,$A$3:$A$341,U$2,$C$3:$C$341,U58) -> 0 | BD58: =SUMIFS($CH$3:$CH$341,$A$3:$A$341,V$2,$C$3:$C$341,V58) -> 0 | BE58: =SUMIFS($CH$3:$CH$341,$A$3:$A$341,W$2,$C$3:$C$341,W58) -> 0 | BF58: =SUMIFS($CH$3:$CH$341,$A$3:$A$341,X$2,$C$3:$C$341,X58) -> 0 | ... CF58: =SUMIFS($CH$3:$CH$341,$A$3:$A$341,AX$2,$C$3:$C$341,AX58) -> 0 | CG58: =MAX(AY58:CF58) -> 0 | CH58: =MAX(F58,CG58) -> 2
A59: Barracks | B59: Building | C59: 2 | D59: 1 | E59: 2 | F59: 2 | H59: 600 | I59: 10 | J59: =ROUNDUP(H59/30,0) -> 20 | K59: 0 | L59: 500 | M59: 2400 | N59: 3000 | O59: 1000 | T59: 1 | AY59: =SUMIFS($CH$3:$CH$341,$A$3:$A$341,Q$2,$C$3:$C$341,Q59) -> 0 | AZ59: =SUMIFS($CH$3:$CH$341,$A$3:$A$341,R$2,$C$3:$C$341,R59) -> 0 | BA59: =SUMIFS($CH$3:$CH$341,$A$3:$A$341,S$2,$C$3:$C$341,S59) -> 0 | BB59: =SUMIFS($CH$3:$CH$341,$A$3:$A$341,T$2,$C$3:$C$341,T59) -> 2 | BC59: =SUMIFS($CH$3:$CH$341,$A$3:$A$341,U$2,$C$3:$C$341,U59) -> 0 | BD59: =SUMIFS($CH$3:$CH$341,$A$3:$A$341,V$2,$C$3:$C$341,V59) -> 0 | BE59: =SUMIFS($CH$3:$CH$341,$A$3:$A$341,W$2,$C$3:$C$341,W59) -> 0 | BF59: =SUMIFS($CH$3:$CH$341,$A$3:$A$341,X$2,$C$3:$C$341,X59) -> 0 | ... CF59: =SUMIFS($CH$3:$CH$341,$A$3:$A$341,AX$2,$C$3:$C$341,AX59) -> 0 | CG59: =MAX(AY59:CF59) -> 2 | CH59: =MAX(F59,CG59) -> 2
A60: Barracks | B60: Building | C60: 3 | D60: 1 | E60: 3 | F60: 2 | H60: 1200 | I60: 20 | J60: =ROUNDUP(H60/30,0) -> 40 | K60: 0 | L60: 1000 | M60: 4800 | N60: 6000 | O60: 2000 | T60: 2 | AY60: =SUMIFS($CH$3:$CH$341,$A$3:$A$341,Q$2,$C$3:$C$341,Q60) -> 0 | AZ60: =SUMIFS($CH$3:$CH$341,$A$3:$A$341,R$2,$C$3:$C$341,R60) -> 0 | BA60: =SUMIFS($CH$3:$CH$341,$A$3:$A$341,S$2,$C$3:$C$341,S60) -> 0 | BB60: =SUMIFS($CH$3:$CH$341,$A$3:$A$341,T$2,$C$3:$C$341,T60) -> 2 | BC60: =SUMIFS($CH$3:$CH$341,$A$3:$A$341,U$2,$C$3:$C$341,U60) -> 0 | BD60: =SUMIFS($CH$3:$CH$341,$A$3:$A$341,V$2,$C$3:$C$341,V60) -> 0 | BE60: =SUMIFS($CH$3:$CH$341,$A$3:$A$341,W$2,$C$3:$C$341,W60) -> 0 | BF60: =SUMIFS($CH$3:$CH$341,$A$3:$A$341,X$2,$C$3:$C$341,X60) -> 0 | ... CF60: =SUMIFS($CH$3:$CH$341,$A$3:$A$341,AX$2,$C$3:$C$341,AX60) -> 0 | CG60: =MAX(AY60:CF60) -> 2 | CH60: =MAX(F60,CG60) -> 2
A61: Barracks | B61: Building | C61: 4 | D61: 1 | E61: 4 | F61: 2 | H61: 2400 | I61: 40 | J61: =ROUNDUP(H61/30,0) -> 80 | K61: 0 | L61: 2000 | M61: 9600 | N61: 12000 | O61: 4000 | T61: 3 | AY61: =SUMIFS($CH$3:$CH$341,$A$3:$A$341,Q$2,$C$3:$C$341,Q61) -> 0 | AZ61: =SUMIFS($CH$3:$CH$341,$A$3:$A$341,R$2,$C$3:$C$341,R61) -> 0 | BA61: =SUMIFS($CH$3:$CH$341,$A$3:$A$341,S$2,$C$3:$C$341,S61) -> 0 | BB61: =SUMIFS($CH$3:$CH$341,$A$3:$A$341,T$2,$C$3:$C$341,T61) -> 2 | BC61: =SUMIFS($CH$3:$CH$341,$A$3:$A$341,U$2,$C$3:$C$341,U61) -> 0 | BD61: =SUMIFS($CH$3:$CH$341,$A$3:$A$341,V$2,$C$3:$C$341,V61) -> 0 | BE61: =SUMIFS($CH$3:$CH$341,$A$3:$A$341,W$2,$C$3:$C$341,W61) -> 0 | BF61: =SUMIFS($CH$3:$CH$341,$A$3:$A$341,X$2,$C$3:$C$341,X61) -> 0 | ... CF61: =SUMIFS($CH$3:$CH$341,$A$3:$A$341,AX$2,$C$3:$C$341,AX61) -> 0 | CG61: =MAX(AY61:CF61) -> 2 | CH61: =MAX(F61,CG61) -> 2
A62: Barracks | B62: Building | C62: 5 | D62: 1 | E62: 5 | F62: 2 | H62: 4800 | I62: 80 | J62: =ROUNDUP(H62/30,0) -> 160 | K62: 0 | L62: 4000 | M62: 19200 | N62: 24000 | O62: 8000 | T62: 4 | AY62: =SUMIFS($CH$3:$CH$341,$A$3:$A$341,Q$2,$C$3:$C$341,Q62) -> 0 | AZ62: =SUMIFS($CH$3:$CH$341,$A$3:$A$341,R$2,$C$3:$C$341,R62) -> 0 | BA62: =SUMIFS($CH$3:$CH$341,$A$3:$A$341,S$2,$C$3:$C$341,S62) -> 0 | BB62: =SUMIFS($CH$3:$CH$341,$A$3:$A$341,T$2,$C$3:$C$341,T62) -> 2 | BC62: =SUMIFS($CH$3:$CH$341,$A$3:$A$341,U$2,$C$3:$C$341,U62) -> 0 | BD62: =SUMIFS($CH$3:$CH$341,$A$3:$A$341,V$2,$C$3:$C$341,V62) -> 0 | BE62: =SUMIFS($CH$3:$CH$341,$A$3:$A$341,W$2,$C$3:$C$341,W62) -> 0 | BF62: =SUMIFS($CH$3:$CH$341,$A$3:$A$341,X$2,$C$3:$C$341,X62) -> 0 | ... CF62: =SUMIFS($CH$3:$CH$341,$A$3:$A$341,AX$2,$C$3:$C$341,AX62) -> 0 | CG62: =MAX(AY62:CF62) -> 2 | CH62: =MAX(F62,CG62) -> 2
A63: Barracks | B63: Building | C63: 6 | D63: 1 | E63: 6 | F63: 2 | H63: 9600 | I63: 160 | J63: =ROUNDUP(H63/30,0) -> 320 | K63: 0 | L63: 8000 | M63: 38400 | N63: 48000 | O63: 16000 | T63: 5 | AY63: =SUMIFS($CH$3:$CH$341,$A$3:$A$341,Q$2,$C$3:$C$341,Q63) -> 0 | AZ63: =SUMIFS($CH$3:$CH$341,$A$3:$A$341,R$2,$C$3:$C$341,R63) -> 0 | BA63: =SUMIFS($CH$3:$CH$341,$A$3:$A$341,S$2,$C$3:$C$341,S63) -> 0 | BB63: =SUMIFS($CH$3:$CH$341,$A$3:$A$341,T$2,$C$3:$C$341,T63) -> 2 | BC63: =SUMIFS($CH$3:$CH$341,$A$3:$A$341,U$2,$C$3:$C$341,U63) -> 0 | BD63: =SUMIFS($CH$3:$CH$341,$A$3:$A$341,V$2,$C$3:$C$341,V63) -> 0 | BE63: =SUMIFS($CH$3:$CH$341,$A$3:$A$341,W$2,$C$3:$C$341,W63) -> 0 | BF63: =SUMIFS($CH$3:$CH$341,$A$3:$A$341,X$2,$C$3:$C$341,X63) -> 0 | ... CF63: =SUMIFS($CH$3:$CH$341,$A$3:$A$341,AX$2,$C$3:$C$341,AX63) -> 0 | CG63: =MAX(AY63:CF63) -> 2 | CH63: =MAX(F63,CG63) -> 2
A64: Barracks | B64: Building | C64: 7 | D64: 1 | E64: 7 | F64: 2 | H64: 19200 | I64: 320 | J64: =ROUNDUP(H64/30,0) -> 640 | K64: 0 | L64: 16000 | M64: 76800 | N64: 96000 | O64: 32000 | T64: 6 | AY64: =SUMIFS($CH$3:$CH$341,$A$3:$A$341,Q$2,$C$3:$C$341,Q64) -> 0 | AZ64: =SUMIFS($CH$3:$CH$341,$A$3:$A$341,R$2,$C$3:$C$341,R64) -> 0 | BA64: =SUMIFS($CH$3:$CH$341,$A$3:$A$341,S$2,$C$3:$C$341,S64) -> 0 | BB64: =SUMIFS($CH$3:$CH$341,$A$3:$A$341,T$2,$C$3:$C$341,T64) -> 2 | BC64: =SUMIFS($CH$3:$CH$341,$A$3:$A$341,U$2,$C$3:$C$341,U64) -> 0 | BD64: =SUMIFS($CH$3:$CH$341,$A$3:$A$341,V$2,$C$3:$C$341,V64) -> 0 | BE64: =SUMIFS($CH$3:$CH$341,$A$3:$A$341,W$2,$C$3:$C$341,W64) -> 0 | BF64: =SUMIFS($CH$3:$CH$341,$A$3:$A$341,X$2,$C$3:$C$341,X64) -> 0 | ... CF64: =SUMIFS($CH$3:$CH$341,$A$3:$A$341,AX$2,$C$3:$C$341,AX64) -> 0 | CG64: =MAX(AY64:CF64) -> 2 | CH64: =MAX(F64,CG64) -> 2
A65: Barracks | B65: Building | C65: 8 | D65: 1 | E65: 8 | F65: 2 | H65: 38400 | I65: 640 | J65: =ROUNDUP(H65/30,0) -> 1280 | K65: 0 | L65: 32000 | M65: 153600 | N65: 192000 | O65: 64000 | T65: 7 | AY65: =SUMIFS($CH$3:$CH$341,$A$3:$A$341,Q$2,$C$3:$C$341,Q65) -> 0 | AZ65: =SUMIFS($CH$3:$CH$341,$A$3:$A$341,R$2,$C$3:$C$341,R65) -> 0 | BA65: =SUMIFS($CH$3:$CH$341,$A$3:$A$341,S$2,$C$3:$C$341,S65) -> 0 | BB65: =SUMIFS($CH$3:$CH$341,$A$3:$A$341,T$2,$C$3:$C$341,T65) -> 2 | BC65: =SUMIFS($CH$3:$CH$341,$A$3:$A$341,U$2,$C$3:$C$341,U65) -> 0 | BD65: =SUMIFS($CH$3:$CH$341,$A$3:$A$341,V$2,$C$3:$C$341,V65) -> 0 | BE65: =SUMIFS($CH$3:$CH$341,$A$3:$A$341,W$2,$C$3:$C$341,W65) -> 0 | BF65: =SUMIFS($CH$3:$CH$341,$A$3:$A$341,X$2,$C$3:$C$341,X65) -> 0 | ... CF65: =SUMIFS($CH$3:$CH$341,$A$3:$A$341,AX$2,$C$3:$C$341,AX65) -> 0 | CG65: =MAX(AY65:CF65) -> 2 | CH65: =MAX(F65,CG65) -> 2
A66: Barracks | B66: Building | C66: 9 | D66: 1 | E66: 9 | F66: 2 | H66: 76800 | I66: 1280 | J66: =ROUNDUP(H66/30,0) -> 2560 | K66: 0 | L66: 64000 | M66: 307200 | N66: 384000 | O66: 128000 | T66: 8 | AY66: =SUMIFS($CH$3:$CH$341,$A$3:$A$341,Q$2,$C$3:$C$341,Q66) -> 0 | AZ66: =SUMIFS($CH$3:$CH$341,$A$3:$A$341,R$2,$C$3:$C$341,R66) -> 0 | BA66: =SUMIFS($CH$3:$CH$341,$A$3:$A$341,S$2,$C$3:$C$341,S66) -> 0 | BB66: =SUMIFS($CH$3:$CH$341,$A$3:$A$341,T$2,$C$3:$C$341,T66) -> 2 | BC66: =SUMIFS($CH$3:$CH$341,$A$3:$A$341,U$2,$C$3:$C$341,U66) -> 0 | BD66: =SUMIFS($CH$3:$CH$341,$A$3:$A$341,V$2,$C$3:$C$341,V66) -> 0 | BE66: =SUMIFS($CH$3:$CH$341,$A$3:$A$341,W$2,$C$3:$C$341,W66) -> 0 | BF66: =SUMIFS($CH$3:$CH$341,$A$3:$A$341,X$2,$C$3:$C$341,X66) -> 0 | ... CF66: =SUMIFS($CH$3:$CH$341,$A$3:$A$341,AX$2,$C$3:$C$341,AX66) -> 0 | CG66: =MAX(AY66:CF66) -> 2 | CH66: =MAX(F66,CG66) -> 2
A67: Barracks | B67: Building | C67: 10 | D67: 1 | E67: 10 | F67: 2 | G67: Divine Inspiration | H67: 153600 | I67: 2560 | J67: =ROUNDUP(H67/30,0) -> 5120 | K67: 0 | L67: 128000 | M67: 614400 | N67: 768000 | O67: 256000 | T67: 9 | AY67: =SUMIFS($CH$3:$CH$341,$A$3:$A$341,Q$2,$C$3:$C$341,Q67) -> 0 | AZ67: =SUMIFS($CH$3:$CH$341,$A$3:$A$341,R$2,$C$3:$C$341,R67) -> 0 | BA67: =SUMIFS($CH$3:$CH$341,$A$3:$A$341,S$2,$C$3:$C$341,S67) -> 0 | BB67: =SUMIFS($CH$3:$CH$341,$A$3:$A$341,T$2,$C$3:$C$341,T67) -> 2 | BC67: =SUMIFS($CH$3:$CH$341,$A$3:$A$341,U$2,$C$3:$C$341,U67) -> 0 | BD67: =SUMIFS($CH$3:$CH$341,$A$3:$A$341,V$2,$C$3:$C$341,V67) -> 0 | BE67: =SUMIFS($CH$3:$CH$341,$A$3:$A$341,W$2,$C$3:$C$341,W67) -> 0 | BF67: =SUMIFS($CH$3:$CH$341,$A$3:$A$341,X$2,$C$3:$C$341,X67) -> 0 | ... CF67: =SUMIFS($CH$3:$CH$341,$A$3:$A$341,AX$2,$C$3:$C$341,AX67) -> 0 | CG67: =MAX(AY67:CF67) -> 2 | CH67: =MAX(F67,CG67) -> 2
A68: Far Seeing | B68: Research | C68: 1 | D68: 1 | E68: 1 | F68: 0 | H68: 30 | I68: 0.5 | J68: =ROUNDUP(H68/30,0) -> 1 | K68: 2000 | L68: 300 | M68: 0 | N68: 0 | O68: 0 | R68: 1 | AY68: =SUMIFS($CH$3:$CH$341,$A$3:$A$341,Q$2,$C$3:$C$341,Q68) -> 0 | AZ68: =SUMIFS($CH$3:$CH$341,$A$3:$A$341,R$2,$C$3:$C$341,R68) -> 2 | BA68: =SUMIFS($CH$3:$CH$341,$A$3:$A$341,S$2,$C$3:$C$341,S68) -> 0 | BB68: =SUMIFS($CH$3:$CH$341,$A$3:$A$341,T$2,$C$3:$C$341,T68) -> 0 | BC68: =SUMIFS($CH$3:$CH$341,$A$3:$A$341,U$2,$C$3:$C$341,U68) -> 0 | BD68: =SUMIFS($CH$3:$CH$341,$A$3:$A$341,V$2,$C$3:$C$341,V68) -> 0 | BE68: =SUMIFS($CH$3:$CH$341,$A$3:$A$341,W$2,$C$3:$C$341,W68) -> 0 | BF68: =SUMIFS($CH$3:$CH$341,$A$3:$A$341,X$2,$C$3:$C$341,X68) -> 0 | ... CF68: =SUMIFS($CH$3:$CH$341,$A$3:$A$341,AX$2,$C$3:$C$341,AX68) -> 0 | CG68: =MAX(AY68:CF68) -> 2 | CH68: =MAX(F68,CG68) -> 2 | CI68: =K68 -> 2000 | CJ68: =IF(CJ$2<>$A68,SUMIFS($CY$1:$CY$464,$A$1:$A$464,CJ$2,$C$1:$C$464,BR68),0) -> 0 | CK68: =IF(CK$2<>$A68,SUMIFS($CY$1:$CY$464,$A$1:$A$464,CK$2,$C$1:$C$464,BS68),0) -> 0 | CL68: =IF(CL$2<>$A68,SUMIFS($CY$1:$CY$464,$A$1:$A$464,CL$2,$C$1:$C$464,BT68),0) -> 0 | CM68: =IF(CM$2<>$A68,SUMIFS($CY$1:$CY$464,$A$1:$A$464,CM$2,$C$1:$C$464,BU68),0) -> 0 | CN68: =IF(CN$2<>$A68,SUMIFS($CY$1:$CY$464,$A$1:$A$464,CN$2,$C$1:$C$464,BV68),0) -> 0 | CO68: =IF(CO$2<>$A68,SUMIFS($CY$1:$CY$464,$A$1:$A$464,CO$2,$C$1:$C$464,BW68),0) -> 0 | CP68: =IF(CP$2<>$A68,SUMIFS($CY$1:$CY$464,$A$1:$A$464,CP$2,$C$1:$C$464,BX68),0) -> 0 | CQ68: =IF(CQ$2<>$A68,SUMIFS($CY$1:$CY$464,$A$1:$A$464,CQ$2,$C$1:$C$464,BY68),0) -> 0 | ... CX68: =IF(CX$2<>$A68,SUMIFS($CY$1:$CY$464,$A$1:$A$464,CX$2,$C$1:$C$464,CF68),0) -> 0 | CY68: =SUM(CI68:CX68) -> 2000
A69: Far Seeing | B69: Research | C69: 2 | D69: 1 | E69: 2 | F69: 0 | H69: 600 | I69: 10 | J69: =ROUNDUP(H69/30,0) -> 20 | K69: 4000 | L69: 600 | M69: 0 | N69: 0 | O69: 0 | R69: 2 | AO69: 1 | AY69: =SUMIFS($CH$3:$CH$341,$A$3:$A$341,Q$2,$C$3:$C$341,Q69) -> 0 | AZ69: =SUMIFS($CH$3:$CH$341,$A$3:$A$341,R$2,$C$3:$C$341,R69) -> 2 | BA69: =SUMIFS($CH$3:$CH$341,$A$3:$A$341,S$2,$C$3:$C$341,S69) -> 0 | BB69: =SUMIFS($CH$3:$CH$341,$A$3:$A$341,T$2,$C$3:$C$341,T69) -> 0 | BC69: =SUMIFS($CH$3:$CH$341,$A$3:$A$341,U$2,$C$3:$C$341,U69) -> 0 | BD69: =SUMIFS($CH$3:$CH$341,$A$3:$A$341,V$2,$C$3:$C$341,V69) -> 0 | BE69: =SUMIFS($CH$3:$CH$341,$A$3:$A$341,W$2,$C$3:$C$341,W69) -> 0 | BF69: =SUMIFS($CH$3:$CH$341,$A$3:$A$341,X$2,$C$3:$C$341,X69) -> 0 | ... CF69: =SUMIFS($CH$3:$CH$341,$A$3:$A$341,AX$2,$C$3:$C$341,AX69) -> 0 | CG69: =MAX(AY69:CF69) -> 2 | CH69: =MAX(F69,CG69) -> 2 | CI69: =CI68+K69 -> 6000 | CJ69: =IF(CJ$2<>$A69,SUMIFS($CY$1:$CY$464,$A$1:$A$464,CJ$2,$C$1:$C$464,BR69),0) -> 0 | CK69: =IF(CK$2<>$A69,SUMIFS($CY$1:$CY$464,$A$1:$A$464,CK$2,$C$1:$C$464,BS69),0) -> 0 | CL69: =IF(CL$2<>$A69,SUMIFS($CY$1:$CY$464,$A$1:$A$464,CL$2,$C$1:$C$464,BT69),0) -> 0 | CM69: =IF(CM$2<>$A69,SUMIFS($CY$1:$CY$464,$A$1:$A$464,CM$2,$C$1:$C$464,BU69),0) -> 0 | CN69: =IF(CN$2<>$A69,SUMIFS($CY$1:$CY$464,$A$1:$A$464,CN$2,$C$1:$C$464,BV69),0) -> 0 | CO69: =IF(CO$2<>$A69,SUMIFS($CY$1:$CY$464,$A$1:$A$464,CO$2,$C$1:$C$464,BW69),0) -> 0 | CP69: =IF(CP$2<>$A69,SUMIFS($CY$1:$CY$464,$A$1:$A$464,CP$2,$C$1:$C$464,BX69),0) -> 0 | CQ69: =IF(CQ$2<>$A69,SUMIFS($CY$1:$CY$464,$A$1:$A$464,CQ$2,$C$1:$C$464,BY69),0) -> 0 | ... CX69: =IF(CX$2<>$A69,SUMIFS($CY$1:$CY$464,$A$1:$A$464,CX$2,$C$1:$C$464,CF69),0) -> 0 | CY69: =SUM(CI69:CX69) -> 6000
A70: Far Seeing | B70: Research | C70: 3 | D70: 1 | E70: 3 | F70: 0 | H70: 1200 | I70: 20 | J70: =ROUNDUP(H70/30,0) -> 40 | K70: 8000 | L70: 1200 | M70: 0 | N70: 0 | O70: 0 | R70: 3 | AO70: 2 | AY70: =SUMIFS($CH$3:$CH$341,$A$3:$A$341,Q$2,$C$3:$C$341,Q70) -> 0 | AZ70: =SUMIFS($CH$3:$CH$341,$A$3:$A$341,R$2,$C$3:$C$341,R70) -> 2 | BA70: =SUMIFS($CH$3:$CH$341,$A$3:$A$341,S$2,$C$3:$C$341,S70) -> 0 | BB70: =SUMIFS($CH$3:$CH$341,$A$3:$A$341,T$2,$C$3:$C$341,T70) -> 0 | BC70: =SUMIFS($CH$3:$CH$341,$A$3:$A$341,U$2,$C$3:$C$341,U70) -> 0 | BD70: =SUMIFS($CH$3:$CH$341,$A$3:$A$341,V$2,$C$3:$C$341,V70) -> 0 | BE70: =SUMIFS($CH$3:$CH$341,$A$3:$A$341,W$2,$C$3:$C$341,W70) -> 0 | BF70: =SUMIFS($CH$3:$CH$341,$A$3:$A$341,X$2,$C$3:$C$341,X70) -> 0 | ... CF70: =SUMIFS($CH$3:$CH$341,$A$3:$A$341,AX$2,$C$3:$C$341,AX70) -> 0 | CG70: =MAX(AY70:CF70) -> 2 | CH70: =MAX(F70,CG70) -> 2 | CI70: =CI69+K70 -> 14000 | CJ70: =IF(CJ$2<>$A70,SUMIFS($CY$1:$CY$464,$A$1:$A$464,CJ$2,$C$1:$C$464,BR70),0) -> 0 | CK70: =IF(CK$2<>$A70,SUMIFS($CY$1:$CY$464,$A$1:$A$464,CK$2,$C$1:$C$464,BS70),0) -> 0 | CL70: =IF(CL$2<>$A70,SUMIFS($CY$1:$CY$464,$A$1:$A$464,CL$2,$C$1:$C$464,BT70),0) -> 0 | CM70: =IF(CM$2<>$A70,SUMIFS($CY$1:$CY$464,$A$1:$A$464,CM$2,$C$1:$C$464,BU70),0) -> 0 | CN70: =IF(CN$2<>$A70,SUMIFS($CY$1:$CY$464,$A$1:$A$464,CN$2,$C$1:$C$464,BV70),0) -> 0 | CO70: =IF(CO$2<>$A70,SUMIFS($CY$1:$CY$464,$A$1:$A$464,CO$2,$C$1:$C$464,BW70),0) -> 0 | CP70: =IF(CP$2<>$A70,SUMIFS($CY$1:$CY$464,$A$1:$A$464,CP$2,$C$1:$C$464,BX70),0) -> 0 | CQ70: =IF(CQ$2<>$A70,SUMIFS($CY$1:$CY$464,$A$1:$A$464,CQ$2,$C$1:$C$464,BY70),0) -> 0 | ... CX70: =IF(CX$2<>$A70,SUMIFS($CY$1:$CY$464,$A$1:$A$464,CX$2,$C$1:$C$464,CF70),0) -> 0 | CY70: =SUM(CI70:CX70) -> 14000
A71: Far Seeing | B71: Research | C71: 4 | D71: 1 | E71: 4 | F71: 0 | H71: 2400 | I71: 40 | J71: =ROUNDUP(H71/30,0) -> 80 | K71: 16000 | L71: 2400 | M71: 0 | N71: 0 | O71: 0 | R71: 4 | AO71: 3 | AY71: =SUMIFS($CH$3:$CH$341,$A$3:$A$341,Q$2,$C$3:$C$341,Q71) -> 0 | AZ71: =SUMIFS($CH$3:$CH$341,$A$3:$A$341,R$2,$C$3:$C$341,R71) -> 2 | BA71: =SUMIFS($CH$3:$CH$341,$A$3:$A$341,S$2,$C$3:$C$341,S71) -> 0 | BB71: =SUMIFS($CH$3:$CH$341,$A$3:$A$341,T$2,$C$3:$C$341,T71) -> 0 | BC71: =SUMIFS($CH$3:$CH$341,$A$3:$A$341,U$2,$C$3:$C$341,U71) -> 0 | BD71: =SUMIFS($CH$3:$CH$341,$A$3:$A$341,V$2,$C$3:$C$341,V71) -> 0 | BE71: =SUMIFS($CH$3:$CH$341,$A$3:$A$341,W$2,$C$3:$C$341,W71) -> 0 | BF71: =SUMIFS($CH$3:$CH$341,$A$3:$A$341,X$2,$C$3:$C$341,X71) -> 0 | ... CF71: =SUMIFS($CH$3:$CH$341,$A$3:$A$341,AX$2,$C$3:$C$341,AX71) -> 0 | CG71: =MAX(AY71:CF71) -> 2 | CH71: =MAX(F71,CG71) -> 2 | CI71: =CI70+K71 -> 30000 | CJ71: =IF(CJ$2<>$A71,SUMIFS($CY$1:$CY$464,$A$1:$A$464,CJ$2,$C$1:$C$464,BR71),0) -> 0 | CK71: =IF(CK$2<>$A71,SUMIFS($CY$1:$CY$464,$A$1:$A$464,CK$2,$C$1:$C$464,BS71),0) -> 0 | CL71: =IF(CL$2<>$A71,SUMIFS($CY$1:$CY$464,$A$1:$A$464,CL$2,$C$1:$C$464,BT71),0) -> 0 | CM71: =IF(CM$2<>$A71,SUMIFS($CY$1:$CY$464,$A$1:$A$464,CM$2,$C$1:$C$464,BU71),0) -> 0 | CN71: =IF(CN$2<>$A71,SUMIFS($CY$1:$CY$464,$A$1:$A$464,CN$2,$C$1:$C$464,BV71),0) -> 0 | CO71: =IF(CO$2<>$A71,SUMIFS($CY$1:$CY$464,$A$1:$A$464,CO$2,$C$1:$C$464,BW71),0) -> 0 | CP71: =IF(CP$2<>$A71,SUMIFS($CY$1:$CY$464,$A$1:$A$464,CP$2,$C$1:$C$464,BX71),0) -> 0 | CQ71: =IF(CQ$2<>$A71,SUMIFS($CY$1:$CY$464,$A$1:$A$464,CQ$2,$C$1:$C$464,BY71),0) -> 0 | ... CX71: =IF(CX$2<>$A71,SUMIFS($CY$1:$CY$464,$A$1:$A$464,CX$2,$C$1:$C$464,CF71),0) -> 0 | CY71: =SUM(CI71:CX71) -> 30000
A72: Far Seeing | B72: Research | C72: 5 | D72: 1 | E72: 5 | F72: 0 | H72: 4800 | I72: 80 | J72: =ROUNDUP(H72/30,0) -> 160 | K72: 32000 | L72: 4800 | M72: 0 | N72: 0 | O72: 0 | R72: 5 | AO72: 4 | AY72: =SUMIFS($CH$3:$CH$341,$A$3:$A$341,Q$2,$C$3:$C$341,Q72) -> 0 | AZ72: =SUMIFS($CH$3:$CH$341,$A$3:$A$341,R$2,$C$3:$C$341,R72) -> 2 | BA72: =SUMIFS($CH$3:$CH$341,$A$3:$A$341,S$2,$C$3:$C$341,S72) -> 0 | BB72: =SUMIFS($CH$3:$CH$341,$A$3:$A$341,T$2,$C$3:$C$341,T72) -> 0 | BC72: =SUMIFS($CH$3:$CH$341,$A$3:$A$341,U$2,$C$3:$C$341,U72) -> 0 | BD72: =SUMIFS($CH$3:$CH$341,$A$3:$A$341,V$2,$C$3:$C$341,V72) -> 0 | BE72: =SUMIFS($CH$3:$CH$341,$A$3:$A$341,W$2,$C$3:$C$341,W72) -> 0 | BF72: =SUMIFS($CH$3:$CH$341,$A$3:$A$341,X$2,$C$3:$C$341,X72) -> 0 | ... CF72: =SUMIFS($CH$3:$CH$341,$A$3:$A$341,AX$2,$C$3:$C$341,AX72) -> 0 | CG72: =MAX(AY72:CF72) -> 2 | CH72: =MAX(F72,CG72) -> 2 | CI72: =CI71+K72 -> 62000 | CJ72: =IF(CJ$2<>$A72,SUMIFS($CY$1:$CY$464,$A$1:$A$464,CJ$2,$C$1:$C$464,BR72),0) -> 0 | CK72: =IF(CK$2<>$A72,SUMIFS($CY$1:$CY$464,$A$1:$A$464,CK$2,$C$1:$C$464,BS72),0) -> 0 | CL72: =IF(CL$2<>$A72,SUMIFS($CY$1:$CY$464,$A$1:$A$464,CL$2,$C$1:$C$464,BT72),0) -> 0 | CM72: =IF(CM$2<>$A72,SUMIFS($CY$1:$CY$464,$A$1:$A$464,CM$2,$C$1:$C$464,BU72),0) -> 0 | CN72: =IF(CN$2<>$A72,SUMIFS($CY$1:$CY$464,$A$1:$A$464,CN$2,$C$1:$C$464,BV72),0) -> 0 | CO72: =IF(CO$2<>$A72,SUMIFS($CY$1:$CY$464,$A$1:$A$464,CO$2,$C$1:$C$464,BW72),0) -> 0 | CP72: =IF(CP$2<>$A72,SUMIFS($CY$1:$CY$464,$A$1:$A$464,CP$2,$C$1:$C$464,BX72),0) -> 0 | CQ72: =IF(CQ$2<>$A72,SUMIFS($CY$1:$CY$464,$A$1:$A$464,CQ$2,$C$1:$C$464,BY72),0) -> 0 | ... CX72: =IF(CX$2<>$A72,SUMIFS($CY$1:$CY$464,$A$1:$A$464,CX$2,$C$1:$C$464,CF72),0) -> 0 | CY72: =SUM(CI72:CX72) -> 62000
A73: Far Seeing | B73: Research | C73: 6 | D73: 1 | E73: 6 | F73: 0 | H73: 9600 | I73: 160 | J73: =ROUNDUP(H73/30,0) -> 320 | K73: 64000 | L73: 9600 | M73: 0 | N73: 0 | O73: 0 | R73: 6 | AO73: 5 | AY73: =SUMIFS($CH$3:$CH$341,$A$3:$A$341,Q$2,$C$3:$C$341,Q73) -> 0 | AZ73: =SUMIFS($CH$3:$CH$341,$A$3:$A$341,R$2,$C$3:$C$341,R73) -> 2 | BA73: =SUMIFS($CH$3:$CH$341,$A$3:$A$341,S$2,$C$3:$C$341,S73) -> 0 | BB73: =SUMIFS($CH$3:$CH$341,$A$3:$A$341,T$2,$C$3:$C$341,T73) -> 0 | BC73: =SUMIFS($CH$3:$CH$341,$A$3:$A$341,U$2,$C$3:$C$341,U73) -> 0 | BD73: =SUMIFS($CH$3:$CH$341,$A$3:$A$341,V$2,$C$3:$C$341,V73) -> 0 | BE73: =SUMIFS($CH$3:$CH$341,$A$3:$A$341,W$2,$C$3:$C$341,W73) -> 0 | BF73: =SUMIFS($CH$3:$CH$341,$A$3:$A$341,X$2,$C$3:$C$341,X73) -> 0 | ... CF73: =SUMIFS($CH$3:$CH$341,$A$3:$A$341,AX$2,$C$3:$C$341,AX73) -> 0 | CG73: =MAX(AY73:CF73) -> 2 | CH73: =MAX(F73,CG73) -> 2 | CI73: =CI72+K73 -> 126000 | CJ73: =IF(CJ$2<>$A73,SUMIFS($CY$1:$CY$464,$A$1:$A$464,CJ$2,$C$1:$C$464,BR73),0) -> 0 | CK73: =IF(CK$2<>$A73,SUMIFS($CY$1:$CY$464,$A$1:$A$464,CK$2,$C$1:$C$464,BS73),0) -> 0 | CL73: =IF(CL$2<>$A73,SUMIFS($CY$1:$CY$464,$A$1:$A$464,CL$2,$C$1:$C$464,BT73),0) -> 0 | CM73: =IF(CM$2<>$A73,SUMIFS($CY$1:$CY$464,$A$1:$A$464,CM$2,$C$1:$C$464,BU73),0) -> 0 | CN73: =IF(CN$2<>$A73,SUMIFS($CY$1:$CY$464,$A$1:$A$464,CN$2,$C$1:$C$464,BV73),0) -> 0 | CO73: =IF(CO$2<>$A73,SUMIFS($CY$1:$CY$464,$A$1:$A$464,CO$2,$C$1:$C$464,BW73),0) -> 0 | CP73: =IF(CP$2<>$A73,SUMIFS($CY$1:$CY$464,$A$1:$A$464,CP$2,$C$1:$C$464,BX73),0) -> 0 | CQ73: =IF(CQ$2<>$A73,SUMIFS($CY$1:$CY$464,$A$1:$A$464,CQ$2,$C$1:$C$464,BY73),0) -> 0 | ... CX73: =IF(CX$2<>$A73,SUMIFS($CY$1:$CY$464,$A$1:$A$464,CX$2,$C$1:$C$464,CF73),0) -> 0 | CY73: =SUM(CI73:CX73) -> 126000
A74: Far Seeing | B74: Research | C74: 7 | D74: 1 | E74: 7 | F74: 0 | H74: 19200 | I74: 320 | J74: =ROUNDUP(H74/30,0) -> 640 | K74: 128000 | L74: 19200 | M74: 0 | N74: 0 | O74: 0 | R74: 7 | AO74: 6 | AY74: =SUMIFS($CH$3:$CH$341,$A$3:$A$341,Q$2,$C$3:$C$341,Q74) -> 0 | AZ74: =SUMIFS($CH$3:$CH$341,$A$3:$A$341,R$2,$C$3:$C$341,R74) -> 2 | BA74: =SUMIFS($CH$3:$CH$341,$A$3:$A$341,S$2,$C$3:$C$341,S74) -> 0 | BB74: =SUMIFS($CH$3:$CH$341,$A$3:$A$341,T$2,$C$3:$C$341,T74) -> 0 | BC74: =SUMIFS($CH$3:$CH$341,$A$3:$A$341,U$2,$C$3:$C$341,U74) -> 0 | BD74: =SUMIFS($CH$3:$CH$341,$A$3:$A$341,V$2,$C$3:$C$341,V74) -> 0 | BE74: =SUMIFS($CH$3:$CH$341,$A$3:$A$341,W$2,$C$3:$C$341,W74) -> 0 | BF74: =SUMIFS($CH$3:$CH$341,$A$3:$A$341,X$2,$C$3:$C$341,X74) -> 0 | ... CF74: =SUMIFS($CH$3:$CH$341,$A$3:$A$341,AX$2,$C$3:$C$341,AX74) -> 0 | CG74: =MAX(AY74:CF74) -> 2 | CH74: =MAX(F74,CG74) -> 2 | CI74: =CI73+K74 -> 254000 | CJ74: =IF(CJ$2<>$A74,SUMIFS($CY$1:$CY$464,$A$1:$A$464,CJ$2,$C$1:$C$464,BR74),0) -> 0 | CK74: =IF(CK$2<>$A74,SUMIFS($CY$1:$CY$464,$A$1:$A$464,CK$2,$C$1:$C$464,BS74),0) -> 0 | CL74: =IF(CL$2<>$A74,SUMIFS($CY$1:$CY$464,$A$1:$A$464,CL$2,$C$1:$C$464,BT74),0) -> 0 | CM74: =IF(CM$2<>$A74,SUMIFS($CY$1:$CY$464,$A$1:$A$464,CM$2,$C$1:$C$464,BU74),0) -> 0 | CN74: =IF(CN$2<>$A74,SUMIFS($CY$1:$CY$464,$A$1:$A$464,CN$2,$C$1:$C$464,BV74),0) -> 0 | CO74: =IF(CO$2<>$A74,SUMIFS($CY$1:$CY$464,$A$1:$A$464,CO$2,$C$1:$C$464,BW74),0) -> 0 | CP74: =IF(CP$2<>$A74,SUMIFS($CY$1:$CY$464,$A$1:$A$464,CP$2,$C$1:$C$464,BX74),0) -> 0 | CQ74: =IF(CQ$2<>$A74,SUMIFS($CY$1:$CY$464,$A$1:$A$464,CQ$2,$C$1:$C$464,BY74),0) -> 0 | ... CX74: =IF(CX$2<>$A74,SUMIFS($CY$1:$CY$464,$A$1:$A$464,CX$2,$C$1:$C$464,CF74),0) -> 0 | CY74: =SUM(CI74:CX74) -> 254000
A75: Far Seeing | B75: Research | C75: 8 | D75: 1 | E75: 8 | F75: 0 | H75: 38400 | I75: 640 | J75: =ROUNDUP(H75/30,0) -> 1280 | K75: 256000 | L75: 38400 | M75: 0 | N75: 0 | O75: 0 | R75: 8 | AO75: 7 | AY75: =SUMIFS($CH$3:$CH$341,$A$3:$A$341,Q$2,$C$3:$C$341,Q75) -> 0 | AZ75: =SUMIFS($CH$3:$CH$341,$A$3:$A$341,R$2,$C$3:$C$341,R75) -> 2 | BA75: =SUMIFS($CH$3:$CH$341,$A$3:$A$341,S$2,$C$3:$C$341,S75) -> 0 | BB75: =SUMIFS($CH$3:$CH$341,$A$3:$A$341,T$2,$C$3:$C$341,T75) -> 0 | BC75: =SUMIFS($CH$3:$CH$341,$A$3:$A$341,U$2,$C$3:$C$341,U75) -> 0 | BD75: =SUMIFS($CH$3:$CH$341,$A$3:$A$341,V$2,$C$3:$C$341,V75) -> 0 | BE75: =SUMIFS($CH$3:$CH$341,$A$3:$A$341,W$2,$C$3:$C$341,W75) -> 0 | BF75: =SUMIFS($CH$3:$CH$341,$A$3:$A$341,X$2,$C$3:$C$341,X75) -> 0 | ... CF75: =SUMIFS($CH$3:$CH$341,$A$3:$A$341,AX$2,$C$3:$C$341,AX75) -> 0 | CG75: =MAX(AY75:CF75) -> 2 | CH75: =MAX(F75,CG75) -> 2 | CI75: =CI74+K75 -> 510000 | CJ75: =IF(CJ$2<>$A75,SUMIFS($CY$1:$CY$464,$A$1:$A$464,CJ$2,$C$1:$C$464,BR75),0) -> 0 | CK75: =IF(CK$2<>$A75,SUMIFS($CY$1:$CY$464,$A$1:$A$464,CK$2,$C$1:$C$464,BS75),0) -> 0 | CL75: =IF(CL$2<>$A75,SUMIFS($CY$1:$CY$464,$A$1:$A$464,CL$2,$C$1:$C$464,BT75),0) -> 0 | CM75: =IF(CM$2<>$A75,SUMIFS($CY$1:$CY$464,$A$1:$A$464,CM$2,$C$1:$C$464,BU75),0) -> 0 | CN75: =IF(CN$2<>$A75,SUMIFS($CY$1:$CY$464,$A$1:$A$464,CN$2,$C$1:$C$464,BV75),0) -> 0 | CO75: =IF(CO$2<>$A75,SUMIFS($CY$1:$CY$464,$A$1:$A$464,CO$2,$C$1:$C$464,BW75),0) -> 0 | CP75: =IF(CP$2<>$A75,SUMIFS($CY$1:$CY$464,$A$1:$A$464,CP$2,$C$1:$C$464,BX75),0) -> 0 | CQ75: =IF(CQ$2<>$A75,SUMIFS($CY$1:$CY$464,$A$1:$A$464,CQ$2,$C$1:$C$464,BY75),0) -> 0 | ... CX75: =IF(CX$2<>$A75,SUMIFS($CY$1:$CY$464,$A$1:$A$464,CX$2,$C$1:$C$464,CF75),0) -> 0 | CY75: =SUM(CI75:CX75) -> 510000
A76: Far Seeing | B76: Research | C76: 9 | D76: 1 | E76: 9 | F76: 0 | H76: 76800 | I76: 1280 | J76: =ROUNDUP(H76/30,0) -> 2560 | K76: 512000 | L76: 76800 | M76: 0 | N76: 0 | O76: 0 | R76: 9 | AO76: 8 | AY76: =SUMIFS($CH$3:$CH$341,$A$3:$A$341,Q$2,$C$3:$C$341,Q76) -> 0 | AZ76: =SUMIFS($CH$3:$CH$341,$A$3:$A$341,R$2,$C$3:$C$341,R76) -> 2 | BA76: =SUMIFS($CH$3:$CH$341,$A$3:$A$341,S$2,$C$3:$C$341,S76) -> 0 | BB76: =SUMIFS($CH$3:$CH$341,$A$3:$A$341,T$2,$C$3:$C$341,T76) -> 0 | BC76: =SUMIFS($CH$3:$CH$341,$A$3:$A$341,U$2,$C$3:$C$341,U76) -> 0 | BD76: =SUMIFS($CH$3:$CH$341,$A$3:$A$341,V$2,$C$3:$C$341,V76) -> 0 | BE76: =SUMIFS($CH$3:$CH$341,$A$3:$A$341,W$2,$C$3:$C$341,W76) -> 0 | BF76: =SUMIFS($CH$3:$CH$341,$A$3:$A$341,X$2,$C$3:$C$341,X76) -> 0 | ... CF76: =SUMIFS($CH$3:$CH$341,$A$3:$A$341,AX$2,$C$3:$C$341,AX76) -> 0 | CG76: =MAX(AY76:CF76) -> 2 | CH76: =MAX(F76,CG76) -> 2 | CI76: =CI75+K76 -> 1022000 | CJ76: =IF(CJ$2<>$A76,SUMIFS($CY$1:$CY$464,$A$1:$A$464,CJ$2,$C$1:$C$464,BR76),0) -> 0 | CK76: =IF(CK$2<>$A76,SUMIFS($CY$1:$CY$464,$A$1:$A$464,CK$2,$C$1:$C$464,BS76),0) -> 0 | CL76: =IF(CL$2<>$A76,SUMIFS($CY$1:$CY$464,$A$1:$A$464,CL$2,$C$1:$C$464,BT76),0) -> 0 | CM76: =IF(CM$2<>$A76,SUMIFS($CY$1:$CY$464,$A$1:$A$464,CM$2,$C$1:$C$464,BU76),0) -> 0 | CN76: =IF(CN$2<>$A76,SUMIFS($CY$1:$CY$464,$A$1:$A$464,CN$2,$C$1:$C$464,BV76),0) -> 0 | CO76: =IF(CO$2<>$A76,SUMIFS($CY$1:$CY$464,$A$1:$A$464,CO$2,$C$1:$C$464,BW76),0) -> 0 | CP76: =IF(CP$2<>$A76,SUMIFS($CY$1:$CY$464,$A$1:$A$464,CP$2,$C$1:$C$464,BX76),0) -> 0 | CQ76: =IF(CQ$2<>$A76,SUMIFS($CY$1:$CY$464,$A$1:$A$464,CQ$2,$C$1:$C$464,BY76),0) -> 0 | ... CX76: =IF(CX$2<>$A76,SUMIFS($CY$1:$CY$464,$A$1:$A$464,CX$2,$C$1:$C$464,CF76),0) -> 0 | CY76: =SUM(CI76:CX76) -> 1022000
A77: Far Seeing | B77: Research | C77: 10 | D77: 1 | E77: 10 | F77: 0 | H77: 153600 | I77: 2560 | J77: =ROUNDUP(H77/30,0) -> 5120 | K77: 1024000 | L77: 153600 | M77: 0 | N77: 0 | O77: 0 | R77: 10 | AO77: 9 | AY77: =SUMIFS($CH$3:$CH$341,$A$3:$A$341,Q$2,$C$3:$C$341,Q77) -> 0 | AZ77: =SUMIFS($CH$3:$CH$341,$A$3:$A$341,R$2,$C$3:$C$341,R77) -> 2 | BA77: =SUMIFS($CH$3:$CH$341,$A$3:$A$341,S$2,$C$3:$C$341,S77) -> 0 | BB77: =SUMIFS($CH$3:$CH$341,$A$3:$A$341,T$2,$C$3:$C$341,T77) -> 0 | BC77: =SUMIFS($CH$3:$CH$341,$A$3:$A$341,U$2,$C$3:$C$341,U77) -> 0 | BD77: =SUMIFS($CH$3:$CH$341,$A$3:$A$341,V$2,$C$3:$C$341,V77) -> 0 | BE77: =SUMIFS($CH$3:$CH$341,$A$3:$A$341,W$2,$C$3:$C$341,W77) -> 0 | BF77: =SUMIFS($CH$3:$CH$341,$A$3:$A$341,X$2,$C$3:$C$341,X77) -> 0 | ... CF77: =SUMIFS($CH$3:$CH$341,$A$3:$A$341,AX$2,$C$3:$C$341,AX77) -> 0 | CG77: =MAX(AY77:CF77) -> 2 | CH77: =MAX(F77,CG77) -> 2 | CI77: =CI76+K77 -> 2046000 | CJ77: =IF(CJ$2<>$A77,SUMIFS($CY$1:$CY$464,$A$1:$A$464,CJ$2,$C$1:$C$464,BR77),0) -> 0 | CK77: =IF(CK$2<>$A77,SUMIFS($CY$1:$CY$464,$A$1:$A$464,CK$2,$C$1:$C$464,BS77),0) -> 0 | CL77: =IF(CL$2<>$A77,SUMIFS($CY$1:$CY$464,$A$1:$A$464,CL$2,$C$1:$C$464,BT77),0) -> 0 | CM77: =IF(CM$2<>$A77,SUMIFS($CY$1:$CY$464,$A$1:$A$464,CM$2,$C$1:$C$464,BU77),0) -> 0 | CN77: =IF(CN$2<>$A77,SUMIFS($CY$1:$CY$464,$A$1:$A$464,CN$2,$C$1:$C$464,BV77),0) -> 0 | CO77: =IF(CO$2<>$A77,SUMIFS($CY$1:$CY$464,$A$1:$A$464,CO$2,$C$1:$C$464,BW77),0) -> 0 | CP77: =IF(CP$2<>$A77,SUMIFS($CY$1:$CY$464,$A$1:$A$464,CP$2,$C$1:$C$464,BX77),0) -> 0 | CQ77: =IF(CQ$2<>$A77,SUMIFS($CY$1:$CY$464,$A$1:$A$464,CQ$2,$C$1:$C$464,BY77),0) -> 0 | ... CX77: =IF(CX$2<>$A77,SUMIFS($CY$1:$CY$464,$A$1:$A$464,CX$2,$C$1:$C$464,CF77),0) -> 0 | CY77: =SUM(CI77:CX77) -> 2046000
A78: Saddlebags | B78: Research | C78: 1 | D78: 1 | E78: 1 | F78: 0 | H78: 1600 | I78: 26.666667 | J78: =ROUNDUP(H78/30,0) -> 54 | K78: 3000 | L78: 500 | M78: 0 | N78: 200 | O78: 0 | R78: 1 | AY78: =SUMIFS($CH$3:$CH$341,$A$3:$A$341,Q$2,$C$3:$C$341,Q78) -> 0 | AZ78: =SUMIFS($CH$3:$CH$341,$A$3:$A$341,R$2,$C$3:$C$341,R78) -> 2 | BA78: =SUMIFS($CH$3:$CH$341,$A$3:$A$341,S$2,$C$3:$C$341,S78) -> 0 | BB78: =SUMIFS($CH$3:$CH$341,$A$3:$A$341,T$2,$C$3:$C$341,T78) -> 0 | BC78: =SUMIFS($CH$3:$CH$341,$A$3:$A$341,U$2,$C$3:$C$341,U78) -> 0 | BD78: =SUMIFS($CH$3:$CH$341,$A$3:$A$341,V$2,$C$3:$C$341,V78) -> 0 | BE78: =SUMIFS($CH$3:$CH$341,$A$3:$A$341,W$2,$C$3:$C$341,W78) -> 0 | BF78: =SUMIFS($CH$3:$CH$341,$A$3:$A$341,X$2,$C$3:$C$341,X78) -> 0 | ... CF78: =SUMIFS($CH$3:$CH$341,$A$3:$A$341,AX$2,$C$3:$C$341,AX78) -> 0 | CG78: =MAX(AY78:CF78) -> 2 | CH78: =MAX(F78,CG78) -> 2 | CI78: =K78 -> 3000 | CJ78: =IF(CJ$2<>$A78,SUMIFS($CY$1:$CY$464,$A$1:$A$464,CJ$2,$C$1:$C$464,BR78),0) -> 0 | CK78: =IF(CK$2<>$A78,SUMIFS($CY$1:$CY$464,$A$1:$A$464,CK$2,$C$1:$C$464,BS78),0) -> 0 | CL78: =IF(CL$2<>$A78,SUMIFS($CY$1:$CY$464,$A$1:$A$464,CL$2,$C$1:$C$464,BT78),0) -> 0 | CM78: =IF(CM$2<>$A78,SUMIFS($CY$1:$CY$464,$A$1:$A$464,CM$2,$C$1:$C$464,BU78),0) -> 0 | CN78: =IF(CN$2<>$A78,SUMIFS($CY$1:$CY$464,$A$1:$A$464,CN$2,$C$1:$C$464,BV78),0) -> 0 | CO78: =IF(CO$2<>$A78,SUMIFS($CY$1:$CY$464,$A$1:$A$464,CO$2,$C$1:$C$464,BW78),0) -> 0 | CP78: =IF(CP$2<>$A78,SUMIFS($CY$1:$CY$464,$A$1:$A$464,CP$2,$C$1:$C$464,BX78),0) -> 0 | CQ78: =IF(CQ$2<>$A78,SUMIFS($CY$1:$CY$464,$A$1:$A$464,CQ$2,$C$1:$C$464,BY78),0) -> 0 | ... CX78: =IF(CX$2<>$A78,SUMIFS($CY$1:$CY$464,$A$1:$A$464,CX$2,$C$1:$C$464,CF78),0) -> 0 | CY78: =SUM(CI78:CX78) -> 3000
A79: Saddlebags | B79: Research | C79: 2 | D79: 1 | E79: 2 | F79: 0 | H79: 3200 | I79: 53.333333 | J79: =ROUNDUP(H79/30,0) -> 107 | K79: 6000 | L79: 1000 | M79: 0 | N79: 400 | O79: 0 | R79: 2 | AR79: 1 | AY79: =SUMIFS($CH$3:$CH$341,$A$3:$A$341,Q$2,$C$3:$C$341,Q79) -> 0 | AZ79: =SUMIFS($CH$3:$CH$341,$A$3:$A$341,R$2,$C$3:$C$341,R79) -> 2 | BA79: =SUMIFS($CH$3:$CH$341,$A$3:$A$341,S$2,$C$3:$C$341,S79) -> 0 | BB79: =SUMIFS($CH$3:$CH$341,$A$3:$A$341,T$2,$C$3:$C$341,T79) -> 0 | BC79: =SUMIFS($CH$3:$CH$341,$A$3:$A$341,U$2,$C$3:$C$341,U79) -> 0 | BD79: =SUMIFS($CH$3:$CH$341,$A$3:$A$341,V$2,$C$3:$C$341,V79) -> 0 | BE79: =SUMIFS($CH$3:$CH$341,$A$3:$A$341,W$2,$C$3:$C$341,W79) -> 0 | BF79: =SUMIFS($CH$3:$CH$341,$A$3:$A$341,X$2,$C$3:$C$341,X79) -> 0 | ... CF79: =SUMIFS($CH$3:$CH$341,$A$3:$A$341,AX$2,$C$3:$C$341,AX79) -> 0 | CG79: =MAX(AY79:CF79) -> 2 | CH79: =MAX(F79,CG79) -> 2 | CI79: =CI78+K79 -> 9000 | CJ79: =IF(CJ$2<>$A79,SUMIFS($CY$1:$CY$464,$A$1:$A$464,CJ$2,$C$1:$C$464,BR79),0) -> 0 | CK79: =IF(CK$2<>$A79,SUMIFS($CY$1:$CY$464,$A$1:$A$464,CK$2,$C$1:$C$464,BS79),0) -> 0 | CL79: =IF(CL$2<>$A79,SUMIFS($CY$1:$CY$464,$A$1:$A$464,CL$2,$C$1:$C$464,BT79),0) -> 0 | CM79: =IF(CM$2<>$A79,SUMIFS($CY$1:$CY$464,$A$1:$A$464,CM$2,$C$1:$C$464,BU79),0) -> 0 | CN79: =IF(CN$2<>$A79,SUMIFS($CY$1:$CY$464,$A$1:$A$464,CN$2,$C$1:$C$464,BV79),0) -> 0 | CO79: =IF(CO$2<>$A79,SUMIFS($CY$1:$CY$464,$A$1:$A$464,CO$2,$C$1:$C$464,BW79),0) -> 0 | CP79: =IF(CP$2<>$A79,SUMIFS($CY$1:$CY$464,$A$1:$A$464,CP$2,$C$1:$C$464,BX79),0) -> 0 | CQ79: =IF(CQ$2<>$A79,SUMIFS($CY$1:$CY$464,$A$1:$A$464,CQ$2,$C$1:$C$464,BY79),0) -> 0 | ... CX79: =IF(CX$2<>$A79,SUMIFS($CY$1:$CY$464,$A$1:$A$464,CX$2,$C$1:$C$464,CF79),0) -> 0 | CY79: =SUM(CI79:CX79) -> 9000
A80: Saddlebags | B80: Research | C80: 3 | D80: 1 | E80: 3 | F80: 0 | H80: 6400 | I80: 106.66667 | J80: =ROUNDUP(H80/30,0) -> 214 | K80: 12000 | L80: 2000 | M80: 0 | N80: 800 | O80: 0 | R80: 3 | AR80: 2 | AY80: =SUMIFS($CH$3:$CH$341,$A$3:$A$341,Q$2,$C$3:$C$341,Q80) -> 0 | AZ80: =SUMIFS($CH$3:$CH$341,$A$3:$A$341,R$2,$C$3:$C$341,R80) -> 2 | BA80: =SUMIFS($CH$3:$CH$341,$A$3:$A$341,S$2,$C$3:$C$341,S80) -> 0 | BB80: =SUMIFS($CH$3:$CH$341,$A$3:$A$341,T$2,$C$3:$C$341,T80) -> 0 | BC80: =SUMIFS($CH$3:$CH$341,$A$3:$A$341,U$2,$C$3:$C$341,U80) -> 0 | BD80: =SUMIFS($CH$3:$CH$341,$A$3:$A$341,V$2,$C$3:$C$341,V80) -> 0 | BE80: =SUMIFS($CH$3:$CH$341,$A$3:$A$341,W$2,$C$3:$C$341,W80) -> 0 | BF80: =SUMIFS($CH$3:$CH$341,$A$3:$A$341,X$2,$C$3:$C$341,X80) -> 0 | ... CF80: =SUMIFS($CH$3:$CH$341,$A$3:$A$341,AX$2,$C$3:$C$341,AX80) -> 0 | CG80: =MAX(AY80:CF80) -> 2 | CH80: =MAX(F80,CG80) -> 2 | CI80: =CI79+K80 -> 21000 | CJ80: =IF(CJ$2<>$A80,SUMIFS($CY$1:$CY$464,$A$1:$A$464,CJ$2,$C$1:$C$464,BR80),0) -> 0 | CK80: =IF(CK$2<>$A80,SUMIFS($CY$1:$CY$464,$A$1:$A$464,CK$2,$C$1:$C$464,BS80),0) -> 0 | CL80: =IF(CL$2<>$A80,SUMIFS($CY$1:$CY$464,$A$1:$A$464,CL$2,$C$1:$C$464,BT80),0) -> 0 | CM80: =IF(CM$2<>$A80,SUMIFS($CY$1:$CY$464,$A$1:$A$464,CM$2,$C$1:$C$464,BU80),0) -> 0 | CN80: =IF(CN$2<>$A80,SUMIFS($CY$1:$CY$464,$A$1:$A$464,CN$2,$C$1:$C$464,BV80),0) -> 0 | CO80: =IF(CO$2<>$A80,SUMIFS($CY$1:$CY$464,$A$1:$A$464,CO$2,$C$1:$C$464,BW80),0) -> 0 | CP80: =IF(CP$2<>$A80,SUMIFS($CY$1:$CY$464,$A$1:$A$464,CP$2,$C$1:$C$464,BX80),0) -> 0 | CQ80: =IF(CQ$2<>$A80,SUMIFS($CY$1:$CY$464,$A$1:$A$464,CQ$2,$C$1:$C$464,BY80),0) -> 0 | ... CX80: =IF(CX$2<>$A80,SUMIFS($CY$1:$CY$464,$A$1:$A$464,CX$2,$C$1:$C$464,CF80),0) -> 0 | CY80: =SUM(CI80:CX80) -> 21000
A81: Saddlebags | B81: Research | C81: 4 | D81: 1 | E81: 4 | F81: 0 | H81: 12800 | I81: 213.33333 | J81: =ROUNDUP(H81/30,0) -> 427 | K81: 24000 | L81: 4000 | M81: 0 | N81: 1600 | O81: 0 | R81: 4 | AR81: 3 | AY81: =SUMIFS($CH$3:$CH$341,$A$3:$A$341,Q$2,$C$3:$C$341,Q81) -> 0 | AZ81: =SUMIFS($CH$3:$CH$341,$A$3:$A$341,R$2,$C$3:$C$341,R81) -> 2 | BA81: =SUMIFS($CH$3:$CH$341,$A$3:$A$341,S$2,$C$3:$C$341,S81) -> 0 | BB81: =SUMIFS($CH$3:$CH$341,$A$3:$A$341,T$2,$C$3:$C$341,T81) -> 0 | BC81: =SUMIFS($CH$3:$CH$341,$A$3:$A$341,U$2,$C$3:$C$341,U81) -> 0 | BD81: =SUMIFS($CH$3:$CH$341,$A$3:$A$341,V$2,$C$3:$C$341,V81) -> 0 | BE81: =SUMIFS($CH$3:$CH$341,$A$3:$A$341,W$2,$C$3:$C$341,W81) -> 0 | BF81: =SUMIFS($CH$3:$CH$341,$A$3:$A$341,X$2,$C$3:$C$341,X81) -> 0 | ... CF81: =SUMIFS($CH$3:$CH$341,$A$3:$A$341,AX$2,$C$3:$C$341,AX81) -> 0 | CG81: =MAX(AY81:CF81) -> 2 | CH81: =MAX(F81,CG81) -> 2 | CI81: =CI80+K81 -> 45000 | CJ81: =IF(CJ$2<>$A81,SUMIFS($CY$1:$CY$464,$A$1:$A$464,CJ$2,$C$1:$C$464,BR81),0) -> 0 | CK81: =IF(CK$2<>$A81,SUMIFS($CY$1:$CY$464,$A$1:$A$464,CK$2,$C$1:$C$464,BS81),0) -> 0 | CL81: =IF(CL$2<>$A81,SUMIFS($CY$1:$CY$464,$A$1:$A$464,CL$2,$C$1:$C$464,BT81),0) -> 0 | CM81: =IF(CM$2<>$A81,SUMIFS($CY$1:$CY$464,$A$1:$A$464,CM$2,$C$1:$C$464,BU81),0) -> 0 | CN81: =IF(CN$2<>$A81,SUMIFS($CY$1:$CY$464,$A$1:$A$464,CN$2,$C$1:$C$464,BV81),0) -> 0 | CO81: =IF(CO$2<>$A81,SUMIFS($CY$1:$CY$464,$A$1:$A$464,CO$2,$C$1:$C$464,BW81),0) -> 0 | CP81: =IF(CP$2<>$A81,SUMIFS($CY$1:$CY$464,$A$1:$A$464,CP$2,$C$1:$C$464,BX81),0) -> 0 | CQ81: =IF(CQ$2<>$A81,SUMIFS($CY$1:$CY$464,$A$1:$A$464,CQ$2,$C$1:$C$464,BY81),0) -> 0 | ... CX81: =IF(CX$2<>$A81,SUMIFS($CY$1:$CY$464,$A$1:$A$464,CX$2,$C$1:$C$464,CF81),0) -> 0 | CY81: =SUM(CI81:CX81) -> 45000
A82: Saddlebags | B82: Research | C82: 5 | D82: 1 | E82: 5 | F82: 0 | H82: 25600 | I82: 426.66667 | J82: =ROUNDUP(H82/30,0) -> 854 | K82: 48000 | L82: 8000 | M82: 0 | N82: 3200 | O82: 0 | R82: 5 | AR82: 4 | AY82: =SUMIFS($CH$3:$CH$341,$A$3:$A$341,Q$2,$C$3:$C$341,Q82) -> 0 | AZ82: =SUMIFS($CH$3:$CH$341,$A$3:$A$341,R$2,$C$3:$C$341,R82) -> 2 | BA82: =SUMIFS($CH$3:$CH$341,$A$3:$A$341,S$2,$C$3:$C$341,S82) -> 0 | BB82: =SUMIFS($CH$3:$CH$341,$A$3:$A$341,T$2,$C$3:$C$341,T82) -> 0 | BC82: =SUMIFS($CH$3:$CH$341,$A$3:$A$341,U$2,$C$3:$C$341,U82) -> 0 | BD82: =SUMIFS($CH$3:$CH$341,$A$3:$A$341,V$2,$C$3:$C$341,V82) -> 0 | BE82: =SUMIFS($CH$3:$CH$341,$A$3:$A$341,W$2,$C$3:$C$341,W82) -> 0 | BF82: =SUMIFS($CH$3:$CH$341,$A$3:$A$341,X$2,$C$3:$C$341,X82) -> 0 | ... CF82: =SUMIFS($CH$3:$CH$341,$A$3:$A$341,AX$2,$C$3:$C$341,AX82) -> 0 | CG82: =MAX(AY82:CF82) -> 2 | CH82: =MAX(F82,CG82) -> 2 | CI82: =CI81+K82 -> 93000 | CJ82: =IF(CJ$2<>$A82,SUMIFS($CY$1:$CY$464,$A$1:$A$464,CJ$2,$C$1:$C$464,BR82),0) -> 0 | CK82: =IF(CK$2<>$A82,SUMIFS($CY$1:$CY$464,$A$1:$A$464,CK$2,$C$1:$C$464,BS82),0) -> 0 | CL82: =IF(CL$2<>$A82,SUMIFS($CY$1:$CY$464,$A$1:$A$464,CL$2,$C$1:$C$464,BT82),0) -> 0 | CM82: =IF(CM$2<>$A82,SUMIFS($CY$1:$CY$464,$A$1:$A$464,CM$2,$C$1:$C$464,BU82),0) -> 0 | CN82: =IF(CN$2<>$A82,SUMIFS($CY$1:$CY$464,$A$1:$A$464,CN$2,$C$1:$C$464,BV82),0) -> 0 | CO82: =IF(CO$2<>$A82,SUMIFS($CY$1:$CY$464,$A$1:$A$464,CO$2,$C$1:$C$464,BW82),0) -> 0 | CP82: =IF(CP$2<>$A82,SUMIFS($CY$1:$CY$464,$A$1:$A$464,CP$2,$C$1:$C$464,BX82),0) -> 0 | CQ82: =IF(CQ$2<>$A82,SUMIFS($CY$1:$CY$464,$A$1:$A$464,CQ$2,$C$1:$C$464,BY82),0) -> 0 | ... CX82: =IF(CX$2<>$A82,SUMIFS($CY$1:$CY$464,$A$1:$A$464,CX$2,$C$1:$C$464,CF82),0) -> 0 | CY82: =SUM(CI82:CX82) -> 93000
A83: Saddlebags | B83: Research | C83: 6 | D83: 1 | E83: 6 | F83: 0 | H83: 51200 | I83: 853.33333 | J83: =ROUNDUP(H83/30,0) -> 1707 | K83: 96000 | L83: 16000 | M83: 0 | N83: 6400 | O83: 0 | R83: 6 | AR83: 5 | AY83: =SUMIFS($CH$3:$CH$341,$A$3:$A$341,Q$2,$C$3:$C$341,Q83) -> 0 | AZ83: =SUMIFS($CH$3:$CH$341,$A$3:$A$341,R$2,$C$3:$C$341,R83) -> 2 | BA83: =SUMIFS($CH$3:$CH$341,$A$3:$A$341,S$2,$C$3:$C$341,S83) -> 0 | BB83: =SUMIFS($CH$3:$CH$341,$A$3:$A$341,T$2,$C$3:$C$341,T83) -> 0 | BC83: =SUMIFS($CH$3:$CH$341,$A$3:$A$341,U$2,$C$3:$C$341,U83) -> 0 | BD83: =SUMIFS($CH$3:$CH$341,$A$3:$A$341,V$2,$C$3:$C$341,V83) -> 0 | BE83: =SUMIFS($CH$3:$CH$341,$A$3:$A$341,W$2,$C$3:$C$341,W83) -> 0 | BF83: =SUMIFS($CH$3:$CH$341,$A$3:$A$341,X$2,$C$3:$C$341,X83) -> 0 | ... CF83: =SUMIFS($CH$3:$CH$341,$A$3:$A$341,AX$2,$C$3:$C$341,AX83) -> 0 | CG83: =MAX(AY83:CF83) -> 2 | CH83: =MAX(F83,CG83) -> 2 | CI83: =CI82+K83 -> 189000 | CJ83: =IF(CJ$2<>$A83,SUMIFS($CY$1:$CY$464,$A$1:$A$464,CJ$2,$C$1:$C$464,BR83),0) -> 0 | CK83: =IF(CK$2<>$A83,SUMIFS($CY$1:$CY$464,$A$1:$A$464,CK$2,$C$1:$C$464,BS83),0) -> 0 | CL83: =IF(CL$2<>$A83,SUMIFS($CY$1:$CY$464,$A$1:$A$464,CL$2,$C$1:$C$464,BT83),0) -> 0 | CM83: =IF(CM$2<>$A83,SUMIFS($CY$1:$CY$464,$A$1:$A$464,CM$2,$C$1:$C$464,BU83),0) -> 0 | CN83: =IF(CN$2<>$A83,SUMIFS($CY$1:$CY$464,$A$1:$A$464,CN$2,$C$1:$C$464,BV83),0) -> 0 | CO83: =IF(CO$2<>$A83,SUMIFS($CY$1:$CY$464,$A$1:$A$464,CO$2,$C$1:$C$464,BW83),0) -> 0 | CP83: =IF(CP$2<>$A83,SUMIFS($CY$1:$CY$464,$A$1:$A$464,CP$2,$C$1:$C$464,BX83),0) -> 0 | CQ83: =IF(CQ$2<>$A83,SUMIFS($CY$1:$CY$464,$A$1:$A$464,CQ$2,$C$1:$C$464,BY83),0) -> 0 | ... CX83: =IF(CX$2<>$A83,SUMIFS($CY$1:$CY$464,$A$1:$A$464,CX$2,$C$1:$C$464,CF83),0) -> 0 | CY83: =SUM(CI83:CX83) -> 189000
A84: Saddlebags | B84: Research | C84: 7 | D84: 1 | E84: 7 | F84: 0 | H84: 102400 | I84: 1706.6667 | J84: =ROUNDUP(H84/30,0) -> 3414 | K84: 192000 | L84: 32000 | M84: 0 | N84: 12800 | O84: 0 | R84: 7 | AR84: 6 | AY84: =SUMIFS($CH$3:$CH$341,$A$3:$A$341,Q$2,$C$3:$C$341,Q84) -> 0 | AZ84: =SUMIFS($CH$3:$CH$341,$A$3:$A$341,R$2,$C$3:$C$341,R84) -> 2 | BA84: =SUMIFS($CH$3:$CH$341,$A$3:$A$341,S$2,$C$3:$C$341,S84) -> 0 | BB84: =SUMIFS($CH$3:$CH$341,$A$3:$A$341,T$2,$C$3:$C$341,T84) -> 0 | BC84: =SUMIFS($CH$3:$CH$341,$A$3:$A$341,U$2,$C$3:$C$341,U84) -> 0 | BD84: =SUMIFS($CH$3:$CH$341,$A$3:$A$341,V$2,$C$3:$C$341,V84) -> 0 | BE84: =SUMIFS($CH$3:$CH$341,$A$3:$A$341,W$2,$C$3:$C$341,W84) -> 0 | BF84: =SUMIFS($CH$3:$CH$341,$A$3:$A$341,X$2,$C$3:$C$341,X84) -> 0 | ... CF84: =SUMIFS($CH$3:$CH$341,$A$3:$A$341,AX$2,$C$3:$C$341,AX84) -> 0 | CG84: =MAX(AY84:CF84) -> 2 | CH84: =MAX(F84,CG84) -> 2 | CI84: =CI83+K84 -> 381000 | CJ84: =IF(CJ$2<>$A84,SUMIFS($CY$1:$CY$464,$A$1:$A$464,CJ$2,$C$1:$C$464,BR84),0) -> 0 | CK84: =IF(CK$2<>$A84,SUMIFS($CY$1:$CY$464,$A$1:$A$464,CK$2,$C$1:$C$464,BS84),0) -> 0 | CL84: =IF(CL$2<>$A84,SUMIFS($CY$1:$CY$464,$A$1:$A$464,CL$2,$C$1:$C$464,BT84),0) -> 0 | CM84: =IF(CM$2<>$A84,SUMIFS($CY$1:$CY$464,$A$1:$A$464,CM$2,$C$1:$C$464,BU84),0) -> 0 | CN84: =IF(CN$2<>$A84,SUMIFS($CY$1:$CY$464,$A$1:$A$464,CN$2,$C$1:$C$464,BV84),0) -> 0 | CO84: =IF(CO$2<>$A84,SUMIFS($CY$1:$CY$464,$A$1:$A$464,CO$2,$C$1:$C$464,BW84),0) -> 0 | CP84: =IF(CP$2<>$A84,SUMIFS($CY$1:$CY$464,$A$1:$A$464,CP$2,$C$1:$C$464,BX84),0) -> 0 | CQ84: =IF(CQ$2<>$A84,SUMIFS($CY$1:$CY$464,$A$1:$A$464,CQ$2,$C$1:$C$464,BY84),0) -> 0 | ... CX84: =IF(CX$2<>$A84,SUMIFS($CY$1:$CY$464,$A$1:$A$464,CX$2,$C$1:$C$464,CF84),0) -> 0 | CY84: =SUM(CI84:CX84) -> 381000
A85: Saddlebags | B85: Research | C85: 8 | D85: 1 | E85: 8 | F85: 0 | H85: 204800 | I85: 3413.3333 | J85: =ROUNDUP(H85/30,0) -> 6827 | K85: 384000 | L85: 64000 | M85: 0 | N85: 25600 | O85: 0 | R85: 8 | AR85: 7 | AY85: =SUMIFS($CH$3:$CH$341,$A$3:$A$341,Q$2,$C$3:$C$341,Q85) -> 0 | AZ85: =SUMIFS($CH$3:$CH$341,$A$3:$A$341,R$2,$C$3:$C$341,R85) -> 2 | BA85: =SUMIFS($CH$3:$CH$341,$A$3:$A$341,S$2,$C$3:$C$341,S85) -> 0 | BB85: =SUMIFS($CH$3:$CH$341,$A$3:$A$341,T$2,$C$3:$C$341,T85) -> 0 | BC85: =SUMIFS($CH$3:$CH$341,$A$3:$A$341,U$2,$C$3:$C$341,U85) -> 0 | BD85: =SUMIFS($CH$3:$CH$341,$A$3:$A$341,V$2,$C$3:$C$341,V85) -> 0 | BE85: =SUMIFS($CH$3:$CH$341,$A$3:$A$341,W$2,$C$3:$C$341,W85) -> 0 | BF85: =SUMIFS($CH$3:$CH$341,$A$3:$A$341,X$2,$C$3:$C$341,X85) -> 0 | ... CF85: =SUMIFS($CH$3:$CH$341,$A$3:$A$341,AX$2,$C$3:$C$341,AX85) -> 0 | CG85: =MAX(AY85:CF85) -> 2 | CH85: =MAX(F85,CG85) -> 2 | CI85: =CI84+K85 -> 765000 | CJ85: =IF(CJ$2<>$A85,SUMIFS($CY$1:$CY$464,$A$1:$A$464,CJ$2,$C$1:$C$464,BR85),0) -> 0 | CK85: =IF(CK$2<>$A85,SUMIFS($CY$1:$CY$464,$A$1:$A$464,CK$2,$C$1:$C$464,BS85),0) -> 0 | CL85: =IF(CL$2<>$A85,SUMIFS($CY$1:$CY$464,$A$1:$A$464,CL$2,$C$1:$C$464,BT85),0) -> 0 | CM85: =IF(CM$2<>$A85,SUMIFS($CY$1:$CY$464,$A$1:$A$464,CM$2,$C$1:$C$464,BU85),0) -> 0 | CN85: =IF(CN$2<>$A85,SUMIFS($CY$1:$CY$464,$A$1:$A$464,CN$2,$C$1:$C$464,BV85),0) -> 0 | CO85: =IF(CO$2<>$A85,SUMIFS($CY$1:$CY$464,$A$1:$A$464,CO$2,$C$1:$C$464,BW85),0) -> 0 | CP85: =IF(CP$2<>$A85,SUMIFS($CY$1:$CY$464,$A$1:$A$464,CP$2,$C$1:$C$464,BX85),0) -> 0 | CQ85: =IF(CQ$2<>$A85,SUMIFS($CY$1:$CY$464,$A$1:$A$464,CQ$2,$C$1:$C$464,BY85),0) -> 0 | ... CX85: =IF(CX$2<>$A85,SUMIFS($CY$1:$CY$464,$A$1:$A$464,CX$2,$C$1:$C$464,CF85),0) -> 0 | CY85: =SUM(CI85:CX85) -> 765000
A86: Saddlebags | B86: Research | C86: 9 | D86: 1 | E86: 9 | F86: 0 | H86: 409600 | I86: 6826.6667 | J86: =ROUNDUP(H86/30,0) -> 13654 | K86: 768000 | L86: 128000 | M86: 0 | N86: 51200 | O86: 0 | R86: 9 | AR86: 8 | AY86: =SUMIFS($CH$3:$CH$341,$A$3:$A$341,Q$2,$C$3:$C$341,Q86) -> 0 | AZ86: =SUMIFS($CH$3:$CH$341,$A$3:$A$341,R$2,$C$3:$C$341,R86) -> 2 | BA86: =SUMIFS($CH$3:$CH$341,$A$3:$A$341,S$2,$C$3:$C$341,S86) -> 0 | BB86: =SUMIFS($CH$3:$CH$341,$A$3:$A$341,T$2,$C$3:$C$341,T86) -> 0 | BC86: =SUMIFS($CH$3:$CH$341,$A$3:$A$341,U$2,$C$3:$C$341,U86) -> 0 | BD86: =SUMIFS($CH$3:$CH$341,$A$3:$A$341,V$2,$C$3:$C$341,V86) -> 0 | BE86: =SUMIFS($CH$3:$CH$341,$A$3:$A$341,W$2,$C$3:$C$341,W86) -> 0 | BF86: =SUMIFS($CH$3:$CH$341,$A$3:$A$341,X$2,$C$3:$C$341,X86) -> 0 | ... CF86: =SUMIFS($CH$3:$CH$341,$A$3:$A$341,AX$2,$C$3:$C$341,AX86) -> 0 | CG86: =MAX(AY86:CF86) -> 2 | CH86: =MAX(F86,CG86) -> 2 | CI86: =CI85+K86 -> 1533000 | CJ86: =IF(CJ$2<>$A86,SUMIFS($CY$1:$CY$464,$A$1:$A$464,CJ$2,$C$1:$C$464,BR86),0) -> 0 | CK86: =IF(CK$2<>$A86,SUMIFS($CY$1:$CY$464,$A$1:$A$464,CK$2,$C$1:$C$464,BS86),0) -> 0 | CL86: =IF(CL$2<>$A86,SUMIFS($CY$1:$CY$464,$A$1:$A$464,CL$2,$C$1:$C$464,BT86),0) -> 0 | CM86: =IF(CM$2<>$A86,SUMIFS($CY$1:$CY$464,$A$1:$A$464,CM$2,$C$1:$C$464,BU86),0) -> 0 | CN86: =IF(CN$2<>$A86,SUMIFS($CY$1:$CY$464,$A$1:$A$464,CN$2,$C$1:$C$464,BV86),0) -> 0 | CO86: =IF(CO$2<>$A86,SUMIFS($CY$1:$CY$464,$A$1:$A$464,CO$2,$C$1:$C$464,BW86),0) -> 0 | CP86: =IF(CP$2<>$A86,SUMIFS($CY$1:$CY$464,$A$1:$A$464,CP$2,$C$1:$C$464,BX86),0) -> 0 | CQ86: =IF(CQ$2<>$A86,SUMIFS($CY$1:$CY$464,$A$1:$A$464,CQ$2,$C$1:$C$464,BY86),0) -> 0 | ... CX86: =IF(CX$2<>$A86,SUMIFS($CY$1:$CY$464,$A$1:$A$464,CX$2,$C$1:$C$464,CF86),0) -> 0 | CY86: =SUM(CI86:CX86) -> 1533000
A87: Saddlebags | B87: Research | C87: 10 | D87: 1 | E87: 10 | F87: 0 | H87: 819200 | I87: 13653.333 | J87: =ROUNDUP(H87/30,0) -> 27307 | K87: 1536000 | L87: 256000 | M87: 0 | N87: 102400 | O87: 0 | R87: 10 | AR87: 9 | AY87: =SUMIFS($CH$3:$CH$341,$A$3:$A$341,Q$2,$C$3:$C$341,Q87) -> 0 | AZ87: =SUMIFS($CH$3:$CH$341,$A$3:$A$341,R$2,$C$3:$C$341,R87) -> 2 | BA87: =SUMIFS($CH$3:$CH$341,$A$3:$A$341,S$2,$C$3:$C$341,S87) -> 0 | BB87: =SUMIFS($CH$3:$CH$341,$A$3:$A$341,T$2,$C$3:$C$341,T87) -> 0 | BC87: =SUMIFS($CH$3:$CH$341,$A$3:$A$341,U$2,$C$3:$C$341,U87) -> 0 | BD87: =SUMIFS($CH$3:$CH$341,$A$3:$A$341,V$2,$C$3:$C$341,V87) -> 0 | BE87: =SUMIFS($CH$3:$CH$341,$A$3:$A$341,W$2,$C$3:$C$341,W87) -> 0 | BF87: =SUMIFS($CH$3:$CH$341,$A$3:$A$341,X$2,$C$3:$C$341,X87) -> 0 | ... CF87: =SUMIFS($CH$3:$CH$341,$A$3:$A$341,AX$2,$C$3:$C$341,AX87) -> 0 | CG87: =MAX(AY87:CF87) -> 2 | CH87: =MAX(F87,CG87) -> 2 | CI87: =CI86+K87 -> 3069000 | CJ87: =IF(CJ$2<>$A87,SUMIFS($CY$1:$CY$464,$A$1:$A$464,CJ$2,$C$1:$C$464,BR87),0) -> 0 | CK87: =IF(CK$2<>$A87,SUMIFS($CY$1:$CY$464,$A$1:$A$464,CK$2,$C$1:$C$464,BS87),0) -> 0 | CL87: =IF(CL$2<>$A87,SUMIFS($CY$1:$CY$464,$A$1:$A$464,CL$2,$C$1:$C$464,BT87),0) -> 0 | CM87: =IF(CM$2<>$A87,SUMIFS($CY$1:$CY$464,$A$1:$A$464,CM$2,$C$1:$C$464,BU87),0) -> 0 | CN87: =IF(CN$2<>$A87,SUMIFS($CY$1:$CY$464,$A$1:$A$464,CN$2,$C$1:$C$464,BV87),0) -> 0 | CO87: =IF(CO$2<>$A87,SUMIFS($CY$1:$CY$464,$A$1:$A$464,CO$2,$C$1:$C$464,BW87),0) -> 0 | CP87: =IF(CP$2<>$A87,SUMIFS($CY$1:$CY$464,$A$1:$A$464,CP$2,$C$1:$C$464,BX87),0) -> 0 | CQ87: =IF(CQ$2<>$A87,SUMIFS($CY$1:$CY$464,$A$1:$A$464,CQ$2,$C$1:$C$464,BY87),0) -> 0 | ... CX87: =IF(CX$2<>$A87,SUMIFS($CY$1:$CY$464,$A$1:$A$464,CX$2,$C$1:$C$464,CF87),0) -> 0 | CY87: =SUM(CI87:CX87) -> 3069000
A88: Fertilizer | B88: Research | C88: 1 | D88: 1 | E88: 1 | F88: 0 | H88: 30 | I88: 0.5 | J88: =ROUNDUP(H88/30,0) -> 1 | K88: 1000 | L88: 500 | M88: 0 | N88: 0 | O88: 100 | R88: 1 | AF88: 1 | AY88: =SUMIFS($CH$3:$CH$341,$A$3:$A$341,Q$2,$C$3:$C$341,Q88) -> 0 | AZ88: =SUMIFS($CH$3:$CH$341,$A$3:$A$341,R$2,$C$3:$C$341,R88) -> 2 | BA88: =SUMIFS($CH$3:$CH$341,$A$3:$A$341,S$2,$C$3:$C$341,S88) -> 0 | BB88: =SUMIFS($CH$3:$CH$341,$A$3:$A$341,T$2,$C$3:$C$341,T88) -> 0 | BC88: =SUMIFS($CH$3:$CH$341,$A$3:$A$341,U$2,$C$3:$C$341,U88) -> 0 | BD88: =SUMIFS($CH$3:$CH$341,$A$3:$A$341,V$2,$C$3:$C$341,V88) -> 0 | BE88: =SUMIFS($CH$3:$CH$341,$A$3:$A$341,W$2,$C$3:$C$341,W88) -> 0 | BF88: =SUMIFS($CH$3:$CH$341,$A$3:$A$341,X$2,$C$3:$C$341,X88) -> 0 | ... CF88: =SUMIFS($CH$3:$CH$341,$A$3:$A$341,AX$2,$C$3:$C$341,AX88) -> 0 | CG88: =MAX(AY88:CF88) -> 2 | CH88: =MAX(F88,CG88) -> 2 | CI88: =K88 -> 1000 | CJ88: =IF(CJ$2<>$A88,SUMIFS($CY$1:$CY$464,$A$1:$A$464,CJ$2,$C$1:$C$464,BR88),0) -> 0 | CK88: =IF(CK$2<>$A88,SUMIFS($CY$1:$CY$464,$A$1:$A$464,CK$2,$C$1:$C$464,BS88),0) -> 0 | CL88: =IF(CL$2<>$A88,SUMIFS($CY$1:$CY$464,$A$1:$A$464,CL$2,$C$1:$C$464,BT88),0) -> 0 | CM88: =IF(CM$2<>$A88,SUMIFS($CY$1:$CY$464,$A$1:$A$464,CM$2,$C$1:$C$464,BU88),0) -> 0 | CN88: =IF(CN$2<>$A88,SUMIFS($CY$1:$CY$464,$A$1:$A$464,CN$2,$C$1:$C$464,BV88),0) -> 0 | CO88: =IF(CO$2<>$A88,SUMIFS($CY$1:$CY$464,$A$1:$A$464,CO$2,$C$1:$C$464,BW88),0) -> 0 | CP88: =IF(CP$2<>$A88,SUMIFS($CY$1:$CY$464,$A$1:$A$464,CP$2,$C$1:$C$464,BX88),0) -> 0 | CQ88: =IF(CQ$2<>$A88,SUMIFS($CY$1:$CY$464,$A$1:$A$464,CQ$2,$C$1:$C$464,BY88),0) -> 0 | ... CX88: =IF(CX$2<>$A88,SUMIFS($CY$1:$CY$464,$A$1:$A$464,CX$2,$C$1:$C$464,CF88),0) -> 0 | CY88: =SUM(CI88:CX88) -> 1000
A89: Fertilizer | B89: Research | C89: 2 | D89: 1 | E89: 2 | F89: 0 | H89: 800 | I89: 13.333333 | J89: =ROUNDUP(H89/30,0) -> 27 | K89: 2000 | L89: 1000 | M89: 0 | N89: 0 | O89: 200 | R89: 2 | AF89: 2 | AJ89: 1 | AY89: =SUMIFS($CH$3:$CH$341,$A$3:$A$341,Q$2,$C$3:$C$341,Q89) -> 0 | AZ89: =SUMIFS($CH$3:$CH$341,$A$3:$A$341,R$2,$C$3:$C$341,R89) -> 2 | BA89: =SUMIFS($CH$3:$CH$341,$A$3:$A$341,S$2,$C$3:$C$341,S89) -> 0 | BB89: =SUMIFS($CH$3:$CH$341,$A$3:$A$341,T$2,$C$3:$C$341,T89) -> 0 | BC89: =SUMIFS($CH$3:$CH$341,$A$3:$A$341,U$2,$C$3:$C$341,U89) -> 0 | BD89: =SUMIFS($CH$3:$CH$341,$A$3:$A$341,V$2,$C$3:$C$341,V89) -> 0 | BE89: =SUMIFS($CH$3:$CH$341,$A$3:$A$341,W$2,$C$3:$C$341,W89) -> 0 | BF89: =SUMIFS($CH$3:$CH$341,$A$3:$A$341,X$2,$C$3:$C$341,X89) -> 0 | ... CF89: =SUMIFS($CH$3:$CH$341,$A$3:$A$341,AX$2,$C$3:$C$341,AX89) -> 0 | CG89: =MAX(AY89:CF89) -> 2 | CH89: =MAX(F89,CG89) -> 2 | CI89: =CI88+K89 -> 3000 | CJ89: =IF(CJ$2<>$A89,SUMIFS($CY$1:$CY$464,$A$1:$A$464,CJ$2,$C$1:$C$464,BR89),0) -> 0 | CK89: =IF(CK$2<>$A89,SUMIFS($CY$1:$CY$464,$A$1:$A$464,CK$2,$C$1:$C$464,BS89),0) -> 0 | CL89: =IF(CL$2<>$A89,SUMIFS($CY$1:$CY$464,$A$1:$A$464,CL$2,$C$1:$C$464,BT89),0) -> 0 | CM89: =IF(CM$2<>$A89,SUMIFS($CY$1:$CY$464,$A$1:$A$464,CM$2,$C$1:$C$464,BU89),0) -> 0 | CN89: =IF(CN$2<>$A89,SUMIFS($CY$1:$CY$464,$A$1:$A$464,CN$2,$C$1:$C$464,BV89),0) -> 0 | CO89: =IF(CO$2<>$A89,SUMIFS($CY$1:$CY$464,$A$1:$A$464,CO$2,$C$1:$C$464,BW89),0) -> 0 | CP89: =IF(CP$2<>$A89,SUMIFS($CY$1:$CY$464,$A$1:$A$464,CP$2,$C$1:$C$464,BX89),0) -> 0 | CQ89: =IF(CQ$2<>$A89,SUMIFS($CY$1:$CY$464,$A$1:$A$464,CQ$2,$C$1:$C$464,BY89),0) -> 0 | ... CX89: =IF(CX$2<>$A89,SUMIFS($CY$1:$CY$464,$A$1:$A$464,CX$2,$C$1:$C$464,CF89),0) -> 0 | CY89: =SUM(CI89:CX89) -> 3000
A90: Fertilizer | B90: Research | C90: 3 | D90: 1 | E90: 3 | F90: 0 | H90: 1600 | I90: 26.666667 | J90: =ROUNDUP(H90/30,0) -> 54 | K90: 4000 | L90: 2000 | M90: 0 | N90: 0 | O90: 400 | R90: 3 | AF90: 3 | AJ90: 2 | AY90: =SUMIFS($CH$3:$CH$341,$A$3:$A$341,Q$2,$C$3:$C$341,Q90) -> 0 | AZ90: =SUMIFS($CH$3:$CH$341,$A$3:$A$341,R$2,$C$3:$C$341,R90) -> 2 | BA90: =SUMIFS($CH$3:$CH$341,$A$3:$A$341,S$2,$C$3:$C$341,S90) -> 0 | BB90: =SUMIFS($CH$3:$CH$341,$A$3:$A$341,T$2,$C$3:$C$341,T90) -> 0 | BC90: =SUMIFS($CH$3:$CH$341,$A$3:$A$341,U$2,$C$3:$C$341,U90) -> 0 | BD90: =SUMIFS($CH$3:$CH$341,$A$3:$A$341,V$2,$C$3:$C$341,V90) -> 0 | BE90: =SUMIFS($CH$3:$CH$341,$A$3:$A$341,W$2,$C$3:$C$341,W90) -> 0 | BF90: =SUMIFS($CH$3:$CH$341,$A$3:$A$341,X$2,$C$3:$C$341,X90) -> 0 | ... CF90: =SUMIFS($CH$3:$CH$341,$A$3:$A$341,AX$2,$C$3:$C$341,AX90) -> 0 | CG90: =MAX(AY90:CF90) -> 2 | CH90: =MAX(F90,CG90) -> 2 | CI90: =CI89+K90 -> 7000 | CJ90: =IF(CJ$2<>$A90,SUMIFS($CY$1:$CY$464,$A$1:$A$464,CJ$2,$C$1:$C$464,BR90),0) -> 0 | CK90: =IF(CK$2<>$A90,SUMIFS($CY$1:$CY$464,$A$1:$A$464,CK$2,$C$1:$C$464,BS90),0) -> 0 | CL90: =IF(CL$2<>$A90,SUMIFS($CY$1:$CY$464,$A$1:$A$464,CL$2,$C$1:$C$464,BT90),0) -> 0 | CM90: =IF(CM$2<>$A90,SUMIFS($CY$1:$CY$464,$A$1:$A$464,CM$2,$C$1:$C$464,BU90),0) -> 0 | CN90: =IF(CN$2<>$A90,SUMIFS($CY$1:$CY$464,$A$1:$A$464,CN$2,$C$1:$C$464,BV90),0) -> 0 | CO90: =IF(CO$2<>$A90,SUMIFS($CY$1:$CY$464,$A$1:$A$464,CO$2,$C$1:$C$464,BW90),0) -> 0 | CP90: =IF(CP$2<>$A90,SUMIFS($CY$1:$CY$464,$A$1:$A$464,CP$2,$C$1:$C$464,BX90),0) -> 0 | CQ90: =IF(CQ$2<>$A90,SUMIFS($CY$1:$CY$464,$A$1:$A$464,CQ$2,$C$1:$C$464,BY90),0) -> 0 | ... CX90: =IF(CX$2<>$A90,SUMIFS($CY$1:$CY$464,$A$1:$A$464,CX$2,$C$1:$C$464,CF90),0) -> 0 | CY90: =SUM(CI90:CX90) -> 7000
A91: Fertilizer | B91: Research | C91: 4 | D91: 1 | E91: 4 | F91: 0 | H91: 3200 | I91: 53.333333 | J91: =ROUNDUP(H91/30,0) -> 107 | K91: 8000 | L91: 4000 | M91: 0 | N91: 0 | O91: 800 | R91: 4 | AF91: 4 | AJ91: 3 | AY91: =SUMIFS($CH$3:$CH$341,$A$3:$A$341,Q$2,$C$3:$C$341,Q91) -> 0 | AZ91: =SUMIFS($CH$3:$CH$341,$A$3:$A$341,R$2,$C$3:$C$341,R91) -> 2 | BA91: =SUMIFS($CH$3:$CH$341,$A$3:$A$341,S$2,$C$3:$C$341,S91) -> 0 | BB91: =SUMIFS($CH$3:$CH$341,$A$3:$A$341,T$2,$C$3:$C$341,T91) -> 0 | BC91: =SUMIFS($CH$3:$CH$341,$A$3:$A$341,U$2,$C$3:$C$341,U91) -> 0 | BD91: =SUMIFS($CH$3:$CH$341,$A$3:$A$341,V$2,$C$3:$C$341,V91) -> 0 | BE91: =SUMIFS($CH$3:$CH$341,$A$3:$A$341,W$2,$C$3:$C$341,W91) -> 0 | BF91: =SUMIFS($CH$3:$CH$341,$A$3:$A$341,X$2,$C$3:$C$341,X91) -> 0 | ... CF91: =SUMIFS($CH$3:$CH$341,$A$3:$A$341,AX$2,$C$3:$C$341,AX91) -> 0 | CG91: =MAX(AY91:CF91) -> 2 | CH91: =MAX(F91,CG91) -> 2 | CI91: =CI90+K91 -> 15000 | CJ91: =IF(CJ$2<>$A91,SUMIFS($CY$1:$CY$464,$A$1:$A$464,CJ$2,$C$1:$C$464,BR91),0) -> 0 | CK91: =IF(CK$2<>$A91,SUMIFS($CY$1:$CY$464,$A$1:$A$464,CK$2,$C$1:$C$464,BS91),0) -> 0 | CL91: =IF(CL$2<>$A91,SUMIFS($CY$1:$CY$464,$A$1:$A$464,CL$2,$C$1:$C$464,BT91),0) -> 0 | CM91: =IF(CM$2<>$A91,SUMIFS($CY$1:$CY$464,$A$1:$A$464,CM$2,$C$1:$C$464,BU91),0) -> 0 | CN91: =IF(CN$2<>$A91,SUMIFS($CY$1:$CY$464,$A$1:$A$464,CN$2,$C$1:$C$464,BV91),0) -> 0 | CO91: =IF(CO$2<>$A91,SUMIFS($CY$1:$CY$464,$A$1:$A$464,CO$2,$C$1:$C$464,BW91),0) -> 0 | CP91: =IF(CP$2<>$A91,SUMIFS($CY$1:$CY$464,$A$1:$A$464,CP$2,$C$1:$C$464,BX91),0) -> 0 | CQ91: =IF(CQ$2<>$A91,SUMIFS($CY$1:$CY$464,$A$1:$A$464,CQ$2,$C$1:$C$464,BY91),0) -> 0 | ... CX91: =IF(CX$2<>$A91,SUMIFS($CY$1:$CY$464,$A$1:$A$464,CX$2,$C$1:$C$464,CF91),0) -> 0 | CY91: =SUM(CI91:CX91) -> 15000
A92: Fertilizer | B92: Research | C92: 5 | D92: 1 | E92: 5 | F92: 0 | H92: 6400 | I92: 106.66667 | J92: =ROUNDUP(H92/30,0) -> 214 | K92: 16000 | L92: 8000 | M92: 0 | N92: 0 | O92: 1600 | R92: 5 | AF92: 5 | AJ92: 4 | AY92: =SUMIFS($CH$3:$CH$341,$A$3:$A$341,Q$2,$C$3:$C$341,Q92) -> 0 | AZ92: =SUMIFS($CH$3:$CH$341,$A$3:$A$341,R$2,$C$3:$C$341,R92) -> 2 | BA92: =SUMIFS($CH$3:$CH$341,$A$3:$A$341,S$2,$C$3:$C$341,S92) -> 0 | BB92: =SUMIFS($CH$3:$CH$341,$A$3:$A$341,T$2,$C$3:$C$341,T92) -> 0 | BC92: =SUMIFS($CH$3:$CH$341,$A$3:$A$341,U$2,$C$3:$C$341,U92) -> 0 | BD92: =SUMIFS($CH$3:$CH$341,$A$3:$A$341,V$2,$C$3:$C$341,V92) -> 0 | BE92: =SUMIFS($CH$3:$CH$341,$A$3:$A$341,W$2,$C$3:$C$341,W92) -> 0 | BF92: =SUMIFS($CH$3:$CH$341,$A$3:$A$341,X$2,$C$3:$C$341,X92) -> 0 | ... CF92: =SUMIFS($CH$3:$CH$341,$A$3:$A$341,AX$2,$C$3:$C$341,AX92) -> 0 | CG92: =MAX(AY92:CF92) -> 2 | CH92: =MAX(F92,CG92) -> 2 | CI92: =CI91+K92 -> 31000 | CJ92: =IF(CJ$2<>$A92,SUMIFS($CY$1:$CY$464,$A$1:$A$464,CJ$2,$C$1:$C$464,BR92),0) -> 0 | CK92: =IF(CK$2<>$A92,SUMIFS($CY$1:$CY$464,$A$1:$A$464,CK$2,$C$1:$C$464,BS92),0) -> 0 | CL92: =IF(CL$2<>$A92,SUMIFS($CY$1:$CY$464,$A$1:$A$464,CL$2,$C$1:$C$464,BT92),0) -> 0 | CM92: =IF(CM$2<>$A92,SUMIFS($CY$1:$CY$464,$A$1:$A$464,CM$2,$C$1:$C$464,BU92),0) -> 0 | CN92: =IF(CN$2<>$A92,SUMIFS($CY$1:$CY$464,$A$1:$A$464,CN$2,$C$1:$C$464,BV92),0) -> 0 | CO92: =IF(CO$2<>$A92,SUMIFS($CY$1:$CY$464,$A$1:$A$464,CO$2,$C$1:$C$464,BW92),0) -> 0 | CP92: =IF(CP$2<>$A92,SUMIFS($CY$1:$CY$464,$A$1:$A$464,CP$2,$C$1:$C$464,BX92),0) -> 0 | CQ92: =IF(CQ$2<>$A92,SUMIFS($CY$1:$CY$464,$A$1:$A$464,CQ$2,$C$1:$C$464,BY92),0) -> 0 | ... CX92: =IF(CX$2<>$A92,SUMIFS($CY$1:$CY$464,$A$1:$A$464,CX$2,$C$1:$C$464,CF92),0) -> 0 | CY92: =SUM(CI92:CX92) -> 31000
A93: Fertilizer | B93: Research | C93: 6 | D93: 1 | E93: 6 | F93: 0 | H93: 12800 | I93: 213.33333 | J93: =ROUNDUP(H93/30,0) -> 427 | K93: 32000 | L93: 16000 | M93: 0 | N93: 0 | O93: 3200 | R93: 6 | AF93: 6 | AJ93: 5 | AY93: =SUMIFS($CH$3:$CH$341,$A$3:$A$341,Q$2,$C$3:$C$341,Q93) -> 0 | AZ93: =SUMIFS($CH$3:$CH$341,$A$3:$A$341,R$2,$C$3:$C$341,R93) -> 2 | BA93: =SUMIFS($CH$3:$CH$341,$A$3:$A$341,S$2,$C$3:$C$341,S93) -> 0 | BB93: =SUMIFS($CH$3:$CH$341,$A$3:$A$341,T$2,$C$3:$C$341,T93) -> 0 | BC93: =SUMIFS($CH$3:$CH$341,$A$3:$A$341,U$2,$C$3:$C$341,U93) -> 0 | BD93: =SUMIFS($CH$3:$CH$341,$A$3:$A$341,V$2,$C$3:$C$341,V93) -> 0 | BE93: =SUMIFS($CH$3:$CH$341,$A$3:$A$341,W$2,$C$3:$C$341,W93) -> 0 | BF93: =SUMIFS($CH$3:$CH$341,$A$3:$A$341,X$2,$C$3:$C$341,X93) -> 0 | ... CF93: =SUMIFS($CH$3:$CH$341,$A$3:$A$341,AX$2,$C$3:$C$341,AX93) -> 0 | CG93: =MAX(AY93:CF93) -> 2 | CH93: =MAX(F93,CG93) -> 2 | CI93: =CI92+K93 -> 63000 | CJ93: =IF(CJ$2<>$A93,SUMIFS($CY$1:$CY$464,$A$1:$A$464,CJ$2,$C$1:$C$464,BR93),0) -> 0 | CK93: =IF(CK$2<>$A93,SUMIFS($CY$1:$CY$464,$A$1:$A$464,CK$2,$C$1:$C$464,BS93),0) -> 0 | CL93: =IF(CL$2<>$A93,SUMIFS($CY$1:$CY$464,$A$1:$A$464,CL$2,$C$1:$C$464,BT93),0) -> 0 | CM93: =IF(CM$2<>$A93,SUMIFS($CY$1:$CY$464,$A$1:$A$464,CM$2,$C$1:$C$464,BU93),0) -> 0 | CN93: =IF(CN$2<>$A93,SUMIFS($CY$1:$CY$464,$A$1:$A$464,CN$2,$C$1:$C$464,BV93),0) -> 0 | CO93: =IF(CO$2<>$A93,SUMIFS($CY$1:$CY$464,$A$1:$A$464,CO$2,$C$1:$C$464,BW93),0) -> 0 | CP93: =IF(CP$2<>$A93,SUMIFS($CY$1:$CY$464,$A$1:$A$464,CP$2,$C$1:$C$464,BX93),0) -> 0 | CQ93: =IF(CQ$2<>$A93,SUMIFS($CY$1:$CY$464,$A$1:$A$464,CQ$2,$C$1:$C$464,BY93),0) -> 0 | ... CX93: =IF(CX$2<>$A93,SUMIFS($CY$1:$CY$464,$A$1:$A$464,CX$2,$C$1:$C$464,CF93),0) -> 0 | CY93: =SUM(CI93:CX93) -> 63000
A94: Fertilizer | B94: Research | C94: 7 | D94: 1 | E94: 7 | F94: 0 | H94: 25600 | I94: 426.66667 | J94: =ROUNDUP(H94/30,0) -> 854 | K94: 64000 | L94: 32000 | M94: 0 | N94: 0 | O94: 6400 | R94: 7 | AF94: 7 | AJ94: 6 | AY94: =SUMIFS($CH$3:$CH$341,$A$3:$A$341,Q$2,$C$3:$C$341,Q94) -> 0 | AZ94: =SUMIFS($CH$3:$CH$341,$A$3:$A$341,R$2,$C$3:$C$341,R94) -> 2 | BA94: =SUMIFS($CH$3:$CH$341,$A$3:$A$341,S$2,$C$3:$C$341,S94) -> 0 | BB94: =SUMIFS($CH$3:$CH$341,$A$3:$A$341,T$2,$C$3:$C$341,T94) -> 0 | BC94: =SUMIFS($CH$3:$CH$341,$A$3:$A$341,U$2,$C$3:$C$341,U94) -> 0 | BD94: =SUMIFS($CH$3:$CH$341,$A$3:$A$341,V$2,$C$3:$C$341,V94) -> 0 | BE94: =SUMIFS($CH$3:$CH$341,$A$3:$A$341,W$2,$C$3:$C$341,W94) -> 0 | BF94: =SUMIFS($CH$3:$CH$341,$A$3:$A$341,X$2,$C$3:$C$341,X94) -> 0 | ... CF94: =SUMIFS($CH$3:$CH$341,$A$3:$A$341,AX$2,$C$3:$C$341,AX94) -> 0 | CG94: =MAX(AY94:CF94) -> 2 | CH94: =MAX(F94,CG94) -> 2 | CI94: =CI93+K94 -> 127000 | CJ94: =IF(CJ$2<>$A94,SUMIFS($CY$1:$CY$464,$A$1:$A$464,CJ$2,$C$1:$C$464,BR94),0) -> 0 | CK94: =IF(CK$2<>$A94,SUMIFS($CY$1:$CY$464,$A$1:$A$464,CK$2,$C$1:$C$464,BS94),0) -> 0 | CL94: =IF(CL$2<>$A94,SUMIFS($CY$1:$CY$464,$A$1:$A$464,CL$2,$C$1:$C$464,BT94),0) -> 0 | CM94: =IF(CM$2<>$A94,SUMIFS($CY$1:$CY$464,$A$1:$A$464,CM$2,$C$1:$C$464,BU94),0) -> 0 | CN94: =IF(CN$2<>$A94,SUMIFS($CY$1:$CY$464,$A$1:$A$464,CN$2,$C$1:$C$464,BV94),0) -> 0 | CO94: =IF(CO$2<>$A94,SUMIFS($CY$1:$CY$464,$A$1:$A$464,CO$2,$C$1:$C$464,BW94),0) -> 0 | CP94: =IF(CP$2<>$A94,SUMIFS($CY$1:$CY$464,$A$1:$A$464,CP$2,$C$1:$C$464,BX94),0) -> 0 | CQ94: =IF(CQ$2<>$A94,SUMIFS($CY$1:$CY$464,$A$1:$A$464,CQ$2,$C$1:$C$464,BY94),0) -> 0 | ... CX94: =IF(CX$2<>$A94,SUMIFS($CY$1:$CY$464,$A$1:$A$464,CX$2,$C$1:$C$464,CF94),0) -> 0 | CY94: =SUM(CI94:CX94) -> 127000
A95: Fertilizer | B95: Research | C95: 8 | D95: 1 | E95: 8 | F95: 0 | H95: 51200 | I95: 853.33333 | J95: =ROUNDUP(H95/30,0) -> 1707 | K95: 128000 | L95: 64000 | M95: 0 | N95: 0 | O95: 12800 | R95: 8 | AF95: 8 | AJ95: 7 | AY95: =SUMIFS($CH$3:$CH$341,$A$3:$A$341,Q$2,$C$3:$C$341,Q95) -> 0 | AZ95: =SUMIFS($CH$3:$CH$341,$A$3:$A$341,R$2,$C$3:$C$341,R95) -> 2 | BA95: =SUMIFS($CH$3:$CH$341,$A$3:$A$341,S$2,$C$3:$C$341,S95) -> 0 | BB95: =SUMIFS($CH$3:$CH$341,$A$3:$A$341,T$2,$C$3:$C$341,T95) -> 0 | BC95: =SUMIFS($CH$3:$CH$341,$A$3:$A$341,U$2,$C$3:$C$341,U95) -> 0 | BD95: =SUMIFS($CH$3:$CH$341,$A$3:$A$341,V$2,$C$3:$C$341,V95) -> 0 | BE95: =SUMIFS($CH$3:$CH$341,$A$3:$A$341,W$2,$C$3:$C$341,W95) -> 0 | BF95: =SUMIFS($CH$3:$CH$341,$A$3:$A$341,X$2,$C$3:$C$341,X95) -> 0 | ... CF95: =SUMIFS($CH$3:$CH$341,$A$3:$A$341,AX$2,$C$3:$C$341,AX95) -> 0 | CG95: =MAX(AY95:CF95) -> 2 | CH95: =MAX(F95,CG95) -> 2 | CI95: =CI94+K95 -> 255000 | CJ95: =IF(CJ$2<>$A95,SUMIFS($CY$1:$CY$464,$A$1:$A$464,CJ$2,$C$1:$C$464,BR95),0) -> 0 | CK95: =IF(CK$2<>$A95,SUMIFS($CY$1:$CY$464,$A$1:$A$464,CK$2,$C$1:$C$464,BS95),0) -> 0 | CL95: =IF(CL$2<>$A95,SUMIFS($CY$1:$CY$464,$A$1:$A$464,CL$2,$C$1:$C$464,BT95),0) -> 0 | CM95: =IF(CM$2<>$A95,SUMIFS($CY$1:$CY$464,$A$1:$A$464,CM$2,$C$1:$C$464,BU95),0) -> 0 | CN95: =IF(CN$2<>$A95,SUMIFS($CY$1:$CY$464,$A$1:$A$464,CN$2,$C$1:$C$464,BV95),0) -> 0 | CO95: =IF(CO$2<>$A95,SUMIFS($CY$1:$CY$464,$A$1:$A$464,CO$2,$C$1:$C$464,BW95),0) -> 0 | CP95: =IF(CP$2<>$A95,SUMIFS($CY$1:$CY$464,$A$1:$A$464,CP$2,$C$1:$C$464,BX95),0) -> 0 | CQ95: =IF(CQ$2<>$A95,SUMIFS($CY$1:$CY$464,$A$1:$A$464,CQ$2,$C$1:$C$464,BY95),0) -> 0 | ... CX95: =IF(CX$2<>$A95,SUMIFS($CY$1:$CY$464,$A$1:$A$464,CX$2,$C$1:$C$464,CF95),0) -> 0 | CY95: =SUM(CI95:CX95) -> 255000
A96: Fertilizer | B96: Research | C96: 9 | D96: 1 | E96: 9 | F96: 0 | H96: 102400 | I96: 1706.6667 | J96: =ROUNDUP(H96/30,0) -> 3414 | K96: 256000 | L96: 128000 | M96: 0 | N96: 0 | O96: 25600 | R96: 9 | AF96: 9 | AJ96: 8 | AY96: =SUMIFS($CH$3:$CH$341,$A$3:$A$341,Q$2,$C$3:$C$341,Q96) -> 0 | AZ96: =SUMIFS($CH$3:$CH$341,$A$3:$A$341,R$2,$C$3:$C$341,R96) -> 2 | BA96: =SUMIFS($CH$3:$CH$341,$A$3:$A$341,S$2,$C$3:$C$341,S96) -> 0 | BB96: =SUMIFS($CH$3:$CH$341,$A$3:$A$341,T$2,$C$3:$C$341,T96) -> 0 | BC96: =SUMIFS($CH$3:$CH$341,$A$3:$A$341,U$2,$C$3:$C$341,U96) -> 0 | BD96: =SUMIFS($CH$3:$CH$341,$A$3:$A$341,V$2,$C$3:$C$341,V96) -> 0 | BE96: =SUMIFS($CH$3:$CH$341,$A$3:$A$341,W$2,$C$3:$C$341,W96) -> 0 | BF96: =SUMIFS($CH$3:$CH$341,$A$3:$A$341,X$2,$C$3:$C$341,X96) -> 0 | ... CF96: =SUMIFS($CH$3:$CH$341,$A$3:$A$341,AX$2,$C$3:$C$341,AX96) -> 0 | CG96: =MAX(AY96:CF96) -> 2 | CH96: =MAX(F96,CG96) -> 2 | CI96: =CI95+K96 -> 511000 | CJ96: =IF(CJ$2<>$A96,SUMIFS($CY$1:$CY$464,$A$1:$A$464,CJ$2,$C$1:$C$464,BR96),0) -> 0 | CK96: =IF(CK$2<>$A96,SUMIFS($CY$1:$CY$464,$A$1:$A$464,CK$2,$C$1:$C$464,BS96),0) -> 0 | CL96: =IF(CL$2<>$A96,SUMIFS($CY$1:$CY$464,$A$1:$A$464,CL$2,$C$1:$C$464,BT96),0) -> 0 | CM96: =IF(CM$2<>$A96,SUMIFS($CY$1:$CY$464,$A$1:$A$464,CM$2,$C$1:$C$464,BU96),0) -> 0 | CN96: =IF(CN$2<>$A96,SUMIFS($CY$1:$CY$464,$A$1:$A$464,CN$2,$C$1:$C$464,BV96),0) -> 0 | CO96: =IF(CO$2<>$A96,SUMIFS($CY$1:$CY$464,$A$1:$A$464,CO$2,$C$1:$C$464,BW96),0) -> 0 | CP96: =IF(CP$2<>$A96,SUMIFS($CY$1:$CY$464,$A$1:$A$464,CP$2,$C$1:$C$464,BX96),0) -> 0 | CQ96: =IF(CQ$2<>$A96,SUMIFS($CY$1:$CY$464,$A$1:$A$464,CQ$2,$C$1:$C$464,BY96),0) -> 0 | ... CX96: =IF(CX$2<>$A96,SUMIFS($CY$1:$CY$464,$A$1:$A$464,CX$2,$C$1:$C$464,CF96),0) -> 0 | CY96: =SUM(CI96:CX96) -> 511000
A97: Fertilizer | B97: Research | C97: 10 | D97: 1 | E97: 10 | F97: 0 | H97: 204800 | I97: 3413.3333 | J97: =ROUNDUP(H97/30,0) -> 6827 | K97: 512000 | L97: 256000 | M97: 0 | N97: 0 | O97: 51200 | R97: 10 | AF97: 10 | AJ97: 9 | AY97: =SUMIFS($CH$3:$CH$341,$A$3:$A$341,Q$2,$C$3:$C$341,Q97) -> 0 | AZ97: =SUMIFS($CH$3:$CH$341,$A$3:$A$341,R$2,$C$3:$C$341,R97) -> 2 | BA97: =SUMIFS($CH$3:$CH$341,$A$3:$A$341,S$2,$C$3:$C$341,S97) -> 0 | BB97: =SUMIFS($CH$3:$CH$341,$A$3:$A$341,T$2,$C$3:$C$341,T97) -> 0 | BC97: =SUMIFS($CH$3:$CH$341,$A$3:$A$341,U$2,$C$3:$C$341,U97) -> 0 | BD97: =SUMIFS($CH$3:$CH$341,$A$3:$A$341,V$2,$C$3:$C$341,V97) -> 0 | BE97: =SUMIFS($CH$3:$CH$341,$A$3:$A$341,W$2,$C$3:$C$341,W97) -> 0 | BF97: =SUMIFS($CH$3:$CH$341,$A$3:$A$341,X$2,$C$3:$C$341,X97) -> 0 | ... CF97: =SUMIFS($CH$3:$CH$341,$A$3:$A$341,AX$2,$C$3:$C$341,AX97) -> 0 | CG97: =MAX(AY97:CF97) -> 2 | CH97: =MAX(F97,CG97) -> 2 | CI97: =CI96+K97 -> 1023000 | CJ97: =IF(CJ$2<>$A97,SUMIFS($CY$1:$CY$464,$A$1:$A$464,CJ$2,$C$1:$C$464,BR97),0) -> 0 | CK97: =IF(CK$2<>$A97,SUMIFS($CY$1:$CY$464,$A$1:$A$464,CK$2,$C$1:$C$464,BS97),0) -> 0 | CL97: =IF(CL$2<>$A97,SUMIFS($CY$1:$CY$464,$A$1:$A$464,CL$2,$C$1:$C$464,BT97),0) -> 0 | CM97: =IF(CM$2<>$A97,SUMIFS($CY$1:$CY$464,$A$1:$A$464,CM$2,$C$1:$C$464,BU97),0) -> 0 | CN97: =IF(CN$2<>$A97,SUMIFS($CY$1:$CY$464,$A$1:$A$464,CN$2,$C$1:$C$464,BV97),0) -> 0 | CO97: =IF(CO$2<>$A97,SUMIFS($CY$1:$CY$464,$A$1:$A$464,CO$2,$C$1:$C$464,BW97),0) -> 0 | CP97: =IF(CP$2<>$A97,SUMIFS($CY$1:$CY$464,$A$1:$A$464,CP$2,$C$1:$C$464,BX97),0) -> 0 | CQ97: =IF(CQ$2<>$A97,SUMIFS($CY$1:$CY$464,$A$1:$A$464,CQ$2,$C$1:$C$464,BY97),0) -> 0 | ... CX97: =IF(CX$2<>$A97,SUMIFS($CY$1:$CY$464,$A$1:$A$464,CX$2,$C$1:$C$464,CF97),0) -> 0 | CY97: =SUM(CI97:CX97) -> 1023000
A98: Fletching | B98: Research | C98: 1 | D98: 1 | E98: 1 | F98: 0 | H98: 2400 | I98: 40 | J98: =ROUNDUP(H98/30,0) -> 80 | K98: 5000 | L98: 0 | M98: 800 | N98: 500 | O98: 600 | R98: 1 | AK98: 4 | AY98: =SUMIFS($CH$3:$CH$341,$A$3:$A$341,Q$2,$C$3:$C$341,Q98) -> 0 | AZ98: =SUMIFS($CH$3:$CH$341,$A$3:$A$341,R$2,$C$3:$C$341,R98) -> 2 | BA98: =SUMIFS($CH$3:$CH$341,$A$3:$A$341,S$2,$C$3:$C$341,S98) -> 0 | BB98: =SUMIFS($CH$3:$CH$341,$A$3:$A$341,T$2,$C$3:$C$341,T98) -> 0 | BC98: =SUMIFS($CH$3:$CH$341,$A$3:$A$341,U$2,$C$3:$C$341,U98) -> 0 | BD98: =SUMIFS($CH$3:$CH$341,$A$3:$A$341,V$2,$C$3:$C$341,V98) -> 0 | BE98: =SUMIFS($CH$3:$CH$341,$A$3:$A$341,W$2,$C$3:$C$341,W98) -> 0 | BF98: =SUMIFS($CH$3:$CH$341,$A$3:$A$341,X$2,$C$3:$C$341,X98) -> 0 | ... CF98: =SUMIFS($CH$3:$CH$341,$A$3:$A$341,AX$2,$C$3:$C$341,AX98) -> 0 | CG98: =MAX(AY98:CF98) -> 2 | CH98: =MAX(F98,CG98) -> 2 | CI98: =K98 -> 5000 | CJ98: =IF(CJ$2<>$A98,SUMIFS($CY$1:$CY$464,$A$1:$A$464,CJ$2,$C$1:$C$464,BR98),0) -> 0 | CK98: =IF(CK$2<>$A98,SUMIFS($CY$1:$CY$464,$A$1:$A$464,CK$2,$C$1:$C$464,BS98),0) -> 3600 | CL98: =IF(CL$2<>$A98,SUMIFS($CY$1:$CY$464,$A$1:$A$464,CL$2,$C$1:$C$464,BT98),0) -> 0 | CM98: =IF(CM$2<>$A98,SUMIFS($CY$1:$CY$464,$A$1:$A$464,CM$2,$C$1:$C$464,BU98),0) -> 0 | CN98: =IF(CN$2<>$A98,SUMIFS($CY$1:$CY$464,$A$1:$A$464,CN$2,$C$1:$C$464,BV98),0) -> 0 | CO98: =IF(CO$2<>$A98,SUMIFS($CY$1:$CY$464,$A$1:$A$464,CO$2,$C$1:$C$464,BW98),0) -> 0 | CP98: =IF(CP$2<>$A98,SUMIFS($CY$1:$CY$464,$A$1:$A$464,CP$2,$C$1:$C$464,BX98),0) -> 0 | CQ98: =IF(CQ$2<>$A98,SUMIFS($CY$1:$CY$464,$A$1:$A$464,CQ$2,$C$1:$C$464,BY98),0) -> 0 | ... CX98: =IF(CX$2<>$A98,SUMIFS($CY$1:$CY$464,$A$1:$A$464,CX$2,$C$1:$C$464,CF98),0) -> 0 | CY98: =SUM(CI98:CX98) -> 8600
A99: Fletching | B99: Research | C99: 2 | D99: 1 | E99: 2 | F99: 0 | H99: 4800 | I99: 80 | J99: =ROUNDUP(H99/30,0) -> 160 | K99: 10000 | L99: 0 | M99: 1600 | N99: 1000 | O99: 1200 | R99: 2 | AK99: 4 | AU99: 1 | AY99: =SUMIFS($CH$3:$CH$341,$A$3:$A$341,Q$2,$C$3:$C$341,Q99) -> 0 | AZ99: =SUMIFS($CH$3:$CH$341,$A$3:$A$341,R$2,$C$3:$C$341,R99) -> 2 | BA99: =SUMIFS($CH$3:$CH$341,$A$3:$A$341,S$2,$C$3:$C$341,S99) -> 0 | BB99: =SUMIFS($CH$3:$CH$341,$A$3:$A$341,T$2,$C$3:$C$341,T99) -> 0 | BC99: =SUMIFS($CH$3:$CH$341,$A$3:$A$341,U$2,$C$3:$C$341,U99) -> 0 | BD99: =SUMIFS($CH$3:$CH$341,$A$3:$A$341,V$2,$C$3:$C$341,V99) -> 0 | BE99: =SUMIFS($CH$3:$CH$341,$A$3:$A$341,W$2,$C$3:$C$341,W99) -> 0 | BF99: =SUMIFS($CH$3:$CH$341,$A$3:$A$341,X$2,$C$3:$C$341,X99) -> 0 | ... CF99: =SUMIFS($CH$3:$CH$341,$A$3:$A$341,AX$2,$C$3:$C$341,AX99) -> 0 | CG99: =MAX(AY99:CF99) -> 2 | CH99: =MAX(F99,CG99) -> 2 | CI99: =CI98+K99 -> 15000 | CJ99: =IF(CJ$2<>$A99,SUMIFS($CY$1:$CY$464,$A$1:$A$464,CJ$2,$C$1:$C$464,BR99),0) -> 0 | CK99: =IF(CK$2<>$A99,SUMIFS($CY$1:$CY$464,$A$1:$A$464,CK$2,$C$1:$C$464,BS99),0) -> 3600 | CL99: =IF(CL$2<>$A99,SUMIFS($CY$1:$CY$464,$A$1:$A$464,CL$2,$C$1:$C$464,BT99),0) -> 0 | CM99: =IF(CM$2<>$A99,SUMIFS($CY$1:$CY$464,$A$1:$A$464,CM$2,$C$1:$C$464,BU99),0) -> 0 | CN99: =IF(CN$2<>$A99,SUMIFS($CY$1:$CY$464,$A$1:$A$464,CN$2,$C$1:$C$464,BV99),0) -> 0 | CO99: =IF(CO$2<>$A99,SUMIFS($CY$1:$CY$464,$A$1:$A$464,CO$2,$C$1:$C$464,BW99),0) -> 0 | CP99: =IF(CP$2<>$A99,SUMIFS($CY$1:$CY$464,$A$1:$A$464,CP$2,$C$1:$C$464,BX99),0) -> 0 | CQ99: =IF(CQ$2<>$A99,SUMIFS($CY$1:$CY$464,$A$1:$A$464,CQ$2,$C$1:$C$464,BY99),0) -> 0 | ... CX99: =IF(CX$2<>$A99,SUMIFS($CY$1:$CY$464,$A$1:$A$464,CX$2,$C$1:$C$464,CF99),0) -> 0 | CY99: =SUM(CI99:CX99) -> 18600
A100: Fletching | B100: Research | C100: 3 | D100: 1 | E100: 3 | F100: 0 | H100: 9600 | I100: 160 | J100: =ROUNDUP(H100/30,0) -> 320 | K100: 20000 | L100: 0 | M100: 3200 | N100: 2000 | O100: 2400 | R100: 3 | AK100: 4 | AU100: 2 | AY100: =SUMIFS($CH$3:$CH$341,$A$3:$A$341,Q$2,$C$3:$C$341,Q100) -> 0 | AZ100: =SUMIFS($CH$3:$CH$341,$A$3:$A$341,R$2,$C$3:$C$341,R100) -> 2 | BA100: =SUMIFS($CH$3:$CH$341,$A$3:$A$341,S$2,$C$3:$C$341,S100) -> 0 | BB100: =SUMIFS($CH$3:$CH$341,$A$3:$A$341,T$2,$C$3:$C$341,T100) -> 0 | BC100: =SUMIFS($CH$3:$CH$341,$A$3:$A$341,U$2,$C$3:$C$341,U100) -> 0 | BD100: =SUMIFS($CH$3:$CH$341,$A$3:$A$341,V$2,$C$3:$C$341,V100) -> 0 | BE100: =SUMIFS($CH$3:$CH$341,$A$3:$A$341,W$2,$C$3:$C$341,W100) -> 0 | BF100: =SUMIFS($CH$3:$CH$341,$A$3:$A$341,X$2,$C$3:$C$341,X100) -> 0 | ... CF100: =SUMIFS($CH$3:$CH$341,$A$3:$A$341,AX$2,$C$3:$C$341,AX100) -> 0 | CG100: =MAX(AY100:CF100) -> 2 | CH100: =MAX(F100,CG100) -> 2 | CI100: =CI99+K100 -> 35000 | CJ100: =IF(CJ$2<>$A100,SUMIFS($CY$1:$CY$464,$A$1:$A$464,CJ$2,$C$1:$C$464,BR100),0) -> 0 | CK100: =IF(CK$2<>$A100,SUMIFS($CY$1:$CY$464,$A$1:$A$464,CK$2,$C$1:$C$464,BS100),0) -> 3600 | CL100: =IF(CL$2<>$A100,SUMIFS($CY$1:$CY$464,$A$1:$A$464,CL$2,$C$1:$C$464,BT100),0) -> 0 | CM100: =IF(CM$2<>$A100,SUMIFS($CY$1:$CY$464,$A$1:$A$464,CM$2,$C$1:$C$464,BU100),0) -> 0 | CN100: =IF(CN$2<>$A100,SUMIFS($CY$1:$CY$464,$A$1:$A$464,CN$2,$C$1:$C$464,BV100),0) -> 0 | CO100: =IF(CO$2<>$A100,SUMIFS($CY$1:$CY$464,$A$1:$A$464,CO$2,$C$1:$C$464,BW100),0) -> 0 | CP100: =IF(CP$2<>$A100,SUMIFS($CY$1:$CY$464,$A$1:$A$464,CP$2,$C$1:$C$464,BX100),0) -> 0 | CQ100: =IF(CQ$2<>$A100,SUMIFS($CY$1:$CY$464,$A$1:$A$464,CQ$2,$C$1:$C$464,BY100),0) -> 0 | ... CX100: =IF(CX$2<>$A100,SUMIFS($CY$1:$CY$464,$A$1:$A$464,CX$2,$C$1:$C$464,CF100),0) -> 0 | CY100: =SUM(CI100:CX100) -> 38600
...

Sheet resourcedivision
A2: pleyerlevel | B2: Building / Research | C2: type | D2: Gold | E2: Food | F2: Wood | G2: Stone | H2: Ore | I2: Build Time (sec) | J2: experience earned | K2: gold(percent) | L2: food(percent) | M2: wood(percent) | N2: stone(percent) | O2: ore(percent)
A3: 0 | B3: keep | C3: =VLOOKUP(B3,'hobbits requirement'!$A$3:$B$341,2,FALSE) -> Building | D3: =SUMIFS('hobbits requirement'!K$3:K$341,'hobbits requirement'!$CH$3:$CH$341,$A3,'hobbits requirement'!$A$3:$A$341,$B3) -> 0 | E3: =SUMIFS('hobbits requirement'!L$3:L$341,'hobbits requirement'!$CH$3:$CH$341,$A3,'hobbits requirement'!$A$3:$A$341,$B3) -> 600 | F3: =SUMIFS('hobbits requirement'!M$3:M$341,'hobbits requirement'!$CH$3:$CH$341,$A3,'hobbits requirement'!$A$3:$A$341,$B3) -> 9000 | G3: =SUMIFS('hobbits requirement'!N$3:N$341,'hobbits requirement'!$CH$3:$CH$341,$A3,'hobbits requirement'!$A$3:$A$341,$B3) -> 7500 | H3: =SUMIFS('hobbits requirement'!O$3:O$341,'hobbits requirement'!$CH$3:$CH$341,$A3,'hobbits requirement'!$A$3:$A$341,$B3) -> 300 | I3: =SUMIFS('hobbits requirement'!H$3:H$341,'hobbits requirement'!$CH$3:$CH$341,$A3,'hobbits requirement'!$A$3:$A$341,$B3) -> 2700 | J3: =ROUNDUP(I3/30,0) -> 90 | K3: =IF(K$38=0,0,ROUND(D3/K$38*100,1)) -> 0 | L3: =IF(L$38=0,0,ROUND(E3/L$38*100,1)) -> 0.1 | M3: =IF(M$38=0,0,ROUND(F3/M$38*100,1)) -> 0.6 | N3: =IF(N$38=0,0,ROUND(G3/N$38*100,1)) -> 0.7 | O3: =IF(O$38=0,0,ROUND(H3/O$38*100,1)) -> 0
A4: 0 | B4: Academy | C4: =VLOOKUP(B4,'hobbits requirement'!$A$3:$B$341,2,FALSE) -> Building | D4: =SUMIFS('hobbits requirement'!K$3:K$341,'hobbits requirement'!$CH$3:$CH$341,$A4,'hobbits requirement'!$A$3:$A$341,$B4) -> 0 | E4: =SUMIFS('hobbits requirement'!L$3:L$341,'hobbits requirement'!$CH$3:$CH$341,$A4,'hobbits requirement'!$A$3:$A$341,$B4) -> 0 | F4: =SUMIFS('hobbits requirement'!M$3:M$341,'hobbits requirement'!$CH$3:$CH$341,$A4,'hobbits requirement'!$A$3:$A$341,$B4) -> 0 | G4: =SUMIFS('hobbits requirement'!N$3:N$341,'hobbits requirement'!$CH$3:$CH$341,$A4,'hobbits requirement'!$A$3:$A$341,$B4) -> 0 | H4: =SUMIFS('hobbits requirement'!O$3:O$341,'hobbits requirement'!$CH$3:$CH$341,$A4,'hobbits requirement'!$A$3:$A$341,$B4) -> 0 | I4: =SUMIFS('hobbits requirement'!H$3:H$341,'hobbits requirement'!$CH$3:$CH$341,$A4,'hobbits requirement'!$A$3:$A$341,$B4) -> 0 | J4: =ROUNDUP(I4/30,0) -> 0 | K4: =IF(K$38=0,0,ROUND(D4/K$38*100,1)) -> 0 | L4: =IF(L$38=0,0,ROUND(E4/L$38*100,1)) -> 0 | M4: =IF(M$38=0,0,ROUND(F4/M$38*100,1)) -> 0 | N4: =IF(N$38=0,0,ROUND(G4/N$38*100,1)) -> 0 | O4: =IF(O$38=0,0,ROUND(H4/O$38*100,1)) -> 0
A5: 0 | B5: home | C5: =VLOOKUP(B5,'hobbits requirement'!$A$3:$B$341,2,FALSE) -> Building | D5: =SUMIFS('hobbits requirement'!K$3:K$341,'hobbits requirement'!$CH$3:$CH$341,$A5,'hobbits requirement'!$A$3:$A$341,$B5) -> 0 | E5: =SUMIFS('hobbits requirement'!L$3:L$341,'hobbits requirement'!$CH$3:$CH$341,$A5,'hobbits requirement'!$A$3:$A$341,$B5) -> 700 | F5: =SUMIFS('hobbits requirement'!M$3:M$341,'hobbits requirement'!$CH$3:$CH$341,$A5,'hobbits requirement'!$A$3:$A$341,$B5) -> 3500 | G5: =SUMIFS('hobbits requirement'!N$3:N$341,'hobbits requirement'!$CH$3:$CH$341,$A5,'hobbits requirement'!$A$3:$A$341,$B5) -> 700 | H5: =SUMIFS('hobbits requirement'!O$3:O$341,'hobbits requirement'!$CH$3:$CH$341,$A5,'hobbits requirement'!$A$3:$A$341,$B5) -> 350 | I5: =SUMIFS('hobbits requirement'!H$3:H$341,'hobbits requirement'!$CH$3:$CH$341,$A5,'hobbits requirement'!$A$3:$A$341,$B5) -> 155 | J5: =ROUNDUP(I5/30,0) -> 6 | K5: =IF(K$38=0,0,ROUND(D5/K$38*100,1)) -> 0 | L5: =IF(L$38=0,0,ROUND(E5/L$38*100,1)) -> 0.1 | M5: =IF(M$38=0,0,ROUND(F5/M$38*100,1)) -> 0.2 | N5: =IF(N$38=0,0,ROUND(G5/N$38*100,1)) -> 0.1 | O5: =IF(O$38=0,0,ROUND(H5/O$38*100,1)) -> 0
A6: 0 | B6: Barracks | C6: =VLOOKUP(B6,'hobbits requirement'!$A$3:$B$341,2,FALSE) -> Building | D6: =SUMIFS('hobbits requirement'!K$3:K$341,'hobbits requirement'!$CH$3:$CH$341,$A6,'hobbits requirement'!$A$3:$A$341,$B6) -> 0 | E6: =SUMIFS('hobbits requirement'!L$3:L$341,'hobbits requirement'!$CH$3:$CH$341,$A6,'hobbits requirement'!$A$3:$A$341,$B6) -> 0 | F6: =SUMIFS('hobbits requirement'!M$3:M$341,'hobbits requirement'!$CH$3:$CH$341,$A6,'hobbits requirement'!$A$3:$A$341,$B6) -> 0 | G6: =SUMIFS('hobbits requirement'!N$3:N$341,'hobbits requirement'!$CH$3:$CH$341,$A6,'hobbits requirement'!$A$3:$A$341,$B6) -> 0 | H6: =SUMIFS('hobbits requirement'!O$3:O$341,'hobbits requirement'!$CH$3:$CH$341,$A6,'hobbits requirement'!$A$3:$A$341,$B6) -> 0 | I6: =SUMIFS('hobbits requirement'!H$3:H$341,'hobbits requirement'!$CH$3:$CH$341,$A6,'hobbits requirement'!$A$3:$A$341,$B6) -> 0 | J6: =ROUNDUP(I6/30,0) -> 0 | K6: =IF(K$38=0,0,ROUND(D6/K$38*100,1)) -> 0 | L6: =IF(L$38=0,0,ROUND(E6/L$38*100,1)) -> 0 | M6: =IF(M$38=0,0,ROUND(F6/M$38*100,1)) -> 0 | N6: =IF(N$38=0,0,ROUND(G6/N$38*100,1)) -> 0 | O6: =IF(O$38=0,0,ROUND(H6/O$38*100,1)) -> 0
A7: 0 | B7: Great hall | C7: =VLOOKUP(B7,'hobbits requirement'!$A$3:$B$341,2,FALSE) -> Building | D7: =SUMIFS('hobbits requirement'!K$3:K$341,'hobbits requirement'!$CH$3:$CH$341,$A7,'hobbits requirement'!$A$3:$A$341,$B7) -> 0 | E7: =SUMIFS('hobbits requirement'!L$3:L$341,'hobbits requirement'!$CH$3:$CH$341,$A7,'hobbits requirement'!$A$3:$A$341,$B7) -> 0 | F7: =SUMIFS('hobbits requirement'!M$3:M$341,'hobbits requirement'!$CH$3:$CH$341,$A7,'hobbits requirement'!$A$3:$A$341,$B7) -> 0 | G7: =SUMIFS('hobbits requirement'!N$3:N$341,'hobbits requirement'!$CH$3:$CH$341,$A7,'hobbits requirement'!$A$3:$A$341,$B7) -> 0 | H7: =SUMIFS('hobbits requirement'!O$3:O$341,'hobbits requirement'!$CH$3:$CH$341,$A7,'hobbits requirement'!$A$3:$A$341,$B7) -> 0 | I7: =SUMIFS('hobbits requirement'!H$3:H$341,'hobbits requirement'!$CH$3:$CH$341,$A7,'hobbits requirement'!$A$3:$A$341,$B7) -> 0 | J7: =ROUNDUP(I7/30,0) -> 0 | K7: =IF(K$38=0,0,ROUND(D7/K$38*100,1)) -> 0 | L7: =IF(L$38=0,0,ROUND(E7/L$38*100,1)) -> 0 | M7: =IF(M$38=0,0,ROUND(F7/M$38*100,1)) -> 0 | N7: =IF(N$38=0,0,ROUND(G7/N$38*100,1)) -> 0 | O7: =IF(O$38=0,0,ROUND(H7/O$38*100,1)) -> 0
A8: 0 | B8: vault | C8: =VLOOKUP(B8,'hobbits requirement'!$A$3:$B$341,2,FALSE) -> Building | D8: =SUMIFS('hobbits requirement'!K$3:K$341,'hobbits requirement'!$CH$3:$CH$341,$A8,'hobbits requirement'!$A$3:$A$341,$B8) -> 0 | E8: =SUMIFS('hobbits requirement'!L$3:L$341,'hobbits requirement'!$CH$3:$CH$341,$A8,'hobbits requirement'!$A$3:$A$341,$B8) -> 0 | F8: =SUMIFS('hobbits requirement'!M$3:M$341,'hobbits requirement'!$CH$3:$CH$341,$A8,'hobbits requirement'!$A$3:$A$341,$B8) -> 0 | G8: =SUMIFS('hobbits requirement'!N$3:N$341,'hobbits requirement'!$CH$3:$CH$341,$A8,'hobbits requirement'!$A$3:$A$341,$B8) -> 0 | H8: =SUMIFS('hobbits requirement'!O$3:O$341,'hobbits requirement'!$CH$3:$CH$341,$A8,'hobbits requirement'!$A$3:$A$341,$B8) -> 0 | I8: =SUMIFS('hobbits requirement'!H$3:H$341,'hobbits requirement'!$CH$3:$CH$341,$A8,'hobbits requirement'!$A$3:$A$341,$B8) -> 0 | J8: =ROUNDUP(I8/30,0) -> 0 | K8: =IF(K$38=0,0,ROUND(D8/K$38*100,1)) -> 0 | L8: =IF(L$38=0,0,ROUND(E8/L$38*100,1)) -> 0 | M8: =IF(M$38=0,0,ROUND(F8/M$38*100,1)) -> 0 | N8: =IF(N$38=0,0,ROUND(G8/N$38*100,1)) -> 0 | O8: =IF(O$38=0,0,ROUND(H8/O$38*100,1)) -> 0
A9: 0 | B9: Muster Field | C9: =VLOOKUP(B9,'hobbits requirement'!$A$3:$B$341,2,FALSE) -> Building | D9: =SUMIFS('hobbits requirement'!K$3:K$341,'hobbits requirement'!$CH$3:$CH$341,$A9,'hobbits requirement'!$A$3:$A$341,$B9) -> 0 | E9: =SUMIFS('hobbits requirement'!L$3:L$341,'hobbits requirement'!$CH$3:$CH$341,$A9,'hobbits requirement'!$A$3:$A$341,$B9) -> 0 | F9: =SUMIFS('hobbits requirement'!M$3:M$341,'hobbits requirement'!$CH$3:$CH$341,$A9,'hobbits requirement'!$A$3:$A$341,$B9) -> 0 | G9: =SUMIFS('hobbits requirement'!N$3:N$341,'hobbits requirement'!$CH$3:$CH$341,$A9,'hobbits requirement'!$A$3:$A$341,$B9) -> 0 | H9: =SUMIFS('hobbits requirement'!O$3:O$341,'hobbits requirement'!$CH$3:$CH$341,$A9,'hobbits requirement'!$A$3:$A$341,$B9) -> 0 | I9: =SUMIFS('hobbits requirement'!H$3:H$341,'hobbits requirement'!$CH$3:$CH$341,$A9,'hobbits requirement'!$A$3:$A$341,$B9) -> 0 | J9: =ROUNDUP(I9/30,0) -> 0 | K9: =IF(K$38=0,0,ROUND(D9/K$38*100,1)) -> 0 | L9: =IF(L$38=0,0,ROUND(E9/L$38*100,1)) -> 0 | M9: =IF(M$38=0,0,ROUND(F9/M$38*100,1)) -> 0 | N9: =IF(N$38=0,0,ROUND(G9/N$38*100,1)) -> 0 | O9: =IF(O$38=0,0,ROUND(H9/O$38*100,1)) -> 0
